Workbook

Sheet survey
A1: type | B1: name | C1: label::English (en) | D1: label:: | E1: hint::English (en) | F1: hint:: | G1: required | H1: appearance | I1: constraint | J1: constraint_message | K1: relevant | L1: choice_filter | M1: parameters | N1: calculation | S1: Mandatory | U1: New question duration (sec) | V1: Estimated percentage of repondents | W1: Weighted time | X1: Weighted time for core vars
A2: start | B2: start | W2: =IF(U2<>"",U2*V2,"") | X2: =IF(AND(U2<>"",S2="yes"),U2*V2,"")
A3: end | B3: end | W3: =IF(U3<>"",U3*V3,"") | X3: =IF(AND(U3<>"",S3="yes"),U3*V3,"")
A4: today | B4: today | W4: =IF(U4<>"",U4*V4,"") | X4: =IF(AND(U4<>"",S4="yes"),U4*V4,"")
A5: deviceid | B5: deviceid | W5: =IF(U5<>"",U5*V5,"") | X5: =IF(AND(U5<>"",S5="yes"),U5*V5,"")
A6: audit | B6: audit
A7: calculate | B7: audio_random | N7: once(random())
A8: background-audio | B8: background-audio | K8: ${audio_random}<=0.02 | M8: quality=low
A9: select_one enumteam | B9: enum_team | C9: Enumerator team number or code
A10: select_one enumerator | B10: enumerator | C10: Name of enumerator | G10: true | L10: my_filter_admin=${enum_team} | S10: yes | W10: =IF(U10<>"",U10*V10,"") | X10: =IF(AND(U10<>"",S10="yes"),U10*V10,"")
A11: calculate | B11: enumerator_ | N11: jr:choice-name(${enumerator},'${enumerator}') | S11: yes | W11: =IF(U11<>"",U11*V11,"") | X11: =IF(AND(U11<>"",S11="yes"),U11*V11,"")
A13: note | B13: introduction | C13: Hello sir/ma'am, my name is ${enumerator_}. On behalf of the Food and Agriculture Organization of the United Nations (FAO), we are conducting a survey on household livelihoods and the ability to access food in your area. I would like to ask you some questions about your household. The survey usually takes 20 / 30 minutes to complete. Any information that you provide will be kept strictly confidential, only used for the purpose of the survey and will not be shown to other people. Your voluntary participation in the outcome of this interview is NOT IN ANY WAY linked to your personal chance of receiving any assistance. This is voluntary and you can choose not to answer any or all of the questions if you want. However, we hope that you will participate since your views are important. Do you have any questions? | E13: [INSTRUCTIONS: ADDRESS QUESTIONS FROM RESPONDENT, IF ANY.] | G13: false | S13: no | U13: 50.82254 | W13: =IF(U13<>"",U13*V13,"") -> 0 | X13: =IF(AND(U13<>"",S13="yes"),U13*V13,"")
A14: select_one yesno | B14: resp_agree | C14: Are you interested in participating in this survey? | G14: false | S14: yes | U14: 3.5 | V14: =1 -> 1 | W14: =IF(U14<>"",U14*V14,"") -> 3.5 | X14: =IF(AND(U14<>"",S14="yes"),U14*V14,"") -> 3.5
A15: geopoint | B15: gps_1 | C15: GPS INSTRUCTION: Take a GPS measurement. | E15: NOTE: It might take a few minutes for the tablet to register the GPS. Wait for it to load. If it takes longer than 3 minutes, skip to the next question. You can take the GPS reading at the end of the interview. | G15: false | K15: ${resp_agree} = '1' | U15: 0 | V15: 1 | W15: =IF(U15<>"",U15*V15,"") -> 0
A16: note | B16: Refusal | C16: Thank you for your time, you will be removed from today's survey. | G16: false | K16: ${resp_agree} = '2' | S16: no | U16: 0 | V16: 1 | W16: =IF(U16<>"",U16*V16,"") -> 0 | X16: =IF(AND(U16<>"",S16="yes"),U16*V16,"")
W17: =IF(U17<>"",U17*V17,"") | X17: =IF(AND(U17<>"",S17="yes"),U17*V17,"")
A18: begin_group | B18: eligibility | C18: ELIGIBILITY CRITERIA | G18: false | K18: ${resp_agree} = '1' | S18: yes | W18: =IF(U18<>"",U18*V18,"") | X18: =IF(AND(U18<>"",S18="yes"),U18*V18,"")
W19: =IF(U19<>"",U19*V19,"") | X19: =IF(AND(U19<>"",S19="yes"),U19*V19,"")
A20: text | B20: resp_firstname | C20: What is your first name? | E20: [INSTRUCTIONS: RECORD THE RESPONDENT'S FIRST NAME. ENTER 999 FOR REFUSED] | G20: true | S20: yes | U20: 10 | V20: =1 -> 1 | W20: =IF(U20<>"",U20*V20,"") -> 10 | X20: =IF(AND(U20<>"",S20="yes"),U20*V20,"") -> 10
A21: text | B21: resp_lastname | C21: What is your last name? | E21: [INSTRUCTIONS: RECORD THE RESPONDENT'S LAST NAME. ENTER 999 FOR REFUSED] | G21: true | S21: yes | U21: 10 | V21: =1 -> 1 | W21: =IF(U21<>"",U21*V21,"") -> 10 | X21: =IF(AND(U21<>"",S21="yes"),U21*V21,"") -> 10
V22: =1 -> 1 | W22: =IF(U22<>"",U22*V22,"") | X22: =IF(AND(U22<>"",S22="yes"),U22*V22,"")
A23: integer | B23: resp_age | C23: How old are you? | E23: [INSTRUCTIONS: RECORD AGE IN NUMBER OF YEARS. ROUND UP TO NEAREST WHOLE NUMBER. IF THE RESPONDENT GIVES BIRTH YEAR, REPEAT THE QUESTION. ENTER 888 FOR DON'T KNOW.] | G23: true | I23: (. >= 18 and . <= 100) or . = 888 | S23: yes | U23: 13.753073 | V23: =1 -> 1 | W23: =IF(U23<>"",U23*V23,"") -> 13.753073 | X23: =IF(AND(U23<>"",S23="yes"),U23*V23,"") -> 13.753073
V24: =1 -> 1 | W24: =IF(U24<>"",U24*V24,"") | X24: =IF(AND(U24<>"",S24="yes"),U24*V24,"")
A25: select_one gender | B25: resp_gender | C25: What is the gender of the respondent? | E25: [INSTRUCTIONS: DO NOT ASK THIS QUESTION OUT LOUD. SELECT THE GENDER OF THE RESPONDENT.] | G25: true | S25: no | U25: 2.1173561 | V25: =1 -> 1 | W25: =IF(U25<>"",U25*V25,"") -> 2.1173561 | X25: =IF(AND(U25<>"",S25="yes"),U25*V25,"")
V26: =1 -> 1 | W26: =IF(U26<>"",U26*V26,"") | X26: =IF(AND(U26<>"",S26="yes"),U26*V26,"")
A27: text | B27: phone_number_personal | C27: What is your phone number? | G27: true | H27: numbers | I27: regex(.,’^[0-9]{9}$’) | J27: Please enter the telephone number in the correct format, e.g. 076xxxxxx | S27: yes - panel | U27: 10 | V27: =1 -> 1 | W27: =IF(U27<>"",U27*V27,"") -> 10 | X27: =IF(AND(U27<>"",S27="yes"),U27*V27,"")
A28: select_one contact_info | B28: contact_2 | C28: Can you give me an additonal phone number belonging to you, a relative or a friend at which you can be reached? | G28: true | S28: yes - panel | U28: 10 | V28: =1 -> 1 | W28: =IF(U28<>"",U28*V28,"") -> 10 | X28: =IF(AND(U28<>"",S28="yes"),U28*V28,"")
A29: text | B29: phone_number_2 | C29: What is the additional phone number? | G29: true | H29: numbers | I29: regex(.,’^[0-9]{9}$’) | J29: Please enter the telephone number in the correct format, e.g. 076xxxxxx | K29: ${contact_2} = '1' or ${contact_2} = '2' | S29: yes - panel | U29: 10 | V29: =1 -> 1 | W29: =IF(U29<>"",U29*V29,"") -> 10 | X29: =IF(AND(U29<>"",S29="yes"),U29*V29,"")
A30: text | B30: contact_2_name | C30: What is the name of the contact? | G30: true | K30: ${contact_2} = '2' | S30: yes - panel | U30: 10 | V30: =1 -> 1 | W30: =IF(U30<>"",U30*V30,"") -> 10 | X30: =IF(AND(U30<>"",S30="yes"),U30*V30,"")
A31: select_one contact_info | B31: contact_3 | C31: Can you give me an additonal phone number belonging to you, a relative or a friend at which you can be reached? | G31: true | K31: ${contact_2} ='1' or ${contact_2} = '2' | S31: yes - panel | U31: 10 | V31: =1 -> 1 | W31: =IF(U31<>"",U31*V31,"") -> 10 | X31: =IF(AND(U31<>"",S31="yes"),U31*V31,"")
A32: text | B32: phone_number_3 | C32: What is the additional phone number? | G32: true | H32: numbers | I32: regex(.,’^[0-9]{9}$’) | J32: Please enter the telephone number in the correct format, e.g. 076xxxxxx | K32: ${contact_3} = '1' or ${contact_3} = '2' | S32: yes - panel | U32: 10 | V32: =1 -> 1 | W32: =IF(U32<>"",U32*V32,"") -> 10 | X32: =IF(AND(U32<>"",S32="yes"),U32*V32,"")
A33: text | B33: contact_3_name | C33: What is the name of the contact? | G33: true | K33: ${contact_3} = '2' | S33: yes - panel | U33: 10 | V33: =1 -> 1 | W33: =IF(U33<>"",U33*V33,"") -> 10 | X33: =IF(AND(U33<>"",S33="yes"),U33*V33,"")
V34: =1 -> 1 | W34: =IF(U34<>"",U34*V34,"") | X34: =IF(AND(U34<>"",S34="yes"),U34*V34,"")
A35: select_one admin1 | B35: adm1_pcode | C35: Currently, in which Regional does your household reside? | E35: [HINT: HOUSEHOLD CONSISTS OF ALL MEMBERS LIVING TOGETHER, SHARING RESOURCES & EATING FROM THE SAME POT.] | G35: true | H35: minimal | S35: yes | U35: 8.8 | V35: =1 -> 1 | W35: =IF(U35<>"",U35*V35,"") -> 8.8 | X35: =IF(AND(U35<>"",S35="yes"),U35*V35,"") -> 8.8
A36: calculate | B36: adm1_name | N36: jr:choice-name(${adm1_pcode},'${adm1_pcode}') | S36: yes | V36: =1 -> 1 | W36: =IF(U36<>"",U36*V36,"") | X36: =IF(AND(U36<>"",S36="yes"),U36*V36,"")
A37: select_one admin2 | B37: adm2_pcode | C37: Currently, in which District does your household reside? | G37: true | H37: minimal | L37: my_filter_admin=${adm1_pcode} | S37: yes | U37: 10.4 | V37: =1 -> 1 | W37: =IF(U37<>"",U37*V37,"") -> 10.4 | X37: =IF(AND(U37<>"",S37="yes"),U37*V37,"") -> 10.4
A38: calculate | B38: adm2_name | N38: jr:choice-name(${adm2_pcode},'${adm2_pcode}') | S38: yes | V38: =1 -> 1 | W38: =IF(U38<>"",U38*V38,"") | X38: =IF(AND(U38<>"",S38="yes"),U38*V38,"")
V39: =1 -> 1 | W39: =IF(U39<>"",U39*V39,"") | X39: =IF(AND(U39<>"",S39="yes"),U39*V39,"")
A40: select_one agricactivity | B40: hh_agricactivity | C40: Has anybody in your household produced crops or livestock for household consumption or for sale in the past 12 months, including household members currently away for transhumance? | E40: [INSTRUCTIONS: THIS IS THE MAIN SCREENING QUESTION.] [HINT FOR PROBING: Do you cultivate any plants to sale or consume? Do you raise any animals with the intent of selling or consuming them or their products like meat, milk, wool or leather? Is one of your household member currently away with cattle or other animals for transhumance?] | G40: true | S40: yes | U40: 31.372377 | V40: =1 -> 1 | W40: =IF(U40<>"",U40*V40,"") -> 31.372377 | X40: =IF(AND(U40<>"",S40="yes"),U40*V40,"") -> 31.372377
V41: =1 -> 1 | W41: =IF(U41<>"",U41*V41,"") | X41: =IF(AND(U41<>"",S41="yes"),U41*V41,"")
A42: end_group | W42: =IF(U42<>"",U42*V42,"") | X42: =IF(AND(U42<>"",S42="yes"),U42*V42,"")
A43: begin_group | B43: generalInfo | C43: GENERAL INFORMATION | G43: false | K43: ${resp_agree} = '1' and ${hh_agricactivity} != '5' and ${hh_agricactivity} != '6' | S43: yes | W43: =IF(U43<>"",U43*V43,"") | X43: =IF(AND(U43<>"",S43="yes"),U43*V43,"")
V44: =1 -> 1 | W44: =IF(U44<>"",U44*V44,"") | X44: =IF(AND(U44<>"",S44="yes"),U44*V44,"")
A45: select_one yes_no | B45: resp_id | C45: Are you the head of household? | G45: true | S45: yes
A46: select_one gender | B46: hh_gender | C46: Is the head of your household male or female? | G46: true | K46: ${resp_id} != '1' | S46: yes | U46: 10.085732 | V46: =1 -> 1 | W46: =IF(U46<>"",U46*V46,"") -> 10.085732 | X46: =IF(AND(U46<>"",S46="yes"),U46*V46,"") -> 10.085732
V47: =1 -> 1 | W47: =IF(U47<>"",U47*V47,"") | X47: =IF(AND(U47<>"",S47="yes"),U47*V47,"")
A48: select_one edu | B48: hh_education | C48: What is the educational level attained by the head of household? | G48: true | S48: yes | U48: 12.894034 | V48: =1 -> 1 | W48: =IF(U48<>"",U48*V48,"") -> 12.894034 | X48: =IF(AND(U48<>"",S48="yes"),U48*V48,"") -> 12.894034
V49: =1 -> 1 | W49: =IF(U49<>"",U49*V49,"") | X49: =IF(AND(U49<>"",S49="yes"),U49*V49,"")
A50: select_one water | B50: hh_wealth_water | C50: Where does the water that you drink at home come from? | G50: true | S50: yes | U50: 15.265829 | V50: =1 -> 1 | W50: =IF(U50<>"",U50*V50,"") -> 15.265829 | X50: =IF(AND(U50<>"",S50="yes"),U50*V50,"") -> 15.265829
A51: select_one toilet | B51: hh_wealth_toilet | C51: Where do household members typically go to use the toilet? | G51: true | S51: yes | U51: 15.123718 | V51: =1 -> 1 | W51: =IF(U51<>"",U51*V51,"") -> 15.123718 | X51: =IF(AND(U51<>"",S51="yes"),U51*V51,"") -> 15.123718
A52: select_one light | B52: hh_wealth_light | C52: What is the main source of light in your dwelling? | G52: true | S52: yes | U52: 13.760139 | V52: =1 -> 1 | W52: =IF(U52<>"",U52*V52,"") -> 13.760139 | X52: =IF(AND(U52<>"",S52="yes"),U52*V52,"") -> 13.760139
V53: =1 -> 1 | W53: =IF(U53<>"",U53*V53,"") | X53: =IF(AND(U53<>"",S53="yes"),U53*V53,"")
A54: select_one residence | B54: hh_residencetype | C54: Which in the following types of residence best describes your residence? | E54: [INSTRUCTIONS: READ OUT THE OPTIONS.] [HINT: IF RESPONDENT IS ONLY AWAY FROM THE HOUSEHOLD FOR SHORT SEASONAL WORK (<6 MONTHS) OR TRANSHUMANCE, MAKE SURE TO REFER TO THEIR HOUSEHOLD BACK WHERE THEY TYPICALLY ARE LOCATED.] | G54: true | S54: no | U54: 30.646189 | V54: =1 -> 1 | W54: =IF(U54<>"",U54*V54,"") -> 30.646189 | X54: =IF(AND(U54<>"",S54="yes"),U54*V54,"")
A55: integer | B55: hh_size | C55: How many people are part of the household? | E55: [INSTRUCTIONS: RECORD NUMBER OF MEMBERS IN HOUSEHOLD. ENTER 888 FOR DON'T KNOW & 999 FOR REFUSED.] [HINT: TO BE A PART OF THE SAME HOUSEHOLD, MEMBERS MUST LIVE UNDER THE SAME ROOF, SHARE THE SAME RESOURCES & EAT FROM THE SAME POT.] | G55: true | I55: (. >= 1 and . <= 50) or . = 888 or . = 999 | S55: no | U55: 15.211848 | V55: =1 -> 1 | W55: =IF(U55<>"",U55*V55,"") -> 15.211848 | X55: =IF(AND(U55<>"",S55="yes"),U55*V55,"")
A56: select_multiple asset_prod | B56: hh_asset_prod | C56: Does your household own any of the following productive assets? | E56: [INSTRUCTIONS: MULTIPLE RESPONSES POSSIBLE. READ ANSWER OPTIONS OUT LOUD.] | G56: true | I56: if(selected(.,'none') or selected(.,'dk') or selected(.,'ref'), count-selected(.) = 1, count-selected(.) >= 1) | S56: no | U56: 17 | V56: =1 -> 1 | W56: =IF(U56<>"",U56*V56,"") -> 17 | X56: =IF(AND(U56<>"",S56="yes"),U56*V56,"")
A57: select_multiple asset_transp | B57: hh_asset_transp | C57: Do you or any member of household own any of the following transportation assets? | E57: [INSTRUCTIONS: MULTIPLE RESPONSES POSSIBLE. READ ANSWER OPTIONS OUT LOUD.] | G57: true | I57: if(selected(.,'none') or selected(.,'dk') or selected(.,'ref'), count-selected(.) = 1, count-selected(.) >= 1) | S57: no | U57: 17 | V57: =1 -> 1 | W57: =IF(U57<>"",U57*V57,"") -> 17 | X57: =IF(AND(U57<>"",S57="yes"),U57*V57,"")
A58: select_one maritalstat | B58: hh_maritalstat | C58: What is the head of household’s current marital status? | G58: true | S58: no | U58: 17 | V58: =1 -> 1 | W58: =IF(U58<>"",U58*V58,"") -> 17 | X58: =IF(AND(U58<>"",S58="yes"),U58*V58,"")
A59: select_one agegroup | B59: hh_age | C59: How old is the head of household? | G59: true | S59: no | U59: 8.2288065 | V59: =1 -> 1 | W59: =IF(U59<>"",U59*V59,"") -> 8.2288065 | X59: =IF(AND(U59<>"",S59="yes"),U59*V59,"")
V60: =1 -> 1 | W60: =IF(U60<>"",U60*V60,"") | X60: =IF(AND(U60<>"",S60="yes"),U60*V60,"")
A61: end_group | V61: =1 -> 1 | W61: =IF(U61<>"",U61*V61,"") | X61: =IF(AND(U61<>"",S61="yes"),U61*V61,"")
A62: begin_group | B62: Income_Shocks_group | C62: INCOME SOURCES, LIVELIHOODS AND SHOCKS | G62: false | K62: ${resp_agree} = '1' and ${hh_agricactivity} != '5' and ${hh_agricactivity} != '6' | S62: yes | V62: =1 -> 1 | W62: =IF(U62<>"",U62*V62,"") | X62: =IF(AND(U62<>"",S62="yes"),U62*V62,"")
V63: =1 -> 1 | W63: =IF(U63<>"",U63*V63,"") | X63: =IF(AND(U63<>"",S63="yes"),U63*V63,"")
A64: select_one incomesource1 | B64: income_main | C64: What was your household's main source of income in the past 3 months? | E64: [INSTRUCTIONS: REFUSED OPTIONS SHOULD BE AVOIDED AS MUCH AS POSSIBLE.] | G64: true | H64: minimal | S64: yes | U64: 36.928734 | V64: =1 -> 1 | W64: =IF(U64<>"",U64*V64,"") -> 36.928734 | X64: =IF(AND(U64<>"",S64="yes"),U64*V64,"") -> 36.928734
A65: calculate | B65: incomemain | N65: jr:choice-name(${income_main},'${income_main}') | S65: yes | V65: =1 -> 1 | W65: =IF(U65<>"",U65*V65,"") | X65: =IF(AND(U65<>"",S65="yes"),U65*V65,"")
A66: select_one yes_no | B66: income_main_crop_check | C66: Are the crops that you sell produced by you or anyone in your household? | G66: true | K66: ${income_main} = '1' or ${income_main} = '2' or ${income_main} = '3' | S66: yes | U66: 0 | V66: =1 -> 1 | W66: =IF(U66<>"",U66*V66,"") -> 0 | X66: =IF(AND(U66<>"",S66="yes"),U66*V66,"") -> 0
A67: select_one yes_no | B67: income_main_ls_check | C67: Are the livestock and livestock products that you sell produced by you or anyone in your household? | G67: true | K67: ${income_main} = '4' | S67: yes | U67: 0 | V67: =1 -> 1 | W67: =IF(U67<>"",U67*V67,"") -> 0 | X67: =IF(AND(U67<>"",S67="yes"),U67*V67,"") -> 0
A68: select_one yes_no | B68: income_main_fish_check | C68: Are the fish and/or fish products that you sell also captured or harvested by you or anyone in your household? | G68: true | K68: ${income_main} = '6' | S68: yes | U68: 0 | V68: =1 -> 1 | W68: =IF(U68<>"",U68*V68,"") -> 0 | X68: =IF(AND(U68<>"",S68="yes"),U68*V68,"") -> 0
V69: =1 -> 1 | W69: =IF(U69<>"",U69*V69,"") | X69: =IF(AND(U69<>"",S69="yes"),U69*V69,"")
A70: decimal | B70: income_main_amount | C70: How much was earned (in SLE ) from your main income source, ${incomemain}, in the past 3 months ? | E70: [INSTRUCTIONS: MAKE SURE THE INFORMATION IS RECORDED IN THE CORRECT CURRENCY. ENTER 888 FOR DON'T KNOW AND 999 FOR REFUSED.] | G70: true | I70: . > 1 or . = 888 or . = 999 | K70: ${income_main} != '19' and ${income_main} != '20' | S70: no | U70: 40.047318 | V70: =1 -> 1 | W70: =IF(U70<>"",U70*V70,"") -> 40.047318 | X70: =IF(AND(U70<>"",S70="yes"),U70*V70,"")
A71: select_one continue | B71: income_main_amount_conf | C71: Can you confirm the amount of income you just stated is correct? | E71: [INSTRUCTIONS: IF THE RESPONDENT CONFIRMS THAT THE INCOME AMOUNT EARNED FROM THIS INCOME SOURCE OVER THE PAST 3 MONTH IS INDEED OVER 15000, CLICK ON CONTINUE. OTHERWISE, GO BACK AND CHANGE THE AMOUNT ENTERED.] | G71: false | K71: ${income_main_amount} > 15000 and (${income_main} != '19' and ${income_main} != '20') | S71: no | U71: 3.687011 | V71: =1 -> 1 | W71: =IF(U71<>"",U71*V71,"") -> 3.687011 | X71: =IF(AND(U71<>"",S71="yes"),U71*V71,"")
A73: select_one gender_inc_1 | B73: income_main_gender | C73: What is the gender of the household member(s) generating income from this source? | G73: true | K73: ${income_main} != '19' and ${income_main} != '20'
A74: select_one gender_inc_2 | B74: income_main_control | C74: Who controls the revenue that is earned from this source? | G74: true | K74: ${income_main} != '19' and ${income_main} != '20'
V75: =1 -> 1 | W75: =IF(U75<>"",U75*V75,"") | X75: =IF(AND(U75<>"",S75="yes"),U75*V75,"")
A76: select_one change | B76: income_main_comp | C76: Has your household's income from ${incomemain} changed in the last 3 months compared to the same period of last year? | G76: true | K76: ${income_main} != '19' and ${income_main} != '20' | S76: yes | U76: 27.242167 | V76: =1 -> 1 | W76: =IF(U76<>"",U76*V76,"") -> 27.242167 | X76: =IF(AND(U76<>"",S76="yes"),U76*V76,"") -> 27.242167
V77: =1 -> 1 | W77: =IF(U77<>"",U77*V77,"") | X77: =IF(AND(U77<>"",S77="yes"),U77*V77,"")
A78: select_one incomesource2 | B78: income_sec | C78: What was your household's second most important source of income in the past 3 months? | E78: [INSTRUCTIONS: DON'T KNOW AND REFUSED OPTIONS SHOULD BE AVOIDED AS MUCH AS POSSIBLE.] | G78: true | H78: minimal | K78: ${income_main} != '19' and ${income_main} != '20' | L78: not(selected(${income_main}, name)) | S78: yes | U78: 25.308004 | V78: =1 -> 1 | W78: =IF(U78<>"",U78*V78,"") -> 25.308004 | X78: =IF(AND(U78<>"",S78="yes"),U78*V78,"") -> 25.308004
A79: calculate | B79: incomesec | N79: jr:choice-name(${income_sec},'${income_sec}') | S79: yes | V79: =1 -> 1 | W79: =IF(U79<>"",U79*V79,"") | X79: =IF(AND(U79<>"",S79="yes"),U79*V79,"")
A80: select_one yes_no | B80: income_sec_crop_check | C80: Are the crops that you sell produced by you or anyone in your household? | G80: true | K80: ${income_sec} = '1' or ${income_sec} = '2' or ${income_sec} = '3' | S80: yes | U80: 0 | V80: =1 -> 1 | W80: =IF(U80<>"",U80*V80,"") -> 0 | X80: =IF(AND(U80<>"",S80="yes"),U80*V80,"") -> 0
A81: select_one yes_no | B81: income_sec_ls_check | C81: Are the livestock and livestock products that you sell produced by you or anyone in your household? | G81: true | K81: ${income_sec} = '4' | S81: yes | U81: 0 | V81: =1 -> 1 | W81: =IF(U81<>"",U81*V81,"") -> 0 | X81: =IF(AND(U81<>"",S81="yes"),U81*V81,"") -> 0
A82: select_one yes_no | B82: income_sec_fish_check | C82: Are the fish products that you sell produced by you or anyone in your household? | G82: true | K82: ${income_sec} = '6' | S82: yes | U82: 0 | V82: =1 -> 1 | W82: =IF(U82<>"",U82*V82,"") -> 0 | X82: =IF(AND(U82<>"",S82="yes"),U82*V82,"") -> 0
V83: =1 -> 1 | W83: =IF(U83<>"",U83*V83,"") | X83: =IF(AND(U83<>"",S83="yes"),U83*V83,"")
A84: decimal | B84: income_sec_amount | C84: How much was earned (in SLE ) from your second main income source, ${incomesec}, in the past 3 months ? | E84: [INSTRUCTIONS: MAKE SURE THE INFORMATION IS RECORDED IN THE CORRECT CURRENCY. ENTER 888 FOR DON'T KNOW AND 999 FOR REFUSED.] | G84: true | I84: . > 1 or . = 888 or . = 999 | K84: ${income_main} != '19' and ${income_main} != '20' and ${income_sec} != '19' and ${income_sec} != '20' and ${income_sec} != '21' | S84: no | U84: 30.82847 | V84: =1 -> 1 | W84: =IF(U84<>"",U84*V84,"") -> 30.82847 | X84: =IF(AND(U84<>"",S84="yes"),U84*V84,"")
A85: select_one continue | B85: income_sec_amount_conf | C85: Can you confirm the amount of income you just stated is correct? | E85: [INSTRUCTIONS: IF THE RESPONDENT CONFIRMS THAT THE INCOME AMOUNT EARNED FROM THIS INCOME SOURCE OVER THE PAST 3 MONTH IS INDEED OVER 15000, CLICK ON CONTINUE. OTHERWISE, GO BACK AND CHANGE THE AMOUNT ENTERED.] | G85: false | K85: ${income_sec_amount} > 15000 and (${income_main} != '19' and ${income_main} != '20' and ${income_sec} != '19' and ${income_sec} != '20' and ${income_sec} != '21') | S85: no | U85: 2.2941177 | V85: =1 -> 1 | W85: =IF(U85<>"",U85*V85,"") -> 2.2941177 | X85: =IF(AND(U85<>"",S85="yes"),U85*V85,"")
V86: =1 -> 1 | W86: =IF(U86<>"",U86*V86,"") | X86: =IF(AND(U86<>"",S86="yes"),U86*V86,"")
A87: select_one gender_inc_1 | B87: income_sec_gender | C87: What is the gender of the household member(s) generating income from this source? | G87: true | K87: ${income_main} != '19' and ${income_main} != '20' and ${income_sec} != '19' and ${income_sec} != '20' and ${income_sec} != '21'
A88: select_one gender_inc_2 | B88: income_sec_control | C88: Who controls the revenue that is earned from this source? | G88: true | K88: ${income_main} != '19' and ${income_main} != '20' and ${income_sec} != '19' and ${income_sec} != '20' and ${income_sec} != '21'
V89: =1 -> 1 | W89: =IF(U89<>"",U89*V89,"") | X89: =IF(AND(U89<>"",S89="yes"),U89*V89,"")
A90: select_one change | B90: income_sec_comp | C90: Has your household's income from ${incomesec} changed in the last 3 months compared to the same period of last year? | G90: true | K90: ${income_main} != '19' and ${income_main} != '20' and ${income_sec} != '19' and ${income_sec} != '20' and ${income_sec} != '21' | S90: yes | U90: 21.193256 | V90: =1 -> 1 | W90: =IF(U90<>"",U90*V90,"") -> 21.193256 | X90: =IF(AND(U90<>"",S90="yes"),U90*V90,"") -> 21.193256
V91: =1 -> 1 | W91: =IF(U91<>"",U91*V91,"") | X91: =IF(AND(U91<>"",S91="yes"),U91*V91,"")
A92: select_one incomesource3 | B92: income_third | C92: What was your household's third most important source of income in the past 3 months? | E92: [INSTRUCTIONS: DON'T KNOW AND REFUSED OPTIONS SHOULD BE AVOIDED AS MUCH AS POSSIBLE.] | G92: true | H92: minimal | K92: ${income_main} != '19' and ${income_main} != '20' and ${income_sec} != '19' and ${income_sec} != '20' and ${income_sec} != '21' | L92: not(selected(${income_main}, name) or selected(${income_sec}, name)) | S92: yes | U92: 20.229927 | V92: =1 -> 1 | W92: =IF(U92<>"",U92*V92,"") -> 20.229927 | X92: =IF(AND(U92<>"",S92="yes"),U92*V92,"") -> 20.229927
A93: calculate | B93: incomethird | N93: jr:choice-name(${income_third},'${income_third}') | S93: yes | V93: =1 -> 1 | W93: =IF(U93<>"",U93*V93,"") | X93: =IF(AND(U93<>"",S93="yes"),U93*V93,"")
A94: select_one yes_no | B94: income_third_crop_check | C94: Are the crops that you sell produced by you or anyone in your household? | G94: true | K94: ${income_third} = '1' or ${income_third} = '2' or ${income_third} = '3' | S94: yes | U94: 0 | V94: =1 -> 1 | W94: =IF(U94<>"",U94*V94,"") -> 0 | X94: =IF(AND(U94<>"",S94="yes"),U94*V94,"") -> 0
A95: select_one yes_no | B95: income_third_ls_check | C95: Are the livestock and livestock products that you sell produced by you or anyone in your household? | G95: true | K95: ${income_third} = '4' | S95: yes | U95: 0 | V95: =1 -> 1 | W95: =IF(U95<>"",U95*V95,"") -> 0 | X95: =IF(AND(U95<>"",S95="yes"),U95*V95,"") -> 0
A96: select_one yes_no | B96: income_third_fish_check | C96: Are the fish products that you sell produced by you or anyone in your household? | G96: true | K96: ${income_third} = '6' | S96: yes | U96: 0 | V96: =1 -> 1 | W96: =IF(U96<>"",U96*V96,"") -> 0 | X96: =IF(AND(U96<>"",S96="yes"),U96*V96,"") -> 0
V97: =1 -> 1 | W97: =IF(U97<>"",U97*V97,"") | X97: =IF(AND(U97<>"",S97="yes"),U97*V97,"")
V98: =1 -> 1 | W98: =IF(U98<>"",U98*V98,"") | X98: =IF(AND(U98<>"",S98="yes"),U98*V98,"")
A99: select_one change | B99: income_third_comp | C99: Has your household's income from ${incomethird} changed in the last 3 months compared to the same period of last year? | G99: true | K99: ${income_main} != '19' and ${income_main} != '20' and ${income_sec} != '19' and ${income_sec} != '20' and ${income_sec} != '21' and ${income_third} != '19' and ${income_third} != '20' and ${income_third} != '21' | S99: yes | U99: 16.348396 | V99: =1 -> 1 | W99: =IF(U99<>"",U99*V99,"") -> 16.348396 | X99: =IF(AND(U99<>"",S99="yes"),U99*V99,"") -> 16.348396
V100: =1 -> 1 | W100: =IF(U100<>"",U100*V100,"") | X100: =IF(AND(U100<>"",S100="yes"),U100*V100,"")
A101: select_multiple shock | B101: shock | C101: Has your household or community faced any particular disaster or crisis affecting your household's ability to raise an income and/or to produce food for self consumption in the last 3 months, and if so, which ones? | E101: [INSTRUCTIONS: SELECT RELEVANT SHOCKS EXPERIENCED BY THE HOUSEHOLD. MULTIPLE RESPONSES POSSIBLE. REFER TO ECONOMIC SHOCKS, CROP AND LIVESTOCK SHOCKS, INTRA-HOUSEHOLD SHOCK, NATURAL HAZARDS AND HUMAN-INDUCED HAZARDS.] | G101: true | I101: if(selected(.,'noshock') or selected(.,'dk') or selected(.,'ref'), count-selected(.) = 1, count-selected(.) >= 1) | S101: yes | U101: 46.247528 | V101: =1 -> 1 | W101: =IF(U101<>"",U101*V101,"") -> 46.247528 | X101: =IF(AND(U101<>"",S101="yes"),U101*V101,"") -> 46.247528
V102: =1 -> 1 | W102: =IF(U102<>"",U102*V102,"") | X102: =IF(AND(U102<>"",S102="yes"),U102*V102,"")
...

Sheet choices
A1: list_name | B1: name | C1: label::English (en) | D1: label:: | E1: my_filter_admin
A2: enumteam | B2: 1 | C2: Enumerator team 1
A3: enumteam | B3: 2 | C3: Enumerator team 2
A4: enumteam | B4: 3 | C4: Enumerator team 3
A5: enumteam | B5: 4 | C5: Enumerator team 4
A7: enumerator | B7: 1 | C7: enumerator name 1
A8: enumerator | B8: 2 | C8: enumerator name 2
A9: enumerator | B9: 3 | C9: enumerator name 3
A11: yes_no | B11: 1 | C11: YES
A12: yes_no | B12: 2 | C12: NO
A13: yes_no | B13: 3 | C13: DON'T KNOW
A14: yes_no | B14: 4 | C14: REFUSED
A16: continue | B16: continue | C16: continue
A18: yesno | B18: 1 | C18: Yes
A19: yesno | B19: 2 | C19: No
A21: language | B21: en | C21: English
A22: language | B22: fr | C22: French
A23: language | B23: … | C23: …
A25: gender | B25: 1 | C25: Male
A26: gender | B26: 2 | C26: Female
A27: gender | B27: 3 | C27: DON'T KNOW
A28: gender | B28: 4 | C28: REFUSED
A30: contact_info | B30: 1 | C30: YES - mine
A31: contact_info | B31: 2 | C31: YES - friend or relative
A32: contact_info | B32: 3 | C32: NO
A34: agricactivity | B34: 1 | C34: Yes - crop production
A35: agricactivity | B35: 2 | C35: Yes - livestock production
A36: agricactivity | B36: 3 | C36: Yes - both crop and livestock production
A37: agricactivity | B37: 4 | C37: No
A38: agricactivity | B38: 5 | C38: DON'T KNOW
... A85: residence | B85: 7 | C85: REFUSED
A87: asset_prod | B87: process | C87: Processing assets (e.g. grinding/crushing machine, mill, oil press)
A88: asset_prod | B88: farmmach | C88: Farm machinery (e.g. tractor, plough, sickle, etc.)
A89: asset_prod | B89: sewing | C89: Sewing machine or weaving tool
A90: asset_prod | B90: taxi | C90: Taxi
A91: asset_prod | B91: truck | C91: Truck
A92: asset_prod | B92: other | C92: Other productive machines or assets
A93: asset_prod | B93: none | C93: No productive machines or assets
A94: asset_prod | B94: dk | C94: DON'T KNOW
A95: asset_prod | B95: ref | C95: REFUSED
A97: asset_transp | B97: bici | C97: Bicycle
A98: asset_transp | B98: cart | C98: Cart (animal drawn)
A99: asset_transp | B99: boat | C99: Boat / canoe
... A106: asset_transp | B106: ref | C106: REFUSED
A108: maritalstat | B108: 1 | C108: Single / never married
A109: maritalstat | B109: 2 | C109: Married
A110: maritalstat | B110: 3 | C110: Separated
A111: maritalstat | B111: 4 | C111: Divorced
A112: maritalstat | B112: 5 | C112: Widowed
A113: maritalstat | B113: 6 | C113: DON’T KNOW
A114: maritalstat | B114: 7 | C114: REFUSED
A116: agegroup | B116: 1 | C116: Under 18
A117: agegroup | B117: 2 | C117: 18 to 40
A118: agegroup | B118: 3 | C118: 41 to 65
A119: agegroup | B119: 4 | C119: Over 65
A120: agegroup | B120: 5 | C120: DON'T KNOW
... A206: incomesource3 | B206: 21 | C206: REFUSED
A208: shock | B208: noshock | C208: No shock
A209: shock | B209: sicknessordeathofhh | C209: Sickness or accident or death of household member[s] [sickness of breadwinner / unusually high medical expenditure / funeral expenses / death of breadwinner]
A210: shock | B210: lostemplorwork | C210: Lost employment or working opportunities [not due to illness/accident]
A211: shock | B211: otherintrahhshock | C211: Other intra-household shock
A212: shock | B212: higherfoodprices | C212: Unusually high food prices
A213: shock | B213: higherfuelprices | C213: Unusually high l fuel prices or transport prices
A214: shock | B214: mvtrestrict | C214: Population movement restrictions [e.g. due to epidemic or infrastructure damage]
A215: shock | B215: othereconomicshock | C215: Other economic shock
A216: shock | B216: pestoutbreak | C216: Pest outbreak
A217: shock | B217: plantdisease | C217: Plant disease
A218: shock | B218: animaldisease | C218: Animal disease [affecting many animals] or death
A219: shock | B219: napasture | C219: Lack of physical access to pasture
... A247: covidmeasures | B247: ref | C247: REFUSED
A249: landsize_unit | B249: 1 | C249: Acres
A250: landsize_unit | B250: 2 | C250: Hectares
A251: landsize_unit | B251: 3 | C251: Square meters
A252: landsize_unit | B252: 4 | C252: Square feet
A254: cropcheck | B254: 1 | C254: Don’t usually produce during this season
A255: cropcheck | B255: 2 | C255: Wasn't able to produce (e.g. due to difficulties)
A257: irrigation | B257: 1 | C257: Rainfed
A258: irrigation | B258: 2 | C258: Groundwater
A259: irrigation | B259: 3 | C259: Natural surface water [river, lake, stream, pond, etc.]
A260: irrigation | B260: 4 | C260: Constructed water point [canal, dam, etc.]
A261: irrigation | B261: 5 | C261: Public water supply system [e.g. tap water]
A262: irrigation | B262: 6 | C262: Other [specify]
... A272: irrigpump | B272: 7 | C272: REFUSED
A274: seedsupply | B274: ownprod | C274: Own production
A275: seedsupply | B275: market | C275: Local market or agro-input shop / dealer
A276: seedsupply | B276: company | C276: Private seed company
A277: seedsupply | B277: ngo | C277: NGOs
A278: seedsupply | B278: organized_community | C278: Community seed banks / farmer networks / farmers' association / etc.
A279: seedsupply | B279: gov | C279: Government [e.g. MoA]
A280: seedsupply | B280: relatives_friends | C280: Relatives or friends
A281: seedsupply | B281: other | C281: Other
A282: seedsupply | B282: dk | C282: DON'T KNOW
A283: seedsupply | B283: ref | C283: REFUSED
A285: harv_unit | B285: 1 | C285: Kilograms [kgs]
A286: harv_unit | B286: 2 | C286: Tonnes
A287: harv_unit | B287: 3 | C287: Ounces
A288: harv_unit | B288: 4 | C288: Pounds
A289: harv_unit | B289: 5 | C289: Bags
A290: harv_unit | B290: 6 | C290: Boxes
A291: harv_unit | B291: 7 | C291: Bundles
...

Sheet settings
A1: version | B1: default_language | C1: allow_choice_duplicates | D1: style
A2: vM6cWXyHNhR3djPbARkHWi | B2: English (en) | C2: yes | D2: theme-grid no-text-transform

Sheet Crop list
C3: Select top 10 crops | D3: Dataset code | E3: Label (EN)
C4: x | D4: 1.1 | E4: Rice
D5: 1.2 | E5: Wheat
D6: 1.3 | E6: Millet
D7: 1.4 | E7: Sorghum
C8: x | D8: 1.5 | E8: Maize
D9: 1.6 | E9: Barley
D10: 1.99 | E10: Other Cereal
C11: x | D11: 2.1 | E11: Cassava
D12: 2.2 | E12: Potatoe
C13: x | D13: 2.3 | E13: Sweet Potatoes
D14: 2.4 | E14: Yams
D15: 2.5 | E15: Carrots
D16: 2.6 | E16: Cocoyam
D17: 2.99 | E17: Other tubers
C18: x | D18: 3.1 | E18: Beans
D19: 3.2 | E19: Lentils
D20: 3.3 | E20: Peas
D21: 3.4 | E21: Soybeans
D22: 3.5 | E22: Chickpeas
D23: 3.6 | E23: Fava beans
D24: 3.7 | E24: Broad beans
D25: 3.99 | E25: Other pulses
D26: 4.1 | E26: Cabbage
D27: 4.2 | E27: Lettuce
D28: 4.3 | E28: Spinach-Amaranth
D29: 4.4 | E29: Cassava leaves
D30: 4.5 | E30: Potatoe leaves
... D37: 5.2 | E37: Cucumber
C38: x | D38: 5.3 | E38: Pumpkin
D39: 5.4 | E39: Eggplant/aubergine
D40: 5.5 | E40: Zucchini
C41: x | D41: 5.6 | E41: Okra
D42: 5.7 | E42: Bell pepper
D43: 5.8 | E43: Onions
D44: 5.9 | E44: Haricot
D45: 5.101 | E45: Green peas
D46: 5.11 | E46: Fava beans green
D47: 5.99 | E47: Other non leafy vegs
D48: 6.1 | E48: Orange
D49: 6.2 | E49: Lemon
D50: 6.3 | E50: Grapefruit
D51: 6.4 | E51: Mandarins/clementines
D52: 6.99 | E52: Other citrus fruit
D53: 7.1 | E53: Sweet Banana
... D72: 8.1 | E72: Coconuts
C73: x | D73: 8.2 | E73: Groundnut/peanut
D74: 8.3 | E74: Cashew Nut
D75: 8.4 | E75: Kola Nut
D76: 8.5 | E76: Sesame
D77: 8.6 | E77: Bambara nut
D78: 8.7 | E78: Almond
D79: 8.8 | E79: Walnut
D80: 8.99 | E80: Other nuts
C81: x | D81: 9.1 | E81: Cocoa
C82: x | D82: 9.2 | E82: Coffee
D83: 9.3 | E83: Tea
D84: 9.4 | E84: Sugarcane
D85: 9.5 | E85: Sunflower
D86: 9.99 | E86: Other food cash crop
D87: 10.1 | E87: Cotton
D88: 10.2 | E88: Rubber
D89: 10.3 | E89: Jute
D90: 10.4 | E90: Fodder
D91: 10.5 | E91: Tobacco
D92: 10.6 | E92: Qat
D93: 10.99 | E93: Other non-food cash crop

Sheet Additional information
C2: Original | D2: Replacement | E2: Comment | F2: Example
B3: FOR CORE QUESTIONS . (Mandatory to fill out) . | C3: phone number | D3: 076xxxxxx | E3: Type a phone number from your country in typical format, e.g. 77******* [please use exactly the number of characters that are found in a phone number]. | F3: 070******
C4: age | D4: 18 | E4: Minimum age of respondent (recommend 18 years old) | F4: 18
C5: ADMIN1 | D5: Regional | E5: The first subdivision of the country, after national level; region; province; governorate; etc. Only one word should be inputted - Do not include spaces. | F5: region
C6: ADMIN2 | D6: District | E6: The second subdivision of the country; district; municipality; LGA; etc. Only one word should be inputted - Do not include spaces. | F6: district
C7: reference year | D7: last year | E7: Comparison questions will need need a reference year. Select whether you want to use "last year" or "a normal year" as a baseline. A "normal year" should refers to an average year from the past 5 years - make sure to train the enumerators accordingly. | F7: a normal year
C8: season | D8: Last season | E8: Name the crop season(s) of interest if there are several cropping seasons in the country (e.g. Meher and Belg in Ethiopia, rainy season / flood-recession cropping / irrigated dry season in the Sahel). You can refer to the “last season” or “ongoing season". | F8: wet season
C9: season phase | D9: Recently finished | E9: Indicate the phase of the season at the time of data collection. If the harvest from the season has not yet occurred, the question on crop harvest (crp_harv_change) will include the word “expected” (where #expected or nothing# is located). If the harvest has occured, "expected" will not be inserted in the question. | F9: Harvesting
C10: local measurement unit | E10: Specify the local measurement unit for land size, other than acres, hectares, square meters and square feet. If no other unit of measurement is needed, keep this cell blank. | F10: Jeribs
C11: local measurement unit conversion | E11: Include the conversion of the local measurement unit to hectares. In other words, how many local measurement units are in 1 ha. | F11: 0.2
B12: FOR OPTIONAL QUESTIONS . (Fill out if applicable) . | C12: currency | D12: SLE | E12: The name of the main currency used nationally; USD; Naira; Rial; Pesos; etc. | F12: Naira
C13: MIN AMOUNT | D13: 1 | E13: The minimum amount for an income source should be set at 0 or any value below which it is not possible to do a transaction. For example, the smallest coin/banknote in a currency can be 1000, in which case you would set the minimum at 1000. Provide this input in the same currency as specified above. Only digits should be inputted. | F13: 5
C14: THRESHOLD | D14: 15000 | E14: The threshold salary should be calculated to flag outliers (responses that look suspiciously high). Using previous representative surveys for this population, a good estimate is the average plus three (3) standard deviations, which should give the threshold for the 3 or 4% highest income values. Provide this input in the same currency as specified above. Only digits should be inputted. | F14: 1200000
C15: local vegetables | D15: Okra, Potato leaves, Cassava leaves, Garden eggs , Tomatoes, Green, Krain krain,Llettuce, Cabbage,Carrot, Pepper, Onions, Cucumber, pumpkin | E15: Input some common local vegetables [to be used as examples in the food consumption score indicator]. | F15: eggplants, zucchini, cauliflower
C16: local fruits | D16: Banana, 0ranges, Plantain, Grape fruits, Avocado, Lemon, Guava, Pineapple, Water melon , Apple, Pawpaw | E16: Input some common local fruits [to be used as examples in the food consumption score indicator]. | F16: apples, bananas, oranges
B18: FILL OUT FOR QUESTIONNAIRE DURATION ESTIMATION . | C18: Expected percentage of respondents cultivating crops | D18: 0.91 | E18: If the survey is representative and has no quotas, write the proportion of rural households cultivating crops at country level, or if the survey follows a previous round with identical sample design, just report the percentage from the previous round. If you are using quotas, calculate the ratio of the quota over the minimum sample size at the level where the quota is implemented (so if you have a minimum sample size per strata of 110 with a quota of 100 crop producers, then it's 100/110 = 91% (the maximum you should write is 100%). | F18: 0.91
C19: Expected percentage of respondents raising livestock | D19: 0.91 | E19: If the survey is representative and has no quotas, write the proportion of rural households raising livestock at country level, or if the survey follows a previous round with identical sample design, just report the percentage from the previous round. If you are using quotas, calculate the ratio of the quota over the minimum sample size at the level where the quota is implemented (so if you have a minimum sample size of 110 but a quota of 100 livestock producers, then it's 100/110 = 91% (the maximum you should write is 100%) | F19: 0.91
C20: Expected percentage of respondents involved in fishery | D20: 0.05 | E20: If the survey is representative and has no quotas, write the proportion of rural households involved in fisheries or aquaculture, otherwise if you are using quotas, calculate the ratio of the quota over the sample size at the level where the quota is implemented. (so if you haven't set a quota, and you expect to have a representative proportion of fishermen, just write the percentage of fishermen in the population you are targeting, in the example to the right, 5%) | F20: 0.05
