Workbook

Sheet New Durations
A1: question | B1: duration | C1: responded % | D1: weighted time
A2: introduction | B2: 50.82254 | C2: 1 | D2: 50.82254
A3: agree | B3: 3.4964738 | C3: 0.79698741 | D3: 2.7866456
A4: resp_age | B4: 13.753073 | C4: 1 | D4: 13.753073
A5: resp_gender | B5: 2.1173561 | C5: 1 | D5: 2.1173561
A6: quotareached | B6: 2.28425 | C6: 0.79698741 | D6: 1.8205185
A7: hh_agricactivity | B7: 31.372377 | C7: 1 | D7: 31.372377
A8: hh_milieu | B8: 7.9225454 | C8: 0.15190348 | D8: 1.2034622
A9: hh_gender | B9: 10.085732 | C9: 1 | D9: 10.085732
A10: hh_education | B10: 12.894034 | C10: 1 | D10: 12.894034
A11: hh_wealth_water | B11: 15.265829 | C11: 0.63796463 | D11: 9.739059
A12: hh_wealth_toilet | B12: 15.123718 | C12: 0.59180156 | D12: 8.95024
A13: hh_wealthwall | B13: 12.821411 | C13: 0.15190348 | D13: 1.9476169
... A164: adm1_name | B164: 10.743817 | C164: 0.20301259 | D164: 2.1811302
A165: adm2_name | C165: 0 | D165: 0
A166: covid | B166: 56.471024 | C166: 0.20301259 | D166: 11.464329
A167: crp_landright | B167: 31 | C167: 0.0040467626 | D167: 0.12544964
A168: crp_seed | B168: 30.833334 | C168: 0.0040467626 | D168: 0.12477518
A169: crp_proddif | B169: 16.882986 | C169: 0.11848022 | D169: 2.0002998
A170: crp_salesdif | B170: 16.82699 | C170: 0.086630695 | D170: 1.4577339
A171: crp_saledif_2 | B171: 39.486874 | C171: 0.03139988 | D171: 1.2398831
A172: ls_proddif | B172: 15.938099 | C172: 0.10169365 | D172: 1.6208034
A173: ls_salesdif | B173: 13.330855 | C173: 0.060476619 | D173: 0.80620506
A174: ls_proc | B174: 16.437651 | C174: 0.0625 | D174: 1.0273532
A175: ls_proc_fac_state | B175: 8.666667 | C175: 0.00067446043 | D175: 0.005845324
A176: fish_proddif | B176: 12.523809 | C176: 0.001573741 | D176: 0.019709232
A177: cs_spentsavings | B177: 22.220184 | C177: 0.0081684652 | D177: 0.1815048
... A193: ls_proddif_2_covid19 | B193: 3.3438249 | C193: 1 | D193: 3.3438249

Sheet survey
A1: GeoPoll Submission Form | Z1: Change made
A2: FAO - Household Questionnaire | P2: Additional notes
A3: Q # | B3: Q Name | C3: Suggested Qname | D3: English | E3: Length | F3: French | G3: Length | H3: Q Type | I3: Randomize | J3: Conditional | K3: Programming Instructions | L3: Skip Pattern | M3: Default skip patterns & conditional | N3: Specify skip pattern variable (from blue text) | O3: UNIVERSE | Q3: Duration average (sec) | R3: Estimated percentage of repondents | S3: Weighted Duration | V3: Mandatory
A4: A. PRESENTATION OF THE SURVEY AND ELIGIBILITY CRITERIA SELECTION | V4: no
A5: NA | B5: Optin | D5: Optin | E5: =LEN(D5) -> 5 | F5: Optin | G5: =LEN(F5) -> 5 | H5: Open Ended | I5: NA | J5: NA | K5: Form Type - TextBox | L5: Any Response = phone_number | M5: NA | O5: ALL | Q5: 0 | S5: =Q5*R5 -> 0 | V5: no
A6: NA | B6: phone_number | C6: phone_number | D6: Input the phone number that you are contacting: | E6: =LEN(D6) -> 48 | F6: Saisir le numéro de téléphone que vous chercher à contacter: | G6: =LEN(F6) -> 61 | H6: Open Ended | I6: NA | J6: NA | K6: Form Type - TextBox | L6: Any Response = hh_id | M6: NA | O6: ALL | Q6: 0 | S6: =Q6*R6 -> 0 | V6: yes | Z6: New question
A7: NA | B7: hh_id | C7: hh_id | D7: Input the household ID, if applicable: | E7: =LEN(D7) -> 38 | F7: Le cas échéant, saisir l'identifiant du ménage: | G7: =LEN(F7) -> 47 | H7: Open Ended | I7: NA | J7: NA | K7: Form Type - TextBox | L7: Any Response = calldispo | M7: NA | O7: ALL | Q7: 0 | S7: =Q7*R7 -> 0 | V7: yes | Z7: New question
A8: NA | B8: calldispo | C8: calldispo | D8: Phone number: #CATI_MOBILENUMBER# 1)Someone answers 2)Answering machine 3)No answer 4)Hang up or refusal 5)Call back 6)Under review 7)Disconnected | E8: =LEN(D8) -> 146 | F8: Numéro de téléphone: #CATI_MOBILENUMBER# 1)Quelqu’un répond 2)Répondeur 3)Pas de réponse 4)Raccroche/Refuse 5)Doit être rappeler 6)À l’étude 7)Déconnecté | G8: =LEN(F8) -> 153 | H8: Single Choice | I8: NA | J8: NA | K8: Form Type - Buttons | L8: 1 = resp_language 2 = AnsweringMachine 3 = NoAnswer 4 = Refusal 5 = WhenCallBack 6 = UnderReview 7 = Disconnected | M8: NA | O8: ALL | Q8: 0 | S8: =Q8*R8 -> 0 | V8: no
A9: NA | B9: AnsweringMachine | C9: calldispo_answeringmachine | D9: Reached an answering machine. | E9: =LEN(D9) -> 29 | F9: L'appel a abouti sur un répondeur. | G9: =LEN(F9) -> 34 | H9: NA | I9: NA | J9: NA | K9: NA | L9: End Poll AnsweringMachine | M9: NA | O9: calldispo = 2 | Q9: 0 | S9: =Q9*R9 -> 0 | V9: no
A10: NA | B10: NoAnswer | C10: calldispo_noanswer | D10: Phone rang and no one answered. | E10: =LEN(D10) -> 31 | F10: Le téléphone a sonné et personne n'a répondu. | G10: =LEN(F10) -> 45 | H10: NA | I10: NA | J10: NA | K10: NA | L10: End Poll NoAnswer | M10: NA | O10: calldispo = 3 | Q10: 0 | S10: =Q10*R10 -> 0 | V10: no
A11: NA | B11: UnderReview | C11: calldispo_underreview | D11: Case needs review by a supervisor. | E11: =LEN(D11) -> 34 | F11: Le cas doit être examiné par un superviseur. | G11: =LEN(F11) -> 44 | H11: NA | I11: NA | J11: NA | K11: NA | L11: End Poll UnderReview | M11: NA | O11: calldispo = 6 | Q11: 0 | S11: =Q11*R11 -> 0 | V11: no
A12: NA | B12: Disconnected | C12: calldispo_disconnected | D12: Phone was disconnected or out of service. | E12: =LEN(D12) -> 41 | F12: Le téléphone est déconnecté ou hors service. | G12: =LEN(F12) -> 44 | H12: NA | I12: NA | J12: NA | K12: NA | L12: End Poll Disconnected | M12: NA | O12: calldispo = 7 | Q12: 0 | S12: =Q12*R12 -> 0 | V12: no
A13: NA | B13: resp_language | C13: resp_language | D13: Which language do you wish to proceed with? [OPERATOR: READ ANSWER CHOICES. SINGLE RESPONSE.] 1)English 2)other options [add as many as necessary] | E13: =LEN(D13) -> 148 | F13: Dans quelle langue souhaitez-vous que nous parlions? [OPÉRATEUR/OPÉRATRICE: LISEZ LES CHOIX, RÉPONSE UNIQUE] 1)Français 2)autre [ajouter autant d'options que nécessaire] | G13: =LEN(F13) -> 171 | H13: Single Choice | I13: NA | J13: NA | K13: Form Type - Buttons | L13: 1 = introduction [English] 2 = introduction [languages & add more if needed] | M13: For any response, go to introduction | O13: ALL | P13: Insert most common national languages here [max 4 for translation with GeoPoll]. Insérer ici les langues nationales les plus courantes [4 maximum pour la traduction avec GeoPoll]. | Q13: 3.0622325 | S13: =Q13*R13 -> 0 | V13: no
A14: NA | B14: introduction | C14: introduction | D14: Hello sir/ma'am, my name is #OPERATOR#, and I am calling from GeoPoll Polling Agency on behalf of the humanitarian organization called Food and Agriculture Organization of the United Nations (FAO). We are conducting a survey on households' ability to access food in your area and the impact of COVID-19 pandemic. I would like to ask you some questions about your household. The survey usually takes 15/20 minutes to complete. Any information that you provide will be kept strictly confidential, only used for the purpose of the survey and will not be shown to other people. No personal identifying information will be collected. Your voluntary participation in the outcome of this interview is NOT IN ANY WAY linked to your personal chance of receiving any assistance. This is voluntary and you can choose not to answer any or all of the questions if you want. However, we hope that you will participate since your views are important. You will receive #TOPUP#! of communication credit as an incentive for the participation of the survey. Please note that this call may be recorded for quality purposes. Do you have any questions? [OPERATOR: ADDRESS QUESTIONS FROM RESPONDENT, IF ANY.] 1)CONTINUE | E14: =LEN(D14) -> 1204 | F14: Bonjour Monsieur/Madame, mon nom est #OPERATOR#. Je vous appelle de la part de l'agence de sondage GeoPoll pour le compte de l'organisation humanitaire appelée l'Organisation des Nations Unies pour l'alimentation et l'agriculture (la FAO). Nous menons une enquête sur la capacité des ménages à accéder à la nourriture dans votre région et sur l'impact de la pandémie de covid-19. J'aimerais vous poser quelques questions sur votre ménage. L'enquête dure généralement entre 15 et 20 minutes. Toutes les informations que vous fournirez resteront strictement confidentielles; elles ne seront utilisées que pour cette enquête et ne seront pas communiquées à d'autres personnes. Aucune information permettant de vous identifier personnellement ne sera recueillie. Votre participation volontaire à cet entretien n'est en AUCUN CAS liée à la possibilité de recevoir une quelconque aide. Votre participation est volontaire et, si vous le souhaitez, vous pouvez choisir de ne pas répondre à une partie ou à la totalité des questions. Cependant, nous espérons que vous voudrez bien participer car votre avis est important. Vous recevrez #TOPUP#! de crédit téléphonique comme incitation à participer à l'enquête. Veuillez noter que cet appel peut être enregistré à des fins de contrôle de la qualité. Avez-vous des questions? [OPÉRATEUR/OPÉRATRICE: RÉPONDRE, LE CAS ÉCHÉANT, AUX QUESTIONS DE LA PERSONNE INTERROGÉE.] 1)CONTINUER | G14: =LEN(F14) -> 1424 | H14: Single Choice | I14: NA | J14: NA | K14: Form Type - Buttons | L14: 1 = Agree | M14: For any response, go to Agree | O14: ALL | P14: Set the amount of incentive here, if any. Le cas échéant, définir ici le montant de l'incitation. | Q14: 50.82254 | S14: =Q14*R14 -> 0 | V14: no
A15: NA | B15: Agree | C15: resp_agree | D15: Are you interested in participating in this survey? [OPERATOR: SINGLE RESPONSE] 1)Yes 2)Not now but another time in the week 3)No | E15: =LEN(D15) -> 134 | F15: Souhaitez-vous participer à cette enquête? [OPÉRATEUR/OPÉRATRICE: RÉPONSE UNIQUE] 1)Oui 2)Pas maintenant, mais à un autre moment de la semaine 3)Non | G15: =LEN(F15) -> 152 | H15: StartRecording | I15: NA | J15: NA | K15: Form Type - Buttons | L15: 1 = resp_firstname 2 = WhenCallBack 3 = resp_refusalwhy | M15: if Agree = 1, go to resp_firstname if Agree = 2, go to WhenCallBack if Agree = 3, go to resp_refusalwhy | O15: ALL | Q15: 3.4964738 | R15: 1 | S15: =Q15*R15 -> 3.4964738 | V15: no
A16: NA | B16: resp_refusalwhy | C16: resp_refusalwhy | D16: Please let us know why you have REFUSED to take the survey. [OPERATOR: SINGLE RESPONSE] 1)Not interested 2)Do not want to be recorded 3)Other [specify] | E16: =LEN(D16) -> 153 | F16: Pourriez-vous m'indiquer pourquoi vous refusez de répondre à l'enquête. [OPÉRATEUR/OPÉRATRICE: RÉPONSE UNIQUE] 1)Pas intéressé 2)Ne veut pas être enregistré 3)Autre [préciser] | G16: =LEN(F16) -> 178 | H16: Open Ended - Single Choice | I16: NA | J16: NA | K16: Form Type - RadioList | L16: Any Response = Refusal | M16: For any response, go to Refusal | O16: resp_agree = 3 | Q16: 0 | R16: 1 | S16: =Q16*R16 -> 0 | V16: no
A17: NA | B17: WhenCallBack | C17: resp_whencallback | D17: When would it be a good time to call you back? [RECORD HH/MM/DD/MM OF CALLBACK] | E17: =LEN(D17) -> 80 | F17: À quel moment pourrais-je vous rappeler? [ENREGISTRER HH/MM/JJ/MM DU RAPPEL] | G17: =LEN(F17) -> 77 | H17: Open Ended | I17: NA | J17: NA | K17: Form Type - TextBox set as demographic | L17: Any Response = CallbackMessageEN | M17: For any response, go to CallbackMessageEN | O17: resp_agree = 2 | Q17: 0 | R17: 1 | S17: =Q17*R17 -> 0 | V17: no
A18: NA | B18: CallbackMessageEN | C18: callbackmessage_en | D18: Thank you, we will call you back at #WhenCallBack# you requested. Thank you again and have a great day! [OPERATOR: ENTER CALL NOTES BELOW, WHO YOU SPOKE TO AND WHAT THEY SAID] | E18: =LEN(D18) -> 176 | F18: Merci, nous vous rappellerons à #WhenCallBack#. Merci encore et bonne journée! [OPÉRATEUR/OPÉRATRICE: SAISIR LES DONNÉES D'APPEL CI-DESSOUS, LE NOM DE LA PERSONNE À LAQUELLE VOUS AVEZ PARLÉ ET CE QU'ELLE A DIT] | G18: =LEN(F18) -> 211 | H18: Open Ended | I18: NA | J18: NA | K18: Form Type - TextBox | L18: End poll callback | M18: NA | O18: resp_agree = 2 | Q18: 0 | R18: 1 | S18: =Q18*R18 -> 0 | V18: no
A19: NA | B19: Ineligible | C19: NA | D19: You are ineligible for this survey. Thank you for your time and please look out for future GeoPoll surveys! For more information visit GeoPoll.com | E19: =LEN(D19) -> 146 | F19: Vous ne pouvez être retenu pour cette enquête. Merci pour votre temps et renseignez-vous sur les prochains sondages GeoPoll! Pour plus d'informations, consultez GeoPoll.com | G19: =LEN(F19) -> 172 | H19: NA | I19: NA | J19: NA | K19: NA | L19: End Poll Ineligible | M19: NA | O19: NA | Q19: 0 | R19: 1 | S19: =Q19*R19 -> 0 | V19: no
A20: NA | B20: Refusal | C20: NA | D20: Thank you for your time, you will be removed from today's survey. | E20: =LEN(D20) -> 65 | F20: Merci pour votre temps. Vous serez écarté de l'enquête d'aujourd'hui. | G20: =LEN(F20) -> 69 | H20: NA | I20: NA | J20: NA | K20: NA | L20: End poll declined | M20: NA | O20: calldispo = 4 | Q20: 0 | R20: 1 | S20: =Q20*R20 -> 0 | V20: no
A21: B. GENERAL INFORMATION & ELIGIBILITY CRITERIA
A22: NA | B22: resp_firstname | C22: resp_firstname | D22: What is your first name? [OPERATOR: RECORD THE RESPONDENT'S FIRST NAME. ENTER 999 FOR REFUSED.] | E22: =LEN(D22) -> 96 | F22: Quel est votre prénom ? [OPÉRATEUR/OPÉRATRICE: ENREGISTRER LE PRÉNOM DE LA PERSONNE INTÉRROGÉE. SAISIR 999 POUR REFUSÉ.] | G22: =LEN(F22) -> 122 | H22: Open Ended | I22: NA | J22: NA | K22: Form Type - TextBox | L22: Any Response = resp_lastname | M22: For any response, go to resp_lastname | O22: resp_agree = 1 | Q22: 10 | R22: =1 -> 1 | S22: =Q22*R22 -> 10 | V22: yes | Z22: new question
A23: NA | B23: resp_lastname | C23: resp_lastname | D23: What is your last name? [OPERATOR: RECORD THE RESPONDENT'S LAST NAME. ENTER 999 FOR REFUSED.] | E23: =LEN(D23) -> 95 | F23: Quel est votre nom de famille ? [OPÉRATEUR/OPÉRATRICE: ENREGISTRER LE NOM DE FAMILLE DE LA PERSONNE INTÉRROGÉE. SAISIR 999 POUR REFUSÉ.] | G23: =LEN(F23) -> 138 | H23: Open Ended | I23: NA | J23: NA | K23: Form Type - TextBox | L23: Any Response = resp_age | M23: For any response, go to resp_age | O23: resp_agree = 1 | Q23: 10 | R23: =1 -> 1 | S23: =Q23*R23 -> 10 | V23: yes | Z23: new question
A24: 1 | B24: resp_age | C24: resp_age | D24: How old are you? [OPERATOR: RECORD AGE IN NUMBER OF YEARS. ROUND UP TO NEAREST WHOLE NUMBER. IF THE RESPONDENT GIVES BIRTH YEAR, REPEAT THE QUESTION. ENTER 00 FOR DON'T KNOW.] | E24: =LEN(D24) -> 177 | F24: Quel âge avez-vous (en années) ? [OPÉRATEUR/OPÉRATRICE: ENREGISTRER L'ÂGE EN ANNÉES. ARRONDIR AU NOMBRE ENTIER LE PLUS PROCHE. SI LE RÉPONDANT DONNE SON ANNÉE DE NAISSANCE, RÉPÉTER LA QUESTION. SAISIR 00 pour JE NE SAIS PAS.] | G24: =LEN(F24) -> 226 | H24: Range | I24: NA | J24: NA | K24: Form Type - TextBox | L24: 0-17 = Ineligible 18-100 = resp_gender 00 = Ineligible | M24: Only respondents from 18-100 will be eligible for the surve. | O24: resp_agree = 1 | Q24: 13.753073 | R24: =1 -> 1 | S24: =Q24*R24 -> 13.753073 | V24: yes
A25: =A24+1 -> 2 | B25: resp_gender | C25: resp_gender | D25: What is the gender of the respondent? [OPERATOR: DO NOT ASK THIS QUESTIONNAIRE. LISTEN TO THE VOICE AND CHECK THE CORRECT BOX.] 1)Male 2)Female 3)DON'T KNOW 4)REFUSED | E25: =LEN(D25) -> 168 | F25: Quel est le sexe du répondant ? [OPÉRATEUR/OPÉRATRICE: ÉCOUTER LA VOIX ET DÉTERMINER SI LE RÉPONDANT EST UN HOMME OU UNE FEMME.] 1)Homme 2)Femme 3)NE SAIT PAS 4)REFUSÉ | G25: =LEN(F25) -> 171 | H25: Single Choice | I25: NA | J25: NA | K25: Form Type - Buttons | L25: 1-4 = phone_number_conf | M25: For any response, go to phone_number_conf | O25: resp_agree = 1 resp_age = 18-100 | Q25: 2.1173561 | R25: =1 -> 1 | S25: =Q25*R25 -> 2.1173561 | V25: yes
R26: =1 -> 1 | S26: =Q26*R26 -> 0
B27: phone_number_conf | C27: phone_number_conf | D27: Is the phone number I am calling you on yours or a household member's? [OPERATOR: SINGLE RESPONSE.] 1)YES 2)NO 3)DON'T KNOW 4)REFUSED | E27: =LEN(D27) -> 135 | F27: Le numéro de téléphone sur lequel je vous appelle est-il le vôtre ou celui d'un membre de votre famille ? [OPÉRATEUR/OPÉRATRICE: RÉPONSE UNIQUE.] 1)Oui 2)Non 3)NE SAIT PAS 4)REFUSÉ | G27: =LEN(F27) -> 182 | H27: Single Choice | I27: NA | J27: NA | K27: Form Type - Buttons | L27: 1 = contact_2 2 = phone_number_personal 3-4 = contact_2 | M27: if phone_number_conf = 1, go to contact_2 if phone_number_conf = 2, go to phone_number_personal if phone_number_conf = 3-4, go to contact_2 | O27: resp_agree = 1 resp_age = 18-100 | Q27: 10 | R27: =1 -> 1 | S27: =Q27*R27 -> 10 | V27: yes - panel | Z27: new question
B28: phone_number_personal | C28: phone_number_pers | D28: What is your phone number? | E28: =LEN(D28) -> 26 | F28: Quel est votre numéro de téléphone ? | G28: =LEN(F28) -> 36 | H28: Open Ended | I28: NA | J28: NA | K28: Form Type - TextBox | L28: Any Response = contact_2 | M28: For any response, go to contact_2 | O28: resp_agree = 1 resp_age = 18-100 phone_number_conf = 2 | Q28: 10 | R28: =1 -> 1 | S28: =Q28*R28 -> 10 | V28: yes - panel | Z28: new question
B29: contact_2 | C29: contact_2 | D29: Can you give me an additonal phone number belonging to you, a relative or a friend at which you can be reached? [OPERATOR: SINGLE RESPONSE.] 1)YES - mine 2)YES - friend or relative 3)NO 4)DON'T KNOW 5)REFUSED | E29: =LEN(D29) -> 211 | F29: Pouvez-vous me donner un autre numéro de téléphone, le vôtre, celui d'un parent ou d'un ami, auquel vous pouvez être joint ? [OPÉRATEUR/OPÉRATRICE: RÉPONSE UNIQUE.] 1)Oui - le mien 2)Oui - celui d'un ami ou d'un parent 3)Non 4)NE SAIT PAS 5)REFUSÉ | G29: =LEN(F29) -> 249 | H29: Single Choice | I29: NA | J29: NA | K29: Form Type - Buttons | L29: 1-2 = phone_number_2 3-5 = hh_admin1 | M29: if contact_2 = 1-2, go to phone_number_2 if contact_2 = 3-5, go to contact_3 | O29: resp_agree = 1 resp_age = 18-100 | Q29: 10 | R29: =1 -> 1 | S29: =Q29*R29 -> 10 | V29: yes - panel | Z29: new question
B30: phone_number_2 | C30: phone_number_2 | D30: What is the additional phone number? | E30: =LEN(D30) -> 36 | F30: Quel est cet autre numéro de téléphone ? | G30: =LEN(F30) -> 40 | H30: Open Ended | I30: NA | J30: NA | K30: Form Type - TextBox | L30: Any Response = contact_2_name | M30: For any response, go to contact_2_name | O30: resp_agree = 1 resp_age = 18-100 contact_2 = 1 | 2 | Q30: 10 | R30: =1 -> 1 | S30: =Q30*R30 -> 10 | V30: yes - panel | Z30: new question
B31: contact_2_name | C31: contact_2_name | D31: What is the name of the contact? | E31: =LEN(D31) -> 32 | F31: Quel est le nom du contact associé à ce numéro de téléphone ? | G31: =LEN(F31) -> 61 | H31: Open Ended | I31: NA | J31: Send if "contact_2" "Equals" "YES - friend or relative", if not satisfied go to "contact_3" | K31: Form Type - TextBox | L31: Any Response = contact_3 | M31: Asked if "contact_2" "Equals" "YES - friend or relative". Otherwise, it skips to "contact_3". For any response, go to contact_3 | O31: resp_agree = 1 resp_age = 18-100 contact_2 = 2 | Q31: 10 | R31: =1 -> 1 | S31: =Q31*R31 -> 10 | V31: yes - panel
B32: contact_3 | C32: contact_3 | D32: Can you give me an additonal phone number belonging to you, a relative or a friend at which you can be reached? [OPERATOR: SINGLE RESPONSE.] 1)YES - mine 2)YES - friend or relative 3)NO 4)DON'T KNOW 5)REFUSED | E32: =LEN(D32) -> 211 | F32: Pouvez-vous me donner un autre numéro de téléphone, le vôtre, celui d'un parent ou d'un ami, auquel vous pouvez être joint ? [OPÉRATEUR/OPÉRATRICE: RÉPONSE UNIQUE.] 1)Oui - le mien 2)Oui - celui d'un ami ou d'un parent 3)Non 4)NE SAIT PAS 5)REFUSÉ | G32: =LEN(F32) -> 249 | H32: Single Choice | I32: NA | J32: NA | K32: Form Type - Buttons | L32: 1-2= phone_number_3 3-5 = hh_admin1 | M32: if contact_3 = 1-2, go to phone_number_3 if contact_3 = 3-5, go to hh_admin1 | O32: resp_agree = 1 resp_age = 18-100 contact_2 = 1 | 2 | Q32: 10 | R32: =1 -> 1 | S32: =Q32*R32 -> 10 | V32: yes - panel | Z32: new question
B33: phone_number_3 | C33: phone_number_3 | D33: What is the additional phone number? | E33: =LEN(D33) -> 36 | F33: Quel est cet autre numéro de téléphone ? | G33: =LEN(F33) -> 40 | H33: Open Ended | I33: NA | J33: NA | K33: Form Type - TextBox | L33: Any Response = contact_3_name | M33: For any response, go to contact_3_name | O33: resp_agree = 1 resp_age = 18-100 contact_3 = 1 | 2 | Q33: 10 | R33: =1 -> 1 | S33: =Q33*R33 -> 10 | V33: yes - panel | Z33: new question
B34: contact_3_name | C34: phone_number_3_name | D34: What is the name of the contact? | E34: =LEN(D34) -> 32 | F34: Quel est le nom du contact associé à ce numéro de téléphone ? | G34: =LEN(F34) -> 61 | H34: Open Ended | I34: NA | J34: Send if "contact_3" "Equals" "YES - friend or relative", if not satisfied go to "hh_admin1" | K34: Form Type - TextBox | L34: Any Response = hh_admin1 | M34: Asked if "contact_3" "Equals" "YES - friend or relative". Otherwise, it skips to "hh_admin1". For any response, go to hh_admin1 | O34: resp_agree = 1 resp_age = 18-100 contact_3 = 2 | Q34: 10 | R34: =1 -> 1 | S34: =Q34*R34 -> 10 | V34: yes - panel
R35: =1 -> 1 | S35: =Q35*R35 -> 0
A36: 3 | B36: hh_admin1 | C36: hh_admin1 | D36: Currently, in which $ADMIN1$ does your household reside? [OPERATOR: SINGLE SELECTION.] [HINT: HOUSEHOLD CONSISTS OF ALL MEMBERS LIVING TOGETHER, SHARING RESOURCES & EATING FROM THE SAME POT.] 1) … 2) … 3)DON'T KNOW 4)REFUSED | E36: =LEN(D36) -> 229 | F36: Actuellement, dans quel $ADMIN1$ votre ménage vit-il ? [OPÉRATEUR/OPÉRATRICE: RÉPONSE UNIQUE.] [CONSEIL: LE MÉNAGE EST COMPOSÉ DE TOUTES LES PERSONNES VIVANT ENSEMBLE, PARTAGEANT LEURS RESSOURCES ET MANGEANT DANS UNE MARMITE COMMUNE.] 1)... 2)... 3)NE SAIT PAS 4)REFUSÉ | G36: =LEN(F36) -> 273 | H36: Single Choice | I36: NA | J36: NA | K36: Form Type - Buttons set Demographic - ADM1 | L36: 1 = hh_admin2_1 2 = hh_admin2_2 […] 3-4 = Ineligible | M36: The administrative information will be updated by GeoPoll based on the sample design document and the administrative boundaries provided by the dashboard team after the questionnaire validation. | O36: resp_agree = 1 resp_age = 18-100 | Q36: 8.8 | R36: =1 -> 1 | S36: =Q36*R36 -> 8.8 | V36: yes
A37: =A36+1 -> 4 | B37: hh_admin2_1 | C37: hh_admin2_1 | D37: Currently, in which $ADMIN2$ does your household reside? [OPERATOR: SINGLE RESPONSE.] 1) … 2) … 3)DON'T KNOW 4)REFUSED | E37: =LEN(D37) -> 123 | F37: Actuellement, dans quel $ADMIN2$ votre ménage vit-il ? [OPÉRATEUR/OPÉRATRICE: RÉPONSE UNIQUE.] 1)... 2)... 3)NE SAIT PAS 4)REFUSÉ | G37: =LEN(F37) -> 134 | H37: Single Choice | I37: NA | J37: NA | K37: Form Type - Buttons set Demographic - ADM2 | L37: 1-2 = quotareached 3-4 = Ineligible | O37: resp_agree = 1 resp_age = 18-100 hh_admin1 = 1 | Q37: 10.4 | R37: =1 -> 1 | S37: =Q37*R37 -> 10.4 | V37: yes
A38: 4 | B38: hh_admin2_2 | C38: hh_admin2_2 | D38: Currently, in which $ADMIN2$ does your household reside? [OPERATOR: SINGLE RESPONSE.] 1) … 2) … 3) DON'T KNOW 4) REFUSED | E38: =LEN(D38) -> 125 | F38: Actuellement, dans quel $ADMIN2$ votre ménage vit-il ? [OPÉRATEUR/OPÉRATRICE: RÉPONSE UNIQUE.] 1) ... 2) ... 3)NE SAIT PAS 4)REFUSÉ | G38: =LEN(F38) -> 135 | H38: Single Choice | I38: NA | J38: NA | K38: Form Type - Buttons set Demographic - ADM2 | L38: 1-2 = quotareached 3-4 = Ineligible | O38: resp_agree = 1 resp_age = 18-100 hh_admin1 = 2 | R38: =1 -> 1 | S38: =Q38*R38 -> 0 | V38: yes
A39: =A38+1 -> 5 | B39: quotareached | C39: quotareached | D39: [OPERATOR: DO NOT READ. ANSWER QUESTION BELOW.] THIS RESPONDENT REPORTED THEY LIVE IN: #ADM1# #ADM2# 1)THE GOAL FOR THIS LOCATION HAS BEEN ACHIEVED - END SURVEY 2)THE GOAL FOR THIS LOCATION IS OPEN - CONTINUE SURVEY | E39: =LEN(D39) -> 218 | F39: [OPÉRATEUR/OPÉRATRICE: NE PAS LIRE. RÉPONDRE À LA QUESTION EN DESSOUS.] CE RÉPONDANT DIT VIVRE À: #ADM1# #ADM2# 1)L'OBJECTIF DANS CETTE ZONE A ÉTÉ ATTEINT - FIN DU SONDAGE 2)L'OBJECTIF DANS CETTE ZONE N'EST PAS ENCORE ATTEINT - CONTINUER LE SONDAGE | G39: =LEN(F39) -> 251 | H39: Single Choice | I39: NA | J39: NA | K39: Form Type - Buttons | L39: 1 = End Poll Quota Reached 2 = hh_agricactivity | M39: If the quota has not been reached, continue the questionnaire. If it has, end of survey. | O39: resp_agree = 1 resp_age = 18-100 | Q39: 2.28425 | R39: =1 -> 1 | S39: =Q39*R39 -> 2.28425 | V39: no
A40: =A39+1 -> 6 | B40: hh_agricactivity | C40: hh_agricactivity | D40: Has anybody in your household been producing crops or livestock for household consumption or for sale in the past 12 months, including household members currently away for transhumance? [OPERATOR: SINGLE RESPONSE. THIS IS THE MAIN SCREENING QUESTION. THE RESPONDENT WILL HAVE TO ANSWER. DON'T FORGET TO PROBE ABOUT TRANSHUMANCE.] [HINT: HOUSEHOLD CONSISTS OF ALL MEMBERS LIVING TOGETHER, SHARING RESOURCES & EATING FROM THE SAME POT.] 1)Yes - crop production 2)Yes - livestock production 3)Yes - both crop and livestock production 4)No 5)DON'T KNOW 6)REFUSED | E40: =LEN(D40) -> 563 | F40: Est-ce que quelqu'un dans votre ménage a produit des cultures ou du bétail pour la consommation du ménage ou pour la vente au cours des 12 derniers mois, y compris des membres du ménage actuellement partis pour la transhumance ? [OPÉRATEUR/OPÉRATRICE: RÉPONSE UNIQUE. IL S'AGIT DE LA PRINCIPALE QUESTION DE SÉLECTION. LA PERSONNE INTERROGÉE DOIT Y RÉPONDRE. NE PAS OUBLIER DE MENTIONNER LA TRANSHUMANCE]. [CONSEIL: LE MÉNAGE EST COMPOSÉ DE TOUTES LES PERSONNES VIVANT ENSEMBLE, PARTAGEANT LEURS RESSOURCES ET MANGEANT DANS UNE MARMITE COMMUNE.] 1)Oui - production végétale 2)Oui - production animale 3)Oui - production végétale et animale 4)Non 5)NE SAIT PAS 6)REFUSÉ | G40: =LEN(F40) -> 671 | H40: Single Choice | I40: NA | J40: NA | K40: Form Type - Buttons | L40: 1-4 = hh_gender 5-6 = Ineligible | M40: if hh_agricactivity = 1-4, go to hh_gender. Otherwise, the respondent is ineligible. | O40: resp_agree = 1 resp_age = 18-100 quotareached = 2 | Q40: 31.372377 | R40: =1 -> 1 | S40: =Q40*R40 -> 31.372377 | V40: yes
R41: =1 -> 1 | S41: =Q41*R41 -> 0
A42: B. GENERAL HOUSEHOLD INFORMATION
R43: =1 -> 1 | S43: =Q43*R43 -> 0
A44: =A40+1 -> 7 | B44: hh_gender | C44: hh_gender | D44: Is the head of your household male or female? [OPERATOR: SINGLE RESPONSE.] 1)Male 2)Female 3)DON'T KNOW 4)REFUSED | E44: =LEN(D44) -> 116 | F44: Le chef de votre ménage est-il un homme ou une femme ? [OPÉRATEUR/OPÉRATRICE: RÉPONSE UNIQUE.] 1)Homme 2)Femme 3)NE SAIT PAS 4)REFUSÉ | G44: =LEN(F44) -> 135 | H44: Single Choice | I44: NA | J44: NA | K44: Form Type - Buttons | L44: 1-4 = hh_education | M44: if hh_gender = 1-4, go to hh_education. | O44: resp_age = 18-100 hh_agricactivity = 1 | 2 | 3 | 4 quotareached = 2 | Q44: 10.085732 | R44: =1 -> 1 | S44: =Q44*R44 -> 10.085732 | V44: yes
R45: =1 -> 1 | S45: =Q45*R45 -> 0
A46: =A44+1 -> 8 | B46: hh_education | C46: hh_education | D46: What is the educational level attained by the head of household? [OPERATOR: SINGLE RESPONSE.] 1)None or did not complete primary school 2)Completed primary school 3)Completed secondary school 4)Completed higher education [University / College] degree 5)Religious or informal education only 6)DON'T KNOW 7)REFUSED | E46: =LEN(D46) -> 314 | F46: Quel est le niveau d'éducation du chef de votre ménage ? [OPÉRATEUR/OPÉRATRICE: RÉPONSE UNIQUE.] 1)Aucun ou n'a pas terminé l'école primaire 2)A terminé l'école primaire 3)A terminé l'école secondaire 4)Diplôme de l'enseignement supérieur [Université] 5)Enseignement religieux ou informel uniquement 6)NE SAIT PAS 7)REFUSÉ | G46: =LEN(F46) -> 324 | H46: Single Choice | I46: NA | J46: NA | K46: Form Type - Buttons | L46: 1-7 = hh_wealth | M46: if hh_education = 1-7, go to hh_wealth. | O46: resp_age = 18-100 hh_agricactivity = 1 | 2 | 3 | 4 quotareached = 2 | Q46: 12.894034 | R46: =1 -> 1 | S46: =Q46*R46 -> 12.894034 | V46: yes | Z46: Changed answer option 5
R47: =1 -> 1 | S47: =Q47*R47 -> 0
A48: 10 | B48: hh_wealth_water | C48: hh_wealth_water | D48: Where does the water that you drink at home come from? [OPERATOR: SINGLE CHOICE.] 1)Private tap from piped water 2)Public tap 3)Protected well 4)Bottled water 5)Other safe source 6)River 7)Unprotected well 8)Spring water 9)Canal or other surface water 10)Other unsafe source 11)DON'T KNOW 12)REFUSED | E48: =LEN(D48) -> 301 | F48: Où procurez-vous habituellement l'eau l'eau que vous buvez dans votre foyer ? [OPÉRATEUR/OPÉRATRICE: RÉPONSE UNIQUE.] 1)Robinet privé avec eau courante 2)Robinet public 3)Puits protégé 4)Eau en bouteille 5)Autre source sûre 6)Rivière 7)Puits non protégé 8)Eau de source 9)Canal ou autre eau de surface 10)Autre source non sûre 11)NE SAIT PAS 12)REFUSÉ | G48: =LEN(F48) -> 353 | H48: Single Choice | I48: NA | J48: NA | K48: Form Type - Buttons | L48: 1-12 = [income_main OR other optional question] | M48: For any response, go to [income_main OR other optional question] | O48: resp_age = 18-100 hh_agricactivity = 1 | 2 | 3 | 4 quotareached = 2 | P48: Choose one of three of the wealth indicators (delete those that you do not want to use). If none of these indicators work in the context of your country, other wealth proxies are proposed in the optional questions below. Remember that baseline data will be necessary, and the variable should be defined properly in the "weight_input_table". Choisir un des trois indicateurs de richesse (supprimer ceux qui ne sont pas utilisés). Si aucun de ces indicateurs n'est adapté au contexte de votre pays, se reporter aux autres indicateurs de richesse proposés dans les questions facultatives ci-dessous. Ne pas oublier que des données de base seront nécessaires, et que la variable doit être définie correctement dans la "weight_input_table". | Q48: 15.265829 | R48: =1 -> 1 | S48: =Q48*R48 -> 15.265829 | V48: yes | Z48: Change in question text
A49: 10 | B49: hh_wealth_toilet | C49: hh_wealth_toilet | D49: Where do household members typically go to use a toilet? [OPERATOR: SINGLE CHOICE.] 1)Flush latrine [toilet with water] 2)Traditional pit latrine [no water] 3)Open pit [whole in the ground for excrement without water, roof or wall] 4)Communal latrine [with or without water] 5)None – bush 6)DON'T KNOW 7)REFUSED | E49: =LEN(D49) -> 313 | F49: Où vous rendez-vous généralement, vous et les membres de votre ménage, pour aller aux toilettes ? [OPÉRATEUR/OPÉRATRICE: RÉPONSE UNIQUE.] 1)Latrines à chasse d'eau [toilettes avec eau] 2)Latrines traditionnelles à fosse [sans eau] 3)Fosse ouverte [trou dans le sol pour les excréments, sans eau, toit ni mur] 4)Latrines communautaires [avec ou sans eau] 5)Aucune – brousse 6)NE SAIT PAS 7)REFUSÉ | G49: =LEN(F49) -> 397 | H49: Single Choice | I49: NA | J49: NA | K49: Form Type - Buttons | L49: 1-7 = [income_main OR other optional question] | M49: For any response, go to [income_main OR other optional question] | O49: resp_age = 18-100 hh_agricactivity = 1 | 2 | 3 | 4 quotareached = 2 | Q49: 15.123718 | R49: =1 -> 1 | S49: =Q49*R49 -> 15.123718 | V49: yes
A50: 10 | B50: hh_wealth_light | C50: hh_wealth_light | D50: What is the main source of light in your dwelling? [OPERATOR: SINGLE RESPONSE.] 1)Electricity [from generator or electrical grid or solar panel] 2)Candle 3)Petrol lamp 4)Lamp with batteries 5)Other [no electric supply to the house] 6)DON'T KNOW 7)REFUSED | E50: =LEN(D50) -> 256 | F50: Quelle est la principale source de lumière de votre logement ? [OPÉRATEUR/OPÉRATRICE: RÉPONSE UNIQUE.] 1)Électricité [à partir d'un générateur, du réseau électrique ou de panneaux solaires] 2)Bougie 3)Lampe à pétrole 4)Lampe à piles 5)Autre [pas d'alimentation électrique dans la maison] 6)NE SAIT PAS 7)REFUSÉ | G50: =LEN(F50) -> 312 | H50: Single Choice | I50: NA | J50: NA | K50: Form Type - Buttons | L50: 1-7 = [income_main OR other optional question] | M50: For any response, go to [income_main OR other optional question] | O50: resp_age = 18-100 hh_agricactivity = 1 | 2 | 3 | 4 quotareached = 2 | Q50: 13.760139 | R50: =1 -> 1 | S50: =Q50*R50 -> 13.760139 | V50: yes | Z50: Change in question text + answer option 1
R51: =1 -> 1 | S51: =Q51*R51 -> 0
A52: =A50+1 -> 11 | B52: hh_residencetype | C52: hh_residencetype | D52: Which in the following types of residence best describes your residence? [OPERATOR: READ OUT THE OPTIONS. SINGLE RESPONSE.] [HINT: IF RESPONDENT IS ONLY AWAY FROM THE HOUSEHOLD FOR SHORT SEASONAL WORK (<6 MONTHS) OR TRANSHUMANCE, MAKE SURE TO REFER TO THEIR HOUSEHOLD BACK WHERE THEY TYPICALLY ARE LOCATED.] 1)Permanent Resident - you have been living in your village / town for longer than two years and this is what you consider your habitual residence 2)Recent migrant not forcefully displaced - you have been living in your current place of residence for less than two years and you moved there voluntarily for work / family or other reasons that are not related to conflict or natural disaster 3)Returnee - you have only come back to this residence in the last two years after having been forced to move to another location having fled conflict or natural disaster [if return was over 2 years ago the respondent is considered a permanent resident] 4)Internally displaced person [IDP] - you were forced to flee your village or town because of conflict or natural disaster and you are now an internally displaced person in your current place of residence 5)Refugee - you were forced to flee your country because of conflict or natural disaster and you are now a refugee in your current place of residence 6)DON'T KNOW 7)REFUSED | E52: =LEN(D52) -> 1333 | F52: Parmi les propositions suivantes, laquelle décrit le mieux votre résidence ? [OPÉRATEUR/OPÉRATRICE: LIRE LES OPTIONS, RÉPONSE UNIQUE]. [CONSEIL: SI LA PERSONNE INTERROGÉE N'EST ÉLOIGNÉE DU FOYER QUE POUR UN TRAVAIL SAISONNIER DE COURTE DURÉE (<6 MOIS) OU POUR LA TRANSHUMANCE, FAIRE RÉFÉRENCE AU FOYER DE RETOUR OÙ ELLE VIT HABITUELLEMENT]. 1)Résident permanent - vous vivez dans votre village/ville depuis plus de deux ans et vous le/la considérez comme votre résidence habituelle 2)Migrant récent non déplacé de force - vous vivez dans votre lieu de résidence actuel depuis moins de deux ans et vous vous y êtes déplacé volontairement pour des raisons professionnelles, familiales ou autres qui ne sont pas liées à un conflit ou à une catastrophe naturelle 3)Personne rapatriée - vous êtes revenu dans ce lieu de résidence au cours des deux dernières années après avoir été contraint de vous déplacer pour fuir un conflit ou une catastrophe naturelle [si le retour a eu lieu il y a plus de deux ans, le répondant est considéré comme un résident permanent] 4)Personne déplacée à l'intérieur de son pays - vous avez été forcé de fuir votre village ou votre ville en raison d'un conflit ou d'une catastrophe naturelle et vous êtes une personne déplacée à l'intérieur de son propre pays dans votre lieu de résidence actuel 5)Réfugié - vous avez été forcé de fuir votre pays en raison d'un conflit ou d'une catastrophe naturelle et vous êtes un réfugié dans votre lieu de résidence actuel 6)NE SAIT PAS 7)REFUSÉ | G52: =LEN(F52) -> 1511 | H52: Single Choice | I52: NA | J52: NA | K52: Form Type - Buttons | L52: 1-8 = hh_size | O52: resp_age = 18-100 hh_agricactivity = 1 | 2 | 3 | 4 quotareached = 2 | Q52: 30.646189 | R52: =1 -> 1 | S52: =Q52*R52 -> 30.646189 | V52: no
A53: =A52+1 -> 12 | B53: hh_size | C53: hh_size | D53: How many people are part of the household? [OPERATOR: RECORD NUMBER OF MEMBERS IN HOUSEHOLD. ENTER 88 FOR DON'T KNOW & 99 FOR REFUSED.] | E53: =LEN(D53) -> 136 | F53: De combien de personnes est composé votre ménage ? [OPÉRATEUR/OPÉRATRICE: ENREGISTRER LE NOMBRE DE MEMBRES DU MÉNAGE. ENTRER 88 POUR «NE SAIT PAS» ET 99 POUR «REFUSÉ».] | G53: =LEN(F53) -> 169 | H53: Range | I53: NA | J53: NA | K53: Form Type - TextBox | L53: 1-50 = hh_asset_prod 88-88 = hh_asset_prod 99-99 = hh_asset_prod | O53: resp_age = 18-100 hh_agricactivity = 1 | 2 | 3 | 4 quotareached = 2 | Q53: 15.211848 | R53: =1 -> 1 | S53: =Q53*R53 -> 15.211848 | V53: no
A54: =A53+1 -> 13 | B54: hh_asset_prod | C54: hh_asset_prod_ 1) hh_asset_prod_taxi 2) hh_asset_prod_truck 3) hh_asset_prod_farmmach 4) hh_asset_prod_sewing 5) hh_asset_prod_other 6) hh_asset_prod_none 7) hh_asset_prod_dk 8) hh_asset_prod_ref | D54: Does your household own any of the following production assets? [OPERATOR: MULTIPLE RESPONSES.] 1)Taxi 2)Truck 3)Farm machinery (tractor, other) 4)Sewing machine 5)Other productive machines 6)No productive machines 7)DON'T KNOW 8)REFUSED | E54: =LEN(D54) -> 240 | F54: Votre ménage possède-t-il l'un des actifs productifs suivants ? [OPÉRATEUR/OPÉRATRICE: PLUSIEURS RÉPONSE POSSIBLES.] 1)Taxi 2)Camion 3)Machine agricole (tracteur, autre) 4)Machine à coudre 5)Autre machine productive 6)Pas de machine productive 7)NE SAIT PAS 8)REFUSÉ | G54: =LEN(F54) -> 270 | H54: Select All That Apply | I54: NA | J54: NA | K54: Form Type - Checklist | L54: 1-8 = hh_asset_transp | O54: resp_age = 18-100 hh_agricactivity = 1 | 2 | 3 | 4 quotareached = 2 | P54: This wealth indicator may be useful to Identify poor households in middle income countries. It could be interesting for F2F surveys, to be used as baseline reference for follow-up surveys. Cet indicateur de richesse peut permettre d'identifier les ménages pauvres dans les pays à revenu intermédiaire. Il peut être utile pour les enquêtes en face à face et servir de référence de base pour les enquêtes de suivi. | Q54: 17 | R54: =1 -> 1 | S54: =Q54*R54 -> 17 | V54: no | Z54: new question
A55: =A54+1 -> 14 | B55: hh_asset_transp | C55: hh_asset_transp_ 1) hh_asset_transp_bici 2) hh_asset_transp_motorbike 3) hh_asset_transp_car 4) hh_asset_transp_van 5) hh_asset_transp_other 6) hh_asset_transp_none 7) hh_asset_transp_dk 8) hh_asset_transp_ref | D55: Does you or anyone in your household own any of the following transportation assets? [OPERATOR: MULTIPLE RESPONSES.] 1)Bicycle 2)Motorbike or auto rickshaw 3)Car 4)Van or small truck 5)Other motor vehicle 6)None of the above 7)DON'T KNOW 8)REFUSED | E55: =LEN(D55) -> 250 | F55: Est-ce que vous ou un membre de votre ménage possède un des véhicules suivants ? [OPÉRATEUR/OPÉRATRICE: PLUSIEURS RÉPONSE POSSIBLES.] 1)Bicyclette 2)Moto ou pousse-pousse 3)Voiture 4)Fourgonnette ou petit camion 5)Autre véhicule motorisé 6)Aucune des propositions citées 7)NE SAIT PAS 8)REFUSÉ | G55: =LEN(F55) -> 300 | H55: Select All That Apply | I55: NA | J55: NA | K55: . | L55: 1-8 = hh_maritalstat | O55: resp_age = 18-100 hh_agricactivity = 1 | 2 | 3 | 4 quotareached = 2 | P55: This wealth indicator may be useful to Identify poor households in middle income countries. It could be interesting for F2F surveys, to be used as baseline reference for follow-up surveys. Cet indicateur de richesse peut permettre d'identifier les ménages pauvres dans les pays à revenu intermédiaire. Il peut être utile pour les enquêtes en face à face et servir de référence de base pour les enquêtes de suivi. | Q55: 17 | R55: =1 -> 1 | S55: =Q55*R55 -> 17 | V55: no | Z55: new question
A56: =A55+1 -> 15 | B56: hh_maritalstat | C56: hh_maritalstat | D56: What is the head of household’s current marital status? [OPERATOR: SINGLE RESPONSE.] 1)Single / never married 2)Married 3)Separated 4)Divorced 5)Widowed 6)DON’T KNOW 7)REFUSED | E56: =LEN(D56) -> 180 | F56: Quel est le status marital actuel du chef de ménage ? [OPÉRATEUR/OPÉRATRICE: RÉPONSE UNIQUE.] 1)Célibataire / jamais marié 2)Marié(e) 3)Séparé(e) 4)Divorcé(e) 5)Veuf ou veuve 6)NE SAIT PAS 7)REFUSÉ | G56: =LEN(F56) -> 200 | H56: Single Choice | I56: NA | J56: NA | K56: Form Type - Buttons | L56: 1-7 = hh_age | O56: resp_age = 18-100 hh_agricactivity = 1 | 2 | 3 | 4 quotareached = 2 | Q56: 17 | R56: =1 -> 1 | S56: =Q56*R56 -> 17 | V56: no
A57: =A56+1 -> 16 | B57: hh_age | C57: hh_age | D57: How old is the head of household? [OPERATOR: SINGLE RESPONSE.] 1)Under 18 2)18 to 40 3)41 to 65 4)Over 65 5)DON'T KNOW 6)REFUSED | E57: =LEN(D57) -> 133 | F57: Quel âge du chef de famille ? [OPÉRATEUR/OPÉRATRICE: RÉPONSE UNIQUE.] 1)Moins de 18 ans 2)18 à 40 ans 3)41 à 65 ans 4)Plus de 65 ans 5)NE SAIT PAS 6)REFUSÉ | G57: =LEN(F57) -> 158 | H57: Single Choice | I57: NA | J57: NA | K57: Form Type - Buttons | L57: 1-6 = income_main | O57: resp_age = 18-100 hh_agricactivity = 1 | 2 | 3 | 4 quotareached = 2 | Q57: 8.2288065 | R57: =1 -> 1 | S57: =Q57*R57 -> 8.2288065 | V57: no
A58: C. INCOME SOURCES, LIVELIHOOD AND SHOCKS
R59: =1 -> 1 | S59: =Q59*R59 -> 0
A60: =A57+1 -> 17 | B60: income_main | C60: income_main | D60: What has been your household's main source of income in the past 3 months? [OPERATOR: SINGLE RESPONSE. REFUSED OPTION SHOULD BE AVOIDED AS MUCH AS POSSIBLE.] 1)Production and sale of staple crops 2)Production and sale of vegetable or fruit 3)Production and sale of cashcrops 4)Production and sale of livestock and livestock products 5)Production and sale of fish 6)Collection and sale of forestry or bush products 7)Informal agricultural trade EXCLUDING producers 8)Formal agricultural trade EXCLUDING producers 9)Daily wage on farms and other casual employment in agricultural sector 10)Stable employment in agricultural sector 11)Non-agricultural self-employed or liberal profession / doctor / architect / lawyer / including restaurant 12)Off-farm daily wages and other non-agricultural casual employment 13)Stable employment in non-agricultural sector 14)Public employment 15)Income not derived from work / Charity 16)Income not derived from work / Welfare transfer, pension, humanitarian aid 17)Income not derived from work / Remittances 18)Income not derived from work / Income from other rents 19)No income source in the last 3 months and used exclusively savings 20)No income source in the last 3 months and used exclusively debt 21)REFUSED | E60: =LEN(D60) -> 1260 | F60: Quelle a été la principale source de revenu de votre ménage au cours des trois derniers mois ? [OPÉRATEUR/OPÉRATRICE: RÉPONSE UNIQUE. L'OPTION «REFUSÉ» DOIT ÊTRE, AUTANT QUE POSSIBLE, ÉVITÉE.] 1)Production et vente de cultures d'aliments de base 2)Production et vente de légumes ou de fruits 3)Production et vente de cultures de rente 4)Production et vente de bétail et de produits animaux 5)Production et vente de poisson 6)Collecte et vente de produits forestiers ou de brousse 7)Commerce agricole informel EXCLUANT les producteurs 8)Commerce agricole formel EXCLUANT les producteurs 9)Salaire journalier dans une exploitation et autres emplois occasionnels dans le secteur agricole 10)Emploi stable dans le secteur agricole 11)Indépendant non-agricole ou profession libérale / médecin / architecte / avocat / y compris restaurant 12)Salaire journalier et autres emplois occasionnels non agricoles 13)Emploi stable dans le secteur non-agricole 14)Emploi public 15)Revenu non tiré du travail / Charité 16)Revenu non tiré du travail / Transferts sociaux, pension, aide humanitaire 17)Revenu non tiré du travail / Envoi de fonds des migrants 18)Revenu non tiré du travail / Revenu d'autres loyers 19)Aucune source de revenu au cours des trois derniers mois et utilisation exclusive de l'épargne 20)Aucune source de revenu au cours des trois derniers mois et création de dettes 21)REFUSÉ | G60: =LEN(F60) -> 1391 | H60: Single Choice | I60: NA | J60: NA | K60: Form Type - Buttons set demographic | L60: 1-3 = income_main_cropcheck 4 = income_main_lscheck 5 = income_main_fishcheck 6-18 = income_main_comp OR optional question 19-21 = shock | M60: if options #1-3 selected go to income_main_cropcheck if options #4 selected go to income_main_lscheck if options #5 selected go to income_main_fishcheck if options #6-18 selected, go to [income_main_comp OR income_main_amount OR income_main_gender] if options #19-21 selected, go to shock | O60: resp_age = 18-100 hh_agricactivity = 1 | 2 | 3 | 4 quotareached = 2 | Q60: 36.928734 | R60: =1 -> 1 | S60: =Q60*R60 -> 36.928734 | V60: yes | Z60: Change in skip pattern (col J) Change in answer option #1
A61: 18 | B61: income_main_cropcheck | C61: income_main_cropcheck | D61: Are the crops that you sell produced by you or anyone in your household? [OPERATOR: SINGLE RESPONSE.] 1)YES 2)NO 3)DON'T KNOW 4)REFUSED | E61: =LEN(D61) -> 138 | F61: Les cultures que vous vendez sont-elles produites par vous ou par un des membres de votre ménage ? [OPÉRATEUR/OPÉRATRICE: RÉPONSE UNIQUE.] 1)Oui 2)Non 3)NE SAIT PAS 4)REFUSÉ | G61: =LEN(F61) -> 175 | H61: Single Choice | I61: NA | J61: NA | K61: Form Type - Buttons | L61: 1-4 = income_main_comp OR optional question | M61: if options #1-4, go to [income_main_comp OR income_main_amount OR income_main_gender] | O61: resp_age = 18-100 hh_agricactivity = 1 | 2 | 3 | 4 quotareached = 2 income_main = 1 | 2 | 3 | R61: =1 -> 1 | S61: =Q61*R61 -> 0 | V61: yes | Z61: New question
A62: 18 | B62: income_main_lscheck | C62: income_main_lscheck | D62: Are the livestock and livestock products that you sell produced by you or anyone in your household? [OPERATOR: SINGLE RESPONSE.] 1)YES 2)NO 3)DON'T KNOW 4)REFUSED | E62: =LEN(D62) -> 165 | F62: Le bétail et les produits du bétail que vous vendez sont-ils produits par vous par un des membres de votre ménage ? [OPÉRATEUR/OPÉRATRICE: RÉPONSE UNIQUE.] 1)Oui 2)Non 3)NE SAIT PAS 4)REFUSÉ | G62: =LEN(F62) -> 194 | H62: Single Choice | I62: NA | J62: NA | K62: Form Type - Buttons | L62: 1-4 = income_main_comp OR optional question | M62: if options #1-4, go to [income_main_comp OR income_main_amount OR income_main_gender] | O62: resp_age = 18-100 hh_agricactivity = 1 | 2 | 3 | 4 quotareached = 2 income_main = 4 | R62: =1 -> 1 | S62: =Q62*R62 -> 0 | V62: yes | Z62: New question
A63: 18 | B63: income_main_fishcheck | C63: income_main_fishcheck | D63: Are the fish products that you sell produced by you or anyone in your household? [OPERATOR: SINGLE RESPONSE.] 1)YES 2)NO 3)DON'T KNOW 4)REFUSED | E63: =LEN(D63) -> 146 | F63: Les produits de la pêche que vous vendez sont-ils produits par vous ou par un membre de votre ménage ? [OPÉRATEUR/OPÉRATRICE: RÉPONSE UNIQUE.] 1)Oui 2)Non 3)NE SAIT PAS 4)REFUSÉ | G63: =LEN(F63) -> 180 | H63: Single Choice | I63: NA | J63: NA | K63: Form Type - Buttons | L63: 1-4 = income_main_comp OR optional question | M63: if options #1-4, go to [income_main_comp OR income_main_amount OR income_main_gender] | O63: resp_age = 18-100 hh_agricactivity = 1 | 2 | 3 | 4 quotareached = 2 income_main = 5 | R63: =1 -> 1 | S63: =Q63*R63 -> 0 | V63: yes | Z63: New question
R64: =1 -> 1 | S64: =Q64*R64 -> 0
A65: 18 | B65: income_main_gender | C65: income_main_gender | D65: Is the person earning from #income_main# male or female? [OPERATOR: SINGLE RESPONSE.] 1)Male 2)Female 3)DON'T KNOW 4)REFUSED | E65: =LEN(D65) -> 128 | F65: La personne qui perçoit #income_main# est-elle un homme ou une femme ? [OPÉRATEUR/OPÉRATRICE: RÉPONSE UNIQUE.] 1)Homme 2)Femme 3)NE SAIT PAS 4)REFUSÉ | G65: =LEN(F65) -> 151 | H65: Single Choice | I65: NA | J65: NA | K65: Form Type - Buttons | L65: 1-4 = income_main_comp OR optional question | M65: if options #1-4, go to [income_main_comp OR income_main_amount] | O65: resp_age = 18-100 hh_agricactivity = 1 | 2 | 3 | 4 quotareached = 2 income_main = 1-18 | Q65: 17 | R65: =1 -> 1 | S65: =Q65*R65 -> 17 | V65: no | Z65: New question
A66: 19 | B66: income_main_amount | C66: income_main_amount | D66: How much was earned (in $currency$) from your main income source, #income_main#, in the past 3 months ? [OPERATOR: DOUBLE CHECK FOR OUTLIERS & MAKE SURE THE INFORMATION IS RECORDED IN THE CORRECT CURRENCY. ENTER 8888888 FOR DON'T KNOW AND 9999999 FOR REFUSED.] | E66: =LEN(D66) -> 261 | F66: Quelle somme (en $currency$) a rapporté votre principale source de revenu, #income_main#, au cours des trois derniers mois ? [OPÉRATEUR/OPÉRATRICE: VÉRIFIER QUE LA RÉPONSE N’EST PAS INCOHÉRENTE ET QU'ELLE EST ENREGISTRÉE DANS LA BONNE DEVISE. SAISIR 8888888 POUR «NE SAIT PAS» ET 9999999 POUR «REFUSÉ».] | G66: =LEN(F66) -> 304 | H66: Range | I66: NA | J66: NA | K66: Form Type - TextBox | L66: $MIN AMOUNT$ - $THRESHOLD$ = income_main_comp $THRESHOLD$ - $MAX AMOUNT$ = income_main_amount_conf 8888888-8888888 = income_main_comp 9999999-9999999 = income_main_comp | M66: If the income amount is over the threshold set in "Additional information", the respondent will be asked to confirm with income_main_amount_conf. Otherwise, go to income_main_comp. | O66: resp_age = 18-100 hh_agricactivity = 1 | 2 | 3 | 4 quotareached = 2 income_main = 1-18 | P66: We recommend using this pair of questions together. | Q66: 40.047318 | R66: =1 -> 1 | S66: =Q66*R66 -> 40.047318 | V66: no | Z66: Change in question text (col D)
A67: 19 | B67: income_main_amount_conf | C67: income_main_amount_conf | D67: Can you confirm the amount of income you just stated is correct? [OPERATOR: IF THE AMOUNT EARNED FROM THIS INCOME SOURCE OVER THE PAST 3 MONTH IS INDEED OVER $THRESHOLD$, CLICK ON CONTINUE. OTHERWISE, GO BACK AND CHANGE THE AMOUNT ENTERED.] 1)CONTINUE | E67: =LEN(D67) -> 253 | F67: Pouvez-vous confirmer que le montant que vous venez de déclarer est correct ? [OPÉRATEUR/OPÉRATRICE: SI LE MONTANT ISSU DE CETTE SOURCE DE REVENU AU COURS DES TROIS DERNIERS MOIS EST BIEN SUPÉRIEUR AU $THRESHOLD$, CLIQUER SUR CONTINUER. SINON, REVENIR EN ARRIÈRE ET MODIFIER LE MONTANT SAISI.] 1)CONTINUER | G67: =LEN(F67) -> 307 | H67: Single Choice | I67: NA | J67: NA | K67: Form Type - Buttons | L67: 1 = income_main_comp | M67: if income_main_amount_conf = 1, go to income_main_comp | O67: NA | Q67: 3.687011 | R67: =1 -> 1 | S67: =Q67*R67 -> 3.687011 | V67: no
R68: =1 -> 1 | S68: =Q68*R68 -> 0
A69: =A67+1 -> 20 | B69: income_main_comp | C69: income_main_comp | D69: Has your household's income from #income_main# changed in the last 3 months compared to the same period in $reference year$? [OPERATOR: SINGLE RESPONSE.] 1)A lot more [increased by more than 50%] 2)Slightly more 3)Same 4)Slightly less 5)A lot less [less than half as much] 6)DON'T KNOW 7)REFUSED | E69: =LEN(D69) -> 298 | F69: Le revenu de votre ménage provenant de #income_main# aa-t-il changé au cours des trois derniers mois par rapport à la même période de $reference year FR$ ? [OPÉRATEUR/OPÉRATRICE: RÉPONSE UNIQUE.] 1)Très supérieur [augmentation de plus de 50%] 2)Légèrement supérieur 3)Identique 5)Légèrement inférieur 5)Très inférieur [moins de la moitié] 6)NE SAIT PAS 7)REFUSÉ | G69: =LEN(F69) -> 364 | H69: Single Choice | I69: NA | J69: NA | K69: Form Type - Buttons | L69: 1-7= income_sec | M69: if income_main_comp = 1-7, go to income_sec | O69: resp_age = 18-100 hh_agricactivity = 1 | 2 | 3 | 4 quotareached = 2 income_main = 1-18 | Q69: 27.242167 | R69: =1 -> 1 | S69: =Q69*R69 -> 27.242167 | V69: yes | Z69: Change in options #2,4 + question formulation (col D) + hint
R70: =1 -> 1 | S70: =Q70*R70 -> 0
A71: =A69+1 -> 21 | B71: income_sec | C71: income_sec | D71: What has been your household's second most important source of income in the past 3 months? [OPERATOR: SINGLE RESPONSE. DON'T KNOW AND REFUSED OPTIONS SHOULD BE AVOIDED AS MUCH AS POSSIBLE.] 1)Production and sale of staple crops 2)Production and sale of vegetable or fruit 3)Production and sale of cashcrops 4)Production and sale of livestock and livestock products 5)Production and sale of fish 6)Collection and sale of forestry or bush products 7)Informal agricultural trade EXCLUDING producers 8)Formal agricultural trade EXCLUDING producers 9)Daily wage on farms and other casual employment in agricultural sector 10)Stable employment in agricultural sector 11)Non-agricultural self-employed or liberal profession / doctor / architect / lawyer / including restaurant 12)Off-farm daily wages and other non-agricultural casual employment 13)Stable employment in non-agricultural sector 14)Public employment 15)Income not derived from work / Charity 16)Income not derived from work / Welfare transfer, pension, humanitarian aid 17)Income not derived from work / Remittances 18)Income not derived from work / Income from other rents 19)No second most important source of income 20)DON'T KNOW 21)REFUSED | E71: =LEN(D71) -> 1213 | F71: Quelle a été la deuxième source principale de revenu de votre ménage au cours des trois derniers mois ? [OPÉRATEUR/OPÉRATRICE: RÉPONSE UNIQUE. LES OPTIONS «NE SAIT PAS» ET «REFUSÉ» DOIVENT ÊTRE ÉVITÉES AUTANT QUE POSSIBLE]. 1)Production et vente de cultures d'aliments de base 2)Production et vente de légumes ou de fruits 3)Production et vente de cultures de rente 4)Production et vente de bétail et de produits du bétail 5)Production et vente de poisson 6)Collecte et vente de produits forestiers ou de brousse 7)Commerce agricole informel EXCLUANT les producteurs 8)Commerce agricole formel EXCLUANT les producteurs 9)Salaire journalier dans une exploitation et autres emplois occasionnels dans le secteur agricole 10)Emploi stable dans le secteur agricole 11)Indépendant non-agricole ou profession libérale / médecin / architecte / avocat / y compris restaurant 12)Salaire journalier et autres emplois occasionnels non agricoles 13)Emploi stable dans le secteur non-agricole 14)Emploi public 15)Revenu non tiré du travail / Charité 16)Revenu non tiré du travail / Transferts sociaux, pension, aide humanitaire 17)Revenu non tiré du travail / Envoi de fonds des migrants 18)Revenu non tiré du travail / Revenu d'autres loyers 19)Pas de deuxième source principale de revenu 20)NE SAIT PAS 21)REFUSÉ | G71: =LEN(F71) -> 1307 | H71: Single Choice | I71: NA | J71: NA | K71: Form Type - Buttons Add all options manually exclude selected "income_main" set demographic | L71: 1-3 = income_sec_cropcheck 4 = income_sec_lscheck 5 = income_sec_fishcheck 6-18 = income_sec_comp OR optional question 19-21 = shock | M71: if options #1-3 selected go to income_sec_cropcheck if options #4 selected go to income_sec_lscheck if options #5 selected go to income_sec_fishcheck if options #6-18 selected, go to [income_sec_comp OR income_sec_amount OR income_sec_gender] if options #19-21 selected, go to shock | O71: resp_age = 18-100 hh_agricactivity = 1 | 2 | 3 | 4 quotareached = 2 income_main = 1-18 | Q71: 25.308004 | R71: =1 -> 1 | S71: =Q71*R71 -> 25.308004 | V71: yes | Z71: Change in skip pattern (col J) Change in answer option #1
A72: 18 | B72: income_sec_cropcheck | C72: income_sec_cropcheck | D72: Are the crops that you sell produced by you or anyone in your household? [OPERATOR: SINGLE RESPONSE.] 1)YES 2)NO 3)DON'T KNOW 4)REFUSED | E72: =LEN(D72) -> 138 | F72: Les cultures que vous vendez sont-elles produites par vous ou par un des membres de votre ménage ? [OPÉRATEUR/OPÉRATRICE: RÉPONSE UNIQUE.] 1)Oui 2)Non 3)NE SAIT PAS 4)REFUSÉ | G72: =LEN(F72) -> 175 | H72: Single Choice | I72: NA | J72: NA | K72: Form Type - Buttons | L72: 1-4 = income_sec_comp OR optional question | M72: if options #1-4, go to [income_sec_comp OR income_sec_amount OR income_sec_gender] | O72: resp_age = 18-100 hh_agricactivity = 1 | 2 | 3 | 4 quotareached = 2 income_sec = 1 | 2 | 3 | R72: =1 -> 1 | S72: =Q72*R72 -> 0 | V72: yes | Z72: New question
A73: 18 | B73: income_sec_lscheck | C73: income_sec_lscheck | D73: Are the livestock and livestock products that you sell produced by you or anyone in your household? [OPERATOR: SINGLE RESPONSE.] 1)YES 2)NO 3)DON'T KNOW 4)REFUSED | E73: =LEN(D73) -> 165 | F73: Le bétail et les produits du bétail que vous vendez sont-ils produits par vous par un des membres de votre ménage ? [OPÉRATEUR/OPÉRATRICE: RÉPONSE UNIQUE.] 1)Oui 2)Non 3)NE SAIT PAS 4)REFUSÉ | G73: =LEN(F73) -> 194 | H73: Single Choice | I73: NA | J73: NA | K73: Form Type - Buttons | L73: 1-4 = income_sec_comp OR optional question | M73: if options #1-4, go to [income_sec_comp OR income_sec_amount OR income_sec_gender] | O73: resp_age = 18-100 hh_agricactivity = 1 | 2 | 3 | 4 quotareached = 2 income_sec = 4 | R73: =1 -> 1 | S73: =Q73*R73 -> 0 | V73: yes | Z73: New question
A74: 18 | B74: income_sec_fishcheck | C74: income_sec_fishcheck | D74: Are the fish products that you sell produced by you or anyone in your household? [OPERATOR: SINGLE RESPONSE.] 1)YES 2)NO 3)DON'T KNOW 4)REFUSED | E74: =LEN(D74) -> 146 | F74: Les produits de la pêche que vous vendez sont-ils produits par vous ou par un membre de votre ménage ? [OPÉRATEUR/OPÉRATRICE: RÉPONSE UNIQUE.] 1)Oui 2)Non 3)NE SAIT PAS 4)REFUSÉ | G74: =LEN(F74) -> 180 | H74: Single Choice | I74: NA | J74: NA | K74: Form Type - Buttons | L74: 1-4 = income_sec_comp OR optional question | M74: if options #1-4, go to [income_sec_comp OR income_sec_amount OR income_sec_gender] | O74: resp_age = 18-100 hh_agricactivity = 1 | 2 | 3 | 4 quotareached = 2 income_sec = 5 | R74: =1 -> 1 | S74: =Q74*R74 -> 0 | V74: yes | Z74: New question
R75: =1 -> 1 | S75: =Q75*R75 -> 0
A76: 18 | B76: income_sec_gender | C76: income_sec_gender | D76: Is the person earning from #income_sec# male or female? [OPERATOR: SINGLE RESPONSE.] 1)Male 2)Female 3)DON'T KNOW 4)REFUSED | E76: =LEN(D76) -> 127 | F76: La personne qui perçoit #income_sec# est-elle un homme ou une femme ? [OPÉRATEUR/OPÉRATRICE: RÉPONSE UNIQUE.] 1)Homme 2)Femme 3)NE SAIT PAS 4)REFUSÉ | G76: =LEN(F76) -> 150 | H76: Single Choice | I76: NA | J76: NA | K76: Form Type - Buttons | L76: 1-4 = income_sec_comp OR optional question | M76: if options #1-4, go to [income_sec_comp OR income_sec_amount] | O76: resp_age = 18-100 hh_agricactivity = 1 | 2 | 3 | 4 quotareached = 2 income_sec = 1-18 | Q76: 17 | R76: =1 -> 1 | S76: =Q76*R76 -> 17 | V76: no | Z76: New question
A77: 19 | B77: income_sec_amount | C77: income_sec_amount | D77: How much was earned (in $currency$) from your second main income source, #income_sec#, in the past 3 months ? [OPERATOR: DOUBLE CHECK FOR OUTLIERS & MAKE SURE THE INFORMATION IS RECORDED IN THE CORRECT CURRENCY. ENTER 8888888 FOR DON'T KNOW AND 9999999 FOR REFUSED.] | E77: =LEN(D77) -> 267 | F77: Quelle somme (en $currency$) a rapporté votre deuxième source de revenu, #income_sec#, au cours des trois derniers mois ? [OPÉRATEUR/OPÉRATRICE: VÉRIFIER QUE LA RÉPONSE N’EST PAS INCOHÉRENTE ET QU'ELLE EST ENREGISTRÉE DANS LA BONNE DEVISE. SAISIR 8888888 POUR «NE SAIT PAS» ET 9999999 POUR «REFUSÉ».] | G77: =LEN(F77) -> 301 | H77: Range | I77: NA | J77: NA | K77: Form Type - TextBox | L77: $MIN AMOUNT$ - $THRESHOLD$ = income_sec_comp $THRESHOLD$ - $MAX AMOUNT$ = income_sec_amount_conf 8888888-8888888 = income_sec_comp 9999999-9999999 = income_sec_comp | M77: If the income amount is over the threshold set in "Additional information", the respondent will be asked to confirm with income_sec_amount_conf. Otherwise, go to income_sec_comp. | O77: resp_age = 18-100 hh_agricactivity = 1 | 2 | 3 | 4 quotareached = 2 income_sec = 1-18 | P77: We recommend using this pair of questions together. Nous vous recommandons d'utiliser ces deux questions ensemble. | Q77: 30.82847 | R77: =1 -> 1 | S77: =Q77*R77 -> 30.82847 | V77: no | Z77: Change in question text (col D)
A78: =A76+1 -> 19 | B78: income_sec_amount_conf | C78: income_sec_amount_conf | D78: Can you confirm the amount of income you just stated is correct? [OPERATOR: IF THE AMOUNT EARNED FROM THIS INCOME SOURCE OVER THE PAST 3 MONTH IS INDEED OVER $THRESHOLD$, CLICK ON CONTINUE. OTHERWISE, GO BACK AND CHANGE THE AMOUNT ENTERED.] 1)CONTINUE | E78: =LEN(D78) -> 253 | F78: Pouvez-vous confirmer que le montant que vous venez de déclarer est correct ? [OPÉRATEUR/OPÉRATRICE: SI LE MONTANT ISSU DE CETTE SOURCE DE REVENU AU COURS DES TROIS DERNIERS MOIS EST SUPÉRIEURX $THRESHOLD$, CLIQUER SUR CONTINUER. SINON, REVENIR EN ARRIÈRE ET MODIFIER LE MONTANT SAISI.] 1)CONTINUER | G78: =LEN(F78) -> 300 | H78: Single Choice | I78: NA | J78: NA | K78: Form Type - Buttons | L78: 1 = income_sec_comp | M78: if income_sec_amount_conf = 1, go to income_sec_comp | O78: NA | Q78: 2.2941177 | R78: =1 -> 1 | S78: =Q78*R78 -> 2.2941177 | V78: no
R79: =1 -> 1 | S79: =Q79*R79 -> 0
A80: =A76+1 -> 19 | B80: income_sec_comp | C80: income_sec_comp | D80: Has your household's income from #income_sec# changed in the last 3 months compared to the same period of $reference year$? [OPERATOR: SINGLE RESPONSE.] 1)A lot more [increased by more than 50%] 2)Slightly more 3)Same 4)Slightly less 5)A lot less [less than half as much] 6)DON'T KNOW 7)REFUSED | E80: =LEN(D80) -> 296 | F80: Le revenu de votre ménage provenant de #income_sec# a-t-il changé au cours des trois derniers mois par rapport à la même période de $reference year FR$ ? [OPÉRATEUR/OPÉRATRICE: RÉPONSE UNIQUE.] 1)Très supérieur [augmentation de plus de 50%] 2)Légèrement supérieur 3)Identique 5)Légèrement inférieur 5)Très inférieur [moins de la moitié] 6)NE SAIT PAS 7)REFUSÉ | G80: =LEN(F80) -> 361 | H80: Single Choice | I80: NA | J80: NA | K80: Form Type - Buttons | L80: 1-7= income_third | M80: if income_sec_comp = 1-7, go to income_third | O80: resp_age = 18-100 hh_agricactivity = 1 | 2 | 3 | 4 quotareached = 2 income_main = 1-18 income_sec = 1-18 | Q80: 21.193256 | R80: =1 -> 1 | S80: =Q80*R80 -> 21.193256 | V80: yes | Z80: Change in options #2,4 + question formulation (col D)
R81: =1 -> 1 | S81: =Q81*R81 -> 0
A82: =A80+1 -> 20 | B82: income_third | C82: income_third | D82: What has been your household's third most important source of income in the past 3 months? [OPERATOR: SINGLE RESPONSE. DON'T KNOW AND REFUSED OPTIONS SHOULD RARELY/NOT AVOIDED AS MUCH AS POSSIBLE.] 1)Production and sale of staple crops 2)Production and sale of vegetable or fruit 3)Production and sale of cashcrops 4)Production and sale of livestock and livestock products 5)Production and sale of fish 6)Collection and sale of forestry or bush products 7)Informal agricultural trade EXCLUDING producers 8)Formal agricultural trade EXCLUDING producers 9)Daily wage on farms and other casual employment in agricultural sector 10)Stable employment in agricultural sector 11)Non-agricultural self-employed or liberal profession / doctor / architect / lawyer / including restaurant 12)Off-farm daily wages and other non-agricultural casual employment 13)Stable employment in non-agricultural sector 14)Public employment 15)Income not derived from work / Charity 16)Income not derived from work / Welfare transfer, pension, humanitarian aid 17)Income not derived from work / Remittances 18)Income not derived from work / Income from other rents 19)No third most important source of income 20)DON'T KNOW 21)REFUSED | E82: =LEN(D82) -> 1219 | F82: Quelle a été la troisième source principale de revenu de votre ménage au cours des trois derniers mois ? [OPÉRATEUR/OPÉRATRICE: RÉPONSE UNIQUE. LES OPTIONS «NE SAIT PAS» ET «REFUSÉ» DOIVENT ÊTRE ÉVITÉES AUTANT QUE POSSIBLE.] 1)Production et vente de cultures d'aliments de base 2)Production et vente de légumes ou de fruits 3)Production et vente de cultures de rente 4)Production et vente de bétail et de produits du bétail 5)Production et vente de poisson 6)Collecte et vente de produits forestiers ou de brousse 7)Commerce agricole informel EXCLUANT les producteurs 8)Commerce agricole formel EXCLUANT les producteurs 9)Salaire journalier dans une exploitation et autres emplois occasionnels dans le secteur agricole 10)Emploi stable dans le secteur agricole 11)Indépendant non-agricole ou profession libérale / médecin / architecte / avocat / y compris restaurant 12)Salaire journalier et autres emplois occasionnels non agricoles 13)Emploi stable dans le secteur non-agricole 14)Emploi public 15)Revenu non tiré du travail / Charité 16)Revenu non tiré du travail / Transferts sociaux, pension, aide humanitaire 17)Revenu non tiré du travail / Envoi de fonds des migrants 18)Revenu non tiré du travail / Revenu d'autres loyers 19)Pas de troisième source principale de revenu 20)NE SAIT PAS 21)REFUSÉ | G82: =LEN(F82) -> 1309 | H82: Single Choice | I82: NA | J82: NA | K82: Form Type - Buttons Add all options manually exclude selected "income_main" exclude selected "income_sec" set demographic | L82: 1-3 = income_third_cropcheck 4 = income_third_lscheck 5 = income_third_fishcheck 6-18 = income_third_comp OR optional question 19-21 = shock | M82: if options #1-3 selected go to income_third_cropcheck if options #4 selected go to income_third_lscheck if options #5 selected go to income_third_fishcheck if options #6-18 selected, go to [income_third_comp OR income_third_amount OR income_third_gender] if options #19-21 selected, go to shock | O82: resp_age = 18-100 hh_agricactivity = 1 | 2 | 3 | 4 quotareached = 2 income_main = 1-18 income_sec = 1-18 | Q82: 20.229927 | R82: =1 -> 1 | S82: =Q82*R82 -> 20.229927 | V82: yes | Z82: Change in skip pattern (col J) Change in answer option #1
A83: 18 | B83: income_third_cropcheck | C83: income_third_cropcheck | D83: Are the crops that you sell produced by you or anyone in your household? [OPERATOR: SINGLE RESPONSE.] 1)YES 2)NO 3)DON'T KNOW 4)REFUSED | E83: =LEN(D83) -> 138 | F83: Les cultures que vous vendez sont-elles produites par vous ou par un des membres de votre ménage ? [OPÉRATEUR/OPÉRATRICE: RÉPONSE UNIQUE.] 1)Oui 2)Non 3)NE SAIT PAS 4)REFUSÉ | G83: =LEN(F83) -> 175 | H83: Single Choice | I83: NA | J83: NA | K83: Form Type - Buttons | L83: 1-4 = income_third_comp OR optional question | M83: if options #1-4, go to [income_third_comp OR income_third_amount OR income_third_gender] | O83: resp_age = 18-100 hh_agricactivity = 1 | 2 | 3 | 4 quotareached = 2 income_third = 1 | 2 | 3 | R83: =1 -> 1 | S83: =Q83*R83 -> 0 | V83: yes | Z83: New question
A84: 18 | B84: income_third_lscheck | C84: income_third_lscheck | D84: Are the livestock and livestock products that you sell produced by you or anyone in your household? [OPERATOR: SINGLE RESPONSE.] 1)YES 2)NO 3)DON'T KNOW 4)REFUSED | E84: =LEN(D84) -> 165 | F84: Le bétail et les produits du bétail que vous vendez sont-ils produits par vous par un des membres de votre ménage ? [OPÉRATEUR/OPÉRATRICE: RÉPONSE UNIQUE.] 1)Oui 2)Non 3)NE SAIT PAS 4)REFUSÉ | G84: =LEN(F84) -> 194 | H84: Single Choice | I84: NA | J84: NA | K84: Form Type - Buttons | L84: 1-4 = income_third_comp OR optional question | M84: if options #1-4, go to [income_third_comp OR income_third_amount OR income_third_gender] | O84: resp_age = 18-100 hh_agricactivity = 1 | 2 | 3 | 4 quotareached = 2 income_third = 4 | R84: =1 -> 1 | S84: =Q84*R84 -> 0 | V84: yes | Z84: New question
A85: 18 | B85: income_third_fishcheck | C85: income_third_fishcheck | D85: Are the fish products that you sell produced by you or anyone in your household? [OPERATOR: SINGLE RESPONSE.] 1)YES 2)NO 3)DON'T KNOW 4)REFUSED | E85: =LEN(D85) -> 146 | F85: Les produits de la pêche que vous vendez sont-ils produits par vous ou par un membre de votre ménage ? [OPÉRATEUR/OPÉRATRICE: RÉPONSE UNIQUE.] 1)Oui 2)Non 3)NE SAIT PAS 4)REFUSÉ | G85: =LEN(F85) -> 180 | H85: Single Choice | I85: NA | J85: NA | K85: Form Type - Buttons | L85: 1-4 = income_third_comp OR optional question | M85: if options #1-4, go to [income_third_comp OR income_third_amount OR income_third_gender] | O85: resp_age = 18-100 hh_agricactivity = 1 | 2 | 3 | 4 quotareached = 2 income_third = 5 | R85: =1 -> 1 | S85: =Q85*R85 -> 0 | V85: yes | Z85: New question
R86: =1 -> 1 | S86: =Q86*R86 -> 0
A87: 18 | B87: income_third_gender | C87: income_third_gender | D87: Is the person earning from #income_third# male or female? [OPERATOR: SINGLE RESPONSE.] 1)Male 2)Female 3)DON'T KNOW 4)REFUSED | E87: =LEN(D87) -> 129 | F87: La personne qui perçoit #income_third# est-elle un homme ou une femme ? [OPÉRATEUR/OPÉRATRICE: RÉPONSE UNIQUE.] 1)Homme 2)Femme 3)NE SAIT PAS 4)REFUSÉ | G87: =LEN(F87) -> 152 | H87: Single Choice | I87: NA | J87: NA | K87: Form Type - Buttons | L87: 1-4 = income_third_comp OR optional question | M87: if options #1-4, go to [income_third_comp OR income_third_amount] | O87: resp_age = 18-100 hh_agricactivity = 1 | 2 | 3 | 4 quotareached = 2 income_third = 1-18 | Q87: 17 | R87: =1 -> 1 | S87: =Q87*R87 -> 17 | V87: no | Z87: New question
A88: =A82+1 -> 21 | B88: income_third_amount | C88: income_third_amount | D88: How much was earned (in $currency$) from your third main source of income, #income_third#, in the past 3 months ? [OPERATOR: DOUBLE CHECK FOR OUTLIERS & MAKE SURE THE INFORMATION IS RECORDED IN THE CORRECT CURRENCY. ENTER 8888888 FOR DON'T KNOW AND 9999999 FOR REFUSED.] | E88: =LEN(D88) -> 271 | F88: Quelle somme (en $currency$) a rapporté votre troisième source de revenu, #income_third#, au cours des trois derniers mois ? [OPÉRATEUR/OPÉRATRICE: VÉRIFIER QUE LA RÉPONSE N’EST PAS INCOHÉRENTE ET QU'ELLE EST ENREGISTRÉE DANS LA BONNE DEVISE. SAISIR 8888888 POUR «NE SAIT PAS» ET 9999999 POUR «REFUSÉ».] | G88: =LEN(F88) -> 304 | H88: Range | I88: NA | J88: NA | K88: Form Type - TextBox | L88: $MIN AMOUNT$ - $THRESHOLD$ = income_third_comp $THRESHOLD$ - $MAX AMOUNT$ = income_third_amount_conf 8888888-8888888 = income_third_comp 9999999-9999999 = income_third_comp | M88: If the income amount is over the threshold set in "Additional information", the respondent will be asked to confirm with income_third_amount_conf. Otherwise, go to income_third_comp. | O88: resp_age = 18-100 hh_agricactivity = 1 | 2 | 3 | 4 quotareached = 2 income_main = 1-18 income_sec = 1-18 income_third = 1-18 | P88: We recommend using this pair of questions together. Nous vous recommandons d'utiliser ces deux questions ensemble. | Q88: 29.429832 | R88: =1 -> 1 | S88: =Q88*R88 -> 29.429832 | V88: no | Z88: Change in question text (col D)
A89: =A88+1 -> 22 | B89: income_third_amount_conf | C89: income_third_amount_conf | D89: Can you confirm the amount of income you just stated is correct? [OPERATOR: IF THE AMOUNT EARNED FROM THIS INCOME SOURCE OVER THE PAST 3 MONTH IS INDEED OVER $THRESHOLD$, CLICK ON CONTINUE. OTHERWISE, GO BACK AND CHANGE THE AMOUNT ENTERED.] 1)CONTINUE | E89: =LEN(D89) -> 253 | F89: Pouvez-vous confirmer que le montant que vous venez de déclarer est correct ? [OPÉRATEUR/OPÉRATRICE: SI LE MONTANT ISSU DE CETTE SOURCE DE REVENU AU COURS DES TROIS DERNIERS MOIS EST BIEN SUPÉRIEUR AU $THRESHOLD$, CLIQUER SUR CONTINUER. SINON, REVENIR EN ARRIÈRE ET MODIFIER LE MONTANT SAISI.] 1)CONTINUER | G89: =LEN(F89) -> 307 | H89: Single Choice | I89: NA | J89: NA | K89: Form Type - Buttons | L89: 1 = income_third_comp | M89: if income_third_amount_conf = 1, go to income_third_comp | O89: NA | Q89: 1.5555556 | R89: =1 -> 1 | S89: =Q89*R89 -> 1.5555556 | V89: no
R90: =1 -> 1 | S90: =Q90*R90 -> 0
A91: =A89+1 -> 23 | B91: income_third_comp | C91: income_third_comp | D91: Has your household's income from #income_third# changed in the last 3 months compared to the same period of $reference year$? [OPERATOR: SINGLE RESPONSE.] 1)A lot more [increased by more than 50%] 2)Slightly more 3)Same 4)Slightly less 5)A lot less [less than half as much] 6)DON'T KNOW 7)REFUSED | E91: =LEN(D91) -> 298 | F91: Le revenu de votre ménage provenant de #income_third# a-t-il changé au cours des trois derniers mois par rapport à la même période de $reference year FR$ ? [OPÉRATEUR/OPÉRATRICE: RÉPONSE UNIQUE.] 1)Très supérieur [augmentation de plus de 50%] 2)Légèrement supérieur 3)Identique 5)Légèrement inférieur 5)Très inférieur [moins de la moitié] 6)NE SAIT PAS 7)REFUSÉ | G91: =LEN(F91) -> 363 | H91: Single Choice | I91: NA | J91: NA | K91: Form Type - Buttons | L91: 1-7= shock OR optional question | M91: if income_third_comp = 1-7, go to shock OR income_gender_control | O91: resp_age = 18-100 hh_agricactivity = 1 | 2 | 3 | 4 quotareached = 2 income_main = 1-18 income_sec = 1-18 income_third = 1-18 | Q91: 16.348396 | R91: =1 -> 1 | S91: =Q91*R91 -> 16.348396 | V91: yes | Z91: Change in options #2,4 + question formulation (col D)
R92: =1 -> 1 | S92: =Q92*R92 -> 0
B93: income_gender_control | C93: income_gender_control | D93: Are women in this household able to decide how to use the income they earn? [OPERATOR: SINGLE RESPONSE.] 1)YES 2)NO 3)DON'T KNOW 4)REFUSED | E93: =LEN(D93) -> 140 | F93: Les femmes de votre ménage sont-elles en mesure de décider de l'utilisation des revenus qu'elles rapportent ? [OPÉRATEUR/OPÉRATRICE: RÉPONSE UNIQUE.] 1)Oui 2)Non 3)NE SAIT PAS 4)REFUSÉ | G93: =LEN(F93) -> 186 | H93: Single Choice | I93: NA | J93: Send if "income_main_gender" "Equals" "Female" Or "income_sec_gender" "Equals" "Female" Or "income_third_gender" "Equals" "Female", if not satisfied go to "shock" | K93: Form Type - Buttons | L93: 1-4 = shock | M93: If the respondent indicated that any of the three main income sources is generated by a female household member, this question is asked. Otherwise, go to the next question. if income_gender_control = 1-4, go to shock | O93: resp_age = 18-100 hh_agricactivity = 1 | 2 | 3 | 4 (income_main_gender = 1) | (income_sec_gender = 1) | (income_third_gender = 1) quotareached = 2 | Q93: 0 | R93: =1 -> 1 | S93: =Q93*R93 -> 0 | V93: no | Z93: New question
R94: =1 -> 1 | S94: =Q94*R94 -> 0
A95: =A97+1 -> 25 | B95: shock | C95: shock_ 1) shock_noshock 2) shock_sicknessordeathofhh 3) shock_lostemplorwork 4) shock_otherintrahhshock 5) shock_higherfoodprices 6) shock_higherfuelprices 7) shock_cantworkordobusiness 8) shock_othereconomicshock 9) shock_pestoutbreak 10) shock_plantdisease 11) shock_animaldisease 12) shock_napasture 13) shock_othercropandlivests 14) shock_coldtemporhail 15) shock_flood 16) shock_hurricane 17) shock_drought 18) shock_earthquake 19) shock_landslides 20) shock_firenatural 21) shock_othernathazard 22) shock_violenceinsecconf 23) shock_theftofprodassets 24) shock_fire 25) shock_othermanmadehazard 26) shock_dk 27) shock_ref | D95: Has your household faced any particular disaster or crisis affecting your community or your household that affected your ability to raise an income and/or to produce food for self consumption in the last 3 months? [OPERATOR: SELECT RELEVANT SHOCKS EXPERIENCED BY THE HOUSEHOLD. MULTIPLE RESPONSES POSSIBLE. REFER TO ECONOMIC SHOCKS, CROP AND LIVESTOCK SHOCKS, INTRA-HOUSEHOLD SHOCK, NATURAL HAZARDS AND MAN-MADE HAZARDS.] 1)No shock 2)Sickness or accident or death of household member[s] [sickness of breadwinner / unusually high medical expenditure / funeral expenses / death of breadwinner] 3)Lost employment or working opportunities [mainly applies for daily work] 4)Other intra household shock 5)Much higher than usual food prices 6)Much higher than usual fuel prices or transport prices 7)Could not continue business as usual due to external constraints [such as covid restrictions, insecurity, infrastructure damage, etc.] 8)Other economic shock 9)Pest outbreak 10)Plant disease 11)Animal disease affecting many animals or death of animals 12)Lack of physical access to pasture [because of conflict / infrastructure damage / COVID-19 restrictions] 13)Other crop and livestock shock 14)Cold temperatures or hail 15)Flood / riverbank erosion 16)Hurricane / cyclone / tornado 17)Drought / heat stress 18)Earthquake 19)Landslides 20)Fire from natural disaster 21)Other natural hazard 22)Violence and insecurity / conflict 23)Theft of production assets [land / livestock / tools / etc] 24)Fire from man-made disaster 25)Other man-made hazard 26)DON'T KNOW 27)REFUSED | E95: =LEN(D95) -> 1573 | F95: Au cours des trois derniers mois, votre ménage a-t-il été confronté à une catastrophe ou une crise particulière touchant votre communauté ou votre ménage et qui a atteint votre capacité à dégager un revenu et/ou à produire des aliments pour votre propre consommation ? [OPÉRATEUR/OPÉRATRICE: SÉLECTIONNER LES CHOCS PERTINENTS SUBIS PAR LE MÉNAGE. PLUSIEURS RÉPONSES POSSIBLES. SE RÉFÉRER AUX CHOCS ÉCONOMIQUES, AUX CHOCS TOUCHANT LES RÉCOLTES ET LE BÉTAIL, AUX CHOCS INTRA-MÉNAGE, AUX RISQUES NATURELS ET AUX RISQUES D'ORIGINE HUMAINE] 1)Aucun choc 2)Maladie, accident ou décès d'un ou plusieurs membres du ménage [maladie du soutien de famille / dépenses médicales anormalement élevées / frais funéraires / décès du soutien de famille] 3)Perte d'emploi ou de possibilités de travail [principalement travail journalier] 4)Autre choc interne au ménage 5)Prix des denrées alimentaires beaucoup plus élevés que d'habitude 6)Prix des carburants ou des transports beaucoup plus élevés que d'habitude 7)Impossibilité de poursuivre les activités habituelles en raison de contraintes externes [restrictions budgétaires, insécurité, infrastructures endommagées, etc.] 8)Autre choc économique 9)Invasion d'organismes nuisibles 10)Maladie des plantes 11)Maladie animale touchant de nombreux animaux ou mort d'animaux 12)Accès difficile aux pâturages [en raison de conflits / d'infrastructures endommagées / des restrictions liées à la covid-19] 13)Autres chocs touchant les cultures et le bétail 14)Températures froides / grêle 15)Inondations / érosion des berges 16)Ouragan / cyclone / tornade 17)Sécheresse / stress dû à la chaleur 18)Tremblement de terre 19)Glissement de terrain 20)Incendie dû à une catastrophe naturelle 21)Autres risques naturels 22)Violence et insécurité / conflit 23)Vol d'actifs de production [terres/ bétail/ outils/ etc.] 24)Incendie d'orgine humaine 25)Autre risque d'origine humaine 26)NE SAIT PAS 27)REFUSÉ | G95: =LEN(F95) -> 1930 | H95: Select All That Apply | I95: NA | J95: NA | K95: Form Type - Checklist 1, 26, 27 = IsNone | L95: 1-27 = [covid or optional question] | M95: if shock = 1-27, go to [covid or hh_explanation] | O95: resp_age = 18-100 hh_agricactivity = 1 | 2 | 3 | 4 quotareached = 2 | Q95: 46.247528 | R95: =1 -> 1 | S95: =Q95*R95 -> 46.247528 | V95: yes | Z95: Changes in options #2, 6, 11, 15, 16, 17 Change in skip pattern
A96: 28 | B96: hh_explanation | C96: hh_explanation | D96: If the household was affected by a major recent shock object of this assessment (for example, an earthquake), what do you think are the consequences for your household, in your own words? [OPERATOR: RECORD IN FEW WORDS THE MAIN CONSEQUENCE OF THE RECENT SHOCKS. ENTER 88 FOR DON'T KNOW AND 99 FOR REFUSED.] | E96: =LEN(D96) -> 307 | F96: Si votre ménage a été concerné par un choc majeur récent objet de cette évaluation (par exemple, un tremblement de terre), quelles en sont, selon vous et dans vos propres mots, les conséquences pour votre ménage ? [OPÉRATEUR/OPÉRATRICE: SAISIR EN QUELQUES MOTS LA PRINCIPALE CONSÉQUENCE DES RÉCENTS CHOCS. SAISIR 88 POUR «NE SAIT PAS» ET 99 POUR «REFUSÉ»]. | G96: =LEN(F96) -> 357 | H96: Open Ended | I96: NA | J96: NA | K96: Form Type - TextBox | L96: Any Response = covid | M96: For any response to hh_explanation, go to covid. | Q96: 26.118782 | R96: =1 -> 1 | S96: =Q96*R96 -> 26.118782 | V96: no | Z96: Change in skip pattern
A97: =A91+1 -> 24 | B97: covid | C97: covid_ 1) covid_goodstransp 2) covid_marketclosed 3) covid_borderclosed 4) covid_stayhome 5) covid_gatherings 6) covid_processclosed 7) covid_other 8) covid_none 9) covid_dk 10) covid_ref | D97: Have you or anyone in your household been affected by movement restrictions or social distancing measures aimed at containing COVID-19 in the last 3 months? [OPERATOR: MULTIPLE RESPONSES POSSIBLE.] 1)Movement restrictions [sometimes producing product scarcity or price heights] 2)Closure of food markets or other businesses 3)Closure of international borders [affecting the purchase of imported inputs or the sale of goods for export or transhumance] 4)Stay at home order 5)Ban on gatherings 6)Closure of food processors [slaughterhouse / dairy cooperatives / etc] or restaurants 7)Other [specify] 8)Not affected by restrictions 9)DON'T KNOW 10)REFUSED | E97: =LEN(D97) -> 654 | F97: Au cours des trois derniers mois, vez-vous, ou un membre de votre ménage, été touché par des restrictions de mouvement ou des mesures de distanciation sociale visant à contenir la covid-19 ? [OPÉRATEUR/OPÉRATRICE: PLUSIEURS RÉPONSES POSSIBLES.] 1)Restrictions de mouvement [entraînant parfois une raréfaction des produits ou une forte hausse des prix] 2)Fermeture des marchés alimentaires ou d'autres commerces 3)Fermeture des frontières internationales [ayant un impact sur l'achat d'intrants importés, la vente de marchandises exportées ou la transhumance] 4)Ordre de confinement 5)Interdiction des rassemblements 6)Fermeture des lieux de transformation des aliments (abattoirs, coopératives laitières, etc.) ou des restaurants 7)Autre [préciser] 8)Non touché par les restrictions 9)NE SAIT PAS 10)REFUSÉ | G97: =LEN(F97) -> 809 | H97: Open Ended - Select All That Apply | I97: NA | J97: NA | K97: Form Type - Checklist 8,9,10 = IsNone | L97: 1-10 = crp_intro | M97: if covid = 1-10, go to crp_intro | O97: resp_age = 18-100 hh_agricactivity = 1 | 2 | 3 | 4 quotareached = 2 | Q97: 56.471024 | R97: =1 -> 1 | S97: =Q97*R97 -> 56.471024 | V97: yes | Z97: Change in question text + options #1, 2 change in skip pattern according to new placement
R98: =1 -> 1 | S98: =Q98*R98 -> 0
A99: D. CROP PRODUCTION
A100: =A96+1 -> 29 | B100: crp_intro | C100: crp_intro | D100: We will now ask you some questions about crop production which apply to you and anyone in your household that is involved in crop production or sales. All questions refer to the crops grown during $season$. 1)CONTINUE | E100: =LEN(D100) -> 219 | F100: Nous allons maintenant vous poser quelques questions sur la production végétale. Ces questions vous concernent ainsi que toute personne de votre ménage impliquée dans la production ou la vente de cultures. Toutes les questions se rapportent aux cultures pratiquées pendant la $saison$. 1)CONTINUER | G100: =LEN(F100) -> 299 | H100: Single Choice | I100: NA | J100: Send if "hh_agricactivity" "Equals" "Yes - crop production" Or "hh_agricactivity" "Equals" "Yes - both crop and livestock production" Or "income_main_cropcheck" "Equals" "YES" Or "income_sec_cropcheck" "Equals" "YES" Or "income_third_cropcheck" "Equals" "YES", if not satisfied go to "crp_salesmain" | K100: Form Type - Buttons | L100: 1 = crp_landsize_num | M100: If hh_agricactivity = "Yes - crop production" or "Yes - both crop and livestock production" or if they reported production and sales of crops in one of the three main income sources and confirmed that they are involved in production, then this section will be asked to respondents. Otherwise, skip to crp_salesmain. Next question is crp_landsize_num | O100: resp_age = 18-100 (hh_agricactivity = 1 | 3) | (income_main_cropcheck = 1) | (income_sec_cropcheck = 1) | (income_third_cropcheck = 1) quotareached = 2 | Q100: 7.5 | R100: ='Additional information'!$D$17 -> 0.91 | S100: =Q100*R100 -> 6.825 | V100: yes | Z100: New question + change in conditional for this section
...

Sheet Crop list
I2: Dernier numéro
C3: Select top 10 crops | D3: GeoPoll code | E3: Dataset code | F3: Label (EN) | G3: Label (FR) | I3: =MAX(D:D) -> 94
D4: 1 | E4: 1.1 | F4: Rice | G4: Riz
D5: 2 | E5: 1.2 | F5: Wheat | G5: Blé
D6: 3 | E6: 1.3 | F6: Millet | G6: Mil
D7: 4 | E7: 1.4 | F7: Sorghum | G7: Sorgho
D8: 5 | E8: 1.5 | F8: Maize | G8: Maïs
D9: 6 | E9: 1.6 | F9: Barley | G9: Orge
D10: 7 | E10: 1.99 | F10: Other Cereal | G10: Autres céréales
D11: 8 | E11: 2.1 | F11: Cassava | G11: Manioc
D12: 9 | E12: 2.2 | F12: Potatoe | G12: Pommes de terre
D13: 10 | E13: 2.3 | F13: Sweet Potatoes | G13: Patates douces
D14: 11 | E14: 2.4 | F14: Yams | G14: Ignames
D15: 12 | E15: 2.5 | F15: Carrots | G15: Carottes
... D93: 66 | E93: 10.99 | F93: Other non-food cash crop | G93: Autre culture de rente non alimentaire

Sheet Additional information
C2: Original EN / FR | D2: Replacement (EN) | E2: Remplacement (FR) | F2: Comment (EN) | G2: Comment (FR) | H2: Example (EN) | I2: Exemple (FR)
B3: FOR CORE QUESTIONS . (Mandatory to fill out) . | C3: ADMIN1 / ADMIN1 | F3: The first subdivision of the country, after national level; region; province; governorate; etc. | G3: La première subdivision du pays, après le niveau national ; par exemple, région ; province ; gouvernorat ; etc. | H3: region | I3: region
C4: ADMIN2 / ADMIN2 | F4: The second subdivision of the country; district; municipality; LGA; etc. | G4: La deuxième subdivision du pays ; par exemple, district, municipalité, LGA, etc. | H4: district | I4: district
C5: reference year / reference year FR | F5: Comparison questions will need need a reference year. Select whether you want to use "last year" or "a normal year" as a baseline. A "normal year" should refers to an average year from the past 5 years - make sure to train the enumerators accordingly. | G5: Les questions de comparaison auront besoin d'une année de référence. Choisissez si vous voulez utiliser "l'année dernière" ou "une année normale" comme année de référence. Une "année normale" doit correspondre à une année moyenne des 5 dernières années - veillez à former les recenseurs en conséquence. | H5: a normal year | I5: une année normale
C6: season / saison | F6: Name the crop season(s) of interest if there are several cropping seasons in the country (e.g. Meher and Belg in Ethiopia, rainy season / flood-recession cropping / irrigated dry season in the Sahel). You can refer to the “last season” or “ongoing season". | G6: Nommez la ou les saisons culturales concernée(s) en ANGLAIS s'il y en a plusieurs dans le pays (par exemple, Meher et Belg en Ethiopie, saison des pluies / cultures de décrue / saison sèche irriguée au Sahel). Vous pouvez vous référer à la "dernière saison" ou "saison actuelle". | H6: wet season | I6: saison des pluies
C7: season phase / phase de la saison | D7: =IF(E7="Pas encore en saison","Not yet in season",IF(E7="Préparation du terrain","Land preparation",IF(E7="Semis / plantation","Planting",IF(E7="Début de la croissance","Early growing",IF(E7="Croissance","Growing",IF(E7="Proche de la récolte","Maturing",IF(E7="Récolte","Harvesting",IF(E7="Post-récolte","Recently finished","")))))))) | F7: Indicate the phase of the season at the time of data collection. If the harvest from the season has not yet occurred, the question on crop harvest (crp_harv_change) will include the word “expected” (where #expected or nothing# is located). If the harvest has occured, "expected" will not be inserted in the question. | G7: Indiquez le stade de la saison culturale au moment de la collecte des données. Si la récolte de la saison n'a pas encore eu lieu, la question sur la récolte des cultures (crp_harv_change) inclura le mot "attendue" (là où se trouve #attendue ou rien#). Si la récolte a eu lieu, "attendue" ne sera pas inséré dans la question. | H7: Harvesting | I7: Récolte
C8: local measurement unit | F8: Specify the local measurement unit for land size, other than acres, hectares, square meters and square feet. If no other unit of measurement is needed, keep this cell blank. | G8: Indiquez l'unité utilisée localement pour mesurer la taille des terrains, autre que les acres, les hectares, les mètres carrés et les pieds carrés. Si aucune autre unité de mesure n'est nécessaire, garder cette cellule vide. | H8: Jeribs | I8: Jeribs
C9: local measurement unit conversion | D9: =IF(E9<>"",E9,"") | F9: Include the conversion of the local measurement unit to hectares. In other words, how many local measurement units are in 1 ha. | G9: Indiquez la conversion de l'unité de mesure locale en hectares. En d'autres termes, indiquez combien d'unités de mesure locales y a-t-il dans 1 ha. | H9: 0.2 | I9: 0.2
B10: FOR OPTIONAL QUESTIONS . (Fill out if applicable) . | C10: currency / devise | D10: =IF(E10="","",E10) | F10: The name of the main currency used nationally; USD; Naira; Rial; Pesos; etc. | G10: Nom de la principale devise utilisée au niveau national; par exemple, USD; Naira; Rial; Pesos; etc. | H10: Naira | I10: Naira
C11: MIN AMOUNT / MIN AMOUNT | D11: =IF(E11="","",E11) | F11: The minimum amount for an income source should be set at 0 or any value below which it is not possible to do a transaction. For example, the smallest coin/banknote in a currency can be 1000, in which case you would set the minimum at 1000. Provide this input in the same currency as specified above. Only digits should be inputted. | G11: Le montant minimum d'une source de revenu doit être fixé à 0 ou à toute valeur en dessous de laquelle il n'est pas possible d'effectuer une transaction. Par exemple, la plus petite pièce/billet d'une devise peut être de 1000, auquel cas vous fixerez le minimum à 1000. Cette saisie doit être effectuée dans la même devise que celle spécifiée ci-dessus. Seuls des chiffres doivent être saisis. | H11: 5 | I11: 5
C12: MAX AMOUNT / MAX AMOUNT | D12: =IF(E12="","",E12) | F12: Set the maximum amount for an income source over 3 months. It will not be possible for enumerators to input values above this amount in questions related to income amounts. Using previous representative surveys for this population, you can estimate this amount by using the mean income plus five (5) standard deviations, unless the country has high inflation. In the latter case, set the maximum value based on your country context (higher than the proposed approach). Provide this input in the same currency as specified above. Only digits should be inputted. | G12: Fixez le montant maximum pouvant être généré par une source de revenu sur 3 mois. Il ne sera pas possible pour les enquêteurs d'entrer des valeurs supérieures à ce montant dans les questions relatives aux montants des revenus. En vous basant sur des enquêtes précédentes représentatives de cette population, vous pouvez estimer ce montant en utilisant le revenu moyen plus cinq (5) écarts types, sauf si le pays connaît une forte inflation. Dans ce dernier cas, fixez la valeur maximale en fonction du contexte de votre pays (plus élevée que l'approche proposée). Cette saisie doit être effectuée dans la même devise que celle spécifiée ci-dessus. Seuls des chiffres doivent être saisis. | H12: 5000000 | I12: 5000000
C13: THRESHOLD / THRESHOLD | D13: =IF(E13="","",E13) | F13: The threshold salary should be calculated to flag outliers (responses that look suspiciously high). Using previous representative surveys for this population, a good estimate is the average plus three (3) standard deviations, which should give the threshold for the 3 or 4% highest income values. Provide this input in the same currency as specified above. Only digits should be inputted. | G13: Le salaire seuil doit être calculé pour signaler les valeurs aberrantes (réponses qui semblent suspectes). En utilisant des enquêtes précédentes représentatives de cette population, une bonne estimation est la moyenne plus deux écarts types, ce qui devrait dégager le seuil pour les 3 ou 4% des valeurs de revenu les plus élevées. Cette saisie doit être effectuée dans la même devise que celle spécifiée ci-dessus. Seuls des chiffres doivent être saisis. | H13: 1200000 | I13: 1200000
C14: local vegetables / légumes locaux | F14: Input some common local vegetables [to be used as examples in the food consumption score indicator]. | G14: Saisissez quelques légumes locaux courants [à utiliser comme exemples dans l'indicateur de score de consommation alimentaire]. | H14: eggplants, zucchini, cauliflower | I14: aubergines, courgettes, choux-fleurs
C15: local fruits / fruits locaux | F15: Input some common local fruits [to be used as examples in the food consumption score indicator]. | G15: Indiquez quelques fruits locaux courants [à utiliser comme exemples dans l'indicateur de score de consommation alimentaire]. | H15: apples, bananas, oranges | I15: pommes, bananes, oranges
B17: FILL OUT FOR QUESTIONNAIRE DURATION ESTIMATION . | C17: Expected percentage of respondents cultivating crops | D17: =IF(E17="","",E17) -> 0.91 | E17: 0.91 | F17: If the survey is representative and has no quotas, write the proportion of rural households cultivating crops at country level, or if the survey follows a previous round with identical sample design, just report the percentage from the previous round. If you are using quotas, calculate the ratio of the quota over the minimum sample size at the level where the quota is implemented (so if you have a minimum sample size per strata of 110 with a quota of 100 crop producers, then it's 100/110 = 91% (the maximum you should write is 100%). | G17: Si l'enquête est représentative et ne comporte pas de quotas, écrivez la proportion de ménages ruraux impliqués dans les cultures au niveau du pays, ou si l'enquête suit un cycle précédent avec un plan d'échantillonnage identique, indiquez simplement le pourcentage du cycle précédent. Si vous utilisez des quotas, calculez le rapport entre le quota et la taille minimale de l'échantillon au niveau où le quota est appliqué (ainsi, si vous avez une taille minimale d'échantillon par strate de 110 avec un quota de 100 producteurs de cultures, alors c'est 100/110 = 91% (le maximum que vous devez écrire est 100%). | H17: 0.91 | I17: 0.91
C18: Expected percentage of respondents raising livestock | D18: =IF(E18="","",E18) -> 0.91 | E18: 0.91 | F18: If the survey is representative and has no quotas, write the proportion of rural households raising livestock at country level, or if the survey follows a previous round with identical sample design, just report the percentage from the previous round. If you are using quotas, calculate the ratio of the quota over the minimum sample size at the level where the quota is implemented (so if you have a minimum sample size of 110 but a quota of 100 livestock producers, then it's 100/110 = 91% (the maximum you should write is 100%) | G18: Si l'enquête est représentative et ne comporte pas de quotas, écrivez la proportion de ménages ruraux impliqués dans l'élevage, ou si l'enquête suit un cycle précédent avec un plan d'échantillonnage identique, indiquez simplement le pourcentage du cycle précédent. Si vous utilisez des quotas, calculez le rapport entre le quota et la taille minimale de l'échantillon au niveau où le quota est appliqué (ainsi, si vous avez une taille minimale d'échantillon par strate de 110 avec un quota de 100 éleveurs, alors c'est 100/110 = 91% (le maximum que vous devez écrire est 100%). | H18: 0.91 | I18: 0.91
C19: Expected percentage of respondents involved in fishery | D19: =IF(E19="","",E19) -> 0.05 | E19: 0.05 | F19: If the survey is representative and has no quotas, write the proportion of rural households involved in fisheries or aquaculture, otherwise if you are using quotas, calculate the ratio of the quota over the sample size at the level where the quota is implemented. (so if you haven't set a quota, and you expect to have a representative proportion of fishermen, just write the percentage of fishermen in the population you are targeting, in the example to the right, 5%) | G19: Si l'enquête est représentative et ne comporte pas de quotas, écrivez la proportion de ménages ruraux impliqués dans la pêche ou l'aquaculture; sinon, si vous utilisez des quotas, calculez le rapport entre le quota et la taille de l'échantillon au niveau où le quota est appliqué (ainsi, si vous n'avez pas fixé de quota, et que vous pensez avoir une proportion représentative de pêcheurs, écrivez simplement le pourcentage de pêcheurs dans la population que vous ciblez, dans l'exemple à droite, 5%). | H19: 0.05 | I19: 0.05
