Workbook

Sheet survey
A1: GeoPoll Submission Form
A2: FAO - Household Questionnaire | P2: Additional notes
A3: Q # | B3: Q Name | C3: Suggested Qname | D3: English | E3: Length | F3: French | G3: Length | H3: Q Type | I3: Randomize | J3: Conditional | K3: Programming Instructions | L3: Skip Pattern | M3: Codes | N3: Default skip patterns & conditional | O3: Specify skip pattern variable (from blue text) | Q3: Estimated percentage of repondents | T3: Mandatory | X3: Duration (sec) | Y3: Weighted duration | Z3: Core questions only
A4: A. PRESENTATION OF THE SURVEY AND ELIGIBILITY CRITERIA SELECTION | T4: no | Y4: =IF(X4="","",X4*V4) | Z4: =IF(T4="yes",Y4,"")
A5: NA | B5: Optin | D5: Optin | E5: =LEN(D5) -> 5 | F5: Optin | G5: =LEN(F5) -> 5 | H5: Open Ended | I5: NA | J5: NA | K5: Form Type - TextBox | L5: Any Response = phone_number | M5: NA | N5: NA | T5: no | X5: 0 | Y5: =IF(X5="","",X5*Q5) -> 0 | Z5: =IF(T5="yes",Y5,"")
A6: NA | B6: phone_number | C6: phone_number | D6: Input the phone number that you are contacting: | E6: =LEN(D6) -> 48 | F6: Saisir le numéro de téléphone que vous chercher à contacter: | G6: =LEN(F6) -> 61 | H6: Open Ended | I6: NA | J6: NA | K6: Form Type - TextBox | L6: Any Response = calldispo | M6: NA | N6: NA | T6: yes | X6: 0 | Y6: =IF(X6="","",X6*Q6) -> 0 | Z6: =IF(T6="yes",Y6,"") -> 0
A7: NA | B7: calldispo | C7: calldispo | D7: Phone number: #CATI_MOBILENUMBER# 1)Someone answers 2)Answering machine 3)No answer 4)Hang up or refusal 5)Call back 6)Under review 7)Disconnected | E7: =LEN(D7) -> 146 | F7: Numéro de téléphone: #CATI_MOBILENUMBER# 1)Quelqu’un répond 2)Répondeur 3)Pas de réponse 4)Raccroche/Refuse 5)Doit être rappelé 6)À l’étude 7)Déconnecté | G7: =LEN(F7) -> 152 | H7: Single Choice | I7: NA | J7: NA | K7: Form Type - Buttons | L7: 1 = resp_language 2 = AnsweringMachine 3 = NoAnswer 4 = Refusal 5 = WhenCallBack 6 = UnderReview 7 = Disconnected | M7: NA | N7: NA | T7: no | X7: 14.695308 | Y7: =IF(X7="","",X7*Q7) -> 0 | Z7: =IF(T7="yes",Y7,"")
A8: NA | B8: AnsweringMachine | C8: calldispo_answeringmachine | D8: Reached an answering machine. | E8: =LEN(D8) -> 29 | F8: L'appel a abouti sur un répondeur/une messagerie. | G8: =LEN(F8) -> 49 | H8: NA | I8: NA | J8: NA | K8: NA | L8: End Poll AnsweringMachine | M8: NA | N8: NA | T8: no | X8: 0 | Y8: =IF(X8="","",X8*Q8) -> 0 | Z8: =IF(T8="yes",Y8,"")
A9: NA | B9: NoAnswer | C9: calldispo_noanswer | D9: Phone rang and no one answered. | E9: =LEN(D9) -> 31 | F9: Le téléphone a sonné et personne n'a répondu. | G9: =LEN(F9) -> 45 | H9: NA | I9: NA | J9: NA | K9: NA | L9: End Poll NoAnswer | M9: NA | N9: NA | T9: no | X9: 0 | Y9: =IF(X9="","",X9*Q9) -> 0 | Z9: =IF(T9="yes",Y9,"")
A10: NA | B10: UnderReview | C10: calldispo_underreview | D10: Case needs review by a supervisor. | E10: =LEN(D10) -> 34 | F10: Le cas doit être examiné par un superviseur. | G10: =LEN(F10) -> 44 | H10: NA | I10: NA | J10: NA | K10: NA | L10: End Poll UnderReview | M10: NA | N10: NA | T10: no | X10: 0 | Y10: =IF(X10="","",X10*Q10) -> 0 | Z10: =IF(T10="yes",Y10,"")
A11: NA | B11: Disconnected | C11: calldispo_disconnected | D11: Phone was disconnected or out of service. | E11: =LEN(D11) -> 41 | F11: Le téléphone est déconnecté ou hors service. | G11: =LEN(F11) -> 44 | H11: NA | I11: NA | J11: NA | K11: NA | L11: End Poll Disconnected | M11: NA | N11: NA | T11: no | X11: 0 | Y11: =IF(X11="","",X11*Q11) -> 0 | Z11: =IF(T11="yes",Y11,"")
A12: NA | B12: resp_language | C12: resp_language | D12: Which language do you wish to proceed with? [OPERATOR: READ ANSWER CHOICES. SINGLE RESPONSE.] 1)English 2)other options [add as many as necessary] | E12: =LEN(D12) -> 148 | F12: Quelle langue souhaitez-vous utiliser? [OPÉRATEUR/OPÉRATRICE: LIRE LES CHOIX, RÉPONSE UNIQUE] 1)Français 2)autre [ajouter autant d'options que nécessaire] | G12: =LEN(F12) -> 156 | H12: Single Choice | I12: NA | J12: NA | K12: Form Type - Buttons | L12: 1 = introduction [English] 2 = introduction [languages & add more if needed] | M12: NA | N12: For any response, go to introduction | P12: Insert most common national languages here [max 4 for translation with GeoPoll]. | T12: no | X12: 3.1032724 | Y12: =IF(X12="","",X12*Q12) -> 0 | Z12: =IF(T12="yes",Y12,"")
A13: NA | B13: introduction | C13: introduction | D13: Hello sir/ma'am, my name is #OPERATOR#, and I am calling from GeoPoll Polling Agency on behalf of the Food and Agriculture Organization of the United Nations [FAO]. We are conducting a survey on household livelihoods and the ability to access food in your area. I would like to ask you some questions about your household. The survey usually takes 15/20 minutes to complete. Any information that you provide will be kept strictly confidential, only used for the purpose of the survey and will not be shown to other people. Your voluntary participation in the outcome of this interview is NOT IN ANY WAY linked to your personal chance of receiving any assistance. This is voluntary and you can choose not to answer any or all of the questions if you want. However, we hope that you will participate since your views are important. You will receive #TOPUP#! of communication credit as an incentive for the participation of the survey. Please note that this call may be recorded for quality purposes. Do you have any questions? [OPERATOR: ADDRESS QUESTIONS FROM RESPONDENT, IF ANY.] 1)CONTINUE | E13: =LEN(D13) -> 1098 | F13: Bonjour Monsieur/Madame, mon nom est #OPERATOR#. Je vous appelle de la part de l'agence de sondage GeoPoll pour le compte de l'Organisation des Nations Unies pour l'alimentation et l'agriculture [la FAO]. Nous menons une enquête sur les moyens d'existence et la capacité des ménages à accéder à la nourriture dans votre région. J'aimerais vous poser quelques questions sur votre ménage. L'enquête dure généralement entre 15 et 20 minutes. Toutes les informations que vous fournirez resteront strictement confidentielles; elles ne seront utilisées que dans le cadre de cette enquête et ne seront pas communiquées à d'autres personnes. Votre participation volontaire à cet entretien n'est en AUCUN CAS liée à la possibilité de recevoir une quelconque aide. Votre participation est volontaire et, si vous le souhaitez, vous pouvez choisir de ne pas répondre à une partie ou à la totalité des questions. Cependant, nous espérons que vous voudrez bien participer car votre avis est important. Vous recevrez #TOPUP#! de crédit téléphonique comme incitation à participer à l'enquête. Veuillez noter que cet appel peut être enregistré à des fins de contrôle qualité. Avez-vous des questions? [OPÉRATEUR/OPÉRATRICE: LE CAS ÉCHÉANT, RÉPONDRE AUX QUESTIONS DE LA PERSONNE INTERROGÉE.] 1)CONTINUER | G13: =LEN(F13) -> 1293 | H13: Single Choice | I13: NA | J13: NA | K13: Form Type - Buttons | L13: 1 = Agree | M13: NA | N13: For any response, go to Agree | P13: Set the amount of incentive here, if any. | T13: no | X13: 37.418449 | Y13: =IF(X13="","",X13*Q13) -> 0 | Z13: =IF(T13="yes",Y13,"")
A14: NA | B14: Agree | C14: resp_agree | D14: Are you interested in participating in this survey? [OPERATOR: SINGLE RESPONSE] 1)Yes 2)Not now but another time in the week 3)No | E14: =LEN(D14) -> 134 | F14: Souhaitez-vous participer à cette enquête? [OPÉRATEUR/OPÉRATRICE: RÉPONSE UNIQUE] 1)Oui 2)Pas maintenant, mais à un autre moment de la semaine 3)Non | G14: =LEN(F14) -> 152 | H14: StartRecording | I14: NA | J14: NA | K14: Form Type - Buttons | L14: 1 = resp_firstname 2 = WhenCallBack 3 = resp_refusalwhy | M14: NA | N14: if Agree = 1, go to resp_firstname if Agree = 2, go to WhenCallBack if Agree = 3, go to resp_refusalwhy | Q14: 1 | T14: no | X14: 3.8059516 | Y14: =IF(X14="","",X14*Q14) -> 3.8059516 | Z14: =IF(T14="yes",Y14,"")
A15: NA | B15: resp_refusalwhy | C15: resp_refusalwhy | D15: Please let us know why you have REFUSED to take the survey. [OPERATOR: SINGLE RESPONSE] 1)Not interested 2)Do not want to be recorded 3)Other [specify] | E15: =LEN(D15) -> 153 | F15: Pourriez-vous m'indiquer pourquoi vous refusez de répondre à l'enquête. [OPÉRATEUR/OPÉRATRICE: RÉPONSE UNIQUE] 1)Pas intéressé 2)Ne veut pas être enregistré 3)Autre [préciser] | G15: =LEN(F15) -> 178 | H15: Open Ended - Single Choice | I15: NA | J15: NA | K15: Form Type - RadioList | L15: Any Response = Refusal | M15: NA | N15: For any response, go to Refusal | Q15: 1 | T15: no | X15: 0 | Y15: =IF(X15="","",X15*Q15) -> 0 | Z15: =IF(T15="yes",Y15,"")
A16: NA | B16: WhenCallBack | C16: resp_whencallback | D16: When would it be a good time to call you back? [RECORD HH/MM/DD/MM OF CALLBACK] | E16: =LEN(D16) -> 80 | F16: À quel moment pourrais-je vous rappeler? [ENREGISTRER HH/MM/JJ/MM DU RAPPEL] | G16: =LEN(F16) -> 77 | H16: Open Ended | I16: NA | J16: NA | K16: Form Type - TextBox IsCallBackDemographic | L16: Any Response = CallbackMessageEN | M16: NA | N16: For any response, go to CallbackMessageEN | Q16: 1 | T16: no | X16: 0 | Y16: =IF(X16="","",X16*Q16) -> 0 | Z16: =IF(T16="yes",Y16,"")
A17: NA | B17: CallbackMessageEN | C17: callbackmessage_en | D17: Thank you, we will call you back at {WhenCallBack} you requested. Thank you again and have a great day! [OPERATOR: ENTER CALL NOTES BELOW, WHO YOU SPOKE TO AND WHAT THEY SAID] | E17: =LEN(D17) -> 176 | F17: Merci, nous vous rappellerons à {WhenCallBack}. Merci encore et bonne journée! [OPÉRATEUR/OPÉRATRICE: SAISIR LES DONNÉES D'APPEL CI-DESSOUS, LE NOM DE LA PERSONNE À LAQUELLE VOUS AVEZ PARLÉ ET CE QU'ELLE A DIT] | G17: =LEN(F17) -> 211 | H17: Open Ended | I17: NA | J17: NA | K17: Form Type - TextBox | L17: Any Response = End poll callback | M17: NA | N17: NA | Q17: 1 | T17: no | X17: 0 | Y17: =IF(X17="","",X17*Q17) -> 0 | Z17: =IF(T17="yes",Y17,"")
A18: NA | B18: Ineligible | C18: NA | D18: You are ineligible for this survey. Thank you for your time and please look out for future surveys! | E18: =LEN(D18) -> 99 | F18: Vous êtes inéligible pour participer à cette enquête. Merci pour votre temps et renseignez-vous sur les prochains sondages! | G18: =LEN(F18) -> 123 | H18: NA | I18: NA | J18: NA | K18: NA | L18: End Poll Ineligible | M18: NA | N18: NA | Q18: 1 | T18: no | X18: 0 | Y18: =IF(X18="","",X18*Q18) -> 0 | Z18: =IF(T18="yes",Y18,"")
A19: NA | B19: Refusal | C19: NA | D19: Thank you for your time, you will be removed from today's survey. | E19: =LEN(D19) -> 65 | F19: Merci pour votre temps. Vous allez être retiré de l'enquête d'aujourd'hui. | G19: =LEN(F19) -> 74 | H19: NA | I19: NA | J19: NA | K19: NA | L19: End poll declined | M19: NA | N19: NA | Q19: 1 | T19: no | X19: 0 | Y19: =IF(X19="","",X19*Q19) -> 0 | Z19: =IF(T19="yes",Y19,"")
A20: B. GENERAL INFORMATION & ELIGIBILITY CRITERIA | Y20: =IF(X20="","",X20*Q20) | Z20: =IF(T20="yes",Y20,"")
A21: NA | B21: resp_firstname | C21: resp_firstname | D21: What is your first name? [OPERATOR: RECORD THE RESPONDENT'S FIRST NAME. ENTER 999 FOR REFUSED.] | E21: =LEN(D21) -> 96 | F21: Quel est votre prénom? [OPÉRATEUR/OPÉRATRICE: SAISIR LE PRÉNOM DE LA PERSONNE INTÉRROGÉE. SAISIR 999 POUR REFUSÉ.] | G21: =LEN(F21) -> 116 | H21: Open Ended | I21: NA | J21: NA | K21: Form Type - TextBox | L21: Any Response = resp_lastname | M21: NA | N21: For any response, go to resp_lastname | Q21: =1 -> 1 | T21: yes | X21: 25.874027 | Y21: =IF(X21="","",X21*Q21) -> 25.874027 | Z21: =IF(T21="yes",Y21,"") -> 25.874027
A22: NA | B22: resp_lastname | C22: resp_lastname | D22: What is your last name? [OPERATOR: RECORD THE RESPONDENT'S LAST NAME. ENTER 999 FOR REFUSED.] | E22: =LEN(D22) -> 95 | F22: Quel est votre nom de famille? [OPÉRATEUR/OPÉRATRICE: SAISIR LE NOM DE FAMILLE DE LA PERSONNE INTÉRROGÉE. SAISIR 999 POUR REFUSÉ.] | G22: =LEN(F22) -> 132 | H22: Open Ended | I22: NA | J22: NA | K22: Form Type - TextBox | L22: Any Response = resp_age | M22: NA | N22: For any response, go to resp_age | Q22: =1 -> 1 | T22: yes | X22: 8.5994816 | Y22: =IF(X22="","",X22*Q22) -> 8.5994816 | Z22: =IF(T22="yes",Y22,"") -> 8.5994816
A23: 1 | B23: resp_age | C23: resp_age | D23: How old are you? [OPERATOR: RECORD AGE IN NUMBER OF YEARS. ROUND UP TO NEAREST WHOLE NUMBER. IF THE RESPONDENT GIVES BIRTH YEAR, REPEAT THE QUESTION. ENTER 00 FOR DON'T KNOW.] | E23: =LEN(D23) -> 177 | F23: Quel âge avez-vous [en années]? [OPÉRATEUR/OPÉRATRICE: SAISIR L'ÂGE EN ANNÉES. ARRONDIR AU NOMBRE ENTIER LE PLUS PROCHE. SI LE RÉPONDANT DONNE SON ANNÉE DE NAISSANCE, RÉPÉTER LA QUESTION. SAISIR 00 POUR "NE SAIT PAS".] | G23: =LEN(F23) -> 219 | H23: Range | I23: NA | J23: NA | K23: Form Type - TextBox | L23: 0-17 = Ineligible 18-100 = resp_gender 00 = Ineligible | M23: NA | N23: Only respondents from 18-100 will be eligible for the survey. | Q23: =1 -> 1 | T23: yes | X23: 9.8907185 | Y23: =IF(X23="","",X23*Q23) -> 9.8907185 | Z23: =IF(T23="yes",Y23,"") -> 9.8907185
A24: =A23+1 -> 2 | B24: resp_gender | C24: resp_gender | D24: What is the gender of the respondent? [OPERATOR: DO NOT ASK THIS QUESTION OUT LOUD. LISTEN TO THE VOICE AND SELECT THE GENDER.] 1)Male 2)Female 3)DON'T KNOW 4)REFUSED | E24: =LEN(D24) -> 168 | F24: Quel est le sexe du répondant? [OPÉRATEUR/OPÉRATRICE: NE PAS POSER CETTE QUESTION À VOIX HAUTE. ÉCOUTER LA VOIX ET DÉTERMINER LE SEXE.] 1)Homme 2)Femme 3)NE SAIT PAS 4)REFUSÉ | G24: =LEN(F24) -> 178 | H24: Single Choice | I24: NA | J24: NA | K24: Form Type - Buttons | L24: 1-4 = phone_number_conf | M24: NA | N24: For any response, go to phone_number_conf | Q24: =1 -> 1 | T24: yes | X24: 1.7156482 | Y24: =IF(X24="","",X24*Q24) -> 1.7156482 | Z24: =IF(T24="yes",Y24,"") -> 1.7156482
Q25: =1 -> 1 | Y25: =IF(X25="","",X25*Q25) | Z25: =IF(T25="yes",Y25,"")
B26: phone_number_conf | C26: phone_number_conf | D26: Is the phone number I am calling you on yours or a household members? [OPERATOR: SINGLE RESPONSE.] 1)YES 2)NO 3)DON'T KNOW 4)REFUSED | E26: =LEN(D26) -> 134 | F26: Le numéro de téléphone sur lequel je vous appelle est-il le vôtre ou celui d'un membre de votre famille? [OPÉRATEUR/OPÉRATRICE: RÉPONSE UNIQUE.] 1)Oui 2)Non 3)NE SAIT PAS 4)REFUSÉ | G26: =LEN(F26) -> 181 | H26: Single Choice | I26: NA | J26: NA | K26: Form Type - Buttons | L26: 1 = contact_2 2 = phone_number_personal 3-4 = contact_2 | M26: NA | N26: if phone_number_conf = 1, go to contact_2 if phone_number_conf = 2, go to phone_number_personal if phone_number_conf = 3-4, go to contact_2 | Q26: =1 -> 1 | T26: yes - panel | X26: 6.375237 | Y26: =IF(X26="","",X26*Q26) -> 6.375237 | Z26: =IF(T26="yes",Y26,"")
B27: phone_number_personal | C27: phone_number_pers | D27: What is your phone number? [OPERATOR: RECORD THE NUMBER GIVEN] | E27: =LEN(D27) -> 63 | F27: Quel est votre numéro de téléphone? [OPÉRATEUR/OPÉRATRICE: SAISIR LE NUMERO.] | G27: =LEN(F27) -> 78 | H27: Open Ended | I27: NA | J27: NA | K27: Form Type - TextBox | L27: Any Response = contact_2 | M27: NA | N27: For any response, go to contact_2 | Q27: =1 -> 1 | T27: yes - panel | X27: 28.700001 | Y27: =IF(X27="","",X27*Q27) -> 28.700001 | Z27: =IF(T27="yes",Y27,"")
B28: contact_2 | C28: contact_2 | D28: Can you give me an additonal phone number belonging to you, a relative or a friend at which you can be reached? [OPERATOR: SINGLE RESPONSE.] 1)YES - mine 2)YES - friend or relative 3)NO 4)DON'T KNOW 5)REFUSED | E28: =LEN(D28) -> 211 | F28: Pouvez-vous me donner un autre numéro de téléphone, le vôtre, celui d'un parent ou d'un ami, auquel vous pouvez être joint? [OPÉRATEUR/OPÉRATRICE: RÉPONSE UNIQUE.] 1)Oui - le mien 2)Oui - celui d'un ami ou d'un parent 3)Non 4)NE SAIT PAS 5)REFUSÉ | G28: =LEN(F28) -> 248 | H28: Single Choice | I28: NA | J28: NA | K28: Form Type - Buttons | L28: 1-2 = phone_number_2 3-5 = hh_admin1 | M28: NA | N28: if contact_2 = 1-2, go to phone_number_2 if contact_2 = 3-5, go to contact_3 | Q28: =1 -> 1 | T28: yes - panel | X28: 10.141817 | Y28: =IF(X28="","",X28*Q28) -> 10.141817 | Z28: =IF(T28="yes",Y28,"")
B29: phone_number_2 | C29: phone_number_2 | D29: What is the additional phone number? [OPERATOR: RECORD THE NUMBER GIVEN] | E29: =LEN(D29) -> 73 | F29: Quel est cet autre numéro de téléphone? [OPÉRATEUR/OPÉRATRICE: SAISIR LE NUMERO.] | G29: =LEN(F29) -> 82 | H29: Open Ended | I29: NA | J29: NA | K29: Form Type - TextBox | L29: Any Response = contact_2_name | M29: NA | N29: For any response, go to contact_2_name | Q29: =1 -> 1 | T29: yes - panel | X29: 21.659983 | Y29: =IF(X29="","",X29*Q29) -> 21.659983 | Z29: =IF(T29="yes",Y29,"")
B30: contact_2_name | C30: contact_2_name | D30: What is the name of the contact? [OPERATOR: RECORD THE NAME OF THE CONTACT FOR THE PHONE NUMBER.] | E30: =LEN(D30) -> 98 | F30: Quel est le nom du contact associé à ce numéro de téléphone? [OPÉRATEUR/OPÉRATRICE: SAISIR LENOM DU CONTACT POUR CE NUMERO DE TÉLÉPHONE.] | G30: =LEN(F30) -> 138 | H30: Open Ended | I30: NA | J30: Send if "contact_2" "Equals" "YES - friend or relative", if not satisfied go to "contact_3" | K30: Form Type - TextBox | L30: Any Response = contact_3 | M30: NA | N30: Asked if "contact_2" "Equals" "YES - friend or relative". Otherwise, it skips to "contact_3". For any response, go to contact_3 | Q30: =1 -> 1 | T30: yes - panel | X30: 11.821796 | Y30: =IF(X30="","",X30*Q30) -> 11.821796 | Z30: =IF(T30="yes",Y30,"")
B31: contact_3 | C31: contact_3 | D31: Can you give me an additonal phone number belonging to you, a relative or a friend at which you can be reached? [OPERATOR: SINGLE RESPONSE.] 1)YES - mine 2)YES - friend or relative 3)NO 4)DON'T KNOW 5)REFUSED | E31: =LEN(D31) -> 211 | F31: Pouvez-vous me donner un autre numéro de téléphone, le vôtre, celui d'un parent ou d'un ami, auquel vous pouvez être joint? [OPÉRATEUR/OPÉRATRICE: RÉPONSE UNIQUE.] 1)Oui - le mien 2)Oui - celui d'un ami ou d'un parent 3)Non 4)NE SAIT PAS 5)REFUSÉ | G31: =LEN(F31) -> 248 | H31: Single Choice | I31: NA | J31: NA | K31: Form Type - Buttons | L31: 1-2= phone_number_3 3-5 = hh_admin1 | M31: NA | N31: if contact_3 = 1-2, go to phone_number_3 if contact_3 = 3-5, go to hh_admin1 | Q31: =1 -> 1 | T31: yes - panel | X31: 3.163594 | Y31: =IF(X31="","",X31*Q31) -> 3.163594 | Z31: =IF(T31="yes",Y31,"")
B32: phone_number_3 | C32: phone_number_3 | D32: What is the additional phone number? [OPERATOR: RECORD THE NUMBER GIVEN] | E32: =LEN(D32) -> 73 | F32: Quel est cet autre numéro de téléphone? [OPÉRATEUR/OPÉRATRICE: SAISIR LE NUMERO.] | G32: =LEN(F32) -> 82 | H32: Open Ended | I32: NA | J32: NA | K32: Form Type - TextBox | L32: Any Response = contact_3_name | M32: NA | N32: For any response, go to contact_3_name | Q32: =1 -> 1 | T32: yes - panel | X32: 10.830144 | Y32: =IF(X32="","",X32*Q32) -> 10.830144 | Z32: =IF(T32="yes",Y32,"")
B33: contact_3_name | C33: phone_number_3_name | D33: What is the name of the contact? [OPERATOR: RECORD THE NAME OF THE CONTACT FOR THE PHONE NUMBER.] | E33: =LEN(D33) -> 98 | F33: Quel est le nom du contact associé à ce numéro de téléphone? [OPÉRATEUR/OPÉRATRICE: SAISIR LENOM DU CONTACT POUR CE NUMERO DE TÉLÉPHONE.] | G33: =LEN(F33) -> 138 | H33: Open Ended | I33: NA | J33: Send if "contact_3" "Equals" "YES - friend or relative", if not satisfied go to "hh_admin1" | K33: Form Type - TextBox | L33: Any Response = hh_admin1 | M33: NA | N33: Asked if "contact_3" "Equals" "YES - friend or relative". Otherwise, it skips to "hh_admin1". For any response, go to hh_admin1 | Q33: =1 -> 1 | T33: yes - panel | X33: 11.260417 | Y33: =IF(X33="","",X33*Q33) -> 11.260417 | Z33: =IF(T33="yes",Y33,"")
Q34: =1 -> 1 | Y34: =IF(X34="","",X34*Q34) | Z34: =IF(T34="yes",Y34,"")
A35: 3 | B35: hh_admin1 | C35: hh_admin1 | D35: Currently, in which region does your household reside? [hint: household consists of all members living together, sharing resources & eating from the same pot.] [OPERATOR: SINGLE SELECTION.] 1)BAS-UELE 2)EQUATEUR 3)HAUT-KATANGA 4)HAUT-LOMAMI 5)HAUT-UELE 6)ITURI 7)KASAI 8)KASAI-CENTRAL 9)KASAI-ORIENTAL 10)KINSHASA 11)KONGO CENTRAL 12)KWANGO 13)KWILU 14)LOMAMI 15)LUALABA 16)MAI-NDOMBE 17)MANIEMA 18)MONGALA 19)NORD-KIVU 20)NORD-UBANGI 21)SANKURU 22)SUD-KIVU 23)SUD-UBANGI 24)TANGANYIKA 25)TSHOPO 26)TSHUAPA 27)DON'T KNOW 28)REFUSED | E35: =LEN(D35) -> 533 | F35: Actuellement, dans quel region votre ménage vit-il ? [conseil: le ménage est composé de toutes les personnes vivant ensemble, partageant leurs ressources et mangeant dans une marmite commune.] [OPÉRATEUR/OPÉRATRICE: RÉPONSE UNIQUE.] 1)BAS-UELE 2)EQUATEUR 3)HAUT-KATANGA 4)HAUT-LOMAMI 5)HAUT-UELE 6)ITURI 7)KASAI 8)KASAI-CENTRAL 9)KASAI-ORIENTAL 10)KINSHASA 11)KONGO CENTRAL 12)KWANGO 13)KWILU 14)LOMAMI 15)LUALABA 16)MAI-NDOMBE 17)MANIEMA 18)MONGALA 19)NORD-KIVU 20)NORD-UBANGI 21)SANKURU 22)SUD-KIVU 23)SUD-UBANGI 24)TANGANYIKA 25)TSHOPO 26)TSHUAPA 27)DON'T KNOW 28)REFUSED | G35: =LEN(F35) -> 576 | H35: Single Choice | I35: NA | J35: NA | K35: Form Type - Buttons IsDemographic - ADM1 | L35: 1 = hh_admin2_1 2-3 = Ineligible | M35: NA | N35: The administrative information will be updated by GeoPoll based on the sample design document and the administrative boundaries provided by the dashboard team after the questionnaire validation. | Q35: =1 -> 1 | T35: yes | X35: 13.957259 | Y35: =IF(X35="","",X35*Q35) -> 13.957259 | Z35: =IF(T35="yes",Y35,"") -> 13.957259
A36: =A35+1 -> 4 | B36: hh_admin2_1 | C36: hh_admin2_1 | D36: Currently, in which territory do your household live in? [OPERATOR: DO NOT READ THE OPTIONS. SINGLE SELECTION] 1)ARIWARA 2)ARU 3)ARU CITY 4)BUNIA 5)DJUGU 6)INGBOKOLO 7)IRUMU 8)MAHAGI 9)MAHAGI CITY 10)MAMBASA 11)MONGWALU 12)DON'T KNOW 13)REFUSED | E36: =LEN(D36) -> 247 | F36: Dans quelle territoire vit votre ménage actuellement? [OPERATEUR/OPERATRICE: NE LISEZ PAS LES OPTIONS. SEULEMENT UNE REPONSE] 1)ARIWARA 2)ARU 3)ARU CITY 4)BUNIA 5)DJUGU 6)INGBOKOLO 7)IRUMU 8)MAHAGI 9)MAHAGI CITY 10)MAMBASA 11)MONGWALU 12) NE SAIT PAS 13)REFUSE | G36: =LEN(F36) -> 262 | H36: Single Choice | I36: NA | J36: NA | K36: Form Type - Buttons IsDemographic - ADM2 | L36: 1 = hh_agricactivity 2-3 = Ineligible | M36: NA | Q36: =1 -> 1 | T36: yes | X36: 7.954999 | Y36: =IF(X36="","",X36*Q36) -> 7.954999 | Z36: =IF(T36="yes",Y36,"") -> 7.954999
B37: hh_admin2_2 | D37: Currently, in which territory do your household live in? [OPERATOR: DO NOT READ THE OPTIONS. SINGLE SELECTION] 1)DEKESE 2)ILEBO 3)ILEBO CITY 4)KAMONIA 5)LUEBO 6)LUEBO CITY 7)MWEKA 8)TSHIKAPA 9)DON'T KNOW 10)REFUSED | F37: Dans quelle territoire vit votre ménage actuellement? [OPERATEUR/OPERATRICE: NE LISEZ PAS LES OPTIONS. SEULEMENT UNE REPONSE] 1)DEKESE 2)ILEBO 3)ILEBO CITY 4)KAMONIA 5)LUEBO 6)LUEBO CITY 7)MWEKA 8)TSHIKAPA 9)NE SAIT PAS 10)REFUSE | H37: Single Choice
B38: hh_admin2_3 | D38: Currently, in which territory do your household live in? [OPERATOR: DO NOT READ THE OPTIONS. SINGLE SELECTION] 1)DEMBA 2)DIBAYA 3)DMBELENGE 4)KANANGA 5)KAZUMBA 6)LUIZA 7)TSHIMBULU 8)DON'T KNOW 9)REFUSED | F38: Dans quelle territoire vit votre ménage actuellement? [OPERATEUR/OPERATRICE: NE LISEZ PAS LES OPTIONS. SEULEMENT UNE REPONSE] 1)DEMBA 2)DIBAYA 3)DMBELENGE 4)KANANGA 5)KAZUMBA 6)LUIZA 7)TSHIMBULU 8)NE SAIT PAS 9)REFUSE | H38: Single Choice
B39: hh_admin2_4 | D39: Currently, in which territory do your household live in? [OPERATOR: DO NOT READ THE OPTIONS. SINGLE SELECTION] 1)KABEYA-KAMWANGA 2)KATANDA 3)LUKALABA 4)LUPATAPATA 5)MBUJI-MAYI 6)MIABI 7)MIABI CITY 8)TSHILENGE 9)TSHILENGE CITY 10)DON'T KNOW 11)REFUSED | F39: Dans quelle territoire vit votre ménage actuellement? [OPERATEUR/OPERATRICE: NE LISEZ PAS LES OPTIONS. SEULEMENT UNE REPONSE] 1)KABEYA-KAMWANGA 2)KATANDA 3)LUKALABA 4)LUPATAPATA 5)MBUJI-MAYI 6)MIABI 7)MIABI CITY 8)TSHILENGE 9)TSHILENGE CITY 10)NE SAIT PAS 11)REFUSE | H39: Single Choice
B40: hh_admin2_5 | D40: Currently, in which territory do your household live in? [OPERATOR: DO NOT READ THE OPTIONS. SINGLE SELECTION] 1)BENI 2)BUTEMBO 3)GOMA 4)LUBERO 5)MASISI 6)NYIRAGONGO 7)OICHA 8)OICHA CITY 9)RUTSHURU 10)RUTSHURU CITY 11)WALIKAME 12)DON'T KNOW 13)REFUSED | F40: Dans quelle territoire vit votre ménage actuellement? [OPERATEUR/OPERATRICE: NE LISEZ PAS LES OPTIONS. SEULEMENT UNE REPONSE] 1)BENI 2)BUTEMBO 3)GOMA 4)LUBERO 5)MASISI 6)NYIRAGONGO 7)OICHA 8)OICHA CITY 9)RUTSHURU 10)RUTSHURU CITY 11)WALIKAME 12)NE SAIT PAS 13)REFUSE | H40: Single Choice
B41: hh_admin2_6 | D41: Currently, in which territory do your household live in? [OPERATOR: DO NOT READ THE OPTIONS. SINGLE SELECTION] 1)BOSOBOLO 2)BUSINGA 3)GBADOLITE 4)MOBAYI-MBONGO 5)MOBAYI-MBONGO CITY 6)YAKOMA 7)DON'T KNOW 8)REFUSED | F41: Dans quelle territoire vit votre ménage actuellement? [OPERATEUR/OPERATRICE: NE LISEZ PAS LES OPTIONS. SEULEMENT UNE REPONSE] 1)BOSOBOLO 2)BUSINGA 3)GBADOLITE 4)MOBAYI-MBONGO 5)MOBAYI-MBONGO CITY 6)YAKOMA 7)NE SAIT PAS 8)REFUSE | H41: Single Choice
B42: hh_admin2_7 | D42: Currently, in which territory do your household live in? [OPERATOR: DO NOT READ THE OPTIONS. SINGLE SELECTION] 1)BARAKA 2)BUKAVU 3)FIZI 4)IDJWI 5)KABARE 6)KALEHE 7)KAMITUGA 8)MWENGA 9)SHABUNDA 10)SHABUNDA CITY 11)UVIRA 12)UVIRA CITY 13)WALUNGU 14)DON'T KNOW 15)REFUSED | F42: Dans quelle territoire vit votre ménage actuellement? [OPERATEUR/OPERATRICE: NE LISEZ PAS LES OPTIONS. SEULEMENT UNE REPONSE] 1)BARAKA 2)BUKAVU 3)FIZI 4)IDJWI 5)KABARE 6)KALEHE 7)KAMITUGA 8)MWENGA 9)SHABUNDA 10)SHABUNDA CITY 11)UVIRA 12)UVIRA CITY 13)WALUNGU 14)NE SAIT PAS 15)REFUSE | H42: Single Choice
B43: hh_admin2_8 | D43: Currently, in which territory do your household live in? [OPERATOR: DO NOT READ THE OPTIONS. SINGLE SELECTION] 1)BUDJALA 2)GEMENA 3)GEMENA CITY 4)KUNGU 5)LIBENGE 6)ZONGO 7)DON'T KNOW 8)REFUSED | F43: Dans quelle territoire vit votre ménage actuellement? [OPERATEUR/OPERATRICE: NE LISEZ PAS LES OPTIONS. SEULEMENT UNE REPONSE] 1)BUDJALA 2)GEMENA 3)GEMENA CITY 4)KUNGU 5)LIBENGE 6)ZONGO 7)NE SAIT PAS 8)REFUSE | H43: Single Choice
B44: hh_admin2_9 | D44: Currently, in which territory do your household live in? [OPERATOR: DO NOT READ THE OPTIONS. SINGLE SELECTION] 1)KABALO 2)KALEMIE 3) KAOZE 4)KONGOLO 5)KONGOLO CITY 6)MANONO 7)MANONO CITY 8)MOBA 9)NYUNZU 10)DON'T KNOW 11)REFUSED | F44: Dans quelle territoire vit votre ménage actuellement? [OPERATEUR/OPERATRICE: NE LISEZ PAS LES OPTIONS. SEULEMENT UNE REPONSE] 1)KABALO 2)KALEMIE 3) KAOZE 4)KONGOLO 5)KONGOLO CITY 6)MANONO 7)MANONO CITY 8)MOBA 9)NYUNZU 10)NE SAIT PAS 11)REFUSE | H44: Single Choice
B45: quotareached | C45: quotareached | D45: [OPERATOR: DO NOT READ. ANSWER QUESTION BELOW.] THIS RESPONDENT REPORTED THEY LIVE IN: {ADM1} {ADM2} 1)THE GOAL FOR THIS LOCATION HAS BEEN ACHIEVED - END SURVEY 2)THE GOAL FOR THIS LOCATION IS OPEN - CONTINUE SURVEY | E45: =LEN(D45) -> 218 | F45: [OPÉRATEUR/OPÉRATRICE: NE PAS LIRE. RÉPONDRE À LA QUESTION CI-DESSOUS.] CE RÉPONDANT DIT VIVRE À: {ADM1} {ADM2} 1)L'OBJECTIF DANS CETTE ZONE A ÉTÉ ATTEINT - FIN DU SONDAGE 2)L'OBJECTIF DANS CETTE ZONE N'EST PAS ENCORE ATTEINT - CONTINUER LE SONDAGE | G45: =LEN(F45) -> 251 | H45: Single Choice | I45: NA | J45: NA | K45: Form Type - Buttons | L45: 1 = End Poll Quota Reached 2 = hh_agricactivity | M45: NA
A46: 1 | B46: hh_agricactivity | C46: hh_agricactivity | D46: Has anybody in your household produced crops or livestock for household consumption or for sale in the past 12 months, including household members currently away for transhumance? [OPERATOR: SINGLE RESPONSE. THIS IS THE MAIN SCREENING QUESTION.] [HINT FOR PROBING: Do you cultivate any plants to sale or consume? Do you raise any animals with the intent of selling or consuming them or their products like meat, milk, wool or leather? Is one of your household member currently away with cattle or other animals for transhumance?] 1)Yes - crop production 2)Yes - livestock production 3)Yes - both crop and livestock production 4)No 5)DON'T KNOW 6)REFUSED | E46: =LEN(D46) -> 658 | F46: Est-ce que quelqu'un dans votre ménage a produit des cultures ou du bétail pour la consommation du ménage ou pour la vente au cours des 12 derniers mois, y compris des membres du ménage actuellement partis pour la transhumance? [OPÉRATEUR / OPÉRATRICE : RÉPONSE UNIQUE. IL S'AGIT DE LA PRINCIPALE QUESTION DE SÉLECTION.] [CONSEILS POUR PRÉCISER : Cultivez-vous des végétaux afin de les vendre ou de les consommer ? Élevez-vous des animaux afin de les vendre ou de les consommer, y compris les produits issus de l'élevage, comme la viande, le lait, la laine ou le cuir ? L'un des membres de votre ménage est-il actuellement parti avec du bétail pour la transhumance ?] 1)Oui - production végétale 2)Oui - production animale 3)Oui - production végétale et animale 4)Non 5)NE SAIT PAS 6)REFUSÉ | G46: =LEN(F46) -> 794 | H46: Single Choice | I46: NA | J46: NA | K46: Form Type - Buttons | L46: 1-4 = resp_id 5-6 = Ineligible | M46: NA | N46: if hh_agricactivity = 1-4, go to resp_id. Otherwise, the respondent is ineligible. | Q46: =1 -> 1 | T46: yes | X46: 24.410839 | Y46: =IF(X46="","",X46*Q46) -> 24.410839 | Z46: =IF(T46="yes",Y46,"") -> 24.410839
Q47: =1 -> 1 | Y47: =IF(X47="","",X47*Q47) | Z47: =IF(T47="yes",Y47,"")
A48: B. GENERAL HOUSEHOLD INFORMATION | Y48: =IF(X48="","",X48*Q48) | Z48: =IF(T48="yes",Y48,"")
Q49: =1 -> 1 | Y49: =IF(X49="","",X49*Q49) | Z49: =IF(T49="yes",Y49,"")
A50: =A46+1 -> 2 | B50: resp_id | C50: resp_id | D50: Are you the head of household? [OPERATOR: SINGLE RESPONSE.] 1)Yes 2)No 3)DON'T KNOW 4)REFUSED | E50: =LEN(D50) -> 97 | F50: Êtes-vous le chef de ménage? [OPÉRATEUR/OPÉRATRICE: RÉPONSE UNIQUE.] 1)Oui 2)Non 3)NE SAIT PAS 4)REFUSÉ | G50: =LEN(F50) -> 105 | H50: Single Choice | I50: NA | J50: NA | K50: Form Type - Buttons | L50: 1 = hh_education 2-4 = hh_gender | M50: NA | N50: if resp_id = 1, go to hh_education. Otherwise, go to hh_gender. | Q50: 1 | T50: yes | X50: 10.5 | Y50: =IF(X50="","",X50*Q50) -> 10.5 | Z50: =IF(T50="yes",Y50,"") -> 10.5
A51: =A50+1 -> 3 | B51: hh_gender | C51: hh_gender | D51: Is the head of your household male or female? [OPERATOR: SINGLE RESPONSE.] 1)Male 2)Female 3)DON'T KNOW 4)REFUSED | E51: =LEN(D51) -> 116 | F51: Le chef de votre ménage est-il un homme ou une femme? [OPÉRATEUR/OPÉRATRICE: RÉPONSE UNIQUE.] 1)Homme 2)Femme 3)NE SAIT PAS 4)REFUSÉ | G51: =LEN(F51) -> 134 | H51: Single Choice | I51: NA | J51: NA | K51: Form Type - Buttons | L51: 1-4 = hh_education | M51: NA | N51: if hh_gender = 1-4, go to hh_education. | Q51: =1 -> 1 | T51: yes | X51: 10.504534 | Y51: =IF(X51="","",X51*Q51) -> 10.504534 | Z51: =IF(T51="yes",Y51,"") -> 10.504534
Q52: =1 -> 1 | Y52: =IF(X52="","",X52*Q52) | Z52: =IF(T52="yes",Y52,"")
A53: =A51+1 -> 4 | B53: hh_education | C53: hh_education | D53: What is the educational level attained by the head of household? [OPERATOR: SINGLE RESPONSE.] 1)None or did not complete primary school 2)Completed primary school 3)Completed secondary school 4)Completed higher education [University / College] degree 5)Religious or informal education only 6)DON'T KNOW 7)REFUSED | E53: =LEN(D53) -> 314 | F53: Quel est le niveau d'éducation du chef de votre ménage ? [OPÉRATEUR/OPÉRATRICE: RÉPONSE UNIQUE.] 1)Aucun ou n'a pas terminé l'école primaire 2)A terminé l'école primaire 3)A terminé l'école secondaire 4)Diplôme de l'enseignement supérieur [Université] 5)Enseignement religieux ou informel uniquement 6)NE SAIT PAS 7)REFUSÉ | G53: =LEN(F53) -> 324 | H53: Single Choice | I53: NA | J53: NA | K53: Form Type - Buttons | L53: 1-7 = hh_wealth | M53: NA | N53: if hh_education = 1-7, go to hh_wealth. | Q53: =1 -> 1 | T53: yes | X53: 12.421899 | Y53: =IF(X53="","",X53*Q53) -> 12.421899 | Z53: =IF(T53="yes",Y53,"") -> 12.421899
Q54: =1 -> 1 | Y54: =IF(X54="","",X54*Q54) | Z54: =IF(T54="yes",Y54,"")
A55: 10 | B55: hh_wealth_water | C55: hh_wealth_water | D55: Where does the water that you drink at home come from? [OPERATOR: SINGLE CHOICE.] 1)Private tap from piped water 2)Public tap 3)Protected well 4)Bottled water 5)Other safe source 6)River 7)Unprotected well 8)Spring water 9)Surface water [e.g. canals, ponds, dams] 10)Other unsafe source 11)DON'T KNOW 12)REFUSED | E55: =LEN(D55) -> 313 | F55: Où vous procurez-vous habituellement l'eau que vous buvez dans votre foyer? [OPÉRATEUR/OPÉRATRICE: RÉPONSE UNIQUE.] 1)Robinet privé avec eau courante 2)Robinet public 3)Puits protégé 4)Eau en bouteille 5)Autre source sûre 6)Rivière 7)Puits non protégé 8)Eau de source 9)Eaux de surface [par ex. canaux, étangs, barrages] 10)Autre source non sûre 11)NE SAIT PAS 12)REFUSÉ | G55: =LEN(F55) -> 372 | H55: Single Choice | I55: NA | J55: NA | K55: Form Type - Buttons | L55: 1-12 = [income_main OR other optional question] | M55: NA | N55: For any response, go to [income_main OR other optional question] | P55: Select wealth indicators based on baseline information available; you can delete those that you do not want to use. If none of these indicators work in the context of your country, other wealth proxies are proposed in the optional questions below. Remember that baseline data will be necessary, and the variable should be defined properly in the "weight_input_table". | Q55: =1 -> 1 | T55: yes | X55: 16.615656 | Y55: =IF(X55="","",X55*Q55) -> 16.615656 | Z55: =IF(T55="yes",Y55,"") -> 16.615656
A56: 10 | B56: hh_wealth_toilet | C56: hh_wealth_toilet | D56: Where do household members typically go to use a toilet? [OPERATOR: SINGLE CHOICE.] 1)Flush latrine [toilet with water] 2)Traditional pit latrine [no water] 3)Open pit [hole in the ground for excrement without water, roof or wall] 4)Communal latrine [with or without water] 5)None – bush 6)DON'T KNOW 7)REFUSED | E56: =LEN(D56) -> 312 | F56: Quel genre de toilettes les membres de votre ménage utilisent-ils? [OPÉRATEUR/OPÉRATRICE: RÉPONSE UNIQUE.] 1)Latrines à chasse d'eau [toilettes avec eau] 2)Latrines traditionnelles à fosse [sans eau] 3)Fosse ouverte [trou dans le sol pour les excréments, sans eau, toit ni mur] 4)Latrines communautaires [avec ou sans eau] 5)Aucune – brousse 6)NE SAIT PAS 7)REFUSÉ | G56: =LEN(F56) -> 366 | H56: Single Choice | I56: NA | J56: NA | K56: Form Type - Buttons | L56: 1-7 = [income_main OR other optional question] | M56: NA | N56: For any response, go to [income_main OR other optional question] | Q56: =1 -> 1 | T56: yes | X56: 12.600021 | Y56: =IF(X56="","",X56*Q56) -> 12.600021 | Z56: =IF(T56="yes",Y56,"") -> 12.600021
A57: 10 | B57: hh_wealth_light | C57: hh_wealth_light | D57: What is the main source of light in your dwelling? [OPERATOR: SINGLE RESPONSE.] 1)Electricity [from generator or electrical grid] 2)Candle 3)Petrol lamp 4)Lamp with batteries 5)Solar panel 6)Other [no electric supply to the house] 7)DON'T KNOW 8)REFUSED | E57: =LEN(D57) -> 255 | F57: Quelle est la principale source de lumière de votre logement? [OPÉRATEUR/OPÉRATRICE: RÉPONSE UNIQUE.] 1)Électricité [générateur ou réseau électrique] 2)Bougie 3)Lampe à pétrole 4)Lampe à piles 5)Panneaux solaires 6)Autre [pas d'alimentation électrique dans la maison] 7)NE SAIT PAS 8)REFUSÉ | G57: =LEN(F57) -> 292 | H57: Single Choice | I57: NA | J57: NA | K57: Form Type - Buttons | L57: 1-8 = [income_main OR other optional question] | M57: NA | N57: For any response, go to [income_main OR other optional question] | Q57: =1 -> 1 | T57: yes | X57: 11.655923 | Y57: =IF(X57="","",X57*Q57) -> 11.655923 | Z57: =IF(T57="yes",Y57,"") -> 11.655923
Q58: =1 -> 1 | Y58: =IF(X58="","",X58*Q58) | Z58: =IF(T58="yes",Y58,"")
A59: =A57+1 -> 11 | B59: hh_residencetype | C59: hh_residencetype | D59: Which in the following types of residence best describes your residence? [OPERATOR: READ OUT THE OPTIONS. SINGLE RESPONSE.] [HINT: IF RESPONDENT IS ONLY AWAY FROM THE HOUSEHOLD FOR SHORT SEASONAL WORK (<6 MONTHS) OR TRANSHUMANCE, MAKE SURE TO REFER TO THEIR HOUSEHOLD BACK WHERE THEY TYPICALLY ARE LOCATED.] 1)Permanent Resident - you have been living in your village / town for longer than two years and this is what you consider your habitual residence 2)Recent migrant not forcefully displaced - you have been living in your current place of residence for less than two years and you moved there voluntarily for work / family or other reasons that are not related to conflict or natural disaster 3)Returnee - you have only come back to this residence in the last two years after having been forced to move to another location having fled conflict or natural disaster [if return was over 2 years ago the respondent is considered a permanent resident] 4)Internally displaced person [IDP] - you were forced to flee your village or town because of conflict or natural disaster and you are now an internally displaced person in your current place of residence 5)Refugee - you were forced to flee your country because of conflict or natural disaster and you are now a refugee in your current place of residence 6)DON'T KNOW 7)REFUSED | E59: =LEN(D59) -> 1333 | F59: Parmi les propositions suivantes, laquelle décrit le mieux votre statut de résidence? [OPÉRATEUR/OPÉRATRICE: LIRE LES OPTIONS, RÉPONSE UNIQUE]. [CONSEIL: SI LA PERSONNE INTERROGÉE N'EST ÉLOIGNÉE DU FOYER QUE POUR UN TRAVAIL SAISONNIER DE COURTE DURÉE (<6 MOIS) OU POUR LA TRANSHUMANCE, FAIRE RÉFÉRENCE AU FOYER DE RETOUR OÙ ELLE VIT HABITUELLEMENT]. 1)Résident permanent - vous vivez dans votre village/ville depuis plus de deux ans et vous le/la considérez comme votre lieu de résidence habituel 2)Migrant récent non déplacé de force - vous vivez dans votre lieu de résidence actuel depuis moins de deux ans et vous vous y êtes déplacé volontairement pour des raisons professionnelles, familiales ou autres qui ne sont pas liées à un conflit ou à une catastrophe naturelle 3)Personne rapatriée - vous êtes revenu dans votre lieu de résidence au cours des deux dernières années après avoir été contraint de vous déplacer pour fuir un conflit ou une catastrophe naturelle [si le retour a eu lieu il y a plus de deux ans, le répondant est considéré comme un résident permanent] 4)Personne déplacée à l'intérieur de son pays - vous avez été forcé de fuir votre village ou votre ville en raison d'un conflit ou d'une catastrophe naturelle et, dans votre lieu de résidence actuel, vous êtes une personne déplacée à l'intérieur de son propre pays 5)Réfugié - vous avez été forcé de fuir votre pays en raison d'un conflit ou d'une catastrophe naturelle et, dans votre lieu de résidence actuel, vous êtes un réfugié 6)NE SAIT PAS 7)REFUSÉ | G59: =LEN(F59) -> 1534 | H59: Single Choice | I59: NA | J59: NA | K59: Form Type - Buttons | L59: 1-7 = hh_size | M59: NA | N59: For any response, go to [next question] | Q59: =1 -> 1 | T59: no | X59: 13.220665 | Y59: =IF(X59="","",X59*Q59) -> 13.220665 | Z59: =IF(T59="yes",Y59,"")
A60: =A59+1 -> 12 | B60: hh_size | C60: hh_size | D60: How many people are part of the household? [OPERATOR: RECORD NUMBER OF MEMBERS IN HOUSEHOLD. ENTER 88 FOR DON'T KNOW & 99 FOR REFUSED.] [HINT: TO BE A PART OF THE SAME HOUSEHOLD, MEMBERS MUST LIVE UNDER THE SAME ROOF, SHARE THE SAME RESOURCES & EAT FROM THE SAME POT.] | E60: =LEN(D60) -> 269 | F60: De combien de personnes est composé votre ménage? [OPÉRATEUR/OPÉRATRICE: ENREGISTRER LE NOMBRE DE MEMBRES DU MÉNAGE. ENTRER 88 POUR «NE SAIT PAS» ET 99 POUR «REFUSÉ».] [CONSEIL: POUR FAIRE PARTIE D'UN MÊME MÉNAGE, LES MEMBRES DOIVENT VIVRE ENSEMBLE, METTRE EN COMMUN LEURS RESSOURCES ET PARTAGER LEURS REPAS.] | G60: =LEN(F60) -> 310 | H60: Range | I60: NA | J60: NA | K60: Form Type - TextBox | L60: 1-50 = hh_asset_prod 88-88 = hh_asset_prod 99-99 = hh_asset_prod | M60: NA | N60: For any response, go to [next question] | Q60: =1 -> 1 | T60: no | X60: 16.902294 | Y60: =IF(X60="","",X60*Q60) -> 16.902294 | Z60: =IF(T60="yes",Y60,"")
A61: =A60+1 -> 13 | B61: hh_asset_prod | C61: hh_asset_prod_ 1) hh_asset_prod_process 2) hh_asset_prod_farmmach 3) hh_asset_prod_sewing 4) hh_asset_prod_taxi 5) hh_asset_prod_truck 6) hh_asset_prod_other 7) hh_asset_prod_none 8) hh_asset_prod_dk 9) hh_asset_prod_ref | D61: Does your household own any of the following productive assets? [OPERATOR: MULTIPLE RESPONSES POSSIBLE. READ ANSWER OPTIONS OUT LOUD.] 1)Processing assets [e.g. grinding/crushing machine, mill, oil press] 2)Farm machinery [e.g. tractor, plough, sickle, etc.] 3)Sewing machine or weaving tool 4)Taxi 5)Truck 6)Other productive machines or assets 7)No productive machines or assets 8)DON'T KNOW 9)REFUSED | E61: =LEN(D61) -> 406 | F61: Votre ménage possède-t-il l'un des actifs productifs suivants? [OPÉRATEUR / OPÉRATRICE : PLUSIEURS RÉPONSES POSSIBLES. LIRE LES OPTIONS DE RÉPONSE À HAUTE VOIX.] 1)Actifs de transformation [par exempe broyeur, moulin, presse à huile] 2)Machine agricole [par exemple tracteur, charrue, faucille, etc.] 3)Machine à coudre ou métier à tisser 4)Taxi 5)Camion 6)Autres machines ou actifs productifs 7)Aucune machine ou actif productif 8)NE SAIT PAS 9)REFUSÉ | G61: =LEN(F61) -> 455 | H61: Select All That Apply | I61: NA | J61: NA | K61: Form Type - Checklist 7,8,9 = IsNone | L61: 1-9 = hh_asset_transp | M61: 1)hh_asset_prod_process 2)hh_asset_prod_farmmach 3)hh_asset_prod_sewing 4)hh_asset_prod_taxi 5)hh_asset_prod_truck 6)hh_asset_prod_other 7)hh_asset_prod_none 8)hh_asset_prod_dk 9)hh_asset_prod_ref | N61: For any response, go to [next question] | P61: This wealth indicator may be useful to Identify poor households in middle income countries. It could be interesting for F2F surveys, to be used as baseline reference for follow-up surveys. | Q61: =1 -> 1 | T61: no | X61: 16.957804 | Y61: =IF(X61="","",X61*Q61) -> 16.957804 | Z61: =IF(T61="yes",Y61,"")
A62: =A61+1 -> 14 | B62: hh_asset_transp | C62: hh_asset_transp_ 1) hh_asset_transp_bici 2) hh_asset_transp_cart 3) hh_asset_transp_boat 4) hh_asset_transp_motorbike 5) hh_asset_transp_car 6) hh_asset_transp_van 7) hh_asset_transp_other 8) hh_asset_transp_none 9) hh_asset_transp_dk 10) hh_asset_transp_ref | D62: Do you or any member of your household own any of the following transportation assets? [OPERATOR: MULTIPLE RESPONSES POSSIBLE. READ ANSWER OPTIONS OUT LOUD.] 1)Bicycle 2)Cart [animal drawn] 3)Boat/canoe 4)Motorbike / scooter / auto rickshaw 5)Car 6)Van or small truck 7)Other motor vehicle 8)None of the above 9)DON'T KNOW 10)REFUSED | E62: =LEN(D62) -> 336 | F62: Est-ce que vous ou un membre de votre ménage possède un des véhicules suivants? [OPÉRATEUR / OPÉRATRICE : PLUSIEURS RÉPONSES POSSIBLES. LIRE LES OPTIONS DE RÉPONSE À HAUTE VOIX.] 1)Bicyclette 2)Chariot [tiré par un animal] 3)Bateau/barque 4)Moto/scooter/pousse-pousse 5)Voiture 6)Fourgonnette ou petit camion 7)Autre véhicule motorisé 8)Aucun des véhicules proposés 9)NE SAIT PAS 10)REFUSÉ | G62: =LEN(F62) -> 396 | H62: Select All That Apply | I62: NA | J62: NA | K62: Form Type - Checklist 8,9,10 = IsNone | L62: 1-10 = hh_maritalstat | M62: 1)hh_asset_transp_bici 2)hh_asset_transp_cart 3)hh_asset_transp_boat 4)hh_asset_transp_motorbike 5)hh_asset_transp_car 6)hh_asset_transp_van 7)hh_asset_transp_other 8)hh_asset_transp_none 9)hh_asset_transp_dk 10)hh_asset_transp_ref | N62: For any response, go to [next question] | P62: This wealth indicator may be useful to Identify poor households in middle income countries. It could be interesting for F2F surveys, to be used as baseline reference for follow-up surveys. | Q62: =1 -> 1 | T62: no | X62: 11.022029 | Y62: =IF(X62="","",X62*Q62) -> 11.022029 | Z62: =IF(T62="yes",Y62,"")
A63: =#REF!+1 -> #REF! | B63: hh_age | C63: hh_age | D63: How old is the head of household? [OPERATOR: SINGLE RESPONSE.] 1)Under 18 2)18 to 40 3)41 to 65 4)Over 65 5)DON'T KNOW 6)REFUSED | E63: =LEN(D63) -> 133 | F63: Quel âge a le chef de famille? [OPÉRATEUR/OPÉRATRICE: RÉPONSE UNIQUE.] 1)Moins de 18 ans 2)entre 18 et 40 ans 3)entre 41 et 65 ans 4)Plus de 65 ans 5)NE SAIT PAS 6)REFUSÉ | G63: =LEN(F63) -> 173 | H63: Single Choice | I63: NA | J63: NA | K63: Form Type - Buttons | L63: 1-6 = income_main | M63: NA | N63: For any response, go to [next question] | Q63: =1 -> 1 | T63: no | X63: 7.0248413 | Y63: =IF(X63="","",X63*Q63) -> 7.0248413 | Z63: =IF(T63="yes",Y63,"")
A64: C. INCOME SOURCES, LIVELIHOOD AND SHOCKS | Y64: =IF(X64="","",X64*Q64) | Z64: =IF(T64="yes",Y64,"")
Q65: =1 -> 1 | Y65: =IF(X65="","",X65*Q65) | Z65: =IF(T65="yes",Y65,"")
A66: =A63+1 -> #REF! | B66: income_main | C66: income_main | D66: What was your household's main source of income in the past 3 months? [OPERATOR: SINGLE RESPONSE. REFUSED OPTION SHOULD BE AVOIDED AS MUCH AS POSSIBLE.] 1)Production and sale of staple crops 2)Production and sale of vegetables or fruit 3)Production and sale of cashcrops 4)Production and sale of livestock and livestock products 5)Production and sale of honey or bee products 6)Production and sale of fish 7)Collection and sale of forestry or bush products 8)Agricultural trade EXCLUDING producers [formal or informal] 9)Daily wage on farms and other casual employment in agricultural sector 10)Stable employment in agricultural sector 11)Non-agricultural self-employed or liberal profession / doctor / architect / lawyer / including restaurant 12)Off-farm daily wages and other non-agricultural casual employment 13)Stable employment in non-agricultural sector 14)Public employment 15)Income not derived from work / Charity 16)Income not derived from work / Welfare transfer, pension, humanitarian aid 17)Income not derived from work / Remittances 18)Income not derived from work / Income from other rents 19)No income source in the last 3 months and used exclusively savings / debt 20)REFUSED | E66: =LEN(D66) -> 1204 | F66: Quelle était la principale source de revenus de votre ménage au cours des trois derniers mois? [OPÉRATEUR/OPÉRATRICE: RÉPONSE UNIQUE. L'OPTION «REFUSÉ» DOIT ÊTRE, AUTANT QUE POSSIBLE, ÉVITÉE.] 1)Production et vente de cultures vivrières 2)Production et vente de légumes ou de fruits 3)Production et vente de cultures de rente 4)Production et vente de bétail et de produits animaux 5)Production et vente de miel ou de produits apicoles 6)Production et vente de poisson 7)Collecte et vente de produits forestiers ou de brousse 8)Commerce agricole EXCLUANT les producteurs [formel ou informel] 9)Salaire journalier dans une exploitation et autres emplois occasionnels dans le secteur agricole 10)Emploi stable dans le secteur agricole 11)Indépendant non-agricole ou profession libérale / médecin / architecte / avocat / y compris restaurant 12)Salaire journalier hors exploitation et autres emplois occasionnels non agricoles 13)Emploi stable dans le secteur non-agricole 14)Emploi public 15)Revenu non tiré du travail / Charité 16)Revenu non tiré du travail / Transferts sociaux, pension, aide humanitaire 17)Revenu non tiré du travail / Envois de fonds des migrants 18)Revenu non tiré du travail / Revenu d'autres loyers 19)Aucune source de revenus au cours des trois derniers mois et recours exclusif à l'épargne / création de dettes 20)REFUSÉ | G66: =LEN(F66) -> 1349 | H66: Single Choice | I66: NA | J66: NA | K66: Form Type - Buttons IsDemographic | L66: 1-3 = income_main_crop_check 4 = income_main_ls_check 5 = income_main_comp OR optional question 6 = income_main_fish_check 7-18 = income_main_comp OR optional question 19-20 = shock | M66: NA | N66: if options #1-3 selected go to income_main_crop_check if options #4 selected go to income_main_ls_check if options #6 selected go to income_main_fish_check if options #5, 7-18 selected, go to [income_main_comp OR optional question] if options #19-20 selected, go to shock | Q66: =1 -> 1 | T66: yes | X66: 31.888334 | Y66: =IF(X66="","",X66*Q66) -> 31.888334 | Z66: =IF(T66="yes",Y66,"") -> 31.888334
B67: income_main_crop_check | C67: income_main_crop_check | D67: Are the crops that you sell also produced by you or anyone in your household? [OPERATOR: SINGLE RESPONSE.] 1)YES 2)NO 3)DON'T KNOW 4)REFUSED | E67: =LEN(D67) -> 143 | F67: Les cultures que vous vendez sont-elles produites par vous ou par un des membres de votre ménage ? [OPÉRATEUR/OPÉRATRICE: RÉPONSE UNIQUE.] 1)Oui 2)Non 3)NE SAIT PAS 4)REFUSÉ | G67: =LEN(F67) -> 175 | H67: Single Choice | I67: NA | J67: NA | K67: Form Type - Buttons | L67: 1-4 = income_main_comp OR optional question | M67: NA | N67: if income_main_crop_check = 1-4, go to [income_main_comp OR optional question] | Q67: =1 -> 1 | T67: yes | X67: 8 | Y67: =IF(X67="","",X67*Q67) -> 8 | Z67: =IF(T67="yes",Y67,"") -> 8
B68: income_main_ls_check | C68: income_main_ls_check | D68: Are the livestock and livestock products that you sell also produced by you or anyone in your household? [OPERATOR: SINGLE RESPONSE.] 1)YES 2)NO 3)DON'T KNOW 4)REFUSED | E68: =LEN(D68) -> 170 | F68: Le bétail et les produits du bétail que vous vendez sont-ils produits par vous par un des membres de votre ménage ? [OPÉRATEUR/OPÉRATRICE: RÉPONSE UNIQUE.] 1)Oui 2)Non 3)NE SAIT PAS 4)REFUSÉ | G68: =LEN(F68) -> 194 | H68: Single Choice | I68: NA | J68: NA | K68: Form Type - Buttons | L68: 1-4 = income_main_comp OR optional question | M68: NA | N68: if income_main_ls_check = 1-4, go to [income_main_comp OR optional question] | Q68: =1 -> 1 | T68: yes | X68: 8 | Y68: =IF(X68="","",X68*Q68) -> 8 | Z68: =IF(T68="yes",Y68,"") -> 8
B69: income_main_fish_check | C69: income_main_fish_check | D69: Are the fish and/or fish products that you sell also captured or harvested by you or anyone in your household? [OPERATOR: SINGLE RESPONSE.] 1)YES 2)NO 3)DON'T KNOW 4)REFUSED | E69: =LEN(D69) -> 176 | F69: Les produits de la pêche / aquaculture que vous vendez sont-ils produits par vous ou par un membre de votre ménage ? [OPÉRATEUR/OPÉRATRICE: RÉPONSE UNIQUE.] 1)Oui 2)Non 3)NE SAIT PAS 4)REFUSÉ | G69: =LEN(F69) -> 194 | H69: Single Choice | I69: NA | J69: NA | K69: Form Type - Buttons | L69: 1-4 = income_main_comp OR optional question | M69: NA | N69: if income_main_fish_check = 1-4, go to [income_main_comp OR optional question] | Q69: =1 -> 1 | T69: yes | X69: 8 | Y69: =IF(X69="","",X69*Q69) -> 8 | Z69: =IF(T69="yes",Y69,"") -> 8
Q70: =1 -> 1 | Y70: =IF(X70="","",X70*Q70) | Z70: =IF(T70="yes",Y70,"")
A71: 19 | B71: income_main_amount | C71: income_main_amount | D71: How much was earned [in CDF] from your main income source, {income_main}, in the past 3 months ? [OPERATOR: MAKE SURE THE INFORMATION IS RECORDED IN THE CORRECT CURRENCY. ENTER 8888888 FOR DON'T KNOW AND 9999999 FOR REFUSED.] | E71: =LEN(D71) -> 226 | F71: Quelle somme [en CDF] a rapporté votre principale source de revenus, {income_main}, au cours des trois derniers mois? [OPÉRATEUR/OPÉRATRICE: VÉRIFIER QUE LA RÉPONSE EST ENREGISTRÉE DANS LA BONNE DEVISE. SAISIR 8888888 POUR «NE SAIT PAS» ET 9999999 POUR «REFUSÉ».] | G71: =LEN(F71) -> 264 | H71: Range | I71: NA | J71: NA | K71: Form Type - TextBox | L71: 1 - 2000000 = income_main_comp OR optional question 2000000 - 10000000 = income_main_amount_conf 8888888-8888888 = income_main_comp OR optional question 9999999-9999999 = income_main_comp OR optional question | M71: NA | N71: If the income amount is over the threshold set in "Additional information", the respondent will be asked to confirm with income_main_amount_conf. Otherwise, go to income_main_comp or optional question. | P71: We recommend using this pair of questions together. | Q71: =1 -> 1 | T71: no | X71: 31.963766 | Y71: =IF(X71="","",X71*Q71) -> 31.963766 | Z71: =IF(T71="yes",Y71,"")
A72: 19 | B72: income_main_amount_conf | C72: income_main_amount_conf | D72: Can you confirm the amount of income you just stated is correct? [OPERATOR: IF THE AMOUNT EARNED FROM THIS INCOME SOURCE OVER THE PAST 3 MONTH IS INDEED OVER 2000000, CLICK ON CONTINUE. OTHERWISE, GO BACK AND CHANGE THE AMOUNT ENTERED.] 1)CONTINUE | E72: =LEN(D72) -> 249 | F72: Pouvez-vous confirmer que le montant que vous venez de déclarer est correct? [OPÉRATEUR/OPÉRATRICE: SI LE MONTANT ISSU DE CETTE SOURCE DE REVENU AU COURS DES TROIS DERNIERS MOIS EST SUPÉRIEUR AU 2000000, CLIQUER SUR CONTINUER. SINON, REVENIR EN ARRIÈRE ET MODIFIER LE MONTANT SAISI.] 1)CONTINUER | G72: =LEN(F72) -> 297 | H72: Single Choice | I72: NA | J72: NA | K72: Form Type - Buttons | L72: 1 = income_main_comp OR optional question | M72: NA | N72: if income_main_amount_conf = 1, go to income_main_comp or optional question | Q72: =1 -> 1 | T72: no | X72: 2.2273674 | Y72: =IF(X72="","",X72*Q72) -> 2.2273674 | Z72: =IF(T72="yes",Y72,"")
A73: 18 | B73: income_main_gender | C73: income_main_gender | D73: What is the gender of the household member[s] generating income from this source? [OPERATOR: SINGLE RESPONSE.] 1)Male 2)Female 3)Joint [both male & female] 4)DON'T KNOW 5)REFUSED | E73: =LEN(D73) -> 181 | F73: Quel est le sexe du ou des membres du ménage qui génèrent des revenus de cette source? [OPÉRATEUR/OPÉRATRICE: RÉPONSE UNIQUE]. 1)Homme 2)Femme 3)Mixte [homme et femme] 4)NE SAIT PAS 5)REFUSÉ | G73: =LEN(F73) -> 193 | H73: Single Choice | I73: NA | J73: NA | K73: Form Type - Buttons | L73: 1-5 = [income_main_comp OR optional question] | M73: NA | N73: if income_main_gender = 1-5, go to income_main_comp or optional question | Q73: =1 -> 1 | T73: no | X73: 4.7874017 | Y73: =IF(X73="","",X73*Q73) -> 4.7874017 | Z73: =IF(T73="yes",Y73,"")
B74: income_main_control | C74: income_main_control | D74: Who controls the revenue that is earned from this source? [OPERATOR: SINGLE RESPONSE.] 1)Male household member[s] 2)Female household member[s] 3)Joint household members [both female & male] 4)DON'T KNOW 5)REFUSED | E74: =LEN(D74) -> 215 | F74: Qui contrôle les revenus qui proviennent de cette source? [OPÉRATEUR/OPÉRATRICE: RÉPONSE UNIQUE]. 1)Membre[s] masculin[s] du ménage 2)Membre[s] féminin[s] du ménage 3)Membres du ménage conjointement [femme et homme] 4)NE SAIT PAS 5)REFUSÉ | G74: =LEN(F74) -> 241 | H74: Single Choice | I74: NA | J74: NA | K74: Form Type - Buttons | L74: 1-5 = income_main_comp | M74: NA | N74: if income_main_control = 1-5, go to income_main_comp | Q74: =1 -> 1 | T74: no | X74: 20.918367 | Y74: =IF(X74="","",X74*Q74) -> 20.918367 | Z74: =IF(T74="yes",Y74,"")
Q75: =1 -> 1 | Y75: =IF(X75="","",X75*Q75) | Z75: =IF(T75="yes",Y75,"")
A76: =A72+1 -> 20 | B76: income_main_comp | C76: income_main_comp | D76: Has your household's income from {income_main} changed in the last 3 months compared to the same period of last year? [OPERATOR: SINGLE RESPONSE.] 1)A lot more [increased by more than 50%] 2)Slightly more 3)Same 4)Slightly less 5)A lot less [less than half as much] 6)DON'T KNOW 7)REFUSED | E76: =LEN(D76) -> 290 | F76: Le revenu de votre ménage provenant de {income_main} a-t-il changé au cours des trois derniers mois par rapport à la même période de l'année dernière? [OPÉRATEUR/OPÉRATRICE: RÉPONSE UNIQUE.] 1)Très supérieur [augmentation de plus de 50%] 2)Légèrement supérieur 3)Identique 5)Légèrement inférieur 5)Très inférieur [moins de la moitié] 6)NE SAIT PAS 7)REFUSÉ | G76: =LEN(F76) -> 359 | H76: Single Choice | I76: NA | J76: NA | K76: Form Type - Buttons | L76: 1-7= income_sec | M76: NA | N76: if income_main_comp = 1-7, go to income_sec | Q76: =1 -> 1 | T76: yes | X76: 22.126215 | Y76: =IF(X76="","",X76*Q76) -> 22.126215 | Z76: =IF(T76="yes",Y76,"") -> 22.126215
Q77: =1 -> 1 | Y77: =IF(X77="","",X77*Q77) | Z77: =IF(T77="yes",Y77,"")
A78: =A76+1 -> 21 | B78: income_sec | C78: income_sec | D78: What was your household's second most important source of income in the past 3 months? [OPERATOR: SINGLE RESPONSE. DON'T KNOW AND REFUSED OPTIONS SHOULD BE AVOIDED AS MUCH AS POSSIBLE.] 1)Production and sale of staple crops 2)Production and sale of vegetables or fruit 3)Production and sale of cashcrops 4)Production and sale of livestock and livestock products 5)Production and sale of honey or bee products 6)Production and sale of fish 7)Collection and sale of forestry or bush products 8)Agricultural trade EXCLUDING producers [formal or informal] 9)Daily wage on farms and other casual employment in agricultural sector 10)Stable employment in agricultural sector 11)Non-agricultural self-employed or liberal profession / doctor / architect / lawyer / including restaurant 12)Off-farm daily wages and other non-agricultural casual employment 13)Stable employment in non-agricultural sector 14)Public employment 15)Income not derived from work / Charity 16)Income not derived from work / Welfare transfer, pension, humanitarian aid 17)Income not derived from work / Remittances 18)Income not derived from work / Income from other rents 19)No second most important source of income 20)DON'T KNOW 21)REFUSED | E78: =LEN(D78) -> 1218 | F78: Quelle était la deuxième source principale de revenus de votre ménage au cours des trois derniers mois? [OPÉRATEUR/OPÉRATRICE: RÉPONSE UNIQUE. LES OPTIONS «NE SAIT PAS» ET «REFUSÉ» DOIVENT ÊTRE ÉVITÉES AUTANT QUE POSSIBLE]. 1)Production et vente de cultures vivrières 2)Production et vente de légumes ou de fruits 3)Production et vente de cultures de rente 4)Production et vente de bétail et de produits animaux 5)Production et vente de miel ou de produits apicoles 6)Production et vente de poisson 7)Collecte et vente de produits forestiers ou de brousse 8)Commerce agricole EXCLUANT les producteurs [formel ou informel] 9)Salaire journalier dans une exploitation et autres emplois occasionnels dans le secteur agricole 10)Emploi stable dans le secteur agricole 11)Indépendant non-agricole ou profession libérale / médecin / architecte / avocat / y compris restaurant 12)Salaire journalier hors exploitation et autres emplois occasionnels non agricoles 13)Emploi stable dans le secteur non-agricole 14)Emploi public 15)Revenu non tiré du travail / Charité 16)Revenu non tiré du travail / Transferts sociaux, pension, aide humanitaire 17)Revenu non tiré du travail / Envois de fonds des migrants 18)Revenu non tiré du travail / Revenu d'autres loyers 19)Pas de deuxième source principale de revenus 20)NE SAIT PAS 21)REFUSÉ | G78: =LEN(F78) -> 1329 | H78: Single Choice | I78: NA | J78: NA | K78: Form Type - Buttons exclude selected "income_main" IsDemographic | L78: 1-3 = income_sec_crop_check 4 = income_sec_ls_check 5 = income_sec_comp OR optional question 6 = income_sec_fish_check 7-18 = income_sec_comp OR optional question 19-21 = shock | M78: NA | N78: if options #1-3 selected, go to income_sec_crop_check if options #4 selected, go to income_sec_ls_check if options #6 selected, go to income_sec_fish_check if options #5, 7-18 selected, go to [income_sec_comp OR optional question] if options #19-21 selected, go to shock | Q78: =1 -> 1 | T78: yes | X78: 18.710653 | Y78: =IF(X78="","",X78*Q78) -> 18.710653 | Z78: =IF(T78="yes",Y78,"") -> 18.710653
B79: income_sec_crop_check | C79: income_sec_crop_check | D79: Are the crops that you sell also produced by you or anyone in your household? [OPERATOR: SINGLE RESPONSE.] 1)YES 2)NO 3)DON'T KNOW 4)REFUSED | E79: =LEN(D79) -> 143 | F79: Les cultures que vous vendez sont-elles produites par vous ou par un des membres de votre ménage ? [OPÉRATEUR/OPÉRATRICE: RÉPONSE UNIQUE.] 1)Oui 2)Non 3)NE SAIT PAS 4)REFUSÉ | G79: =LEN(F79) -> 175 | H79: Single Choice | I79: NA | J79: NA | K79: Form Type - Buttons | L79: 1-4 = income_sec_comp OR optional question | M79: NA | N79: if income_sec_crop_check = 1-4, go to [income_sec_comp OR optional question] | Q79: =1 -> 1 | T79: yes | X79: 8 | Y79: =IF(X79="","",X79*Q79) -> 8 | Z79: =IF(T79="yes",Y79,"") -> 8
B80: income_sec_ls_check | C80: income_sec_ls_check | D80: Are the livestock and livestock products that you sell also produced by you or anyone in your household? [OPERATOR: SINGLE RESPONSE.] 1)YES 2)NO 3)DON'T KNOW 4)REFUSED | E80: =LEN(D80) -> 170 | F80: Le bétail et les produits du bétail que vous vendez sont-ils produits par vous par un des membres de votre ménage ? [OPÉRATEUR/OPÉRATRICE: RÉPONSE UNIQUE.] 1)Oui 2)Non 3)NE SAIT PAS 4)REFUSÉ | G80: =LEN(F80) -> 194 | H80: Single Choice | I80: NA | J80: NA | K80: Form Type - Buttons | L80: 1-4 = income_sec_comp OR optional question | M80: NA | N80: if income_sec_ls_check = 1-4, go to [income_sec_comp OR optional question] | Q80: =1 -> 1 | T80: yes | X80: 8 | Y80: =IF(X80="","",X80*Q80) -> 8 | Z80: =IF(T80="yes",Y80,"") -> 8
B81: income_sec_fish_check | C81: income_sec_fish_check | D81: Are the fish and/or fish products that you sell also captured or harvested by you or anyone in your household? [OPERATOR: SINGLE RESPONSE.] 1)YES 2)NO 3)DON'T KNOW 4)REFUSED | E81: =LEN(D81) -> 176 | F81: Les produits de la pêche / aquaculture que vous vendez sont-ils produits par vous ou par un membre de votre ménage ? [OPÉRATEUR/OPÉRATRICE: RÉPONSE UNIQUE.] 1)Oui 2)Non 3)NE SAIT PAS 4)REFUSÉ | G81: =LEN(F81) -> 194 | H81: Single Choice | I81: NA | J81: NA | K81: Form Type - Buttons | L81: 1-4 = income_sec_comp OR optional question | M81: NA | N81: if income_sec_fish_check = 1-4, go to [income_sec_comp OR optional question] | Q81: =1 -> 1 | T81: yes | X81: 8 | Y81: =IF(X81="","",X81*Q81) -> 8 | Z81: =IF(T81="yes",Y81,"") -> 8
Q82: =1 -> 1 | Y82: =IF(X82="","",X82*Q82) | Z82: =IF(T82="yes",Y82,"")
A83: 19 | B83: income_sec_amount | C83: income_sec_amount | D83: How much was earned [in CDF] from your second main income source, {income_sec}, in the past 3 months ? [OPERATOR: MAKE SURE THE INFORMATION IS RECORDED IN THE CORRECT CURRENCY. ENTER 8888888 FOR DON'T KNOW AND 9999999 FOR REFUSED.] | E83: =LEN(D83) -> 232 | F83: Quelle somme [en CDF] a rapporté votre deuxième principale source de revenu, {income_sec}, au cours des trois derniers mois? [OPÉRATEUR/OPÉRATRICE: VÉRIFIER QUE LA RÉPONSE EST ENREGISTRÉE DANS LA BONNE DEVISE. SAISIR 8888888 POUR «NE SAIT PAS» ET 9999999 POUR «REFUSÉ».] | G83: =LEN(F83) -> 271 | H83: Range | I83: NA | J83: NA | K83: Form Type - TextBox | L83: 1 - 2000000 = income_sec_comp or optional question 2000000 - 10000000 = income_sec_amount_conf 8888888-8888888 = income_sec_comp or optional question 9999999-9999999 = income_sec_comp or optional question | M83: NA | N83: If the income amount is over the threshold set in "Additional information", the respondent will be asked to confirm with income_sec_amount_conf. Otherwise, go to income_sec_comp. | P83: We recommend using this pair of questions together. | Q83: =1 -> 1 | T83: no | X83: 23.20038 | Y83: =IF(X83="","",X83*Q83) -> 23.20038 | Z83: =IF(T83="yes",Y83,"")
A84: =#REF!+1 -> #REF! | B84: income_sec_amount_conf | C84: income_sec_amount_conf | D84: Can you confirm the amount of income you just stated is correct? [OPERATOR: IF THE AMOUNT EARNED FROM THIS INCOME SOURCE OVER THE PAST 3 MONTH IS INDEED OVER 2000000, CLICK ON CONTINUE. OTHERWISE, GO BACK AND CHANGE THE AMOUNT ENTERED.] 1)CONTINUE | E84: =LEN(D84) -> 249 | F84: Pouvez-vous confirmer que le montant que vous venez de déclarer est correct? [OPÉRATEUR/OPÉRATRICE: SI LE MONTANT ISSU DE CETTE SOURCE DE REVENU AU COURS DES TROIS DERNIERS MOIS EST SUPÉRIEUR AU 2000000, CLIQUER SUR CONTINUER. SINON, REVENIR EN ARRIÈRE ET MODIFIER LE MONTANT SAISI.] 1)CONTINUER | G84: =LEN(F84) -> 297 | H84: Single Choice | I84: NA | J84: NA | K84: Form Type - Buttons | L84: 1 = income_sec_comp or optional question | M84: NA | N84: if income_sec_amount_conf = 1, go to income_sec_comp | Q84: =1 -> 1 | T84: no | X84: 1.9277389 | Y84: =IF(X84="","",X84*Q84) -> 1.9277389 | Z84: =IF(T84="yes",Y84,"")
A85: 18 | B85: income_sec_gender | C85: income_sec_gender | D85: What is the gender of the household member[s] generating income from this source? [OPERATOR: SINGLE RESPONSE.] 1)Male 2)Female 3)Joint [both male & female] 4)DON'T KNOW 5)REFUSED | E85: =LEN(D85) -> 181 | F85: Quel est le sexe du ou des membres du ménage qui génèrent des revenus de cette source? [OPÉRATEUR/OPÉRATRICE: RÉPONSE UNIQUE]. 1)Homme 2)Femme 3)Mixte [homme et femme] 4)NE SAIT PAS 5)REFUSÉ | G85: =LEN(F85) -> 193 | H85: Single Choice | I85: NA | J85: NA | K85: Form Type - Buttons | L85: 1-5 = [income_sec_comp OR optional question] | M85: NA | N85: if income_sec_gender = 1-5, go to income_sec_comp or optional question | Q85: =1 -> 1 | T85: no | X85: 4.7874017 | Y85: =IF(X85="","",X85*Q85) -> 4.7874017 | Z85: =IF(T85="yes",Y85,"")
Q86: =1 -> 1 | Y86: =IF(X86="","",X86*Q86) | Z86: =IF(T86="yes",Y86,"")
A87: =#REF!+1 -> #REF! | B87: income_sec_comp | C87: income_sec_comp | D87: Has your household's income from {income_sec} changed in the last 3 months compared to the same period of last year? [OPERATOR: SINGLE RESPONSE.] 1)A lot more [increased by more than 50%] 2)Slightly more 3)Same 4)Slightly less 5)A lot less [less than half as much] 6)DON'T KNOW 7)REFUSED | E87: =LEN(D87) -> 290 | F87: Le revenu de votre ménage provenant de {income_sec} a-t-il changé au cours des trois derniers mois par rapport à la même période de l'année dernière? [OPÉRATEUR/OPÉRATRICE: RÉPONSE UNIQUE.] 1)Très supérieur [augmentation de plus de 50%] 2)Légèrement supérieur 3)Identique 5)Légèrement inférieur 5)Très inférieur [moins de la moitié] 6)NE SAIT PAS 7)REFUSÉ | G87: =LEN(F87) -> 358 | H87: Single Choice | I87: NA | J87: NA | K87: Form Type - Buttons | L87: 1-7= income_third | M87: NA | N87: if income_sec_comp = 1-7, go to income_third | Q87: =1 -> 1 | T87: yes | X87: 17.261402 | Y87: =IF(X87="","",X87*Q87) -> 17.261402 | Z87: =IF(T87="yes",Y87,"") -> 17.261402
Q88: =1 -> 1 | Y88: =IF(X88="","",X88*Q88) | Z88: =IF(T88="yes",Y88,"")
A89: =A87+1 -> #REF! | B89: income_third | C89: income_third | D89: What was your household's third most important source of income in the past 3 months? [OPERATOR: SINGLE RESPONSE. DON'T KNOW AND REFUSED OPTIONS SHOULD RARELY/NOT AVOIDED AS MUCH AS POSSIBLE.] 1)Production and sale of staple crops 2)Production and sale of vegetables or fruit 3)Production and sale of cashcrops 4)Production and sale of livestock and livestock products 5)Production and sale of honey or bee products 6)Production and sale of fish 7)Collection and sale of forestry or bush products 8)Agricultural trade EXCLUDING producers [formal and informal] 9)Daily wage on farms and other casual employment in agricultural sector 10)Stable employment in agricultural sector 11)Non-agricultural self-employed or liberal profession / doctor / architect / lawyer / including restaurant 12)Off-farm daily wages and other non-agricultural casual employment 13)Stable employment in non-agricultural sector 14)Public employment 15)Income not derived from work / Charity 16)Income not derived from work / Welfare transfer, pension, humanitarian aid 17)Income not derived from work / Remittances 18)Income not derived from work / Income from other rents 19)No third most important source of income 20)DON'T KNOW 21)REFUSED | E89: =LEN(D89) -> 1225 | F89: Quelle était la troisième source principale de revenus de votre ménage au cours des trois derniers mois? [OPÉRATEUR/OPÉRATRICE: RÉPONSE UNIQUE. LES OPTIONS «NE SAIT PAS» ET «REFUSÉ» DOIVENT ÊTRE ÉVITÉES AUTANT QUE POSSIBLE]. 1)Production et vente de cultures vivrières 2)Production et vente de légumes ou de fruits 3)Production et vente de cultures de rente 4)Production et vente de bétail et de produits animaux 5)Production et vente de miel ou de produits apicoles 6)Production et vente de poisson 7)Collecte et vente de produits forestiers ou de brousse 8)Commerce agricole EXCLUANT les producteurs [formel ou informel] 9)Salaire journalier dans une exploitation et autres emplois occasionnels dans le secteur agricole 10)Emploi stable dans le secteur agricole 11)Indépendant non-agricole ou profession libérale / médecin / architecte / avocat / y compris restaurant 12)Salaire journalier hors exploitation et autres emplois occasionnels non agricoles 13)Emploi stable dans le secteur non-agricole 14)Emploi public 15)Revenu non tiré du travail / Charité 16)Revenu non tiré du travail / Transferts sociaux, pension, aide humanitaire 17)Revenu non tiré du travail / Envois de fonds des migrants 18)Revenu non tiré du travail / Revenu d'autres loyers 19)Pas de troisième source principale de revenus 20)NE SAIT PAS 21)REFUSÉ | G89: =LEN(F89) -> 1331 | H89: Single Choice | I89: NA | J89: NA | K89: Form Type - Buttons exclude selected "income_main" exclude selected "income_sec" IsDemographic | L89: 1-3 = income_third_crop_check 4 = income_third_ls_check 5 = income_third_comp OR optional question 6 = income_third_fish_check 7-18 = income_third_comp OR optional question 19-21 = shock | M89: NA | N89: if options #1-3 selected, go to income_third_crop_check if options #4 selected, go to income_third_ls_check if option #6 selected, go to income_third_fish_check if options #5, 7-18 selected, go to [income_third_comp OR optional question] if options #19-21 selected, go to shock | Q89: =1 -> 1 | T89: yes | X89: 14.475392 | Y89: =IF(X89="","",X89*Q89) -> 14.475392 | Z89: =IF(T89="yes",Y89,"") -> 14.475392
B90: income_third_crop_check | C90: income_third_crop_check | D90: Are the crops that you sell also produced by you or anyone in your household? [OPERATOR: SINGLE RESPONSE.] 1)YES 2)NO 3)DON'T KNOW 4)REFUSED | E90: =LEN(D90) -> 143 | F90: Les cultures que vous vendez sont-elles produites par vous ou par un des membres de votre ménage ? [OPÉRATEUR/OPÉRATRICE: RÉPONSE UNIQUE.] 1)Oui 2)Non 3)NE SAIT PAS 4)REFUSÉ | G90: =LEN(F90) -> 175 | H90: Single Choice | I90: NA | J90: NA | K90: Form Type - Buttons | L90: 1-4 = income_third_comp OR optional question | M90: NA | N90: if income_third_crop_check = 1-4, go to [income_third_comp OR optional question] | Q90: =1 -> 1 | T90: yes | X90: 8 | Y90: =IF(X90="","",X90*Q90) -> 8 | Z90: =IF(T90="yes",Y90,"") -> 8
B91: income_third_ls_check | C91: income_third_ls_check | D91: Are the livestock and livestock products that you sell also produced by you or anyone in your household? [OPERATOR: SINGLE RESPONSE.] 1)YES 2)NO 3)DON'T KNOW 4)REFUSED | E91: =LEN(D91) -> 170 | F91: Le bétail et les produits du bétail que vous vendez sont-ils produits par vous par un des membres de votre ménage ? [OPÉRATEUR/OPÉRATRICE: RÉPONSE UNIQUE.] 1)Oui 2)Non 3)NE SAIT PAS 4)REFUSÉ | G91: =LEN(F91) -> 194 | H91: Single Choice | I91: NA | J91: NA | K91: Form Type - Buttons | L91: 1-4 = income_third_comp OR optional question | M91: NA | N91: if income_third_ls_check = 1-4, go to [income_third_comp OR optional question] | Q91: =1 -> 1 | T91: yes | X91: 8 | Y91: =IF(X91="","",X91*Q91) -> 8 | Z91: =IF(T91="yes",Y91,"") -> 8
B92: income_third_fish_check | C92: income_third_fish_check | D92: Are the fish and/or fish products that you sell also captured or harvested by you or anyone in your household? [OPERATOR: SINGLE RESPONSE.] 1)YES 2)NO 3)DON'T KNOW 4)REFUSED | E92: =LEN(D92) -> 176 | F92: Les produits de la pêche / aquaculture que vous vendez sont-ils produits par vous ou par un membre de votre ménage ? [OPÉRATEUR/OPÉRATRICE: RÉPONSE UNIQUE.] 1)Oui 2)Non 3)NE SAIT PAS 4)REFUSÉ | G92: =LEN(F92) -> 194 | H92: Single Choice | I92: NA | J92: NA | K92: Form Type - Buttons | L92: 1-4 = income_third_comp OR optional question | M92: NA | N92: if income_third_fish_check = 1-4, go to [income_third_comp OR optional question] | Q92: =1 -> 1 | T92: yes | X92: 8 | Y92: =IF(X92="","",X92*Q92) -> 8 | Z92: =IF(T92="yes",Y92,"") -> 8
Q93: =1 -> 1 | Y93: =IF(X93="","",X93*Q93) | Z93: =IF(T93="yes",Y93,"")
A94: =A89+1 -> #REF! | B94: income_third_amount | C94: income_third_amount | D94: How much was earned [in CDF] from your third main source of income, {income_third}, in the past 3 months ? [OPERATOR: MAKE SURE THE INFORMATION IS RECORDED IN THE CORRECT CURRENCY. ENTER 8888888 FOR DON'T KNOW AND 9999999 FOR REFUSED.] | E94: =LEN(D94) -> 236 | F94: Quelle somme [en CDF] a rapporté votre troisième principale source de revenu, {income_sec}, au cours des trois derniers mois? [OPÉRATEUR/OPÉRATRICE: VÉRIFIER QUE LA RÉPONSE EST ENREGISTRÉE DANS LA BONNE DEVISE. SAISIR 8888888 POUR «NE SAIT PAS» ET 9999999 POUR «REFUSÉ».] | G94: =LEN(F94) -> 272 | H94: Range | I94: NA | J94: NA | K94: Form Type - TextBox | L94: 1 - 2000000 = income_third_comp or optional question 2000000 - 10000000 = income_third_amount_conf 8888888-8888888 = income_third_comp or optional question 9999999-9999999 = income_third_comp or optional question | M94: NA | N94: If the income amount is over the threshold set in "Additional information", the respondent will be asked to confirm with income_third_amount_conf. Otherwise, go to income_third_comp or optional question. | P94: We recommend using this pair of questions together. | Q94: =1 -> 1 | T94: no | X94: 24.401098 | Y94: =IF(X94="","",X94*Q94) -> 24.401098 | Z94: =IF(T94="yes",Y94,"")
A95: =A94+1 -> #REF! | B95: income_third_amount_conf | C95: income_third_amount_conf | D95: Can you confirm the amount of income you just stated is correct? [OPERATOR: IF THE AMOUNT EARNED FROM THIS INCOME SOURCE OVER THE PAST 3 MONTH IS INDEED OVER 2000000, CLICK ON CONTINUE. OTHERWISE, GO BACK AND CHANGE THE AMOUNT ENTERED.] 1)CONTINUE | E95: =LEN(D95) -> 249 | F95: Pouvez-vous confirmer que le montant que vous venez de déclarer est correct? [OPÉRATEUR/OPÉRATRICE: SI LE MONTANT ISSU DE CETTE SOURCE DE REVENU AU COURS DES TROIS DERNIERS MOIS EST SUPÉRIEUR AU 2000000, CLIQUER SUR CONTINUER. SINON, REVENIR EN ARRIÈRE ET MODIFIER LE MONTANT SAISI.] 1)CONTINUER | G95: =LEN(F95) -> 297 | H95: Single Choice | I95: NA | J95: NA | K95: Form Type - Buttons | L95: 1 = income_third_comp or optional question | M95: NA | N95: if income_third_amount_conf = 1, go to income_third_comp or optional question | Q95: =1 -> 1 | T95: no | X95: 2.47 | Y95: =IF(X95="","",X95*Q95) -> 2.47 | Z95: =IF(T95="yes",Y95,"")
Q96: =1 -> 1 | Y96: =IF(X96="","",X96*Q96) | Z96: =IF(T96="yes",Y96,"")
A97: =#REF!+1 -> #REF! | B97: income_third_comp | C97: income_third_comp | D97: Has your household's income from {income_third} changed in the last 3 months compared to the same period of last year? [OPERATOR: SINGLE RESPONSE.] 1)A lot more [increased by more than 50%] 2)Slightly more 3)Same 4)Slightly less 5)A lot less [less than half as much] 6)DON'T KNOW 7)REFUSED | E97: =LEN(D97) -> 291 | F97: Le revenu de votre ménage provenant de {income_third} a-t-il changé au cours des trois derniers mois par rapport à la même période de l'année dernière? [OPÉRATEUR/OPÉRATRICE: RÉPONSE UNIQUE.] 1)Très supérieur [augmentation de plus de 50%] 2)Légèrement supérieur 3)Identique 5)Légèrement inférieur 5)Très inférieur [moins de la moitié] 6)NE SAIT PAS 7)REFUSÉ | G97: =LEN(F97) -> 360 | H97: Single Choice | I97: NA | J97: NA | K97: Form Type - Buttons | L97: 1-7= shock | M97: NA | N97: if income_third_comp = 1-7, go to shock | Q97: =1 -> 1 | T97: yes | X97: 15.876503 | Y97: =IF(X97="","",X97*Q97) -> 15.876503 | Z97: =IF(T97="yes",Y97,"") -> 15.876503
Q98: =1 -> 1 | Y98: =IF(X98="","",X98*Q98) | Z98: =IF(T98="yes",Y98,"")
A99: =#REF!+1 -> #REF! | B99: shock | C99: shock_ 1) shock_noshock 2) shock_sicknessordeathofhh 3) shock_lostemplorwork 4) shock_otherintrahhshock 5) shock_higherfoodprices 6) shock_higherfuelprices 7) shock_mvtrestrict 8) shock_othereconomicshock 9) shock_pestoutbreak 10) shock_plantdisease 11) shock_animaldisease 12) shock_napasture 13) shock_othercropandlivests 14) shock_coldtemporhail 15) shock_flood 16) shock_hurricane 17) shock_drought 18) shock_earthquake 19) shock_landslides 20) shock_firenatural 21) shock_othernathazard 22) shock_violenceinsecconf 23) shock_theftofprodassets 24) shock_firemanmade 25) shock_othermanmadehazard 26) shock_dk 27) shock_ref | D99: Has your household or community faced any particular disaster or crisis affecting your household's ability to raise an income and/or to produce food for self consumption in the last 3 months, and if so, which one[s]? [OPERATOR: SELECT RELEVANT SHOCKS EXPERIENCED BY THE HOUSEHOLD. MULTIPLE RESPONSES POSSIBLE. REFER TO ECONOMIC SHOCKS, CROP AND LIVESTOCK SHOCKS, INTRA-HOUSEHOLD SHOCK, NATURAL HAZARDS AND HUMAN-INDUCED HAZARDS.] 1)No shock 2)Sickness or accident or death of household member[s] [sickness of breadwinner / unusually high medical expenditure / funeral expenses / death of breadwinner] 3)Lost employment or working opportunities [not due to illness/accident] 4)Other intra-household shock 5)Unusually high food prices 6)Unusually high fuel prices or transport prices 7)Population movement restrictions [e.g. due to epidemic or infrastructure damage] 8)Other economic shock 9)Pest outbreak 10)Plant disease 11)Animal disease [affecting many animals] or death 12)Lack of physical access to pasture 13)Other crop and livestock shock 14)Cold temperatures or hail 15)Flood / riverbank erosion 16)Hurricane / cyclone / tornado 17)Drought / heat stress 18)Earthquake 19)Landslides 20)Fire from natural disaster 21)Other natural hazard 22)Violence and insecurity / conflict 23)Theft of production assets [land / livestock / tools / etc] 24)Fire from human-induced disaster 25)Other human-induced hazard 26)DON'T KNOW 27)REFUSED | E99: =LEN(D99) -> 1440 | F99: Au cours des trois derniers mois, est-ce que votre ménage ou votre communauté ont été confrontés à une catastrophe ou une crise particulières qui a atteint votre capacité à dégager un revenu et/ou à produire des aliments pour votre propre consommation? Si oui, lesquelles? [OPÉRATEUR/OPÉRATRICE: SÉLECTIONNER LES CHOCS PERTINENTS SUBIS PAR LE MÉNAGE. PLUSIEURS RÉPONSES POSSIBLES. SE RÉFÉRER AUX CHOCS ÉCONOMIQUES, AUX CHOCS TOUCHANT LES RÉCOLTES ET LE BÉTAIL, AUX CHOCS INTRA-MÉNAGE, AUX RISQUES NATURELS ET AUX RISQUES D'ORIGINE HUMAINE] 1)Aucun choc 2)Maladie, accident ou décès d'un ou plusieurs membres du ménage [maladie du soutien de famille / dépenses médicales anormalement élevées / frais funéraires / décès du soutien de famille] 3)Perte d'emploi ou d'opportunités de travail [non due à la maladie ou à un accident] 4)Autre choc interne au ménage 5)Prix des denrées alimentaires anormalement élevés 6)Prix des carburants ou des transports anormalement élevés 7)Restrictions de mouvements de population [par exemple, en raison d'une épidémie ou de dommages causés aux infrastructures]. 8)Autre choc économique 9)Invasion d'organismes nuisibles 10)Maladie des plantes 11)Maladie animale [touchant de nombreux animaux] ou mort d'animaux 12)Accès difficile aux pâturages 13)Autre choc touchant les cultures et le bétail 14)Températures froides / grêle 15)Inondations / érosion des berges 16)Ouragan / cyclone / tornade 17)Sécheresse / stress dû à la chaleur 18)Tremblement de terre 19)Glissement de terrain 20)Incendie dû à une catastrophe naturelle 21)Autre risque naturel 22)Violence et insécurité / conflit 23)Vol d'actifs de production [terres/ bétail/ outils/ etc.] 24)Incendie dû à une catastrophe d'origine humaine 25)Autre risque d'origine humaine 26)NE SAIT PAS 27)REFUSÉ | G99: =LEN(F99) -> 1790 | H99: Select All That Apply | I99: NA | J99: NA | K99: Form Type - Checklist 1,26,27 = IsNone | L99: 1-27 = [crp_intro or optional question] | M99: 1)shock_noshock 2)shock_sicknessordeathofhh 3)shock_lostemplorwork 4)shock_otherintrahhshock 5)shock_higherfoodprices 6)shock_higherfuelprices 7)shock_mvtrestrict 8)shock_othereconomicshock 9)shock_pestoutbreak 10)shock_plantdisease 11)shock_animaldisease 12)shock_napasture 13)shock_othercropandlivests 14)shock_coldtemporhail 15)shock_flood 16)shock_hurricane 17)shock_drought 18)shock_earthquake 19)shock_landslides 20)shock_firenatural 21)shock_othernathazard 22)shock_violenceinsecconf 23)shock_theftofprodassets 24)shock_firemanmade 25)shock_othermanmadehazard 26)shock_dk 27)shock_ref | N99: if shock = 1-27, go to [crp_intro or optional question] | Q99: =1 -> 1 | T99: yes | X99: 37.85363 | Y99: =IF(X99="","",X99*Q99) -> 37.85363 | Z99: =IF(T99="yes",Y99,"") -> 37.85363
A100: 28 | B100: hh_explanation | C100: hh_explanation | D100: If the household was affected by a major recent shock as indicated in this assessment [for example, an earthquake], what are the [already observed or expected] consequences for your household, in your own words? [OPERATOR: RECORD IN FEW WORDS THE MAIN CONSEQUENCE OF THE RECENT SHOCKS. ENTER 88 FOR DON'T KNOW AND 99 FOR REFUSED.] | E100: =LEN(D100) -> 331 | F100: Si votre ménage a récemment été concerné par un choc majeur mentionné dans cette évaluation [par exemple, un tremblement de terre], quelles en sont, selon vous et dans vos propres mots, les conséquences [déjà ressenties ou attendues] pour votre ménage? [OPÉRATEUR/OPÉRATRICE: SAISIR EN QUELQUES MOTS LA PRINCIPALE CONSÉQUENCE DES RÉCENTS CHOCS. SAISIR 88 POUR «NE SAIT PAS» ET 99 POUR «REFUSÉ»]. | G100: =LEN(F100) -> 396 | H100: Open Ended | I100: NA | J100: NA | K100: Form Type - TextBox | L100: Any Response = covid | M100: NA | N100: For any response to hh_explanation, go to covid. | Q100: =1 -> 1 | T100: no | Y100: =IF(X100="","",X100*Q100) | Z100: =IF(T100="yes",Y100,"")
...

Sheet New Durations
A1: question | B1: duration | C1: responded % | D1: weighted time
A2: introduction | B2: 50.82254 | C2: 1 | D2: 50.82254
A3: agree | B3: 3.4964738 | C3: 0.79698741 | D3: 2.7866456
A4: resp_age | B4: 13.753073 | C4: 1 | D4: 13.753073
A5: resp_gender | B5: 2.1173561 | C5: 1 | D5: 2.1173561
A6: quotareached | B6: 2.28425 | C6: 0.79698741 | D6: 1.8205185
A7: hh_agricactivity | B7: 31.372377 | C7: 1 | D7: 31.372377
A8: hh_milieu | B8: 7.9225454 | C8: 0.15190348 | D8: 1.2034622
A9: hh_gender | B9: 10.085732 | C9: 1 | D9: 10.085732
A10: hh_education | B10: 12.894034 | C10: 1 | D10: 12.894034
A11: hh_wealth_water | B11: 15.265829 | C11: 0.63796463 | D11: 9.739059
A12: hh_wealth_toilet | B12: 15.123718 | C12: 0.59180156 | D12: 8.95024
A13: hh_wealthwall | B13: 12.821411 | C13: 0.15190348 | D13: 1.9476169
... A164: adm1_name | B164: 10.743817 | C164: 0.20301259 | D164: 2.1811302
A165: adm2_name | C165: 0 | D165: 0
A166: covid | B166: 56.471024 | C166: 0.20301259 | D166: 11.464329
A167: crp_landright | B167: 31 | C167: 0.0040467626 | D167: 0.12544964
A168: crp_seed | B168: 30.833334 | C168: 0.0040467626 | D168: 0.12477518
A169: crp_proddif | B169: 16.882986 | C169: 0.11848022 | D169: 2.0002998
A170: crp_salesdif | B170: 16.82699 | C170: 0.086630695 | D170: 1.4577339
A171: crp_saledif_2 | B171: 39.486874 | C171: 0.03139988 | D171: 1.2398831
A172: ls_proddif | B172: 15.938099 | C172: 0.10169365 | D172: 1.6208034
A173: ls_salesdif | B173: 13.330855 | C173: 0.060476619 | D173: 0.80620506
A174: ls_proc | B174: 16.437651 | C174: 0.0625 | D174: 1.0273532
A175: ls_proc_fac_state | B175: 8.666667 | C175: 0.00067446043 | D175: 0.005845324
A176: fish_proddif | B176: 12.523809 | C176: 0.001573741 | D176: 0.019709232
A177: cs_spentsavings | B177: 22.220184 | C177: 0.0081684652 | D177: 0.1815048
... A193: ls_proddif_2_covid19 | B193: 3.3438249 | C193: 1 | D193: 3.3438249

Sheet Crop list
C3: Select top 10 crops | D3: GeoPoll code | E3: Dataset code | F3: Label (EN) | G3: Label (FR)
C4: x | D4: {=_xlfn.SEQUENCE(90,1,1,1)} -> 1 | E4: 1.1 | F4: Rice | G4: Riz
D5: 2 | E5: 1.2 | F5: Wheat | G5: Blé
C6: x | D6: 3 | E6: 1.3 | F6: Millet | G6: Mil
C7: x | D7: 4 | E7: 1.4 | F7: Sorghum | G7: Sorgho
C8: x | D8: 5 | E8: 1.5 | F8: Maize | G8: Maïs
D9: 6 | E9: 1.6 | F9: Barley | G9: Orge
D10: 7 | E10: 1.99 | F10: Other Cereal | G10: Autres céréales
C11: x | D11: 8 | E11: 2.1 | F11: Cassava | G11: Manioc
C12: x | D12: 9 | E12: 2.2 | F12: Potatoe | G12: Pommes de terre
D13: 10 | E13: 2.3 | F13: Sweet Potatoes | G13: Patates douces
D14: 11 | E14: 2.4 | F14: Yams | G14: Ignames
D15: 12 | E15: 2.5 | F15: Carrots | G15: Carottes
D16: 13 | E16: 2.6 | F16: Cocoyam | G16: Chou caraïbe
D17: 14 | E17: 2.99 | F17: Other tubers | G17: Autres tubercules
C18: x | D18: 15 | E18: 3.1 | F18: Beans | G18: Haricots
D19: 16 | E19: 3.2 | F19: Lentils | G19: Lentilles
D20: 17 | E20: 3.3 | F20: Peas | G20: Pois
C21: x | D21: 18 | E21: 3.4 | F21: Soybeans | G21: Soja
D22: 19 | E22: 3.5 | F22: Chickpeas | G22: Pois chiches
D23: 20 | E23: 3.6 | F23: Fava beans | G23: Fève
D24: 21 | E24: 3.7 | F24: Broad beans | G24: Fève large
D25: 22 | E25: 3.99 | F25: Other pulses | G25: Autres légumineuses
D26: 23 | E26: 4.1 | F26: Cabbage | G26: Choux
D27: 24 | E27: 4.2 | F27: Lettuce | G27: Laitue
D28: 25 | E28: 4.3 | F28: Spinach-Amaranth | G28: Epinards-Amaranthe
D29: 26 | E29: 4.4 | F29: Cassava leaves | G29: Feuilles de manioc
D30: 27 | E30: 4.5 | F30: Potatoe leaves | G30: Feuilles de pomme de terre
D31: 28 | E31: 4.6 | F31: Moringa | G31: Moringa
D32: 29 | E32: 4.7 | F32: Sorrel Hibiscus / Rosselle | G32: Oseille Hibiscus / Rosselle
D33: 30 | E33: 4.9 | F33: Green salad herbs [thyme, parsley, mint, rocca, other] | G33: Herbes aromatiques [thym, persil, menthe, rocca, autres]
... D53: 50 | E53: 7.1 | F53: Sweet Banana | G53: Banane douce
C54: x | D54: 51 | E54: 7.2 | F54: Plantains | G54: Banane plantain
C55: x | D55: 52 | E55: 7.3 | F55: Papaya | G55: Papaye
D56: 53 | E56: 7.4 | F56: Mango | G56: Mangue
D57: 54 | E57: 7.5 | F57: Guava | G57: Goyave
D58: 55 | E58: 7.6 | F58: Pineapple | G58: Ananas
D59: 56 | E59: 7.7 | F59: Avocado | G59: Avocat
D60: 57 | E60: 7.8 | F60: Water Melon | G60: Pastèques
D61: 58 | E61: 7.9 | F61: Dates | G61: Dattes
D62: 59 | E62: 7.101 | F62: Figs | G62: Figues
D63: 60 | E63: 7.11 | F63: Grapes | G63: Raisins
D64: 61 | E64: 7.12 | F64: Olives | G64: Olives
D65: 62 | E65: 7.13 | F65: Apple | G65: Pomme
D66: 63 | E66: 7.14 | F66: Apricot | G66: Abricot
D67: 64 | E67: 7.15 | F67: Cherries | G67: Cerises
... D72: 69 | E72: 8.1 | F72: Coconuts | G72: Noix de coco
C73: x | D73: 70 | E73: 8.2 | F73: Groundnut/peanut | G73: Arachide / cacahuète
D74: 71 | E74: 8.3 | F74: Cashew Nut | G74: Noix de cajou
D75: 72 | E75: 8.4 | F75: Kola Nut | G75: Noix de kola
D76: 73 | E76: 8.5 | F76: Sesame | G76: Sésame
D77: 74 | E77: 8.6 | F77: Bambara nut | G77: Noix de bambara
D78: 75 | E78: 8.7 | F78: Almond | G78: Amande
D79: 76 | E79: 8.8 | F79: Walnut | G79: Noix
D80: 77 | E80: 8.99 | F80: Other nuts | G80: Autres fruits à coque
D81: 78 | E81: 9.1 | F81: Cocoa | G81: Cacao
C82: x | D82: 79 | E82: 9.2 | F82: Coffee | G82: Café
D83: 80 | E83: 9.3 | F83: Tea | G83: Thé
D84: 81 | E84: 9.4 | F84: Sugarcane | G84: Canne à sucre
D85: 82 | E85: 9.5 | F85: Sunflower | G85: Tournesol
D86: 83 | E86: 9.99 | F86: Other food cash crop | G86: Autres cultures vivrières de rente
D87: 84 | E87: 10.1 | F87: Cotton | G87: Coton
D88: 85 | E88: 10.2 | F88: Rubber | G88: Caoutchouc
D89: 86 | E89: 10.3 | F89: Jute | G89: Jute
D90: 87 | E90: 10.4 | F90: Fodder | G90: Fourrage
D91: 88 | E91: 10.5 | F91: Tobacco | G91: Tabac
D92: 89 | E92: 10.6 | F92: Qat | G92: Qat
D93: 90 | E93: 10.99 | F93: Other non-food cash crop | G93: Autre culture de rente non alimentaire

Sheet Additional information
C2: Original EN / FR | D2: Replacement (EN) | E2: Remplacement (FR) | F2: Comment (EN) | G2: Commentaire (FR) | H2: Examples (EN) | I2: Exemples (FR)
B3: FOR CORE QUESTIONS . (Mandatory to fill out) . | C3: ADMIN1 | D3: Province | E3: Province | F3: The first subdivision of the country, after national level; region; province; governorate; etc. | G3: La première subdivision du pays, après le niveau national ; par exemple, région ; province ; gouvernorat ; etc. | H3: region | I3: region
C4: ADMIN2 | D4: Territory | E4: Territoire | F4: The second subdivision of the country; district; municipality; LGA; etc. | G4: La deuxième subdivision du pays ; par exemple, district, municipalité, LGA, etc. | H4: district | I4: district
C5: reference year | D5: last year | E5: l'année dernière | F5: Comparison questions will need need a reference year. Select whether you want to use "last year" or "a normal year" as a baseline. A "normal year" should refers to an average year from the past 5 years - make sure to train the enumerators accordingly. | G5: Les questions de comparaison auront besoin d'une année de référence. Choisissez si vous voulez utiliser "l'année dernière" ou "une année normale" comme année de référence. Une "année normale" doit correspondre à une année moyenne des 5 dernières années - veillez à former les recenseurs en conséquence. | H5: a normal year | I5: une année normale
C6: season | D6: Rainy season | E6: Saison des pluies | F6: Name the crop season(s) of interest if there are several cropping seasons in the country (e.g. Meher and Belg in Ethiopia, rainy season / flood-recession cropping / irrigated dry season in the Sahel). You can refer to the “last season” or “ongoing season". | G6: Nommez la ou les saisons culturales concernée(s) en ANGLAIS s'il y en a plusieurs dans le pays (par exemple, Meher et Belg en Ethiopie, saison des pluies / cultures de décrue / saison sèche irriguée au Sahel). Vous pouvez vous référer à la "dernière saison" ou "saison actuelle". | H6: wet season | I6: saison des pluies
C7: season phase | D7: Maturing | E7: Proche de la récolte | F7: Indicate the phase of the season at the time of data collection. If the harvest from the season has not yet occurred, the question on crop harvest (crp_harv_change) will include the word “expected” (where #expected or nothing# is located). If the harvest has occured, "expected" will not be inserted in the question. | G7: Indiquez le stade de la saison culturale au moment de la collecte des données. Si la récolte de la saison n'a pas encore eu lieu, la question sur la récolte des cultures (crp_harv_change) inclura le mot "attendue" (là où se trouve #attendue ou rien#). Si la récolte a eu lieu, "attendue" ne sera pas inséré dans la question. | H7: Harvesting | I7: Récolte
C8: local measurement unit | F8: Specify the local measurement unit for land size, other than acres, hectares, square meters and square feet. If no other unit of measurement is needed, keep this cell blank. | G8: Indiquez l'unité utilisée localement pour mesurer la taille des terrains, autre que les acres, les hectares, les mètres carrés et les pieds carrés. Si aucune autre unité de mesure n'est nécessaire, garder cette cellule vide. | H8: Jeribs | I8: Jeribs
C9: local measurement unit conversion | D9: =IF(E9<>"",E9,"") | F9: Include the conversion of the local measurement unit to hectares. In other words, how many local measurement units are in 1 ha. | G9: Indiquez la conversion de l'unité de mesure locale en hectares. En d'autres termes, indiquez combien d'unités de mesure locales y a-t-il dans 1 ha. | H9: 0.2 | I9: 0.2
B10: FOR OPTIONAL QUESTIONS . (Fill out if applicable) . | C10: currency | D10: CDF | E10: CDF | F10: The name of the main currency used nationally; USD; Naira; Rial; Pesos; etc. | G10: Nom de la principale devise utilisée au niveau national; par exemple, USD; Naira; Rial; Pesos; etc. | H10: Naira | I10: Naira
C11: MIN AMOUNT | D11: 1 | E11: 1 | F11: The minimum amount for an income source should be set at 0 or any value below which it is not possible to do a transaction. For example, the smallest coin/banknote in a currency can be 1000, in which case you would set the minimum at 1000. Provide this input in the same currency as specified above. Only digits should be inputted. | G11: Le montant minimum d'une source de revenu doit être fixé à 0 ou à toute valeur en dessous de laquelle il n'est pas possible d'effectuer une transaction. Par exemple, la plus petite pièce/billet d'une devise peut être de 1000, auquel cas vous fixerez le minimum à 1000. Cette saisie doit être effectuée dans la même devise que celle spécifiée ci-dessus. Seuls des chiffres doivent être saisis. | H11: 5 | I11: 5
C12: MAX AMOUNT | D12: 10000000 | E12: 10000000 | F12: Set the maximum amount for an income source over 3 months. Enumerators will not be able to input values above this amount in questions related to income amounts. Using previous representative surveys for this population, you can estimate this amount by using the mean income plus five (5) standard deviations, unless the country has high inflation. In the latter case, set the maximum value based on your country context (higher than the proposed approach). Provide this input in the same currency as specified above. Only digits should be inputted. | G12: Fixez le montant maximum pouvant être généré par une source de revenu sur 3 mois. Il ne sera pas possible pour les enquêteurs d'entrer des valeurs supérieures à ce montant dans les questions relatives aux montants des revenus. En vous basant sur des enquêtes précédentes représentatives de cette population, vous pouvez estimer ce montant en utilisant le revenu moyen plus cinq (5) écarts types, sauf si le pays connaît une forte inflation. Dans ce dernier cas, fixez la valeur maximale en fonction du contexte de votre pays (plus élevée que l'approche proposée). Cette saisie doit être effectuée dans la même devise que celle spécifiée ci-dessus. Seuls des chiffres doivent être saisis. | H12: 5000000 | I12: 5000000
C13: THRESHOLD | D13: 2000000 | E13: 2000000 | F13: The threshold salary should be calculated to flag outliers (responses that look suspiciously high). Using previous representative surveys for this population, a good estimate is the average plus three (3) standard deviations, which should give the threshold for the 3 or 4% highest income values. Provide this input in the same currency as specified above. Only digits should be inputted. | G13: Le salaire seuil doit être calculé pour signaler les valeurs aberrantes (réponses qui semblent suspectes). En utilisant des enquêtes précédentes représentatives de cette population, une bonne estimation est la moyenne plus deux écarts types, ce qui devrait dégager le seuil pour les 3 ou 4% des valeurs de revenu les plus élevées. Cette saisie doit être effectuée dans la même devise que celle spécifiée ci-dessus. Seuls des chiffres doivent être saisis. | H13: 1200000 | I13: 1200000
C14: local vegetables | D14: Funbwa, spinach, cabbage, carrot | E14: Fumbwa, épinard, choux, carottes | F14: Input some common local vegetables [to be used as examples in the food consumption score indicator]. | G14: Saisissez quelques légumes locaux courants [à utiliser comme exemples dans l'indicateur de score de consommation alimentaire]. | H14: eggplants, zucchini, cauliflower | I14: aubergines, courgettes, choux-fleurs
C15: local fruits | D15: bananas, oranges, mangos | E15: bananes, oranges, mangues | F15: Input some common local fruits [to be used as examples in the food consumption score indicator]. | G15: Indiquez quelques fruits locaux courants [à utiliser comme exemples dans l'indicateur de score de consommation alimentaire]. | H15: apples, bananas, oranges | I15: pommes, bananes, oranges
B17: FILL OUT FOR QUESTIONNAIRE DURATION ESTIMATION . | C17: Expected percentage of respondents cultivating crops | D17: =IF(E17="","",E17) -> 0.75 | E17: 0.75 | F17: If the survey is representative and has no quotas, write the proportion of rural households cultivating crops at country level, or if the survey follows a previous round with identical sample design, just report the percentage from the previous round. If you are using quotas, calculate the ratio of the quota over the minimum sample size at the level where the quota is implemented (so if you have a minimum sample size per strata of 110 with a quota of 100 crop producers, then it's 100/110 = 91% (the maximum you should write is 100%). | G17: Si l'enquête est représentative et ne comporte pas de quotas, écrivez la proportion de ménages ruraux impliqués dans les cultures au niveau du pays, ou si l'enquête suit un cycle précédent avec un plan d'échantillonnage identique, indiquez simplement le pourcentage du cycle précédent. Si vous utilisez des quotas, calculez le rapport entre le quota et la taille minimale de l'échantillon au niveau où le quota est appliqué (ainsi, si vous avez une taille minimale d'échantillon par strate de 110 avec un quota de 100 producteurs de cultures, alors c'est 100/110 = 91% (le maximum que vous devez écrire est 100%). | H17: 0.91 | I17: 0.91
C18: Expected percentage of respondents raising livestock | D18: =IF(E18="","",E18) -> 0.2 | E18: 0.2 | F18: If the survey is representative and has no quotas, write the proportion of rural households raising livestock at country level, or if the survey follows a previous round with identical sample design, just report the percentage from the previous round. If you are using quotas, calculate the ratio of the quota over the minimum sample size at the level where the quota is implemented (so if you have a minimum sample size of 110 but a quota of 100 livestock producers, then it's 100/110 = 91% (the maximum you should write is 100%) | G18: Si l'enquête est représentative et ne comporte pas de quotas, écrivez la proportion de ménages ruraux impliqués dans l'élevage, ou si l'enquête suit un cycle précédent avec un plan d'échantillonnage identique, indiquez simplement le pourcentage du cycle précédent. Si vous utilisez des quotas, calculez le rapport entre le quota et la taille minimale de l'échantillon au niveau où le quota est appliqué (ainsi, si vous avez une taille minimale d'échantillon par strate de 110 avec un quota de 100 éleveurs, alors c'est 100/110 = 91% (le maximum que vous devez écrire est 100%). | H18: 0.91 | I18: 0.91
C19: Expected percentage of respondents involved in fishery | D19: =IF(E19="","",E19) -> 0.05 | E19: 0.05 | F19: If the survey is representative and has no quotas, write the proportion of rural households involved in fisheries or aquaculture, otherwise if you are using quotas, calculate the ratio of the quota over the sample size at the level where the quota is implemented. (so if you haven't set a quota, and you expect to have a representative proportion of fishermen, just write the percentage of fishermen in the population you are targeting, in the example to the right, 5%) | G19: Si l'enquête est représentative et ne comporte pas de quotas, écrivez la proportion de ménages ruraux impliqués dans la pêche ou l'aquaculture; sinon, si vous utilisez des quotas, calculez le rapport entre le quota et la taille de l'échantillon au niveau où le quota est appliqué (ainsi, si vous n'avez pas fixé de quota, et que vous pensez avoir une proportion représentative de pêcheurs, écrivez simplement le pourcentage de pêcheurs dans la population que vous ciblez, dans l'exemple à droite, 5%). | H19: 0.05 | I19: 0.05

Sheet Admin 2 info1
A1: adm2_name | B1: adm2_name_local | C1: adm2_pcode | D1: adm1_name | E1: adm1_pcode | F1: adm0_name | G1: adm0_ISO3
A2: Gemena | B2: Gemena | C2: CD4202 | D2: Sud-Ubangi | E2: CD42 | F2: Democratic Republic of the Congo | G2: COD
A3: Gbadolite | B3: Gbadolite | C3: CD4301 | D3: Nord-Ubangi | E3: CD43 | F3: Democratic Republic of the Congo | G3: COD
A4: Fizi | B4: Fizi | C4: CD6210 | D4: Sud-Kivu | E4: CD62 | F4: Democratic Republic of the Congo | G4: COD
A5: Feshi | B5: Feshi | C5: CD3103 | D5: Kwango | E5: CD31 | F5: Democratic Republic of the Congo | G5: COD
A6: Faradje | B6: Faradje | C6: CD5307 | D6: Haut-Uele | E6: CD53 | F6: Democratic Republic of the Congo | G6: COD
A7: Dungu | B7: Dungu | C7: CD5305 | D7: Haut-Uele | E7: CD53 | F7: Democratic Republic of the Congo | G7: COD
A8: Djugu | B8: Djugu | C8: CD5405 | D8: Ituri | E8: CD54 | F8: Democratic Republic of the Congo | G8: COD
A9: Djolu | B9: Djolu | C9: CD4504 | D9: Tshuapa | E9: CD45 | F9: Democratic Republic of the Congo | G9: COD
A10: Dingila | B10: Dingila | C10: CD5210 | D10: Bas-Uele | E10: CD52 | F10: Democratic Republic of the Congo | G10: COD
A11: Dimbelenge | B11: Dimbelenge | C11: CD9107 | D11: Kasaï-Central | E11: CD91 | F11: Democratic Republic of the Congo | G11: COD
A12: Dilolo | B12: Dilolo | C12: CD7205 | D12: Lualaba | E12: CD72 | F12: Democratic Republic of the Congo | G12: COD
... A190: Goma | B190: Goma | C190: CD6101 | D190: Nord-Kivu | E190: CD61 | F190: Democratic Republic of the Congo | G190: COD
