Workbook

Sheet survey
A1: type | B1: name | C1: label::English (en) | D1: label::French (fr) | E1: label::Haoussa (ha) | F1: label::Djerma (dj) | G1: label::Peulh (pe) | H1: label::Kanuri (kr) | I1: label::Tamachek (ta) | J1: label:: | K1: hint::English (en) | L1: hint::French (fr) | M1: hint::Haoussa (ha) | N1: hint::Djerma (dj) | O1: hint::Peulh (pe) | P1: hint::Kanuri (kr) | Q1: hint::Tamachek (ta) | R1: hint:: | S1: required | T1: appearance | U1: constraint | V1: constraint_message | W1: relevant | X1: choice_filter | Y1: parameters | Z1: calculation | AE1: Mandatory | AG1: New question duration (sec) | AH1: Estimated percentage of repondents | AI1: Weighted time | AJ1: Weighted time for core vars
A2: start | B2: start | AI2: =IF(AG2<>"",AG2*AH2,"") | AJ2: =IF(AND(AG2<>"",AE2="yes"),AG2*AH2,"")
A3: end | B3: end | AI3: =IF(AG3<>"",AG3*AH3,"") | AJ3: =IF(AND(AG3<>"",AE3="yes"),AG3*AH3,"")
A4: today | B4: today | AI4: =IF(AG4<>"",AG4*AH4,"") | AJ4: =IF(AND(AG4<>"",AE4="yes"),AG4*AH4,"")
A5: deviceid | B5: deviceid | AI5: =IF(AG5<>"",AG5*AH5,"") | AJ5: =IF(AND(AG5<>"",AE5="yes"),AG5*AH5,"")
A6: audit | B6: audit
A7: calculate | B7: audio_random | Z7: once(random())
A8: background-audio | B8: background-audio | W8: ${audio_random}<=0.02 | Y8: quality=low
A9: select_one enumerator | B9: enumerator | C9: Name of enumerator | D9: Nom de l'énquêteur | E9: Sunan mai tambaya | F9: Ay mayo no ti….. | G9: Innde ƴamoowo | H9: Tchou kulachimaye | I9: essim nimissesten | S9: true | T9: autocomplete | AE9: yes | AI9: =IF(AG9<>"",AG9*AH9,"") | AJ9: =IF(AND(AG9<>"",AE9="yes"),AG9*AH9,"")
A10: calculate | B10: enumerator_ | Z10: jr:choice-name(${enumerator},'${enumerator}') | AE10: yes | AI10: =IF(AG10<>"",AG10*AH10,"") | AJ10: =IF(AND(AG10<>"",AE10="yes"),AG10*AH10,"")
A12: note | B12: introduction | C12: Hello sir/ma'am, my name is ${enumerator_}. On behalf of the Food and Agriculture Organization of the United Nations (FAO), we are conducting a survey on household livelihoods and the ability to access food in your area. I would like to ask you some questions about your household. The survey usually takes 20 / 30 minutes to complete. Any information that you provide will be kept strictly confidential, only used for the purpose of the survey and will not be shown to other people. Your voluntary participation in the outcome of this interview is NOT IN ANY WAY linked to your personal chance of receiving any assistance. This is voluntary and you can choose not to answer any or all of the questions if you want. However, we hope that you will participate since your views are important. Do you have any questions? | D12: Bonjour Monsieur/Madame, mon nom est ${enumerator_}. Nous sommes ici de la part de l'Organisation des Nations Unies pour l'alimentation et l'agriculture (la FAO). Nous menons une enquête sur les moyens d'existence et la capacité des ménages à accéder à la nourriture dans votre région. J'aimerais vous poser quelques questions sur votre ménage. L'enquête dure généralement entre 20 / 30 minutes. Toutes les informations que vous fournirez resteront strictement confidentielles; elles ne seront utilisées que dans le cadre de cette enquête et ne seront pas communiquées à d'autres personnes. Votre participation volontaire à cet entretien n'est en AUCUN CAS liée à la possibilité de recevoir une quelconque aide. Votre participation est volontaire et, si vous le souhaitez, vous pouvez choisir de ne pas répondre à une partie ou à la totalité des questions. Cependant, nous espérons que vous voudrez bien participer car votre avis est important. Avez-vous des questions? | E12: Sannu Sir/Madam, sunana ${enumerator_}. Muna nan a madadin Hukumar Abinci da Aikin Noma ta Majalisar Dinkin Duniya (FAO). Muna gudanar da bincike kan abubuwan rayuwa da iyawar gidaje don samun abinci a yankinku. Ina so in yi muku 'yan tambayoyi game da gidan ku. Binciken gabaɗaya yana ɗauka tsakanin mintuna 20/30. Duk bayanan da kuka bayar za a kiyaye su sosai; za a yi amfani da su ne kawai a cikin mahallin wannan binciken kuma ba za a sanar da su ga wasu mutane ba. Kasancewar ku na son rai a cikin wannan hirar ba ta da alaƙa da yuwuwar samun kowane taimako. Shigar da ku na son rai ne kuma, idan kuna so, za ku iya zaɓar kada ku amsa wasu ko duk tambayoyin. Koyaya, muna fatan za ku yarda ku shiga saboda ra'ayin ku yana da mahimmanci. Kuna da wasu tambayoyi? | F12: Mataran go albora/weybora, ay ma ti ${enumerator_}. no ne ayma aran ke Anduniya Fu Beero Kan Ga haw goy nda Mee Nwaari nda Farmoo fondara. Iri goga keki ga bey matan kan kina aran goga bafuney da da mo mata ga aran ga dou me gnwari aran koira ra,iri ga bai iri ma hanyan fo te aran se aran wane almiyalo bon. Aran gonda dama irma fakarey keyna. fahamayey kulu kan aran giri no si goro kala tugurey ;isi goy dey kala hayaney wo fondara boro kulu no si ma rey.da aran ga ba aran ma fouro siguiro ra manti gakasiney du yan kulu se no.aran siguiro ra furo yanwo hima ga te aran bayi koirey ra,da aran si ba manti dole no aran ma tu wala aran matu giarey ga ama dey iri ga gnwarey aran ma tu iri se zakan aran tu yanwo ga beri iri ga.i ga samba aran se keyan noru furo yanwo se .wa bey mo kan iri ga hini ga keyan wo sambu iri ma du ga hagoy da hayan ka iri goga te se no. da aran gonda hayan iri goga hangane aran se. koy da gine? | G12: "Salaamaleykum, binndin'a, isii na ${enumerator_}. Mi bulaaku nan FAO, haa dem ɓeyn'ɗoo oo wi'ɗin'a. Mi ko'booj'o foyƴi bunnudeejeede e wooɗɗudeede e nganndu'e, o faydii mi ko'banndu'ɓe laasiri e toɗɗu oo. Minnde heɗɗoɗo gannde mon ɗemngal wooɗo ko'o huuɗa ndu'ɓe. Mon ɗemɗeɗe yenndi njiidiyaaɗi e laaɓe 20/30. Nde wondudee mi woɗɗaa waɗde nde, mi tawa'ɗe neɗɗo kala. Yaɓɓe wooɗo laaɓe laasiri nii goɗɗiɗo e nde, ka'i kadi ɗum konnde jaaɓi e humpitoondi. Woɗɗo lunniri kala ɗemɗe mi njemra e entenɗa nii kadi. En entenɗa kadi e heɗɗo ngam wooɗɗoo saka mon kala. Kanko, mon ganndaa oo kadi hannde en, sabu nganndu'e nii yahdu mum waɗtoojal. E leɗɓeɗe ɗemngal kadi, woɗɗi njiɗtanteede sundeende. To mo jiɗɗo njiɗɗaa?" | H12: Salaamaleykum, ɓarka da yin asalin kuyanga, sunana ${enumerator_}. Muna hanyar FAO, an samu nasara a gari. Muna gudanar da hanyoyin rayuwarmu da ikirarin kudin jiki a yankin ku. Ina so ka yi min tambayoyin da za ku amsa game da gida. Yanayin rayuwa ya mayar da 20/30 da dari. Duk da cewa za ku amsa, muna son ku yin amfani da shawarwarku. Duk da cewa ku yin kulle-kulle ko duk wani tambayoyi. Hakanan kuma muna son ku ɓoye. Amma, muna yin tsokaci domin rashin amsa ba shi da wani damar samun sadarwa. Ku yiba, idan kun bincike wani tambaya? | I12: Tagodayam nak issinine enumerator. Nahade fell assagawar yigan tegawar titawene inken firgan wassamalan fao. Nosadou iken sistinan ikalnine fel tagawere in guiwanan dik akal nawan. Aré adawounaga issistinan wiyade fell iguiwananawan. Asostan idakal agudiyan 20/30 ən minitan. Isalan dak wi mad tifim adakamin aylan garenaɣ, imba damatkalan ad-daɣ tabarat tan asostan əd imba diqilan atiwalaɣen ye idinat iyad. Wala iyan asostan ən nawadim wa rika atwisiɣim. Tihawt nawan ən tiridawt daɣ liɣitan ən asostan wen wareqel daɣ WALA IYAT tabarat tartayat əd tabaɣor nadinat ye agaraw ən atamosan tilalt. Eqal tiridawt əd tadobem atikisam iba nəliɣi ye asostan meɣ asostanan dak afal tarham awen. Agudendaɣ, norda as atigišam falas erhet nawan eqal ayfan. Tilam asostan ? | K12: [INSTRUCTIONS: ADDRESS QUESTIONS FROM RESPONDENT, IF ANY.] | L12: [OPÉRATEUR/OPÉRATRICE: LE CAS ÉCHÉANT, RÉPONDRE AUX QUESTIONS DE LA PERSONNE INTERROGÉE.] | M12: [mai tambaya: IDAN AKWAI, AN AYI TAMBAYA GA MUTUM DA ZA A SHIRIYA.] | N12: Ha ko: da tou ko yarda, i ga tou a wana ha yan wo sé | O12: [GAƊOOWO GOLLAL NGAL DEBBO NAA GORKO SE HEƁAAKA, NOOTO ƳAMƊE ƳAMAAƊO ON .] | P12: Kasuma/kamu aw kwa Am njade diyonadu korowa jawuwadu tchadunaro waltou | Q12: amachaghal / timachaghalte : astouwirilen adajawab awedan yissistanane wintawaganen yawedan wassihor dastiwigune | S12: false | AE12: no | AG12: 50.82254 | AI12: =IF(AG12<>"",AG12*AH12,"") -> 0 | AJ12: =IF(AND(AG12<>"",AE12="yes"),AG12*AH12,"")
A13: select_one yesno | B13: resp_agree | C13: Are you interested in participating in this survey? | D13: Souhaitez-vous participer à cette enquête? | E13: KU na so ku shiga wannan binciken? | F13: Aran ga ba aran ma furo iri hayan siguiro ra? | G13: Adayidi wonude e ngol humpitigol naa? | H13: Nyiye kulashi korobe adəro rəbtaadə məradənəma wa? | I13: Tardede Assintide? | S13: false | AE13: yes | AG13: 3.5 | AH13: =1 -> 1 | AI13: =IF(AG13<>"",AG13*AH13,"") -> 3.5 | AJ13: =IF(AND(AG13<>"",AE13="yes"),AG13*AH13,"") -> 3.5
A14: geopoint | B14: gps_1 | C14: GPS INSTRUCTION: Take a GPS measurement. | D14: INSTRUCTION : Récupérer les coordonnées GPS. | E14: Umarni: Daukar labarun gidan da na'oura | F14: Koira fo no aran go ga tou ir sé? | G14: TINNDINOORE : ɗum ada ko GPS wurtini. | I14: Tissousinte :ibazadou raquaman in tissidik koul | K14: NOTE: It might take a few minutes for the tablet to register the GPS. Wait for it to load. If it takes longer than 3 minutes, skip to the next question. You can take the GPS reading at the end of the interview. | L14: REMARQUE : L'enregistrement des coordonnées peut prendre quelques temps - il faudra peut-être patienter quelques minutes. Si cela prend plus de 3 minutes, passez à la question suivante. Vous pouvez récupérer les coordonnées GPS à la fin de l'entretien. | M14: JAWABI: Saurar bayanin jiranin GPS za a iya daukar da kwanakin lokacin - za a iya girmama minti biyu. Idan ya dauka minti biyu, tafiya zuwa tambaya ta biyu. Zaka iya samun bayanin GPS bayanin ya gaba da magana. | N14: Labarey: Batama labarey sambu yan wo ga hine ga sambu lokatchi kayna. Aran ga hine suru kayna. Da bissa minti 3, i ma to ha yan fo ga, ir ga yé ga ka labarey din ga, dir bane | O14: PAHME : adol seedaaji no waawi adugo wakkati seɗɗa - haani neɗɗo munya mintaaje seɗɗa. Senii wittake mintaaje 3, haani wittoo e ƴamal yeesowal. Haani adon ko wurtinaa nder GPS se ƴame ɗen ngaynaama | P14: Barka da zuwa! Amsa tawa ayamatu daga samun maganin kayan haƙi kamar dauke da lokaci. Za a iya daukan su bayan minti goma sha uku. Idan aka dauka mafi goma sha uku, duba wuraren sauran tambayan kuma za ka iya samun koordinatun GPS bayan an taimaka. | Q14: Tissousinte : issijil in tissidik ifrag adidkil arate nalwak - ichil adagou awedan tazedarte namazay ghour issistanete assimos ass issistan Di id kal karad minutatane widi adaki awedan sisistan wahadan idi amaran ifrag awedan adibiz raquaman in tissidik ghour agharid in sistanane | S14: false | W14: ${resp_agree} = '1' | AG14: 0 | AH14: 1 | AI14: =IF(AG14<>"",AG14*AH14,"") -> 0
A15: note | B15: Refusal | C15: Thank you for your time, you will be removed from today's survey. | D15: Merci pour votre temps. Vous serez écarté de l'enquête d'aujourd'hui. | E15: Mum gode da lokacin da kuka bamu. ZA'ah cireka daga binciken yau. | F15: Fondo goy nda lokoco kan aran na iri no, iri ga aran ka hayaney siguiro ra hunkuna. | G15: Mi yanti, min nonditan’on {WhenCallBack}. Mi yanti kaden gnan leiin djam | H15: Loktunəm kənjoro nyiro askəra, nya suro kulashi kuye adən tutuluwin. | I15: Nidjake alharadjene, nikaskayine dague issistane ikna yallah achal. | S15: false | W15: ${resp_agree} = '2' | AE15: no | AG15: 0 | AH15: 1 | AI15: =IF(AG15<>"",AG15*AH15,"") -> 0 | AJ15: =IF(AND(AG15<>"",AE15="yes"),AG15*AH15,"")
AI16: =IF(AG16<>"",AG16*AH16,"") | AJ16: =IF(AND(AG16<>"",AE16="yes"),AG16*AH16,"")
A17: begin_group | B17: eligibility | C17: ELIGIBILITY CRITERIA | D17: CRITÈRES D'ÉLIGIBILITÉ | E17: wa'adin zabé | F17: soubane yan Alhalo | G17: LAABI CUƁIRƊI | I17: anamod wan wassitag imidkil | S17: false | W17: ${resp_agree} = '1' | AE17: yes | AI17: =IF(AG17<>"",AG17*AH17,"") | AJ17: =IF(AND(AG17<>"",AE17="yes"),AG17*AH17,"")
AI18: =IF(AG18<>"",AG18*AH18,"") | AJ18: =IF(AND(AG18<>"",AE18="yes"),AG18*AH18,"")
A19: text | B19: resp_firstname | C19: What is your first name? | D19: Quel est votre prénom? | E19: Menene Sunanka ? | F19: Mate no iga aran ce da? | G19: Noy won innde mon? | H19: Abi suwum buroi yo? | I19: Əndek əsim ən-nak ? | K19: [INSTRUCTIONS: RECORD THE RESPONDENT'S FIRST NAME. ENTER 999 FOR REFUSED] | L19: [INSTRUCTIONS : SAISIR LE PRÉNOM DE LA PERSONNE INTÉRROGÉE. SAISIR 999 POUR REFUSÉ.] | M19: [MAI GUDANARWA: SHIGAR DA SUNAN FARKON MAI BADA AMSAR. SHIGAR DA 999 A MADADIN ƘIN AMINCEWA.] | N19: [Hantum ka : wa bora mayo hantoum.wa hantum 999 da bora wandji] | O19: [TINNDINOOJE : WINNDE INNDE NEƊƊO ƳAMAAƊO OON. WINNDEE NDER MASSIN 999 TO SALAKE.] | P19: [ ƘWAREWAƊI : SU BUROI JAWAU MAYE IKK3. IKK3 999 WAA NOMAA.] | Q19: [tissousinte : SAQAYMU ƏSIM ƏN WA ATIWASASTANAN. IGIŠ 999 FAL TUGINT.] | S19: true | AE19: yes | AG19: 10 | AH19: =1 -> 1 | AI19: =IF(AG19<>"",AG19*AH19,"") -> 10 | AJ19: =IF(AND(AG19<>"",AE19="yes"),AG19*AH19,"") -> 10
A20: text | B20: resp_lastname | C20: What is your last name? | D20: Quel est votre nom de famille? | E20: Menene sunanka na ƙarshe? | F20: Ifo ti aran baba mayo? | G20: Noy wani indéé bam’ma / abbaa’ma | H20: Abi suwum darai yo? | I20: Əndek əsim ən alɣayal inak ? | K20: [INSTRUCTIONS: RECORD THE RESPONDENT'S LAST NAME. ENTER 999 FOR REFUSED] | L20: [INSTRUCTIONS : SAISIR LE PRÉNOM DE LA PERSONNE INTÉRROGÉE. SAISIR 999 POUR REFUSÉ.] | M20: Umarni: sunan may bada amsawar. rubuta 999 DON HANA.] | N20: [Hantum ka : wa bora mayo hantoum.wa hantum 999 da bora wandji.] | O20: [TINNDINOOJE : WINNDE INNDE NEƊƊO ƳAMAAƊO OON. WINNDEE NDER MASSIN 999 TO SALAKE.] | P20: [ ƘWAREWAƊI : SU DARAI JAWAU MAYE IKK3. IKK3 999 WAA NOMAA.] | Q20: [tissousinte : SAQAYMU ƏSIM ƏN WA ATIWASASTANAN. IGIŠ 999 FAL TUGINT.] | S20: true | AE20: yes | AG20: 10 | AH20: =1 -> 1 | AI20: =IF(AG20<>"",AG20*AH20,"") -> 10 | AJ20: =IF(AND(AG20<>"",AE20="yes"),AG20*AH20,"") -> 10
AH21: =1 -> 1 | AI21: =IF(AG21<>"",AG21*AH21,"") | AJ21: =IF(AND(AG21<>"",AE21="yes"),AG21*AH21,"")
A22: integer | B22: resp_age | C22: How old are you? | D22: Quel âge avez-vous (en années)? | E22: Shekarunka nawa? | F22: Aran guiri marge? | G22: Duuɓi mon foti? | H22: Saan3m ndawo? | I22: Maniket elan nak ? | K22: [INSTRUCTIONS: RECORD AGE IN NUMBER OF YEARS. ROUND UP TO NEAREST WHOLE NUMBER. IF THE RESPONDENT GIVES BIRTH YEAR, REPEAT THE QUESTION. ENTER 888 FOR DON'T KNOW.] | L22: [INSTRUCTIONS : SAISIR L'ÂGE EN ANNÉES. ARRONDIR AU NOMBRE ENTIER LE PLUS PROCHE. SI LE RÉPONDANT DONNE SON ANNÉE DE NAISSANCE, RÉPÉTER LA QUESTION. SAISIR 888 POUR JE NE SAIS PAS.] | S22: true | U22: (. >= 18 and . <= 100) or . = 888 | AE22: yes | AG22: 13.753073 | AH22: =1 -> 1 | AI22: =IF(AG22<>"",AG22*AH22,"") -> 13.753073 | AJ22: =IF(AND(AG22<>"",AE22="yes"),AG22*AH22,"") -> 13.753073
AH23: =1 -> 1 | AI23: =IF(AG23<>"",AG23*AH23,"") | AJ23: =IF(AND(AG23<>"",AE23="yes"),AG23*AH23,"")
A24: select_one gender | B24: resp_gender | C24: What is the gender of the respondent? | D24: Quel est le sexe du répondant? | E24: Menene jinsin mai amsawar? | F24: Aran wanne tu ka albor no wala weybor? | G24: A débbo naa a gorko? | H24: Jawau mad3 kamu la kongaa? | I24: Indek awa eqal awadim wa itawasastanan? | K24: [INSTRUCTIONS: DO NOT ASK THIS QUESTION OUT LOUD. SELECT THE GENDER OF THE RESPONDENT.] | L24: [OPÉRATEUR/OPÉRATRICE: NE PAS POSER CETTE QUESTION À VOIX HAUTE. INDIQUER LE SEXE DU RÉPONDANT.] | M24: [MAI GUDANARWA: SHIGAR DA SUNAN ƘARSHEN MAI BADA AMSAR. SHIGAR DA 999 A MADADIN ƘIN AMINCEWA.] | N24: [HANTUM ka :wa guirey hantum ,WA GUIREY HANTUM TAK da tu ka na inga heyyan guiro no aran se.WA YEGA HANYANWO KI.WA HANTUM 00 JAN GA BEY YAN SE.] | O24: [GOLLOOWO: TAA ƳAMEE NANNDI ƊE ƳAMƊE. HETTINDE HAALA JOOMUM DE MBINNDON]. | P24: [KUNDOMA: WOND3 KORO ADAA DIMI. K3RINNE DAI JIRE MADAA GONE | Q24: [tissousinte : WAR TIGED ASOSTAN WEN. SIDIRGIN YE TAMASLAQ IZAR IKIS EHAN WA AHUSKEN]. | S24: true | AE24: yes | AG24: 2.1173561 | AH24: =1 -> 1 | AI24: =IF(AG24<>"",AG24*AH24,"") -> 2.1173561 | AJ24: =IF(AND(AG24<>"",AE24="yes"),AG24*AH24,"") -> 2.1173561
AH25: =1 -> 1 | AI25: =IF(AG25<>"",AG25*AH25,"") | AJ25: =IF(AND(AG25<>"",AE25="yes"),AG25*AH25,"")
A26: text | B26: phone_number_personal | C26: What is your phone number? | D26: Quel est votre numéro de téléphone ? | E26: Wacce ce ita lambar wayar?? | F26: Ifo ti aran telfon lamba? | G26: Bataanan limoro mada? | H26: Abi lamba wayamme? | I26: Indek numoro nak wa telefone ? | S26: true | T26: numbers | U26: regex(.,’^[0-9]{11}$’) | V26: Please enter the telephone number in the correct format, e.g. nan | AE26: yes - panel | AG26: 10 | AH26: =1 -> 1 | AI26: =IF(AG26<>"",AG26*AH26,"") -> 10 | AJ26: =IF(AND(AG26<>"",AE26="yes"),AG26*AH26,"")
A27: select_one contact_info | B27: contact_2 | C27: Can you give me an additional phone number belonging to you, another household member or a close relation living outside of the household at which you can be reached? | D27: Pouvez-vous me donner un numéro de téléphone supplémentaire, le vôtre, celui d'un autre membre du ménage ou d’un proche vivant en dehors du ménage, auquel vous pouvez être joint? | E27: Zaku iya ba mu wata lambar ku ko ta wani mutunan tchikin guida wanda ku ke da halaka da shi | F27: Da aran gonda lamba hinkanté aran ma ir no, da a siino aran ma ir no ara boro mano wané kan bon ir ga hine ga dou aran. | G27: Haak’kan limoro gnon ko mi wawta mondima ; ba limoro korédjima non ; na limoro hii’go ma non ? | H27: Lamba salulaye kanum aw kam fadoye kamaskinum aw korinube fondikinna! | I27: tifragam didoutakfim raquam nawedan iyan chilan nichikagh nawan madey inmehiz nawan iyan dirwirtanamaham aghiwan assimikan ataghrou awedan | S27: true | AE27: yes - panel | AG27: 10 | AH27: =1 -> 1 | AI27: =IF(AG27<>"",AG27*AH27,"") -> 10 | AJ27: =IF(AND(AG27<>"",AE27="yes"),AG27*AH27,"")
A28: text | B28: phone_number_2 | C28: What is the additional phone number? | D28: Quel est cet autre numéro de téléphone ? | E28: Wacce ce ita lambar wayar?? | F28: Ifo ti lamba wodine? | G28: Won’kan limoro guel guidaa? | H28: Abi lamba wayaye gade madoo? | I28: Indek numoro wa telefone iyan? | S28: true | T28: numbers | U28: regex(.,’^[0-9]{11}$’) | V28: Please enter the telephone number in the correct format, e.g. nan | W28: ${contact_2} = '1' or ${contact_2} = '2' or ${contact_2} = '3' | AE28: yes - panel | AG28: 10 | AH28: =1 -> 1 | AI28: =IF(AG28<>"",AG28*AH28,"") -> 10 | AJ28: =IF(AND(AG28<>"",AE28="yes"),AG28*AH28,"")
A29: text | B29: contact_2_name | C29: What is the name of the contact? | D29: Quel est le nom du contact associé à ce numéro de téléphone ? | E29: Menene sunan mai lambar?? | F29: Mayi fo no go hantum lamba dine bon? | G29: Won’kan indé djom limoro on? | H29: Abi su K3manz3ye? | S29: true | W29: ${contact_2} = '2' or ${contact_2} = '3' | AE29: yes - panel | AG29: 10 | AH29: =1 -> 1 | AI29: =IF(AG29<>"",AG29*AH29,"") -> 10 | AJ29: =IF(AND(AG29<>"",AE29="yes"),AG29*AH29,"")
A30: select_one contact_info | B30: contact_3 | C30: Can you give me an additional phone number belonging to you, another household member or a close relation living outside of the household at which you can be reached? | D30: Pouvez-vous me donner un numéro de téléphone supplémentaire, le vôtre, celui d'un autre membre du ménage ou d’un proche vivant en dehors du ménage, auquel vous pouvez être joint? | E30: Zaku iya ba mu wata lambar ku ko ta wani mutunan tchikin guida wanda ku ke da halaka da shi | F30: Da aran gonda lamba hinkanté aran ma ir no, da a siino aran ma ir no ara boro mano wané kan bon ir ga hine ga dou aran. | G30: Iɗon mbaawi hokkugoyam lammba celalol gooɗom, ɗum mooɗon, ɗum goɗɗo gonuɗo nder hoggo ngon naa banndiraawo mooɗom gom laatiiɗo wana nder hoggo mooɗon wuuri, noddeteeɗo heɓa'on ? | H30: Lamba salulaye kanum aw kam fadoye kamaskinum aw korinube fondikinna! | I30: tifragam didoutakfim raquam nawedan iyan chilan nichikagh nawan madey inmehiz nawan iyan dirwirtanamaham aghiwan assimikan ataghrou awedan | S30: true | W30: ${contact_2} = '1' or ${contact_2} = '2' or ${contact_2} = '3' | AE30: yes - panel | AG30: 10 | AH30: =1 -> 1 | AI30: =IF(AG30<>"",AG30*AH30,"") -> 10 | AJ30: =IF(AND(AG30<>"",AE30="yes"),AG30*AH30,"")
A31: text | B31: phone_number_3 | C31: What is the additional phone number? | D31: Quel est cet autre numéro de téléphone ? | E31: Wacce ce ita lambar wayar?? | F31: Ifo ti lamba wodine? | G31: Ngale won limoro noddirga ɓeydoowa? | H31: Abi lamba wayaye gade madoo? | I31: Indek numoro wa telefone iyan? | S31: true | T31: numbers | U31: regex(.,’^[0-9]{11}$’) | V31: Please enter the telephone number in the correct format, e.g. nan | W31: ${contact_3} = '1' or ${contact_3} = '2' or ${contact_3} = '3' | AE31: yes - panel | AG31: 10 | AH31: =1 -> 1 | AI31: =IF(AG31<>"",AG31*AH31,"") -> 10 | AJ31: =IF(AND(AG31<>"",AE31="yes"),AG31*AH31,"")
A32: text | B32: contact_3_name | C32: What is the name of the contact? | D32: Quel est le nom du contact associé à ce numéro de téléphone ? | E32: Menene sunan mai lambar?? | F32: Mayi fo no go hantum lamba dine bon? | G32: Won’kan indé djom limoro on? | H32: Abi su K3manz3ye? | I32: Indek əsim ən numoro? | S32: true | W32: ${contact_3} = '2' or ${contact_3} = '3' | AE32: yes - panel | AG32: 10 | AH32: =1 -> 1 | AI32: =IF(AG32<>"",AG32*AH32,"") -> 10 | AJ32: =IF(AND(AG32<>"",AE32="yes"),AG32*AH32,"")
AH33: =1 -> 1 | AI33: =IF(AG33<>"",AG33*AH33,"") | AJ33: =IF(AND(AG33<>"",AE33="yes"),AG33*AH33,"")
A34: select_one admin1 | B34: adm1_pcode | C34: Currently, in which Region does your household reside? | D34: Actuellement, dans quel Region votre ménage vit-il ? | E34: A halin yanzu, a wanne Yanki gidanka yake? | F34: Sohon ra,koira fo ra no aran almiyalo go? | G34: Noy hourou mo’gonda an heii korédjima hiité? | H34: K3rmaroo, lardilan fatomanumd3 kara? | I34: Amaradaɣ, indek akal wadaɣ izaɣa alɣayal inak ? | K34: [HINT: HOUSEHOLD CONSISTS OF ALL MEMBERS LIVING TOGETHER, SHARING RESOURCES & EATING FROM THE SAME POT.] | L34: [NOTE : LE MÉNAGE EST COMPOSÉ DE TOUTES LES PERSONNES VIVANT ENSEMBLE, PARTAGEANT LEURS RESSOURCES ET MANGEANT DANS UNE MARMITE COMMUNE.] | M34: [NUSARAWA: GIDA YA ƘUNSHI DUKKAN WAƊANDA SUKE ZAUNE A WURI GUDA, SUKE RARRABA ABABEN TA'AMMULI & SUKE KUMA CI A TUKUNYA ƊAYA.] | N34: Cabe yan :almiyalo ti borrey kulu kan go nangu fo,iga koy keki ga dan tchar ra ga nwaa nongu fo] | O34: [TINNDINOOJE : JAWAABU GOOTO]. [MAANAA: ƁAADE NDEN FUH HAWTU JAWDI E ƳAAMEE LEY NOKKU GOOTO]. | P34: [LAI: FATOMADONI SAIMA AM SAMMA FATOFALLIN DASAUNAMAD3, KUMBUWA RAZAUWA SAMMA ROKKO FAIDATEN.] | Q34: [ASIKIN : ALƔAYAL EQAL AYERTAYAN ƏS ADINAT WI IDARNEN DAK, TUZANEN ANAFATAN ƏD TATAN DAƔ AKOS IYAN]. | S34: true | T34: autocomplete | AE34: yes | AG34: 8.8 | AH34: =1 -> 1 | AI34: =IF(AG34<>"",AG34*AH34,"") -> 8.8 | AJ34: =IF(AND(AG34<>"",AE34="yes"),AG34*AH34,"") -> 8.8
A35: calculate | B35: adm1_name | Z35: jr:choice-name(${adm1_pcode},'${adm1_pcode}') | AE35: yes | AH35: =1 -> 1 | AI35: =IF(AG35<>"",AG35*AH35,"") | AJ35: =IF(AND(AG35<>"",AE35="yes"),AG35*AH35,"")
A36: select_one admin2 | B36: adm2_pcode | C36: Currently, in which Department does your household reside? | D36: Actuellement, dans quel Department votre ménage vit-il ? | E36: A halin yanzu, a wanne Sashi gidanka yake? | F36: Sohon, Iri mee ciino bon, dapatema fo ra no aran almiyalo goga bafuney? | G36: Der département oy hourou mon wonnii ? | H36: K3rmaroo, nashailan fatomad3 kara? | I36: Amaradaɣ, indek akal wadaɣ izaɣ alɣayal inak ? | S36: true | T36: autocomplete | X36: my_filter_admin=${adm1_pcode} | AE36: yes | AG36: 10.4 | AH36: =1 -> 1 | AI36: =IF(AG36<>"",AG36*AH36,"") -> 10.4 | AJ36: =IF(AND(AG36<>"",AE36="yes"),AG36*AH36,"") -> 10.4
A37: calculate | B37: adm2_name | Z37: jr:choice-name(${adm2_pcode},'${adm2_pcode}') | AE37: yes | AH37: =1 -> 1 | AI37: =IF(AG37<>"",AG37*AH37,"") | AJ37: =IF(AND(AG37<>"",AE37="yes"),AG37*AH37,"")
AH38: =1 -> 1 | AI38: =IF(AG38<>"",AG38*AH38,"") | AJ38: =IF(AND(AG38<>"",AE38="yes"),AG38*AH38,"")
A39: select_one agricactivity | B39: hh_agricactivity | C39: Has anybody in your household produced crops or livestock for household consumption or for sale in the past 12 months, including household members currently away for transhumance? | D39: Est-ce que quelqu'un dans votre ménage a produit des cultures ou du bétail pour la consommation du ménage ou pour la vente au cours des 12 derniers mois, y compris des membres du ménage actuellement partis pour la transhumance ? | E39: Shin akwai wani a cikin gidan ku da ya samu anfanin gona ko dabobi don anfanin gida ko sayarwa a cikin watani goma sha biyu da suka shige,game da yan gidan a halin yanzu ba su huce daji ba ? | F39: Borfo aran wane almiyalo ra fari wala na almane kuruu windo nwaro se wala nerandi se handu wey kindi hinka kan bissa ra,I ra hada weykanyan go sadji sohon me kino bon? | G39: Der korédjima no wo’di mo réé’mi na mo wadii bissadjé ko naafii baadéé mon lein’bii sam’po hei di’di bintiidé ; | H39: Fatomaima nandon kulo aw dabba doni sha faidaturo aw lodoro g3naz3na suro k3ntawwa 12 koz3na ad3lan bawa, har fatomadoni tsinyero lezanadin kunten? | I39: Yala awadim daɣ alɣayal nawan igyak əsigyak meɣ arizeg fal ašaško ən alɣayal meɣ fal ašinš daɣ 12 uran wihin okaynen, daɣ ahan adinat nalɣayal amaradaɣ daɣ asikil ? | K39: [INSTRUCTIONS: THIS IS THE MAIN SCREENING QUESTION.] [HINT FOR PROBING: Do you cultivate any plants to sale or consume? Do you raise any animals with the intent of selling or consuming them or their products like meat, milk, wool or leather? Is one of your household member currently away with cattle or other animals for transhumance?] | L39: [INSTRUCTIONS : IL S'AGIT DE LA PRINCIPALE QUESTION DE SÉLECTION.] [CONSEILS POUR PRÉCISER : Cultivez-vous des végétaux afin de les vendre ou de les consommer ? Élevez-vous des animaux afin de les vendre ou de les consommer, y compris les produits issus de l'élevage, comme la viande, le lait, la laine ou le cuir ? L'un des membres de votre ménage est-il actuellement parti avec du bétail pour la transhumance ?] | M39: [ma aikaci/ ma aikacia :Tambaya zabe ] [shawarwari don bayanawa: kuna shuka dian itace ne domin sayarwa ko kuma don ci Kuna kiwon bisashe ne domin sayarwa ko kuma don anfani da su,hata da kayayakin da suka shafi abin da ya fito daga kiwo kamar nama,madara,ulu ko kuma fata ;daya daga cikin en gidan ku sun tafi da dabobi daji ne a halin yanzu don kiwo?] | N39: [Hantum ka : Hayyan bero kan iri ga te aran se wane bon dey no.] [ALAMA : Aran ga fari no nerandi wal nwari se ? Aran ga almane kuruu nerandi wala nwari se, ira hada heykulu kan ga funu almane ga, danga hame,waa, couro ? Sohon me kino bon aran wane koireyze fo koy sadji no da almaney ?] | O39: [TINNDINOOJE : JAWAABU GOOTO. WO ƳAMNGAL GOOTAL CUƁEETE. ƳAMAAƊO ON NA HAANI JAABO. TA NJEGGITON ƳAMUDE E EGGOL DU.] [MAANAA : ƁAADE NDEN FUH HAWTU JAWDI WOOƊI E LE'AL GOOTAL ƁE ƝAAMDATA]. Rèmal mon gan tchan’nol non na gan gna’mal no ? Dourwol bissadjé ma gan tchan’nol non na gan gna’mal no ? | P39: [LAI: FATOMADONI SAIMA AM SAMMA FATOFALLIN DASAUNAMAD3, KUMBUWA RAZAUWA SAMMA ROKKO FAIDATEN.] | Q39: [EMASESTƏN : ALƏƔI IYANDAƔ. AMOS ASOSTAN WA ATIWASANAN DAƔ UKIS. AWADIM WA ATIWASASTANAN ANIHAGA ADISUDMIR. WAHIN TITUWAM ASISTINAM ƏN ASOSTAN FAL MISUKAL]. [ASIKIN : ALƔAYAL EQAL AYERTAYAN ƏN ADINAT WI IDARNEN DAK, TUZANEN TANFOTEN ƏD TATANEN DAƔ AKOS IYANDAƔ]. | S39: true | AE39: yes | AG39: 31.372377 | AH39: =1 -> 1 | AI39: =IF(AG39<>"",AG39*AH39,"") -> 31.372377 | AJ39: =IF(AND(AG39<>"",AE39="yes"),AG39*AH39,"") -> 31.372377
A40: select_one yes_no | B40: hh_fish | C40: Has anybody in your household been engaged in aquatic production [fish catch or aquaculture farming] for household consumption or for sales in the past 12 months? | D40: Quelqu'un dans votre ménage a-t-il été impliqué dans la production aquatique [prise de poisson ou aquaculture] pour la consommation du ménage ou pour la vente au cours des 12 derniers mois? | E40: Wani ne a cikin garinka ya take da alƙawarin baki [bakin samaki ko ayyuka] don tunaniya ko sahuwa tun 12 kafin shekarun baya? | F40: Aran almiyalo ra boro gono kan ga hamissa di wal kan ga hamissa biri gwayan wala néré yan sé djiro kan bissa ra? | G40: Nder hoggo mooɗon goɗɗo no woowi gollideego nder keɓal barke nder ndiyam [nanngol liƴƴi naa n ou fuu gollal keɓal barke nder ndiyam] ngam nyaamndu hoggo naa connol nder ɗii lebbi 12 bittiiɗi ? | H40: Churo koro ay ti churo Kinda 12 Kowouna allan kamdolaa buni tayi kumbu aw lade buni tchiran kassu nin tchilado yuworo gaana mbeyiya | I40: kalatimal awedan daghewan nawan askala igaz ichighil wanabaz in moudaran wine naman chila in kifitan madey anabal waygan daghamass naman fil agana wadikalan tetaye nassan madey inazanassan ghour marawadan dichine wintilkamate | K40: [HINT FOR PROBING: It should not include sports fishing. It should be about production of aquatic products [fish catch or aquaculture farming] for household consumption or sales.] | L40: [CONSEIL LORS DU SONDAGE : cette question et réponse ne devraient pas inclure la pêche sportive. Il s'agit plutôt de la production de produits aquatiques [prise de poisson ou aquaculture] pour la consommation ou la vente des ménages.] | M40: [TAMBAYAR WADANDAYE: wanga tambayoyin ba su chahi ma su zuwa kama kifi dan son ray ba, an'ma sun chahi ma su sana'ar kama kifi [bakin samaki ko ayyuka] don tunkarar ko sahu ko sahiyar saƙo].] | N40: [Konkonsa yamar yan'wo : hayan'wo da tou yan 'wo fataoutchi darbey yan na ga goune, manti] | O40: POOƊOL HAKKILO WAKKATI ETOL PUƊƊIRGOL : ƴamal ngal e nootal ngal haana njahda liƴƴaaki fijooɓe. No keɓal barke faro fuu ko tawaa nder ndiyeele [nanngol liƴƴi naa fuu gollal keɓal barke nder ndiyam] ngam nyaamndu naa connol hoggooji/gure] | P40: (Haware kala kan kuladachidi ma'ri: Jande koro koro atti ama buniwi tchare kubu nanga yeh rounjou, ama buni tchariri galanga nagoro koro koro a ti kan za nini) | Q40: inissikha ghour imidkil : issistan widi daljawab nete wirtaniha ichighil wan Aman . wirtaniha har arate wadikalan abaz imoudaran wine aman chilanabaz in kifitan madey anabal waygan daghamass naman ikalan arate izamatchine madey dinzanzine | S40: true | AE40: no | AG40: 17 | AH40: =1 -> 1 | AI40: =IF(AG40<>"",AG40*AH40,"") -> 17
AH41: =1 -> 1 | AI41: =IF(AG41<>"",AG41*AH41,"") | AJ41: =IF(AND(AG41<>"",AE41="yes"),AG41*AH41,"")
A42: end_group | AI42: =IF(AG42<>"",AG42*AH42,"") | AJ42: =IF(AND(AG42<>"",AE42="yes"),AG42*AH42,"")
A43: begin_group | B43: generalInfo | C43: GENERAL INFORMATION | D43: INFORMATIONS GÉNÉRALES | E43: TAMBAYA GABADEY | F43: Labari beri | G43: ANNDINOOJE MAWƊE | H43: Hawarra Sammmaso | I43: issalan koul | S43: false | W43: ${resp_agree} = '1' and ${hh_agricactivity} != '5' and ${hh_agricactivity} != '6' | AE43: yes | AI43: =IF(AG43<>"",AG43*AH43,"") | AJ43: =IF(AND(AG43<>"",AE43="yes"),AG43*AH43,"")
AH44: =1 -> 1 | AI44: =IF(AG44<>"",AG44*AH44,"") | AJ44: =IF(AND(AG44<>"",AE44="yes"),AG44*AH44,"")
A45: select_one yes_no | B45: resp_id | C45: Are you the head of household? | D45: Êtes-vous le chef de ménage ? | E45: Ku ne mai gidan? | F45: Aran kati windo djine bora? | G45: An wani dontidjo baadé ma? | H45: Nyiyaa kura fatoyewo? | I45: Ataqalad amɣar ən amazaɣ? | S45: true | AE45: yes
A46: select_one gender | B46: hh_gender | C46: Is the head of your household male or female? | D46: Le chef de votre ménage est-il un homme ou une femme ? | E46: Jagoran gidanku namiji ne ko mace? | F46: Aran windo djine boro albor no wala weybor no? | G46: Jom wuro mon wo Debbo naa Gorko? | H46: Kura fatoid3 kongaa la kamu? | I46: Anamokal ən alɣayal nawan eqal ahalis meɣ tamaƭ ? | S46: true | W46: ${resp_id} != '1' | AE46: yes | AG46: 10.085732 | AH46: =1 -> 1 | AI46: =IF(AG46<>"",AG46*AH46,"") -> 10.085732 | AJ46: =IF(AND(AG46<>"",AE46="yes"),AG46*AH46,"") -> 10.085732
AH47: =1 -> 1 | AI47: =IF(AG47<>"",AG47*AH47,"") | AJ47: =IF(AND(AG47<>"",AE47="yes"),AG47*AH47,"")
A48: select_one edu | B48: hh_education | C48: What is the educational level attained by the head of household? | D48: Quel est le niveau d'éducation du chef de votre ménage ? | E48: Dai dai wane aji jagoran gidan naku ya tshaya? | F48: Aran windo djine bora tchaw? | G48: Faa toy dontidjo baadé mon darnii janndé moune? | H48: Abi chi k3ra kura fatoimandoi d3? | I48: Indek hadi ən teɣare ta iwad anamokal ən alɣayal nawan ? | S48: true | AE48: yes | AG48: 12.894034 | AH48: =1 -> 1 | AI48: =IF(AG48<>"",AG48*AH48,"") -> 12.894034 | AJ48: =IF(AND(AG48<>"",AE48="yes"),AG48*AH48,"") -> 12.894034
AH49: =1 -> 1 | AI49: =IF(AG49<>"",AG49*AH49,"") | AJ49: =IF(AND(AG49<>"",AE49="yes"),AG49*AH49,"")
A50: select_one water | B50: hh_wealth_water | C50: Where does the water that you drink at home come from? | D50: Où procurez-vous habituellement l'eau que vous buvez dans votre foyer ? | E50: A ina kuke samo ruwan da kuke anfani da shi don sha a gidan? | F50: Man no aran ga hanyan har ikan aran almiyalo ga goy da? | G50: Toy djogo’tom diame jartédan badéé mon ? | H50: Ndaran nji doi fandon yawinnad3 ishin? | I50: Indek diha əd-ditifalan aman wi sasam ɣur ehan ? | S50: true | AE50: yes | AG50: 15.265829 | AH50: =1 -> 1 | AI50: =IF(AG50<>"",AG50*AH50,"") -> 15.265829 | AJ50: =IF(AND(AG50<>"",AE50="yes"),AG50*AH50,"") -> 15.265829
A51: select_one toilet | B51: hh_wealth_toilet | C51: Where do household members typically go to use the toilet? | D51: Quel genre de toilettes les membres de votre ménage utilisent-ils? | E51: Wane irin bandaki yan iyalin ku ké anfani da shi? | F51: Hal aran té sadjora mouradou, koira bandan no aran ga koy wala mo aran gonda kossandi kan ga a té? | G51: Iri ɗeye lootorɗe ɓiɓɓe hoggo mooɗon naftportoo? | H51: Nagadi ndayin Finza fadon faydaniwi | I51: mini inough nahan nichirid wassataghmal aghiwan nawan | S51: true | AE51: yes | AG51: 15.123718 | AH51: =1 -> 1 | AI51: =IF(AG51<>"",AG51*AH51,"") -> 15.123718 | AJ51: =IF(AND(AG51<>"",AE51="yes"),AG51*AH51,"") -> 15.123718
A52: select_one light | B52: hh_wealth_light | C52: What is the main source of light in your dwelling? | D52: Quelle est la principale source de lumière de votre logement ? | E52: Menene babban tushen haske a cikin gidan ku? | F52: Dandji fo douma no aran ga goy windora? | G52: Iri ngale laytal naftortoɗon nder hoggo mooɗon ? | H52: Kannu haskey ir fizan ndayin fadon faydaniwi | I52: memoss arate wastichghalam dagha agana wadikalan ikouss in chiyaye dagh ehanawane | S52: true | AE52: yes | AG52: 13.760139 | AH52: =1 -> 1 | AI52: =IF(AG52<>"",AG52*AH52,"") -> 13.760139 | AJ52: =IF(AND(AG52<>"",AE52="yes"),AG52*AH52,"") -> 13.760139
AH53: =1 -> 1 | AI53: =IF(AG53<>"",AG53*AH53,"") | AJ53: =IF(AND(AG53<>"",AE53="yes"),AG53*AH53,"")
A54: select_one residence | B54: hh_residencetype | C54: Which in the following types of residence best describes your residence? | D54: Parmi les propositions suivantes, laquelle décrit le mieux votre résidence ? | E54: A cikin waennan wane ne yafi kwatanta matshayin ku? | F54: Wey kan yan iga ki sohoda ra wofo no ga himanda nonkan ra aran go ga? | G54: Ley jonndeeji limtaaɗi fuh ndele ɓuri hollinde galle mon? | H54: Suro naa adiyenlan ndara nandowa samunz3? | I54: Daɣ haditan ən ihinan wi ilkamnen, indek wa asisknan hulen ehan wanak ? | K54: [INSTRUCTIONS: READ OUT THE OPTIONS.] [HINT: IF RESPONDENT IS ONLY AWAY FROM THE HOUSEHOLD FOR SHORT SEASONAL WORK (<6 MONTHS) OR TRANSHUMANCE, MAKE SURE TO REFER TO THEIR HOUSEHOLD BACK WHERE THEY TYPICALLY ARE LOCATED.] | L54: [OPÉRATEUR/OPÉRATRICE: LIRE LES OPTIONS, RÉPONSE UNIQUE]. [CONSEIL: SI LA PERSONNE INTERROGÉE N'EST ÉLOIGNÉE DU FOYER QUE POUR UN TRAVAIL SAISONNIER DE COURTE DURÉE (<6 MOIS) OU POUR LA TRANSHUMANCE, FAIRE RÉFÉRENCE AU FOYER DE RETOUR OÙ ELLE VIT HABITUELLEMENT]. | M54: [MAI GUDANARWA: KARANTA ZAƁUKAN. AMSA GUDA ƊAYA.] [NUSARWA: IDAN MAI BAYAR DA AMSAR YA BAR GIDA NA WANI ƊAN LOKACI (<WATA 6)KO YA TASHI DA DABBOBI, KA TABBATA KA NUNA GIDANSU ida SUKE da zama.] | N54: [ hantum ka : tuyan fonlon.] [ALAMA:hal dey bora kan aran goga ha moru fuyan goy se kan lokacio si ku ga bissa handout idou wala sadji koyyan da almaney se,I ma hantoum nonkan a go za hanno.] | O54: [GOLLOOWO : JANNGON MIILO FUH. SUƁOƊOL GOOTEL.] [MAANAA : SO JAABOTOOƊO ON WO DILLU TEFOY DE MAA WO EGGU FUH KEƊƊOƊON GAARTOL (LEWRU 6)MAKKO DE NJAHON TO O JOOƊII JOONI ƊON.]. | P54: [LAI:JAWAUWA MAD3 FATOWA KOLZ3NA KAU GANAALARO (<K3NTAU 6)AU NAFALLONO, NANZA BUROSALAKK3RO SANDIYA KALANNE.] | Q54: [EMASESTƏN : AƔIRE TABARATEN. ALIƔI IYANDAƔ]. [ASIKIN : AFAL WA ISIDMURAN WAREQEL AWINAN AJIHA DAƔ AMAZAƔ YE AŠIƔIL NALWAQ ƏNDIRAN (<6 URAN)MEƔ FAL IHINAN, ANIHAGA ATIGID NEHAL YE ALƔAYAL INES YE UƔIL ƔUR DIHA DILA AGUDAK]. | S54: true | AE54: no | AG54: 30.646189 | AH54: =1 -> 1 | AI54: =IF(AG54<>"",AG54*AH54,"") -> 30.646189 | AJ54: =IF(AND(AG54<>"",AE54="yes"),AG54*AH54,"")
A55: integer | B55: hh_size | C55: How many people are part of the household? | D55: De combien de personnes est composé votre ménage ? | E55: Mutum nawa ne a cikin gidan ku? | F55: Boro marge no aran wene koira? | G55: Himɓe foto njeyaa e wuro ngo? | H55: Am ndawu fatod3n? | I55: Maniket adinat ahanen alɣayal ? | K55: [INSTRUCTIONS: RECORD NUMBER OF MEMBERS IN HOUSEHOLD. ENTER 888 FOR DON'T KNOW & 999 FOR REFUSED.] [HINT: TO BE A PART OF THE SAME HOUSEHOLD, MEMBERS MUST LIVE UNDER THE SAME ROOF, SHARE THE SAME RESOURCES & EAT FROM THE SAME POT.] | L55: [OPÉRATEUR/OPÉRATRICE: ENREGISTRER LE NOMBRE DE MEMBRES DU MÉNAGE. ENTRER 888 POUR «NE SAIT PAS» ET 999 POUR «REFUSÉ».] [CONSEIL: POUR FAIRE PARTIE D'UN MÊME MÉNAGE, LES MEMBRES DOIVENT VIVRE ENSEMBLE, METTRE EN COMMUN LEURS RESSOURCES ET PARTAGER LEURS REPAS.] | M55: [ma aikaci: ku rubuta adadin mutanen gidan. Ku rubuta 888 don rishin sani.ko kuma 999 don kin amsawa ] [nasiha: en gida guda sunne suke zawne wuri guda suna rayuwa tare a nemo a kuma dinga abinci tare] | N55: [HANTUM Ka: wa HANTUM bora marguia kan gono. Wa hantum 88 djan ga bery se da 99 wandji ga tuyan se] [ALAMA: da aran go windi fo aran hima ga goro nongu fo,aran ma keki ga kande ga nwaa tu folon ra.] | O55: [GOLLOOWO: MBINNDON ADADU HIMƁE ƁAADE MAA WATTON 88 SO ON ANNDAA MAA 99 SO SALAADE]. [HINT: MAANAA: ƁAADE NDEN FUH HAWTU JAWDI E ƳAAMEE LEY NOKKU GOOTO.] | P55: [KUNDOMA: IKKE ADUDU YELLA FATOD3N DASAANAMAD3. KIKE 888 RO NOZA NYI KURU 989 RO WANO] [LAI: SURO AM FATODERO WOLTURO, AM FATODIYE SANDIYE NA FALLIN NAMTASO, AWO Y3KT3SO KURU NJE FALLIN KUMBU BOOSO.] | Q55: [EMASESTƏN : SAQAYMU HADI ƏN ALJAMAƔAT ƏN ALƔAYAL. AGIŠ 988 FAL AD WITISENAD ƏD 999 DAL TUNGIT]. [ASISIƔID : FAL IGI ƏN UGISH ƏN AMAZAƔ, HADI ANIHAGA AS IZAƔAN dǎɣ EHAN IYANdǎɣ, TUZANAN TAMAƔATERTE ƏD TATAN dǎɣ AKOS IYANdǎɣ]. | S55: true | U55: (. >= 1 and . <= 50) or . = 888 or . = 999 | AE55: no | AG55: 15.211848 | AH55: =1 -> 1 | AI55: =IF(AG55<>"",AG55*AH55,"") -> 15.211848 | AJ55: =IF(AND(AG55<>"",AE55="yes"),AG55*AH55,"")
A56: select_multiple asset_prod | B56: hh_asset_prod | C56: Does your household own any of the following productive assets? | D56: Votre ménage possède-t-il l'un des actifs productifs suivants ? | E56: Shin gidan ku yana da ɗaya daga cikin waɗannan kaddarorin masu amfani? | F56: aran wido gonda goy guiney no kirgba ga aran han | G56: Hoggo mooɗon no woodi keɓirɗum barke hano nii ? | H56: Nyiye fatomanumme banalaa k3ntauwa 3 koz3na allan sowond3naa, kuru adai ma, jirifi? | I56: Amazaɣ nawan yala igraw tadhil ihat ɣur dǎɣ 3 uran wi hin okaynen, əd afal iya, əs indek əmik? | K56: [INSTRUCTIONS: MULTIPLE RESPONSES POSSIBLE. READ ANSWER OPTIONS OUT LOUD.] | L56: [OPÉRATEUR / OPÉRATRICE : PLUSIEURS RÉPONSES POSSIBLES. LIRE LES OPTIONS DE RÉPONSE À HAUTE VOIX.] | M56: [Mai aiki: AMSOSHI DAYAWA IYAWA. KARANTA ZABEN AMSA.] | N56: Haka, minga guinda sabou, gatchi touyan kan adou | O56: [GAƊOOWO GOLLAL NGAL DEBBO NAA GORKO : NOOTANƊE ƊUUƊUƊE NO MBAAWI HEƁOOGO. ƊUM TOWNINA KONNGOL FARO JANNDE IRI NOOTANNƊE KEƁETEEƊE.] | P56: [KUNDOMA: JAWAU NGUWU. K3RANE AWO SUROID3.] | Q56: [ƏMASESTƏN : ƏLIƔITAN AJOTNEN. WATAƔRED TABARATEN.] | S56: true | U56: if(selected(.,'none') or selected(.,'dk') or selected(.,'ref'), count-selected(.) = 1, count-selected(.) >= 1) | AE56: no | AG56: 17 | AH56: =1 -> 1 | AI56: =IF(AG56<>"",AG56*AH56,"") -> 17 | AJ56: =IF(AND(AG56<>"",AE56="yes"),AG56*AH56,"")
A57: select_multiple asset_transp | B57: hh_asset_transp | C57: Do you or any member of household own any of the following transportation assets? | D57: Est-ce que vous ou un membre de votre ménage possède un des véhicules suivants ? | E57: Shin ku ko dan gidan ku kuna da ɗaya daga cikin abubuwan hawa masu zuwa? | F57: Aran wal aran windora boro fo gonda motey wo ra douma fo? | G57: Nder hogoo mooɗon i woodi gooɗuɗo hano looreeji ɗii ? | H57: Mota fadon mbeyi kanum aw ja"amado fedayan | I57: aghiwan nawan ihaye awedan Ilan iri in tourifte ta? | K57: [INSTRUCTIONS: MULTIPLE RESPONSES POSSIBLE. READ ANSWER OPTIONS OUT LOUD.] | L57: [OPÉRATEUR / OPÉRATRICE : PLUSIEURS RÉPONSES POSSIBLES. LIRE LES OPTIONS DE RÉPONSE À HAUTE VOIX.] | M57: [Mai aiki: AMSOSHI DAYAWA IYAWA. KARANTA ZABEN AMSA.] | N57: Haka, minga guinda sabou, gatchi touyan kan adou | O57: [GAƊOOWO GOLLAL NGAL DEBBO NAA GORKO : NOOTANƊE ƊUUƊUƊE NO MBAAWI HEƁOOGO. ƊUM TOWNINA KONNGOL FARO JANNDE IRI NOOTANNƊE KEƁETEEƊE.] | P57: [KUNDOMA: JAWAU NGUWU. K3RANE AWO SUROID3.] | Q57: [ƏMASESTƏN : ƏLIƔITAN AJOTNEN. WATAƔRED TABARATEN.] | S57: true | U57: if(selected(.,'none') or selected(.,'dk') or selected(.,'ref'), count-selected(.) = 1, count-selected(.) >= 1) | AE57: no | AG57: 17 | AH57: =1 -> 1 | AI57: =IF(AG57<>"",AG57*AH57,"") -> 17 | AJ57: =IF(AND(AG57<>"",AE57="yes"),AG57*AH57,"")
A58: select_one maritalstat | B58: hh_maritalstat | C58: What is the head of household’s current marital status? | D58: Quel est le status marital actuel du chef de ménage ? | E58: Ya matsayin auren jagoran gidan a halin yanzu? | F58: Aran koira gine bora gonad hidjey ? | G58: Jom wuro jooniijo o ndewluɗo naa o gortaalo? | H58: Kura fatoid3 kamua la kamu ba? | I58: Indek awa eqal aduban ən anamokal ən alɣayal ? | S58: true | AE58: no | AG58: 17 | AH58: =1 -> 1 | AI58: =IF(AG58<>"",AG58*AH58,"") -> 17 | AJ58: =IF(AND(AG58<>"",AE58="yes"),AG58*AH58,"")
AH59: =1 -> 1 | AI59: =IF(AG59<>"",AG59*AH59,"") | AJ59: =IF(AND(AG59<>"",AE59="yes"),AG59*AH59,"")
A60: end_group | AH60: =1 -> 1 | AI60: =IF(AG60<>"",AG60*AH60,"") | AJ60: =IF(AND(AG60<>"",AE60="yes"),AG60*AH60,"")
A61: begin_group | B61: Income_Shocks_group | C61: INCOME SOURCES, LIVELIHOODS AND SHOCKS | D61: SOURCES DE REVENUS, MOYENS DE SUBSISTANCE ET CHOCS | E61: TUSHEN KUDI, ARZIKI DA TSORO | F61: hankan ga da aransse norou | G61: GOLLE KEƁIRƊE CEEDE, LAABI GUURIƊI E PADDORƊE | H61: Chana'a finwa gala ma ro adu awi furtunzuwa kuna | I61: SOURCES DE REVENUS, MOYENS DE SUBSISTANCE ET CHOCS | S61: false | W61: ${resp_agree} = '1' and ${hh_agricactivity} != '5' and ${hh_agricactivity} != '6' | AE61: yes | AH61: =1 -> 1 | AI61: =IF(AG61<>"",AG61*AH61,"") | AJ61: =IF(AND(AG61<>"",AE61="yes"),AG61*AH61,"")
AH62: =1 -> 1 | AI62: =IF(AG62<>"",AG62*AH62,"") | AJ62: =IF(AND(AG62<>"",AE62="yes"),AG62*AH62,"")
A63: select_one incomesource1 | B63: income_main | C63: What was your household's main source of income in the past 3 months? | D63: Quelle était la principale source de revenu de votre ménage au cours des trois derniers mois ? | E63: Menene sular k una farko na samun abun hanun ku a guidan a watani 3 nan da suka shige ? | F63: Ifo ti aran almiyalo norou keki yan fonda handu hinzey kan bissa ra? | G63: Ley lebbi tati sakitiiɗi ɗi ɗume tawaa gollal hooreyan nannanoowan ɓaade mon jawdi? | H63: Abi Lai kenyakkmiyo fatomaye lai nze fandiyeyo kintauwa 3 kozina allan? | I63: Indekat tabarat ta tatiwasanat ən agaraw ən alɣayal nawan daɣ alwaq ən 3 uran wi ilkamnen ? | K63: [INSTRUCTIONS: REFUSED OPTIONS SHOULD BE AVOIDED AS MUCH AS POSSIBLE.] | L63: [INSTRUCTIONS : L'OPTION «REFUSÉ» DOIT ÊTRE, AUTANT QUE POSSIBLE, ÉVITÉE.] | M63: [HUKUNCIN: ZA A GUJEWA ZABIN “DA AKE KI” IRIN YIWU.] | N63: touyan wo ma ba da tchanga touyan wo | O63: [TINNDINOOJE: NOOTAAKI «SALAKE » HAANI, FUU NO ƊUM WAƊATA, RUTTEE | P63: Oumarni hangalene kam kuladachi man ri marery kassa tchin amassa wakina la nonokini | Q63: tissousinte :imissistanane adawiyan tarayen koul chinissikan sirisnate digriwan aljawaban yissistanane nassan | S63: true | T63: minimal | AE63: yes | AG63: 36.928734 | AH63: =1 -> 1 | AI63: =IF(AG63<>"",AG63*AH63,"") -> 36.928734 | AJ63: =IF(AND(AG63<>"",AE63="yes"),AG63*AH63,"") -> 36.928734
A64: calculate | B64: incomemain | Z64: jr:choice-name(${income_main},'${income_main}') | AE64: yes | AH64: =1 -> 1 | AI64: =IF(AG64<>"",AG64*AH64,"") | AJ64: =IF(AND(AG64<>"",AE64="yes"),AG64*AH64,"")
A65: select_one yes_no | B65: income_main_crop_check | C65: Are the crops sold also produced by you or anyone in your household? | D65: Les cultures vendues sont-elles également produites par vous ou quelqu'un de votre ménage? | E65: Shin amfanin gonakin kuma ku ne ko wani a cikin gidan ku ke samarwa? | F65: Farmi guiney karan go nera aran boumbo no go gua i far wala aran windo ra borfo wanne no? | G65: Barke demal connaaɗe onon ndemiɗen naa goɗɗo mo nder hoggo mooɗon? | H65: Kumbu Barey fandou wi ri wundu tchi ladi kassou nin ni mama la yallan nim fadoyen | I65: araten windoutigrawam danabal tizinzamtanine kawaney tanibalan me arate dagh etedan nawan | S65: true | W65: ${income_main} = '1' or ${income_main} = '2' or ${income_main} = '3' | AE65: yes | AG65: 0 | AH65: =1 -> 1 | AI65: =IF(AG65<>"",AG65*AH65,"") -> 0 | AJ65: =IF(AND(AG65<>"",AE65="yes"),AG65*AH65,"") -> 0
A66: select_one yes_no | B66: income_main_ls_check | C66: Are the livestock or livestock products sold also produced by you or anyone in your household? | D66: Le bétail ou les produits du bétail vendus sont-ils également produits par vous ou quelqu'un de votre ménage? | E66: Shin ku ko wani a gidanku ne ke sayar da dabbobin ko dabbobin? | F66: Almanney da djiney kan ga funu almaney ga kan aran goga nera aran wanne no wala aran windo ra borfo wanno? | G66: Bisaaji naa barke keɓeteeɗo e bisaaji connaaɗo onon ngaɗataɗum naa goɗɗo mo hoggo mooɗon ? | H66: Limane aw kumbu limane tcham so tchoukou so nandi ambazo la kam layeh | I66: ihirwan madey arate watandigmadan tizinzamtanine kawaney tidikasan me arate dagh etedan nawan | S66: true | W66: ${income_main} = '4' | AE66: yes | AG66: 0 | AH66: =1 -> 1 | AI66: =IF(AG66<>"",AG66*AH66,"") -> 0 | AJ66: =IF(AND(AG66<>"",AE66="yes"),AG66*AH66,"") -> 0
A67: select_one yes_no | B67: income_main_fish_check | C67: Are the fish or aquatic products sold also captured/harvested by you or anyone in your household? | D67: Le poisson ou les produits aquatiques vendus sont-ils également capturés/récoltés par vous ou un membre de votre ménage? | E67: Shin kifaye ko kayan da ake sayar da su na cikin ruwa su ma kai ko wani dangin ku ne suka kama su? | F67: Hamissey kan i go ga néré, aran no go ga ii di wal aran windora boro fo? | G67: Liƴƴi naa barke keɓeteeɗo nder ndiyam cottaaɗo onon nanngi ɗi naa keptiɗum naa goɗɗo mo nder hoggo mooɗon? | H67: Buni ri la kumbu so kassou ladiwirin wounwoundou woundou so tchara ni la yallan nim so buni ra tcha ra | I67: kifitan madey arate wadigmadan imbal dagh aman kawaney tandibazan me arate dagh etedan nawan | S67: true | W67: ${income_main} = '6' | AE67: yes | AG67: 0 | AH67: =1 -> 1 | AI67: =IF(AG67<>"",AG67*AH67,"") -> 0 | AJ67: =IF(AND(AG67<>"",AE67="yes"),AG67*AH67,"") -> 0
AH68: =1 -> 1 | AI68: =IF(AG68<>"",AG68*AH68,"") | AJ68: =IF(AND(AG68<>"",AE68="yes"),AG68*AH68,"")
A69: decimal | B69: income_main_amount | C69: How much was earned (in Francs CFA) from your main income source, ${incomemain}, in the past 3 months ? | D69: Quelle somme (en Francs CFA a rapporté votre principale source de revenu, ${incomemain}, au cours des trois derniers mois ? | E69: Kama nawa aka samu [a kuɗin CFA] abuda kukeyi {income_main},ya kawo muku wata uku da suka shige? | F69: Margue goyo kan aran goga noro kekin da kade aran se handu hinzey kan bissa ra? | G69: No CFA buudi foti heɓuɗon e gollal mon hooreyal nannangal ɗiɗi on jawdi ${incomemain}}, ley ko sakitii e ɗi lebbi 3. | H69: Ndawu fandum [ kunguna CFA ] suro lainum kunguna fandoi madin, {income_main}, kuntauwa 3 kozina allan? | I69: Maniket atigrawam [daɣ CFA] ən tanak tabarat nagaraw, {income_main}, ɣur karad uran wi dilkamnen ? | K69: [INSTRUCTIONS: MAKE SURE THE INFORMATION IS RECORDED IN THE CORRECT CURRENCY. ENTER 888 FOR DON'T KNOW AND 999 FOR REFUSED.] | L69: [INSTRUCTIONS : VÉRIFIER QUE LE MONTANT EST ENREGISTRÉ DANS LA BONNE DEVISE. SAISIR 888 POUR «NE SAIT PAS» ET 999 POUR «REFUSÉ».] | M69: [HUKUNCIN: ku tabatarda kun rubuta amsa a cikin farashin da ya kamata,ku danna 88888888 don rishin sanni DA KUMA 99999999 A MATSAYIN kin amsawa.] | N69: [ HANTUM ka: wa tabatandi kan I na noro dima hantum ka bori.HANTUM 888 djan ga beyrey SE, 999 wandjin gat u yan se] | O69: [TINNDINOOJE : TAYKINEEKE KE JAWAABU ON NA SELLI. MAA WONNITOƊON ON. ADEE 888 SO ON ANNDAA MAA 999 SO SALAADE.]. | P69: [KUNDOMA: walt3na rui nyiye am kattuu kamzanaa & awo gulzanauso kalkallo kala kung3na gulzanad3n ikke. IKKE 8888888 NO ZAYI ro kuru 9999999 WAANO ro.] | Q69: [EMASESTƏN: ASIN AS ISALAN WARAQELAN AWINAN IKNA ƏD AQALAN AQIYMAN DAƔ AHUSKEN OƔADAN. AGU 888 AFAL WATISENAD ƏD 999 FALTUGINT]. | S69: true | U69: . > 5 or . = 888 or . = 999 | W69: ${income_main} != '19' and ${income_main} != '20' | AE69: no | AG69: 40.047318 | AH69: =1 -> 1 | AI69: =IF(AG69<>"",AG69*AH69,"") -> 40.047318 | AJ69: =IF(AND(AG69<>"",AE69="yes"),AG69*AH69,"")
A70: select_one continue | B70: income_main_amount_conf | C70: Can you confirm the amount of income you just stated is correct? | D70: Pouvez-vous confirmer que le montant que vous venez de déclarer est correct ? | E70: Kuna iya tabatarwa da adadin kudin da kuka fada hakanan ne? | F70: Aran ga hini ga tabatandi kan noro kan aran ki iri se yadine no ? | G70: Na on heɓi ngonndinde ke adadu buuɓi keɓal ɗi mbiiɗon ɗi wo noon? | H70: Nyiye walt3m adudu fandiyimme gullumamad3 gulluminna? | I70: Tadobem asidutem as hadi nagaraw wa tisiknam eqal oɣadan ? | K70: [INSTRUCTIONS: IF THE RESPONDENT CONFIRMS THAT THE INCOME AMOUNT EARNED FROM THIS INCOME SOURCE OVER THE PAST 3 MONTH IS INDEED OVER 450000, CLICK ON CONTINUE. OTHERWISE, GO BACK AND CHANGE THE AMOUNT ENTERED.] | L70: [INSTRUCTIONS : SI LE RÉPONDANT CONFIRME QUE LE MONTANT ISSU DE CETTE SOURCE DE REVENU AU COURS DES TROIS DERNIERS MOIS EST BIEN SUPÉRIEUR AU 450000, CLIQUER SUR CONTINUER. SINON, REVENIR EN ARRIÈRE ET MODIFIER LE MONTANT SAISI.] | M70: [HUKUNCI: KYAUTA A KADAN KALMOMI BABBAN SAKAMAKON ARZIKI NA KWANA. Shigar da 888 DON "BAN SANI" DA 999 DON "KASHI"]. | N70: Da haka tchi aranse hanka d'où gato 450 000 aan koy da guitare, da neh aussitôt aran m'a ye banda ga hanser | O70: [TINNDINOOJE : SENII NOOTOTOOƊO TABBININII CEEDE KEƁAAƊE NDER GOLLE ƊEN NDER LEBBI TATI BITTIIƊI, MBITTAKE UJUNAAJE 90 (450000 FCAF) , NOƳƳEE DOW YAHA YEESO. NDE WANAA NON WARTA GAƊA NDEN MOƳƳINA CEEDE ƊE WINNDI ] | P70: Dama fonduma koromanum niro tabbatcuw jarzu kindawu yasku ngawoye kozuna allan 450000 tacinaa ranne lezu wande ngoworo woltuni. | Q70: [EMASESTƏN: AFAL HADI NAWA ATWAGRAWAN ƏN TABARAT TEN ƏN AGARAW DAƔ KARAD URAN WI ILKAMNEN EQAL OGARAN 450 000 ƏFA, AGIŠ FAL UKIY. AFAL BABO, AQILID ƏZDARAƬ ƏD SIMUTIY HADI WA TIGED]. | S70: false | W70: ${income_main_amount} >= 450000 and (${income_main} != '19' and ${income_main} != '20') | AE70: no | AG70: 3.687011 | AH70: =1 -> 1 | AI70: =IF(AG70<>"",AG70*AH70,"") -> 3.687011 | AJ70: =IF(AND(AG70<>"",AE70="yes"),AG70*AH70,"")
A72: select_one gender_inc_1 | B72: income_main_gender | C72: What is the gender of the household member(s) generating income from this source? | D72: Quel est le sexe du ou des membres qui génèrent des revenus de cette source ? | E72: Menene jinsi na memba (s) da ke samar da kudin shiga daga wannan tushe? | F72: Windora, weyborey wal alborey no go ga kambé dan tcharra ga goyo té? | G72: Rewɓe non naa worɓe ngoni no keɓa ceede ɗen? | H72: Churo fandoyen kamu la gonga douno waro na wiro ma royen | I72: mamossan etedan chidoden me medan winogarnen aguenarate ? | S72: true | W72: ${income_main} != '19' and ${income_main} != '20' | AE72: yes
A73: select_one gender_inc_2 | B73: income_main_control | C73: Who controls the revenue that is earned from this source? | D73: Qui contrôle les revenus qui proviennent de cette source? | E73: Wanene ke sarrafa kudaden shiga da ke fitowa daga wannan tushe? | F73: May no go ga haggoy da noro kan i go ga dou goyo ra? | G73: Mo woni deenoowo rsiku keɓaangu nder ngollal ngal ? | H73: Kamm wundu do fandon chana'a adiye kladu curin | I73: metifan darate wassataghmalan etedan ? | S73: true | W73: ${income_main} != '19' and ${income_main} != '20' | AE73: yes
AH74: =1 -> 1 | AI74: =IF(AG74<>"",AG74*AH74,"") | AJ74: =IF(AND(AG74<>"",AE74="yes"),AG74*AH74,"")
A75: select_one change | B75: income_main_comp | C75: Has your household's income from ${incomemain} changed in the last 3 months compared to the same period of a normal year? | D75: Le revenu de votre ménage provenant de ${incomemain} a-t-il changé au cours des trois derniers mois par rapport à la même periode de une année normale ? | E75: Shin tushen kudin da kuke {income_main} samu ya canza cikin watanni uku da suka shige idan aka kwatanta da lokaci kamar wannan a cikin shekara irin na kulum? | F75: Aran wane noro kan aran du goyo karan te wate handu hinzey kan bissa barmey danga sonkine guiro kan bissa? | G75: Keɓal ɓaade mooɗon {income_main} waylake nder lebbi 3 cakitiiɗi ɗii so fonndaama e hono oo wakkati e hitaande hiɓɓunde fuh? | H75: Fandi fatomanumme ${incomemain} falt3naa k3ntauwa yakku 3 koz3na Allan sha saa k3mende allan? | I75: Yala igarawan ən amazaɣ nawan wad idahanen əs ${incomemain} amutayan ɣur dǎɣ 3 uran widǎɣ ahin okaynen dǎɣ sund alwaq ən azaman dǎɣ awatay əmdan? | S75: true | W75: ${income_main} != '19' and ${income_main} != '20' | AE75: yes | AG75: 27.242167 | AH75: =1 -> 1 | AI75: =IF(AG75<>"",AG75*AH75,"") -> 27.242167 | AJ75: =IF(AND(AG75<>"",AE75="yes"),AG75*AH75,"") -> 27.242167
AH76: =1 -> 1 | AI76: =IF(AG76<>"",AG76*AH76,"") | AJ76: =IF(AND(AG76<>"",AE76="yes"),AG76*AH76,"")
A77: select_one incomesource2 | B77: income_sec | C77: What was your household's second most important source of income in the past 3 months? | D77: Quelle était la deuxième source principale de revenu de votre ménage au cours des trois derniers mois ? | E77: Menene sular k una farko na samun abun hanun ku a guidan a watani 3 nan da suka shige ? | F77: Ifo ti aran almiyalo norou keki yan fonda handu hinzey kan bissa ra? | G77: Ngolle won laawol keɓal ɗiɗaɓol ɓurngol nannande ɓaade jawdi ley lebbi 3 sakitiiɗi ɗi? | H77: Abi Lai kindimiyo fatomaye lai nze fandiyeyo kentauwa 3 kozena allan? | I77: Indek tas sanatat tabarat ən agaraw wa togarat tanfo ən alɣayal nawan ɣur 3 uran wi dilkamnen ? | K77: [INSTRUCTIONS: DON'T KNOW AND REFUSED OPTIONS SHOULD BE AVOIDED AS MUCH AS POSSIBLE.] | L77: [INSTRUCTIONS : LES OPTIONS «NE SAIT PAS» ET «REFUSÉ» DOIVENT ÊTRE ÉVITÉES AUTANT QUE POSSIBLE]. | M77: [HUKUNCIN: ZA A GUJEWA ZABIN “DA AKE KI” IRIN YIWU.] | N77: touyan wo ma ba da tchanga touyan wo | O77: [TINNDINOOJE: NOOTAAKI «SALAKE » HAANI, FUU NO ƊUM WAƊATA, RUTTEE | P77: [ Gargajiya: JAWAU FAL NGULONG. WAANO GOTAD3 ZAURO NGUU MBEJIMA NG3LAU.] | Q77: tissousinte :imissistanane adawiyan tarayen koul chinissikan sirisnate digriwan aljawaban yissistanane nassan | S77: true | T77: minimal | W77: ${income_main} != '19' and ${income_main} != '20' | X77: not(selected(${income_main}, name)) | AE77: yes | AG77: 25.308004 | AH77: =1 -> 1 | AI77: =IF(AG77<>"",AG77*AH77,"") -> 25.308004 | AJ77: =IF(AND(AG77<>"",AE77="yes"),AG77*AH77,"") -> 25.308004
A78: calculate | B78: incomesec | Z78: jr:choice-name(${income_sec},'${income_sec}') | AE78: yes | AH78: =1 -> 1 | AI78: =IF(AG78<>"",AG78*AH78,"") | AJ78: =IF(AND(AG78<>"",AE78="yes"),AG78*AH78,"")
A79: select_one yes_no | B79: income_sec_crop_check | C79: Are the crops sold also produced by you or anyone in your household? | D79: Les cultures vendues sont-elles également produites par vous ou quelqu'un de votre ménage? | E79: Shin amfanin gonakin kuma ku ne ko wani a cikin gidan ku ke samarwa? | F79: Doumarisey kan I go ga néré, aran no ni douma wal mo aran windora boro fo? | G79: Barke demal connaaɗe onon ndemiɗen naa goɗɗo mo nder hoggo mooɗon? | H79: Kumbu Barey fandou wi ri wundu tchi ladi kassou nin ni mama la yallan nim fadoyen | I79: Isigyak wihin tišišanmin aqalan adizgaran fal lawan meɣ fal awadim ən alɣayal nawan ? | S79: true | W79: ${income_sec} = '1' or ${income_sec} = '2' or ${income_sec} = '3' | AE79: yes | AG79: 0 | AH79: =1 -> 1 | AI79: =IF(AG79<>"",AG79*AH79,"") -> 0 | AJ79: =IF(AND(AG79<>"",AE79="yes"),AG79*AH79,"") -> 0
A80: select_one yes_no | B80: income_sec_ls_check | C80: Are the livestock or livestock products sold also produced by you or anyone in your household? | D80: Le bétail ou les produits du bétail vendus sont-ils également produits par vous ou quelqu'un de votre ménage? | E80: Shin ku ko wani a gidanku ne ke sayar da dabbobin ko dabbobin? | F80: Almaney wal almaney albarka kan I go néré, aran no na ii biiri wal aran windora boro fo? | G80: Bisaaji naa barke keɓeteeɗo e bisaaji connaaɗo onon ngaɗataɗum naa goɗɗo mo hoggo mooɗon ? | H80: Limane aw kumbu limane tcham so tchoukou so nandi ambazo la kam layeh | I80: Arizeg əd aratan ən arizeg wa šanšem aqalan atigam kawaned me meɣ awadəm iyan ən alɣayal nawan ? | S80: true | W80: ${income_sec} = '4' | AE80: yes | AG80: 0 | AH80: =1 -> 1 | AI80: =IF(AG80<>"",AG80*AH80,"") -> 0 | AJ80: =IF(AND(AG80<>"",AE80="yes"),AG80*AH80,"") -> 0
A81: select_one yes_no | B81: income_sec_fish_check | C81: Are the fish or aquatic products sold also captured/harvested by you or anyone in your household? | D81: Le poisson ou les produits aquatiques vendus sont-ils également capturés/récoltés par vous ou un membre de votre ménage? | E81: Shin kifaye ko kayan da ake sayar da su na cikin ruwa su ma kai ko wani dangin ku ne suka kama su? | F81: Hamissey kan i go ga néré, aran no go ga ii di wal aran windora boro fo? | G81: Liƴƴi naa barke keɓeteeɗo nder ndiyam cottaaɗo onon nanngi ɗi naa keptiɗum naa goɗɗo mo nder hoggo mooɗon? | H81: Buni ri la kumbu so kassou ladiwirin wounwoundou woundou so tchara ni la yallan nim so buni ra tcha ra | I81: Aratan wi nukis ən manan wi šanšem aqalan atiwagan əs kawaned meɣ awadəm iyan ən alɣayal nawan ? | S81: true | W81: ${income_sec} = '6' | AE81: yes | AG81: 0 | AH81: =1 -> 1 | AI81: =IF(AG81<>"",AG81*AH81,"") -> 0 | AJ81: =IF(AND(AG81<>"",AE81="yes"),AG81*AH81,"") -> 0
AH82: =1 -> 1 | AI82: =IF(AG82<>"",AG82*AH82,"") | AJ82: =IF(AND(AG82<>"",AE82="yes"),AG82*AH82,"")
AH83: =1 -> 1 | AI83: =IF(AG83<>"",AG83*AH83,"") | AJ83: =IF(AND(AG83<>"",AE83="yes"),AG83*AH83,"")
A84: select_one change | B84: income_sec_comp | C84: Has your household's income from ${incomesec} changed in the last 3 months compared to the same period of a normal year? | D84: Le revenu de votre ménage provenant de ${incomesec} a-t-il changé au cours des trois derniers mois par rapport à la même période de une année normale ? | E84: Shin kuɗi da kuke nema a canza a cikin watani uku da suka shige idan a ka kwatanta shekara ta kulum? | F84: Aran wane noro kan aran du goy hinkanta karan te wate handu hinzey kan bissa barmey danga sonkine guiro kan bissa? | G84: Keɓal keɓal ɓaade mooɗon ƴuwoowal e ${incomesec} waylake nder lebbi 3 cakitiiɗi ɗii so fonndaama e hono oo wakkati e hitaande hiɓɓunde fuh? | H84: Fandi fatomanumme ${incomesec} falt3naa k3ntauwa yakku 3 koz3na Allan sha saa k3mende allan? | I84: Yala igarawan ən amazaɣ nawan wad idahanen əs {income_sec} amutayan ɣur dǎɣ 3 uran widǎɣ ahin okaynen dǎɣ sund alwaq ən azaman dǎɣ awatay əmdan? | S84: true | W84: ${income_main} != '19' and ${income_main} != '20' and ${income_sec} != '19' and ${income_sec} != '20' and ${income_sec} != '21' | AE84: yes | AG84: 21.193256 | AH84: =1 -> 1 | AI84: =IF(AG84<>"",AG84*AH84,"") -> 21.193256 | AJ84: =IF(AND(AG84<>"",AE84="yes"),AG84*AH84,"") -> 21.193256
AH85: =1 -> 1 | AI85: =IF(AG85<>"",AG85*AH85,"") | AJ85: =IF(AND(AG85<>"",AE85="yes"),AG85*AH85,"")
A86: select_one incomesource3 | B86: income_third | C86: What was your household's third most important source of income in the past 3 months? | D86: Quelle était la troisième source principale de revenu de votre ménage au cours des trois derniers mois ? | E86: Menene sular ku ta uku na samun abun hanun ku a guidan a watani 3 nan da suka shige ? | F86: Ifo ti aran almiyalo norou keki yan fonda handu hinzey kan bissa ra? | G86: Ngolle won laawol keɓal ɗiɗaɓol ɓurngol nannande ɓaade jawdi ley lebbi 3 sakitiiɗi ɗi? | H86: Abi Lai kenyakkmiyo fatomaye ${incomesec} lai nze fandiyeyo kintauwa 3 kozina allan? | I86: Indek tas karadat tabarat ən agaraw wa ogaran tanfo ən alɣayal nawan ɣur karad uran wi dilkamnen ? | K86: [INSTRUCTIONS: DON'T KNOW AND REFUSED OPTIONS SHOULD BE AVOIDED AS MUCH AS POSSIBLE.] | L86: [INSTRUCTIONS : LES OPTIONS «NE SAIT PAS» ET «REFUSÉ» DOIVENT ÊTRE ÉVITÉES AUTANT QUE POSSIBLE]. | M86: [HUKUNCIN: ZA A GUJEWA ZABIN “DA AKE KI” IRIN YIWU.] | N86: touyan wo ma ba da tchanga touyan wo | O86: [TINNDINOOJE: NOOTAAKI «SALAKE » HAANI, FUU NO ƊUM WAƊATA, RUTTEE | P86: [ Gargajiya: JAWAU FAL NGULONG. WAANO GOTAD3 ZAURO NGUU MBEJIMA NG3LAU.] | Q86: [EMASESTƏN : ALƏƔI IYANDAƔ. TABARAT TA TUGAYAT ANIHAGA ATIQIL ATIWAYAN DAƔ HADI ƏN TADABIT]. | S86: true | T86: minimal | W86: ${income_main} != '19' and ${income_main} != '20' and ${income_sec} != '19' and ${income_sec} != '20' and ${income_sec} != '21' | X86: not(selected(${income_main}, name) or selected(${income_sec}, name)) | AE86: yes | AG86: 20.229927 | AH86: =1 -> 1 | AI86: =IF(AG86<>"",AG86*AH86,"") -> 20.229927 | AJ86: =IF(AND(AG86<>"",AE86="yes"),AG86*AH86,"") -> 20.229927
A87: calculate | B87: incomethird | Z87: jr:choice-name(${income_third},'${income_third}') | AE87: yes | AH87: =1 -> 1 | AI87: =IF(AG87<>"",AG87*AH87,"") | AJ87: =IF(AND(AG87<>"",AE87="yes"),AG87*AH87,"")
A88: select_one yes_no | B88: income_third_crop_check | C88: Are the crops sold also produced by you or anyone in your household? | D88: Les cultures vendues sont-elles également produites par vous ou quelqu'un de votre ménage? | E88: Shin amfanin gonakin kuma ku ne ko wani a cikin gidan ku ke samarwa? | F88: Doumarisey kan I go ga néré, aran no ni douma wal mo aran windora boro fo? | G88: Barke demal connaaɗe onon ndemiɗen naa goɗɗo mo nder hoggo mooɗon? | H88: Kumbu Barey fandou wi ri wundu tchi ladi kassou nin ni mama la yallan nim fadoyen | I88: Isigyak wihin tišišanmin aqalan adizgaran fal lawan meɣ fal awadim ən alɣayal nawan ? | S88: true | W88: ${income_third} = '1' or ${income_third} = '2' or ${income_third} = '3' | AE88: yes | AG88: 0 | AH88: =1 -> 1 | AI88: =IF(AG88<>"",AG88*AH88,"") -> 0 | AJ88: =IF(AND(AG88<>"",AE88="yes"),AG88*AH88,"") -> 0
A89: select_one yes_no | B89: income_third_ls_check | C89: Are the livestock or livestock products sold also produced by you or anyone in your household? | D89: Le bétail ou les produits du bétail vendus sont-ils également produits par vous ou quelqu'un de votre ménage? | E89: Shin ku ko wani a gidanku ne ke sayar da dabbobin ko dabbobin? | F89: Almaney wal almaney albarka kan I go néré, aran no na ii biiri wal aran windora boro fo? | G89: Bisaaji naa barke keɓeteeɗo e bisaaji connaaɗo onon ngaɗataɗum naa goɗɗo mo hoggo mooɗon ? | H89: Limane aw kumbu limane tcham so tchoukou so nandi ambazo la kam layeh | I89: Arizeg əd aratan ən arizeg wa šanšem aqalan atigam kawaned me meɣ awadəm iyan ən alɣayal nawan ? | S89: true | W89: ${income_third} = '4' | AE89: yes | AG89: 0 | AH89: =1 -> 1 | AI89: =IF(AG89<>"",AG89*AH89,"") -> 0 | AJ89: =IF(AND(AG89<>"",AE89="yes"),AG89*AH89,"") -> 0
A90: select_one yes_no | B90: income_third_fish_check | C90: Are the fish or aquatic products sold also captured/harvested by you or anyone in your household? | D90: Le poisson ou les produits aquatiques vendus sont-ils également capturés/récoltés par vous ou un membre de votre ménage? | E90: Shin kifaye ko kayan da ake sayar da su na cikin ruwa su ma kai ko wani dangin ku ne suka kama su? | F90: Hamissey kan i go ga néré, aran no go ga ii di wal aran windora boro fo? | G90: Liƴƴi naa barke keɓeteeɗo nder ndiyam cottaaɗo onon nanngi ɗi naa keptiɗum naa goɗɗo mo nder hoggo mooɗon? | H90: Buni ri la kumbu so kassou ladiwirin wounwoundou woundou so tchara ni la yallan nim so buni ra tcha ra | I90: Aratan wi nukis ən manan wi šanšem aqalan atiwagan əs kawaned meɣ awadəm iyan ən alɣayal nawan ? | S90: true | W90: ${income_third} = '6' | AE90: yes | AG90: 0 | AH90: =1 -> 1 | AI90: =IF(AG90<>"",AG90*AH90,"") -> 0 | AJ90: =IF(AND(AG90<>"",AE90="yes"),AG90*AH90,"") -> 0
AH91: =1 -> 1 | AI91: =IF(AG91<>"",AG91*AH91,"") | AJ91: =IF(AND(AG91<>"",AE91="yes"),AG91*AH91,"")
AH92: =1 -> 1 | AI92: =IF(AG92<>"",AG92*AH92,"") | AJ92: =IF(AND(AG92<>"",AE92="yes"),AG92*AH92,"")
A93: select_one change | B93: income_third_comp | C93: Has your household's income from ${incomethird} changed in the last 3 months compared to the same period of a normal year? | D93: Le revenu de votre ménage provenant de ${incomethird} a-t-il changé au cours des trois derniers mois par rapport à la même période de une année normale ? | E93: Shin kuɗi da kuke ${incomethird} nema a canza a cikin watani uku da suka shige idan a ka kwatanta shekara ta kulum? | F93: Aran wane noro kan aran du goy hinzanta karan te wate handu hinzey kan bissa barmey danga sonkine guiro kan bissa? | G93: Keɓal keɓal ɓaade mooɗon ƴuwoowal e ${incomethird} waylake nder lebbi 3 cakitiiɗi ɗii so fonndaama e hono oo wakkati e hitaande hiɓɓunde fuh? | H93: Fandi fatomanumme ${incomethird} falt3naa k3ntauwa yakku 3 koz3na Allan sha saa k3mende allan? | I93: Yala igarawan ən amazaɣ nawan wad idahanen əs {income_third} amutayan ɣur dǎɣ 3 uran widǎɣ ahin okaynen dǎɣ sund alwaq ən azaman dǎɣ awatay əmdan? | S93: true | W93: ${income_main} != '19' and ${income_main} != '20' and ${income_sec} != '19' and ${income_sec} != '20' and ${income_sec} != '21' and ${income_third} != '19' and ${income_third} != '20' and ${income_third} != '21' | AE93: yes | AG93: 16.348396 | AH93: =1 -> 1 | AI93: =IF(AG93<>"",AG93*AH93,"") -> 16.348396 | AJ93: =IF(AND(AG93<>"",AE93="yes"),AG93*AH93,"") -> 16.348396
AH94: =1 -> 1 | AI94: =IF(AG94<>"",AG94*AH94,"") | AJ94: =IF(AND(AG94<>"",AE94="yes"),AG94*AH94,"")
A95: select_multiple shock | B95: shock | C95: Has your household or community faced any particular disaster or crisis affecting your household's ability to raise an income and/or to produce food for self consumption in the last 3 months, and if so, which ones? | D95: Au cours des trois derniers mois, est-ce que votre ménage ou votre communauté ont été confrontés à une catastrophe ou une crise particulières qui a atteint votre capacité à dégager un revenu et/ou à produire des aliments pour votre propre consommation? Si oui, lesquelles? | E95: Shin a cikin watani uku da suka shige gidanku ko kuma al ummar ya taba fuskantar wata annoba ko kuma rikici da ya sakaku kashin kudi ko kula yin abinci don cin ku ? idan hakane wa enne? | F95: Handu hinzey kan bissa ra ,aran windo wala aran kawya mane du hasaraw wala lakal tuney kulu kan na aran gandji noru tetchi yan wala bine aran meh nwaro fari yan?di oho wofoyan ? | G95: Kasaara kewtoke maa fitina tampinɗo buudu mon maa galle mon, de saabii ɓuytaari keɓal mon maa ɓuyti semɓe mon no ngaɗoton no de na on ɲammina gure mon ley lebbi 3 sakitiiɗi ɗi? | H95: Fatomanumye tajirwa laa sha zamzinaa au tajirwa bilai doni fandimma lezinama nasha kumbu kilamme mataro kintauwa 3 kozina allan? | I95: Alɣayal nawan yala inhay asuɣsadan meɣ iba ən harat iyan igrawan aljamaɣat nawan meɣ alɣayal nawan əd wa igrawan aśahat nawan ye agaraw ən tanfo əd/meɣ igi ən šiška fal ataɣam ɣur karad uran wi dilkamnen ? | K95: [INSTRUCTIONS: SELECT RELEVANT SHOCKS EXPERIENCED BY THE HOUSEHOLD. MULTIPLE RESPONSES POSSIBLE. REFER TO ECONOMIC SHOCKS, CROP AND LIVESTOCK SHOCKS, INTRA-HOUSEHOLD SHOCK, NATURAL HAZARDS AND HUMAN-INDUCED HAZARDS.] | L95: [INSTRUCTIONS : SÉLECTIONNER LES CHOCS PERTINENTS SUBIS PAR LE MÉNAGE. PLUSIEURS RÉPONSES POSSIBLES. SE RÉFÉRER AUX CHOCS ÉCONOMIQUES, AUX CHOCS TOUCHANT LES RÉCOLTES ET LE BÉTAIL, AUX CHOCS INTRA-MÉNAGE, AUX RISQUES NATURELS ET AUX RISQUES D'ORIGINE HUMAINE.] | M95: [HUKUNCI: ku zabi abubuwan da mutanen gidan suka fuskanta na gilgiza. Za a iya samun amsoshi da dama. Ku fadi gilgiza da a ka samu a bangaren anfanin gona da dabobi , gilgiza ta aka samu a cikin gidan, anoba mai akuwa a haka da kuma wace mutane ke abka ta.] | N95: [HANTUM KA: Gwa subane hasrawey kan du aran almiyalo.iga hinni ga du tuyan bobo.i ma guna noru hasaraw,hassaraw kan ga lamba dumarey da almaney ga,hasarawey kan ga ka yadini kan iri tamo kande da moh weykan borey no ga te a sabili..] | O95: [INSTRUCTIONS : ƳUBEE TOORAAJE ƁURƊI TOORUDE ƁAADE NDE. JAABOOJ HEWƊI, NDARTON TOORA JAWDI, JAAGU, DAABAAJI, TOORAAJI ƁAADE, KASAARAJI MAA HIMƁE BONƁE.]. | P95: [Gargajiya: AWO SHA SAMUNGAA GONE SHIDONI FATOMAI WAKAZ3NAMA. AWO NGUU GOT3 MOWONJIN TANGNE ARZIYI SO, KULOWA DABBAASO, FATOMAISO, MAJIRAWA KAMS3K3NA WA KURU MAJIRAWAA NGAIMA WAKAANASOWA.] | Q95: [EMASESTƏN : AQIS TAKMO TITBATAT TA TIGRAWAT ALƔAYAL. AJOTNEN ƏLIƔITAN ADOBATNEN. SƏNIHIGAT TAKMO TA NAMAS ƏN ALƔAYAL, ƔUR AƔAŠAD ARTAYNEN DAƔ SIGYAK ƏD ARIZEG, AƔAŠAD NAMAS ALƔAYAL, ASUƔSID NAZAMAN ƏD ASUƔSID ADIFALAN ADINAT]. | S95: true | U95: if(selected(.,'noshock') or selected(.,'dk') or selected(.,'ref'), count-selected(.) = 1, count-selected(.) >= 1) | AE95: yes | AG95: 46.247528 | AH95: =1 -> 1 | AI95: =IF(AG95<>"",AG95*AH95,"") -> 46.247528 | AJ95: =IF(AND(AG95<>"",AE95="yes"),AG95*AH95,"") -> 46.247528
AH96: =1 -> 1 | AI96: =IF(AG96<>"",AG96*AH96,"") | AJ96: =IF(AND(AG96<>"",AE96="yes"),AG96*AH96,"")
A97: text | B97: hh_explanation | C97: If the household was affected by a major recent shock as indicated in this assessment [for example, an earthquake], what are the [expected] consequences for your household, in your own words? | D97: Si votre ménage a récemment été concerné par un choc majeur mentionné dans cette évaluation [par exemple, un tremblement de terre], quelles en sont, selon vous et dans vos propres mots, les conséquences [déjà ressenties ou attendues] pour votre ménage? | E97: Idan kwanan nan wani babban firgici da aka ambata a cikin wannan tantancewa ya shafi gidan ku (misali, girgizar ƙasa), menene kuke tunani kuma a cikin kalmominku sakamakon [an riga an ji ko ana tsammani] ga gidan ku? | F97: Guirbey kan bissa massala fo koul mane aran windo kar, da gono aran tchi irse wofo yan no? | G97: Senii hoggo mooɗon faddake saɗorma mawɗo nder wakkati ɗum mbinndee nder ngol etol [hano, diwnol leydi], ɗeye ngoni, e gi'iiɗe mooɗon nder kelme mooɗon, gacceeji [nanaaɗi naa kawraaɗi] nder hoggo mooɗon? | H97: Wonena fando daayonaro alama joro dibi fando ra batchin karrmo la na,bou wiri nayi damain za kobora nagiri la kanou daji tchijia jictoulaa kedu tidi kamdo aw nalaa wurto curo teruwa adiyi fanumiya nachaa kanumin awi jandero cinumin culiyin | I97: koudza aghiwan nawan kaladinamagraw darate labassan chilan inigunigu namadal matordam kawaney ghour wan daghawal nawan arate wadewaye Adi tifrayamass madey winistikalam dagh aghiwan nawan | K97: [INSTRUCTIONS: RECORD IN FEW WORDS THE MAIN CONSEQUENCE OF THE RECENT SHOCKS. ENTER 888 FOR DON'T KNOW AND 999 FOR REFUSED.] | L97: [INSTRUCTIONS : SAISIR EN QUELQUES MOTS LA PRINCIPALE CONSÉQUENCE DES RÉCENTS CHOCS. SAISIR 888 POUR «NE SAIT PAS» ET 999 POUR «REFUSÉ»]. | M97: [HUKUNCI: KYAUTA A KADAN KALMOMI BABBAN SAKAMAKON ARZIKI NA KWANA. Shigar da 888 DON "BAN SANI" DA 999 DON "KASHI"]. | N97: laran ma tchi irsser aran massala sintiney | O97: [TINNDINOOJE : ƊUM WINNDA KELME GOOƊOM DOW GACCEEJI ƊI KO FADDAA ƊUM WADDI . WINNDEE 888 FARO «ANNDAA» E 999 FARO «SALAKE»]. | P97: Dama Adine kuladachina, kam amsa ma koro koro. na allan kalma gana runumiya jictula asowa naaduro 888 lene,nonumi fuleyin 999 cutto wayin | Q97: tissousinte : iktibate dagharate nilkhirifan madrornene arate wadissibaban yibanarate daghadan winizraya , iktibate itamatimade ditamatimirwen ditam assina awedan wirisen id tizayate id tazatimirwin id taza assougaye sadajawab | S97: false | W97: ${shock} != 'noshock' and ${shock} != 'dk' and ${shock} != 'ref' | AE97: no | AG97: 26.118782 | AH97: =1 -> 1 | AI97: =IF(AG97<>"",AG97*AH97,"") -> 26.118782 | AJ97: =IF(AND(AG97<>"",AE97="yes"),AG97*AH97,"")
AH98: =1 -> 1 | AI98: =IF(AG98<>"",AG98*AH98,"") | AJ98: =IF(AND(AG98<>"",AE98="yes"),AG98*AH98,"")
AH99: =1 -> 1 | AI99: =IF(AG99<>"",AG99*AH99,"") | AJ99: =IF(AND(AG99<>"",AE99="yes"),AG99*AH99,"")
A100: end_group | AI100: =IF(AG100<>"",AG100*AH100,"") | AJ100: =IF(AND(AG100<>"",AE100="yes"),AG100*AH100,"")
A101: begin_group | B101: CropProduction_group | C101: CROP PRODUCTION | D101: PRODUCTION DE CULTURES | E101: Noman iri | F101: Farimi | G101: KEƁAL DOW FILLA DEMAL | H101: Kumbu Ba'ré Nagri yé | I101: tinfan agayak | S101: false | W101: ${resp_agree} = '1' and (${hh_agricactivity}='1' or ${hh_agricactivity} = '3' or ${income_main_crop_check}='1' or ${income_sec_crop_check}='1' or ${income_third_crop_check}='1') | AE101: yes | AI101: =IF(AG101<>"",AG101*AH101,"") | AJ101: =IF(AND(AG101<>"",AE101="yes"),AG101*AH101,"")
A102: note | B102: crp_intro | C102: We will now ask you some questions about crop production which apply to you and anyone in your household that is involved in crop production or sales. All questions refer to the crops grown during irrigated season. | D102: Nous allons maintenant vous poser quelques questions sur la production végétale. Ces questions vous concernent ainsi que toute personne de votre ménage impliquée dans la production ou la vente de cultures. Toutes les questions se rapportent aux cultures pratiquées pendant la saison irrigue'. | E102: Yanzu za mu yi ma ku wasu tambayoyi game da amfanin .wa ennan tamboyi sun shafe ku da ku da kukan wani mutum da yake a cikin gidan ku mai noma ko sayar da kayakin gona .duka wa ennan tambayoyi sun shafi noma da kuke yi a lokacin damana. | F102: Sohon iri yayan foyan te aran se farmo bon? Hayaney wo ga aran guna aran da borfo kulu kan go aran windora kan ga farmi goy te.hayaney wo kulu I manti kala farmey kan I ga te keydiya wate bon no. | G102: Jooni men ngaɗanay on ƴame dow barke keɓeteeɗo to bisaaji . Ƴame ɗen no ndaara on, onon e fuu ngonuɗo nder hoggo mooɗon tawaaɗo nder keɓol barke durngol e connol bisaaji . | H102: Kuwamed3 nya korolaaso ro Koren k3la bareyen shidony3 nya kuru wundudoni fannimin kara'aa k3la bare or kar3 bareyen lodoilan. Koro sammaso k3la awo baret3naye wurat3ye wokt3 ning3riyen zamanz3n. | I102: Akawan nisikin asostan iyaɗ fal sigyak wi hawan igraznen əd awadəm iyan dǎɣ amazaɣ nawan ihan dǎɣ sigyak meɣ dǎɣ ašiš ən sigyak. Asostan dak akan isigyak wi atiwagyaknen dǎɣ alwaq ən azaman wan ginawan. | AE102: yes | AG102: 7.5 | AH102: ='Additional information'!$D$18 -> 0.91 | AI102: =IF(AG102<>"",AG102*AH102,"") -> 6.825 | AJ102: =IF(AND(AG102<>"",AE102="yes"),AG102*AH102,"") -> 6.825
...

Sheet choices
A1: list_name | B1: name | C1: label::English (en) | D1: label::French (fr) | E1: label::Haoussa (ha) | F1: label::Djerma (dj) | G1: label::Peulh (pe) | H1: label::Kanuri (kr) | I1: label::Tamachek (ta) | J1: my_filter_admin
A2: enumteam | B2: 1 | C2: Enumerator team 1 | D2: Équipe d'enquêteurs 1 | E2: Équipe d'enquêteurs 1 | F2: Équipe d'enquêteurs 1 | G2: Équipe d'enquêteurs 1 | H2: Équipe d'enquêteurs 1 | I2: Équipe d'enquêteurs 1
A3: enumteam | B3: 2 | C3: Enumerator team 2 | D3: Équipe d'enquêteurs 2 | E3: Équipe d'enquêteurs 2 | F3: Équipe d'enquêteurs 2 | G3: Équipe d'enquêteurs 2 | H3: Équipe d'enquêteurs 2 | I3: Équipe d'enquêteurs 2
A4: enumteam | B4: 3 | C4: Enumerator team 3 | D4: Équipe d'enquêteurs 3 | E4: Équipe d'enquêteurs 3 | F4: Équipe d'enquêteurs 3 | G4: Équipe d'enquêteurs 3 | H4: Équipe d'enquêteurs 3 | I4: Équipe d'enquêteurs 3
A5: enumteam | B5: 4 | C5: Enumerator team 4 | D5: Équipe d'enquêteurs 4 | E5: Équipe d'enquêteurs 4 | F5: Équipe d'enquêteurs 4 | G5: Équipe d'enquêteurs 4 | H5: Équipe d'enquêteurs 4 | I5: Équipe d'enquêteurs 4
A7: enumerator | B7: NER1 | C7: ABDOULAYE WORGO Salissou | D7: ABDOULAYE WORGO Salissou | E7: ABDOULAYE WORGO Salissou | F7: ABDOULAYE WORGO Salissou | G7: ABDOULAYE WORGO Salissou | H7: ABDOULAYE WORGO Salissou | I7: ABDOULAYE WORGO Salissou
A8: enumerator | B8: NER2 | C8: AMADOU GUIMBARI Rachidou | D8: AMADOU GUIMBARI Rachidou | E8: AMADOU GUIMBARI Rachidou | F8: AMADOU GUIMBARI Rachidou | G8: AMADOU GUIMBARI Rachidou | H8: AMADOU GUIMBARI Rachidou | I8: AMADOU GUIMBARI Rachidou
A9: enumerator | B9: NER3 | C9: ADAMOU TASSAOU Djamilatou | D9: ADAMOU TASSAOU Djamilatou | E9: ADAMOU TASSAOU Djamilatou | F9: ADAMOU TASSAOU Djamilatou | G9: ADAMOU TASSAOU Djamilatou | H9: ADAMOU TASSAOU Djamilatou | I9: ADAMOU TASSAOU Djamilatou
A10: enumerator | B10: NER4 | C10: DJIBO HAMIDOU Nafissatou | D10: DJIBO HAMIDOU Nafissatou | E10: DJIBO HAMIDOU Nafissatou | F10: DJIBO HAMIDOU Nafissatou | G10: DJIBO HAMIDOU Nafissatou | H10: DJIBO HAMIDOU Nafissatou | I10: DJIBO HAMIDOU Nafissatou
A11: enumerator | B11: NER5 | C11: HAMED MOUSSA MANTALA Ahmoudou | D11: HAMED MOUSSA MANTALA Ahmoudou | E11: HAMED MOUSSA MANTALA Ahmoudou | F11: HAMED MOUSSA MANTALA Ahmoudou | G11: HAMED MOUSSA MANTALA Ahmoudou | H11: HAMED MOUSSA MANTALA Ahmoudou | I11: HAMED MOUSSA MANTALA Ahmoudou
A12: enumerator | B12: NER6 | C12: IBRAHIM MALAM HAROUNA Mabrouka | D12: IBRAHIM MALAM HAROUNA Mabrouka | E12: IBRAHIM MALAM HAROUNA Mabrouka | F12: IBRAHIM MALAM HAROUNA Mabrouka | G12: IBRAHIM MALAM HAROUNA Mabrouka | H12: IBRAHIM MALAM HAROUNA Mabrouka | I12: IBRAHIM MALAM HAROUNA Mabrouka
A13: enumerator | B13: NER7 | C13: INOUSSA GALADIMA Lawaye | D13: INOUSSA GALADIMA Lawaye | E13: INOUSSA GALADIMA Lawaye | F13: INOUSSA GALADIMA Lawaye | G13: INOUSSA GALADIMA Lawaye | H13: INOUSSA GALADIMA Lawaye | I13: INOUSSA GALADIMA Lawaye
A14: enumerator | B14: NER8 | C14: KIARI Attouman | D14: KIARI Attouman | E14: KIARI Attouman | F14: KIARI Attouman | G14: KIARI Attouman | H14: KIARI Attouman | I14: KIARI Attouman
A15: enumerator | B15: NER9 | C15: MAIMOUNA MAIFADA | D15: MAIMOUNA MAIFADA | E15: MAIMOUNA MAIFADA | F15: MAIMOUNA MAIFADA | G15: MAIMOUNA MAIFADA | H15: MAIMOUNA MAIFADA | I15: MAIMOUNA MAIFADA
A16: enumerator | B16: NER10 | C16: MOHAMAR YOUSSOUFOU MAIGA Bintou | D16: MOHAMAR YOUSSOUFOU MAIGA Bintou | E16: MOHAMAR YOUSSOUFOU MAIGA Bintou | F16: MOHAMAR YOUSSOUFOU MAIGA Bintou | G16: MOHAMAR YOUSSOUFOU MAIGA Bintou | H16: MOHAMAR YOUSSOUFOU MAIGA Bintou | I16: MOHAMAR YOUSSOUFOU MAIGA Bintou
A17: enumerator | B17: NER11 | C17: NOUHOU Hassane | D17: NOUHOU Hassane | E17: NOUHOU Hassane | F17: NOUHOU Hassane | G17: NOUHOU Hassane | H17: NOUHOU Hassane | I17: NOUHOU Hassane
A18: enumerator | B18: NER12 | C18: SALHA MAHAMADOU Djamila | D18: SALHA MAHAMADOU Djamila | E18: SALHA MAHAMADOU Djamila | F18: SALHA MAHAMADOU Djamila | G18: SALHA MAHAMADOU Djamila | H18: SALHA MAHAMADOU Djamila | I18: SALHA MAHAMADOU Djamila
... A22: enumerator | B22: NER16 | C22: SOUMANA SALEY Moussa | D22: SOUMANA SALEY Moussa | E22: SOUMANA SALEY Moussa | F22: SOUMANA SALEY Moussa | G22: SOUMANA SALEY Moussa | H22: SOUMANA SALEY Moussa | I22: SOUMANA SALEY Moussa
A24: yes_no | B24: 1 | C24: Yes | D24: Oui | E24: EH | F24: AHO | G24: Ayyo | H24: Aa | I24: Iyo
A25: yes_no | B25: 2 | C25: No | D25: Non | E25: Ah'Ah | F25: Ah ah | G25: AA’A | H25: A'ah | I25: Baybo
A26: yes_no | B26: 3 | C26: DON'T KNOW | D26: NE SAIT PAS | E26: BAN SANI BA | F26: djan ga beyyan | G26: ANNDA | H26: NOZA NYI | I26: WARISENAƔ
A27: yes_no | B27: 4 | C27: REFUSED | D27: REFUSÉ | E27: ƘIN amsawa | F27: Wanjii ga tuyyan | G27: SALAADE | H27: WAANO | I27: UGAY
A29: continue | B29: continue | C29: continue | D29: continuez
A31: yesno | B31: 1 | C31: Yes | D31: Oui | E31: EH | F31: AHO | G31: Ayyo | H31: Aa | I31: Iyo
A32: yesno | B32: 2 | C32: No | D32: Non | E32: Ah'Ah | F32: Ah ah | G32: AA’A | H32: A'ah | I32: Baybo
A34: language | B34: en | C34: English | D34: English | E34: English | F34: English | G34: English | H34: English | I34: English
A35: language | B35: fr | C35: French | D35: Français | E35: Français | F35: Français | G35: Français | H35: Français | I35: Français
A36: language | B36: haoussa | C36: Haoussa | D36: Haoussa | E36: Haoussa | F36: Haoussa | G36: Haoussa | H36: Haoussa | I36: Haoussa
A37: language | B37: zerma | C37: Zerma | D37: Zerma | E37: Zerma | F37: Zerma | G37: Zerma | H37: Zerma | I37: Zerma
A38: language | B38: kanuri | C38: Kanuri | D38: Kanuri | E38: Kanuri | F38: Kanuri | G38: Kanuri | H38: Kanuri | I38: Kanuri
A39: language | B39: tamachek | C39: Tamachek | D39: Tamachek | E39: Tamachek | F39: Tamachek | G39: Tamachek | H39: Tamachek | I39: Tamachek
A40: language | B40: peulh | C40: Peulh | D40: Peulh | E40: Peulh | F40: Peulh | G40: Peulh | H40: Peulh | I40: Peulh
A41: language | B41: autre | C41: Autre | D41: Autre | E41: Autre | F41: Autre | G41: Autre | H41: Autre | I41: Autre
A43: gender | B43: 1 | C43: Male | D43: Homme | E43: Namiji | F43: Alboro | G43: Gorko | H43: Kongaa | I43: Ahalis
A44: gender | B44: 2 | C44: Female | D44: Femme | E44: Mace | F44: Wayboro | G44: Debbo | H44: Kamu | I44: Tamaƭ
A45: gender | B45: 3 | C45: DON'T KNOW | D45: NE SAIT PAS | E45: BAN SANI BA | F45: djan ga beyyan | G45: ANNDA | H45: NOZA NYI | I45: WARISENAƔ
A46: gender | B46: 4 | C46: REFUSED | D46: REFUSÉ | E46: ƘIN amsawa | F46: Wanjii ga tuyyan | G46: SALAADE | H46: WAANO | I46: UGAY
A48: contact_info | B48: 1 | C48: YES - mine | D48: Oui - le mien | E48: EH - tawa | F48: AHO - Ay wane no | G48: Ayyo- guel’am | H48: ADAI-kakke | I48: YO -inaw.
A49: contact_info | B49: 2 | C49: YES - other household member | D49: Oui - un autre membre du ménage | E49: EH - wani mutum a iyale | F49: Aho-iri kwara borfo | G49: Ayyo-guel’korédji am | H49: ADAI- Am fannimiye gadeso | I49: IYO – Adinat iyad ən amazaɣ
A50: contact_info | B50: 3 | C50: YES - friend or relative [non household member] | D50: Oui - celui d'un ami ou d'un parent [non membre du ménage] | E50: EH-Wani aboki ko dan uwa [da bai cikin iyalin ku] | F50: aho -ay tshoro fo wala gneyze [kan manti iri koireyze] | G50: Ayyo-guel’hii’go am | H50: ADAI- bawo-yalla fatoye | I50: IYO – alɣayalan wi winan adoban
A51: contact_info | B51: 4 | C51: NO | D51: Non | E51: Ah'Ah | F51: Ah ah | G51: AA’A | H51: A'ah | I51: Baybo
A53: agricactivity | B53: 1 | C53: Yes - crop production | D53: Oui - production végétale | E53: eh – samar da kayan itace | F53: Aho- Farmi | G53: AYYO- gollal kulle cecce. | H53: Adai - kulo baret3 | I53: IYO – asisiriw ən hiškan.
A54: agricactivity | B54: 2 | C54: Yes - livestock production | D54: Oui - production animale | E54: eh – samar da dabobi | F54: aho -almane kourou yan | G54: AYYO- margal. | H54: Adai- dabba roota | I54: IYO – asisiriw ən narizej.
A55: agricactivity | B55: 3 | C55: Yes - both crop and livestock production | D55: Oui - production végétale et animale | E55: eh – samar da kayan itace da dabobi | F55: aho-farmin da almane kouruu yan | G55: AYYO- golle ko hecciɗi e margal. | H55: Adai- kulo wa dabba roota | I55: IYO- asisiriw ən hiškan əd narizej
A56: agricactivity | B56: 4 | C56: No | D56: Non | E56: Ah'Ah | F56: ah ah | G56: AA’A | H56: A'ah | I56: BAYBO
... A104: residence | B104: 7 | C104: REFUSED | D104: REFUSÉ | E104: ƘIN amsawa | F104: wandji ga tu yan | G104: SALAADE | H104: WAANO | I104: UGAY
A106: asset_prod | B106: process | C106: Processing assets (e.g. grinding/crushing machine, mill, oil press, fish tanks) | D106: Actifs de transformation [par ex. broyeur, moulin, presse à huile, aquarium] | E106: Gudanar da kadarorin [misali. crusher, niƙa, latsa mai, akwatin kifaye] | F106: barayan goy guiney {foufouyan, gui téyan wal darbayan} | G106: Naftorteeɗum faro waylugo [hano. Unirɗum , masin niisaago, masin gaɗoowo nebbam, ndiyam ngattanaaɗam liƴƴi desoteeɗam nder suudu] | H106: Machin tutu, yeh kau tutut, karwa tchiida tutu | I106: aratan win nibiriki ( michine tanchidite ,tendey)
A107: asset_prod | B107: farmmach | C107: Farm or fishing machinery (e.g. tractor, plough, sickle, boats, engines) | D107: Machine agricole ou de pêche [par ex. tracteur, charrue, faucille, bateaux, moteurs] | E107: Injin noma ko kamun kifi [misali. tarakta, garma, sickle, jirgin ruwa, injuna] | F107: farmi goy guiney wal darbayan | G107: Masin demal naa liƴƴotooɗo [hano. ndemirga, Saaret mo jale, taƴirɗum huɗo, akale ndiyam, mooter | H107: injinin kolo kolo ye ,Tarko luname, injinin baré ye , kolo kolo galgajia hé | I107: aratan win isstigayakam madey titabazam sirssan kifitan kalmitan ,malankaye wan zigran
A108: asset_prod | B108: sewing | C108: Sewing machine or weaving tool | D108: Machine à coudre ou métier à tisser | E108: Injin dinki ko sabulu | F108: tella wal tchakay | G108: Masin nyootoowo naa canyoowo | H108: Tchida tela , keke | I108: tela tanizamaye
A109: asset_prod | B109: taxi | C109: Taxi | D109: Taxi | E109: Taxi | F109: faba | G109: Taasi | H109: Mota aariyé aw machine | I109: tourifte tan arouzmatan
A110: asset_prod | B110: truck | C110: Truck | D110: Camion | E110: Motoci | F110: moto | G110: Loore mawnga | H110: Mota kura | I110: elam
A111: asset_prod | B111: other | C111: Other productive machines or assets | D111: Autres machines ou actifs productifs | E111: Sauran injuna ko kadarori masu albarka | F111: goy guineyfo yan ki ga nafan da | G111: Masiniiji gom naa fuu ko wallata faro keptol | H111: Mota ko ijinine awo wiri maraye | I111: daratan wintilam wirtanimel
A112: asset_prod | B112: none | C112: No productive machines or assets | D112: Aucune machine ou actif productif | E112: Babu inji ko kadarori masu amfani | F112: goy guiney ki ga nafan da | G112: Masin naa fuu ko wallata faro keptol walaa | H112: ko fal bawo bawo churo injine ri | I112: wælɑ́ ìy-æn Machine tan
A113: asset_prod | B113: dk | C113: DON'T KNOW | D113: NE SAIT PAS | E113: rishin sanni | F113: djan ga beyrey | G113: ANNDA | H113: NOZA NYI | I113: WARISENAƔ
A114: asset_prod | B114: ref | C114: REFUSED | D114: REFUSÉ | E114: kin amsawa | F114: wandji ga tu yan | G114: ANNDA | H114: WAANO | I114: UGAY
A116: asset_transp | B116: bici | C116: Bicycle | D116: Bicyclette | E116: Keke | F116: guru bari | G116: Beelo | H116: Kéké | I116: kekaye
A117: asset_transp | B117: cart | C117: Cart (animal drawn) | D117: Chariot [tiré par un animal] | E117: Cart [da dabba ya ja] | F117: farkay torko | G117: Saaret tuufeteeɗum [pootirteeɗum bisa] | H117: Torko Lunam | I117: malankaye tan izodan
A118: asset_transp | B118: boatmotor | C118: Boat with an engine [inboard or outboard] | D118: Bateau avec moteur [in-bord ou hors-bord] | E118: Jirgin ruwa mai injin [ciki ko waje] | F118: annasara hi | G118: Akala ndiyam mo mooter [tawaaɗum nder naa yasi] | H118: Kololo injinin | I118: aghlal naman waylan moteur,
... A126: asset_transp | B126: ref | C126: REFUSED | D126: REFUSÉ | E126: kin amsawa | F126: wandji ga tu yan | G126: ANNDA | H126: WAANO | I126: UGAY
A128: maritalstat | B128: 1 | C128: Single / never married | D128: Célibataire / jamais marié | E128: ba shida aure / bai taba aure ba | F128: a mane bey ga hidji | G128: O gortaalo/ ndewlay ginan. | H128: Fal Ngulong/ ngaltima nyiyaa s3dinyi | I128: Amasro/kala wad izizlay.
A129: maritalstat | B129: 2 | C129: Married | D129: Marié(e) | E129: da auren shi | F129: a gonad hidjey | G129: O ndewlii. | H129: Nyiyaaa | I129: Azizlay
A130: maritalstat | B130: 3 | C130: Separated | D130: Séparé(e) | E130: ya rabu | F130: i si tchar bon | G130: O seedi. | H130: Yektanaa | I130: Abdan
A131: maritalstat | B131: 4 | C131: Divorced | D131: Divorcé(e) | E131: Bazauri/ bazaura | F131: a fey | G131: O seerii. | H131: Dubkata | I131: Amizay
A132: maritalstat | B132: 5 | C132: Widowed | D132: Veuf ou veuve | E132: miji ko mata ya rassu | F132: korkasina tekasi | G132: O mayraaɗo. | H132: kwanz3 baz3na | I132: Aziwar meɣ tasiwar
A133: maritalstat | B133: 6 | C133: DON’T KNOW | D133: NE SAIT PAS | E133: rishin sanni | F133: djan ga beyrey | G133: ANNDA | H133: NOZA NYI | I133: WARISENAƔ
A134: maritalstat | B134: 7 | C134: REFUSED | D134: REFUSÉ | E134: kin amsawa | F134: wandji ga tu yan | G134: SALAADE | H134: WAANO | I134: UGAY
A136: agegroup | B136: 1 | C136: Under 18 | D136: Moins de 18 ans
A137: agegroup | B137: 2 | C137: 18 to 40 | D137: 18 à 40 ans
A138: agegroup | B138: 3 | C138: 41 to 65 | D138: 41 à 65 ans
A139: agegroup | B139: 4 | C139: Over 65 | D139: Plus de 65 ans
A140: agegroup | B140: 5 | C140: DON'T KNOW | D140: NE SAIT PAS
A141: agegroup | B141: 6 | C141: REFUSED | D141: REFUSÉ
D142: REFUSÉ
A143: incomesource1 | B143: 1 | C143: Production and sale of staple crops | D143: Production et vente de cultures vivrières | E143: shuka da kuma sayar da amfanin gona | F143: farmi da gnawrey ki fari fawciyan | G143: Keɓal e cogguuji keɓe hooreeje. | H143: Natoso kuru ladaso kare kuloi | I143: Adamu əd ašinš ən sigyak wi atiwasanen.
A144: incomesource1 | B144: 2 | C144: Production and sale of vegetables or fruit | D144: Production et vente de légumes ou de fruits | E144: shuka da kuma sayar da kayan marmari ko ya en itatuwa | F144: farmi da farmiize wala turizey fatawciyan | G144: Cogguuji keɓe leydi e ɓiɓɓe leɗɗe. | H144: Natoso kuru ladaso karek3riye au k3skai | I144: Adamu əd ašinš ən legumetan meɣ aratan ən hiškan
A145: incomesource1 | B145: 3 | C145: Production and sale of cashcrops | D145: Production et vente de cultures de rente | E145: shuka da kuma sayar da amfanin gona na sayarwa | F145: farmin da farmi guiney ki ga ka tarey neran yan | G145: Keɓal leydi maa daabaaji e coggu ko ngaɗantee jaagu. | H145: Natoso au ladaso kare kuloi zamanne | I145: Adamu əd ašinš ən sigyak wi agaraw.
A146: incomesource1 | B146: 4 | C146: Production and sale of livestock or livestock products | D146: Production et vente de bétail ou de produits animaux | E146: Haɓaka da sayar da dabbobi ko dabbobi | F146: almane kurun da nera yan hada guiney kan ga funu almane ga. | G146: Keɓal leydi maa jaagu daabaaji beydi coggu ɲaamee dammucce. | H146: Natuso au ladoso kumbu dabbaye | I146: Adamu əd ašinš ən arizeg əd lalan wi arizeg
A147: incomesource1 | B147: 5 | C147: Production and sale of honey and bee products | D147: Production et vente de miel ou de produits apicoles | E147: yi da kuma sayar da zuma ko kayan zuma | F147: yuu kayan da neran yan | G147: Sottude liƴƴi. | H147: B3nyi rot3 ladowa | I147: Adamau əd ašinš ən manan.
A148: incomesource1 | B148: 6 | C148: Production and sale of fish or aquatic products | D148: Production et vente de poisson ou de produits aquatiques | E148: Kerawa da sayar da kifi ko kayayyakin ruwa | F148: hamissa biri yan da nerando | G148: Ittude ɓiɓɓe leɗɗe ladde Sotta. | H148: Samarin da kuma samar da ɗanɗano ko kayan ruwa. | I148: Asiduw əd ašinš ən lalan ən hiškan meɣ ən finta
A149: incomesource1 | B149: 7 | C149: Collection and sale of natural resources (including forestry or bush products) | D149: Collecte et vente de produits forestiers ou de brousse | E149: tari da sayar da gandun daji | F149: sadji ra guiney keki yan di nera yan | G149: Jaagu awtirdi ndi saria hokkay laawol/so remooɓe wattay baka. | H149: Yadum kude kare aarigaljaye tandoma BARO | I149: Inazan ən asigyik ən salan daɣ ukis ən magyakan.
A150: incomesource1 | B150: 8 | C150: Agricultural trade EXCLUDING producers (formal or informal) | D150: Commerce agricole EXCLUANT les producteurs [formel ou informel] | E150: Kasuwancin kayan noma na zamani AMMA BANDA masu samarwa | F150: Zaamani faarmize jinay neeran yan kan raa cinda alfaray | G150: Jaagu ngu sariya jaɓi/ fay so remooɓe wattay baka. | H150: Yadum kude fatoi kare aarigaljaye tandoma BARO | I150: Inazan ən asigyik ən salan daɣ ukis ən magyakan.
A151: incomesource1 | B151: 9 | C151: Daily wage on farms and other casual employment in agricultural sector | D151: Salaire journalier dans une exploitation et autres emplois occasionnels dans le secteur agricole | E151: Albashin rana a kan gonaki da wasu ƙananan ayyukan a sashin noma | F151: Zaari Farfara wala goy-goyaa ga duu nooruu faarmi fondaraa | G151: Njomri ɲannden wootere e gollal margal / e golle goɗɗe ley ndemri. | H151: Kullumro kare kuloiya ngaltaso kuru chidau kela aarigaljaye | I151: Alhak daɣ ašal daɣ qalan əd iyad ašiɣilan nalwaq daɣ tabarat tan asi.
A152: incomesource1 | B152: 10 | C152: Stable employment in agricultural sector | D152: Emploi stable dans le secteur agricole | E152: Tabbataccen aiki a sahin noma | F152: goy tabatante farmi goyo ra | G152: Gollal gootal ley golle ndemri. | H152: Chidau kundot3ye k3la aarigaljaye | I152: Ašiɣil adiken daɣ tabarat tan asigyik.
A153: incomesource1 | B153: 11 | C153: Non-agricultural self-employed or liberal profession, doctor, architect, lawyer, including restaurant | D153: Indépendant non-agricole ou profession libérale / médecin / architecte / avocat / y compris restaurant | E153: Aiki na ƙashi-kai da ba na sahin noma ba ko kuma aiki ƙwarewa na taimako / likita /mai zane-zane / lauya / har ma da aikin gidan saida abinci | F153: Hari kan manti faarmi goy sanga day lokkotoro taray/ciinaari beeri goy/aboca Hada hawru nerandi | G153: Gollal keƴu ngal hoore mum ngal haɓɓodaaki e ndemri maa gollal gongal. | H153: Chidama doni aarigaljayi nguyi k3lanz3ye au k3ra tomoz3nama/liita/fato | I153: Ašiɣil ən idmanes winan eqel agayak meɣ Ašiɣil ən erhet [ laətor/ amuɣan/ amilal/ daɣ ahan kal məsiwan].
A154: incomesource1 | B154: 12 | C154: Off-farm daily wages and other non-agricultural casual employment | D154: Salaire journalier hors exploitation et autres emplois occasionnels non agricoles | E154: Albashin rana-rana da ba na ɓangaren noma ba ko wasu ƙananan ayyukan | F154: Hekan mate farmi goi banadi nda goi kan mate farmi goi | G154: Njomri ɲannden wootere e ɗo Aa’a gollal nawtorangal e golle goɗɗe ɗe haɓɓo daaki e demal. | H154: Chida kullume kuru chida doni aarigaljaye guiyi | I154: Alhak daɣ ašal winan iha ašišiɣil əd iyad ašiɣilan nagudiyan winan eqel ən agayak
... A226: incomesource3 | B226: 21 | C226: REFUSED | D226: REFUSÉ | E226: kin amsawa | F226: wandji ga tuyan | G226: SALAADE | H226: WAANO | I226: UGAY
A228: shock | B228: noshock | C228: No shock | D228: Aucun choc | E228: babu wata gilgiza | F228: hasaraw ba afo | G228: Warhoore fuh ngaɗay | H228: Karuukam baro | I228: Wala iyan aɣašad
A229: shock | B229: sicknessordeathofhh | C229: Sickness or accident or death of household member[s] [sickness of breadwinner / unusually high medical expenditure / funeral expenses / death of breadwinner] | D229: Maladie, accident ou décès d'un ou plusieurs membres du ménage [maladie du soutien de famille / dépenses médicales anormalement élevées / frais funéraires / décès du soutien de famille] | E229: Rashin lafiya ko hatsari ko mtuwa na wani daga cikin mutanen gidan rashin lafiyar wanda gidan suka dogara da shi/ita/ biyan kuɗaɗen magani da ba saba fuskanta ba/ kashe kuɗaɗe a yayin al'adun mutuwa/ mutuwar wanda gida ya dogara da shi/ita.] | F229: djonte/fonda bon hasaraw wala almiyalo ra borfo wala boroyan buyan [windo gandjo djonta / safarey nonu bobo wii yon / bu yan ga noru wii yan /windo gandjo buyan] | G229: Ɲawu/masiiba maa mayde neɗɗo gooto maa himɓe ɓaade. | H229: Numdondi au majarawa au kurmu am fatomaye[so] [numdondi kurafatoi/ kunguna nguu numdondilan yezoso/ kurmoye kunguna yezoso/ kurmu kura fatoiye] | I229: Turhina/ anməɣgar meɣ iba ən adinat ajotnen ən alɣayal [turhina tan tadhil ən amazan/azruf ajen winan anihaga ye laətor/ azruf ye duawu/ ibz namadhal ən alɣayal].
A230: shock | B230: lostemplorwork | C230: Lost employment or working opportunities [not due to illness/accident] | D230: Perte d'emploi ou d'opportunités de travail [non due à la maladie ou à un accident] | E230: Rasa aiki ko damar aikin [wanda ba shi da alaka da rishin lafia ko hatshari] | F230: goy djanney kan manti djonte wala fondo hasaraw se] | G230: Muursude gollal maa sabaabu golle lobbo. | H230: Chida doni fandoro teyerina au chida fandoyi [chida kau falle] | I230: Agamad ən ašiɣil meɣ ən morda nəšiɣil [astawaga atamosan əšiɣil wa hinan].
A231: shock | B231: otherintrahhshock | C231: Other intra-household shock | D231: Autre choc interne au ménage | E231: Wani gilgiza can daban na cikin gida | F231: hasaraw fo kan te windo rahasaraw fo kan te windo ra | G231: Naawalla goɗɗo ley wuro. | H231: Awogade faton g3natuso | I231: Iyad ənmigaran non gar alɣayal.
A232: shock | B232: higherfoodprices | C232: Unusually high food prices | D232: Prix des denrées alimentaires anormalement élevés | E232: hawan farashin kudin abinci hiye da yada a ke zato | F232: nwaro noro tchada gumo | G232: Tiiɗorma ko ɲaametee faa ɓuri no woorunoo. | H232: Kung3na kumbuye doni t3rana nangam buron not3na dilan | I232: Alhak wan šiška awid hulen ye awa ən hadani.
A233: shock | B233: higherfuelprices | C233: Unusually high fuel prices or transport prices | D233: Prix des carburants ou des transports anormalement élevés | E233: hawan farashin kuɗin mai ko kuma sufuri. Hiye da yanda a ke zato | F233: essensso da moto sabu yan noro tchada gumo | G233: Tiiɗugol coggu sensi e njahol faa ɓettii no tawraa no. | H233: Kung3na feturre au lenumk3nshee doni t3rana nangam buron not3na dilan | I233: Alhak ən əarburantan meɣ ən transɗortan awid ye awa ən hadani
A234: shock | B234: mvtrestrict | C234: Population movement restrictions [e.g. due to epidemic or infrastructure damage] | D234: Restrictions de mouvements de population [par exemple, en raison d'une épidémie ou de dommages causés aux infrastructures] | E234: rage kai da kawon al uma [kamar misali saboda anoba ko lalacewar ababen more rayuwa] | F234: goyey zabu [dori fo kan goga borey kar wala goy nangey sara yan] | G234: Ngollal boowaangal ngal wawtataa golleede ngasin saabe tooraaji yaasin ɗi | H234: Kasuu da goz3 kojin bau sau awolaa gade kateduro gaana duro [suronzan kwasa covid doi s3ka fomno baro s3dinadaa/lamar namt3 ng3lefai/ gar zamanne wurturo gade soo.] | I234: Imbas nadobat anəlkim ye ašiɣil wan hadani fal salan nəsibaban izganen [atamosan ifanazan nataɣam/ ən tamograrzt ən təmuqunen/ darat awen]
A235: shock | B235: othereconomicshock | C235: Other economic shock | D235: Autre choc économique | E235: wata gilgiza ta daban na bangaren tattalin arziki | F235: noru hasaraw fo | G235: Toora/tampiri faggudu. | H235: Awaa gad3 s3kk3 razuu bannat3na | I235: Iyan animgar ən azruf.
A236: shock | B236: pestoutbreak | C236: Pest outbreak | D236: Invasion d'organismes nuisibles | E236: Annobar ƙwari | F236: gangamizey | G236: Ɲaw tuundiiji. | H236: Kwasa kuriyaye | I236: Turhina tan tiwikawen.
A237: shock | B237: plantdisease | C237: Plant disease | D237: Maladie des plantes | E237: Cutar shuka | F237: Dumizey doro | G237: Ɲaw fuɗngooji. | H237: K3ska sowa namt3 | I237: urhina ən hiškan.
A238: shock | B238: animaldisease | C238: Animal disease [affecting many animals] or death | D238: Maladie animale [touchant de nombreux animaux] ou mort d'animaux | E238: Rashin lafiyar dabbobi da suke shafar dabbobi da dama ko mutuwar dabbobi | F238: Almeney dori.kan na almane bobo di wala almane bobo buyan | G238: Ɲaw daabaaji raaɓoowu kulle kewɗe maa waatugol majji. | H238: Kwasa doni dabbaa zamz3na har s3kk3 kurmu dabbaa yeh so waano | I238: Turhina tan arizeg garawat arizeg ajen meɣ naqu arizeg
A239: shock | B239: napasture | C239: Lack of physical access to pasture | D239: Accès difficile aux pâturages | E239: tshananin samun wurin kiwo | F239: almane kuru yan nangu gabi | G239: Rafi kewtugol nokkuje duriirde | H239: Samuwar hanaɗa ga hanaɗa. | I239: Iba nagaraw nugiš itawanhayan ən asamodone
... A254: shock | B254: ref | C254: REFUSED | D254: REFUSÉ | E254: kin amsawa | F254: wandji ga tuyan | G254: SALAADE | H254: WAANO | I254: UGAY
A256: covidmeasures | B256: goodstransp | C256: Movement restrictions [sometimes producing product scarcity or price hikes] | D256: Restrictions de mouvement [entraînant parfois une raréfaction des produits ou une forte hausse des prix]
...

Sheet Feuil1
A1: list_name | B1: name | C1: label:: | D1: my_filter_admin
A2: admin2 | B2: NE001001 | C2: Aderbissinat | D2: NE001
A3: admin2 | B3: NE001002 | C3: Arlit | D3: NE001
A4: admin2 | B4: NE001003 | C4: Bilma | D4: NE001
A5: admin2 | B5: NE001004 | C5: Iferouane | D5: NE001
A6: admin2 | B6: NE001005 | C6: In-Gall | D6: NE001
A7: admin2 | B7: NE001006 | C7: Tchirozérine | D7: NE001
A8: admin2 | B8: NE002001 | C8: Bosso | D8: NE002
A9: admin2 | B9: NE002002 | C9: Diffa | D9: NE002
A10: admin2 | B10: NE002003 | C10: Goudoumaria | D10: NE002
A11: admin2 | B11: NE002004 | C11: Maïné Soroa | D11: NE002
A12: admin2 | B12: NE002005 | C12: Ngourti | D12: NE002
... A64: admin2 | B64: NE007010 | C64: Tasker | D64: NE007

Sheet settings
A1: version | B1: default_language | C1: allow_choice_duplicates | D1: style
A2: vM6cWXyHNhR3djPbARkHWi | B2: French (fr) | C2: yes | D2: theme-grid no-text-transform

Sheet Crop list
C3: Select top 10 crops | D3: Dataset code | E3: Label (EN) | F3: Label (FR)
C4: x | D4: 1.1 | E4: Rice | F4: Riz
D5: 1.2 | E5: Wheat | F5: Blé
D6: 1.3 | E6: Millet | F6: Mil
D7: 1.4 | E7: Sorghum | F7: Sorgho
C8: x | D8: 1.5 | E8: Maize | F8: Maïs
D9: 1.6 | E9: Barley | F9: Orge
D10: 1.99 | E10: Other Cereal | F10: Autres céréales
C11: x | D11: 2.1 | E11: Cassava | F11: Manioc
C12: x | D12: 2.2 | E12: Potatoe | F12: Pommes de terre
D13: 2.3 | E13: Sweet Potatoes | F13: Patates douces
D14: 2.4 | E14: Yams | F14: Ignames
C15: x | D15: 2.5 | E15: Carrots | F15: Carottes
D16: 2.6 | E16: Cocoyam | F16: Chou caraïbe
D17: 2.99 | E17: Other tubers | F17: Autres tubercules
D18: 3.1 | E18: Beans | F18: Haricots
D19: 3.2 | E19: Lentils | F19: Lentilles
D20: 3.3 | E20: Peas | F20: Pois
D21: 3.4 | E21: Soybeans | F21: Soja
D22: 3.5 | E22: Chickpeas | F22: Pois chiches
D23: 3.6 | E23: Fava beans | F23: Fève
D24: 3.7 | E24: Broad beans | F24: Fève large
D25: 3.99 | E25: Other pulses | F25: Autres légumineuses
C26: x | D26: 4.1 | E26: Cabbage | F26: Choux
C27: x | D27: 4.2 | E27: Lettuce | F27: Laitue
D28: 4.3 | E28: Spinach-Amaranth | F28: Epinards-Amaranthe
D29: 4.4 | E29: Cassava leaves | F29: Feuilles de manioc
D30: 4.5 | E30: Potatoe leaves | F30: Feuilles de pomme de terre
C31: x | D31: 4.6 | E31: Moringa | F31: Moringa
D32: 4.7 | E32: Sorrel Hibiscus / Rosselle | F32: Oseille Hibiscus / Rosselle
D33: 4.9 | E33: Green salad herbs (thyme, parsley, mint, rocca, other) | F33: Herbes aromatiques (thym, persil, menthe, rocca, autres)
D34: 4.101 | E34: Cauliflower | F34: Choux-fleur
D35: 4.99 | E35: Other leafy vegetables | F35: Autres légumes à feuilles
C36: x | D36: 5.1 | E36: Tomatoes | F36: Tomates
D37: 5.2 | E37: Cucumber | F37: Concombre
D38: 5.3 | E38: Pumpkin | F38: Citrouille
D39: 5.4 | E39: Eggplant/aubergine | F39: Aubergines/aubergines
D40: 5.5 | E40: Zucchini | F40: Courgettes
D41: 5.6 | E41: Okra | F41: Okra
D42: 5.7 | E42: Bell pepper | F42: Poivron
D43: 5.8 | E43: Onions | F43: Oignons
C44: x | D44: 5.9 | E44: Haricot | F44: Haricot
D45: 5.101 | E45: Green peas | F45: Petit pois
D46: 5.11 | E46: Fava beans green | F46: Pois fève
D47: 5.99 | E47: Other non leafy vegs | F47: Autres légumes non feuillus
D48: 6.1 | E48: Orange | F48: Orange
D49: 6.2 | E49: Lemon | F49: Citron
D50: 6.3 | E50: Grapefruit | F50: Pamplemousse
D51: 6.4 | E51: Mandarins/clementines | F51: Tangerine/clémentine
D52: 6.99 | E52: Other citrus fruit | F52: Autres agrumes
D53: 7.1 | E53: Sweet Banana | F53: Banane douce
D54: 7.2 | E54: Plantains | F54: Banane plantain
D55: 7.3 | E55: Papaya | F55: Papaye
D56: 7.4 | E56: Mango | F56: Mangue
... D93: 10.99 | E93: Other non-food cash crop | F93: Autre culture de rente non alimentaire

Sheet Additional information
C2: Original | D2: Replacement (FR) | E2: Replacement (EN) | F2: Comment (FR) | G2: Comment (EN) | H2: Exemple (FR) | I2: Example(EN)
B3: FOR CORE QUESTIONS . (Mandatory to fill out) . | C3: phone number | F3: Tapez un numéro de téléphone dans le format typique du pays, par exemple 77******* [veuillez écrire le nombre exact de chiffres qu'il y a dans un numéro de téléphone]. | G3: Type a phone number from your country in typical format, e.g. 77******* [please use exactly the number of characters that are found in a phone number]. | H3: 070****** | I3: 070******
C4: age | D4: 18 | E4: 18 | F4: Âge minimum du répondant (nous recommandons 18 ans) | G4: Minimum age of respondent (recommend 18 years old) | H4: 18 | I4: 18
C5: ADMIN1 | D5: Region | E5: Region | F5: La première subdivision du pays, après le niveau national ; par exemple, région ; province ; gouvernorat ; etc. Un seul mot doit être saisi - Ne pas inclure d'espaces. | G5: The first subdivision of the country, after national level; region; province; governorate; etc. Only one word should be inputted - Do not include spaces. | H5: region | I5: region
C6: ADMIN2 | D6: Department | E6: Department | F6: La deuxième subdivision du pays ; par exemple, district, municipalité, LGA, etc. Un seul mot doit être saisi - Ne pas inclure d'espaces. | G6: The second subdivision of the country; district; municipality; LGA; etc. Only one word should be inputted - Do not include spaces. | H6: district | I6: district
C7: reference year | D7: une année normale | E7: a normal year | F7: Les questions de comparaison auront besoin d'une année de référence. Choisissez si vous voulez utiliser "l'année dernière" ou "une année normale" comme année de référence. Une "année normale" doit correspondre à une année moyenne des 5 dernières années - veillez à former les recenseurs en conséquence. | G7: Comparison questions will need need a reference year. Select whether you want to use "last year" or "a normal year" as a baseline. A "normal year" should refers to an average year from the past 5 years - make sure to train the enumerators accordingly. | H7: une année normale | I7: a normal year
C8: season | D8: saison irrigue' | E8: irrigated season | F8: Nommez la ou les saisons culturales concernée(s) en ANGLAIS s'il y en a plusieurs dans le pays (par exemple, Meher et Belg en Ethiopie, saison des pluies / cultures de décrue / saison sèche irriguée au Sahel). Vous pouvez vous référer à la "dernière saison" ou "saison actuelle". | G8: Name the crop season(s) of interest if there are several cropping seasons in the country (e.g. Meher and Belg in Ethiopia, rainy season / flood-recession cropping / irrigated dry season in the Sahel). You can refer to the “last season” or “ongoing season". | H8: saison des pluies | I8: wet season
C9: season phase | D9: Post-récolte | E9: Recently finished | F9: Indiquez le stade de la saison culturale au moment de la collecte des données. Si la récolte de la saison n'a pas encore eu lieu, la question sur la récolte des cultures (crp_harv_change) inclura le mot "attendue" (là où se trouve #attendue ou rien#). Si la récolte a eu lieu, "attendue" ne sera pas inséré dans la question. | G9: Indicate the phase of the season at the time of data collection. If the harvest from the season has not yet occurred, the question on crop harvest (crp_harv_change) will include the word “expected” (where #expected or nothing# is located). If the harvest has occured, "expected" will not be inserted in the question. | H9: Récolte | I9: Harvesting
C10: local measurement unit | F10: Indiquez l'unité utilisée localement pour mesurer la taille des terrains, autre que les acres, les hectares, les mètres carrés et les pieds carrés. Si aucune autre unité de mesure n'est nécessaire, garder cette cellule vide. | G10: Specify the local measurement unit for land size, other than acres, hectares, square meters and square feet. If no other unit of measurement is needed, keep this cell blank. | H10: Jeribs | I10: Jeribs
C11: local measurement unit conversion | F11: Indiquez la conversion de l'unité de mesure locale en hectares. En d'autres termes, indiquez combien d'unités de mesure locales y a-t-il dans 1 ha. | G11: Include the conversion of the local measurement unit to hectares. In other words, how many local measurement units are in 1 ha. | H11: 0.2 | I11: 0.2
B12: FOR OPTIONAL QUESTIONS . (Fill out if applicable) . | C12: currency | D12: Francs CFA | E12: Francs CFA | F12: Nom de la principale devise utilisée au niveau national; par exemple, USD; Naira; Rial; Pesos; etc. | G12: The name of the main currency used nationally; USD; Naira; Rial; Pesos; etc. | H12: Naira | I12: Naira
C13: MIN AMOUNT | D13: 5 | E13: 5 | F13: Le montant minimum d'une source de revenu doit être fixé à 0 ou à toute valeur en dessous de laquelle il n'est pas possible d'effectuer une transaction. Par exemple, la plus petite pièce/billet d'une devise peut être de 1000, auquel cas vous fixerez le minimum à 1000. Cette saisie doit être effectuée dans la même devise que celle spécifiée ci-dessus. Seuls des chiffres doivent être saisis. | G13: The minimum amount for an income source should be set at 0 or any value below which it is not possible to do a transaction. For example, the smallest coin/banknote in a currency can be 1000, in which case you would set the minimum at 1000. Provide this input in the same currency as specified above. Only digits should be inputted. | H13: 5 | I13: 5
C14: THRESHOLD | D14: 450000 | E14: 450000 | F14: Le salaire seuil doit être calculé pour signaler les valeurs aberrantes (réponses qui semblent suspectes). En utilisant des enquêtes précédentes représentatives de cette population, une bonne estimation est la moyenne plus deux écarts types, ce qui devrait dégager le seuil pour les 3 ou 4% des valeurs de revenu les plus élevées. Cette saisie doit être effectuée dans la même devise que celle spécifiée ci-dessus. Seuls des chiffres doivent être saisis. | G14: The threshold salary should be calculated to flag outliers (responses that look suspiciously high). Using previous representative surveys for this population, a good estimate is the average plus three (3) standard deviations, which should give the threshold for the 3 or 4% highest income values. Provide this input in the same currency as specified above. Only digits should be inputted. | H14: 1200000 | I14: 1200000
C15: local vegetables | D15: moringa, oseille, chou, tomate, laitue, concombre, courgette, aubergine, carotte | E15: moringa, oseille, chou, tomate, laitue, concombre, courgette, aubergine, carotte | F15: Saisissez quelques légumes locaux courants [à utiliser comme exemples dans l'indicateur de score de consommation alimentaire]. | G15: Input some common local vegetables [to be used as examples in the food consumption score indicator]. | H15: aubergines, courgettes, choux-fleurs | I15: eggplants, zucchini, cauliflower
C16: local fruits | D16: Mangue, pastèque, banane, ananas, dattes, orange, melon | E16: Mangue, pastèque, banane, ananas, dattes, orange, melon | F16: Indiquez quelques fruits locaux courants [à utiliser comme exemples dans l'indicateur de score de consommation alimentaire]. | G16: Input some common local fruits [to be used as examples in the food consumption score indicator]. | H16: pommes, bananes, oranges | I16: apples, bananas, oranges
B18: FILL OUT FOR QUESTIONNAIRE DURATION ESTIMATION . | C18: Expected percentage of respondents cultivating crops | D18: 0.91 | E18: 0.91 | F18: Si l'enquête est représentative et ne comporte pas de quotas, écrivez la proportion de ménages ruraux impliqués dans les cultures au niveau du pays, ou si l'enquête suit un cycle précédent avec un plan d'échantillonnage identique, indiquez simplement le pourcentage du cycle précédent. Si vous utilisez des quotas, calculez le rapport entre le quota et la taille minimale de l'échantillon au niveau où le quota est appliqué (ainsi, si vous avez une taille minimale d'échantillon par strate de 110 avec un quota de 100 producteurs de cultures, alors c'est 100/110 = 91% (le maximum que vous devez écrire est 100%). | G18: If the survey is representative and has no quotas, write the proportion of rural households cultivating crops at country level, or if the survey follows a previous round with identical sample design, just report the percentage from the previous round. If you are using quotas, calculate the ratio of the quota over the minimum sample size at the level where the quota is implemented (so if you have a minimum sample size per strata of 110 with a quota of 100 crop producers, then it's 100/110 = 91% (the maximum you should write is 100%). | H18: 0.91 | I18: 0.91
C19: Expected percentage of respondents raising livestock | D19: 0.91 | E19: 0.91 | F19: Si l'enquête est représentative et ne comporte pas de quotas, écrivez la proportion de ménages ruraux impliqués dans l'élevage, ou si l'enquête suit un cycle précédent avec un plan d'échantillonnage identique, indiquez simplement le pourcentage du cycle précédent. Si vous utilisez des quotas, calculez le rapport entre le quota et la taille minimale de l'échantillon au niveau où le quota est appliqué (ainsi, si vous avez une taille minimale d'échantillon par strate de 110 avec un quota de 100 éleveurs, alors c'est 100/110 = 91% (le maximum que vous devez écrire est 100%). | G19: If the survey is representative and has no quotas, write the proportion of rural households raising livestock at country level, or if the survey follows a previous round with identical sample design, just report the percentage from the previous round. If you are using quotas, calculate the ratio of the quota over the minimum sample size at the level where the quota is implemented (so if you have a minimum sample size of 110 but a quota of 100 livestock producers, then it's 100/110 = 91% (the maximum you should write is 100%) | H19: 0.91 | I19: 0.91
C20: Expected percentage of respondents involved in fishery | D20: 0.05 | E20: 0.05 | F20: Si l'enquête est représentative et ne comporte pas de quotas, écrivez la proportion de ménages ruraux impliqués dans la pêche ou l'aquaculture; sinon, si vous utilisez des quotas, calculez le rapport entre le quota et la taille de l'échantillon au niveau où le quota est appliqué (ainsi, si vous n'avez pas fixé de quota, et que vous pensez avoir une proportion représentative de pêcheurs, écrivez simplement le pourcentage de pêcheurs dans la population que vous ciblez, dans l'exemple à droite, 5%). | G20: If the survey is representative and has no quotas, write the proportion of rural households involved in fisheries or aquaculture, otherwise if you are using quotas, calculate the ratio of the quota over the sample size at the level where the quota is implemented. (so if you haven't set a quota, and you expect to have a representative proportion of fishermen, just write the percentage of fishermen in the population you are targeting, in the example to the right, 5%) | H20: 0.05 | I20: 0.05
