Workbook

Sheet survey
A1: GeoPoll Submission Form
A2: FAO - Household Questionnaire | N2: Additional notes
A3: Q # | B3: Q Name | C3: Suggested Qname | D3: English | E3: Length | F3: Q Type | G3: Randomize | H3: Conditional | I3: Programming Instructions | J3: Skip Pattern | K3: Codes | L3: Default skip patterns & conditional | M3: Specify skip pattern variable (from blue text) | O3: Estimated percentage of repondents | R3: Mandatory | V3: Duration (sec) | W3: Weighted duration | X3: Core questions only
A4: A. PRESENTATION OF THE SURVEY AND ELIGIBILITY CRITERIA SELECTION | R4: no | W4: =IF(V4="","",V4*T4) | X4: =IF(R4="yes",W4,"")
A5: NA | B5: Optin | D5: Optin | E5: =LEN(D5) -> 5 | F5: Open Ended | G5: NA | H5: NA | I5: Form Type - TextBox | J5: Any Response = phone_number | K5: NA | L5: NA | R5: no | V5: 0 | W5: =IF(V5="","",V5*O5) -> 0 | X5: =IF(R5="yes",W5,"")
A6: NA | B6: phone_number | C6: phone_number | D6: Input the phone number that you are contacting: | E6: =LEN(D6) -> 48 | F6: Open Ended | G6: NA | H6: NA | I6: Form Type - TextBox | J6: Any Response = calldispo | K6: NA | L6: NA | R6: yes | V6: 0 | W6: =IF(V6="","",V6*O6) -> 0 | X6: =IF(R6="yes",W6,"") -> 0
A7: NA | B7: calldispo | C7: calldispo | D7: Phone number: #CATI_MOBILENUMBER# 1)Someone answers 2)Answering machine 3)No answer 4)Hang up or refusal 5)Call back 6)Under review 7)Disconnected | E7: =LEN(D7) -> 146 | F7: Single Choice | G7: NA | H7: NA | I7: Form Type - Buttons | J7: 1 = resp_language 2 = AnsweringMachine 3 = NoAnswer 4 = Refusal 5 = WhenCallBack 6 = UnderReview 7 = Disconnected | K7: NA | L7: NA | R7: no | V7: 14.695308 | W7: =IF(V7="","",V7*O7) -> 0 | X7: =IF(R7="yes",W7,"")
A8: NA | B8: AnsweringMachine | C8: calldispo_answeringmachine | D8: Reached an answering machine. | E8: =LEN(D8) -> 29 | F8: NA | G8: NA | H8: NA | I8: NA | J8: End Poll AnsweringMachine | K8: NA | L8: NA | R8: no | V8: 0 | W8: =IF(V8="","",V8*O8) -> 0 | X8: =IF(R8="yes",W8,"")
A9: NA | B9: NoAnswer | C9: calldispo_noanswer | D9: Phone rang and no one answered. | E9: =LEN(D9) -> 31 | F9: NA | G9: NA | H9: NA | I9: NA | J9: End Poll NoAnswer | K9: NA | L9: NA | R9: no | V9: 0 | W9: =IF(V9="","",V9*O9) -> 0 | X9: =IF(R9="yes",W9,"")
A10: NA | B10: UnderReview | C10: calldispo_underreview | D10: Case needs review by a supervisor. | E10: =LEN(D10) -> 34 | F10: NA | G10: NA | H10: NA | I10: NA | J10: End Poll UnderReview | K10: NA | L10: NA | R10: no | V10: 0 | W10: =IF(V10="","",V10*O10) -> 0 | X10: =IF(R10="yes",W10,"")
A11: NA | B11: Disconnected | C11: calldispo_disconnected | D11: Phone was disconnected or out of service. | E11: =LEN(D11) -> 41 | F11: NA | G11: NA | H11: NA | I11: NA | J11: End Poll Disconnected | K11: NA | L11: NA | R11: no | V11: 0 | W11: =IF(V11="","",V11*O11) -> 0 | X11: =IF(R11="yes",W11,"")
A12: NA | B12: resp_language | C12: resp_language | D12: Which language do you wish to proceed with? [OPERATOR: READ ANSWER CHOICES. SINGLE RESPONSE.] 1)English 2)other options [add as many as necessary] | E12: =LEN(D12) -> 148 | F12: Single Choice | G12: NA | H12: NA | I12: Form Type - Buttons | J12: 1 = introduction [English] 2 = introduction [languages & add more if needed] | K12: NA | L12: For any response, go to introduction | N12: Insert most common national languages here [max 4 for translation with GeoPoll]. | R12: no | V12: 3.1032724 | W12: =IF(V12="","",V12*O12) -> 0 | X12: =IF(R12="yes",W12,"")
A13: NA | B13: introduction | C13: introduction | D13: Hello sir/ma'am, my name is #OPERATOR#, and I am calling from GeoPoll Polling Agency on behalf of the Food and Agriculture Organization of the United Nations [FAO] and the World Food Programme (WFP). We are conducting a survey on household livelihoods and the ability to access food in your area. I would like to ask you some questions about your household. The survey usually takes 15/20 minutes to complete. Any information that you provide will be kept strictly confidential, only used for the purpose of the survey and will not be shown to other people. Your voluntary participation in the outcome of this interview is NOT IN ANY WAY linked to your personal chance of receiving any assistance. This is voluntary and you can choose not to answer any or all of the questions if you want. However, we hope that you will participate since your views are important. You will receive #TOPUP#! of communication credit as an incentive for the participation of the survey. Please note that this call may be recorded for quality purposes. Do you have any questions? [OPERATOR: ADDRESS QUESTIONS FROM RESPONDENT, IF ANY.] 1)CONTINUE | E13: =LEN(D13) -> 1133 | F13: Single Choice | G13: NA | H13: NA | I13: Form Type - Buttons | J13: 1 = Agree | K13: NA | L13: For any response, go to Agree | N13: Set the amount of incentive here, if any. | R13: no | V13: 37.418449 | W13: =IF(V13="","",V13*O13) -> 0 | X13: =IF(R13="yes",W13,"")
A14: NA | B14: Agree | C14: resp_agree | D14: Are you interested in participating in this survey? [OPERATOR: SINGLE RESPONSE] 1)Yes 2)Not now but another time in the week 3)No | E14: =LEN(D14) -> 134 | F14: StartRecording | G14: NA | H14: NA | I14: Form Type - Buttons | J14: 1 = resp_firstname 2 = WhenCallBack 3 = resp_refusalwhy | K14: NA | L14: if Agree = 1, go to resp_firstname if Agree = 2, go to WhenCallBack if Agree = 3, go to resp_refusalwhy | O14: 1 | R14: no | V14: 3.8059516 | W14: =IF(V14="","",V14*O14) -> 3.8059516 | X14: =IF(R14="yes",W14,"")
A15: NA | B15: resp_refusalwhy | C15: resp_refusalwhy | D15: Please let us know why you have REFUSED to take the survey. [OPERATOR: SINGLE RESPONSE] 1)Not interested 2)Do not want to be recorded 3)Other [specify] | E15: =LEN(D15) -> 153 | F15: Open Ended - Single Choice | G15: NA | H15: NA | I15: Form Type - RadioList | J15: Any Response = Refusal | K15: NA | L15: For any response, go to Refusal | O15: 1 | R15: no | V15: 0 | W15: =IF(V15="","",V15*O15) -> 0 | X15: =IF(R15="yes",W15,"")
A16: NA | B16: WhenCallBack | C16: resp_whencallback | D16: When would it be a good time to call you back? [RECORD HH/MM/DD/MM OF CALLBACK] | E16: =LEN(D16) -> 80 | F16: Open Ended | G16: NA | H16: NA | I16: Form Type - TextBox IsCallBackDemographic | J16: Any Response = CallbackMessageEN | K16: NA | L16: For any response, go to CallbackMessageEN | O16: 1 | R16: no | V16: 0 | W16: =IF(V16="","",V16*O16) -> 0 | X16: =IF(R16="yes",W16,"")
A17: NA | B17: CallbackMessageEN | C17: callbackmessage_en | D17: Thank you, we will call you back at {WhenCallBack} you requested. Thank you again and have a great day! [OPERATOR: ENTER CALL NOTES BELOW, WHO YOU SPOKE TO AND WHAT THEY SAID] | E17: =LEN(D17) -> 176 | F17: Open Ended | G17: NA | H17: NA | I17: Form Type - TextBox | J17: Any Response = End poll callback | K17: NA | L17: NA | O17: 1 | R17: no | V17: 0 | W17: =IF(V17="","",V17*O17) -> 0 | X17: =IF(R17="yes",W17,"")
A18: NA | B18: Ineligible | C18: NA | D18: You are ineligible for this survey. Thank you for your time and please look out for future surveys! | E18: =LEN(D18) -> 99 | F18: NA | G18: NA | H18: NA | I18: NA | J18: End Poll Ineligible | K18: NA | L18: NA | O18: 1 | R18: no | V18: 0 | W18: =IF(V18="","",V18*O18) -> 0 | X18: =IF(R18="yes",W18,"")
A19: NA | B19: Refusal | C19: NA | D19: Thank you for your time, you will be removed from today's survey. | E19: =LEN(D19) -> 65 | F19: NA | G19: NA | H19: NA | I19: NA | J19: End poll declined | K19: NA | L19: NA | O19: 1 | R19: no | V19: 0 | W19: =IF(V19="","",V19*O19) -> 0 | X19: =IF(R19="yes",W19,"")
A20: B. GENERAL INFORMATION & ELIGIBILITY CRITERIA | W20: =IF(V20="","",V20*O20) | X20: =IF(R20="yes",W20,"")
A21: 1 | B21: resp_age | C21: resp_age | D21: How old are you? [OPERATOR: RECORD AGE IN NUMBER OF YEARS. ROUND UP TO NEAREST WHOLE NUMBER. IF THE RESPONDENT GIVES BIRTH YEAR, REPEAT THE QUESTION. ENTER 00 FOR DON'T KNOW.] | E21: =LEN(D21) -> 177 | F21: Range | G21: NA | H21: NA | I21: Form Type - TextBox | J21: 0-17 = Ineligible 18-100 = resp_gender 00 = Ineligible | K21: NA | L21: Only respondents from 18-100 will be eligible for the survey. | O21: =1 -> 1 | R21: yes | V21: 9.8907185 | W21: =IF(V21="","",V21*O21) -> 9.8907185 | X21: =IF(R21="yes",W21,"") -> 9.8907185
A22: =A21+1 -> 2 | B22: resp_gender | C22: resp_gender | D22: What is the gender of the respondent? [OPERATOR: DO NOT ASK THIS QUESTION OUT LOUD. LISTEN TO THE VOICE AND SELECT THE GENDER.] 1)Male 2)Female 3)DON'T KNOW 4)REFUSED | E22: =LEN(D22) -> 168 | F22: Single Choice | G22: NA | H22: NA | I22: Form Type - Buttons | J22: 1-4 = phone_number_conf | K22: NA | L22: For any response, go to phone_number_conf | O22: =1 -> 1 | R22: yes | V22: 1.7156482 | W22: =IF(V22="","",V22*O22) -> 1.7156482 | X22: =IF(R22="yes",W22,"") -> 1.7156482
O23: =1 -> 1 | W23: =IF(V23="","",V23*O23) | X23: =IF(R23="yes",W23,"")
O24: =1 -> 1 | W24: =IF(V24="","",V24*O24) | X24: =IF(R24="yes",W24,"")
A25: 3 | B25: hh_admin1 | C25: hh_admin1 | D25: Currently, in which State/Region does your household reside? [OPERATOR: SINGLE SELECTION.] [HINT: HOUSEHOLD CONSISTS OF ALL MEMBERS LIVING TOGETHER, SHARING RESOURCES & EATING FROM THE SAME POT.] 1)ADMIN1 2)DON'T KNOW 3)REFUSED | E25: =LEN(D25) -> 230 | F25: Single Choice | G25: NA | H25: NA | I25: Form Type - Buttons IsDemographic - ADM1 | J25: 1 = hh_admin2_1 2-3 = Ineligible | K25: NA | L25: The administrative information will be updated by GeoPoll based on the sample design document and the administrative boundaries provided by the dashboard team after the questionnaire validation. | O25: =1 -> 1 | R25: yes | V25: 13.957259 | W25: =IF(V25="","",V25*O25) -> 13.957259 | X25: =IF(R25="yes",W25,"") -> 13.957259
A26: =A25+1 -> 4 | B26: hh_admin2_1 | C26: hh_admin2_1 | D26: Currently, in which Township does your household reside? [OPERATOR: SINGLE RESPONSE.] 1)ADMIN2 2)DON'T KNOW 3)REFUSED | E26: =LEN(D26) -> 120 | F26: Single Choice | G26: NA | H26: NA | I26: Form Type - Buttons IsDemographic - ADM2 | J26: 1 = hh_agricactivity 2-3 = Ineligible | K26: NA | O26: =1 -> 1 | R26: yes | V26: 7.954999 | W26: =IF(V26="","",V26*O26) -> 7.954999 | X26: =IF(R26="yes",W26,"") -> 7.954999
B27: quotareached | C27: quotareached | D27: [OPERATOR: DO NOT READ. ANSWER QUESTION BELOW.] THIS RESPONDENT REPORTED THEY LIVE IN: {ADM1} {ADM2} 1)THE GOAL FOR THIS LOCATION HAS BEEN ACHIEVED - END SURVEY 2)THE GOAL FOR THIS LOCATION IS OPEN - CONTINUE SURVEY | E27: =LEN(D27) -> 218 | F27: Single Choice | G27: NA | H27: NA | I27: Form Type - Buttons | J27: 1 = End Poll Quota Reached 2 = hh_agricactivity | K27: NA
A28: =#REF!+1 -> #REF! | B28: hh_agricactivity | C28: hh_agricactivity | D28: Has anybody in your household produced crops or livestock for household consumption or for sale in the past 12 months, including household members currently away for transhumance? [OPERATOR: SINGLE RESPONSE. THIS IS THE MAIN SCREENING QUESTION.] [HINT FOR PROBING: Do you cultivate any plants to sale or consume? Do you raise any animals with the intent of selling or consuming them or their products like meat, milk, wool or leather? Is one of your household member currently away with cattle or other animals for transhumance?] 1)Yes - crop production 2)Yes - livestock production 3)Yes - both crop and livestock production 4)No 5)DON'T KNOW 6)REFUSED | E28: =LEN(D28) -> 658 | F28: Single Choice | G28: NA | H28: NA | I28: Form Type - Buttons | J28: 1-4 = resp_id 5-6 = Ineligible | K28: NA | L28: if hh_agricactivity = 1-4, go to resp_id. Otherwise, the respondent is ineligible. | O28: =1 -> 1 | R28: yes | V28: 24.410839 | W28: =IF(V28="","",V28*O28) -> 24.410839 | X28: =IF(R28="yes",W28,"") -> 24.410839
B29: o_cyclaffected | D29: Has your household or community being impacted by Cyclone MOCHA and affected your household ability to raise income and/or to produce food for self consumption? [OPERATOR: SINGLE RESPONSE.] 1)YES 2)NO 3)DON'T KNOW 4)REFUSED | E29: =LEN(D29) -> 226 | F29: Single Choice | O29: =1 -> 1 | W29: =IF(V29="","",V29*O29) | X29: =IF(R29="yes",W29,"")
A31: B. GENERAL HOUSEHOLD INFORMATION | W31: =IF(V31="","",V31*O31) | X31: =IF(R31="yes",W31,"")
O32: =1 -> 1 | W32: =IF(V32="","",V32*O32) | X32: =IF(R32="yes",W32,"")
A33: =#REF!+1 -> #REF! | B33: hh_gender | C33: hh_gender | D33: Is the head of your household male or female? [OPERATOR: SINGLE RESPONSE.] 1)Male 2)Female 3)DON'T KNOW 4)REFUSED | E33: =LEN(D33) -> 116 | F33: Single Choice | G33: NA | H33: NA | I33: Form Type - Buttons | J33: 1-4 = hh_education | K33: NA | L33: if hh_gender = 1-4, go to hh_education. | O33: =1 -> 1 | R33: yes | V33: 10.504534 | W33: =IF(V33="","",V33*O33) -> 10.504534 | X33: =IF(R33="yes",W33,"") -> 10.504534
B34: RuralUrban | D34: Are you living in a rural or urban area? [OPERATOR: CHOOSE ONLY ONE OPTION] 1)RURAL [Village] AREA 2)URBAN [Ward] AREA 3)DON'T KNOW 4)REFUSED | F34: Single Choice | O34: =1 -> 1 | W34: =IF(V34="","",V34*O34) | X34: =IF(R34="yes",W34,"")
A35: =A190+1 -> #REF! | B35: hh_size | C35: hh_size | D35: How many people are part of the household? [OPERATOR: RECORD NUMBER OF MEMBERS IN HOUSEHOLD. ENTER 88 FOR DON'T KNOW & 99 FOR REFUSED.] [HINT: TO BE A PART OF THE SAME HOUSEHOLD, MEMBERS MUST LIVE UNDER THE SAME ROOF, SHARE THE SAME RESOURCES & EAT FROM THE SAME POT.] | E35: =LEN(D35) -> 269 | F35: Range | G35: NA | H35: NA | I35: Form Type - TextBox | J35: 1-50 = hh_asset_prod 88-88 = hh_asset_prod 99-99 = hh_asset_prod | K35: NA | L35: For any response, go to [next question] | O35: =1 -> 1 | R35: no | V35: 16.902294 | W35: =IF(V35="","",V35*O35) -> 16.902294 | X35: =IF(R35="yes",W35,"")
A36: =A35+1 -> #REF! | B36: o_HHSize04 | C36: o_HHSize04 | D36: What is the total number of children aged 0 to 4 years old (0-59 months) in your household? [OPERATOR: RECORD NUMBER GIVEN] | E36: =LEN(D36) -> 124 | F36: Range | N36: GeoPoll: Confirm if we need to add validation rules here. Please note that if we are to add validation rules, we will need to do away with this instruction at hh_size "ENTER 88 FOR DON'T KNOW &99 FOE REFUSED], so as not to interfere with the validations should any of these be selected.
A37: =A36+1 -> #REF! | B37: o_HHSize5_15 | C37: o_HHSize5_15 | D37: What is the total number of members aged 5 to 15 years old in your household? [OPERATOR: RECORD NUMBER GIVEN] | E37: =LEN(D37) -> 110 | F37: Range
A38: =A37+1 -> #REF! | B38: o_HHSize16_59 | C38: o_HHSize16_59 | D38: What is the total number of members aged 16 to 59 years old in your household? [OPERATOR: RECORD NUMBER GIVEN] | E38: =LEN(D38) -> 111 | F38: Range
A39: =A38+1 -> #REF! | B39: o_HHSize60 | C39: o_HHSize60 | D39: What is the total number of members aged 60 years old and older in your household? [OPERATOR: RECORD NUMBER GIVEN] | E39: =LEN(D39) -> 116 | F39: Range
A40: =A39+1 -> #REF! | B40: o_HHDisability | C40: o_HHDisability | D40: How many members of your household have a disability? Note: to count as a disability the person must have a lot of difficulty or cannot do at all, any of the following: seeing (even if wearing glasses), hearing (even if wearing hearing aids), walking or climbing steps, remembering or concentrating, self-care (such as washing or dressing) or communicating (understanding or being understood). [OPERATOR: RECORD THE NUMBER GIVEN] | E40: =LEN(D40) -> 432 | F40: Range | N40: GeoPoll: Same feedback as above.
A41: =#REF!+1 -> #REF! | B41: hh_age | C41: hh_age | D41: How old is the head of household? [OPERATOR: SINGLE RESPONSE.] 1)Under 18 2)18 to 40 3)41 to 65 4)Over 65 5)DON'T KNOW 6)REFUSED | E41: =LEN(D41) -> 133 | F41: Single Choice | G41: NA | H41: NA | I41: Form Type - Buttons | J41: 1-6 = income_main | K41: NA | L41: For any response, go to [next question] | O41: =1 -> 1 | R41: no | V41: 7.0248413 | W41: =IF(V41="","",V41*O41) -> 7.0248413 | X41: =IF(R41="yes",W41,"")
A42: =A33+1 -> #REF! | B42: hh_education | C42: hh_education | D42: What is the educational level attained by the head of household? [OPERATOR: SINGLE RESPONSE.] 1)None or did not complete primary school 2)Completed primary school 3)Completed secondary school 4)Completed higher education [University / College] degree 5)Religious or informal education only 6)DON'T KNOW 7)REFUSED | E42: =LEN(D42) -> 314 | F42: Single Choice | G42: NA | H42: NA | I42: Form Type - Buttons | J42: 1-7 = hh_wealth | K42: NA | L42: if hh_education = 1-7, go to hh_wealth. | O42: =1 -> 1 | R42: yes | V42: 12.421899 | W42: =IF(V42="","",V42*O42) -> 12.421899 | X42: =IF(R42="yes",W42,"") -> 12.421899
O43: =1 -> 1 | W43: =IF(V43="","",V43*O43) | X43: =IF(R43="yes",W43,"")
A44: 10 | B44: hh_wealth_water | C44: hh_wealth_water | D44: Where does the water that you drink at home come from? [OPERATOR: SINGLE CHOICE.] 1)Private tap from piped water 2)Public tap 3)Protected well 4)Bottled water 5)Other safe source 6)River 7)Unprotected well 8)Spring water 9)Surface water [e.g. canals, ponds, dams] 10)Other unsafe source 11)DON'T KNOW 12)REFUSED | E44: =LEN(D44) -> 313 | F44: Single Choice | G44: NA | H44: NA | I44: Form Type - Buttons | J44: 1-12 = [income_main OR other optional question] | K44: NA | L44: For any response, go to [income_main OR other optional question] | N44: Select wealth indicators based on baseline information available; you can delete those that you do not want to use. If none of these indicators work in the context of your country, other wealth proxies are proposed in the optional questions below. Remember that baseline data will be necessary, and the variable should be defined properly in the "weight_input_table". | O44: =1 -> 1 | R44: yes | V44: 16.615656 | W44: =IF(V44="","",V44*O44) -> 16.615656 | X44: =IF(R44="yes",W44,"") -> 16.615656
B45: hh_wealth_house | D45: What kind of dwelling unit does your household live in? [OPERATOR: SINGLE RESPONSE.] 1)Apartment/condominium 2)Bungalow/brick house 3)Semi-pucca house 4)Wooden house 5)Bamboo House 6)Hut [2-3 years] 7)Hut [1 years] 8)Tent/plastic sheets 9)Substandard shelter / collective shelter [factory/warehouse/garage/shop/worksite/unfinished building] 10)No shelter [sleeping in open] 11)Other [specify] 12)DON'T KNOW 13)REFUSED | F45: Single Choice
O46: =1 -> 1 | W46: =IF(V46="","",V46*O46) | X46: =IF(R46="yes",W46,"")
A47: C. INCOME SOURCES, LIVELIHOOD AND SHOCKS | W47: =IF(V47="","",V47*O47) | X47: =IF(R47="yes",W47,"")
B50: HHIncEarners | D50: How many members of your household earned an income in the last 3 months? [OPERATOR: RECORD NUMBER GIVEN] | F50: Range | O50: =1 -> 1 | W50: =IF(V50="","",V50*O50) | X50: =IF(R50="yes",W50,"")
B51: HHIncEarners_year | D51: How many members of your household were earning an income in this period one year ago? [OPERATOR: RECORD NUMBER GIVEN] | F51: Range
A52: =A41+1 -> #REF! | B52: income_main | C52: income_main | D52: What was your household's main source of income in the past 3 months? [OPERATOR: SINGLE RESPONSE. REFUSED OPTION SHOULD BE AVOIDED AS MUCH AS POSSIBLE.] 1)Production and sale of staple crops 2)Production and sale of vegetables or fruit 3)Production and sale of cashcrops 4)Production and sale of livestock and livestock products 5)Production and sale of honey or bee products 6)Production and sale of fish 7)Collection and sale of forestry or bush products 8)Agricultural trade EXCLUDING producers [formal or informal] 9)Daily wage on farms and other casual employment in agricultural sector 10)Stable employment in agricultural sector 11)Non-agricultural self-employed or liberal profession / doctor / architect / lawyer / including restaurant 12)Off-farm daily wages and other non-agricultural casual employment 13)Stable employment in non-agricultural sector 14)Public employment 15)Income not derived from work / Charity 16)Income not derived from work / Welfare transfer, pension, humanitarian aid 17)Income not derived from work / Remittances 18)Income not derived from work / Income from other rents 19)No income source in the last 3 months and used exclusively savings / debt 20)REFUSED | E52: =LEN(D52) -> 1204 | F52: Single Choice | G52: NA | H52: NA | I52: Form Type - Buttons IsDemographic | J52: 1-3 = income_main_crop_check 4 = income_main_ls_check 5 = income_main_comp OR optional question 6 = income_main_fish_check 7-18 = income_main_comp OR optional question 19-20 = shock | K52: NA | L52: if options #1-3 selected go to income_main_crop_check if options #4 selected go to income_main_ls_check if options #6 selected go to income_main_fish_check if options #5, 7-18 selected, go to [income_main_comp OR optional question] if options #19-20 selected, go to shock | O52: =1 -> 1 | R52: yes | V52: 31.888334 | W52: =IF(V52="","",V52*O52) -> 31.888334 | X52: =IF(R52="yes",W52,"") -> 31.888334
B53: income_main_crop_check | C53: income_main_crop_check | D53: Are the crops that you sell also produced by you or anyone in your household? [OPERATOR: SINGLE RESPONSE.] 1)YES 2)NO 3)DON'T KNOW 4)REFUSED | E53: =LEN(D53) -> 143 | F53: Single Choice | G53: NA | H53: NA | I53: Form Type - Buttons | J53: 1-4 = income_main_comp OR optional question | K53: NA | L53: if income_main_crop_check = 1-4, go to [income_main_comp OR optional question] | O53: =1 -> 1 | R53: yes | V53: 8 | W53: =IF(V53="","",V53*O53) -> 8 | X53: =IF(R53="yes",W53,"") -> 8
B54: income_main_ls_check | C54: income_main_ls_check | D54: Are the livestock and livestock products that you sell also produced by you or anyone in your household? [OPERATOR: SINGLE RESPONSE.] 1)YES 2)NO 3)DON'T KNOW 4)REFUSED | E54: =LEN(D54) -> 170 | F54: Single Choice | G54: NA | H54: NA | I54: Form Type - Buttons | J54: 1-4 = income_main_comp OR optional question | K54: NA | L54: if income_main_ls_check = 1-4, go to [income_main_comp OR optional question] | O54: =1 -> 1 | R54: yes | V54: 8 | W54: =IF(V54="","",V54*O54) -> 8 | X54: =IF(R54="yes",W54,"") -> 8
B55: income_main_fish_check | C55: income_main_fish_check | D55: Are the fish and/or fish products that you sell also captured or harvested by you or anyone in your household? [OPERATOR: SINGLE RESPONSE.] 1)YES 2)NO 3)DON'T KNOW 4)REFUSED | E55: =LEN(D55) -> 176 | F55: Single Choice | G55: NA | H55: NA | I55: Form Type - Buttons | J55: 1-4 = income_main_comp OR optional question | K55: NA | L55: if income_main_fish_check = 1-4, go to [income_main_comp OR optional question] | O55: =1 -> 1 | R55: yes | V55: 8 | W55: =IF(V55="","",V55*O55) -> 8 | X55: =IF(R55="yes",W55,"") -> 8
B57: o_income_main_selfemployed | D57: What type of self-employment / liberal profession? [OPERATOR: SINGLE RESPONSE.] 1)Liberal profession [doctor/architect/layer...] 2)Petty trade/selling on streets [own business/self or with family] 3)Small trade [own business/ <5 employees] 4)Medium/large trade [own business/>=5 employees] 5)Other 6)DON'T KNOW 7)REFUSED | F57: Single Choice | O57: =1 -> 1 | W57: =IF(V57="","",V57*O57) | X57: =IF(R57="yes",W57,"")
B58: o_wage_main_amount | D58: What was the typical wage for wage labourers per person per day in the past one month (30 days)? [OPERATOR: RECORD NUMBER GIVEN. ENTER 8888888 FOR DON'T KNOW & 9999999 FOR REFUSED.] | F58: Range
O59: =1 -> 1 | W59: =IF(V59="","",V59*O59) | X59: =IF(R59="yes",W59,"")
A60: =#REF!+1 -> #REF! | B60: income_main_comp | C60: income_main_comp | D60: Has your household's income from {income_main} changed in the last 3 months compared to the same period of a normal year? [OPERATOR: SINGLE RESPONSE.] 1)A lot more [increased by more than 50%] 2)Slightly more 3)Same 4)Slightly less 5)A lot less [less than half as much] 6)DON'T KNOW 7)REFUSED | E60: =LEN(D60) -> 294 | F60: Single Choice | G60: NA | H60: NA | I60: Form Type - Buttons | J60: 1-7= income_sec | K60: NA | L60: if income_main_comp = 1-7, go to income_sec | O60: =1 -> 1 | R60: yes | V60: 22.126215 | W60: =IF(V60="","",V60*O60) -> 22.126215 | X60: =IF(R60="yes",W60,"") -> 22.126215
B61: o_incomechangereduced | D61: Please describe the degree of income reduction: [OPERATOR: SINGLE RESPONSE] 1)0-25% 2)26-50% 3)51-75% 4)76-100% 5)DON'T KNOW 6)REFUSED | F61: Single Choice | O61: =1 -> 1 | W61: =IF(V61="","",V61*O61) | X61: =IF(R61="yes",W61,"")
A62: =A60+1 -> #REF! | B62: income_sec | C62: income_sec | D62: What was your household's second most important source of income in the past 3 months? [OPERATOR: SINGLE RESPONSE. DON'T KNOW AND REFUSED OPTIONS SHOULD BE AVOIDED AS MUCH AS POSSIBLE.] 1)Production and sale of staple crops 2)Production and sale of vegetables or fruit 3)Production and sale of cashcrops 4)Production and sale of livestock and livestock products 5)Production and sale of honey or bee products 6)Production and sale of fish 7)Collection and sale of forestry or bush products 8)Agricultural trade EXCLUDING producers [formal or informal] 9)Daily wage on farms and other casual employment in agricultural sector 10)Stable employment in agricultural sector 11)Non-agricultural self-employed or liberal profession / doctor / architect / lawyer / including restaurant 12)Off-farm daily wages and other non-agricultural casual employment 13)Stable employment in non-agricultural sector 14)Public employment 15)Income not derived from work / Charity 16)Income not derived from work / Welfare transfer, pension, humanitarian aid 17)Income not derived from work / Remittances 18)Income not derived from work / Income from other rents 19)No second most important source of income 20)DON'T KNOW 21)REFUSED | E62: =LEN(D62) -> 1218 | F62: Single Choice | G62: NA | H62: NA | I62: Form Type - Buttons exclude selected "income_main" IsDemographic | J62: 1-3 = income_sec_crop_check 4 = income_sec_ls_check 5 = income_sec_comp OR optional question 6 = income_sec_fish_check 7-18 = income_sec_comp OR optional question 19-21 = shock | K62: NA | L62: if options #1-3 selected, go to income_sec_crop_check if options #4 selected, go to income_sec_ls_check if options #6 selected, go to income_sec_fish_check if options #5, 7-18 selected, go to [income_sec_comp OR optional question] if options #19-21 selected, go to shock | O62: =1 -> 1 | R62: yes | V62: 18.710653 | W62: =IF(V62="","",V62*O62) -> 18.710653 | X62: =IF(R62="yes",W62,"") -> 18.710653
B63: income_sec_crop_check | C63: income_sec_crop_check | D63: Are the crops that you sell also produced by you or anyone in your household? [OPERATOR: SINGLE RESPONSE.] 1)YES 2)NO 3)DON'T KNOW 4)REFUSED | E63: =LEN(D63) -> 143 | F63: Single Choice | G63: NA | H63: NA | I63: Form Type - Buttons | J63: 1-4 = income_sec_comp OR optional question | K63: NA | L63: if income_sec_crop_check = 1-4, go to [income_sec_comp OR optional question] | O63: =1 -> 1 | R63: yes | V63: 8 | W63: =IF(V63="","",V63*O63) -> 8 | X63: =IF(R63="yes",W63,"") -> 8
B64: income_sec_ls_check | C64: income_sec_ls_check | D64: Are the livestock and livestock products that you sell also produced by you or anyone in your household? [OPERATOR: SINGLE RESPONSE.] 1)YES 2)NO 3)DON'T KNOW 4)REFUSED | E64: =LEN(D64) -> 170 | F64: Single Choice | G64: NA | H64: NA | I64: Form Type - Buttons | J64: 1-4 = income_sec_comp OR optional question | K64: NA | L64: if income_sec_ls_check = 1-4, go to [income_sec_comp OR optional question] | O64: =1 -> 1 | R64: yes | V64: 8 | W64: =IF(V64="","",V64*O64) -> 8 | X64: =IF(R64="yes",W64,"") -> 8
B65: income_sec_fish_check | C65: income_sec_fish_check | D65: Are the fish and/or fish products that you sell also captured or harvested by you or anyone in your household? [OPERATOR: SINGLE RESPONSE.] 1)YES 2)NO 3)DON'T KNOW 4)REFUSED | E65: =LEN(D65) -> 176 | F65: Single Choice | G65: NA | H65: NA | I65: Form Type - Buttons | J65: 1-4 = income_sec_comp OR optional question | K65: NA | L65: if income_sec_fish_check = 1-4, go to [income_sec_comp OR optional question] | O65: =1 -> 1 | R65: yes | V65: 8 | W65: =IF(V65="","",V65*O65) -> 8 | X65: =IF(R65="yes",W65,"") -> 8
B66: o_income_sec_selfemployed | D66: What type of self-employment / liberal profession? [OPERATOR: SINGLE RESPONSE.] 1)Liberal profession [doctor/architect/layer...] 2)Petty trade/selling on streets [own business/self or with family] 3)Small trade [own business/<5 employees] 4)Medium/large trade [own business/>=5 employees] 5)Other 6)DON'T KNOW 7)REFUSED | E66: =LEN(D66) -> 321 | F66: Single Choice | O66: =1 -> 1 | W66: =IF(V66="","",V66*O66) | X66: =IF(R66="yes",W66,"")
A67: =A66+1 -> 1 | B67: o_wage_sec_amount | C67: o_wage_main_amount | D67: What was the typical wage for wage labourers per person per day in the past one month (30 days)? [OPERATOR: RECORD NUMBER GIVEN. ENTER 8888888 FOR DON'T KNOW & 9999999 FOR REFUSED.] | E67: =LEN(D67) -> 185 | F67: Range | G67: =LEN(F67) -> 5 | H67: Range | I67: NA | J67: NA | K67: Form Type - TextBox | O67: if options #1-4, go to [income_main_comp OR income_main_amount] | Q67: resp_age = 18-100 hh_agricactivity = 1 | 2 | 3 | 4 quotareached = 2 income_main = 1-18 | S67: 17 | T67: =1 -> 1 | U67: =S67*T67 -> 17 | X67: no | AB67: New question
O68: =1 -> 1 | W68: =IF(V68="","",V68*O68) | X68: =IF(R68="yes",W68,"")
A69: =#REF!+1 -> #REF! | B69: income_sec_comp | C69: income_sec_comp | D69: Has your household's income from {income_sec} changed in the last 3 months compared to the same period of a normal year? [OPERATOR: SINGLE RESPONSE.] 1)A lot more [increased by more than 50%] 2)Slightly more 3)Same 4)Slightly less 5)A lot less [less than half as much] 6)DON'T KNOW 7)REFUSED | E69: =LEN(D69) -> 294 | F69: Single Choice | G69: NA | H69: NA | I69: Form Type - Buttons | J69: 1-7= income_third | K69: NA | L69: if income_sec_comp = 1-7, go to income_third | O69: =1 -> 1 | R69: yes | V69: 17.261402 | W69: =IF(V69="","",V69*O69) -> 17.261402 | X69: =IF(R69="yes",W69,"") -> 17.261402
O70: =1 -> 1 | W70: =IF(V70="","",V70*O70) | X70: =IF(R70="yes",W70,"")
A71: =A69+1 -> #REF! | B71: income_third | C71: income_third | D71: What was your household's third most important source of income in the past 3 months? [OPERATOR: SINGLE RESPONSE. DON'T KNOW AND REFUSED OPTIONS SHOULD RARELY/NOT AVOIDED AS MUCH AS POSSIBLE.] 1)Production and sale of staple crops 2)Production and sale of vegetables or fruit 3)Production and sale of cashcrops 4)Production and sale of livestock and livestock products 5)Production and sale of honey or bee products 6)Production and sale of fish 7)Collection and sale of forestry or bush products 8)Agricultural trade EXCLUDING producers [formal and informal] 9)Daily wage on farms and other casual employment in agricultural sector 10)Stable employment in agricultural sector 11)Non-agricultural self-employed or liberal profession / doctor / architect / lawyer / including restaurant 12)Off-farm daily wages and other non-agricultural casual employment 13)Stable employment in non-agricultural sector 14)Public employment 15)Income not derived from work / Charity 16)Income not derived from work / Welfare transfer, pension, humanitarian aid 17)Income not derived from work / Remittances 18)Income not derived from work / Income from other rents 19)No third most important source of income 20)DON'T KNOW 21)REFUSED | E71: =LEN(D71) -> 1225 | F71: Single Choice | G71: NA | H71: NA | I71: Form Type - Buttons exclude selected "income_main" exclude selected "income_sec" IsDemographic | J71: 1-3 = income_third_crop_check 4 = income_third_ls_check 5 = income_third_comp OR optional question 6 = income_third_fish_check 7-18 = income_third_comp OR optional question 19-21 = shock | K71: NA | L71: if options #1-3 selected, go to income_third_crop_check if options #4 selected, go to income_third_ls_check if option #6 selected, go to income_third_fish_check if options #5, 7-18 selected, go to [income_third_comp OR optional question] if options #19-21 selected, go to shock | O71: =1 -> 1 | R71: yes | V71: 14.475392 | W71: =IF(V71="","",V71*O71) -> 14.475392 | X71: =IF(R71="yes",W71,"") -> 14.475392
B72: income_third_crop_check | C72: income_third_crop_check | D72: Are the crops that you sell also produced by you or anyone in your household? [OPERATOR: SINGLE RESPONSE.] 1)YES 2)NO 3)DON'T KNOW 4)REFUSED | E72: =LEN(D72) -> 143 | F72: Single Choice | G72: NA | H72: NA | I72: Form Type - Buttons | J72: 1-4 = income_third_comp OR optional question | K72: NA | L72: if income_third_crop_check = 1-4, go to [income_third_comp OR optional question] | O72: =1 -> 1 | R72: yes | V72: 8 | W72: =IF(V72="","",V72*O72) -> 8 | X72: =IF(R72="yes",W72,"") -> 8
B73: income_third_ls_check | C73: income_third_ls_check | D73: Are the livestock and livestock products that you sell also produced by you or anyone in your household? [OPERATOR: SINGLE RESPONSE.] 1)YES 2)NO 3)DON'T KNOW 4)REFUSED | E73: =LEN(D73) -> 170 | F73: Single Choice | G73: NA | H73: NA | I73: Form Type - Buttons | J73: 1-4 = income_third_comp OR optional question | K73: NA | L73: if income_third_ls_check = 1-4, go to [income_third_comp OR optional question] | O73: =1 -> 1 | R73: yes | V73: 8 | W73: =IF(V73="","",V73*O73) -> 8 | X73: =IF(R73="yes",W73,"") -> 8
B74: income_third_fish_check | C74: income_third_fish_check | D74: Are the fish and/or fish products that you sell also captured or harvested by you or anyone in your household? [OPERATOR: SINGLE RESPONSE.] 1)YES 2)NO 3)DON'T KNOW 4)REFUSED | E74: =LEN(D74) -> 176 | F74: Single Choice | G74: NA | H74: NA | I74: Form Type - Buttons | J74: 1-4 = income_third_comp OR optional question | K74: NA | L74: if income_third_fish_check = 1-4, go to [income_third_comp OR optional question] | O74: =1 -> 1 | R74: yes | V74: 8 | W74: =IF(V74="","",V74*O74) -> 8 | X74: =IF(R74="yes",W74,"") -> 8
B75: o_income_third_selfemployed | D75: What type of self-employment / liberal profession? [OPERATOR: SINGLE RESPONSE.] 1)Liberal profession [doctor/architect/layer...] 2)Petty trade/selling on streets [own business/self or with family] 3)Small trade [own business/<5 employees] 4)Medium/large trade [own business/>=5 employees] 5)Other 6)DON'T KNOW 7)REFUSED | E75: =LEN(D75) -> 321 | F75: Single Choice | O75: =1 -> 1 | W75: =IF(V75="","",V75*O75) | X75: =IF(R75="yes",W75,"")
B76: o_wage_third_amount | D76: What was the typical wage for wage labourers per person per day in the past one month (30 days)? [OPERATOR: RECORD NUMBER GIVEN. ENTER 8888888 FOR DON'T KNOW & 9999999 FOR REFUSED.] | F76: range
O77: =1 -> 1 | W77: =IF(V77="","",V77*O77) | X77: =IF(R77="yes",W77,"")
A78: =#REF!+1 -> #REF! | B78: income_third_comp | C78: income_third_comp | D78: Has your household's income from {income_third} changed in the last 3 months compared to the same period of a normal year? [OPERATOR: SINGLE RESPONSE.] 1)A lot more [increased by more than 50%] 2)Slightly more 3)Same 4)Slightly less 5)A lot less [less than half as much] 6)DON'T KNOW 7)REFUSED | E78: =LEN(D78) -> 295 | F78: Single Choice | G78: NA | H78: NA | I78: Form Type - Buttons | J78: 1-7= shock | K78: NA | L78: if income_third_comp = 1-7, go to shock | O78: =1 -> 1 | R78: yes | V78: 15.876503 | W78: =IF(V78="","",V78*O78) -> 15.876503 | X78: =IF(R78="yes",W78,"") -> 15.876503
B80: o_Income_total_amount | D80: How much was the household's total income during the last four weeks [one month]? [OPERATOR: RECORD TOTAL INCOME FOR THE LAST FOUR WEEKS. ENTER 8888888 FOR DON'T KNOW & 9999999 FOR REFUSED] | F80: Range | O80: =1 -> 1 | W80: =IF(V80="","",V80*O80) | X80: =IF(R80="yes",W80,"")
B81: o_Income_total_amount_conf | D81: Can you confirm the amount of income you just stated is correct? [OPERATOR: IF THE TOTAL AMOUNT EARNED OVER THE PAST 1 MONTH IS INDEED OVER 350000 or LESS THAN 25,000, CLICK ON CONTINUE. OTHERWISE, GO BACK AND CHANGE THE AMOUNT ENTERED.] 1)CONTINUE | F81: Single Choice
B82: o_Income_total_comp | D82: Thinking about your household’s total income in the last one month, how has it changed compared to the same period one year ago? [OPERATOR: SINGLE RESPONSE] 1)A lot more [increased by more than 50%] 2)More 3)Same 4)Less 5)A lot less [less than half as much] 6)DON'T KNOW 7)REFUSED | F82: Single Choice
B83: o_HHExpTotal30d | D83: How much was your family’s total expenditure in the last 30 days (in MMK)? [OPERATOR: THE RESPONDENT MENTIONED THAT THEIR TOTAL HOUSEHOLD INCOME IS {Income_total_amount}. PROBE IF THE TOTAL EXPENDITURE IS MORE THAN THE TOTAL HOUSEHOLD INCOME TO ENSURE AMOUNTS ARE CORRECT. RECORD THE AMOUNT GIVEN. ENTER 8888888 FOR DON'T KNOW & 9999999 FOR REFUSED] | F83: Range
B84: o_ExpenseFood30d | D84: What percentage of your household's expenditure did you spend on food in the last 30 days? [OPERATOR: SINGLE RESPONSE] 1)0%-10% 2)11%-20% 3)21%-30% 4)31%- 40% 5)41 % - 50% 6)51% - 60% 7)61%-70% 8)71%-80% 9)81%-90% 10)91%-100% 11)DON'T KNOW 12)REFUSED | F84: Single Choice
B85: HHDebt_yn | D85: Do you or someone in your household currently have any debt that was incurred in the last one year? [OPERATOR: SINGLE RESPONSE] 1)YES 2)NO 3)DON'T KNOW 4)REFUSED | F85: Single Choice
B86: HHDebt_BorrowFrom | D86: From whom have you mainly borrowed this money (or contracted this debt) in the past year? [OPERATOR: SINGLE RESPONSE] 1)Relatives [excluding remittances] 2)Relatives living outside the country 3)Traders/shopkeepers 4)Bank/Credit institution/Government/Micro-credit project 5)Money lender 6)Landlord [more than 1 month behind in rent] 7)Informal savings group 8)Employer 9)Other | F86: Single Choice
B87: HHDebt_more | D87: Given your current situation, do you expect to need to borrow additional money in the coming 6 months? [OPERATOR: SINGLE RESPONSE] 1)YES 2)NO 3)DON'T KNOW 4)REFUSED | F87: Single Choice
A88: =#REF!+1 -> #REF! | B88: shock | C88: shock_ 1) shock_noshock 2) shock_sicknessordeathofhh 3) shock_lostemplorwork 4) shock_otherintrahhshock 5) shock_higherfoodprices 6) shock_higherfuelprices 7) shock_mvtrestrict 8) shock_othereconomicshock 9) shock_pestoutbreak 10) shock_plantdisease 11) shock_animaldisease 12) shock_napasture 13) shock_othercropandlivests 14) shock_coldtemporhail 15) shock_flood 16) shock_hurricane 17) shock_drought 18) shock_earthquake 19) shock_landslides 20) shock_firenatural 21) shock_othernathazard 22) shock_violenceinsecconf 23) shock_theftofprodassets 24) shock_firemanmade 25) shock_othermanmadehazard 26) shock_dk 27) shock_ref | D88: Has your household or community faced any particular disaster or crisis affecting your household's ability to raise an income and/or to produce food for self consumption in the last 3 months, and if so, which one[s]? [OPERATOR: SELECT RELEVANT SHOCKS EXPERIENCED BY THE HOUSEHOLD. MULTIPLE RESPONSES POSSIBLE. REFER TO ECONOMIC SHOCKS, CROP AND LIVESTOCK SHOCKS, INTRA-HOUSEHOLD SHOCK, NATURAL HAZARDS AND HUMAN-INDUCED HAZARDS.] 1)No shock 2)Sickness or accident or death of household member[s] [sickness of breadwinner / unusually high medical expenditure / funeral expenses / death of breadwinner] 3)Lost employment or working opportunities [not due to illness/accident] 4)Other intra-household shock 5)Unusually high food prices 6)Unusually high fuel prices or transport prices 7)Population movement restrictions [e.g. due to epidemic or infrastructure damage] 8)Other economic shock 9)Pest outbreak 10)Plant disease 11)Animal disease [affecting many animals] or death 12)Lack of physical access to pasture 13)Other crop and livestock shock 14)Cold temperatures or hail 15)Flood / riverbank erosion 16)Hurricane / cyclone / tornado 17)Drought / heat stress 18)Earthquake 19)Landslides 20)Fire from natural disaster 21)Other natural hazard 22)Violence and insecurity / conflict 23)Theft of production assets [land / livestock / tools / etc] 24)Fire from human-induced disaster 25)Other human-induced hazard 26)DON'T KNOW 27)REFUSED | E88: =LEN(D88) -> 1440 | F88: Select All That Apply | G88: NA | H88: NA | I88: Form Type - Checklist 1,26,27 = IsNone | J88: 1-27 = [crp_intro or optional question] | K88: 1)shock_noshock 2)shock_sicknessordeathofhh 3)shock_lostemplorwork 4)shock_otherintrahhshock 5)shock_higherfoodprices 6)shock_higherfuelprices 7)shock_mvtrestrict 8)shock_othereconomicshock 9)shock_pestoutbreak 10)shock_plantdisease 11)shock_animaldisease 12)shock_napasture 13)shock_othercropandlivests 14)shock_coldtemporhail 15)shock_flood 16)shock_hurricane 17)shock_drought 18)shock_earthquake 19)shock_landslides 20)shock_firenatural 21)shock_othernathazard 22)shock_violenceinsecconf 23)shock_theftofprodassets 24)shock_firemanmade 25)shock_othermanmadehazard 26)shock_dk 27)shock_ref | L88: if shock = 1-27, go to [crp_intro or optional question] | O88: =1 -> 1 | R88: yes | V88: 37.85363 | W88: =IF(V88="","",V88*O88) -> 37.85363 | X88: =IF(R88="yes",W88,"") -> 37.85363
O89: =1 -> 1 | W89: =IF(V89="","",V89*O89) | X89: =IF(R89="yes",W89,"")
A90: D. CROP PRODUCTION | W90: =IF(V90="","",V90*O90) | X90: =IF(R90="yes",W90,"")
A91: =#REF!+1 -> #REF! | B91: crp_intro | C91: crp_intro | D91: We will now ask you some questions about crop production which apply to you and anyone in your household that is involved in crop production or sales. All questions refer to the crops grown during monsoon season. 1)CONTINUE | E91: =LEN(D91) -> 224 | F91: Single Choice | G91: NA | H91: Send if "hh_agricactivity" "Equals" "Yes - crop production" Or "hh_agricactivity" "Equals" "Yes - both crop and livestock production" Or "income_main_crop_check" "Equals" "YES" Or "income_sec_crop_check" "Equals" "YES" Or "income_third_crop_check" "Equals" "YES", if not satisfied go to "crp_salesmain" | I91: Form Type - Buttons | J91: 1 = crp_landsize_num | K91: NA | L91: If hh_agricactivity = "Yes - crop production" or "Yes - both crop and livestock production" or if they reported production and sales of crops in one of the three main income sources and confirmed that they are involved in production, then this section will be asked to respondents. Otherwise, skip to crp_salesmain. Next question is crp_landsize_num | O91: ='Additional information'!$D$17 -> 0.91 | R91: yes | V91: 7.3040729 | W91: =IF(V91="","",V91*O91) -> 6.6467063 | X91: =IF(R91="yes",W91,"") -> 6.6467063
O92: ='Additional information'!$D$17 -> 0.91 | W92: =IF(V92="","",V92*O92) | X92: =IF(R92="yes",W92,"")
B93: crp_landsize_num | C93: crp_landsize_num | D93: What is the total size of the land you can cultivate? [OPERATOR: RECORD THE TOTAL LAND SIZE PROVIDED BY THE RESPONDENT. WRITE 8888888 FOR DON'T KNOW AND 9999999 FOR REFUSED. MEASUREMENT UNIT WILL BE SPECIFIED IN THE FOLLOWING QUESTION.] | E93: =LEN(D93) -> 237 | F93: Range | G93: NA | H93: NA | I93: Form Type - TextBox | J93: 0-1000000 = crp_landsize_unit 8888888-8888888 = crp_main 9999999-9999999 = crp_main | K93: NA | L93: For any response, go to crp_landsize_unit. Range is between 0 and 1000000. For "Don't know" and "Refused", go to crp_main. | O93: ='Additional information'!$D$17 -> 0.91 | R93: yes | V93: 23.939905 | W93: =IF(V93="","",V93*O93) -> 21.785314 | X93: =IF(R93="yes",W93,"") -> 21.785314
B94: crp_landsize_unit | C94: crp_landsize_unit | D94: Unit of measurement for land size: [OPERATOR: DO NOT READ. SINGLE RESPONSE.] 1)Acres 2)Hectares 3)Square meters 4)Square feet 5)Arces, square meter | E94: =LEN(D94) -> 152 | F94: Single Choice | G94: NA | H94: NA | I94: Form Type - Buttons | J94: 1-5 = crp_main | K94: NA | L94: if crp_landsize_unit = 1-5, go to crp_main | O94: ='Additional information'!$D$17 -> 0.91 | R94: yes | V94: 2.2494626 | W94: =IF(V94="","",V94*O94) -> 2.047011 | X94: =IF(R94="yes",W94,"") -> 2.047011
O95: ='Additional information'!$D$17 -> 0.91 | W95: =IF(V95="","",V95*O95) | X95: =IF(R95="yes",W95,"")
A96: =A91+1 -> #REF! | B96: crp_main | C96: crp_main | D96: What has been the main crop that your household has grown for food and income generation in monsoon season, if any? [OPERATOR: SINGLE RESPONSE. "NO CROP PRODUCTION" IS IN LAST OPTIONS AT THE END.] 1)Rice 2)Wheat 3)Maize 4)Potatoe 5)Beans 6)Onions 7)Groundnut/peanut 8)Sesame 9)Sugarcane 10)Tobacco 11)Millet 12)Sorghum 13)Barley 14)Other Cereal 15)Cassava 16)Sweet Potatoes 17)Yams 18)Carrots 19)Cocoyam 20)Other tubers 21)Lentils 22)Peas 23)Soybeans 24)Chickpeas 25)Fava beans 26)Broad beans 27)Other pulses 28)Cabbage 29)Cauliflower 30)Lettuce 31)Spinach-Amaranth 32)Cassava leaves 33)Potatoe leaves 34)Moringa 35)Sorrel Hibiscus / Rosselle 36)Green salad herbs [thyme, parsley, mint, rocca, other] 37)Other leafy vegetables 38)Tomatoes 39)Green peas 40)Fava beans green 41)Cucumber 42)Pumpkin 43)Eggplant/aubergine 44)Zucchini 45)Okra 46)Bell pepper 47)Haricot 48)Other non leafy vegs 49)Orange 50)Lemon 51)Grapefruit 52)Mandarins/clementines 53)Other citrus fruit 54)Sweet Banana 55)Figs 56)Grapes 57)Olives 58)Apple 59)Apricot 60)Cherries 61)Peach/nectarine 62)Strawberries 63)Melon [Cantaloupe] 64)Plantains 65)Papaya 66)Mango 67)Guava 68)Pineapple 69)Avocado 70)Water Melon 71)Dates 72)Other fruit 73)Coconuts 74)Cashew Nut 75)Kola Nut 76)Bambara nut 77)Almond 78)Walnut 79)Other nuts 80)Cocoa 81)Coffee 82)Tea 83)Sunflower 84)Other food cash crop 85)Cotton 86)Rubber 87)Jute 88)Fodder 89)Qat 90)Other non-food cash crop 91)No crop production 92)DON'T KNOW 93)REFUSED | E96: =LEN(D96) -> 1479 | F96: Single Choice | G96: NA | H96: NA | I96: Form Type - Dropdown IsDemographic | J96: 1-90 = crp_irrig_source 91 = crp_main_check 92-93 = crp_salesmain | K96: 1)1.1 2)1.2 3)1.5 4)2.2 5)3.1 6)5.8 7)8.2 8)8.5 9)9.4 10)10.5 11)1.3 12)1.4 13)1.6 14)1.99 15)2.1 16)2.3 17)2.4 18)2.5 19)2.6 20)2.99 21)3.2 22)3.3 23)3.4 24)3.5 25)3.6 26)3.7 27)3.99 28)4.1 29)4.101 30)4.2 31)4.3 32)4.4 33)4.5 34)4.6 35)4.7 36)4.9 37)4.99 38)5.1 39)5.101 40)5.11 41)5.2 42)5.3 43)5.4 44)5.5 45)5.6 46)5.7 47)5.9 48)5.99 49)6.1 50)6.2 51)6.3 52)6.4 53)6.99 54)7.1 55)7.101 56)7.11 57)7.12 58)7.13 59)7.14 60)7.15 61)7.16 62)7.17 63)7.18 64)7.2 65)7.3 66)7.4 67)7.5 68)7.6 69)7.7 70)7.8 71)7.9 72)7.99 73)8.1 74)8.3 75)8.4 76)8.6 77)8.7 78)8.8 79)8.99 80)9.1 81)9.2 82)9.3 83)9.5 84)9.99 85)10.1 86)10.2 87)10.3 88)10.4 89)10.6 90)10.99 91)777 92)888 93)999 | L96: if crp_main = any type of crop, go to crp_irrig_source; if crp_main = "No crop production", go to crp_main_check if crp_main = "Don't know" or "Refused", go to crp_salesmain | O96: ='Additional information'!$D$17 -> 0.91 | R96: yes | V96: 23.440117 | W96: =IF(V96="","",V96*O96) -> 21.330506 | X96: =IF(R96="yes",W96,"") -> 21.330506
B97: crp_main_check | C97: crp_main_check | D97: Why did you not produce any crops in monsoon season? [OPERATOR: SINGLE RESPONSE.] 1)Don’t usually produce during this season 2)Wasn't able to produce [e.g. due to difficulties] | E97: =LEN(D97) -> 179 | F97: Single Choice | G97: NA | H97: NA | I97: Form Type - Buttons | J97: 1 = crp_salesmain 2 = crp_proddif | K97: NA | L97: if crp_main_check = 1, go to crp_salesmain if crp_main_check = 2, go to crp_proddif | O97: ='Additional information'!$D$17 -> 0.91 | R97: yes | V97: 7.7659574 | W97: =IF(V97="","",V97*O97) -> 7.0670212 | X97: =IF(R97="yes",W97,"") -> 7.0670212
B98: o_mocha:damage | D98: Do the damages from cyclone Mocha have an impact on the area already planted or what you will be able to plant for {crp_main}? [OPERATOR: SINGLE RESPONSE.] 1)Yes - a lot of impact [more than 50% of the area planted] 2)Yes - a slight impact 3)No - there was no impact on the area planted 4)DON'T KNOW | E98: =LEN(D98) -> 302 | N98: IF o_cyclaffected = YES | O98: ='Additional information'!$D$17 -> 0.91 | W98: =IF(V98="","",V98*O98) | X98: =IF(R98="yes",W98,"")
B99: O_crp_assets | D99: Have you lost the majority of the following tools/assets? [OPERATOR: MULTIPLE RESPONSE] 1)Hand tools 2)Agricultural machines 3)Seeds stock 4)Inputs [fertilizer and pesticides] stock 5)Irrigation tools [pumps/ parts…] 6)Farmland due to saltwater intrusion/ debris/ sediments… 7)Drying equipment 8)Store equipment [plastic bags/ tarpaulin/ plastic sheets…] 9)Other 10)No - the majority of tools/assets were not lost 11)DON’T KNOW 12)REFUSED | E99: =LEN(D99) -> 440 | N99: IF o_cyclaffected = YES
A101: =A96+1 -> #REF! | B101: crp_irrig_source | C101: crp_irrig_source | D101: Where do you normally and mainly obtain water for the production of {crp_main}? [OPERATOR: SINGLE RESPONSE.] 1)Rainfed 2)Groundwater 3)Natural surface water [river / lake / stream / pond / etc.] 4)Constructed water point [canal / dam / etc.] 5)Public water supply system [e.g. tap water] 6)Other [specify] 7)DON'T KNOW 8)REFUSED | E101: =LEN(D101) -> 331 | F101: Open Ended - Single Choice | G101: NA | H101: NA | I101: Form Type - RadioList | J101: 1-8 = crp_area_change OR optional question | K101: NA | L101: if crp_irrig_source = 1-8, go to [crp_area_change or optional question] | O101: ='Additional information'!$D$17 -> 0.91 | R101: yes | V101: 16.481756 | W101: =IF(V101="","",V101*O101) -> 14.998398 | X101: =IF(R101="yes",W101,"") -> 14.998398
B102: o_irr_dam | D102: Was the irrigation infrastructure damaged? [OPERATOR: SINGLE RESPONSE.] 1)YES 2)NO 3)DON’T KNOW 4)REFUSED | N102: IF o_cyclaffected = YES | O102: ='Additional information'!$D$17 -> 0.91 | W102: =IF(V102="","",V102*O102) | X102: =IF(R102="yes",W102,"")
O103: ='Additional information'!$D$17 -> 0.91 | W103: =IF(V103="","",V103*O103) | X103: =IF(R103="yes",W103,"")
A104: =#REF!+1 -> #REF! | B104: crp_area_change | C104: crp_area_change | D104: How did the area planted for {crp_main} from monsoon season compare to a normal year? [OPERATOR: SINGLE RESPONSE.] 1)A lot more [increased by more than 50%] 2)Slightly more 3)Same 4)Slightly less 5)A lot less [less than half as much] 6)DON'T KNOW 7)REFUSED | E104: =LEN(D104) -> 258 | F104: Single Choice | G104: NA | H104: NA | I104: Form Type - Buttons | J104: 1-7 = crp_harv_change | K104: NA | L104: if crp_area_change = 1-7, go to crp_harv_change | O104: ='Additional information'!$D$17 -> 0.91 | R104: yes | V104: 20.308681 | W104: =IF(V104="","",V104*O104) -> 18.4809 | X104: =IF(R104="yes",W104,"") -> 18.4809
O105: ='Additional information'!$D$17 -> 0.91 | W105: =IF(V105="","",V105*O105) | X105: =IF(R105="yes",W105,"")
A106: =A104+1 -> #REF! | B106: crp_harv_change | C106: crp_harv_change | D106: How does the expected harvest of {crp_main} in the monsoon season compare to a normal year? [OPERATOR: SINGLE RESPONSE.] 1)A lot more [increased by more than 50%] 2)Slightly more 3)Same 4)Slightly less 5)A lot less [less than half as much] 6)DON'T KNOW 7)REFUSED | E106: =LEN(D106) -> 265 | F106: Single Choice | G106: NA | H106: NA | I106: Form Type - Buttons | J106: 1-7 = crp_proddif OR crp_harv_vol | K106: NA | L106: if crp_harv_change = 1-7, go to [crp_proddif or crp_harv_vol] | O106: ='Additional information'!$D$17 -> 0.91 | R106: yes | V106: 15.448612 | W106: =IF(V106="","",V106*O106) -> 14.058237 | X106: =IF(R106="yes",W106,"") -> 14.058237
...

Sheet New Durations
A1: question | B1: duration | C1: responded % | D1: weighted time
A2: introduction | B2: 50.82254 | C2: 1 | D2: 50.82254
A3: agree | B3: 3.4964738 | C3: 0.79698741 | D3: 2.7866456
A4: resp_age | B4: 13.753073 | C4: 1 | D4: 13.753073
A5: resp_gender | B5: 2.1173561 | C5: 1 | D5: 2.1173561
A6: quotareached | B6: 2.28425 | C6: 0.79698741 | D6: 1.8205185
A7: hh_agricactivity | B7: 31.372377 | C7: 1 | D7: 31.372377
A8: hh_milieu | B8: 7.9225454 | C8: 0.15190348 | D8: 1.2034622
A9: hh_gender | B9: 10.085732 | C9: 1 | D9: 10.085732
A10: hh_education | B10: 12.894034 | C10: 1 | D10: 12.894034
A11: hh_wealth_water | B11: 15.265829 | C11: 0.63796463 | D11: 9.739059
A12: hh_wealth_toilet | B12: 15.123718 | C12: 0.59180156 | D12: 8.95024
A13: hh_wealthwall | B13: 12.821411 | C13: 0.15190348 | D13: 1.9476169
... A164: adm1_name | B164: 10.743817 | C164: 0.20301259 | D164: 2.1811302
A165: adm2_name | C165: 0 | D165: 0
A166: covid | B166: 56.471024 | C166: 0.20301259 | D166: 11.464329
A167: crp_landright | B167: 31 | C167: 0.0040467626 | D167: 0.12544964
A168: crp_seed | B168: 30.833334 | C168: 0.0040467626 | D168: 0.12477518
A169: crp_proddif | B169: 16.882986 | C169: 0.11848022 | D169: 2.0002998
A170: crp_salesdif | B170: 16.82699 | C170: 0.086630695 | D170: 1.4577339
A171: crp_saledif_2 | B171: 39.486874 | C171: 0.03139988 | D171: 1.2398831
A172: ls_proddif | B172: 15.938099 | C172: 0.10169365 | D172: 1.6208034
A173: ls_salesdif | B173: 13.330855 | C173: 0.060476619 | D173: 0.80620506
A174: ls_proc | B174: 16.437651 | C174: 0.0625 | D174: 1.0273532
A175: ls_proc_fac_state | B175: 8.666667 | C175: 0.00067446043 | D175: 0.005845324
A176: fish_proddif | B176: 12.523809 | C176: 0.001573741 | D176: 0.019709232
A177: cs_spentsavings | B177: 22.220184 | C177: 0.0081684652 | D177: 0.1815048
... A193: ls_proddif_2_covid19 | B193: 3.3438249 | C193: 1 | D193: 3.3438249

Sheet Crop list
C3: Select top 10 crops | D3: GeoPoll code | E3: Dataset code | F3: Label (EN)
C4: x | D4: {=_xlfn.SEQUENCE(90,1,1,1)} -> 1 | E4: 1.1 | F4: Rice
C5: x | D5: 2 | E5: 1.2 | F5: Wheat
D6: 3 | E6: 1.3 | F6: Millet
D7: 4 | E7: 1.4 | F7: Sorghum
C8: x | D8: 5 | E8: 1.5 | F8: Maize
D9: 6 | E9: 1.6 | F9: Barley
D10: 7 | E10: 1.99 | F10: Other Cereal
D11: 8 | E11: 2.1 | F11: Cassava
C12: x | D12: 9 | E12: 2.2 | F12: Potatoe
D13: 10 | E13: 2.3 | F13: Sweet Potatoes
D14: 11 | E14: 2.4 | F14: Yams
D15: 12 | E15: 2.5 | F15: Carrots
D16: 13 | E16: 2.6 | F16: Cocoyam
D17: 14 | E17: 2.99 | F17: Other tubers
C18: x | D18: 15 | E18: 3.1 | F18: Beans
D19: 16 | E19: 3.2 | F19: Lentils
D20: 17 | E20: 3.3 | F20: Peas
D21: 18 | E21: 3.4 | F21: Soybeans
D22: 19 | E22: 3.5 | F22: Chickpeas
D23: 20 | E23: 3.6 | F23: Fava beans
D24: 21 | E24: 3.7 | F24: Broad beans
D25: 22 | E25: 3.99 | F25: Other pulses
D26: 23 | E26: 4.1 | F26: Cabbage
D27: 24 | E27: 4.2 | F27: Lettuce
D28: 25 | E28: 4.3 | F28: Spinach-Amaranth
D29: 26 | E29: 4.4 | F29: Cassava leaves
D30: 27 | E30: 4.5 | F30: Potatoe leaves
... D42: 39 | E42: 5.7 | F42: Bell pepper
C43: x | D43: 40 | E43: 5.8 | F43: Onions
D44: 41 | E44: 5.9 | F44: Haricot
D45: 42 | E45: 5.101 | F45: Green peas
D46: 43 | E46: 5.11 | F46: Fava beans green
D47: 44 | E47: 5.99 | F47: Other non leafy vegs
D48: 45 | E48: 6.1 | F48: Orange
D49: 46 | E49: 6.2 | F49: Lemon
D50: 47 | E50: 6.3 | F50: Grapefruit
D51: 48 | E51: 6.4 | F51: Mandarins/clementines
D52: 49 | E52: 6.99 | F52: Other citrus fruit
D53: 50 | E53: 7.1 | F53: Sweet Banana
D54: 51 | E54: 7.2 | F54: Plantains
D55: 52 | E55: 7.3 | F55: Papaya
... D72: 69 | E72: 8.1 | F72: Coconuts
C73: x | D73: 70 | E73: 8.2 | F73: Groundnut/peanut
D74: 71 | E74: 8.3 | F74: Cashew Nut
D75: 72 | E75: 8.4 | F75: Kola Nut
C76: x | D76: 73 | E76: 8.5 | F76: Sesame
D77: 74 | E77: 8.6 | F77: Bambara nut
D78: 75 | E78: 8.7 | F78: Almond
D79: 76 | E79: 8.8 | F79: Walnut
D80: 77 | E80: 8.99 | F80: Other nuts
D81: 78 | E81: 9.1 | F81: Cocoa
D82: 79 | E82: 9.2 | F82: Coffee
D83: 80 | E83: 9.3 | F83: Tea
C84: x | D84: 81 | E84: 9.4 | F84: Sugarcane
D85: 82 | E85: 9.5 | F85: Sunflower
D86: 83 | E86: 9.99 | F86: Other food cash crop
D87: 84 | E87: 10.1 | F87: Cotton
D88: 85 | E88: 10.2 | F88: Rubber
D89: 86 | E89: 10.3 | F89: Jute
D90: 87 | E90: 10.4 | F90: Fodder
C91: x | D91: 88 | E91: 10.5 | F91: Tobacco
D92: 89 | E92: 10.6 | F92: Qat
D93: 90 | E93: 10.99 | F93: Other non-food cash crop

Sheet Additional information
C2: Original | D2: Replacement | E2: Comment | F2: Examples
B3: FOR CORE QUESTIONS . (Mandatory to fill out) . | C3: ADMIN1 | D3: State/Region | E3: The first subdivision of the country, after national level; region; province; governorate; etc. | F3: region
C4: ADMIN2 | D4: Township | E4: The second subdivision of the country; district; municipality; LGA; etc. | F4: district
C5: reference year | D5: a normal year | E5: Comparison questions will need need a reference year. Select whether you want to use "last year" or "a normal year" as a baseline. A "normal year" should refers to an average year from the past 5 years - make sure to train the enumerators accordingly. | F5: a normal year
C6: season | D6: monsoon season | E6: Name the crop season(s) of interest if there are several cropping seasons in the country (e.g. Meher and Belg in Ethiopia, rainy season / flood-recession cropping / irrigated dry season in the Sahel). You can refer to the “last season” or “ongoing season". | F6: wet season
C7: season phase | D7: Early growing | E7: Indicate the phase of the season at the time of data collection. If the harvest from the season has not yet occurred, the question on crop harvest (crp_harv_change) will include the word “expected” (where #expected or nothing# is located). If the harvest has occured, "expected" will not be inserted in the question. | F7: Harvesting
C8: local measurement unit | D8: Arces, square meter | E8: Specify the local measurement unit for land size, other than acres, hectares, square meters and square feet. If no other unit of measurement is needed, keep this cell blank. | F8: Jeribs
C9: local measurement unit conversion | E9: Include the conversion of the local measurement unit to hectares. In other words, how many local measurement units are in 1 ha. | F9: 0.2
B10: FOR OPTIONAL QUESTIONS . (Fill out if applicable) . | C10: currency | D10: MMK | E10: The name of the main currency used nationally; USD; Naira; Rial; Pesos; etc. | F10: Naira
C11: MIN AMOUNT | D11: 100 | E11: The minimum amount for an income source should be set at 0 or any value below which it is not possible to do a transaction. For example, the smallest coin/banknote in a currency can be 1000, in which case you would set the minimum at 1000. Provide this input in the same currency as specified above. Only digits should be inputted. | F11: 5
C12: MAX AMOUNT | D12: 5000000 | E12: Set the maximum amount for an income source over 3 months. Enumerators will not be able to input values above this amount in questions related to income amounts. Using previous representative surveys for this population, you can estimate this amount by using the mean income plus five (5) standard deviations, unless the country has high inflation. In the latter case, set the maximum value based on your country context (higher than the proposed approach). Provide this input in the same currency as specified above. Only digits should be inputted. | F12: 5000000
C13: THRESHOLD | E13: The threshold salary should be calculated to flag outliers (responses that look suspiciously high). Using previous representative surveys for this population, a good estimate is the average plus three (3) standard deviations, which should give the threshold for the 3 or 4% highest income values. Provide this input in the same currency as specified above. Only digits should be inputted. | F13: 1200000
C14: local vegetables | D14: carrot, red pepper, pumpkin, orange sweet potatoes, spinach | E14: Input some common local vegetables [to be used as examples in the food consumption score indicator]. | F14: eggplants, zucchini, cauliflower
C15: local fruits | D15: banana, apple, mango, papaya | E15: Input some common local fruits [to be used as examples in the food consumption score indicator]. | F15: apples, bananas, oranges
B17: FILL OUT FOR QUESTIONNAIRE DURATION ESTIMATION . | C17: Expected percentage of respondents cultivating crops | D17: 0.91 | E17: If the survey is representative and has no quotas, write the proportion of rural households cultivating crops at country level, or if the survey follows a previous round with identical sample design, just report the percentage from the previous round. If you are using quotas, calculate the ratio of the quota over the minimum sample size at the level where the quota is implemented (so if you have a minimum sample size per strata of 110 with a quota of 100 crop producers, then it's 100/110 = 91% (the maximum you should write is 100%). | F17: 0.91
C18: Expected percentage of respondents raising livestock | D18: 0.91 | E18: If the survey is representative and has no quotas, write the proportion of rural households raising livestock at country level, or if the survey follows a previous round with identical sample design, just report the percentage from the previous round. If you are using quotas, calculate the ratio of the quota over the minimum sample size at the level where the quota is implemented (so if you have a minimum sample size of 110 but a quota of 100 livestock producers, then it's 100/110 = 91% (the maximum you should write is 100%) | F18: 0.91
C19: Expected percentage of respondents involved in fishery | D19: 0.05 | E19: If the survey is representative and has no quotas, write the proportion of rural households involved in fisheries or aquaculture, otherwise if you are using quotas, calculate the ratio of the quota over the sample size at the level where the quota is implemented. (so if you haven't set a quota, and you expect to have a representative proportion of fishermen, just write the percentage of fishermen in the population you are targeting, in the example to the right, 5%) | F19: 0.05

Sheet Admin 3 info
A1: adm3_name | B1: adm3_name_local | C1: adm3_pcode | D1: adm2_name | E1: adm2_pcode | F1: adm1_name | G1: adm1_pcode | H1: adm0_name | I1: adm0_ISO3
A2: Muse | B2: မူဆယ် | C2: MMR015009 | D2: Muse | E2: MMR015D002 | F2: Shan | G2: MMR222 | H2: Myanmar | I2: MMR
A3: Kunlong | B3: ကွမ်းလုံ | C3: MMR015020 | D3: Lashio | E3: MMR015D001 | F3: Shan | G3: MMR222 | H3: Myanmar | I3: MMR
A4: Hseni | B4: သိန္နီ | C4: MMR015002 | D4: Lashio | E4: MMR015D001 | F4: Shan | G4: MMR222 | H4: Myanmar | I4: MMR
A5: Mongkaing | B5: မိုင်းကိုင် | C5: MMR014016 | D5: Loilen | E5: MMR014D002 | F5: Shan | G5: MMR222 | H5: Myanmar | I5: MMR
A6: Laihka | B6: လဲချား | C6: MMR014012 | D6: Loilen | E6: MMR014D002 | F6: Shan | G6: MMR222 | H6: Myanmar | I6: MMR
A7: Seikphyu | B7: ဆိပ်ဖြူ | C7: MMR009022 | D7: Pakokku | E7: MMR009D004 | F7: Magway | G7: MMR009 | H7: Myanmar | I7: MMR
A8: Kale | B8: ကလေး | C8: MMR005027 | D8: Kale | E8: MMR005D005 | F8: Sagaing | G8: MMR005 | H8: Myanmar | I8: MMR
A9: Minbu | B9: မင်းဘူး | C9: MMR009007 | D9: Minbu | E9: MMR009D002 | F9: Magway | G9: MMR009 | H9: Myanmar | I9: MMR
A10: Wundwin | B10: ဝမ်းတွင်း | C10: MMR010031 | D10: Meiktila | E10: MMR010D007 | F10: Mandalay | G10: MMR010 | H10: Myanmar | I10: MMR
A11: Kyaukpadaung | B11: ကျောက်ပန်းတောင်း | C11: MMR010020 | D11: Nyaung-U | E11: MMR010D005 | F11: Mandalay | G11: MMR010 | H11: Myanmar | I11: MMR
A12: Taze | B12: တန့်ဆည် | C12: MMR005011 | D12: Shwebo | E12: MMR005D002 | F12: Sagaing | G12: MMR005 | H12: Myanmar | I12: MMR
... A331: Ramree | B331: ရမ်းဗြဲ | C331: MMR012013 | D331: Kyaukpyu | E331: MMR012D003 | F331: Rakhine | G331: MMR012 | H331: Myanmar | I331: MMR
