Workbook

Sheet survey
A1: type | B1: name | C1: label::English (en) | D1: label::Spanish (es) | E1: label:: | F1: hint::English (en) | G1: hint::Spanish (es) | H1: hint:: | I1: required | J1: appearance | K1: constraint | L1: constraint_message | M1: relevant | N1: choice_filter | O1: parameters | P1: calculation | U1: Mandatory | W1: New question duration (sec) | X1: Estimated percentage of repondents | Y1: Weighted time | Z1: Weighted time for core vars
A2: start | B2: start | Y2: =IF(W2<>"",W2*X2,"") | Z2: =IF(AND(W2<>"",U2="yes"),W2*X2,"")
A3: end | B3: end | Y3: =IF(W3<>"",W3*X3,"") | Z3: =IF(AND(W3<>"",U3="yes"),W3*X3,"")
A4: today | B4: today | Y4: =IF(W4<>"",W4*X4,"") | Z4: =IF(AND(W4<>"",U4="yes"),W4*X4,"")
A5: deviceid | B5: deviceid | Y5: =IF(W5<>"",W5*X5,"") | Z5: =IF(AND(W5<>"",U5="yes"),W5*X5,"")
A6: audit | B6: audit
A7: calculate | B7: audio_random | P7: once(random())
A8: background-audio | B8: background-audio | M8: ${audio_random}<=0.02 | O8: quality=low
A9: select_one enumteam | B9: enum_team | C9: Enumerator team number or code | D9: Número o código del equipo de encuestadores
A10: select_one enumerator | B10: enumerator | C10: Name of enumerator | D10: Nombre del encuestador | I10: true | N10: my_filter_admin=${enum_team} | U10: yes | Y10: =IF(W10<>"",W10*X10,"") | Z10: =IF(AND(W10<>"",U10="yes"),W10*X10,"")
A11: calculate | B11: enumerator_ | P11: jr:choice-name(${enumerator},'${enumerator}') | U11: yes | Y11: =IF(W11<>"",W11*X11,"") | Z11: =IF(AND(W11<>"",U11="yes"),W11*X11,"")
A13: note | B13: introduction | C13: Hello sir/ma'am, my name is ${enumerator_}. On behalf of the Food and Agriculture Organization of the United Nations (FAO), we are conducting a survey on household livelihoods and the ability to access food in your area. I would like to ask you some questions about your household. The survey usually takes 20 / 30 minutes to complete. Any information that you provide will be kept strictly confidential, only used for the purpose of the survey and will not be shown to other people. Your voluntary participation in the outcome of this interview is NOT IN ANY WAY linked to your personal chance of receiving any assistance. This is voluntary and you can choose not to answer any or all of the questions if you want. However, we hope that you will participate since your views are important. Do you have any questions? | D13: Buenos días/tardes señor/señora, mi nombre es ${encuestador_}. En nombre de la Organización de las Naciones Unidas para la Alimentación y la Agricultura (FAO), estamos realizando una encuesta sobre los medios de vida de los hogares y la capacidad de acceder a alimentos en su área. Me gustaría hacerle algunas preguntas acerca de su hogar. La encuesta normalmente toma entre 15 / 20 minutes. Toda la información provista será estrictamente guardada con confidencialidad, será utilizada únicamente para los propósitos de la encuesta y no será compartida. Su participación voluntaria en el resultado de esta encuesta, NO ESTÁ DE NINGÚN MODO vinculada a la posibilidad de recibir algún tipo de asistencia o ayuda. Esto es voluntario y puede optar por no responder alguna o todas las preguntas si así lo desea. Sin embargo, esperamos que participe ya que su opinión es muy importante. ¿Tiene alguna pregunta? | F13: [INSTRUCTIONS: ADDRESS QUESTIONS FROM RESPONDENT, IF ANY.] | G13: [ENCUESTADOR/A: RESPONDA LAS PREGUNTAS DEL ENCUESTADO, SI LAS HAY.] | I13: false | U13: no | W13: 50.82254 | Y13: =IF(W13<>"",W13*X13,"") -> 0 | Z13: =IF(AND(W13<>"",U13="yes"),W13*X13,"")
A14: select_one yesno | B14: resp_agree | C14: Are you interested in participating in this survey? | D14: ¿Está interesado en participar en esta encuesta? | I14: false | U14: yes | W14: 3.5 | X14: =1 -> 1 | Y14: =IF(W14<>"",W14*X14,"") -> 3.5 | Z14: =IF(AND(W14<>"",U14="yes"),W14*X14,"") -> 3.5
A15: note | B15: Refusal | C15: Thank you for your time, you will be removed from today's survey. | D15: Gracias por su tiempo, será descartado para la encuesta de hoy. | I15: false | M15: ${resp_agree} = '2' | U15: no | W15: 0 | X15: 1 | Y15: =IF(W15<>"",W15*X15,"") -> 0 | Z15: =IF(AND(W15<>"",U15="yes"),W15*X15,"")
Y16: =IF(W16<>"",W16*X16,"") | Z16: =IF(AND(W16<>"",U16="yes"),W16*X16,"")
A17: begin_group | B17: eligibility | C17: ELIGIBILITY CRITERIA | D17: Criterios de eligibilidad | I17: false | M17: ${resp_agree} = '1' | U17: yes | Y17: =IF(W17<>"",W17*X17,"") | Z17: =IF(AND(W17<>"",U17="yes"),W17*X17,"")
Y18: =IF(W18<>"",W18*X18,"") | Z18: =IF(AND(W18<>"",U18="yes"),W18*X18,"")
A19: text | B19: resp_firstname | C19: What is your first name? | D19: ¿Cuál es su nombre? | F19: [INSTRUCTIONS: RECORD THE RESPONDENT'S FIRST NAME. ENTER 999 FOR REFUSED] | G19: [ENCUESTADOR/A: REGISTRE EL NOMBRE DEL ENCUESTADO.ESCRIBA 999 PARA "NO RESPONDE"] | I19: true | U19: yes | W19: 10 | X19: =1 -> 1 | Y19: =IF(W19<>"",W19*X19,"") -> 10 | Z19: =IF(AND(W19<>"",U19="yes"),W19*X19,"") -> 10
A20: text | B20: resp_lastname | C20: What is your last name? | D20: ¿Cuál es su apellido? | F20: [INSTRUCTIONS: RECORD THE RESPONDENT'S LAST NAME. ENTER 999 FOR REFUSED] | G20: [ENCUESTADOR/A: REGISTRE EL APELLIDO DEL ENCUESTADO.ESCRIBA 999 PARA "NO RESPONDE"] | I20: true | U20: yes | W20: 10 | X20: =1 -> 1 | Y20: =IF(W20<>"",W20*X20,"") -> 10 | Z20: =IF(AND(W20<>"",U20="yes"),W20*X20,"") -> 10
X21: =1 -> 1 | Y21: =IF(W21<>"",W21*X21,"") | Z21: =IF(AND(W21<>"",U21="yes"),W21*X21,"")
A22: integer | B22: resp_age | C22: How old are you? | D22: ¿Qué edad tiene? | F22: [INSTRUCTIONS: RECORD AGE IN NUMBER OF YEARS. ROUND UP TO NEAREST WHOLE NUMBER. IF THE RESPONDENT GIVES BIRTH YEAR, REPEAT THE QUESTION. ENTER 888 FOR DON'T KNOW.] | G22: [ENCUESTADOR/A: REGISTRE LA EDAD EN AÑOS. REDONDEE AL NÚMERO ENTERO MÁS CERCANO. SI EL ENCUESTADO DA SU FECHA DE NACIMIENTO, VUELVA A REPETIR LA PREGUNTA. ESCRIBA 888 PARA "NO SABE"] | I22: true | K22: (. >= 18 and . <= 100) or . = 888 | U22: yes | W22: 13.753073 | X22: =1 -> 1 | Y22: =IF(W22<>"",W22*X22,"") -> 13.753073 | Z22: =IF(AND(W22<>"",U22="yes"),W22*X22,"") -> 13.753073
X23: =1 -> 1 | Y23: =IF(W23<>"",W23*X23,"") | Z23: =IF(AND(W23<>"",U23="yes"),W23*X23,"")
A24: select_one gender | B24: resp_gender | C24: What is the gender of the respondent? | D24: ¿Cuál es el género del encuestado? | F24: [INSTRUCTIONS: DO NOT ASK THIS QUESTION OUT LOUD. SELECT THE GENDER OF THE RESPONDENT.] | G24: [ENCUESTADOR/A: NO LEA LA PREGUNTA EN VOZ ALTA. SELECCIONE EL GENERO DEL ENCUESTADO.] | I24: true | U24: no | W24: 2.1173561 | X24: =1 -> 1 | Y24: =IF(W24<>"",W24*X24,"") -> 2.1173561 | Z24: =IF(AND(W24<>"",U24="yes"),W24*X24,"")
X25: =1 -> 1 | Y25: =IF(W25<>"",W25*X25,"") | Z25: =IF(AND(W25<>"",U25="yes"),W25*X25,"")
X26: =1 -> 1 | Y26: =IF(W26<>"",W26*X26,"") | Z26: =IF(AND(W26<>"",U26="yes"),W26*X26,"")
A27: select_one admin1 | B27: adm1_pcode | C27: Currently, in which Department does your household reside? | D27: Actualmente, ¿en qué Departamento reside su hogar? | F27: [HINT: HOUSEHOLD CONSISTS OF ALL MEMBERS LIVING TOGETHER, SHARING RESOURCES & EATING FROM THE SAME POT.] | G27: [PISTA: EL HOGAR ES EL ESPACIO DONDE TODOS LOS MIEMBROS VIVEN JUNTOS, COMPARTEN RECURSOS Y COMEN DE LA MISMA OLLA.] | I27: true | J27: autocomplete | U27: yes | W27: 8.8 | X27: =1 -> 1 | Y27: =IF(W27<>"",W27*X27,"") -> 8.8 | Z27: =IF(AND(W27<>"",U27="yes"),W27*X27,"") -> 8.8
A28: calculate | B28: adm1_name | P28: jr:choice-name(${adm1_pcode},'${adm1_pcode}') | U28: yes | X28: =1 -> 1 | Y28: =IF(W28<>"",W28*X28,"") | Z28: =IF(AND(W28<>"",U28="yes"),W28*X28,"")
A29: select_one admin2 | B29: adm2_pcode | C29: Currently, in which Municipality does your household reside? | D29: Actualmente, ¿en qué Municipio reside su hogar? | I29: true | J29: autocomplete | N29: my_filter_admin=${adm1_pcode} | U29: yes | W29: 10.4 | X29: =1 -> 1 | Y29: =IF(W29<>"",W29*X29,"") -> 10.4 | Z29: =IF(AND(W29<>"",U29="yes"),W29*X29,"") -> 10.4
A30: calculate | B30: adm2_name | P30: jr:choice-name(${adm2_pcode},'${adm2_pcode}') | U30: yes | X30: =1 -> 1 | Y30: =IF(W30<>"",W30*X30,"") | Z30: =IF(AND(W30<>"",U30="yes"),W30*X30,"")
A31: select_one yes_no | B31: o_area | C31: Is your household located in the urban downtown area? | D31: ¿Se encuentra su hogar en el casco urbano del municipio? | G31: Casco urbano: Área comprendida por los núcleos poblacionales que circunscriben, en forma continua, la Alcaldía Municipal y que es conocida como casco urbano del municipio. | I31: TRUE | W31: 10 | X31: =1 -> 1 | Y31: 10 | Z31: =IF(AND(W31<>"",U31="yes"),W31*X31,"")
A32: select_one agricactivity | B32: hh_agricactivity | C32: Has anybody in your household produced crops or livestock for household consumption or for sale in the past 12 months, including household members currently away for transhumance? | D32: ¿Alguien de su hogar ha producido cultivos o criado animales para el consumo doméstico o para la venta en los últimos 12 meses, incluyendo aquellos miembros del hogar que se encuentran ausentes por trashumancia? | F32: [INSTRUCTIONS: THIS IS THE MAIN SCREENING QUESTION.] [HINT FOR PROBING: Do you cultivate any plants to sale or consume? Do you raise any animals with the intent of selling or consuming them or their products like meat, milk, wool or leather? Is one of your household member currently away with cattle or other animals for transhumance?] | G32: ESTA ES LA PRINCIPAL PREGUNTA-FILTRO.] [PISTA PARA SONDEAR: ¿Usted cultiva alguna planta para la venta o el consumo? ¿Usted cria algún animal con la intención de venderlo o consumirlo, o sus productos como la carne, leche, lana o cuero? ¿Algún miembro de su hogar está lejos con ganado o por trashumancia?] | I32: true | U32: yes | W32: 31.372377 | X32: =1 -> 1 | Y32: =IF(W32<>"",W32*X32,"") -> 31.372377 | Z32: =IF(AND(W32<>"",U32="yes"),W32*X32,"") -> 31.372377
A33: select_one yes_no | B33: hh_fish | C33: Has anybody in your household been engaged in aquatic production [fish catch or aquaculture farming] for household consumption or for sales in the past 12 months? | D33: Algún miembro de su hogar ha estado involucrado en la producción piscícola [pesca o acuicultura] para el consumo del hogar o para la venta? | F33: [HINT FOR PROBING: It should not include sports fishing. It should be about production of aquatic products [fish catch or aquaculture farming] for household consumption or sales.] | G33: [PISTA PARA VALIDACIÓN: NO DEBE ser incluida la pesca deportiva. Debería tratarse de productos piscícolas [pesca o acuicultura] para el consumo del hogar o para la venta.] | I33: true | U33: no | W33: 17 | X33: =1 -> 1 | Y33: =IF(W33<>"",W33*X33,"") -> 17
X34: =1 -> 1 | Y34: =IF(W34<>"",W34*X34,"") | Z34: =IF(AND(W34<>"",U34="yes"),W34*X34,"")
A35: end_group | Y35: =IF(W35<>"",W35*X35,"") | Z35: =IF(AND(W35<>"",U35="yes"),W35*X35,"")
A36: begin_group | B36: generalInfo | C36: GENERAL INFORMATION | D36: INFORMACIÓN GENERAL | I36: false | M36: ${resp_agree} = '1' and ${hh_agricactivity} != '5' and ${hh_agricactivity} != '6' | U36: yes | Y36: =IF(W36<>"",W36*X36,"") | Z36: =IF(AND(W36<>"",U36="yes"),W36*X36,"")
X37: =1 -> 1 | Y37: =IF(W37<>"",W37*X37,"") | Z37: =IF(AND(W37<>"",U37="yes"),W37*X37,"")
A38: select_one yes_no | B38: resp_id | C38: Are you the head of household? | D38: ¿Es usted la cabeza del hogar? | I38: true | U38: yes
A39: select_one gender | B39: hh_gender | C39: Is the head of your household male or female? | D39: ¿Cuál es el género de la persona cabeza de hogar? | I39: true | M39: ${resp_id} != '1' | U39: yes | W39: 10.085732 | X39: =1 -> 1 | Y39: =IF(W39<>"",W39*X39,"") -> 10.085732 | Z39: =IF(AND(W39<>"",U39="yes"),W39*X39,"") -> 10.085732
X40: =1 -> 1 | Y40: =IF(W40<>"",W40*X40,"") | Z40: =IF(AND(W40<>"",U40="yes"),W40*X40,"")
A41: select_one edu | B41: hh_education | C41: What is the educational level attained by the head of household? | D41: ¿Cuál es el nivel de educación de la persona cabeza de hogar? | I41: true | U41: yes | W41: 12.894034 | X41: =1 -> 1 | Y41: =IF(W41<>"",W41*X41,"") -> 12.894034 | Z41: =IF(AND(W41<>"",U41="yes"),W41*X41,"") -> 12.894034
X42: =1 -> 1 | Y42: =IF(W42<>"",W42*X42,"") | Z42: =IF(AND(W42<>"",U42="yes"),W42*X42,"")
A43: select_one water | B43: hh_wealth_water | C43: Where does the water that you drink at home come from? | D43: ¿De dónde proviene el agua que bebe en su hogar? | I43: true | U43: yes | W43: 15.265829 | X43: =1 -> 1 | Y43: =IF(W43<>"",W43*X43,"") -> 15.265829 | Z43: =IF(AND(W43<>"",U43="yes"),W43*X43,"") -> 15.265829
A44: select_one toilet | B44: hh_wealth_toilet | C44: Where do household members typically go to use the toilet? | D44: ¿A dónde suelen ir usted y los miembros de su hogar al baño? | I44: true | U44: yes | W44: 15.123718 | X44: =1 -> 1 | Y44: =IF(W44<>"",W44*X44,"") -> 15.123718 | Z44: =IF(AND(W44<>"",U44="yes"),W44*X44,"") -> 15.123718
A45: select_one light | B45: hh_wealth_light | C45: What is the main source of light in your dwelling? | D45: ¿Cuál es la principal fuente de luz en su vivienda? | I45: true | U45: yes | W45: 13.760139 | X45: =1 -> 1 | Y45: =IF(W45<>"",W45*X45,"") -> 13.760139 | Z45: =IF(AND(W45<>"",U45="yes"),W45*X45,"") -> 13.760139
X46: =1 -> 1 | Y46: =IF(W46<>"",W46*X46,"") | Z46: =IF(AND(W46<>"",U46="yes"),W46*X46,"")
A47: select_one residence | B47: hh_residencetype | C47: Which in the following types of residence best describes your residence? | D47: ¿Cuál de las siguientes opciones describe mejor su tipo de residencia? | F47: [INSTRUCTIONS: READ OUT THE OPTIONS.] [HINT: IF RESPONDENT IS ONLY AWAY FROM THE HOUSEHOLD FOR SHORT SEASONAL WORK (<6 MONTHS) OR TRANSHUMANCE, MAKE SURE TO REFER TO THEIR HOUSEHOLD BACK WHERE THEY TYPICALLY ARE LOCATED.] | G47: [ENCUESTADOR/A: LEA EN VOZ ALTA LAS OPCIONES. RESPUESTA ÚNICA.] [PISTA: SI EL ENCUESTADO ESTÁ FUERA DE CASA SOLO POR TRABAJO ESTACIONAL DE CORTA DURACIÓN (<6 MESES) O POR TRASHUMANCIA, HAGA REFERENCIA AL HOGAR COMO EL LUGAR AL QUE RETORNA Y DONDE VIVE HABITUALMENTE.] | I47: true | U47: no | W47: 30.646189 | X47: =1 -> 1 | Y47: =IF(W47<>"",W47*X47,"") -> 30.646189 | Z47: =IF(AND(W47<>"",U47="yes"),W47*X47,"")
A48: integer | B48: hh_size | C48: How many people are part of the household? | D48: ¿Cuántas personas hacen parte del hogar? | F48: [INSTRUCTIONS: RECORD NUMBER OF MEMBERS IN HOUSEHOLD. ENTER 888 FOR DON'T KNOW & 999 FOR REFUSED.] [HINT: TO BE A PART OF THE SAME HOUSEHOLD, MEMBERS MUST LIVE UNDER THE SAME ROOF, SHARE THE SAME RESOURCES & EAT FROM THE SAME POT.] | G48: [ENCUESTADOR/A: REGISTRE EL NÚMERO DE MIEMBROS. ESCRIBA 888 PARA "NO SABE" Y 999 PARA "NO RESPONDE"] [PISTA: PARA SER PARTE DEL MISMO HOGAR, LOS MIEMBROS DEBEN VIVIR BAJO EL MISMO TECHO, COMPARTIR RECURSOS Y COMER DE LA MISMA OLLA. ] | I48: true | K48: (. >= 1 and . <= 50) or . = 888 or . = 999 | U48: no | W48: 15.211848 | X48: =1 -> 1 | Y48: =IF(W48<>"",W48*X48,"") -> 15.211848 | Z48: =IF(AND(W48<>"",U48="yes"),W48*X48,"")
A49: select_multiple asset_prod | B49: hh_asset_prod | C49: Does your household own any of the following productive assets? | D49: ¿Tiene su hogar alguno de los siguientes activos productivos? | F49: [INSTRUCTIONS: MULTIPLE RESPONSES POSSIBLE. READ ANSWER OPTIONS OUT LOUD.] | G49: [ENCUESTADOR/A: ES POSIBLE SELECCIONAR MÚLTIPLES RESPUESTAS. LEA LAS OPCIONES DE RESPUESTA EN VOZ ALTA.] | I49: true | K49: if(selected(.,'none') or selected(.,'dk') or selected(.,'ref'), count-selected(.) = 1, count-selected(.) >= 1) | U49: no | W49: 17 | X49: =1 -> 1 | Y49: =IF(W49<>"",W49*X49,"") -> 17 | Z49: =IF(AND(W49<>"",U49="yes"),W49*X49,"")
A50: select_multiple asset_transp | B50: hh_asset_transp | C50: Do you or any member of household own any of the following transportation assets? | D50: ¿Tiene su hogar alguno de los siguientes medios de transporte? | F50: [INSTRUCTIONS: MULTIPLE RESPONSES POSSIBLE. READ ANSWER OPTIONS OUT LOUD.] | I50: true | K50: if(selected(.,'none') or selected(.,'dk') or selected(.,'ref'), count-selected(.) = 1, count-selected(.) >= 1) | U50: no | W50: 17 | X50: =1 -> 1 | Y50: =IF(W50<>"",W50*X50,"") -> 17 | Z50: =IF(AND(W50<>"",U50="yes"),W50*X50,"")
A51: select_one maritalstat | B51: hh_maritalstat | C51: What is the head of household’s current marital status? | D51: ¿Cuál es el estado civil actual de la persona cabeza de hogar? | I51: true | U51: no | W51: 17 | X51: =1 -> 1 | Y51: =IF(W51<>"",W51*X51,"") -> 17 | Z51: =IF(AND(W51<>"",U51="yes"),W51*X51,"")
A52: select_one agegroup | B52: hh_age | C52: How old is the head of household? | D52: ¿Cuál es la edad de la persona cabeza de hogar? | I52: true | U52: no | W52: 8.2288065 | X52: =1 -> 1 | Y52: =IF(W52<>"",W52*X52,"") -> 8.2288065 | Z52: =IF(AND(W52<>"",U52="yes"),W52*X52,"")
X53: =1 -> 1 | Y53: =IF(W53<>"",W53*X53,"") | Z53: =IF(AND(W53<>"",U53="yes"),W53*X53,"")
A54: end_group | X54: =1 -> 1 | Y54: =IF(W54<>"",W54*X54,"") | Z54: =IF(AND(W54<>"",U54="yes"),W54*X54,"")
A55: begin_group | B55: Income_Shocks_group | C55: INCOME SOURCES, LIVELIHOODS AND SHOCKS | D55: INCOME SOURCES, LIVELIHOODS AND SHOCKS | I55: false | M55: ${resp_agree} = '1' and ${hh_agricactivity} != '5' and ${hh_agricactivity} != '6' | U55: yes | X55: =1 -> 1 | Y55: =IF(W55<>"",W55*X55,"") | Z55: =IF(AND(W55<>"",U55="yes"),W55*X55,"")
X56: =1 -> 1 | Y56: =IF(W56<>"",W56*X56,"") | Z56: =IF(AND(W56<>"",U56="yes"),W56*X56,"")
A57: select_one incomesource1 | B57: income_main | C57: What was your household's main source of income in the past 3 months? | D57: ¿Cuál ha sido la principal fuente de ingresos de su hogar en los últimos 3 meses? | F57: [INSTRUCTIONS: REFUSED OPTIONS SHOULD BE AVOIDED AS MUCH AS POSSIBLE.] | G57: [OPERADOR:LA OPCIÓN "NO RESPONDE" DEBE EVITARSE EN LA MEDIDA DE LO POSIBLE.] | I57: true | J57: minimal | U57: yes | W57: 36.928734 | X57: =1 -> 1 | Y57: =IF(W57<>"",W57*X57,"") -> 36.928734 | Z57: =IF(AND(W57<>"",U57="yes"),W57*X57,"") -> 36.928734
A58: calculate | B58: incomemain | P58: jr:choice-name(${income_main},'${income_main}') | U58: yes | X58: =1 -> 1 | Y58: =IF(W58<>"",W58*X58,"") | Z58: =IF(AND(W58<>"",U58="yes"),W58*X58,"")
A59: select_one yes_no | B59: income_main_crop_check | C59: Are the crops sold also produced by you or anyone in your household? | D59: ¿Las cosechas de los cultivos vendidos son también producidas por usted o algún miembro de su hogar? | I59: true | M59: ${income_main} = '1' or ${income_main} = '2' or ${income_main} = '3' | U59: yes | W59: 0 | X59: =1 -> 1 | Y59: =IF(W59<>"",W59*X59,"") -> 0 | Z59: =IF(AND(W59<>"",U59="yes"),W59*X59,"") -> 0
A60: select_one yes_no | B60: income_main_ls_check | C60: Are the livestock or livestock products sold also produced by you or anyone in your household? | D60: ¿Los animales o productos de origen animal vendidos son también producidos por usted o algún miembro de su hogar? | I60: true | M60: ${income_main} = '4' | U60: yes | W60: 0 | X60: =1 -> 1 | Y60: =IF(W60<>"",W60*X60,"") -> 0 | Z60: =IF(AND(W60<>"",U60="yes"),W60*X60,"") -> 0
A61: select_one yes_no | B61: income_main_fish_check | C61: Are the fish or aquatic products sold also captured/harvested by you or anyone in your household? | D61: ¿Los productos pesqueros o acuícolas que vende son también capturados/cosechados por usted o algún miembro de su hogar? | I61: true | M61: ${income_main} = '6' | U61: yes | W61: 0 | X61: =1 -> 1 | Y61: =IF(W61<>"",W61*X61,"") -> 0 | Z61: =IF(AND(W61<>"",U61="yes"),W61*X61,"") -> 0
X62: =1 -> 1 | Y62: =IF(W62<>"",W62*X62,"") | Z62: =IF(AND(W62<>"",U62="yes"),W62*X62,"")
A63: decimal | B63: income_main_amount | C63: How much was earned (in USD) from your main income source, ${incomemain}, in the past 3 months ? | D63: ¿Cuánto ganó (en USD) por su principal fuente de ingresos, ${incomemain}, en los últimos 3 meses? | F63: [INSTRUCTIONS: MAKE SURE THE INFORMATION IS RECORDED IN THE CORRECT CURRENCY. ENTER 888 FOR DON'T KNOW AND 999 FOR REFUSED.] | G63: [ENCUESTADOR/A: COMPRUEBE QUE LA RESPUESTA ESTÉ REGISTRADA EN LA MONEDA CORRECTA. ESCRIBA 888 PARA "NO SABE" Y 999 PARA "NO RESPONDE".] | I63: true | K63: . > 0 or . = 888 or . = 999 | M63: ${income_main} != '19' and ${income_main} != '20' | U63: no | W63: 40.047318 | X63: =1 -> 1 | Y63: =IF(W63<>"",W63*X63,"") -> 40.047318 | Z63: =IF(AND(W63<>"",U63="yes"),W63*X63,"")
A64: select_one continue | B64: income_main_amount_conf | C64: Can you confirm the amount of income you just stated is correct? | D64: ¿Podría confirmar que la cantidad de ingresos que acaba de indicar es correcta? | F64: [INSTRUCTIONS: IF THE RESPONDENT CONFIRMS THAT THE INCOME AMOUNT EARNED FROM THIS INCOME SOURCE OVER THE PAST 3 MONTH IS INDEED OVER 5000, CLICK ON CONTINUE. OTHERWISE, GO BACK AND CHANGE THE AMOUNT ENTERED.] | G64: [ENCUESTADOR/A: SI LA CANTIDAD GANADA POR ESTA FUENTE DE INGRESOS EN LOS ÚLTIMOS 3 MESES ESTÁ POR ENCIMA DE 5000 ,HAGA CLICK EN CONTINUAR. DE LO CONTRARIO, REGRESE Y CAMBIE LA CANTIDAD INGRESADA.] | I64: false | M64: ${income_main_amount} > 5000 and (${income_main} != '19' and ${income_main} != '20') | U64: no | W64: 3.687011 | X64: =1 -> 1 | Y64: =IF(W64<>"",W64*X64,"") -> 3.687011 | Z64: =IF(AND(W64<>"",U64="yes"),W64*X64,"")
A66: select_one gender_inc_1 | B66: income_main_gender | C66: What is the gender of the household member(s) generating income from this source? | D66: ¿Cuál es el género del miembro[s] del hogar que genera[n] el ingreso de esta fuente? | I66: true | M66: ${income_main} != '19' and ${income_main} != '20'
A67: select_one gender_inc_2 | B67: income_main_control | C67: Who controls the revenue that is earned from this source? | D67: ¿Quién maneja los ingresos que se obtienen de esta fuente? | I67: true | M67: ${income_main} != '19' and ${income_main} != '20'
X68: =1 -> 1 | Y68: =IF(W68<>"",W68*X68,"") | Z68: =IF(AND(W68<>"",U68="yes"),W68*X68,"")
A69: select_one change | B69: income_main_comp | C69: Has your household's income from ${incomemain} changed in the last 3 months compared to the same period of last year? | D69: En los últimos 3 meses, ¿han cambiado los ingresos del hogar provenientes de la ${incomemain} comparado con el mismo periodo en el año pasado? | I69: true | M69: ${income_main} != '19' and ${income_main} != '20' | U69: yes | W69: 27.242167 | X69: =1 -> 1 | Y69: =IF(W69<>"",W69*X69,"") -> 27.242167 | Z69: =IF(AND(W69<>"",U69="yes"),W69*X69,"") -> 27.242167
X70: =1 -> 1 | Y70: =IF(W70<>"",W70*X70,"") | Z70: =IF(AND(W70<>"",U70="yes"),W70*X70,"")
A71: select_one incomesource2 | B71: income_sec | C71: What was your household's second most important source of income in the past 3 months? | D71: ¿Cuál fue la segunda fuente de ingresos de su hogar en los últimos 3 meses? | F71: [INSTRUCTIONS: DON'T KNOW AND REFUSED OPTIONS SHOULD BE AVOIDED AS MUCH AS POSSIBLE.] | G71: LAS OPCIONES “NO SABE” Y “NO RESPONDE” DEBEN EVITARSE EN LA MEDIDA DE LO POSIBLE. | I71: true | J71: minimal | M71: ${income_main} != '19' and ${income_main} != '20' | N71: not(selected(${income_main}, name)) | U71: yes | W71: 25.308004 | X71: =1 -> 1 | Y71: =IF(W71<>"",W71*X71,"") -> 25.308004 | Z71: =IF(AND(W71<>"",U71="yes"),W71*X71,"") -> 25.308004
A72: calculate | B72: incomesec | P72: jr:choice-name(${income_sec},'${income_sec}') | U72: yes | X72: =1 -> 1 | Y72: =IF(W72<>"",W72*X72,"") | Z72: =IF(AND(W72<>"",U72="yes"),W72*X72,"")
A73: select_one yes_no | B73: income_sec_crop_check | C73: Are the crops sold also produced by you or anyone in your household? | D73: ¿Las cosechas de los cultivos vendidos son también producidas por usted o algún miembro de su hogar? | I73: true | M73: ${income_sec} = '1' or ${income_sec} = '2' or ${income_sec} = '3' | U73: yes | W73: 0 | X73: =1 -> 1 | Y73: =IF(W73<>"",W73*X73,"") -> 0 | Z73: =IF(AND(W73<>"",U73="yes"),W73*X73,"") -> 0
A74: select_one yes_no | B74: income_sec_ls_check | C74: Are the livestock or livestock products sold also produced by you or anyone in your household? | D74: ¿Los animales o productos de origen animal vendidos son también producidos por usted o algún miembro de su hogar? | I74: true | M74: ${income_sec} = '4' | U74: yes | W74: 0 | X74: =1 -> 1 | Y74: =IF(W74<>"",W74*X74,"") -> 0 | Z74: =IF(AND(W74<>"",U74="yes"),W74*X74,"") -> 0
A75: select_one yes_no | B75: income_sec_fish_check | C75: Are the fish or aquatic products sold also captured/harvested by you or anyone in your household? | D75: ¿Los productos pesqueros o acuícolas que vende son también capturados/cosechados por usted o algún miembro de su hogar? | I75: true | M75: ${income_sec} = '6' | U75: yes | W75: 0 | X75: =1 -> 1 | Y75: =IF(W75<>"",W75*X75,"") -> 0 | Z75: =IF(AND(W75<>"",U75="yes"),W75*X75,"") -> 0
X76: =1 -> 1 | Y76: =IF(W76<>"",W76*X76,"") | Z76: =IF(AND(W76<>"",U76="yes"),W76*X76,"")
A77: decimal | B77: income_sec_amount | C77: How much was earned (in USD) from your second main income source, ${incomesec}, in the past 3 months ? | D77: ¿Cuánto ganó (en USD) por la segunda fuente de ingresos, ${incomesec}, en los últimos 3 meses? | F77: [INSTRUCTIONS: MAKE SURE THE INFORMATION IS RECORDED IN THE CORRECT CURRENCY. ENTER 888 FOR DON'T KNOW AND 999 FOR REFUSED.] | G77: [ENCUESTADOR/A: COMPRUEBE QUE LA RESPUESTA ESTÉ REGISTRADA EN LA MONEDA CORRECTA. ESCRIBA 888 PARA "NO SABE" Y 999 PARA "NO RESPONDE".] | I77: true | K77: . > 0 or . = 888 or . = 999 | M77: ${income_main} != '19' and ${income_main} != '20' and ${income_sec} != '19' and ${income_sec} != '20' and ${income_sec} != '21' | U77: no | W77: 30.82847 | X77: =1 -> 1 | Y77: =IF(W77<>"",W77*X77,"") -> 30.82847 | Z77: =IF(AND(W77<>"",U77="yes"),W77*X77,"")
A78: select_one continue | B78: income_sec_amount_conf | C78: Can you confirm the amount of income you just stated is correct? | D78: ¿Podría confirmar que la cantidad de ingresos que acaba de indicar es correcta? | F78: [INSTRUCTIONS: IF THE RESPONDENT CONFIRMS THAT THE INCOME AMOUNT EARNED FROM THIS INCOME SOURCE OVER THE PAST 3 MONTH IS INDEED OVER 5000, CLICK ON CONTINUE. OTHERWISE, GO BACK AND CHANGE THE AMOUNT ENTERED.] | G78: [ENCUESTADOR/A: SI LA CANTIDAD GANADA POR ESTA FUENTE DE INGRESOS EN LOS ÚLTIMOS 3 MESES ESTÁ POR ENCIMA DE 5000 ,HAGA CLICK EN CONTINUAR. DE LO CONTRARIO, REGRESE Y CAMBIE LA CANTIDAD INGRESADA.] | I78: false | M78: ${income_sec_amount} > 5000 and (${income_main} != '19' and ${income_main} != '20' and ${income_sec} != '19' and ${income_sec} != '20' and ${income_sec} != '21') | U78: no | W78: 2.2941177 | X78: =1 -> 1 | Y78: =IF(W78<>"",W78*X78,"") -> 2.2941177 | Z78: =IF(AND(W78<>"",U78="yes"),W78*X78,"")
X79: =1 -> 1 | Y79: =IF(W79<>"",W79*X79,"") | Z79: =IF(AND(W79<>"",U79="yes"),W79*X79,"")
A80: select_one gender_inc_1 | B80: income_sec_gender | C80: What is the gender of the household member(s) generating income from this source? | D80: ¿Cuál es el género del miembro[s] del hogar que genera[n] el ingreso de esta fuente? | I80: true | M80: ${income_main} != '19' and ${income_main} != '20' and ${income_sec} != '19' and ${income_sec} != '20' and ${income_sec} != '21'
A81: select_one gender_inc_2 | B81: income_sec_control | C81: Who controls the revenue that is earned from this source? | D81: ¿Quién maneja los ingresos que se obtienen de esta fuente? | I81: true | M81: ${income_main} != '19' and ${income_main} != '20' and ${income_sec} != '19' and ${income_sec} != '20' and ${income_sec} != '21'
X82: =1 -> 1 | Y82: =IF(W82<>"",W82*X82,"") | Z82: =IF(AND(W82<>"",U82="yes"),W82*X82,"")
A83: select_one change | B83: income_sec_comp | C83: Has your household's income from ${incomesec} changed in the last 3 months compared to the same period of last year? | D83: En los últimos 3 meses, ¿han cambiado los ingresos del hogar provenientes de la ${incomesec} comparado con el mismo periodo en el año pasado? | I83: true | M83: ${income_main} != '19' and ${income_main} != '20' and ${income_sec} != '19' and ${income_sec} != '20' and ${income_sec} != '21' | U83: yes | W83: 21.193256 | X83: =1 -> 1 | Y83: =IF(W83<>"",W83*X83,"") -> 21.193256 | Z83: =IF(AND(W83<>"",U83="yes"),W83*X83,"") -> 21.193256
X84: =1 -> 1 | Y84: =IF(W84<>"",W84*X84,"") | Z84: =IF(AND(W84<>"",U84="yes"),W84*X84,"")
A85: select_one incomesource3 | B85: income_third | C85: What was your household's third most important source of income in the past 3 months? | D85: ¿Cuál fue la tercera fuente de ingresos de su hogar en los últimos 3 meses? | F85: [INSTRUCTIONS: DON'T KNOW AND REFUSED OPTIONS SHOULD BE AVOIDED AS MUCH AS POSSIBLE.] | G85: [OPERADOR: LAS OPCIONES "NO SABE" Y "NO RESPONDE" DEBEN EVITARSE EN LA MEDIDA DE LO POSIBLE.] | I85: true | J85: minimal | M85: ${income_main} != '19' and ${income_main} != '20' and ${income_sec} != '19' and ${income_sec} != '20' and ${income_sec} != '21' | N85: not(selected(${income_main}, name) or selected(${income_sec}, name)) | U85: yes | W85: 20.229927 | X85: =1 -> 1 | Y85: =IF(W85<>"",W85*X85,"") -> 20.229927 | Z85: =IF(AND(W85<>"",U85="yes"),W85*X85,"") -> 20.229927
A86: calculate | B86: incomethird | P86: jr:choice-name(${income_third},'${income_third}') | U86: yes | X86: =1 -> 1 | Y86: =IF(W86<>"",W86*X86,"") | Z86: =IF(AND(W86<>"",U86="yes"),W86*X86,"")
A87: select_one yes_no | B87: income_third_crop_check | C87: Are the crops sold also produced by you or anyone in your household? | D87: ¿Las cosechas de los cultivos vendidos son también producidas por usted o algún miembro de su hogar? | I87: true | M87: ${income_third} = '1' or ${income_third} = '2' or ${income_third} = '3' | U87: yes | W87: 0 | X87: =1 -> 1 | Y87: =IF(W87<>"",W87*X87,"") -> 0 | Z87: =IF(AND(W87<>"",U87="yes"),W87*X87,"") -> 0
A88: select_one yes_no | B88: income_third_ls_check | C88: Are the livestock or livestock products sold also produced by you or anyone in your household? | D88: ¿Los animales o productos de origen animal vendidos son también producidos por usted o algún miembro de su hogar? | I88: true | M88: ${income_third} = '4' | U88: yes | W88: 0 | X88: =1 -> 1 | Y88: =IF(W88<>"",W88*X88,"") -> 0 | Z88: =IF(AND(W88<>"",U88="yes"),W88*X88,"") -> 0
A89: select_one yes_no | B89: income_third_fish_check | C89: Are the fish or aquatic products sold also captured/harvested by you or anyone in your household? | D89: ¿Los productos pesqueros o acuícolas que vende son también capturados/cosechados por usted o algún miembro de su hogar? | I89: true | M89: ${income_third} = '6' | U89: yes | W89: 0 | X89: =1 -> 1 | Y89: =IF(W89<>"",W89*X89,"") -> 0 | Z89: =IF(AND(W89<>"",U89="yes"),W89*X89,"") -> 0
X90: =1 -> 1 | Y90: =IF(W90<>"",W90*X90,"") | Z90: =IF(AND(W90<>"",U90="yes"),W90*X90,"")
A91: decimal | B91: income_third_amount | C91: How much was earned (in USD) from your third main income source, ${incomethird}, in the past 3 months ? | D91: ¿Cuánto ganó (en USD) por la tercera fuente de ingresos, ${incomethird}, en los últimos 3 meses? | F91: [INSTRUCTIONS: MAKE SURE THE INFORMATION IS RECORDED IN THE CORRECT CURRENCY. ENTER 888 FOR DON'T KNOW AND 999 FOR REFUSED.] | I91: true | K91: . > 0 or . = 888 or . = 999 | M91: ${income_main} != '19' and ${income_main} != '20' and ${income_sec} != '19' and ${income_sec} != '20' and ${income_sec} != '21' and ${income_third} != '19' and ${income_third} != '20' and ${income_third} != '21' | U91: no | W91: 29.429832 | X91: =1 -> 1 | Y91: =IF(W91<>"",W91*X91,"") -> 29.429832 | Z91: =IF(AND(W91<>"",U91="yes"),W91*X91,"")
A92: select_one continue | B92: income_third_amount_conf | C92: Can you confirm the amount of income you just stated is correct? | D92: ¿Podría confirmar que la cantidad de ingresos que acaba de indicar es correcta? | F92: [INSTRUCTIONS: IF THE RESPONDENT CONFIRMS THAT THE INCOME AMOUNT EARNED FROM THIS INCOME SOURCE OVER THE PAST 3 MONTH IS INDEED OVER 5000, CLICK ON CONTINUE. OTHERWISE, GO BACK AND CHANGE THE AMOUNT ENTERED.] | I92: false | M92: ${income_third_amount} > 5000 and (${income_main} != '19' and ${income_main} != '20' and ${income_sec} != '19' and ${income_sec} != '20' and ${income_sec} != '21' and ${income_third} != '19' and ${income_third} != '20' and ${income_third} != '21' ) | U92: no | W92: 1.5555556 | X92: =1 -> 1 | Y92: =IF(W92<>"",W92*X92,"") -> 1.5555556 | Z92: =IF(AND(W92<>"",U92="yes"),W92*X92,"")
X93: =1 -> 1 | Y93: =IF(W93<>"",W93*X93,"") | Z93: =IF(AND(W93<>"",U93="yes"),W93*X93,"")
A94: select_one gender_inc_1 | B94: income_third_gender | C94: What is the gender of the household member(s) generating income from this source? | D94: ¿Cuál es el género del miembro[s] del hogar que genera[n] el ingreso de esta fuente? | I94: true | M94: ${income_main} != '19' and ${income_main} != '20' and ${income_sec} != '19' and ${income_sec} != '20' and ${income_sec} != '21' and ${income_third} != '19' and ${income_third} != '20' and ${income_third} != '21'
A95: select_one gender_inc_2 | B95: income_third_control | C95: Who controls the revenue that is earned from this source? | D95: ¿Quién maneja los ingresos que se obtienen de esta fuente? | I95: true | M95: ${income_main} != '19' and ${income_main} != '20' and ${income_sec} != '19' and ${income_sec} != '20' and ${income_sec} != '21' and ${income_third} != '19' and ${income_third} != '20' and ${income_third} != '21'
X96: =1 -> 1 | Y96: =IF(W96<>"",W96*X96,"") | Z96: =IF(AND(W96<>"",U96="yes"),W96*X96,"")
A97: select_one change | B97: income_third_comp | C97: Has your household's income from ${incomethird} changed in the last 3 months compared to the same period of last year? | D97: En los últimos 3 meses, ¿han cambiado los ingresos del hogar provenientes de la ${incomethird} comparado con el mismo periodo en el año pasado? | I97: true | M97: ${income_main} != '19' and ${income_main} != '20' and ${income_sec} != '19' and ${income_sec} != '20' and ${income_sec} != '21' and ${income_third} != '19' and ${income_third} != '20' and ${income_third} != '21' | U97: yes | W97: 16.348396 | X97: =1 -> 1 | Y97: =IF(W97<>"",W97*X97,"") -> 16.348396 | Z97: =IF(AND(W97<>"",U97="yes"),W97*X97,"") -> 16.348396
X98: =1 -> 1 | Y98: =IF(W98<>"",W98*X98,"") | Z98: =IF(AND(W98<>"",U98="yes"),W98*X98,"")
A99: select_multiple shock | B99: shock | C99: Has your household or community faced any particular disaster or crisis affecting your household's ability to raise an income and/or to produce food for self consumption in the last 3 months, and if so, which ones? | D99: ¿Su hogar ha afrontado algún desastre o crisis particular que haya afectado a su hogar o comunidad, disminuyendo la capacidad para generar ingreso y/o producir alimentos para el autoconsumo en los últimos 3 meses? | F99: [INSTRUCTIONS: SELECT RELEVANT SHOCKS EXPERIENCED BY THE HOUSEHOLD. MULTIPLE RESPONSES POSSIBLE. REFER TO ECONOMIC SHOCKS, CROP AND LIVESTOCK SHOCKS, INTRA-HOUSEHOLD SHOCK, NATURAL HAZARDS AND HUMAN-INDUCED HAZARDS.] | G99: [ENCUESTADOR/A: SELECCIONE LAS CRISIS EXPERIMENTADAS POR EL HOGAR. ES POSIBLE SELECCIONAR MÚLTIPLES RESPUESTAS.CONSULTE CRISIS ECONÓMICAS, CRISIS EN CULTIVOS Y GANADERÍA, CRISIS INTRAFAMILIARES, PELIGROS NATURALES Y PELIGROS INDUCIDOS POR EL HOMBRE.] | I99: true | K99: if(selected(.,'noshock') or selected(.,'dk') or selected(.,'ref'), count-selected(.) = 1, count-selected(.) >= 1) | U99: yes | W99: 46.247528 | X99: =1 -> 1 | Y99: =IF(W99<>"",W99*X99,"") -> 46.247528 | Z99: =IF(AND(W99<>"",U99="yes"),W99*X99,"") -> 46.247528
A100: select_one yes_no | B100: o_jornal | C100: Is anyone in your household going to migrate or has already migrated temporarily for casual labor for coffee, cane or other cash crop harvest? | D100: ¿Alguna persona de su hogar va a migrar o ha migrado temporalmente para la cosecha del café, la caña u otro cultivo comercial? | I100: TRUE | W100: 5 | X100: =1 -> 1 | Y100: =IF(W100<>"",W100*X100,"") -> 5 | Z100: =IF(AND(W100<>"",U100="yes"),W100*X100,"")
A101: select_one jornal_cuantas | B101: o_jornal_cuantaspersonas | C101: How many people have emigrated or will migrate temporarily for casual labor for coffee, cane or other cash crop harvest? | D101: ¿Cuántas personas van a migrar o han migrado temporalmente para trabajar como jornalero en la cosecha del café, la caña u otro cultivo comercial? | I101: TRUE | M101: ${o_jornal} = '1' | W101: 5 | X101: 0.3 | Y101: =IF(W101<>"",W101*X101,"") -> 1.5
A102: select_one jornal_cultivo | B102: o_jornal_cultivo | C102: For which crop are the members of your household going to work as casual laborers? | D102: ¿Para qué cultivo los miembros de su hogar van a trabajar como jornaleros? | I102: TRUE | M102: ${o_jornal} = '1' | W102: 5 | X102: 0.3 | Y102: =IF(W102<>"",W102*X102,"") -> 1.5
...

Sheet choices
A1: list_name | B1: name | C1: label::English (en) | D1: label::Spanish (es) | E1: label:: | F1: my_filter_admin
A2: enumteam | B2: 1 | C2: Enumerator team 1 | D2: Equipo de encuestadores 1
A3: enumteam | B3: 2 | C3: Enumerator team 2 | D3: Equipo de encuestadores 2
A4: enumteam | B4: 3 | C4: Enumerator team 3 | D4: Equipo de encuestadores 3
A5: enumteam | B5: 4 | C5: Enumerator team 4 | D5: Equipo de encuestadores 4
A7: enumerator | B7: 1 | C7: enumerator name 1 | D7: nombre de encuestador 1
A8: enumerator | B8: 2 | C8: enumerator name 2 | D8: nombre de encuestador 2
A9: enumerator | B9: 3 | C9: enumerator name 3 | D9: nombre de encuestador 3
A11: yes_no | B11: 1 | C11: Yes | D11: SI
A12: yes_no | B12: 2 | C12: No | D12: NO
A13: yes_no | B13: 3 | C13: DON'T KNOW | D13: NO SABE
A14: yes_no | B14: 4 | C14: REFUSED | D14: NO RESPONDE
A16: continue | B16: continue | C16: continue | D16: continuar
A18: yesno | B18: 1 | C18: Yes | D18: Si
A19: yesno | B19: 2 | C19: No | D19: No
A21: language | B21: en | C21: English | D21: Inglés
A22: language | B22: es | C22: Spanish | D22: Español
A23: language | B23: … | C23: …
A25: gender | B25: 1 | C25: Male | D25: Masculino
A26: gender | B26: 2 | C26: Female | D26: Femenino
A27: gender | B27: 3 | C27: DON'T KNOW | D27: NO SABE
A28: gender | B28: 4 | C28: REFUSED | D28: NO RESPONDE
A30: contact_info | B30: 1 | C30: YES - mine | D30: SI - mio
A31: contact_info | B31: 2 | C31: YES - other household member | D31: SI - De otro miembro del hogar
A32: contact_info | B32: 3 | C32: YES - friend or relative [non-household member] | D32: SI - De un amigo o familiar [no miembro del hogar]
A33: contact_info | B33: 4 | C33: NO | D33: NO
A35: agricactivity | B35: 1 | C35: Yes - crop production | D35: Sí - producción de cultivos
A36: agricactivity | B36: 2 | C36: Yes - livestock production | D36: Sí - producción ganadería/ animales
A37: agricactivity | B37: 3 | C37: Yes - both crop and livestock production | D37: Sí - ambas, producción de cultivos y animal
A38: agricactivity | B38: 4 | C38: No | D38: No
... A86: residence | B86: 7 | C86: REFUSED | D86: NO RESPONDE
A88: asset_prod | B88: process | C88: Processing assets (e.g. grinding/crushing machine, mill, oil press, fish tanks) | D88: Activos para el procesamiento [ej: trituradora, molino, prensa para aceite, tanques para la acuicultura / peceras]
A89: asset_prod | B89: farmmach | C89: Farm or fishing machinery (e.g. tractor, plough, sickle, boats, engines) | D89: Maquinaria agrícola o pesquera [ej: tractor, arado, hoz, botes, motores]
A90: asset_prod | B90: sewing | C90: Sewing machine or weaving tool | D90: Máquina de coser
A91: asset_prod | B91: taxi | C91: Taxi | D91: Taxi
A92: asset_prod | B92: truck | C92: Truck | D92: Camión
A93: asset_prod | B93: other | C93: Other productive machines or assets | D93: Otras máquinas productivas
A94: asset_prod | B94: none | C94: No productive machines or assets | D94: Ningúna máquina porductiva
A95: asset_prod | B95: dk | C95: DON'T KNOW | D95: NO SABE
A96: asset_prod | B96: ref | C96: REFUSED | D96: NO RESPONDE
A98: asset_transp | B98: bici | C98: Bicycle | D98: Bicicleta
A99: asset_transp | B99: cart | C99: Cart (animal drawn) | D99: Carreta (tracción animal
A100: asset_transp | B100: boatmotor | C100: Boat with an engine [inboard or outboard] | D100: Bote con motor [intraborda o fuera de borda]
... A108: asset_transp | B108: ref | C108: REFUSED | D108: NO RESPONDE
A110: maritalstat | B110: 1 | C110: Single / never married | D110: Soltero / nunca se ha casado
A111: maritalstat | B111: 2 | C111: Married | D111: Casado
A112: maritalstat | B112: 3 | C112: Separated | D112: Separado
A113: maritalstat | B113: 4 | C113: Divorced | D113: Divorciado
A114: maritalstat | B114: 5 | C114: Widowed | D114: Viudo
A115: maritalstat | B115: 6 | C115: DON’T KNOW | D115: NO SABE
A116: maritalstat | B116: 7 | C116: REFUSED | D116: NO RESPONDE
A118: agegroup | B118: 1 | C118: Under 18 | D118: Menos de 18 años
A119: agegroup | B119: 2 | C119: 18 to 40 | D119: 18 a 40
A120: agegroup | B120: 3 | C120: 41 to 65 | D120: 41 a 65
A121: agegroup | B121: 4 | C121: Over 65 | D121: Por encima de 65 años
A122: agegroup | B122: 5 | C122: DON'T KNOW | D122: NO SABE
... A208: incomesource3 | B208: 21 | C208: REFUSED | D208: NO RESPONDE
A210: shock | B210: noshock | C210: No shock | D210: Sin afectación
A211: shock | B211: sicknessordeathofhh | C211: Sickness or accident or death of household member[s] [sickness of breadwinner / unusually high medical expenditure / funeral expenses / death of breadwinner] | D211: Enfermedad, accidente o muerte de miembro[s] del hogar [enfermedad del proveedor económico de la familia/gastos médicos inusualmente altos/gastos funerarios/muerte del proveedor económico de la familia]
A212: shock | B212: lostemplorwork | C212: Lost employment or working opportunities [not due to illness/accident] | D212: Pérdida de empleo u oportunidades laborales [aplíca principalmente para trabajo por dias]
A213: shock | B213: otherintrahhshock | C213: Other intra-household shock | D213: Otros impactos dentro del hogar
A214: shock | B214: higherfoodprices | C214: Unusually high food prices | D214: Precios de los alimentos mucho más altos de lo habitual
A215: shock | B215: higherfuelprices | C215: Unusually high fuel prices or transport prices | D215: Precios de combustibles mucho más altos de lo usual
A216: shock | B216: mvtrestrict | C216: Population movement restrictions [e.g. due to epidemic or infrastructure damage] | D216: Eventos externos [restricciones por COVID-19, inseguridad, daños a la infrastructura, etc.] que impiden la continuación del trabajo o negocio
A217: shock | B217: othereconomicshock | C217: Other economic shock | D217: Otras afectaciones económicas
A218: shock | B218: pestoutbreak | C218: Pest outbreak | D218: Brote de plagas
A219: shock | B219: plantdisease | C219: Plant disease | D219: Enfermedad en plantas
A220: shock | B220: animaldisease | C220: Animal disease [affecting many animals] or death | D220: Enfermedad o muerte que afecta a muchos animales
A221: shock | B221: napasture | C221: Lack of physical access to pasture | D221: Falta de acceso a pastos [a causa del conflicto/ daño a la infraestructura / restricciones por COVID-19]
... A249: covidmeasures | B249: ref | C249: REFUSED | D249: NO RESPONDE
A251: landsize_unit | B251: 1 | C251: Acres | D251: Acres
A252: landsize_unit | B252: 2 | C252: Hectares | D252: Hectáreas
A253: landsize_unit | B253: 3 | C253: Square meters | D253: Metros cuadrados
A254: landsize_unit | B254: 4 | C254: Square feet | D254: Pies cuadrados
A255: landsize_unit | B255: 5 | C255: #local measurement unit# | D255: #local measurement unit ES#
A257: cropcheck | B257: 1 | C257: Don’t usually produce during this season | D257: Normalmente no produce durante está temporada
A258: cropcheck | B258: 2 | C258: Wasn't able to produce (e.g. due to difficulties) | D258: No pudo producir (por difícultades, por ejemplo)
A260: irrigation | B260: 1 | C260: Rainfed | D260: Agua lluvia
A261: irrigation | B261: 2 | C261: Groundwater | D261: Agua subterranea
A262: irrigation | B262: 3 | C262: Natural surface water [river, lake, stream, pond, etc.] | D262: Agua natural superficial [río / lago / arroyo / estanque / etc.]
A263: irrigation | B263: 4 | C263: Constructed water point [canal, dam, etc.] | D263: Punto de agua construido [canal / presa / etc.]
A264: irrigation | B264: 5 | C264: Public water supply system [e.g. tap water] | D264: Sistema de abastecimiento de agua público [ej. agua de grifo]
... A275: irrigpump | B275: 7 | C275: REFUSED | D275: NO RESPONDE
A277: seedsupply | B277: ownprod | C277: Own production | D277: Producción propia
A278: seedsupply | B278: market | C278: Local market or agro-input shop / dealer | D278: Mercado local o tienda/vendedor de agroinsumos
A279: seedsupply | B279: company | C279: Private seed company | D279: Empresa privada de semillas
A280: seedsupply | B280: ngo | C280: NGOs | D280: ONG
A281: seedsupply | B281: organized_community | C281: Community seed banks / farmer networks / farmers' association / etc. | D281: Banco de semillas comunitario / redes de agricultores / organización de productores / etc.
A282: seedsupply | B282: gov | C282: Government [e.g. MoA] | D282: Gobierno [ej. Ministerio de Agricultura]
A283: seedsupply | B283: relatives_friends | C283: Relatives or friends | D283: Familiares o amigos
A284: seedsupply | B284: other | C284: Other | D284: Otro
A285: seedsupply | B285: dk | C285: DON'T KNOW | D285: NO SABE
A286: seedsupply | B286: ref | C286: REFUSED | D286: NO RESPONDE
A288: harv_unit | B288: 1 | C288: Kilograms [kgs] | D288: Kilogramos [Kgs]
A289: harv_unit | B289: 2 | C289: Tonnes | D289: Toneladas
A290: harv_unit | B290: 3 | C290: Ounces | D290: Onzas
A291: harv_unit | B291: 4 | C291: Pounds | D291: Libras
A292: harv_unit | B292: 5 | C292: Bags | D292: Costales/bolsas
A293: harv_unit | B293: 6 | C293: Boxes | D293: Cajas
A294: harv_unit | B294: 7 | C294: Bundles | D294: Manojos / fajos /bultos
...

Sheet settings
A1: version | B1: default_language | C1: allow_choice_duplicates | D1: style
A2: vM6cWXyHNhR3djPbARkHWi | B2: Spanish (es) | C2: yes | D2: theme-grid no-text-transform

Sheet Crop list
C3: Select top 10 crops | D3: Dataset code | E3: Label (EN) | F3: Label (ES)
C4: x | D4: 1.1 | E4: Rice | F4: Arroz
D5: 1.2 | E5: Wheat | F5: Trigo
D6: 1.3 | E6: Millet | F6: Mijo
C7: x | D7: 1.4 | E7: Sorghum | F7: Sorgo
C8: x | D8: 1.5 | E8: Maize | F8: Maíz
D9: 1.6 | E9: Barley | F9: Cebada
D10: 1.99 | E10: Other Cereal | F10: Otros cereales
C11: x | D11: 2.1 | E11: Cassava | F11: Yuca
D12: 2.2 | E12: Potatoe | F12: Patatas
D13: 2.3 | E13: Sweet Potatoes | F13: Patatas dulces
D14: 2.4 | E14: Yams | F14: Ñames
D15: 2.5 | E15: Carrots | F15: Zanahorias
D16: 2.6 | E16: Cocoyam | F16: Cocoyam
D17: 2.99 | E17: Other tubers | F17: Otros tubérculos
C18: x | D18: 3.1 | E18: Beans | F18: Frijoles
D19: 3.2 | E19: Lentils | F19: Lentejas
D20: 3.3 | E20: Peas | F20: Guisantes
D21: 3.4 | E21: Soybeans | F21: Soja
D22: 3.5 | E22: Chickpeas | F22: Garbanzos
D23: 3.6 | E23: Fava beans | F23: Habas
D24: 3.7 | E24: Broad beans | F24: Habas
D25: 3.99 | E25: Other pulses | F25: Otras legumbres
D26: 4.1 | E26: Cabbage | F26: Coles
D27: 4.2 | E27: Lettuce | F27: Lechuga
D28: 4.3 | E28: Spinach-Amaranth | F28: Espinacas-amaranto
D29: 4.4 | E29: Cassava leaves | F29: Hojas de yuca/mandioca
D30: 4.5 | E30: Potatoe leaves | F30: Hojas de patata
... D47: 5.99 | E47: Other non leafy vegs | F47: Otras verduras
C48: x | D48: 6.1 | E48: Orange | F48: Naranja
D49: 6.2 | E49: Lemon | F49: Limón
D50: 6.3 | E50: Grapefruit | F50: Pomelo
D51: 6.4 | E51: Mandarins/clementines | F51: Mandarinas
D52: 6.99 | E52: Other citrus fruit | F52: Otros cítricos
D53: 7.1 | E53: Sweet Banana | F53: Plátano dulce / bananas
C54: x | D54: 7.2 | E54: Plantains | F54: Plátano
D55: 7.3 | E55: Papaya | F55: Papaya
D56: 7.4 | E56: Mango | F56: Mango
D57: 7.5 | E57: Guava | F57: Guayaba
D58: 7.6 | E58: Pineapple | F58: Piña
D59: 7.7 | E59: Avocado | F59: Aguacate
D60: 7.8 | E60: Water Melon | F60: Sandías
D61: 7.9 | E61: Dates | F61: Dátiles
D62: 7.101 | E62: Figs | F62: Higos
D63: 7.11 | E63: Grapes | F63: Uvas
D64: 7.12 | E64: Olives | F64: Aceitunas
D65: 7.13 | E65: Apple | F65: Manzanas
D66: 7.14 | E66: Apricot | F66: Albaricoques
... D71: 7.99 | E71: Other fruit | F71: Otras frutas
C72: x | D72: 8.1 | E72: Coconuts | F72: Coco
D73: 8.2 | E73: Groundnut/peanut | F73: Cacahuates/maní
D74: 8.3 | E74: Cashew Nut | F74: Anacardos
D75: 8.4 | E75: Kola Nut | F75: Nuez de cola
D76: 8.5 | E76: Sesame | F76: Sésamo
D77: 8.6 | E77: Bambara nut | F77: Nuez de bambara
D78: 8.7 | E78: Almond | F78: Almendra
D79: 8.8 | E79: Walnut | F79: Nuez
D80: 8.99 | E80: Other nuts | F80: Otros frutos secos
D81: 9.1 | E81: Cocoa | F81: Cacao
C82: x | D82: 9.2 | E82: Coffee | F82: Café
D83: 9.3 | E83: Tea | F83: Té
C84: x | D84: 9.4 | E84: Sugarcane | F84: Caña de azúcar
D85: 9.5 | E85: Sunflower | F85: Girasol (plantas o semillas)
D86: 9.99 | E86: Other food cash crop | F86: Otros cultivos comerciales alimentarios
D87: 10.1 | E87: Cotton | F87: Algodón
D88: 10.2 | E88: Rubber | F88: Caucho
D89: 10.3 | E89: Jute | F89: Yute
D90: 10.4 | E90: Fodder | F90: Forraje
D91: 10.5 | E91: Tobacco | F91: Tabaco
D92: 10.6 | E92: Qat | F92: Qat
D93: 10.99 | E93: Other non-food cash crop | F93: Otros cultivos comerciales no alimentarios

Sheet Additional information
C2: Original | D2: Replacement (EN) | E2: Replacement (ES) | F2: Comment (ES) | G2: Comment (EN) | H2: Exemple (ES) | I2: Example(EN)
B3: FOR CORE QUESTIONS . (Mandatory to fill out) . | C3: phone number | D3: 70****** | E3: 70****** | F3: Escriba un número de teléfono de su país en el formato típico, por ejemplo 77******* [por favor, utilice exactamente el número de caracteres que se encuentran en un número de teléfono]. | G3: Type a phone number from your country in typical format, e.g. 77******* [please use exactly the number of characters that are found in a phone number]. | H3: 070****** | I3: 070******
C4: age | D4: 18 | E4: 18 | F4: Edad mínima del encuestado (recomendamos 18 años). | G4: Minimum age of respondent (recommend 18 years old) | H4: 18 | I4: 18
C5: ADMIN1 | D5: Department | E5: Departamento | F5: La primera subdivisión del país, después del nivel nacional; región; provincia; gobernación; etc. Solo una palabra debe ser ingresada - No incluir espacios. | G5: The first subdivision of the country, after national level; region; province; governorate; etc. Only one word should be inputted - Do not include spaces. | H5: departamento | I5: department
C6: ADMIN2 | D6: Municipality | E6: Municipio | F6: La segunda subdivisión del país; distrito; municipio; LGA; etc. Solo una palabra debe ser ingresada - No incluir espacios. | G6: The second subdivision of the country; district; municipality; LGA; etc. Only one word should be inputted - Do not include spaces. | H6: municipio | I6: municipality
C7: reference year | D7: last year | E7: el año pasado | F7: Las preguntas de comparación necesitarán un año de referencia. Seleccione si desea utilizar "el año pasado" o "un año normal" como referencia. Un "año normal" debe referirse a un año promedio de los últimos 5 años; asegúrese de capacitar a los encuestadores en consecuencia. | G7: Comparison questions will need need a reference year. Select whether you want to use "last year" or "a normal year" as a baseline. A "normal year" should refers to an average year from the past 5 years - make sure to train the enumerators accordingly. | H7: un año normal | I7: a normal year
C8: season | D8: First | E8: Primera | F8: Nombre la(s) temporada(s) de cultivo de interés si hay varias temporadas de cultivo en el país (por ejemplo, Meher y Belg en Etiopía, temporada de lluvias/cultivo de recesión por inundación/temporada seca irrigada en el Sahel). Puede referirse a la "última temporada" o "temporada en curso". | G8: Name the crop season(s) of interest if there are several cropping seasons in the country (e.g. Meher and Belg in Ethiopia, rainy season / flood-recession cropping / irrigated dry season in the Sahel). You can refer to the “last season” or “ongoing season". | H8: la temporada de siembra de primera | I8: the first planting season
C9: season phase | D9: Recently Finished | E9: terminado recientemente | F9: Indique la fase de la temporada en el momento de la recogida de datos. Si la cosecha de la temporada aún no ha ocurrido, la pregunta sobre la cosecha del cultivo (crp_harv_change) incluirá la palabra "esperado" (donde se ubica #esperado o nada#). Si la cosecha ha ocurrido, no se insertará "esperado" en la pregunta. | G9: Indicate the phase of the season at the time of data collection. If the harvest from the season has not yet occurred, the question on crop harvest (crp_harv_change) will include the word “expected” (where #expected or nothing# is located). If the harvest has occured, "expected" will not be inserted in the question. | H9: cosecha | I9: Harvesting
C10: local measurement unit | D10: Manzanas | E10: Manzanas | F10: Especifique la unidad de medida local para el area sembrada, que no sean acres, hectáreas, metros cuadrados y pies cuadrados. Si no se necesita otra unidad de medida, deje esta celda en blanco. | G10: Specify the local measurement unit for land size, other than acres, hectares, square meters and square feet. If no other unit of measurement is needed, keep this cell blank. | H10: Manzanas | I10: Manzanas
C11: local measurement unit conversion | D11: 1.43 | E11: 1.43 | F11: Incluir la conversión de la unidad de medida local a hectáreas. En otras palabras, cuántas unidades de medida locales hay en 1 ha. | G11: Include the conversion of the local measurement unit to hectares. In other words, how many local measurement units are in 1 ha. | H11: 1.43 | I11: 1.43
B12: FOR OPTIONAL QUESTIONS . (Fill out if applicable) . | C12: currency | D12: USD | E12: USD | F12: El nombre de la moneda principal utilizada a nivel nacional; USD; quetzales; lempiras; pesos; etc. | G12: The name of the main currency used nationally; USD; Naira; Rial; Pesos; etc. | H12: Pesos | I12: Pesos
C13: MIN AMOUNT | D13: 0 | E13: 0 | F13: El monto mínimo para una fuente de ingresos debe establecerse en 0 o cualquier valor por debajo del cual no sea posible realizar una transacción. Por ejemplo, la moneda/billete más pequeño de una moneda puede valer 1000, en cuyo caso establecería el mínimo en 1000. Proporcione esta entrada en la misma moneda que se especificó anteriormente. Solo se deben ingresar dígitos. | G13: The minimum amount for an income source should be set at 0 or any value below which it is not possible to do a transaction. For example, the smallest coin/banknote in a currency can be 1000, in which case you would set the minimum at 1000. Provide this input in the same currency as specified above. Only digits should be inputted. | H13: 5 | I13: 5
C14: THRESHOLD | D14: 5000 | E14: 5000 | F14: Establezca la cantidad máxima para una fuente de ingresos durante 3 meses. Los encuestadores no podrán ingresar valores por encima de este monto en preguntas relacionadas con montos de ingresos. Usando encuestas representativas anteriores para esta población, puede estimar esta cantidad usando el ingreso medio más cinco (5) desviaciones estándar, a menos que el país tenga una inflación alta. En este último caso, establezca el valor máximo en función del contexto de su país (superior al enfoque propuesto). Proporcione esta entrada en la misma moneda que se especificó anteriormente. Solo se deben ingresar dígitos. | G14: The threshold salary should be calculated to flag outliers (responses that look suspiciously high). Using previous representative surveys for this population, a good estimate is the average plus three (3) standard deviations, which should give the threshold for the 3 or 4% highest income values. Provide this input in the same currency as specified above. Only digits should be inputted. | H14: 1200000 | I14: 1200000
C15: local vegetables | D15: Green chili, onion, pipian, eggplant, carrot, güisquil | E15: Chile verde, cebolla, pipian, berengena, zanahoria, güisquil | F15: Ingrese algunas verduras locales comunes [para usar como ejemplos en el indicador de puntaje de consumo de alimentos]. | G15: Input some common local vegetables [to be used as examples in the food consumption score indicator]. | H15: berenjenas, calabacín, coliflor | I15: eggplants, zucchini, cauliflower
C16: local fruits | D16: mango, apple, jocote, papaya, pineapple, grapes, guava | E16: mango, manzana, jocote, papaya, piña, uvas, guayaba | F16: Ingrese algunas frutas locales comunes [para usar como ejemplos en el indicador de puntaje de consumo de alimentos]. | G16: Input some common local fruits [to be used as examples in the food consumption score indicator]. | H16: manzanas, bananas, naranjas | I16: apples, bananas, oranges
B18: FILL OUT FOR QUESTIONNAIRE DURATION ESTIMATION . | C18: Expected percentage of respondents cultivating crops | D18: 0.35 | E18: 0.35 | F18: Si la encuesta es representativa y no tiene cuotas, escriba la proporción de hogares rurales que cultivan cultivos a nivel nacional, o si la encuesta sigue una ronda anterior con un diseño de muestra idéntico, solo informe el porcentaje de la ronda anterior. Si está utilizando cuotas, calcule la proporción de la cuota sobre el tamaño mínimo de la muestra en el nivel donde se implementa la cuota (por lo que si tiene un tamaño mínimo de muestra por estrato de 110 con una cuota de 100 productores de cultivos, entonces es 100/ 110 = 91% (lo máximo que debe escribir es 100%). | G18: If the survey is representative and has no quotas, write the proportion of rural households cultivating crops at country level, or if the survey follows a previous round with identical sample design, just report the percentage from the previous round. If you are using quotas, calculate the ratio of the quota over the minimum sample size at the level where the quota is implemented (so if you have a minimum sample size per strata of 110 with a quota of 100 crop producers, then it's 100/110 = 91% (the maximum you should write is 100%). | H18: 0.91 | I18: 0.91
C19: Expected percentage of respondents raising livestock | D19: 0.08 | E19: 0.08 | F19: Si la encuesta es representativa y no tiene cuotas, escriba la proporción de hogares rurales que crían animales a nivel nacional, o si la encuesta sigue una ronda anterior con un diseño de muestra idéntico, solo informe el porcentaje de la ronda anterior. Si está utilizando cuotas, calcule la proporción de la cuota sobre el tamaño mínimo de la muestra en el nivel en el que se implementa la cuota (por lo que si tiene un tamaño mínimo de muestra de 110 pero una cuota de 100 productores de ganado, entonces es 100/110 = 91% (lo máximo que debes escribir es 100%) | G19: If the survey is representative and has no quotas, write the proportion of rural households raising livestock at country level, or if the survey follows a previous round with identical sample design, just report the percentage from the previous round. If you are using quotas, calculate the ratio of the quota over the minimum sample size at the level where the quota is implemented (so if you have a minimum sample size of 110 but a quota of 100 livestock producers, then it's 100/110 = 91% (the maximum you should write is 100%) | H19: 0.91 | I19: 0.91
C20: Expected percentage of respondents involved in fishery | D20: 0.01 | E20: 0.01 | F20: Si la encuesta es representativa y no tiene cuotas, escriba la proporción de hogares rurales involucrados en la pesca o la acuicultura; de lo contrario, si está usando cuotas, calcule la proporción de la cuota sobre el tamaño de la muestra en el nivel donde se implementa la cuota. (Entonces, si no ha establecido una cuota y espera tener una proporción representativa de pescadores, simplemente escriba el porcentaje de pescadores en la población a la que se dirige, en el ejemplo a la derecha, 5%) | G20: If the survey is representative and has no quotas, write the proportion of rural households involved in fisheries or aquaculture, otherwise if you are using quotas, calculate the ratio of the quota over the sample size at the level where the quota is implemented. (so if you haven't set a quota, and you expect to have a representative proportion of fishermen, just write the percentage of fishermen in the population you are targeting, in the example to the right, 5%) | H20: 0.05 | I20: 0.05
