Workbook

Sheet survey
A1: GeoPoll Submission Form
A2: FAO - Household Questionnaire | P2: Additional notes
A3: Q # | B3: Q Name | C3: Suggested Qname | D3: English | E3: Length | F3: Burmese | G3: Length | H3: Q Type | I3: Randomize | J3: Conditional | K3: Programming Instructions | L3: Skip Pattern | M3: Codes | N3: Default skip patterns & conditional | O3: Specify skip pattern variable (from blue text) | Q3: Estimated percentage of repondents | T3: Mandatory | X3: Duration (sec) | Y3: Weighted duration | Z3: Core questions only
A4: A. PRESENTATION OF THE SURVEY AND ELIGIBILITY CRITERIA SELECTION | T4: no | Y4: =IF(X4="","",X4*V4) | Z4: =IF(T4="yes",Y4,"")
A5: NA | B5: Optin | D5: Optin | E5: =LEN(D5) -> 5 | F5: Optin | G5: =LEN(F5) -> 5 | H5: Open Ended | I5: NA | J5: NA | K5: Form Type - TextBox | L5: Any Response = phone_number | M5: NA | N5: NA | T5: no | X5: 0 | Y5: =IF(X5="","",X5*Q5) -> 0 | Z5: =IF(T5="yes",Y5,"")
A6: NA | B6: phone_number | C6: phone_number | D6: Input the phone number that you are contacting: | E6: =LEN(D6) -> 48 | G6: =LEN(F6) -> 0 | H6: Open Ended | I6: NA | J6: NA | K6: Form Type - TextBox | L6: Any Response = calldispo | M6: NA | N6: NA | T6: yes | X6: 0 | Y6: =IF(X6="","",X6*Q6) -> 0 | Z6: =IF(T6="yes",Y6,"") -> 0
A7: NA | B7: calldispo | C7: calldispo | D7: Phone number: #CATI_MOBILENUMBER# 1)Someone answers 2)Answering machine 3)No answer 4)Hang up or refusal 5)Call back 6)Under review 7)Disconnected | E7: =LEN(D7) -> 146 | F7: ဖုန်းနံပါတ်- #CATI_MOBILENUMBER# 1)တစ်စုံတစ်ယောက်က ဖြေကြားသည် 2)ဖုန်းဖြေကြားစက် 3)မဖြေကြားပါ 4)ဖုန်းချလိုက်သည် သို့မဟုတ် ဖုန်းကိုင်ရန် ငြင်းဆိုသည် 5)ဖုန်းပြန်ခေါ်သည် 6)သုံးသပ်နေဆဲ 7)ဖုန်းလိုင်း ပြတ်တောက်သွားသည် | G7: =LEN(F7) -> 210 | H7: Single Choice | I7: NA | J7: NA | K7: Form Type - Buttons | L7: 1 = resp_language 2 = AnsweringMachine 3 = NoAnswer 4 = Refusal 5 = WhenCallBack 6 = UnderReview 7 = Disconnected | M7: NA | N7: NA | T7: no | X7: 14.695308 | Y7: =IF(X7="","",X7*Q7) -> 0 | Z7: =IF(T7="yes",Y7,"")
A8: NA | B8: AnsweringMachine | C8: calldispo_answeringmachine | D8: Reached an answering machine. | E8: =LEN(D8) -> 29 | F8: ဖြေကြားစက်မှ ပြန်လည်ဖြေကြားခဲ့သည်။ | G8: =LEN(F8) -> 34 | H8: NA | I8: NA | J8: NA | K8: NA | L8: End Poll AnsweringMachine | M8: NA | N8: NA | T8: no | X8: 0 | Y8: =IF(X8="","",X8*Q8) -> 0 | Z8: =IF(T8="yes",Y8,"")
A9: NA | B9: NoAnswer | C9: calldispo_noanswer | D9: Phone rang and no one answered. | E9: =LEN(D9) -> 31 | F9: ဖုန်းမြည်ပြီး မည်သူမှပြန်မဖြေပါ။ | G9: =LEN(F9) -> 32 | H9: NA | I9: NA | J9: NA | K9: NA | L9: End Poll NoAnswer | M9: NA | N9: NA | T9: no | X9: 0 | Y9: =IF(X9="","",X9*Q9) -> 0 | Z9: =IF(T9="yes",Y9,"")
A10: NA | B10: UnderReview | C10: calldispo_underreview | D10: Case needs review by a supervisor. | E10: =LEN(D10) -> 34 | F10: ကိစ္စရပ်ကို ကြီးကြပ်သူက ပြန်လည်သုံးသပ်ရန်လိုအပ်သည်။ | G10: =LEN(F10) -> 51 | H10: NA | I10: NA | J10: NA | K10: NA | L10: End Poll UnderReview | M10: NA | N10: NA | T10: no | X10: 0 | Y10: =IF(X10="","",X10*Q10) -> 0 | Z10: =IF(T10="yes",Y10,"")
A11: NA | B11: Disconnected | C11: calldispo_disconnected | D11: Phone was disconnected or out of service. | E11: =LEN(D11) -> 41 | F11: ဖုန်းလိုင်း ပြတ်တောက်သွားခဲ့သည် သို့မဟုတ် ဆက်သွယ်မှုဧရိယာပြင်ပဖြစ်နေခဲ့သည်။ | G11: =LEN(F11) -> 75 | H11: NA | I11: NA | J11: NA | K11: NA | L11: End Poll Disconnected | M11: NA | N11: NA | T11: no | X11: 0 | Y11: =IF(X11="","",X11*Q11) -> 0 | Z11: =IF(T11="yes",Y11,"")
A12: NA | B12: resp_language | C12: resp_language | D12: Which language do you wish to proceed with? [OPERATOR: READ ANSWER CHOICES. SINGLE RESPONSE.] 1)Burmese 2)English [FOR TESTING ONLY] | E12: =LEN(D12) -> 134 | F12: မည်သည့်ဘာသာစကားဖြင့် ဆက်လက်လုပ်ဆောင်လိုပါသလဲ။ [အော်ပရေတာ- အဖြေရွေးချယ်မှုများကို ဖတ်ရှုပါ။ တုံ့ပြန်မှုတစ်ခုသာ။] 1) ဗမာဘာသာ 2) အင်္ဂလိပ်ဘာသာ [စမ်းသပ်ရန်အတွက်သာ] | G12: =LEN(F12) -> 161 | H12: Single Choice | I12: NA | J12: NA | K12: Form Type - Buttons | L12: 1 = introduction [English] 2 = introduction [languages & add more if needed] | M12: NA | N12: For any response, go to introduction | P12: Insert most common national languages here [max 4 for translation with GeoPoll]. | T12: no | X12: 3.1032724 | Y12: =IF(X12="","",X12*Q12) -> 0 | Z12: =IF(T12="yes",Y12,"")
A13: NA | B13: introduction | C13: introduction | D13: Hello sir/ma'am, my name is #OPERATOR#, and I am calling from GeoPoll Polling Agency on behalf of the Food and Agriculture Organization of the United Nations [FAO] and the World Food Programme (WFP). We are conducting a survey on household livelihoods and the ability to access food in your area. I would like to ask you some questions about your household. The survey usually takes 20/25 minutes to complete. Any information that you provide will be kept strictly confidential, only used for the purpose of the survey and will not be shown to other people. Your voluntary participation in the outcome of this interview is NOT IN ANY WAY linked to your personal chance of receiving any assistance. This is voluntary and you can choose not to answer any or all of the questions if you want. However, we hope that you will participate since your views are important. You will receive #TOPUP#! of communication credit as an incentive for the participation of the survey. Please note that this call may be recorded for quality purposes. Do you have any questions? [OPERATOR: ADDRESS QUESTIONS FROM RESPONDENT, IF ANY.] 1)CONTINUE | E13: =LEN(D13) -> 1133 | F13: မင်္ဂလာပါခင်ဗျာ၊ ကျွန်တော့်နာမည်ကတော့ #OPERATOR# ဖြစ်ပြီး ကုလသမဂ္ဂ စားနပ်ရိက္ခာနှင့်စိုက်ပျိုးရေးအဖွဲ့ (FAO) နှင့် ကုလသမဂ္ဂ ကမ္ဘာ့စားနပ်ရိက္ခာအစီအစဉ် (WFP) လို့ခေါ်တဲ့ လူသားချင်းစာနာမှုအဖွဲ့အစည်းကိုယ်စား GeoPoll Polling Agency ကနေ ခေါ်ဆိုတာဖြစ်ပါတယ်။ ကျွန်ုပ်တို့ဟာ လူကြီးမင်းရဲ့ဒေသအတွင်း အိမ်ထောင်စုများရဲ့ အစားအစာကိုလက်လှမ်းမှီနိုင်မှု နှင့် အသက်မွေးဝမ်းကြောင်းဆိုင်ရာ များကို လေ့လာနေခြင်းဖြစ်ပါတယ်။ လူကြီးမင်း၏အိမ်ထောင်စုနှင့်ပတ်သက်ပြီး မေးခွန်းအချို့ မေးမြန်းလိုပါတယ်။ မေးခွန်းပြီးမြောက်အောင်ဖြေဆိုရန်အတွက် အချိန် 20 - 25 မိနစ်ခန့် ကြာမြင့်နိုင်ပါတယ်။ လူကြီးမင်းဖော်ပြသော မည်သည့်သတင်းအချက်အလက်ကိုမဆို သေချာစွာ လျှို့ဝှက်ထားမည်ဖြစ်ပြီး လေ့လာမှုများ၏ ရည်ရွယ်ချက်အတွက်သာ အသုံးပြုမည်ဖြစ်ကာ အခြားသူများထံ ပြသမည်မဟုတ်ပါ။ မည်သူမည်ဝါဖြစ်ကြောင်း ခွဲခြားသိရှိနိုင်သည့်အချက်အလက်များကို ကောက်ယူမည်မဟုတ်ပါ။ ယခုလို အင်တာဗျူးမေးမြန်းမှုတွင်ပါဝင်မှုသည် လူကြီးမင်း၏ဆန္ဒအလျောက်ပါဝင်မှုသာဖြစ်ပြီး ဤလေ့လာမှုရလဒ်သည် လူကြီးမင်းတို့အတွက် အကူအညီတစ်စုံတစ်ရာရရှိနိုင်သည့် အကြောင်းအရာနှင့် လုံးဝဆက်စပ်မှုမရှိပါ။ ဒီအင်တာဗျူးဟာ မိမိသဘောဆန္ဒအလျောက်ပါဝင်နိုင်တဲ့ အင်တာဗျူးဖြစ်ပြီး လူကြီးမင်းဆန္ဒ မရှိပါက မေးခွန်းတစ်စုံတစ်ခုကိုဖြစ်စေ သို့မဟုတ် မေးခွန်းအားလုံးကိုဖြစ်စေ မဖြေကြားရန် ရွေးချယ်နိုင်ပါတယ်။ သို့သော် လူကြီးမင်း၏အမြင်များ ၊ ဖြေဆိုမှုများသည် အရေးကြီးသောကြောင့် လူကြီးမင်းအနေနဲ့ ပါဝင်ပေးဖို့ ကျွန်တော်၊ကျွန်မတို့ မျှော်လင့်ပါတယ်။ ယခုလေ့လာမှုတွင်ပါဝင်ခြင်းအတွက် လက်ဆောင်အဖြစ် ဖုန်းခေါ်ဆိုခွင့်ပမာဏ #TOPUP# ရရှိမှာ ဖြစ်ပါတယ်။ အရည် အသွေးကို ထိန်းသိမ်း ရန် ရည်ရွယ်ချက်အတွက် ဤခေါ်ဆိုမှုကို မှတ်တမ်းတင်ထားနိုင်သည်ကို ကျေးဇူးပြု၍ သတိပြုပါ။ လူကြီးမင်းအနေဖြင့် မေးမြန်းလိုသည်များ ရှိပါသလား။ [အော်ပရေတာ- ဖြေဆိုသူထံမှ မေးခွန်းများရှိပါက ၎င်းတို့ကို ဖြေဆိုပါ။] 1) ရှေ့ဆက်ရန် | G13: =LEN(F13) -> 1652 | H13: Single Choice | I13: NA | J13: NA | K13: Form Type - Buttons | L13: 1 = Agree | M13: NA | N13: For any response, go to Agree | P13: Set the amount of incentive here, if any. | T13: no | X13: 37.418449 | Y13: =IF(X13="","",X13*Q13) -> 0 | Z13: =IF(T13="yes",Y13,"")
A14: NA | B14: Agree | C14: resp_agree | D14: Are you interested in participating in this survey? [OPERATOR: SINGLE RESPONSE] 1)Yes 2)Not now but another time in the week 3)No | E14: =LEN(D14) -> 134 | F14: ဤစစ်တမ်းတွင်ပါဝင်ရန် စိတ်ဝင်စားပါသလား။ [အော်ပရေတာ- တုံ့ပြန်မှုတစ်ခုသာ] 1)ဟုတ် 2)ယခုစိတ်မဝင်စားသေးသော်လည်း တစ်ပတ်အတွင်း စစ်တမ်းနောက်တစ်ကြိမ်ကျင်းပသောအခါ ပါဝင်မည် 3)စိတ်မဝင်စားပါ | G14: =LEN(F14) -> 181 | H14: StartRecording | I14: NA | J14: NA | K14: Form Type - Buttons | L14: 1 = resp_firstname 2 = WhenCallBack 3 = resp_refusalwhy | M14: NA | N14: if Agree = 1, go to resp_firstname if Agree = 2, go to WhenCallBack if Agree = 3, go to resp_refusalwhy | Q14: 1 | T14: no | X14: 3.8059516 | Y14: =IF(X14="","",X14*Q14) -> 3.8059516 | Z14: =IF(T14="yes",Y14,"")
A15: NA | B15: resp_refusalwhy | C15: resp_refusalwhy | D15: Please let us know why you have REFUSED to take the survey. [OPERATOR: SINGLE RESPONSE] 1)Not interested 2)Do not want to be recorded 3)Other [specify] | E15: =LEN(D15) -> 153 | F15: စစ်တမ်းဖြေဆိုရန် အဘယ်ကြောင့်ငြင်းဆန်သည်ကို ကျွန်ုပ်တို့အား အသိပေးပါ။ [အော်ပရေတာ- တုံ့ပြန်မှုတစ်ခုသာ] 1)စိတ်မဝင်စားသောကြောင့် 2)မှတ်တမ်းတင်ခြင်း ကို မပြုလုပ်ချင်​သော​ကြောင့် 3)အခြား [အသေးစိတ်ဖော်ပြပါ] | G15: =LEN(F15) -> 201 | H15: Open Ended - Single Choice | I15: NA | J15: NA | K15: Form Type - RadioList | L15: Any Response = Refusal | M15: NA | N15: For any response, go to Refusal | Q15: 1 | T15: no | X15: 0 | Y15: =IF(X15="","",X15*Q15) -> 0 | Z15: =IF(T15="yes",Y15,"")
A16: NA | B16: WhenCallBack | C16: resp_whencallback | D16: When would it be a good time to call you back? [RECORD HH/MM/DD/MM OF CALLBACK] | E16: =LEN(D16) -> 80 | F16: လူကြီးမင်းအား မည်သည့်အချိန်တွင် ပြန်လည်ခေါ်ဆိုရန် အဆင်ပြေပါသလဲ။ [ပြန်လည်ခေါ်ဆိုမှု မှတ်တမ်း နာရီ /မိနစ် /ရက်/လ] | G16: =LEN(F16) -> 112 | H16: Open Ended | I16: NA | J16: NA | K16: Form Type - TextBox IsCallBackDemographic | L16: Any Response = CallbackMessageEN | M16: NA | N16: For any response, go to CallbackMessageEN | Q16: 1 | T16: no | X16: 0 | Y16: =IF(X16="","",X16*Q16) -> 0 | Z16: =IF(T16="yes",Y16,"")
A17: NA | B17: CallbackMessageEN | C17: callbackmessage_en | D17: Thank you, we will call you back at {WhenCallBack} you requested. Thank you again and have a great day! [OPERATOR: ENTER CALL NOTES BELOW, WHO YOU SPOKE TO AND WHAT THEY SAID] | E17: =LEN(D17) -> 176 | F17: ကျေးဇူးတင်ပါတယ်။ လူကြီးမင်းတောင်းဆိုသော {WhenCallBack} တွင် ဖုန်းပြန်လည်ခေါ်ဆိုပါမယ်။ ကျေးဇူးထပ်မံတင်ရှိပါတယ်။ သာယာတဲ့နေ့လေးဖြစ်ပါစေ။ [အော်ပရေတာ- ဖုန်းခေါ်ဆိုမှုမှတ်တမ်းများကို အောက်တွင် ဖြည့်သွင်းပါ၊ သင်နှင့်စကားပြောဆိုခဲ့သူများနှင့် ၎င်းတို့ပြောဆိုခဲ့သည်များ] | G17: =LEN(F17) -> 262 | H17: Open Ended | I17: NA | J17: NA | K17: Form Type - TextBox | L17: Any Response = End poll callback | M17: NA | N17: NA | Q17: 1 | T17: no | X17: 0 | Y17: =IF(X17="","",X17*Q17) -> 0 | Z17: =IF(T17="yes",Y17,"")
A18: NA | B18: Ineligible | C18: NA | D18: You are ineligible for this survey. Thank you for your time and please look out for future surveys! | E18: =LEN(D18) -> 99 | F18: လူကြီးမင်းသည် ဤစစ်တမ်းအတွက် အရည်အချင်းမပြည့်မီပါ။ လူကြီးမင်း၏အချိန်ပေးမှုအတွက် ကျေးဇူးတင်ရှိပြီး နောင်တွင်လည်း GeoPoll စစ်တမ်းများကို ဖြေကြားပေးစေလိုပါတယ်။ ပိုမိုသိရှိလိုပါက GeoPoll.com သို့ ဝင်ရောက်ကြည့်ရှုပါ | G18: =LEN(F18) -> 209 | H18: NA | I18: NA | J18: NA | K18: NA | L18: End Poll Ineligible | M18: NA | N18: NA | Q18: 1 | T18: no | X18: 0 | Y18: =IF(X18="","",X18*Q18) -> 0 | Z18: =IF(T18="yes",Y18,"")
A19: NA | B19: Refusal | C19: NA | D19: Thank you for your time, you will be removed from today's survey. | E19: =LEN(D19) -> 65 | F19: လူကြီးမင်း၏အချိန်ပေးမှုအတွက် ကျေးဇူးတင်ပါတယ်၊ လူကြီးမင်းအား ယနေ့စစ်တမ်းမှ ဖယ်ထုတ်သွားမှာဖြစ်ပါတယ်။ | G19: =LEN(F19) -> 98 | H19: NA | I19: NA | J19: NA | K19: NA | L19: End poll declined | M19: NA | N19: NA | Q19: 1 | T19: no | X19: 0 | Y19: =IF(X19="","",X19*Q19) -> 0 | Z19: =IF(T19="yes",Y19,"")
A20: B. GENERAL INFORMATION & ELIGIBILITY CRITERIA | Y20: =IF(X20="","",X20*Q20) | Z20: =IF(T20="yes",Y20,"")
A21: 1 | B21: resp_age | C21: resp_age | D21: How old are you? [OPERATOR: RECORD AGE IN NUMBER OF YEARS. ROUND UP TO NEAREST WHOLE NUMBER. IF THE RESPONDENT GIVES BIRTH YEAR, REPEAT THE QUESTION. ENTER 00 FOR DON'T KNOW.] | E21: =LEN(D21) -> 177 | F21: အသက်ဘယ်လောက်ပါလဲ။ [အော်ပရေတာ- အသက်ကို နှစ်အရေအတွက်ဖြင့်မှတ်တမ်းတင်ပါ။ အနီးစပ်ဆုံးကိန်းပြည့်ကို ယူပါ။ အကယ်၍ ဖြေဆိုသူသည် မွေးဖွားသည့်ခုနှစ်ကိုပြောပါက မေးခွန်းကိုပြန်မေးပါ။ မသိပါဟု ဖြေဆိုပါက 00 ဟု ဖြည့်သွင်းပါ။] | G21: =LEN(F21) -> 210 | H21: Range | I21: NA | J21: NA | K21: Form Type - TextBox | L21: 0-17 = Ineligible 18-100 = resp_gender 00 = Ineligible | M21: NA | N21: Only respondents from 18-100 will be eligible for the survey. | Q21: =1 -> 1 | T21: yes | X21: 9.8907185 | Y21: =IF(X21="","",X21*Q21) -> 9.8907185 | Z21: =IF(T21="yes",Y21,"") -> 9.8907185
A22: =A21+1 -> 2 | B22: resp_gender | C22: resp_gender | D22: What is the gender of the respondent? [OPERATOR: DO NOT ASK THIS QUESTION OUT LOUD. LISTEN TO THE VOICE AND SELECT THE GENDER.] 1)Male 2)Female 3)DON'T KNOW 4)REFUSED | E22: =LEN(D22) -> 168 | F22: ဖြေဆိုသူသည် ကျား သို့မဟုတ် မ ဖြစ်ပါသလား။ [အော်ပရေတာ- ထိုမေးခွန်းကို မမေးပါနှင့်။ အသံကိုနားထောင်ပြီး မှန်ကန်သောအကွက်တွင် အမှတ်ခြစ်ပါ။] 1)အမျိုးသား 2)အမျိုးသမီး 3)မသိပါ 4)ဖြေဆိုရန် ငြင်းဆန်သည် | G22: =LEN(F22) -> 192 | H22: Single Choice | I22: NA | J22: NA | K22: Form Type - Buttons | L22: 1-4 = phone_number_conf | M22: NA | N22: For any response, go to phone_number_conf | Q22: =1 -> 1 | T22: yes | X22: 1.7156482 | Y22: =IF(X22="","",X22*Q22) -> 1.7156482 | Z22: =IF(T22="yes",Y22,"") -> 1.7156482
A23: 3 | B23: hh_admin1 | C23: hh_admin1 | D23: Currently, in which State/Region does your household reside? [OPERATOR: SINGLE SELECTION.] [HINT: HOUSEHOLD CONSISTS OF ALL MEMBERS LIVING TOGETHER, SHARING RESOURCES & EATING FROM THE SAME POT.] 1)AYEYARWADY 2)BAGO 3)CHIN 4)KACHIN 5)KAYAH 6)KAYIN 7)MAGWAY 8)MANDALAY 9)MON 10)NAY PYI TAW 11)RAKHINE 12)SAGAING 13)SHAN 14)TANINTHARYI 15)YANGON 16)DON'T KNOW 17)REFUSED | E23: =LEN(D23) -> 371 | F23: လက်ရှိအချိန်၌ လူကြီးမင်း၏အိမ်ထောင်စုသည် မည်သည့်ပြည်နယ်/တိုင်းဒေသကြီးတွင် နေထိုင်သနည်း။ [အော်ပရေတာ- ရွေးချယ်မှုတစ်ခုသာ။] [အရိပ်အမြွက် - အိမ်ထောင်စုတွင် အတူတကွနေထိုင်ကာ ရင်းမြစ်များကို မျှဝေသုံးစွဲပြီး တစ်အိုးတည်းစားသောက်သော မိသားစုဝင်များအားလုံး ပါဝင်သည်။] 1) ဧရာဝတီ 2) ပဲခူး 3) ချင်း 4) ကချင် 5) ကယား 6) ကရင် 7) မကွေး 8) မန္တလေး 9) မွန် 10) နေပြည်တော် 11) ရခိုင် 12) စစ်ကိုင်း 13) ရှမ်း 14) တနင်္သာရီ 15) ရန်ကုန် 16) မသိပါ 17) ဖြေဆိုရန် ငြင်းဆန်သည် | G23: =LEN(F23) -> 451 | H23: Single Choice | I23: NA | J23: NA | K23: Form Type - Buttons IsDemographic - ADM1 | L23: 1 = o_hh_admin3_1 2 = o_hh_admin3_2 3 = o_hh_admin3_3 4 = o_hh_admin3_4 5 = o_hh_admin3_5 6 = o_hh_admin3_6 7 = o_hh_admin3_7 8 = o_hh_admin3_8 9 = o_hh_admin3_9 10 = Ineligible 11 = o_hh_admin3_11 12 = o_hh_admin3_12 13 = o_hh_admin3_13 14 = o_hh_admin3_14 15 = o_hh_admin3_15 16,17 = Ineligible | M23: NA | N23: The administrative information will be updated by GeoPoll based on the sample design document and the administrative boundaries provided by the dashboard team after the questionnaire validation. | Q23: =1 -> 1 | T23: yes | X23: 13.957259 | Y23: =IF(X23="","",X23*Q23) -> 13.957259 | Z23: =IF(T23="yes",Y23,"") -> 13.957259
B24: o_hh_admin3_1 | C24: o_hh_admin3 | D24: Currently, in which Township does your household reside? [OPERATOR: SINGLE RESPONSE.] 1)BOGALE 2)DANUBYU 3)DEDAYE 4)EINME 5)HINTHADA 6)INGAPU 7)KANGYIDAUNT 8)KYAIKLAT 9)KYANGIN 10)KYAUNGGON 11)KYONPYAW 12)LABUTTA 13)LEMYETHNA 14)MAUBIN 15)MAWLAMYINEGYUN 16)MYANAUNG 17)MYAUNGMYA 18)NGAPUDAW 19)NYAUNGDON 20)PANTANAW 21)PATHEIN 22)PYAPON 23)THABAUNG 24)WAKEMA 25)YEGYI 26)ZALUN 27)DON'T KNOW 28)REFUSED | E24: =LEN(D24) -> 403 | F24: လက်ရှိအချိန်တွင် လူကြီးမင်း၏အိမ်ထောင်စုသည် မည်သည့်မြို့နယ်၌ နေထိုင်ပါသနည်း။ [အော်ပရေတာ- တုံ့ပြန်မှုတစ်ခုသာ။] 1)ဘိုကလေး 2)ဓနုဖြူ 3)ဒေးဒရဲ 4)အိမ်မဲ 5)ဟင်္သာတ 6)အင်္ဂပူ 7)ကန်ကြီးထောင့် 8)ကျိုက်လတ် 9)ကြံခင်း 10)ကျောင်းကုန်း 11)ကျုံပျော် 12)လပွတ္တာ 13)လေးမျက်နှာ 14)မအူပင် 15)မော်လမြိုင်ကျွန်း 16)မြန်အောင် 17)မြောင်းမြ 18)ငပုတော 19)ညောင်တုန်း 20)ပန်းတနော် 21)ပုသိမ် 22)ဖျာပုံ 23)သာပေါင်း 24)ဝါးခယ်မ 25)ရေကြည် 26)ဇလွန် 27)မသိပါ 28)ဖြေဆိုရန် ငြင်းဆန်သည် | G24: =LEN(F24) -> 449 | H24: Single Choice | I24: NA | J24: NA | K24: Form Type - Dropdown IsDemographic - ADM3 | L24: 1-26 = quotareached 27-28 = quotareached
B25: o_hh_admin3_2 | C25: o_hh_admin3 | D25: Currently, in which Township does your household reside? [OPERATOR: SINGLE RESPONSE.] 1)BAGO 2)THANATPIN 3)KAWA 4)WAW 5)NYAUNGLEBIN 6)KYAUKTAGA 7)DAIK-U 8)SHWEGYIN 9)TAUNGOO 10)YEDASHE 11)KYAUKKYI 12)PHYU 13)OKTWIN 14)HTANTABIN 15)PYAY 16)PAUKKHAUNG 17)PADAUNG 18)PAUNGDE 19)THEGON 20)SHWEDAUNG 21)THAYARWADY 22)LETPADAN 23)MINHLA 24)OKPHO 25)ZIGON 26)NATTALIN 27)MONYO 28)GYOBINGAUK 29)DON'T KNOW 30)REFUSED | E25: =LEN(D25) -> 411 | F25: လက်ရှိအချိန်တွင် လူကြီးမင်း၏အိမ်ထောင်စုသည် မည်သည့်မြို့နယ်၌ နေထိုင်ပါသနည်း။ [အော်ပရေတာ- တုံ့ပြန်မှုတစ်ခုသာ။] 1)ပဲခူး 2)သနပ်ပင် 3)ကဝ 4)ဝေါ 5)ညောင်လေးပင် 6)ကျောက်တံခါး 7)ဒိုက်ဦး 8)ရွှေကျင် 9)တောင်ငူ 10)ရေတာရှည် 11)ကျောက်ကြီး 12)ဖြူး 13)အုတ်တွင်း 14)ထန်းတပင် 15)ပြည် 16)ပေါက်ခေါင်း 17)ပန်းတောင်း 18)ပေါင်းတည် 19)သဲကုန်း 20)ရွှေတောင် 21)သာယာဝတီ 22)လက်ပံတန်း 23)မင်းလှ 24)အုတ်ဖို 25)ဇီးကုန်း 26)နတ်တလင်း 27)မိုးညို 28)ကြို့ပင်ကောက် 29)မသိပါ 30)ဖြေဆိုရန် ငြင်းဆန်သည် | G25: =LEN(F25) -> 462 | H25: Single Choice | I25: NA | J25: NA | K25: Form Type - Dropdown IsDemographic - ADM3 | L25: 1-28 = quotareached 29-30 = quotareached
B26: o_hh_admin3_3 | C26: o_hh_admin3 | D26: Currently, in which Township does your household reside? [OPERATOR: SINGLE RESPONSE.] 1)FALAM 2)HAKHA 3)KANPETLET 4)MATUPI 5)MINDAT 6)PALETWA 7)TEDIM 8)THANTLANG 9)TONZANG 10)DON'T KNOW 11)REFUSED | E26: =LEN(D26) -> 198 | F26: လက်ရှိအချိန်တွင် လူကြီးမင်း၏အိမ်ထောင်စုသည် မည်သည့်မြို့နယ်၌ နေထိုင်ပါသနည်း။ [အော်ပရေတာ- တုံ့ပြန်မှုတစ်ခုသာ။] 1)ဖလမ်း 2)ဟားခါး 3)ကန်ပက်လက် 4)မတူပီ 5)မင်းတပ် 6)ပလက်ဝ 7)တီးတိန် 8)ထန်တလန် 9)တွန်းဇန် 10)မသိပါ 11)ဖြေဆိုရန် ငြင်းဆန်သည် | G26: =LEN(F26) -> 230 | H26: Single Choice | I26: NA | J26: NA | K26: Form Type - Dropdown IsDemographic - ADM3 | L26: 1-9 = quotareached 10-11 = quotareached
B27: o_hh_admin3_4 | C27: o_hh_admin3 | D27: Currently, in which Township does your household reside? [OPERATOR: SINGLE RESPONSE.] 1)BHAMO 2)CHIPWI 3)HPAKANT 4)INJANGYANG 5)KHAUNGLANHPU 6)MACHANBAW 7)MANSI 8)MOGAUNG 9)MOHNYIN 10)MOMAUK 11)MYITKYINA 12)NAWNGMUN 13)PUTA-O 14)SUMPRABUM 15)TANAI 16)TSAWLAW 17)WAINGMAW 18)DON'T KNOW 19)REFUSED | E27: =LEN(D27) -> 297 | F27: လက်ရှိအချိန်တွင် လူကြီးမင်း၏အိမ်ထောင်စုသည် မည်သည့်မြို့နယ်၌ နေထိုင်ပါသနည်း။ [အော်ပရေတာ- တုံ့ပြန်မှုတစ်ခုသာ။] 1)ဗန်းမော် 2)ချီ​ဖွေ 3)ဖားကန့် 4)အင်ဂျန်းယန် 5)ခေါင်လန်ဖူး 6)မချမ်းဘော 7)မံစီ 8)မိုးကောင်း 9)မိုးညှင်း 10)မိုးမောက် 11)မြစ်ကြီးနား 12)နောင်မွန်း 13)ပူတာအို 14)ဆွမ်ပရာဘွမ် 15)တနိုင်း 16)ဆော့လော် 17)ဝိုင်းမော် 18)မသိပါ 19)ဖြေဆိုရန် ငြင်းဆန်သည် | G27: =LEN(F27) -> 352 | H27: Single Choice | I27: NA | J27: NA | K27: Form Type - Dropdown IsDemographic - ADM3 | L27: 1-17 = quotareached 18-19 = quotareached
B28: o_hh_admin3_5 | C28: o_hh_admin3 | D28: Currently, in which Township does your household reside? [OPERATOR: SINGLE RESPONSE.] 1)BAWLAKE 2)DEMOSO 3)HPASAWNG 4)HPRUSO 5)LOIKAW 6)MESE 7)SHADAW 8)DON'T KNOW 9)REFUSED | E28: =LEN(D28) -> 175 | F28: လက်ရှိအချိန်တွင် လူကြီးမင်း၏အိမ်ထောင်စုသည် မည်သည့်မြို့နယ်၌ နေထိုင်ပါသနည်း။ [အော်ပရေတာ- တုံ့ပြန်မှုတစ်ခုသာ။] 1)ဘောလခဲ 2)ဒီးမော့ဆို 3)ဖားဆောင်း 4)ဖရူဆို 5)လွိုင်ကော် 6)မယ်စဲ 7)ရှားတော 8)မသိပါ 9)ဖြေဆိုရန် ငြင်းဆန်သည် | G28: =LEN(F28) -> 216 | H28: Single Choice | I28: NA | J28: NA | K28: Form Type - Dropdown IsDemographic - ADM3 | L28: 1-7 = quotareached 8-9 = quotareached
B29: o_hh_admin3_6 | C29: o_hh_admin3 | D29: Currently, in which Township does your household reside? [OPERATOR: SINGLE RESPONSE.] 1)HLAINGBWE 2)HPA-AN 3)HPAPUN 4)KAWKAREIK 5)KYAINSEIKGYI 6)MYAWADDY 7)THANDAUNGGYI 8)DON'T KNOW 9)REFUSED | E29: =LEN(D29) -> 193 | F29: လက်ရှိအချိန်တွင် လူကြီးမင်း၏အိမ်ထောင်စုသည် မည်သည့်မြို့နယ်၌ နေထိုင်ပါသနည်း။ [အော်ပရေတာ- တုံ့ပြန်မှုတစ်ခုသာ။] 1)လှိုင်းဘွဲ့ 2)ဘားအံ 3)ဖာပွန် 4)ကော့ကရိတ် 5)ကြာအင်းဆိပ်ကြီး 6)မြဝတီ 7)သံတောင်ကြီး 8)မသိပါ 9)ဖြေဆိုရန် ငြင်းဆန်သည် | G29: =LEN(F29) -> 225 | H29: Single Choice | I29: NA | J29: NA | K29: Form Type - Dropdown IsDemographic - ADM3 | L29: 1-7 = quotareached 8-9 = quotareached
B30: o_hh_admin3_7 | C30: o_hh_admin3 | D30: Currently, in which Township does your household reside? [OPERATOR: SINGLE RESPONSE.] 1)AUNGLAN 2)CHAUK 3)GANGAW 4)KAMMA 5)MAGWAY 6)MINBU 7)MINDON 8)MINHLA 9)MYAING 10)MYOTHIT 11)NATMAUK 12)NGAPE 13)PAKOKKU 14)PAUK 15)PWINTBYU 16)SALIN 17)SAW 18)SEIKPHYU 19)SIDOKTAYA 20)SINBAUNGWE 21)TAUNGDWINGYI 22)THAYET 23)TILIN 24)YENANGYAUNG 25)YESAGYO 26)DON'T KNOW 27)REFUSED | E30: =LEN(D30) -> 370 | F30: လက်ရှိအချိန်တွင် လူကြီးမင်း၏အိမ်ထောင်စုသည် မည်သည့်မြို့နယ်၌ နေထိုင်ပါသနည်း။ [အော်ပရေတာ- တုံ့ပြန်မှုတစ်ခုသာ။] 1)အောင်လံ 2)ချောက် 3)ဂန့်ဂေါ 4)ကံမ 5)မကွေး 6) မင်းဘူး 7)မင်းတုန်း 8)မင်းလှ 9)မြိုင် 10) မြို့သစ် 11)နတ်မောက် 12)ငဖဲ 13)ပခုက္ကူ 14)ပေါက် 15)ပွင့်ဖြူ 16)စလင်း 17)ဆော 18)ဆိပ်ဖြူ 19)စေတုတ္ထရာ 20)ဆင်ပေါင်ဝဲ 21)တောင်တွင်းကြီး 22)သရက် 23)ထီးလင်း 24)ရေနံချောင်း 25)ရေစကြို 26)မသိပါ 27)ဖြေဆိုရန် ငြင်းဆန်သည် | G30: =LEN(F30) -> 409 | H30: Single Choice | I30: NA | J30: NA | K30: Form Type - Dropdown IsDemographic - ADM3 | L30: 1-25 = quotareached 26-27 = quotareached
B31: o_hh_admin3_8 | C31: o_hh_admin3 | D31: Currently, in which Township does your household reside? [OPERATOR: SINGLE RESPONSE.] 1)KYAUKSE 2)PATHEINGYI 3)CHANAYETHAZAN 4)AUNGMYAYTHAZAN 5)YAMETHIN 6)MADAYA 7)THABEIKKYIN 8)MAHAAUNGMYAY 9)AMARAPURA 10)PYINOOLWIN 11)SINTGAING 12)CHANMYATHAZI 13)THAZI 14)TADA-U 15)MOGOKE 16)PYIGYITAGON 17)PYAWBWE 18)NYAUNG-U 19)MEIKTILA 20)MAHLAING 21)TAUNGTHA 22)MYITTHA 23)MYINGYAN 24)NATOGYI 25)SINGU 26)NGAZUN 27)KYAUKPADAUNG 28)WUNDWIN 29)DON'T KNOW 30)REFUSEDD | E31: =LEN(D31) -> 457 | F31: လက်ရှိအချိန်တွင် လူကြီးမင်း၏အိမ်ထောင်စုသည် မည်သည့်မြို့နယ်၌ နေထိုင်ပါသနည်း။ [အော်ပရေတာ- တုံ့ပြန်မှုတစ်ခုသာ။] 1)ကျောက်ဆည် 2)ပုသိမ်ကြီး 3)ချမ်းအေးသာစံ 4)အောင်မြေသာစံ 5)ရမည်းသင်း 6)မတ္တရာ 7)သပိတ်ကျင်း 8)မဟာအောင်မြေ 9)အမရပူရ 10)ပြင်ဦးလွင် 11)စဉ့်ကိုင် 12)ချမ်းမြသာစည် 13)သာစည် 14)တံတားဦး 15)မိုးကုတ် 16)ပြည်ကြီးတံခွန် 17)ပျော်ဘွယ် 18)ညောင်ဦး 19)မိတ္ထီလာ 20)မလှိုင် 21)တောင်သာ 22)မြစ်သား 23)မြင်းခြံ 24)နွားထိုးကြီး 25)စဉ့်ကူး 26)ငါန်းဇွန် 27)ကျောက်ပန်းတောင်း 28)ဝမ်းတွင်း 29)မသိပါ 30)ဖြေဆိုရန် ငြင်းဆန်သည် | G31: =LEN(F31) -> 505 | H31: Single Choice | I31: NA | J31: NA | K31: Form Type - Dropdown IsDemographic - ADM3 | L31: 1-28 = quotareached 29-30 = quotareached
B32: o_hh_admin3_9 | C32: o_hh_admin3 | D32: Currently, in which Township does your household reside? [OPERATOR: SINGLE RESPONSE.] 1)BILIN 2)CHAUNGZON 3)KYAIKMARAW 4)KYAIKTO 5)MAWLAMYINE 6)MUDON 7)PAUNG 8)THANBYUZAYAT 9)THATON 10)YE 11)DON'T KNOW 12)REFUSED | E32: =LEN(D32) -> 215 | F32: လက်ရှိအချိန်တွင် လူကြီးမင်း၏အိမ်ထောင်စုသည် မည်သည့်မြို့နယ်၌ နေထိုင်ပါသနည်း။ [အော်ပရေတာ- တုံ့ပြန်မှုတစ်ခုသာ။] 1)ဘီးလင်း 2)ချောင်းဆုံ 3)ကျိုက်မရော 4)ကျိုက်ထို 5)မော်လမြိုင် 6)မုဒုံ 7)ပေါင် 8)သံဖြူဇရပ် 9)သထုံ 10)ရေး 11)မသိပါ 12)ဖြေဆိုရန် ငြင်းဆန်သည် | G32: =LEN(F32) -> 248 | H32: Single Choice | I32: NA | J32: NA | K32: Form Type - Dropdown IsDemographic - ADM3 | L32: 1-10 = quotareached 11-12 = quotareached
B33: o_hh_admin3_11 | C33: o_hh_admin3 | D33: Currently, in which Township does your household reside? [OPERATOR: SINGLE RESPONSE.] 1)ANN 2)BUTHIDAUNG 3)GWA 4)KYAUKPYU 5)KYAUKTAW 6)MAUNGDAW 7)MINBYA 8)MRAUK-U 9)MUNAUNG 10)MYEBON 11)PAUKTAW 12)PONNAGYUN 13)RAMREE 14)RATHEDAUNG 15)SITTWE 16)THANDWE 17)TOUNGUP 18)DON'T KNOW 19)REFUSED | E33: =LEN(D33) -> 289 | F33: လက်ရှိအချိန်တွင် လူကြီးမင်း၏အိမ်ထောင်စုသည် မည်သည့်မြို့နယ်၌ နေထိုင်ပါသနည်း။ [အော်ပရေတာ- တုံ့ပြန်မှုတစ်ခုသာ။] 1)အမ်း 2)ဘူးသီးတောင် 3)ဂွ 4)ကျောက်ဖြူ 5)ကျောက်တော် 6)မောင်တော 7)မင်းပြား 8)မြောက်ဦး 9)မာန်အောင် 10)မြေပုံ 11)ပေါက်တော 12)ပုဏ္ဏားကျွန်း 13)ရမ်းဗြဲ 14)ရသေ့တောင် 15)စစ်တွေ 16)သံတွဲ 17)တောင်ကုတ် 18)မသိပါ 19)ဖြေဆိုရန် ငြင်းဆန်သည် | G33: =LEN(F33) -> 335 | H33: Single Choice | I33: NA | J33: NA | K33: Form Type - Dropdown IsDemographic - ADM3 | L33: 1-17 = quotareached 18-19 = quotareached
B34: o_hh_admin3_12 | C34: o_hh_admin3 | D34: Currently, in which Township does your household reside? [OPERATOR: SINGLE RESPONSE.] 1)SAGAING 2)MYINMU 3)MYAUNG 4)SHWEBO 5)KHIN-U 6)WETLET 7)KANBALU 8)KYUNHLA 9)YE-U 10)TABAYIN 11)TAZE 12)MONYWA 13)BUDALIN 14)AYADAW 15)CHAUNG-U 16)YINMARBIN 17)KANI 18)SALINGYI 19)PALE 20)KATHA 21)INDAW 22)TIGYAING 23)BANMAUK 24)KAWLIN 25)WUNTHO 26)PINLEBU 27)KALE 28)KALEWA 29)MINGIN 30)TAMU 31)MAWLAIK 32)PAUNGBYIN 33)HKAMTI 34)HOMALIN 35)LAY SHI 36)LAHE 37)NANYUN 38)DON'T KNOW 39)REFUSED | E34: =LEN(D34) -> 479 | F34: လက်ရှိအချိန်တွင် လူကြီးမင်း၏အိမ်ထောင်စုသည် မည်သည့်မြို့နယ်၌ နေထိုင်ပါသနည်း။ [အော်ပရေတာ- တုံ့ပြန်မှုတစ်ခုသာ။] 1)စစ်ကိုင်း 2)မြင်းမူ 3)မြောင် 4)ရွှေဘို 5)ခင်ဦး 6)ဝက်လက် 7)ကန့်ဘလူ 8)ကျွန်းလှ 9)ရေဦး 10)ဒီပဲယင်း 11)တန့်ဆည် 12)မုံရွာ 13)ဘုတလင် 14)အရာတော် 15)ချောင်းဦး 16)ယင်းမာပင် 17)ကနီ 18)ဆားလင်းကြီး 19)ပုလဲ 20)ကသာ 21)အင်းတော် 22)ထီးချိုင့် 23)ဗန်းမောက် 24)ကောလင်း 25)ဝန်းသို 26)ပင်လည်ဘူး 27)ကလေး 28)ကလေးဝ 29)မင်းကင်း 30)တမူး 31)မော်လိုက် 32)ဖောင်းပြင် 33)ခန္တီး 34)ဟုမ္မလင်း 35)လေရှီး 36)လဟယ် 37)နန်းယွန်း 38)မသိပါ 39)ဖြေဆိုရန် ငြင်းဆန်သည် | G34: =LEN(F34) -> 539 | H34: Single Choice | I34: NA | J34: NA | K34: Form Type - Dropdown IsDemographic - ADM3 | L34: 1-37 = quotareached 38-39 = quotareached
B35: o_hh_admin3_13 | C35: o_hh_admin3 | D35: Currently, in which Township does your household reside? [OPERATOR: SINGLE RESPONSE.] 1)TAUNGGYI 2)NYAUNGSHWE 3)HOPONG 4)HSIHSENG 5)KALAW 6)PINDAYA 7)YWANGAN 8)LAWKSAWK 9)PINLAUNG 10)PEKON 11)LOILEN 12)LAIHKA 13)NANSANG 14)KUNHING 15)KYETHI 16)MONGKAING 17)MONGHSU 18)LANGKHO 19)MONGNAI 20)MAWKMAI 21)MONGPAN 22)LASHIO 23)HSENI 24)MONGYAI 25)TANGYAN 26)PANGSANG 27)NARPHAN 28)PANGWAUN 29)MONGMAO 30)MUSE 31)NAMHKAN 32)KUTKAI 33)KYAUKME 34)NAWNGHKIO 35)HSIPAW 36)NAMTU 37)NAMHSAN 38)MONGMIT 39)MABEIN 40)MANTON 41)KUNLONG 42)HOPANG 43)LAUKKAING 44)KONKYAN 45)MATMAN 46)KENGTUNG 47)MONGKHET 48)MONGYANG 49)MONGLA 50)MONGHSAT 51)MONGPING 52)MONGTON 53)TACHILEIK 54)MONGHPYAK 55)MONGYAWNG 56)DON'T KNOW 57)REFUSED | E35: =LEN(D35) -> 711 | F35: လက်ရှိအချိန်တွင် လူကြီးမင်း၏အိမ်ထောင်စုသည် မည်သည့်မြို့နယ်၌ နေထိုင်ပါသနည်း။ [အော်ပရေတာ- တုံ့ပြန်မှုတစ်ခုသာ။] 1)တောင်ကြီး 2)ညောင်ရွှေ 3)ဟိုပုံး 4)ဆီဆိုင် 5)ကလော 6)ပင်းတယ 7)ရွာငံ 8)ရပ်စောက် 9)ပင်လောင်း 10)ဖယ်ခုံ 11)လွိုင်လင် 12)လဲချား 13)နမ့်စန် 14)ကွန်ဟိန်း 15)ကျေးသီး 16)မိုင်းကိုင် 17)မိုင်းရှူး 18)လင်းခေး 19)မိုးနဲ 20)မောက်မယ် 21)မိုင်းပန် 22)လားရှိုး 23)သိန္နီ 24)မိုင်းရယ် 25)တန့်ယန်း 26)ပန်ဆန်း (ပန်ခမ်း) 27)နားဖန်း 28)ပန်ဝိုင် 29)မိုင်းမော 30)မူဆယ် 31)နမ့်ခမ်း 32)ကွတ်ခိုင် 33)ကျောက်မဲ 34)နောင်ချို 35)သီပေါ 36)နမ္မတူ 37)နမ့်ဆန် 38)မိုးမိတ် 39)မဘိမ်း 40)မန်တုံ 41)ကွမ်းလုံ 42)ဟိုပန် 43)လောက်ကိုင် 44)ကုန်းကြမ်း 45)မက်မန်း 46)ကျိုင်းတုံ 47)မိုင်းခတ် 48)မိုင်းယန်း 49)မိုင်းလား 50)မိုင်းဆတ် 51)မိုင်းပျဉ်း 52)မိုင်းတုံ 53)တာချီလိတ် 54)မိုင်းဖြတ် 55)မိုင်းယောင်း 56)မသိပါ 57)ဖြေဆိုရန် ငြင်းဆန်သည် | G35: =LEN(F35) -> 802 | H35: Single Choice | I35: NA | J35: NA | K35: Form Type - Dropdown IsDemographic - ADM3 | L35: 1-55 = quotareached 56-57 = quotareached
... B37: o_hh_admin3_15 | C37: o_hh_admin3 | D37: Currently, in which Township does your household reside? [OPERATOR: SINGLE RESPONSE.] 1)AHLONE 2)BAHAN 3)BOTAHTAUNG 4)COCOKYUN 5)DAGON 6)DAGON MYOTHIT [EAST] 7)DAGON MYOTHIT [NORTH] 8)DAGON MYOTHIT [SEIKKAN] 9)DAGON MYOTHIT [SOUTH] 10)DALA 11)DAWBON 12)HLAING 13)HLAINGTHARYA [EAST] 14)HLAINGTHARYA [WEST] 15)HLEGU 16)HMAWBI 17)HTANTABIN 18)INSEIN 19)KAMARYUT 20)KAWHMU 21)KAYAN 22)KUNGYANGON 23)KYAUKTADA 24)KYAUKTAN 25)KYEEMYINDAING 26)LANMADAW 27)LATHA 28)MAYANGONE 29)MINGALADON 30)MINGALARTAUNGNYUNT 31)NORTH OKKALAPA 32)PABEDAN 33)PAZUNDAUNG 34)SANCHAUNG 35)SEIKGYIKANAUNGTO 36)SHWEPYITHAR 37)SOUTH OKKALAPA 38)TAIKKYI 39)TAMWE 40)THAKETA 41)THANLYIN 42)THINGANGYUN 43)THONGWA 44)TWANTAY 45)YANKIN 46)DON'T KNOW 47)REFUSED | E37: =LEN(D37) -> 731 | F37: လက်ရှိအချိန်တွင် လူကြီးမင်း၏အိမ်ထောင်စုသည် မည်သည့်မြို့နယ်၌ နေထိုင်ပါသနည်း။ [အော်ပရေတာ- တုံ့ပြန်မှုတစ်ခုသာ။] 1)အလုံ 2)ဗဟန်း 3)ဗိုလ်တထောင် 4)ကိုကိုးကျွန်း 5)ဒဂုံ 6)ဒဂုံမြို့သစ် [အရှေ့ပိုင်း] 7)ဒဂုံမြို့သစ် [မြောက်ပိုင်း] 8)ဒဂုံမြို့သစ် [ဆိပ်ကမ်း] 9)ဒဂုံမြို့သစ် [တောင်ပိုင်း] 10)ဒလ 11)ဒေါပုံ 12)လှိုင် 13)လှိုင်သာယာ [အရှေ့ပိုင်း] 14)လှိုင်သာယာ [အနောက်ပိုင်း] 15)လှည်းကူး 16)မှော်ဘီ 17)ထန်းတပင် 18)အင်းစိန် 19)ကမာရွတ် 20)ကော့မှုး 21)ခရမ်း 22)ကွမ်းခြံကုန်း 23)ကျောက်တံတား 24)ကျောက်တန်း 25)ကြည့်မြင်တိုင် 26)လမ်းမတော် 27)လသာ 28)မရမ်းကုန်း 29)မင်္ဂလာဒုံ 30)မင်္ဂလာတောင်ညွန့် 31)မြောက်ဥက္ကလာပ 32)ပန်းဘဲတန်း 33)ပုဇွန်တောင် 34)စမ်းချောင်း 35)ဆိပ်ကြီး/ခနောင်တို 36)ရွှေပြည်သာ 37)တောင်ဥက္ကလာပ 38)တိုက်ကြီး 39)တာမွေ 40)သာကေတ 41)သန်လျင် 42)သင်္ဃန်းကျွန်း 43)သုံးခွ 44)တွံတေး 45)ရန်ကင်း 46)မသိပါ 47)ဖြေဆိုရန် ငြင်းဆန်သည် | G37: =LEN(F37) -> 809 | H37: Single Choice | I37: NA | J37: NA | K37: Form Type - Dropdown IsDemographic - ADM3 | L37: 1-4 = quotareached 5 = Ineligible 6-7 = quotareached 8 = Ineligible 9-22 = quotareached 23 = Ineligible 24-26 = quotareached 27 = Ineligible 28-45 = quotareached 46-47 = Ineligible
B38: quotareached | C38: quotareached | D38: [OPERATOR: DO NOT READ. ANSWER QUESTION BELOW.] THIS RESPONDENT REPORTED THEY LIVE IN: {ADM1} {ADM3} 1)THE GOAL FOR THIS LOCATION HAS BEEN ACHIEVED - END SURVEY 2)THE GOAL FOR THIS LOCATION IS OPEN - CONTINUE SURVEY | E38: =LEN(D38) -> 218 | F38: [အော်ပရေတာ- မဖတ်ပါနှင့်။ အောက်ပါမေးခွန်းကို ဖြေဆိုပါ။] ဖြေဆိုသူသည် ၎င်းတို့နေထိုင်ရာအရပ်ကို ဤသို့ဖော်ပြခဲ့သည် {ADM1} {ADM3} 1)ဤနေရာအတွက် ရည်မှန်းချက် အောင်မြင်ခဲ့ပြီဖြစ်ပါသည်- စစ်တမ်းအား အဆုံးသတ်ရန် 2)ဤနေရာအတွက် ရည်မှန်းချက်ကို ကြိုးပမ်းနိုင်ဆဲဖြစ်ပါသည်- စစ်တမ်းအား ရှေ့ဆက်ရန် | G38: =LEN(F38) -> 279 | H38: Single Choice | I38: NA | J38: NA | K38: Form Type - Buttons | L38: 1 = End Poll Quota Reached 2 = hh_agricactivity | M38: NA
B39: RuralUrban | D39: Are you living in a rural or urban area? [OPERATOR: CHOOSE ONLY ONE OPTION] 1)RURAL [Village] AREA 2)URBAN [Ward] AREA 3)DON'T KNOW 4)REFUSED | F39: လူကြီးမင်းသည် ကျေးလက်ဒေသ သို့မဟုတ် မြို့ပြဒေသတွင် နေထိုင်ပါသလား။ [အော်ပရေတာ- ရွေးချယ်မှုတစ်ခုသာ ရွေးချယ်ပါ] 1)ကျေးလက်ဒေသ [သို့မတုတ်] ရွာ 2)မြို့ပြဒေသ [သို့မဟုတ်] ရပ်ကွက် 3)မသိပါ 4)ဖြေဆိုရန် ငြင်းဆန်သည် | G39: =LEN(F39) -> 203 | H39: Single Choice | Q39: =1 -> 1 | Y39: =IF(X39="","",X39*Q39) | Z39: =IF(T39="yes",Y39,"")
A40: =#REF!+1 -> #REF! | B40: hh_agricactivity | C40: hh_agricactivity | D40: Has anybody in your household produced crops or livestock for household consumption or for sale in the past 12 months, including household members currently away for transhumance? [OPERATOR: SINGLE RESPONSE. THIS IS THE MAIN SCREENING QUESTION.] [HINT FOR PROBING: Do you cultivate any plants to sale or consume? Do you raise any animals with the intent of selling or consuming them or their products like meat, milk, wool or leather? Is one of your household member currently away with cattle or other animals for transhumance?] 1)Yes - crop production 2)Yes - livestock production 3)Yes - both crop and livestock production 4)No 5)DON'T KNOW 6)REFUSED | E40: =LEN(D40) -> 658 | F40: ရွှေ့ပြောင်းမွေးမြူရေးအတွက် လက်ရှိ အဝေးတွင်ရောက်ရှိနေသော အိမ်ထောင်စုပါ မိသားစုဝင်အပါအဝင် လူကြီးမင်း၏အိမ်ထောင်စုထဲမှ တစ်ဦးတစ်ယောက်သည် လွန်ခဲ့သော 12 လအတွင်း အိမ်ထောင်စု စားသောက်ရန် သို့မဟုတ် ရောင်းချရန်အတွက် ကောက်ပဲသီးနှံများ စိုက်ပျိုးရေး သို့မဟုတ် မွေးမြူရေး လုပ်ကိုင်ခဲ့ပါသလား။ [အော်ပရေတာ- တုံ့ပြန်မှုတစ်ခုသာ။ ဤသည်မှာ အဓိကအကဲဖြတ်မေးခွန်းဖြစ်သည်။ ဖြေဆိုသူသည် မဖြေမနေရ ဖြေဆိုရမည်ဖြစ်သည်။ ရွှေ့ပြောင်းမွေးမြူးရေးအကြောင်း မေးမြန်းရန် မမေ့ပါနှင့်။] [အရိပ်အမြွက် - အိမ်ထောင်စုတွင် အတူတကွနေထိုင်ကာ ရင်းမြစ်များကို မျှဝေသုံးစွဲပြီး တစ်အိုးတည်းစားသောက်သော မိသားစုဝင်များအားလုံး ပါဝင်သည်။] [ငါးဖမ်းခြင်း/ငါးမွေးမြူရေးလုပ်ငန်းသည် တိရစ္ဆာန်မွေးမြူရေးမဟုတ်ပါ။ ရောင်းချရန်မဟုတ်သောပန်းစိုက်ပျိုးခြင်းသည် သီးနှံထုတ်လုပ်ခြင်းမဟုတ်ပါ] 1)လုပ်ကိုင်ပါသည် - ကောက်ပဲသီးနှံ စိုက်ပျိုးထုတ်လုပ်ရေး 2)လုပ်ကိုင်ပါသည် - မွေးမြူရေး 3)လုပ်ကိုင်ပါသည်- ကောက်ပဲသီးနှံစိုက်ပျိုးရေးနှင့် မွေးမြူရေးလုပ်ငန်းနှစ်ခုလုံး 4)မလုပ်ကိုင်ပါ 5)မသိပါ 6)ဖြေဆိုရန် ငြင်းဆန်သည် | G40: =LEN(F40) -> 934 | H40: Single Choice | I40: NA | J40: NA | K40: Form Type - Buttons | L40: 1 = hh_agricactivity_Check1 2 = hh_agricactivity_Check2 3 = hh_agricactivity_Check3 4 = hh_agricactivity_Check4 5-6 = Ineligible | M40: NA | N40: if hh_agricactivity = 1-4, go to resp_id. Otherwise, the respondent is ineligible. | Q40: =1 -> 1 | T40: yes | X40: 24.410839 | Y40: =IF(X40="","",X40*Q40) -> 24.410839 | Z40: =IF(T40="yes",Y40,"") -> 24.410839
B41: hh_agricactivity_Check1 | C41: hh_agricactivity_Check1 | D41: You reported that you or someone in your household participated in crop production activities , but no one cared for animals/livestock for household income/consumption at any time during the past 12 months (1 year). Is this correct? [OPERATOR: IF YES, SELECT "NEXT". IF NO, GO BACK TO THE PREVIOUS QUESTION AND CORRECT THE ANSWER.] [FISHING/AQUACULTURE IS NOT LIVESTOCK PRODUCTION. FLOWER PLANTING IS NOT CROP PRODUCTION] 1)NEXT | E41: =LEN(D41) -> 431 | F41: သင် သို့မဟုတ် သင့်အိမ်ထောင်စုရှိ တစ်စုံတစ်ဦးသည် လွန်ခဲ့သည့် 12 လ (1 နှစ်) အတွင်း ကောက်ပဲသီးနှံစိုက်ပျိုးရေး လုပ်ကိုင်ခဲ့သော်လည်း သင်၏ အိမ်ထောင်စု၏ ဝင်ငွေ/စားသုံးမှုအတွက် တိရစ္ဆာန်မွေးမြူရေးကို မပြုလုပ်ခဲ့ပါဟု ဖြေဆိုခဲ့သည်။ ထိုအချက်သည် မှန်ကန်ပါသလား။ [အော်ပရေတာ- ဟုတ်ပါက၊ "နောက်တစ်ခု" ကို ရွေးပါ။ မဟုတ်ပါက၊ ယခင်မေးခွန်းသို့ ပြန်သွားပြီး အဖြေကို ပြင်ပါ။] [ငါးဖမ်းခြင်း/ငါးမွေးမြူရေးလုပ်ငန်းသည် တိရစ္ဆာန်မွေးမြူရေးမဟုတ်ပါ။ ရောင်းချရန်မဟုတ်သောပန်းစိုက်ပျိုးခြင်းသည် သီးနှံထုတ်လုပ်ခြင်းမဟုတ်ပါ] 1) နောက်တစ်ခု | G41: =LEN(F41) -> 526 | H41: Single Choice | I41: NA | J41: NA | K41: Form Type - Buttons | L41: 1=resp_id
B42: hh_agricactivity_Check2 | C42: hh_agricactivity_Check2 | D42: You reported that you or someone in your household participated in livestock activities, but no one cultivated plants for household income/consumption at any time during the past 12 months (1 year). Is this correct? [OPERATOR: IF YES, SELECT "NEXT". IF NO, GO BACK TO THE PREVIOUS QUESTION AND CORRECT THE ANSWER.] [FISHING/AQUACULTURE IS NOT LIVESTOCK PRODUCTION. FLOWER PLANTING IS NOT CROP PRODUCTION] 1)NEXT | E42: =LEN(D42) -> 414 | F42: သင် သို့မဟုတ် သင့်အိမ်ထောင်စုရှိ တစ်စုံတစ်ဦးသည် လွန်ခဲ့သည့် 12 လ (1 နှစ်) အတွင်း တိရစ္ဆာန်မွေးမြူရေး လုပ်ကိုင်ခဲ့သော်လည်း သင်၏ အိမ်ထောင်စု၏ ဝင်ငွေ/စားသုံးမှုအတွက် ကောက်ပဲသီးနှံစိုက်ပျိုးရေးကို မပြုလုပ်ခဲ့ပါဟု ဖြေဆိုခဲ့သည်။ ထိုအချက်သည် မှန်ကန်ပါသလား။ [အော်ပရေတာ- ဟုတ်ပါက၊ "နောက်တစ်ခု" ကို ရွေးပါ။ မဟုတ်ပါက၊ ယခင်မေးခွန်းသို့ ပြန်သွားပြီး အဖြေကို ပြင်ပါ။] [ငါးဖမ်းခြင်း/ငါးမွေးမြူရေးလုပ်ငန်းသည် တိရစ္ဆာန်မွေးမြူရေးမဟုတ်ပါ။ ရောင်းချရန်မဟုတ်သောပန်းစိုက်ပျိုးခြင်းသည် သီးနှံထုတ်လုပ်ခြင်းမဟုတ်ပါ] 1) နောက်တစ်ခု | G42: =LEN(F42) -> 524 | H42: Single Choice | I42: NA | J42: NA | K42: Form Type - Buttons | L42: 1=resp_id
B43: hh_agricactivity_Check3 | C43: hh_agricactivity_Check3 | D43: You reported that you or someone in your household participated in crop production and livestock activities for household income or consumption during the past 12 months (1 year). Is this correct? [OPERATOR: IF YES, SELECT "NEXT". IF NO, GO BACK TO THE PREVIOUS QUESTION AND CORRECT THE ANSWER.] [FISHING/AQUACULTURE IS NOT LIVESTOCK PRODUCTION. FLOWER PLANTING IS NOT CROP PRODUCTION] 1)NEXT | E43: =LEN(D43) -> 395 | F43: သင် သို့မဟုတ် သင့်အိမ်ထောင်စုရှိ တစ်စုံတစ်ဦးသည် လွန်ခဲ့သည့် 12 လ (1 နှစ်) အတွင်း သင်၏ အိမ်ထောင်စု၏ ဝင်ငွေ/စားသုံးမှုအတွက် တိရစ္ဆာန်မွေးမြူရေးရော ကောက်ပဲသီးနှံစိုက်ပျိုးရေးကိုပါ ပြုလုပ်ခဲ့သည်ဟု ဖြေဆိုခဲ့သည်။ ထိုအချက်သည် မှန်ကန်ပါသလား။ [အော်ပရေတာ- ဟုတ်ပါက၊ "နောက်တစ်ခု" ကို ရွေးပါ။ မဟုတ်ပါက၊ ယခင်မေးခွန်းသို့ ပြန်သွားပြီး အဖြေကို ပြင်ပါ။] [ငါးဖမ်းခြင်း/ငါးမွေးမြူရေးလုပ်ငန်းသည် တိရစ္ဆာန်မွေးမြူရေးမဟုတ်ပါ။ ရောင်းချရန်မဟုတ်သောပန်းစိုက်ပျိုးခြင်းသည် သီးနှံထုတ်လုပ်ခြင်းမဟုတ်ပါ] 1) နောက်တစ်ခု | G43: =LEN(F43) -> 541 | H43: Single Choice | I43: NA | J43: NA | K43: Form Type - Buttons | L43: 1=resp_id
B44: hh_agricactivity_Check4 | C44: hh_agricactivity_Check4 | D44: You reported that no one in your household participated in livestock activities or cultivated plants for household income /consumption at any time during the past 12 months (1 year). Is this correct? [OPERATOR: IF YES, SELECT "NEXT". IF NO, GO BACK TO THE PREVIOUS QUESTION AND CORRECT THE ANSWER.] [FISHING/AQUACULTURE IS NOT LIVESTOCK PRODUCTION. FLOWER PLANTING IS NOT CROP PRODUCTION] 1)NEXT | E44: =LEN(D44) -> 400 | F44: သင် သို့မဟုတ် သင့်အိမ်ထောင်စုရှိ တစ်စုံတစ်ဦးသည် လွန်ခဲ့သည့် 12 လ (1 နှစ်) အတွင်း သင်၏ အိမ်ထောင်စု၏ ဝင်ငွေ/စားသုံးမှုအတွက် တိရစ္ဆာန်မွေးမြူရေးရော ကောက်ပဲသီးနှံစိုက်ပျိုးရေးကိုပါ မပြုလုပ်ခဲ့ပါဟု ဖြေဆိုခဲ့သည်။ ထိုအချက်သည် မှန်ကန်ပါသလား။ [အော်ပရေတာ- ဟုတ်ပါက၊ "နောက်တစ်ခု" ကို ရွေးပါ။ မဟုတ်ပါက၊ ယခင်မေးခွန်းသို့ ပြန်သွားပြီး အဖြေကို ပြင်ပါ။] [ငါးဖမ်းခြင်း/ငါးမွေးမြူရေးလုပ်ငန်းသည် တိရစ္ဆာန်မွေးမြူရေးမဟုတ်ပါ။ ရောင်းချရန်မဟုတ်သောပန်းစိုက်ပျိုးခြင်းသည် သီးနှံထုတ်လုပ်ခြင်းမဟုတ်ပါ] 1) နောက်တစ်ခု | G44: =LEN(F44) -> 541 | H44: Single Choice | I44: NA | J44: NA | K44: Form Type - Buttons | L44: 1=resp_id
A45: =A40+1 -> #REF! | B45: resp_id | C45: resp_id | D45: Are you the head of household? [OPERATOR: SINGLE RESPONSE.] 1)Yes 2)No 3)DON'T KNOW 4)REFUSED | E45: =LEN(D45) -> 97 | G45: =LEN(F45) -> 0 | H45: Single Choice | I45: NA | J45: NA | K45: Form Type - Buttons | L45: 1 = hh_education 2-4 = hh_gender | M45: NA | N45: if resp_id = 1, go to hh_education. Otherwise, go to hh_gender. | Q45: 1 | T45: yes | X45: 10.5 | Y45: =IF(X45="","",X45*Q45) -> 10.5 | Z45: =IF(T45="yes",Y45,"") -> 10.5
A46: =A45+1 -> #REF! | B46: hh_gender | C46: hh_gender | D46: Is the head of your household male or female? [OPERATOR: SINGLE RESPONSE.] 1)Male 2)Female 3)DON'T KNOW 4)REFUSED | E46: =LEN(D46) -> 116 | F46: လူကြီးမင်းအိမ်ထောင်စု၏ အိမ်ထောင်ဦးစီးသည် အမျိုးသား သို့မဟုတ် အမျိုးသမီးပါလား။ [အော်ပရေတာ- တုံ့ပြန်မှုတစ်ခုသာ။] 1)အမျိုးသား 2)အမျိုးသမီး 3)မသိပါ 4)ဖြေဆိုရန် ငြင်းဆန်သည် | G46: =LEN(F46) -> 170 | H46: Single Choice | I46: NA | J46: NA | K46: Form Type - Buttons | L46: 1-4 = hh_education | M46: NA | N46: if hh_gender = 1-4, go to hh_education. | Q46: =1 -> 1 | T46: yes | X46: 10.504534 | Y46: =IF(X46="","",X46*Q46) -> 10.504534 | Z46: =IF(T46="yes",Y46,"") -> 10.504534
A47: =A185+1 -> #REF! | B47: hh_size | C47: hh_size | D47: How many people are part of the household? [OPERATOR: RECORD NUMBER OF MEMBERS IN HOUSEHOLD. ENTER 88 FOR DON'T KNOW & 99 FOR REFUSED.] [HINT: TO BE A PART OF THE SAME HOUSEHOLD, MEMBERS MUST LIVE UNDER THE SAME ROOF, SHARE THE SAME RESOURCES & EAT FROM THE SAME POT.] | E47: =LEN(D47) -> 269 | F47: အိမ်ထောင်စုမှာ လူဦးရေ ဘယ်လောက်ရှိပါသလဲ။ [အရိပ်အမြွက် - အိမ်ထောင်စုတွင် အတူတကွနေထိုင်ကာ ရင်းမြစ်များကို မျှဝေသုံးစွဲပြီး တစ်အိုးတည်းစားသောက်သော မိသားစုဝင်များအားလုံး ပါဝင်သည်။] [အော်ပရေတာ- အိမ်ထောင်စုဝင်အရေအတွက်ကိုမှတ်သားပါ။ မသိပါဟု ဖြေဆိုပါက 88 ဟု ဖြည့်သွင်းပြီး ဖြေဆိုရန် ငြင်းဆန်သည်ကို ရွေးချယ်ပါက 99 ဟု ဖြည့်သွင်းပါ။] | G47: =LEN(F47) -> 322 | H47: Range | I47: NA | J47: NA | K47: Form Type - TextBox | L47: 1-50 = hh_asset_prod 88-88 = hh_asset_prod 99-99 = hh_asset_prod | M47: NA | N47: For any response, go to [next question] | Q47: =1 -> 1 | T47: no | X47: 16.902294 | Y47: =IF(X47="","",X47*Q47) -> 16.902294 | Z47: =IF(T47="yes",Y47,"")
B48: hhsizeconfirm | C48: hhsizeconfirm | D48: These {hh_size} people have lived together and eaten their meals from the same kitchen for 6+ months - and the household size includes yourself, head of household, and any elderly/young children. Is this correct? [HINT: MEMBERS THAT ARE TEMPORARILY AWAY BUT NORMALLY LIVE AND EAT IN THE HOUSEHOLD CAN BE COUNTED. NEWLY MARRIED COUPLES AND NEWBORN BABIES SHOULD ALSO BE COUNTED] [OPERATOR: IF YES, SELECT "NEXT". IF NO, GO BACK TO THE PREVIOUS QUESTION AND CORRECT THE ANSWER. 1)NEXT | E48: =LEN(D48) -> 485 | F48: ဤ {hh_size} လူများသည် 6 လကျော်ကြာ တအိမ်ထဲတွင် အတူတကွနေထိုင်ပြီး မီးဖိုချောင်တစ်ခုတည်းမှ အစားအစာများကို စားခဲ့ကြသည် - ယခုသင်ဖြေဆိုခဲ့သော အိမ်ထောင်စုအရွယ်အစားတွင် သင်ကိုယ်တိုင်၊ အိမ်ထောင်ဦးစီးနှင့် သက်ကြီးရွယ်အို/ကလေးငယ်များ ပါဝင်ပါသည်။ အထက်ပါအချက်များသည် မှန်ပါသလား။ [အရိပ်အမြွက်- ခေတ္တအဝေးရောက်နေသော်လည်း အိမ်ထောင်စုတွင် ပုံမှန်အတူတကွ နေထိုင်စားသောက်သောသူများကိုလည်း အိမ်ထောင်စုဝင်အဖြစ် ကို ရေတွက်နိုင်ပါသည်။ လက်ထပ်ပြီးခါစ ဇနီးမောင်နှံများနှင့် မွေးကင်းစကလေးငယ်များကိုလည်း ထည့်သွင်းရေတွက်သင့်သည်] [အော်ပရေတာ- ဟုတ်ပါက၊ "နောက်တစ်ခု" ကို ရွေးပါ။ မဟုတ်ပါက၊ ယခင်မေးခွန်းသို့ ပြန်သွားပြီး အဖြေကို ပြင်ပါ။ ] 1) နောက်တစ်ခု | G48: =LEN(F48) -> 619 | H48: Single Choice | I48: NA | J48: NA | K48: Form Type - Buttons | L48: 1 = o_HHSize04 | M48: NA
A49: =A47+1 -> #REF! | B49: o_HHSize04 | C49: o_HHSize04 | D49: What is the total number of children aged 0 to 4 years old (0-59 months) in your household? [OPERATOR: RECORD NUMBER GIVEN] | E49: =LEN(D49) -> 124 | F49: လူကြီးမင်း၏အိမ်ထောင်စုတွင် အသက် 0 မှ 4 နှစ်အတွင်း (0-59 လ) ကလေးငယ် မည်မျှရှိပါသလဲ။ [အော်ပရေတာ- ဖော်ပြသော အရေအတွက်ကို မှတ်သားပါ] | G49: =LEN(F49) -> 128 | H49: Range | I49: NA | J49: Send if "hh_size" "Equals" "2-50" if not satisfied go to "o_HHDisability" | K49: Form Type - TextBox Validation Rule: Answer to this question is VALID IF ""hhsize" "GreaterThan" "CurrentAnswer" - Unmatched Response [You have given an answer higher than the number of people in your household. Please provide the correct number of children aged 0 to 4 years old (0-59 months) in your household] [လူကြီးမင်းသည် လူကြီးမင်း၏အိမ်ထောင်စုရှိ လူအရေအတွက်ထက်ပိုသော အဖြေကို ပေးခဲ့သည်။ ကျေးဇူးပြု၍ လူကြီးမင်း၏အိမ်ထောင်စုရှိ အသက် 0 မှ 4 နှစ်အတွင်း [0-59 လ] ကလေးအရေအတွက်အမှန်ကို ဖြေဆိုပါ] | L49: 0-0 = o_HHSize5_15 1-50 = o_HHSize5_15 | P49: GeoPoll: Confirm if we need to add validation rules here. Please note that if we are to add validation rules, we will need to do away with this instruction at hh_size "ENTER 88 FOR DON'T KNOW &99 FOE REFUSED], so as not to interfere with the validations should any of these be selected.
A50: =A49+1 -> #REF! | B50: o_HHSize5_15 | C50: o_HHSize5_15 | D50: What is the total number of members aged 5 to 15 years old in your household? [OPERATOR: RECORD NUMBER GIVEN] | E50: =LEN(D50) -> 110 | F50: လူကြီးမင်း၏အိမ်ထောင်စုတွင် အသက် 5 နှစ် မှ 15 နှစ်အတွင်း ကလေးငယ် မည်မျှရှိပါသလဲ။ [အော်ပရေတာ- ဖော်ပြသော အရေအတွက်ကို မှတ်သားပါ] | G50: =LEN(F50) -> 126 | H50: Range | J50: NA | K50: Form Type - TextBox IsDemographic - o_HHSize5_15 Validation rule: Answer to this question is VALID if "<Expression>hhsize - o_HHSize04" "GreaterThan" "CurrentAnswer" Unmatched Response [You have given an answer higher than the number of people in your household. Please provide the correct number of household members aged 5 to 15 years old in your household] [လူကြီးမင်းသည် လူကြီးမင်း၏အိမ်ထောင်စုရှိ လူအရေအတွက်ထက်ပိုသော အဖြေကို ပေးခဲ့သည်။ ကျေးဇူးပြု၍ လူကြီးမင်း၏အိမ်ထောင်စုရှိ အသက် 5 မှ 15 နှစ်အတွင်း ရေအတွက်အမှန်ကို ဖြေဆိုပါ] | L50: 0-0 = o_HHSize16_59 1-50 = o_HHSize16_59
A51: =A50+1 -> #REF! | B51: o_HHSize16_59 | C51: o_HHSize16_59 | D51: What is the total number of members aged 16 to 59 years old in your household? [OPERATOR: RECORD NUMBER GIVEN] | E51: =LEN(D51) -> 111 | F51: လူကြီးမင်း၏အိမ်ထောင်စုတွင် အသက် 16 နှစ် မှ 59 နှစ်အတွင်း မည်မျှရှိပါသလဲ။ [အော်ပရေတာ- ဖော်ပြသော အရေအတွက်ကို မှတ်သားပါ] | G51: =LEN(F51) -> 119 | H51: Range | J51: NA | K51: Form Type - TextBox Validation rule: Answer to this question is VALID if "<Expression>hhsize - o_HHSize04 - o_HHSize5_15" "GreaterThanOrEqual" "CurrentAnswer" Unmatched Response [You have given an answer higher than the number of people in your household. Please provide the correct number of household members aged 16 to 59 years old in your household] [လူကြီးမင်းသည် လူကြီးမင်း၏အိမ်ထောင်စုရှိ လူအရေအတွက်ထက်ပိုသော အဖြေကို ပေးခဲ့သည်။ ကျေးဇူးပြု၍ လူကြီးမင်း၏အိမ်ထောင်စုရှိ အသက် 16 မှ 59 နှစ်အတွင်း ရေအတွက်အမှန်ကို ဖြေဆိုပါ] | L51: 0-50 = o_HHSize60 | M51: 0-50 = o_HHSize60
A52: =A51+1 -> #REF! | B52: o_HHSize60 | C52: o_HHSize60 | D52: What is the total number of members aged 60 years old and older in your household? [OPERATOR: RECORD NUMBER GIVEN] | E52: =LEN(D52) -> 116 | F52: လူကြီးမင်း၏အိမ်ထောင်စုတွင် အသက် 60 နှစ်နှင့် အထက် မည်မျှရှိပါသလဲ။ [အော်ပရေတာ- ဖော်ပြသော အရေအတွက်ကို မှတ်သားပါ] | G52: =LEN(F52) -> 113 | H52: Range | J52: NA | K52: Form Type - TextBox Validation rule: Answer to this question is VALID if "<Expression>hhsize - o_HHSize04 - o_HHSize5_15 - o_HHSize16_59" "Equals" "CurrentAnswer" Unmatched Response [You have given an answer that does not add up to the total. Please provide the correct number of household members aged 60 years or older in your household] [စုစုပေါင်းနှင့် မပေါင်းနိုင်သော အဖြေတစ်ခုကို သင် ပေးခဲ့သည်။ ကျေးဇူးပြု၍ လူကြီးမင်း၏အိမ်ထောင်စုရှိ အသက် 60 နှစ်နှင့် အထက် အရေအတွက်အမှန်ကို ဖြေဆိုပါ] | L52: 0-50 = o_HHDisability
A53: =A52+1 -> #REF! | B53: o_HHDisability | C53: o_HHDisability | D53: How many members of your household have a disability? Note: to count as a disability the person must have a lot of difficulty or cannot do at all, any of the following: seeing (even if wearing glasses), hearing (even if wearing hearing aids), walking or climbing steps, remembering or concentrating, self-care (such as washing or dressing) or communicating (understanding or being understood). [OPERATOR: RECORD THE NUMBER GIVEN] | E53: =LEN(D53) -> 432 | F53: လူကြီးမင်း၏အိမ်ထောင်စုဝင် မည်မျှသည် မသန်စွမ်း ခံစားနေရပါသလဲ။ မှတ်ချက်- အောက်ပါတို့မှ တစ်ခုခုကို လုပ်ရန် အခက်အခဲများစွာ ရှိခြင်း သို့မဟုတ် လုံးဝမပြုလုပ်နိုင်ခြင်း ဖြစ်မှသာ လူတစ်ဦးအား မသန်စွမ်းမှုအဖြစ်သတ်မှတ်နိုင်ပါသည်။၊ မမြင်နိုင်ခြင်း (မျက်မှန်တပ်ထားသည့်တိုင်)၊ မကြားနိုင်ခြင်း (နားကြားကိရိယာများကို ဝတ်ဆင်ထားသည့်တိုင်)၊ လမ်းမလျှောက်နိုင်ခြင်း သို့မဟုတ် အပေါ်မတက်နိုင်ခြင်း၊ မမှတ်မိနိုင်ခြင်း သို့မဟုတ် အာရုံမစူးစိုက်နိုင်ခြင်း၊ မိမိကိုယ်ကို မစောင့်ရှောက်နိုင်ခြင်း (ဆေးကြောသန့်စင်ခြင်း၊ အဝတ်လဲခြင်း) သို့မဟုတ် ဆက်သွယ်မပြောဆိုနိုင်ခြင်း (နားမလည်ခြင်း သို့မဟုတ် နားလည်အောင်မဆက်သွယ် မပြောဆိုနိုင်ခြင်း)။ [အော်ပရေတာ- ဖော်ပြသော အရေအတွက်ကို မှတ်သားပါ] | G53: =LEN(F53) -> 649 | H53: Range | J53: NA | K53: Form Type - TextBox Validation Rule: Answer to this question is VALID IF "hhsize" "GreaterThanOrEqual" "CurrentAnswer" Unmatched Response [You have given an answer higher than the number of people in your household. Please provide the correct number of members with a disability in your household] [လူကြီးမင်းသည် လူကြီးမင်း၏အိမ်ထောင်စုရှိ လူအရေအတွက်ထက်ပိုသော အဖြေကို ပေးခဲ့သည်။ သင့်အိမ်ထောင်စုရှိ မသန်စွမ်းမှုရှိသော အဖွဲ့ဝင်အရေအတွက်ကို ကျေးဇူးပြု၍ ပေးပါ။] | L53: 0-50 = hh_age | P53: GeoPoll: Same feedback as above.
A54: =#REF!+1 -> #REF! | B54: hh_age | C54: hh_age | D54: How old is the head of household? [OPERATOR: SINGLE RESPONSE.] 1)Under 18 2)18 to 40 3)41 to 65 4)Over 65 5)DON'T KNOW 6)REFUSED | E54: =LEN(D54) -> 133 | F54: အိမ်ထောင်ဦးစီးက အသက်ဘယ်လောက်ပါလဲ။ [အော်ပရေတာ- တုံ့ပြန်မှုတစ်ခုသာ။] 1)အသက် 18 နှစ်အောက် 2)18 နှစ်မှ 40 နှစ် 3)41 နှစ် မှ 65 နှစ် 4)65 နှစ်ကျော် 5)မသိပါ 6)ဖြေဆိုရန် ငြင်းဆန်သည် | G54: =LEN(F54) -> 179 | H54: Single Choice | I54: NA | J54: Send if "hh_size" "Equals" "2-50" if not satisfied go to "hh_education" | K54: Form Type - Buttons | L54: 1-6 = hh_education | M54: NA | N54: For any response, go to [next question] | Q54: =1 -> 1 | T54: no | X54: 7.0248413 | Y54: =IF(X54="","",X54*Q54) -> 7.0248413 | Z54: =IF(T54="yes",Y54,"")
A55: =A46+1 -> #REF! | B55: hh_education | C55: hh_education | D55: What is the educational level attained by the head of household? [OPERATOR: SINGLE RESPONSE.] 1)None or did not complete primary school 2)Completed primary school 3)Completed secondary school 4)Completed higher education [University / College] degree 5)Religious or informal education only 6)DON'T KNOW 7)REFUSED | E55: =LEN(D55) -> 314 | F55: အိမ်ထောင်ဦးစီးရဲ့ ပညာအရည်အချင်းမှာ ဘယ်လိုပါလဲ။ [အော်ပရေတာ- တုံ့ပြန်မှုတစ်ခုသာ။] 1)အတန်းပညာမရှိ သို့မဟုတ် မူလတန်း မပြီးဆုံး 2)မူလတန်း ပြီးဆုံးပြီးပါသည် 3)အလယ်တန်း ပြီးဆုံးပါသည် 4)အဆင့်မြင့်ပညာရေး [တက္ကသိုလ်/ကောလိပ်] ဘွဲ့ ရရှိထားသည် 5)အစ္စလာမ် သို့မဟုတ် အခြားသော ဘာသာရေးကျောင်းပညာရေး 6)မသိပါ 7)ဖြေဆိုရန် ငြင်းဆန်သည် | G55: =LEN(F55) -> 315 | H55: Single Choice | I55: NA | J55: NA | K55: Form Type - Buttons | L55: 1-7 = hh_wealth_water | M55: NA | N55: if hh_education = 1-7, go to hh_wealth. | Q55: =1 -> 1 | T55: yes | X55: 12.421899 | Y55: =IF(X55="","",X55*Q55) -> 12.421899 | Z55: =IF(T55="yes",Y55,"") -> 12.421899
A56: 10 | B56: hh_wealth_water | C56: hh_wealth_water | D56: Where does the water that you drink at home come from? [OPERATOR: SINGLE CHOICE.] 1)Private tap from piped water 2)Public tap 3)Protected well 4)Bottled water 5)Other safe source 6)River 7)Unprotected well 8)Spring water 9)Surface water [e.g. canals, ponds, dams] 10)Other unsafe source 11)DON'T KNOW 12)REFUSED | E56: =LEN(D56) -> 313 | F56: လူကြီးမင်း၏အိမ်ထောင်စုဝင်များအတွက် သောက်သုံးရေ၏ အဓိကအရင်းအမြစ်မှာ အဘယ်နည်း။ [အော်ပရေတာ- ရွေးချယ်မှုတစ်ခုသာ ရွေးချယ်ပါ] ​1)ရေပိုက်မှ ရရှိ​သော သီးသန့် ​ရေပိုက်​ခေါင်း 2)အများသုံး ​ရေပိုက်​ခေါင်း 3)အကာအကွယ်ရှိ​သော ​ရေတွင်း ​​4)ရေဘူး 5)အခြား သန့်ရှင်း​သော ရေ 6)မြစ် 7)အကာအကွယ် မရှိ​သော ​ရေတွင်း 8)စီးဆင်း​နေ​သော ​ရေ 9)တူးမြောင်း​ရေ သို့ ​မြေ​ပေါ်​ရေ 10)အခြား မသန့်ရှင်း ​သော ​ရေ 11)မသိပါ။ 12)ငြင်းဆို | G56: =LEN(F56) -> 398 | H56: Single Choice | I56: NA | J56: NA | K56: Form Type - Buttons | L56: 1-12 =o_con_water | M56: NA | N56: For any response, go to [income_main OR other optional question] | P56: Select wealth indicators based on baseline information available; you can delete those that you do not want to use. If none of these indicators work in the context of your country, other wealth proxies are proposed in the optional questions below. Remember that baseline data will be necessary, and the variable should be defined properly in the "weight_input_table". | Q56: =1 -> 1 | T56: yes | X56: 16.615656 | Y56: =IF(X56="","",X56*Q56) -> 16.615656 | Z56: =IF(T56="yes",Y56,"") -> 16.615656
B57: o_con_water | C57: o_con_water | D57: Has your household's access to water source changed in the past 6 months? If yes, how (open-ended) 1)Yes 2)No 3)DON'T KNOW 4)REFUSED | F57: လွန်ခဲ့သည့် 6 လအတွင်း သင်အိမ်ထောင်စု ၏ ရေအရင်းအမြစ်သည် ပြောင်းလဲသွားပါသလား။ 1) ပြောင်းလဲပါသည်။ 2) မပြောင်းလဲပါ။ 3) မသိပါ။ 4) ငြင်းဆိုခဲ့သည်။ | G57: =LEN(F57) -> 142 | L57: 1-4=o_con_school 1=o_con_water_yes
B58: o_con_water_yes | C58: o_con_water_yes | D58: If yes, how (open-ended) | F58: ပြောင်းလဲပါက မည်သည့်ပြောင်းလဲခဲ့ပါသနည်း။ | G58: =LEN(F58) -> 40
B59: o_con_school | C59: o_con_school | D59: Has your household's access to school or other educational facilities changed in the past 6 months? 1)Yes 2)No 3)Not Applicable 4)REFUSED | F59: လွန်ခဲ့သည့် 6 လအတွင်း သင်အိမ်ထောင်စု ၏ ကျောင်း (သို့) ပညာရေး ဆိုင်ရာ လက်လှမ်းမှီနိုင် မှု သည် ပြောင်းလဲသွားပါသလား။ 1) ပြောင်းလဲပါသည်။ 2) မပြောင်းလဲပါ။ 3) မသိပါ။ 4) ငြင်းဆိုခဲ့သည်။ | L59: 1-4=o_con_health 1=o_con_school_yes
B60: o_con_school_yes | C60: o_con_school_yes | D60: If yes, how (open-ended) | F60: ပြောင်းလဲပါက မည်သည့်ပြောင်းလဲခဲ့ပါသနည်း။
B61: o_con_health | C61: o_con_health | D61: Has your access to health facilities/hospital changed in the past 6 months? If yes, how (open-ended) 1)Yes 2)No 3)DON'T KNOW 4)REFUSED | F61: လွန်ခဲ့သည့် 6 လအတွင်း သင်အိမ်ထောင်စု ၏ ဆေးရုံ (သို့) ကျန်းမာရေးဆိုင်ရာ လက်လှမ်းမှီနိုင် မှုသည် ပြောင်းလဲသွားပါသလား။ 1) ပြောင်းလဲပါသည်။ 2) မပြောင်းလဲပါ။ 3) မသိပါ။ 4) ငြင်းဆိုခဲ့သည်။ | L61: 1-4=o_con_tele 1=o_con_health_yes
B62: o_con_health_yes | C62: o_con_health_yes | D62: If yes, how (open-ended) | F62: ပြောင်းလဲပါက မည်သည့်ပြောင်းလဲခဲ့ပါသနည်း။
B63: o_con_tele | C63: o_con_tele | D63: Has the telephone or internet connection interrupted in the past 6 months? 1)Yes 2)No 3)DON'T KNOW 4)REFUSED | F63: လွန်ခဲ့သော 6 လအတွင်း တယ်လီဖုန်း သို့မဟုတ် အင်တာနက်ချိတ်ဆက်မှု ပြတ်တောက်ဖူးပါသလား။ 1) ဟုတ်ပါသည်။ 2) မဟုတ်ပါ။ 3) မသိပါ။ 4) ငြင်းဆိုခဲ့သည်။ | L63: 1-4=o_hh_wealth_house 1=o_con_tele_yes
B64: o_con_tele_yes | C64: o_con_tele_yes | D64: If yes, how (open-ended) | F64: ပြောင်းလဲပါက မည်သည့်ပြောင်းလဲခဲ့ပါသနည်း။
B65: o_hh_wealth_house | C65: o_hh_wealth_house | D65: What kind of dwelling unit does your household live in? [OPERATOR: SINGLE RESPONSE.] 1)Apartment/condominium 2)Bungalow/brick house 3)Semi-pucca house 4)Wooden house 5)Bamboo House 6)Hut [2-3 years] 7)Hut [1 years] 8)Tent/plastic sheets 9)Substandard shelter / collective shelter [factory/warehouse/garage/shop/worksite/unfinished building] 10)No shelter [sleeping in open] 11)Other [specify] 12)DON'T KNOW 13)REFUSED | F65: သင် သည် မည် သို့သော အဆောက်အဉီး အမျိုး အစားတွင် နေထိုင်ပါသနည်း။ [အော်ပရေတာ- တုံ့ပြန်မှုတစ်ခုသာ။] 1)တိုက်ခန်း/ကွန်ဒို 2)လုံးချင်းတိုက်/အုတ်ဖြင့်ဆောက်ထားသောအိမ် 3)အုတ်ညှပ်အိမ် [အုတ်/သစ်/သံတို့ဖြင့်] 4)သစ်အိမ် 5)ဝါးအိမ် 6)ယာယီတဲ [2-3နှစ်ခန်] 7)ယာယီတဲ [၁ နှစ်ခန်] 8)ပလပ်စတစ်ဖြင့် မိုး ကာထားသော ယာယီတဲ 9)တန်းလျား အတွဲ/စုပေါင်း အဆောက်အဉီး သို့မဟုတ် ပုံစံမကျသော/လူနေရန်ရည်ရွယ် ခြင်း မဟုတ်သော အဆောက်အအုံ[စက်ရုံ/ကုန်လှောင်ရုံ/ကားဂိုထောင်/ဈေးဆိုင်/အလုပ်နေရာ/မပြီးသေးသော အဆောက်အဉီး] 10)အမိုးအကာ မရှိ [အပြင် တွင် နေခြင်း] 11)တစ်ခြား[အသေးစိတ်ဖော်ပြပါ] 12)မသိပါ။ 13)ငြင်းဆို | G65: =LEN(F65) -> 561 | H65: Single Choice | L65: 1-13 = HHIncEarners
A66: C. INCOME SOURCES, LIVELIHOOD AND SHOCKS | Y66: =IF(X66="","",X66*Q66) | Z66: =IF(T66="yes",Y66,"")
B67: HHIncEarners | D67: How many members of your household earned an income in the last 3 months? [OPERATOR: RECORD NUMBER GIVEN] | E67: =LEN(D67) -> 107 | F67: လွန်ခဲ့သော ၃ လ အတွင်း တွင် လူကြီးမင်း၏အိမ်ထောင်စုဝင်မည်မျှသည် ဝင်ငွေရှိနေပါသလဲ။ [အော်ပရေတာ- ဖော်ပြသော အရေအတွက်ကို မှတ်သားပါ] | G67: =LEN(F67) -> 125 | H67: Range | K67: Form Type - TextBox IsDemographic - HHIncEarners Validation Rule: Answer to this question is VALID IF "hhsize" "GreaterThanOrEqual" "CurrentAnswer" - Unmatched Response [You have given an answer higher than the number of people in your household. Please provide the correct number of members that earned an income in the last 3 months in your household] [လူကြီးမင်းသည် လူကြီးမင်း၏အိမ်ထောင်စုရှိ လူအရေအတွက်ထက်ပိုသော အဖြေကို ပေးခဲ့သည်။ ကျေးဇူးပြု၍ လူကြီးမင်း၏အိမ်ထောင်စုရှိ လွန်ခဲ့သော ၃ လ အတွင်းတွင် ဝင်ငွေရရှိသော အိမ်ထောင်စုဝင် အရေအတွက် အမှန်ကို ဖြေဆိုပါ]" | L67: 0-0 = HHIncEarners_year 1-50 = HHIncEarners_year | Q67: =1 -> 1 | Y67: =IF(X67="","",X67*Q67) | Z67: =IF(T67="yes",Y67,"")
B68: HHIncEarners_year | D68: How many members of your household were earning an income in this period one year ago? [OPERATOR: RECORD NUMBER GIVEN] | E68: =LEN(D68) -> 119 | F68: ယခင်နှစ် ခုလို အချိန် တွင် လူကြီးမင်း၏အိမ်ထောင်စုဝင်ဘယ်နှစ်ယောက်တွင် ဝင်ငွေ ရှိ သနည်း။ [အော်ပရေတာ- ဖော်ပြသော အရေအတွက်ကို မှတ်သားပါ] | G68: =LEN(F68) -> 132 | H68: Range | L68: 0-50 = income_main
A69: =A54+1 -> #REF! | B69: income_main | C69: income_main | D69: What was your household's main source of income in the past 3 months? [OPERATOR: SINGLE RESPONSE. REFUSED OPTION SHOULD BE AVOIDED AS MUCH AS POSSIBLE.] 1)Production and sale of staple crops 2)Production and sale of vegetables or fruit 3)Production and sale of cashcrops 4)Production and sale of livestock and livestock products 5)Production and sale of honey or bee products 6)Production and sale of fish 7)Collection and sale of forestry or bush products 8)Agricultural trade EXCLUDING producers [formal or informal] 9)Daily wage on farms and other casual employment in agricultural sector 10)Stable employment in agricultural sector 11)Non-agricultural self-employed or liberal profession / doctor / architect / lawyer / including restaurant 12)Off-farm daily wages and other non-agricultural casual employment 13)Stable employment in non-agricultural sector 14)Public employment 15)Income not derived from work / Charity 16)Income not derived from work / Welfare transfer, pension, humanitarian aid 17)Income not derived from work / Remittances 18)Income not derived from work / Income from other rents 19)No income source in the last 3 months and used exclusively savings / debt 20)DON'T KNOW 20)REFUSED | E69: =LEN(D69) -> 1218 | F69: လွန်ခဲ့သော 3 လအတွင်း လူကြီးမင်းအိမ်ထောင်စု၏ အဓိကဝင်ငွေအရင်းအမြစ်က ဘာပါလဲ။ [အော်ပရေတာ- တုံ့ပြန်မှုတစ်ခုသာ။ ငြင်းဆန်သည့်ရွေးချယ်မှုများကို တတ်နိုင်သမျှ မပြုလုပ်ဘဲ/မရှောင်ရှားဘဲ ဖြေဆိုပေးပါ] 1) နှံစားသီးနှံ ထုတ်လုပ်ရောင်းချခြင်း 2) ဟင်းသီးဟင်းရွက် သို့မဟုတ် သစ်သီးဝလံ ထုတ်လုပ်ရောင်းချခြင်း 3)ငွေပေါ်ကောက်ပဲသီးနှံ ထုတ်လုပ်ရောင်းချခြင်း 4)မွေးမြူရေးနှင့် မွေးမြူရေးလုပ်ငန်းထုတ်ကုန်များ ထုတ်လုပ်ရောင်းချခြင်း 5) ပျားရည်နှင့် အခြားဆက်စပ်ထုတ်ကုန်ပစ္စည်းများ ထုတ်လုပ်ရောင်းချခြင်း 6) ငါးမွေးမြူခြင်းနှင့် ရောင်းချခြင်း 7)သစ်တောထွက် သို့မဟုတ် သစ်ပင်ချုံနွယ်ထွက် ကုန်ပစ္စည်းများ စုဆောင်းခြင်းနှင့်ရောင်းချခြင်း 8)ထုတ်လုပ်သူများမဟုတ်ဘဲ လယ်ယာထုတ်ကုန်ကုန်သွယ်သူများ (အလွတ်သဘော သို့မဟုတ် တရားဝင်) 9)လယ်ယာလုပ်ငန်းမှ နေ့စဉ်လုပ်အားခ ရရှိသောစိုက်ပျိုးရေးကဏ္ဍရှိ အခြားကျပန်းအလုပ်အကိုင် 10)စိုက်ပျိုးရေးကဏ္ဍရှိ အတည်တကျအလုပ်အကိုင် 11)စိုက်ပျိုးရေးမဟုတ်သော ကိုယ်ပိုင်လုပ်ငန်း သို့မဟုတ် ပြည်သူ့အကျိုးပြု ပညာရှင်/ ဆရာဝန်/ ဗိသုကာ/ ရှေ့နေ/ စားသောက်ဆိုင်လုပ်ငန်းအပါအဝင် 12)လယ်ယာပြင်ပနေ့စဉ်လုပ်အားခနှင့် အခြားလယ်ယာမဟုတ်သော ကျပန်းအလုပ်အကိုင် 13)စိုက်ပျိုးရေးကဏ္ဍမဟုတ်သော အတည်တကျအလုပ်အကိုင် 14)အစိုးရအလုပ်အကိုင် 15)အလုပ်မှ ရရှိသော ဝင်ငွေမဟုတ်ပါ/ လှူဒါန်းမှု 16)အလုပ်မှ ရရှိသော ဝင်ငွေမဟုတ်ပါ / လူမှုဖူလုံရေးလွှဲပြောင်းခြင်း / ပင်စင် / လူသားချင်းစာနာမှုအကူအညီများ 17)အလုပ်မှ ရရှိသော ဝင်ငွေမဟုတ်ပါ / ငွေလွှဲခြင်း 18)အလုပ်မှ ရရှိသော ဝင်ငွေမဟုတ်ပါ / အခြားငှားရမ်းခများ 19)လွန်ခဲ့သော 3 လအတွင်း 0င်ငွေအရင်းအမြစ်မရှိဘဲ သီးသန့်စုငွေ သို့ ကြွေးမြီကိုသာ အသုံးပြုသည် 20)မသိပါ 20)ဖြေဆိုရန် ငြင်းဆန်သည် | G69: =LEN(F69) -> 1470 | H69: Single Choice | I69: NA | J69: NA | K69: Form Type - Buttons IsDemographic - income_main | L69: 1-3 = income_main_crop_check 4 = income_main_ls_check 5 = income_main_comp 6 = income_main_fish_check 7-8 = income_main_comp 9 = o_wage_main_amount 10 = income_main_comp 11 = o_income_main_selfemployed 12 = o_wage_main_amount 13-18 = income_main_comp 19-20 = o_Income_total_amount | M69: NA | N69: if options #1-3 selected go to income_main_crop_check if options #4 selected go to income_main_ls_check if options #6 selected go to income_main_fish_check if options #5, 7-18 selected, go to [income_main_comp OR optional question] if options #19-20 selected, go to shock | Q69: =1 -> 1 | T69: yes | X69: 31.888334 | Y69: =IF(X69="","",X69*Q69) -> 31.888334 | Z69: =IF(T69="yes",Y69,"") -> 31.888334
B70: income_main_crop_check | C70: income_main_crop_check | D70: Are the crops that you sell also produced by you or anyone in your household? [OPERATOR: SINGLE RESPONSE.] 1)YES 2)NO 3)DON'T KNOW 4)REFUSED | E70: =LEN(D70) -> 143 | F70: သင်၏ အဓိက ၀င်ငွေအရင်းအမြစ်ဖြစ်သော လယ်ယာထွက်ကုန်များကို ကိုယ်တိုင် (သို့) မိသားစုဝင်တစ်ဦးဦးမှ ထုတ်လုပ် နေပါသလား။ [အော်ပရေတာ- တုံ့ပြန်မှုတစ်ခုသာ။] 1)ဟုတ်သည် 2)မဟုတ်ပါ 3)မသိပါ 4)ငြင်းဆိုသည်။ | G70: =LEN(F70) -> 190 | H70: Single Choice | I70: NA | J70: NA | K70: Form Type - Buttons | L70: 1-4 = income_main_comp | M70: NA | N70: if income_main_crop_check = 1-4, go to [income_main_comp OR optional question] | Q70: =1 -> 1 | T70: yes | X70: 8 | Y70: =IF(X70="","",X70*Q70) -> 8 | Z70: =IF(T70="yes",Y70,"") -> 8
B71: income_main_ls_check | C71: income_main_ls_check | D71: Are the livestock and livestock products that you sell also produced by you or anyone in your household? [OPERATOR: SINGLE RESPONSE.] 1)YES 2)NO 3)DON'T KNOW 4)REFUSED | E71: =LEN(D71) -> 170 | F71: သင်၏ အဓိက ၀င်ငွေအရင်းအမြစ်ဖြစ်သော မွေးမြူရေးထုက်ကုန်များကို ကိုယ်တိုင် (သို့) မိသားစုဝင်တစ်ဦးဦးမှ ထုတ်လုပ် နေပါသလား။။ [အော်ပရေတာ- တုံ့ပြန်မှုတစ်ခုသာ။] 1)ဟုတ်သည် 2)မဟုတ်ပါ 3)မသိပါ 4)ငြင်းဆိုသည်။ | G71: =LEN(F71) -> 196 | H71: Single Choice | I71: NA | J71: NA | K71: Form Type - Buttons | L71: 1-4 = income_main_comp | M71: NA | N71: if income_main_ls_check = 1-4, go to [income_main_comp OR optional question] | Q71: =1 -> 1 | T71: yes | X71: 8 | Y71: =IF(X71="","",X71*Q71) -> 8 | Z71: =IF(T71="yes",Y71,"") -> 8
B72: income_main_fish_check | C72: income_main_fish_check | D72: Are the fish and/or fish products that you sell also captured or harvested by you or anyone in your household? [OPERATOR: SINGLE RESPONSE.] 1)YES 2)NO 3)DON'T KNOW 4)REFUSED | E72: =LEN(D72) -> 176 | F72: သင်၏ အဓိက ၀င်ငွေအရင်းအမြစ်ဖြစ်သော ရေထွက်ကုန်များကို ကိုယ်တိုင် (သို့) မိသားစုဝင်တစ်ဦးဦးမှ ထုတ်လုပ် နေပါသလား။ [အော်ပရေတာ- တုံ့ပြန်မှုတစ်ခုသာ။] 1)ဟုတ်သည် 2)မဟုတ်ပါ 3)မသိပါ 4)ငြင်းဆိုသည်။ | G72: =LEN(F72) -> 187 | H72: Single Choice | I72: NA | J72: NA | K72: Form Type - Buttons | L72: 1-4 = income_main_comp | M72: NA | N72: if income_main_fish_check = 1-4, go to [income_main_comp OR optional question] | Q72: =1 -> 1 | T72: yes | X72: 8 | Y72: =IF(X72="","",X72*Q72) -> 8 | Z72: =IF(T72="yes",Y72,"") -> 8
B73: o_income_main_selfemployed | D73: What type of self-employment / liberal profession? [OPERATOR: SINGLE RESPONSE.] 1)Liberal profession [doctor/architect/layer...] 2)Petty trade/selling on streets [own business/self or with family] 3)Small trade [own business/ <5 employees] 4)Medium/large trade [own business/>=5 employees] 5)Other 6)DON'T KNOW 7)REFUSED | F73: သင်သည် မည်သို့သော ကိုယ်ပိုင် အလုပ်/ ပညာရှင် အလုပ်မျိုးကို လုပ် ကိုင်ပါသနည်း။ [အော်ပရေတာ- တုံ့ပြန်မှုတစ်ခုသာ။] 1)ပညာရှင် [ဆရာဝန်/အင်ဂျင်နီယာ/ရှေ့နေ စသည်] 2)လမ်းဘေးဈေးသည် [ကိုယ်ပိုင်/မိသားစု နှင့် အတူ] 3)အသေးစား ကုန်သွယ်မှု [ကိုယ်ပိုင်/ လုပ်သမား ၅ ယောက်အောက်] 4)အလယ်အလတ်/အကြီးစား ကုန်သည် [ကိုယ်ပိုင်/လုပ်သမား၅ ယောက်နှင့် အထက်] 5)အခြား 6)မသိ 7)ငြင်းဆို | G73: =LEN(F73) -> 351 | H73: Single Choice | L73: 1-4 = income_main_comp | Q73: =1 -> 1 | Y73: =IF(X73="","",X73*Q73) | Z73: =IF(T73="yes",Y73,"")
B74: o_wage_main_amount | D74: What was the typical wage for wage labourers per person per day in the past one month (30 days)? [OPERATOR: RECORD NUMBER GIVEN. ENTER 8888888 FOR DON'T KNOW & 9999999 FOR REFUSED.] | F74: လွန်ခဲ့သည့် ရက် ၃၀ အတွင်းမှာ လူတစ်ဦးလျှင် တစ်ရက်လျှင် လုပ်ခ မည်မျှရှိသနည်း။ [အော်ပရေတာ- မှတ်တမ်းနံပါတ်ကို အကြောင်းမဲ့။ မသိခြင်းအတွက် 8888888 နှင့် 9999999 ကို ငြင်းဆိုရန်။] | G74: =LEN(F74) -> 174 | H74: Range | K74: Form Type - TextBox IsDemographic - o_wage_main_amount | L74: 1 - 1000000 = o_wage_main_amount_Check 8888888-8888888 = income_main_comp 9999999-9999999 = income_main_comp
B75: o_wage_main_amount_Check | C75: o_wage_main_amount_Check | D75: You reported the average wage a person recieved per day was {o_wage_main_amount} MMK. Is this correct? [OPERATOR: IF YES, SELECT "NEXT". IF NO, GO BACK TO THE PREVIOUS QUESTION AND CORRECT THE ANSWER. 1)NEXT | F75: တစ်ရက်လျှင် လူတစ်ဦးရရှိသည့် ပျမ်းမျှလုပ်ခမှာ {o_wage_main_amount} MMK ဖြစ်ကြောင်း သင်ဖြေဆိုခဲ့သည်။ ထိုအချက်သည် မှန်ကန်ပါသလား။ [အော်ပရေတာ- ဟုတ်ပါက၊ "နောက်တစ်ခု" ကို ရွေးပါ။ မဟုတ်ပါက၊ ယခင်မေးခွန်းသို့ ပြန်သွားပြီး အဖြေကို ပြင်ပါ။ 1) နောက်တစ်ခု | G75: =LEN(F75) -> 245 | H75: Single Choice | I75: NA | J75: NA | K75: Form Type - Buttons | L75: 1 = income_main_comp | M75: 1 = income_main_comp
A76: =#REF!+1 -> #REF! | B76: income_main_comp | C76: income_main_comp | D76: Has your household's income from {income_main} changed in the last 3 months compared to the same period of a normal year? [OPERATOR: SINGLE RESPONSE.] 1)A lot more [increased by more than 50%] 2)Slightly more 3)Same 4)Slightly less 5)A lot less [less than half as much] 6)DON'T KNOW 7)REFUSED | E76: =LEN(D76) -> 294 | F76: လူကြီးမင်း၏ ပြီးခဲ့သည့် 3 လအတွင်း အိမ်ထောင်စုဝင်ငွေ {income_main} မှာ ကာလတူ ပုံမှန် နှစ် တစ်နှစ်မှ ဝင်ငွေနှင့်နှိုင်းယှဉ်လျှင် ပြောင်းလဲသွားပါသလား။ ...ဟုတ်ပါသလား [အော်ပရေတာ- တုံ့ပြန်မှုတစ်ခုသာ။] 1)အလွန်တိုးလာသည် [50% အထက် တိုးလာသည်] 2)တိုးလာသည် 3)တူညီသည် 4)ပို၍နည်းသည် 5)အလွန်နည်းသည် [ထက်ဝက်စာမျှ နည်းသည်] 6)မသိပါ 7)ဖြေဆိုရန် ငြင်းဆန်သည် | G76: =LEN(F76) -> 339 | H76: Single Choice | I76: NA | J76: NA | K76: Form Type - Buttons | L76: 1-7= income_sec | M76: NA | N76: if income_main_comp = 1-7, go to income_sec | Q76: =1 -> 1 | T76: yes | X76: 22.126215 | Y76: =IF(X76="","",X76*Q76) -> 22.126215 | Z76: =IF(T76="yes",Y76,"") -> 22.126215
B77: o_incomechangereduced | D77: Please describe the degree of income reduction: [OPERATOR: SINGLE RESPONSE] 1)0-25% 2)26-50% 3)51-75% 4)76-100% 5)DON'T KNOW 6)REFUSED | F77: လျော့နည်းသွား​သော ပမာဏ ကို ​ဖော်ပြပါ။ [အော်ပရေတာ- တုံ့ပြန်မှုတစ်ခုသာ။] 1)0-25% 2)26-50% 3)51-75% 4)76-100% 5)မသိပါ 6)ဖြေဆိုရန် ငြင်းဆန်သည် | G77: =LEN(F77) -> 141 | H77: Single Choice | Q77: =1 -> 1 | Y77: =IF(X77="","",X77*Q77) | Z77: =IF(T77="yes",Y77,"")
B78: o_incomechangereduced | D78: Please describe the degree of income reduction: [OPERATOR: SINGLE RESPONSE] 1)0-25% 2)26-50% 3)51-75% 4)76-100% 5)DON'T KNOW 6)REFUSED | E78: =LEN(D78) -> 136 | F78: လျော့နည်းသွား​သော ပမာဏ ကို ​ဖော်ပြပါ။ [အော်ပရေတာ- တုံ့ပြန်မှုတစ်ခုသာ။] 1)0-25% 2)26-50% 3)51-75% 4)76-100% 5)မသိပါ 6)ဖြေဆိုရန် ငြင်းဆန်သည် | G78: =LEN(F78) -> 141 | H78: Single Choice | J78: NA | K78: Form Type - Buttons | L78: 1-6 = income_sec
A79: =A76+1 -> #REF! | B79: income_sec | C79: income_sec | D79: What was your household's second most important source of income in the past 3 months? [OPERATOR: SINGLE RESPONSE. DON'T KNOW AND REFUSED OPTIONS SHOULD BE AVOIDED AS MUCH AS POSSIBLE.] 1)Production and sale of staple crops 2)Production and sale of vegetables or fruit 3)Production and sale of cashcrops 4)Production and sale of livestock and livestock products 5)Production and sale of honey or bee products 6)Production and sale of fish 7)Collection and sale of forestry or bush products 8)Agricultural trade EXCLUDING producers [formal or informal] 9)Daily wage on farms and other casual employment in agricultural sector 10)Stable employment in agricultural sector 11)Non-agricultural self-employed or liberal profession / doctor / architect / lawyer / including restaurant 12)Off-farm daily wages and other non-agricultural casual employment 13)Stable employment in non-agricultural sector 14)Public employment 15)Income not derived from work / Charity 16)Income not derived from work / Welfare transfer, pension, humanitarian aid 17)Income not derived from work / Remittances 18)Income not derived from work / Income from other rents 19)No second most important source of income 20)DON'T KNOW 21)REFUSED | E79: =LEN(D79) -> 1218 | F79: လွန်ခဲ့သော 3 လအတွင်း လူကြီးမင်းအိမ်ထောင်စု၏ ဒုတိယအ‌ရေးအကြီးဆုံး ဝင်ငွေအရင်းအမြစ်က ဘာပါလဲ။ [အော်ပရေတာ- တုံ့ပြန်မှုတစ်ခုသာ။ ငြင်းဆန်သည့်ရွေးချယ်မှုများကို တတ်နိုင်သမျှ မပြုလုပ်ဘဲ/မရှောင်ရှားဘဲ ဖြေဆိုပေးပါ] 1) နှံစားသီးနှံ ထုတ်လုပ်ရောင်းချခြင်း 2) ဟင်းသီးဟင်းရွက် သို့မဟုတ် သစ်သီးဝလံ ထုတ်လုပ်ရောင်းချခြင်း 3)ငွေပေါ်ကောက်ပဲသီးနှံ ထုတ်လုပ်ရောင်းချခြင်း 4)မွေးမြူရေးနှင့် မွေးမြူရေးလုပ်ငန်းထုတ်ကုန်များ ထုတ်လုပ်ရောင်းချခြင်း 5) ပျားရည်နှင့် အခြားဆက်စပ်ထုတ်ကုန်ပစ္စည်းများ ထုတ်လုပ်ရောင်းချခြင်း 6) ငါးမွေးမြူခြင်းနှင့် ရောင်းချခြင်း 7)သစ်တောထွက် သို့မဟုတ် သစ်ပင်ချုံနွယ်ထွက် ကုန်ပစ္စည်းများ စုဆောင်းခြင်းနှင့်ရောင်းချခြင်း 8)ထုတ်လုပ်သူများမဟုတ်ဘဲ လယ်ယာထုတ်ကုန်ကုန်သွယ်သူများ (အလွတ်သဘော သို့မဟုတ် တရားဝင်) 9)လယ်ယာလုပ်ငန်းမှ နေ့စဉ်လုပ်အားခ ရရှိသောစိုက်ပျိုးရေးကဏ္ဍရှိ အခြားကျပန်းအလုပ်အကိုင် 10)စိုက်ပျိုးရေးကဏ္ဍရှိ အတည်တကျအလုပ်အကိုင် 11)စိုက်ပျိုးရေးမဟုတ်သော ကိုယ်ပိုင်လုပ်ငန်း သို့မဟုတ် ပြည်သူ့အကျိုးပြု ပညာရှင်/ ဆရာဝန်/ ဗိသုကာ/ ရှေ့နေ/ စားသောက်ဆိုင်လုပ်ငန်းအပါအဝင် 12)လယ်ယာပြင်ပနေ့စဉ်လုပ်အားခနှင့် အခြားလယ်ယာမဟုတ်သော ကျပန်းအလုပ်အကိုင် 13)စိုက်ပျိုးရေးကဏ္ဍမဟုတ်သော အတည်တကျအလုပ်အကိုင် 14)အစိုးရအလုပ်အကိုင် 15)အလုပ်မှ ရရှိသော ဝင်ငွေမဟုတ်ပါ/ လှူဒါန်းမှု 16)အလုပ်မှ ရရှိသော ဝင်ငွေမဟုတ်ပါ / လူမှုဖူလုံရေးလွှဲပြောင်းခြင်း / ပင်စင် / လူသားချင်းစာနာမှုအကူအညီများ 17)အလုပ်မှ ရရှိသော ဝင်ငွေမဟုတ်ပါ / ငွေလွှဲခြင်း 18)အလုပ်မှ ရရှိသော ဝင်ငွေမဟုတ်ပါ / အခြားငှားရမ်းခများ 19)လွန်ခဲ့သော 3 လအတွင်း 0င်ငွေအရင်းအမြစ်မရှိဘဲ သီးသန့်စုငွေ သို့ ကြွေးမြီကိုသာ အသုံးပြုသည် 20)မသိပါ 20)ဖြေဆိုရန် ငြင်းဆန်သည် | G79: =LEN(F79) -> 1486 | H79: Single Choice | I79: NA | J79: NA | K79: Form Type - Buttons exclude selected "income_main" IsDemographic | L79: 1-3 = income_sec_crop_check 4 = income_sec_ls_check 5 = income_sec_comp 6 = income_sec_fish_check 7-8 = income_sec_comp 9 = o_wage_sec_amount 10 = income_sec_comp 11 = o_income_sec_selfemployed 12 = o_wage_sec_amount 13-18 = income_sec_comp 19-21 = o_Income_total_amount | M79: NA | N79: if options #1-3 selected, go to income_sec_crop_check if options #4 selected, go to income_sec_ls_check if options #6 selected, go to income_sec_fish_check if options #5, 7-18 selected, go to [income_sec_comp OR optional question] if options #19-21 selected, go to shock | Q79: =1 -> 1 | T79: yes | X79: 18.710653 | Y79: =IF(X79="","",X79*Q79) -> 18.710653 | Z79: =IF(T79="yes",Y79,"") -> 18.710653
B80: income_sec_crop_check | C80: income_sec_crop_check | D80: Are the crops that you sell also produced by you or anyone in your household? [OPERATOR: SINGLE RESPONSE.] 1)YES 2)NO 3)DON'T KNOW 4)REFUSED | E80: =LEN(D80) -> 143 | F80: သင်၏ အဓိက ၀င်ငွေအရင်းအမြစ်ဖြစ်သော လယ်ယာထွက်ကုန်များကို ကိုယ်တိုင် (သို့) မိသားစုဝင်တစ်ဦးဦးမှ ထုတ်လုပ် နေပါသလား။ [အော်ပရေတာ- တုံ့ပြန်မှုတစ်ခုသာ။] 1)ဟုတ်သည် 2)မဟုတ်ပါ 3)မသိပါ 4)ငြင်းဆိုသည်။ | G80: =LEN(F80) -> 190 | H80: Single Choice | I80: NA | J80: NA | K80: Form Type - Buttons | L80: 1-4 = income_sec_comp | M80: NA | N80: if income_sec_crop_check = 1-4, go to [income_sec_comp OR optional question] | Q80: =1 -> 1 | T80: yes | X80: 8 | Y80: =IF(X80="","",X80*Q80) -> 8 | Z80: =IF(T80="yes",Y80,"") -> 8
B81: income_sec_ls_check | C81: income_sec_ls_check | D81: Are the livestock and livestock products that you sell also produced by you or anyone in your household? [OPERATOR: SINGLE RESPONSE.] 1)YES 2)NO 3)DON'T KNOW 4)REFUSED | E81: =LEN(D81) -> 170 | F81: သင်၏ အဓိက ၀င်ငွေအရင်းအမြစ်ဖြစ်သော မွေးမြူရေးထွက်ကုန်များကို ကိုယ်တိုင် (သို့) မိသားစုဝင်တစ်ဦးဦးမှ ထုတ်လုပ် နေပါသလား။ [အော်ပရေတာ- တုံ့ပြန်မှုတစ်ခုသာ။] 1)ဟုတ်သည် 2)မဟုတ်ပါ 3)မသိပါ 4)ငြင်းဆိုသည်။ | G81: =LEN(F81) -> 196 | H81: Single Choice | I81: NA | J81: NA | K81: Form Type - Buttons | L81: 1-4 = income_sec_comp | M81: NA | N81: if income_sec_ls_check = 1-4, go to [income_sec_comp OR optional question] | Q81: =1 -> 1 | T81: yes | X81: 8 | Y81: =IF(X81="","",X81*Q81) -> 8 | Z81: =IF(T81="yes",Y81,"") -> 8
B82: income_sec_fish_check | C82: income_sec_fish_check | D82: Are the fish and/or fish products that you sell also captured or harvested by you or anyone in your household? [OPERATOR: SINGLE RESPONSE.] 1)YES 2)NO 3)DON'T KNOW 4)REFUSED | E82: =LEN(D82) -> 176 | F82: သင်၏ အဓိက ၀င်ငွေအရင်းအမြစ်ဖြစ်သော ရေထွက်ကုန်များကို ကိုယ်တိုင် (သို့) မိသားစုဝင်တစ်ဦးဦးမှ ထုတ်လုပ် နေပါသလား။ [အော်ပရေတာ- တုံ့ပြန်မှုတစ်ခုသာ။] 1)ဟုတ်သည် 2)မဟုတ်ပါ 3)မသိပါ 4)ငြင်းဆိုသည်။ | G82: =LEN(F82) -> 188 | H82: Single Choice | I82: NA | J82: NA | K82: Form Type - Buttons | L82: 1-4 = income_sec_comp | M82: NA | N82: if income_sec_fish_check = 1-4, go to [income_sec_comp OR optional question] | Q82: =1 -> 1 | T82: yes | X82: 8 | Y82: =IF(X82="","",X82*Q82) -> 8 | Z82: =IF(T82="yes",Y82,"") -> 8
B83: o_income_sec_selfemployed | C83: o_income_sec_selfemployed | D83: What type of self-employment / liberal profession? [OPERATOR: SINGLE RESPONSE.] 1)Liberal profession [doctor/architect/layer...] 2)Petty trade/selling on streets [own business/self or with family] 3)Small trade [own business/<5 employees] 4)Medium/large trade [own business/>=5 employees] 5)Other 6)DON'T KNOW 7)REFUSED | E83: =LEN(D83) -> 321 | F83: သင်သည် မည်သို့သော ကိုယ်ပိုင် အလုပ်/ ပညာရှင် အလုပ်မျိုးကို လုပ် ကိုင်ပါသနည်း။ [အော်ပရေတာ- တုံ့ပြန်မှုတစ်ခုသာ။] 1)ပညာရှင် [ဆရာဝန်/အင်ဂျင်နီယာ/ရှေ့နေ စသည်] 2)လမ်းဘေးဈေးသည် [ကိုယ်ပိုင်/မိသားစု နှင့် အတူ] 3)အသေးစား ကုန်သွယ်မှု [ကိုယ်ပိုင်/ လုပ်သမား ၅ ယောက်အောက်] 4)အလယ်အလတ်/အကြီးစား ကုန်သည် [ကိုယ်ပိုင်/လုပ်သမား၅ ယောက်နှင့် အထက်] 5)အခြား 6)မသိ 7)ငြင်းဆို | G83: =LEN(F83) -> 351 | H83: Single Choice | L83: 1-4 = income_sec_comp | Q83: =1 -> 1 | Y83: =IF(X83="","",X83*Q83) | Z83: =IF(T83="yes",Y83,"")
A84: =A83+1 -> 1 | B84: o_wage_sec_amount | C84: o_wage_main_amount | D84: What was the typical wage for wage labourers per person per day in the past one month (30 days)? [OPERATOR: RECORD NUMBER GIVEN. ENTER 8888888 FOR DON'T KNOW & 9999999 FOR REFUSED.] | E84: =LEN(D84) -> 185 | F84: လွန်ခဲ့သည့် ရက် ၃၀ အတွင်းမှာ လူတစ်ဦးလျှင် တစ်ရက်လျှင် လုပ်ခ မည်မျှရှိသနည်း။ [အော်ပရေတာ- မှတ်တမ်းနံပါတ်ကို အကြောင်းမဲ့။ မသိခြင်းအတွက် 8888888 နှင့် 9999999 ကို ငြင်းဆိုရန်။] | G84: =LEN(F84) -> 174 | H84: Range | I84: =LEN(H84) -> 5 | J84: Range | K84: Form Type - TextBox IsDemographic - o_wage_sec_amount | L84: 1 - 1000000 = o_wage_sec_amount_Check 8888888-8888888 = income_sec_comp 9999999-9999999 = income_sec_comp | M84: 1 - 1000000 = o_wage_sec_amount_Check 8888888-8888888 = income_sec_comp 9999999-9999999 = income_sec_comp | Q84: if options #1-4, go to [income_main_comp OR income_main_amount] | S84: resp_age = 18-100 hh_agricactivity = 1 | 2 | 3 | 4 quotareached = 2 income_main = 1-18 | U84: 17 | V84: =1 -> 1 | W84: =U84*V84 -> 17 | Z84: no | AD84: New question
B85: o_wage_sec_amount_Check | C85: o_wage_sec_amount_Check | D85: You reported the average wage a person recieved per day was {o_wage_sec_amount} MMK. Is this correct? [OPERATOR: IF YES, SELECT "NEXT". IF NO, GO BACK TO THE PREVIOUS QUESTION AND CORRECT THE ANSWER. 1)NEXT | F85: တစ်ရက်လျှင် လူတစ်ဦးရရှိသည့် ပျမ်းမျှလုပ်ခမှာ {o_wage_sec_amount} MMK ဖြစ်ကြောင်း သင်ဖြေဆိုခဲ့သည်။ ထိုအချက်သည် မှန်ကန်ပါသလား။ [အော်ပရေတာ- ဟုတ်ပါက၊ "နောက်တစ်ခု" ကို ရွေးပါ။ မဟုတ်ပါက၊ ယခင်မေးခွန်းသို့ ပြန်သွားပြီး အဖြေကို ပြင်ပါ။ 1) နောက်တစ်ခု | G85: =LEN(F85) -> 244 | H85: Single Choice | I85: NA | J85: NA | K85: Form Type - Buttons | L85: 1=income_sec_comp
A86: =#REF!+1 -> #REF! | B86: income_sec_comp | C86: income_sec_comp | D86: Has your household's income from {income_sec} changed in the last 3 months compared to the same period of a normal year? [OPERATOR: SINGLE RESPONSE.] 1)A lot more [increased by more than 50%] 2)Slightly more 3)Same 4)Slightly less 5)A lot less [less than half as much] 6)DON'T KNOW 7)REFUSED | E86: =LEN(D86) -> 294 | F86: လူကြီးမင်း၏ ပြီးခဲ့သည့် 3 လအတွင်း အိမ်ထောင်စုဝင်ငွေ {income_sec} မှာ ကာလတူ ပုံမှန် နှစ် တစ်နှစ်မှ ဝင်ငွေနှင့်နှိုင်းယှဉ်လျှင် ပြောင်းလဲသွားပါသလား။ ...ဟုတ်ပါသလား [အော်ပရေတာ- တုံ့ပြန်မှုတစ်ခုသာ။] 1)အလွန်တိုးလာသည် [50% အထက် တိုးလာသည်] 2)တိုးလာသည် 3)တူညီသည် 4)ပို၍နည်းသည် 5)အလွန်နည်းသည် [ထက်ဝက်စာမျှ နည်းသည်] 6)မသိပါ 7)ဖြေဆိုရန် ငြင်းဆန်သည် | H86: Single Choice | I86: NA | J86: NA | K86: Form Type - Buttons | L86: 1-7= income_third | M86: NA | N86: if income_sec_comp = 1-7, go to income_third | Q86: =1 -> 1 | T86: yes | X86: 17.261402 | Y86: =IF(X86="","",X86*Q86) -> 17.261402 | Z86: =IF(T86="yes",Y86,"") -> 17.261402
A87: =A86+1 -> #REF! | B87: income_third | C87: income_third | D87: What was your household's third most important source of income in the past 3 months? [OPERATOR: SINGLE RESPONSE. DON'T KNOW AND REFUSED OPTIONS SHOULD RARELY/NOT AVOIDED AS MUCH AS POSSIBLE.] 1)Production and sale of staple crops 2)Production and sale of vegetables or fruit 3)Production and sale of cashcrops 4)Production and sale of livestock and livestock products 5)Production and sale of honey or bee products 6)Production and sale of fish 7)Collection and sale of forestry or bush products 8)Agricultural trade EXCLUDING producers [formal and informal] 9)Daily wage on farms and other casual employment in agricultural sector 10)Stable employment in agricultural sector 11)Non-agricultural self-employed or liberal profession / doctor / architect / lawyer / including restaurant 12)Off-farm daily wages and other non-agricultural casual employment 13)Stable employment in non-agricultural sector 14)Public employment 15)Income not derived from work / Charity 16)Income not derived from work / Welfare transfer, pension, humanitarian aid 17)Income not derived from work / Remittances 18)Income not derived from work / Income from other rents 19)No third most important source of income 20)DON'T KNOW 21)REFUSED | E87: =LEN(D87) -> 1225 | F87: လွန်ခဲ့သော 3 လအတွင်း လူကြီးမင်းအိမ်ထောင်စု၏ တတိယအ‌ရေးအကြီးဆုံး ဝင်ငွေအရင်းအမြစ်က ဘာပါလဲ။ [အော်ပရေတာ- တုံ့ပြန်မှုတစ်ခုသာ။ ငြင်းဆန်သည့်ရွေးချယ်မှုများကို တတ်နိုင်သမျှ မပြုလုပ်ဘဲ/မရှောင်ရှားဘဲ ဖြေဆိုပေးပါ] 1) နှံစားသီးနှံ ထုတ်လုပ်ရောင်းချခြင်း 2) ဟင်းသီးဟင်းရွက် သို့မဟုတ် သစ်သီးဝလံ ထုတ်လုပ်ရောင်းချခြင်း 3)ငွေပေါ်ကောက်ပဲသီးနှံ ထုတ်လုပ်ရောင်းချခြင်း 4)မွေးမြူရေးနှင့် မွေးမြူရေးလုပ်ငန်းထုတ်ကုန်များ ထုတ်လုပ်ရောင်းချခြင်း 5) ပျားရည်နှင့် အခြားဆက်စပ်ထုတ်ကုန်ပစ္စည်းများ ထုတ်လုပ်ရောင်းချခြင်း 6) ငါးမွေးမြူခြင်းနှင့် ရောင်းချခြင်း 7)သစ်တောထွက် သို့မဟုတ် သစ်ပင်ချုံနွယ်ထွက် ကုန်ပစ္စည်းများ စုဆောင်းခြင်းနှင့်ရောင်းချခြင်း 8)ထုတ်လုပ်သူများမဟုတ်ဘဲ လယ်ယာထုတ်ကုန်ကုန်သွယ်သူများ (အလွတ်သဘော သို့မဟုတ် တရားဝင်) 9)လယ်ယာလုပ်ငန်းမှ နေ့စဉ်လုပ်အားခ ရရှိသောစိုက်ပျိုးရေးကဏ္ဍရှိ အခြားကျပန်းအလုပ်အကိုင် 10)စိုက်ပျိုးရေးကဏ္ဍရှိ အတည်တကျအလုပ်အကိုင် 11)စိုက်ပျိုးရေးမဟုတ်သော ကိုယ်ပိုင်လုပ်ငန်း သို့မဟုတ် ပြည်သူ့အကျိုးပြု ပညာရှင်/ ဆရာဝန်/ ဗိသုကာ/ ရှေ့နေ/ စားသောက်ဆိုင်လုပ်ငန်းအပါအဝင် 12)လယ်ယာပြင်ပနေ့စဉ်လုပ်အားခနှင့် အခြားလယ်ယာမဟုတ်သော ကျပန်းအလုပ်အကိုင် 13)စိုက်ပျိုးရေးကဏ္ဍမဟုတ်သော အတည်တကျအလုပ်အကိုင် 14)အစိုးရအလုပ်အကိုင် 15)အလုပ်မှ ရရှိသော ဝင်ငွေမဟုတ်ပါ/ လှူဒါန်းမှု 16)အလုပ်မှ ရရှိသော ဝင်ငွေမဟုတ်ပါ / လူမှုဖူလုံရေးလွှဲပြောင်းခြင်း / ပင်စင် / လူသားချင်းစာနာမှုအကူအညီများ 17)အလုပ်မှ ရရှိသော ဝင်ငွေမဟုတ်ပါ / ငွေလွှဲခြင်း 18)အလုပ်မှ ရရှိသော ဝင်ငွေမဟုတ်ပါ / အခြားငှားရမ်းခများ 19)လွန်ခဲ့သော 3 လအတွင်း 0င်ငွေအရင်းအမြစ်မရှိဘဲ သီးသန့်စုငွေ သို့ ကြွေးမြီကိုသာ အသုံးပြုသည် 20)မသိပါ 20)ဖြေဆိုရန် ငြင်းဆန်သည် | H87: Single Choice | I87: NA | J87: NA | K87: Form Type - Buttons Exclude selected "income_main" Exclude selected "income_sec" IsDemographic - income_third | L87: 1-3 = income_third_crop_check 4 = income_third_ls_check 5 = income_third_comp 6 = income_third_fish_check 7-8 = income_third_comp 9 = o_wage_third_amount 10 = income_third_comp 11 = o_income_third_selfemployed 12 = o_wage_third_amount 13-18 = income_third_comp 19-21 = o_Income_total_amount | M87: NA | N87: if options #1-3 selected, go to income_third_crop_check if options #4 selected, go to income_third_ls_check if option #6 selected, go to income_third_fish_check if options #5, 7-18 selected, go to [income_third_comp OR optional question] if options #19-21 selected, go to shock | Q87: =1 -> 1 | T87: yes | X87: 14.475392 | Y87: =IF(X87="","",X87*Q87) -> 14.475392 | Z87: =IF(T87="yes",Y87,"") -> 14.475392
B88: income_third_crop_check | C88: income_third_crop_check | D88: Are the crops that you sell also produced by you or anyone in your household? [OPERATOR: SINGLE RESPONSE.] 1)YES 2)NO 3)DON'T KNOW 4)REFUSED | E88: =LEN(D88) -> 143 | F88: သင်၏ အဓိက ၀င်ငွေအရင်းအမြစ်ဖြစ်သော လယ်ယာထွက်ကုန်များကို ကိုယ်တိုင် (သို့) မိသားစုဝင်တစ်ဦးဦးမှ ထုတ်လုပ် နေပါသလား။ [အော်ပရေတာ- တုံ့ပြန်မှုတစ်ခုသာ။] 1)ဟုတ်သည် 2)မဟုတ်ပါ 3)မသိပါ 4)ငြင်းဆိုသည်။ | H88: Single Choice | I88: NA | J88: NA | K88: Form Type - Buttons | L88: 1-4 = income_third_comp | M88: NA | N88: if income_third_crop_check = 1-4, go to [income_third_comp OR optional question] | Q88: =1 -> 1 | T88: yes | X88: 8 | Y88: =IF(X88="","",X88*Q88) -> 8 | Z88: =IF(T88="yes",Y88,"") -> 8
B89: income_third_ls_check | C89: income_third_ls_check | D89: Are the livestock and livestock products that you sell also produced by you or anyone in your household? [OPERATOR: SINGLE RESPONSE.] 1)YES 2)NO 3)DON'T KNOW 4)REFUSED | E89: =LEN(D89) -> 170 | F89: သင်၏ အဓိက ၀င်ငွေအရင်းအမြစ်ဖြစ်သော မွေးမြူရေးထုက်ကုန်များကို ကိုယ်တိုင် (သို့) မိသားစုဝင်တစ်ဦးဦးမှ ထုတ်လုပ် နေပါသလား။။ [အော်ပရေတာ- တုံ့ပြန်မှုတစ်ခုသာ။] 1)ဟုတ်သည် 2)မဟုတ်ပါ 3)မသိပါ 4)ငြင်းဆိုသည်။ | H89: Single Choice | I89: NA | J89: NA | K89: Form Type - Buttons | L89: 1-4 = income_third_comp | M89: NA | N89: if income_third_ls_check = 1-4, go to [income_third_comp OR optional question] | Q89: =1 -> 1 | T89: yes | X89: 8 | Y89: =IF(X89="","",X89*Q89) -> 8 | Z89: =IF(T89="yes",Y89,"") -> 8
B90: income_third_fish_check | C90: income_third_fish_check | D90: Are the fish and/or fish products that you sell also captured or harvested by you or anyone in your household? [OPERATOR: SINGLE RESPONSE.] 1)YES 2)NO 3)DON'T KNOW 4)REFUSED | E90: =LEN(D90) -> 176 | F90: သင်၏ အဓိက ၀င်ငွေအရင်းအမြစ်ဖြစ်သော ရေထွက်ကုန်များကို ကိုယ်တိုင် (သို့) မိသားစုဝင်တစ်ဦးဦးမှ ထုတ်လုပ် နေပါသလား။ [အော်ပရေတာ- တုံ့ပြန်မှုတစ်ခုသာ။] 1)ဟုတ်သည် 2)မဟုတ်ပါ 3)မသိပါ 4)ငြင်းဆိုသည်။ | H90: Single Choice | I90: NA | J90: NA | K90: Form Type - Buttons | L90: 1-4 = income_third_comp | M90: NA | N90: if income_third_fish_check = 1-4, go to [income_third_comp OR optional question] | Q90: =1 -> 1 | T90: yes | X90: 8 | Y90: =IF(X90="","",X90*Q90) -> 8 | Z90: =IF(T90="yes",Y90,"") -> 8
B91: o_income_third_selfemployed | C91: o_income_third_selfemployed | D91: What type of self-employment / liberal profession? [OPERATOR: SINGLE RESPONSE.] 1)Liberal profession [doctor/architect/layer...] 2)Petty trade/selling on streets [own business/self or with family] 3)Small trade [own business/<5 employees] 4)Medium/large trade [own business/>=5 employees] 5)Other 6)DON'T KNOW 7)REFUSED | E91: =LEN(D91) -> 321 | F91: သင်သည် မည်သို့သော ကိုယ်ပိုင် အလုပ်/ ပညာရှင် အလုပ်မျိုးကို လုပ် ကိုင်ပါသနည်း။ [အော်ပရေတာ- တုံ့ပြန်မှုတစ်ခုသာ။] 1)ပညာရှင် [ဆရာဝန်/အင်ဂျင်နီယာ/ရှေ့နေ စသည်] 2)လမ်ဘေးဈေးသည် [ကိုယ်ပိုင်] 3)အသေးစား ကုန်သွယ်မှု [ကိုယ်ပိုင်] 4)အလယ်အလတ်/အကြီးစား ကုန်သည်[ကိုယ်ပိုင်] 5)အခြား 6)မသိ 7)ငြင်းဆို | H91: Single Choice | L91: 1-7 = income_third_comp | Q91: =1 -> 1 | Y91: =IF(X91="","",X91*Q91) | Z91: =IF(T91="yes",Y91,"")
B92: o_wage_third_amount | C92: o_wage_third_amount | D92: What was the typical wage for wage labourers per person per day in the past one month (30 days)? [OPERATOR: RECORD NUMBER GIVEN. ENTER 8888888 FOR DON'T KNOW & 9999999 FOR REFUSED.] | F92: လွန်ခဲ့သည့် ရက် ၃၀ အတွင်းမှာ လူတစ်ဦးလျှင် တစ်ရက်လျှင် လုပ်ခ မည်မျှရှိသနည်း။ [အော်ပရေတာ- မှတ်တမ်းနံပါတ်ကို အကြောင်းမဲ့။ မသိခြင်းအတွက် 8888888 နှင့် 9999999 ကို ငြင်းဆိုရန်။] | H92: range | L92: 1 - 1000000 = o_wage_third_amount_Check 8888888-8888888 = income_third_comp 9999999-9999999 = income_third_comp
B93: o_wage_third_amount_Check | C93: o_wage_third_amount_Check | D93: You reported the average wage a person recieved per day was {o_wage_third_amount} MMK. Is this correct? [OPERATOR: IF YES, SELECT "NEXT". IF NO, GO BACK TO THE PREVIOUS QUESTION AND CORRECT THE ANSWER.] 1)NEXT | F93: တစ်ရက်လျှင် လူတစ်ဦးရရှိသည့် ပျမ်းမျှလုပ်ခမှာ {o_wage_third_amount} MMK ဖြစ်ကြောင်း သင်ဖြေဆိုခဲ့သည်။ ထိုအချက်သည် မှန်ကန်ပါသလား။ [အော်ပရေတာ- ဟုတ်ပါက၊ "နောက်တစ်ခု" ကို ရွေးပါ။ မဟုတ်ပါက၊ ယခင်မေးခွန်းသို့ ပြန်သွားပြီး အဖြေကို ပြင်ပါ။ 1) နောက်တစ်ခု | G93: =LEN(F93) -> 246 | H93: Single Choice | I93: NA | J93: NA | K93: Form Type - Buttons | L93: 1=income_third_comp
A94: =#REF!+1 -> #REF! | B94: income_third_comp | C94: income_third_comp | D94: Has your household's income from {income_third} changed in the last 3 months compared to the same period of a normal year? [OPERATOR: SINGLE RESPONSE.] 1)A lot more [increased by more than 50%] 2)Slightly more 3)Same 4)Slightly less 5)A lot less [less than half as much] 6)DON'T KNOW 7)REFUSED | E94: =LEN(D94) -> 295 | F94: လူကြီးမင်း၏ ပြီးခဲ့သည့် 3 လအတွင်း အိမ်ထောင်စုဝင်ငွေ {income_third} မှာ ကာလတူ ပုံမှန် နှစ် တစ်နှစ်မှ ဝင်ငွေနှင့်နှိုင်းယှဉ်လျှင် ပြောင်းလဲသွားပါသလား။ ...ဟုတ်ပါသလား [အော်ပရေတာ- တုံ့ပြန်မှုတစ်ခုသာ။] 1)အလွန်တိုးလာသည် [50% အထက် တိုးလာသည်] 2)တိုးလာသည် 3)တူညီသည် 4)ပို၍နည်းသည် 5)အလွန်နည်းသည် [ထက်ဝက်စာမျှ နည်းသည်] 6)မသိပါ 7)ဖြေဆိုရန် ငြင်းဆန်သည် | H94: Single Choice | I94: NA | J94: NA | K94: Form Type - Buttons | L94: 1-7= o_Income_total_amount | M94: NA | N94: if income_third_comp = 1-7, go to shock | Q94: =1 -> 1 | T94: yes | X94: 15.876503 | Y94: =IF(X94="","",X94*Q94) -> 15.876503 | Z94: =IF(T94="yes",Y94,"") -> 15.876503
B95: o_Income_total_amount | D95: How much was the household's total income during the last four weeks [one month]? [OPERATOR: RECORD TOTAL INCOME FOR THE LAST FOUR WEEKS. ENTER 8888888 FOR DON'T KNOW & 9999999 FOR REFUSED] | F95: လွန်ခဲသော တစ်လအတွင်း သင်အိမ်ထောင်စု၏ စုစုပေါင်းဝင်ငွေသည် ဘယ်လောက်လဲ။ [အော်ပရေတာ- နောက်ဆုံး လေးပတ်တာအတွက် စုစုပေါင်းဝင်ငွေကို မှတ်တမ်းတင်ပါ။ မသိပါဟု ဖြေဆိုပါက 8888888 ဟု ဖြည့်သွင်းပြီး ဖြေဆိုရန် ငြင်းဆန်သည်ကို ရွေးချယ်ပါက 9999999 ဟု ဖြည့်သွင်းပါ] [မှတ်ချက် အိမ်ထောင်စုတွင် ဝင်ငွေရှာသူများ{HHIncEarners} ရှိပြီး ဝင်ငွေ၏အဓိကအရင်းအမြစ်မှာ {income_main}ဖြစ်သည်။] | H95: Range | L95: 0-0 =o_Income_total_amount_conf 10000-9000000 = o_Income_total_amount_conf 8888888-8888888 = o_Income_total_comp 9999999-9999999 = o_Income_total_comp | Q95: =1 -> 1 | Y95: =IF(X95="","",X95*Q95) | Z95: =IF(T95="yes",Y95,"")
B96: o_Income_total_amount_conf | D96: Can you confirm the amount of income you just stated is correct? [OPERATOR: IF THE TOTAL AMOUNT EARNED OVER THE PAST 1 MONTH IS INDEED OVER 350000 or LESS THAN 25,000, CLICK ON CONTINUE. OTHERWISE, GO BACK AND CHANGE THE AMOUNT ENTERED.] 1)CONTINUE | F96: လူကြီးမင်း ယခုဖော်ပြခဲ့သော ဝင်ငွေပမာဏ မှန်ကန်ကြောင်း အတည်ပြုနိုင်ပါသလား။ [အော်ပရေတာ-လွန်ခဲ့သော တစ်လအတွင်း စုစုဝင်ငွေသည် 350000 ထက်ကျော်လွန်လျှင် ရှေ့ဆက်သွားပါ/ သို့မဟုတ်ပါက ကျန်ခဲ့သော မေးခွန်း ရှိဝင်ငွေကို ပြန်လည်စစ်ဆေး ပြီး ထည့်ပါ]... 1) ဆက်ရန် | H96: Single Choice | L96: 1 = o_Income_total_comp
B97: o_Income_total_comp | D97: Thinking about your household’s total income in the last one month, how has it changed compared to the same period one year ago? [OPERATOR: SINGLE RESPONSE] 1)A lot more [increased by more than 50%] 2)More 3)Same 4)Less 5)A lot less [less than half as much] 6)DON'T KNOW 7)REFUSED | F97: ပြီးခဲ့သောတစ်လအတွင်း သင့်အိမ်ထောင်စု၏ စုစုပေါင်းဝင်ငွေကို တွေးကြည့်ပါ၊ လွန်ခဲ့သော နှစ်၏ တူညီသောကာလနှင့် နှိုင်းယှဉ်ပါက မည်သို့ပြောင်းလဲသွားသနည်း။ [အော်ပရေတာ- တုံ့ပြန်မှုတစ်ခုသာ] 1)အလွန်တိုးလာသည် [50% အထက် တိုးလာသည်] 2)တိုးလာသည် 3)တူညီသည် 4)ပို၍နည်းသည် 5)အလွန်နည်းသည် [ထက်ဝက်စာမျှ နည်းသည်] 6)မသိပါ 7)ဖြေဆိုရန် ငြင်းဆန်သည် | H97: Single Choice | L97: 1-7 = o_HHExpTotal30d
B98: o_HHExpTotal30d | D98: How much was your family’s total expenditure in the last 30 days (in MMK)? [OPERATOR: THE RESPONDENT MENTIONED THAT THEIR TOTAL HOUSEHOLD INCOME IS {Income_total_amount}. PROBE IF THE TOTAL EXPENDITURE IS MORE THAN THE TOTAL HOUSEHOLD INCOME TO ENSURE AMOUNTS ARE CORRECT. RECORD THE AMOUNT GIVEN. ENTER 8888888 FOR DON'T KNOW & 9999999 FOR REFUSED] | F98: လွန်ခဲ့သောရက် 30 အတွင်း လူကြီးမင်းမိသားစု၏ စုစုပေါင်းအသုံးစရိတ် ဘယ်လောက်ရှိပါသလဲ (MMK ဖြင့်)။ [အော်ပရေတာ- ဖြေဆိုသော ပမာဏကို မှတ်သားပါ။ မသိပါဟု ဖြေဆိုပါက 8888888 ဟု ဖြည့်သွင်းပြီး ဖြေဆိုရန် ငြင်းဆန်သည်ကို ရွေးချယ်ပါက 9999999 ဟု ဖြည့်သွင်းပါ] | H98: Range | L98: 0 = o_ExpenseFood30d 1000-8000000 = o_ExpenseFood30d 8888888-8888888 = o_ExpenseFood30d 9999999-9999999 = o_ExpenseFood30d
B99: o_ExpenseFood30d | D99: What percentage of your household's expenditure did you spend on food in the last 30 days? [OPERATOR: SINGLE RESPONSE] 1)0%-10% 2)11%-20% 3)21%-30% 4)31%- 40% 5)41 % - 50% 6)51% - 60% 7)61%-70% 8)71%-80% 9)81%-90% 10)91%-100% 11)DON'T KNOW 12)REFUSED | F99: လွန်ခဲ့သည့်ရက်ပေါင်း 30 အတွင်း အိမ်ထောင်စု စုစု ပေါင်း အသုံးစရိတ်မှ အစားအစာအတွက် အသုံးစရိတ်ကို မည်မျှသုံးစွဲခဲ့ပါသလဲ။ [အော်ပရေတာ- တုံ့ပြန်မှုတစ်ခုသာ] 1)0%-10% 2)11%-20% 3)21%-30% 4)31%- 40% 5)41 % - 50% 6)51% - 60% 7)61%-70% 8)71%-80% 9)81%-90% 10)91%-100% 11)မသိပါ 12)ဖြေဆိုရန် ငြင်းဆန်သည် | H99: Single Choice | L99: 1-12 = HHDebt_yn
B100: HHDebt_yn | D100: Do you or someone in your household currently have any debt that was incurred in the last one year? [OPERATOR: SINGLE RESPONSE] 1)YES 2)NO 3)DON'T KNOW 4)REFUSED | F100: ယခု သင် သို့မဟုတ် သင့်အိမ်ထောင်စုဝင် တစ်ယောက် တွင် လွန်ခဲ့သောနှစ် ကတည်းက ချေးယူထားသောအကြွေး ရှိနေပါသလား။ [အော်ပရေတာ- တုံ့ပြန်မှုတစ်ခုသာ] 1) ရှိသည်။ 2) မရှိပါ။ 3)မသိပါ။ 4) ငြင်းဆိုသည်။ | H100: Single Choice | L100: 1 = HHDebt_BorrowFrom 2-4 = shock
B101: HHDebt_BorrowFrom | D101: From whom have you mainly borrowed this money (or contracted this debt) in the past year? [OPERATOR: SINGLE RESPONSE] 1)Relatives [excluding remittances] 2)Relatives living outside the country 3)Traders/shopkeepers 4)Bank/Credit institution/Government/Micro-credit project 5)Money lender 6)Landlord [more than 1 month behind in rent] 7)Informal savings group 8)Employer 9)Other | F101: လွန်ခဲသောနှစ် တွင် ငွေချေးယူခြင်းကို အဓိကအာဖြင့် မည်သူ့ထံမှ ချေးယူခဲသနည်း။ [အော်ပရေတာ- တုံ့ပြန်မှုတစ်ခုသာ] 1)ဆွေမျိုး [လွဲပို့ငွေများ မပါဝင်ပါ] 2)ဆွေမျိုး [နိုင်ငံပြင်ပနေထိုင်သူ] 3)ကုန်သည်၊ ဈေးဆိုင် 4)ဘဏ်၊ ချေးငွေလုပ်ငန်း၊ အစိုး ရ ချေးငွေ၊အသေးစား ချေးငွေအဖွဲ့ 5)ငွေချေးသူ 6)အိမ်ရှင် [အိမ်ငှားခ ၁ လကျော်အကြွေးတင်] 7)ရပ်ကွက်၊ ကျေးရွာ အတွင်းမှ ငွေစုအဖွဲ့ [စုကြေးလိုက်အဖွဲ့] 8)အလုပ်ရှင် 9)အခြား | H101: Single Choice | L101: 1-9 = HHDebt_more
...

Sheet Crop list
C3: Select top 10 crops | D3: GeoPoll code | E3: Dataset code | F3: Label (EN)
C4: x | D4: {=_xlfn.SEQUENCE(90,1,1,1)} -> 1 | E4: 1.1 | F4: Rice
C5: x | D5: 2 | E5: 1.2 | F5: Wheat
D6: 3 | E6: 1.3 | F6: Millet
D7: 4 | E7: 1.4 | F7: Sorghum
C8: x | D8: 5 | E8: 1.5 | F8: Maize
D9: 6 | E9: 1.6 | F9: Barley
D10: 7 | E10: 1.99 | F10: Other Cereal
D11: 8 | E11: 2.1 | F11: Cassava
C12: x | D12: 9 | E12: 2.2 | F12: Potatoe
D13: 10 | E13: 2.3 | F13: Sweet Potatoes
D14: 11 | E14: 2.4 | F14: Yams
D15: 12 | E15: 2.5 | F15: Carrots
D16: 13 | E16: 2.6 | F16: Cocoyam
D17: 14 | E17: 2.99 | F17: Other tubers
C18: x | D18: 15 | E18: 3.1 | F18: Beans
D19: 16 | E19: 3.2 | F19: Lentils
D20: 17 | E20: 3.3 | F20: Peas
D21: 18 | E21: 3.4 | F21: Soybeans
D22: 19 | E22: 3.5 | F22: Chickpeas
D23: 20 | E23: 3.6 | F23: Fava beans
D24: 21 | E24: 3.7 | F24: Broad beans
D25: 22 | E25: 3.99 | F25: Other pulses
D26: 23 | E26: 4.1 | F26: Cabbage
D27: 24 | E27: 4.2 | F27: Lettuce
D28: 25 | E28: 4.3 | F28: Spinach-Amaranth
D29: 26 | E29: 4.4 | F29: Cassava leaves
D30: 27 | E30: 4.5 | F30: Potatoe leaves
... D42: 39 | E42: 5.7 | F42: Bell pepper
C43: x | D43: 40 | E43: 5.8 | F43: Onions
D44: 41 | E44: 5.9 | F44: Haricot
D45: 42 | E45: 5.101 | F45: Green peas
D46: 43 | E46: 5.11 | F46: Fava beans green
D47: 44 | E47: 5.99 | F47: Other non leafy vegs
D48: 45 | E48: 6.1 | F48: Orange
D49: 46 | E49: 6.2 | F49: Lemon
D50: 47 | E50: 6.3 | F50: Grapefruit
D51: 48 | E51: 6.4 | F51: Mandarins/clementines
D52: 49 | E52: 6.99 | F52: Other citrus fruit
D53: 50 | E53: 7.1 | F53: Sweet Banana
D54: 51 | E54: 7.2 | F54: Plantains
D55: 52 | E55: 7.3 | F55: Papaya
... D72: 69 | E72: 8.1 | F72: Coconuts
C73: x | D73: 70 | E73: 8.2 | F73: Groundnut/peanut
D74: 71 | E74: 8.3 | F74: Cashew Nut
D75: 72 | E75: 8.4 | F75: Kola Nut
C76: x | D76: 73 | E76: 8.5 | F76: Sesame
D77: 74 | E77: 8.6 | F77: Bambara nut
D78: 75 | E78: 8.7 | F78: Almond
D79: 76 | E79: 8.8 | F79: Walnut
D80: 77 | E80: 8.99 | F80: Other nuts
D81: 78 | E81: 9.1 | F81: Cocoa
D82: 79 | E82: 9.2 | F82: Coffee
D83: 80 | E83: 9.3 | F83: Tea
C84: x | D84: 81 | E84: 9.4 | F84: Sugarcane
D85: 82 | E85: 9.5 | F85: Sunflower
D86: 83 | E86: 9.99 | F86: Other food cash crop
D87: 84 | E87: 10.1 | F87: Cotton
D88: 85 | E88: 10.2 | F88: Rubber
D89: 86 | E89: 10.3 | F89: Jute
D90: 87 | E90: 10.4 | F90: Fodder
C91: x | D91: 88 | E91: 10.5 | F91: Tobacco
D92: 89 | E92: 10.6 | F92: Qat
D93: 90 | E93: 10.99 | F93: Other non-food cash crop

Sheet Additional information
C2: Original | D2: Replacement | E2: Comment | F2: Examples
B3: FOR CORE QUESTIONS . (Mandatory to fill out) . | C3: ADMIN1 | D3: State/Region | E3: The first subdivision of the country, after national level; region; province; governorate; etc. | F3: region
C4: ADMIN2 | D4: Township | E4: The second subdivision of the country; district; municipality; LGA; etc. | F4: district
C5: reference year | D5: a normal year | E5: Comparison questions will need need a reference year. Select whether you want to use "last year" or "a normal year" as a baseline. A "normal year" should refers to an average year from the past 5 years - make sure to train the enumerators accordingly. | F5: a normal year
C6: season | D6: Lean Season (dry season) | E6: Name the crop season(s) of interest if there are several cropping seasons in the country (e.g. Meher and Belg in Ethiopia, rainy season / flood-recession cropping / irrigated dry season in the Sahel). You can refer to the “last season” or “ongoing season". | F6: wet season
C7: season phase | D7: Land preparation | E7: Indicate the phase of the season at the time of data collection. If the harvest from the season has not yet occurred, the question on crop harvest (crp_harv_change) will include the word “expected” (where #expected or nothing# is located). If the harvest has occured, "expected" will not be inserted in the question. | F7: Harvesting
C8: local measurement unit | D8: Arces, square meter | E8: Specify the local measurement unit for land size, other than acres, hectares, square meters and square feet. If no other unit of measurement is needed, keep this cell blank. | F8: Jeribs
C9: local measurement unit conversion | E9: Include the conversion of the local measurement unit to hectares. In other words, how many local measurement units are in 1 ha. | F9: 0.2
B10: FOR OPTIONAL QUESTIONS . (Fill out if applicable) . | C10: currency | D10: MMK | E10: The name of the main currency used nationally; USD; Naira; Rial; Pesos; etc. | F10: Naira
C11: MIN AMOUNT | D11: 100 | E11: The minimum amount for an income source should be set at 0 or any value below which it is not possible to do a transaction. For example, the smallest coin/banknote in a currency can be 1000, in which case you would set the minimum at 1000. Provide this input in the same currency as specified above. Only digits should be inputted. | F11: 5
C12: MAX AMOUNT | D12: 5000000 | E12: Set the maximum amount for an income source over 3 months. Enumerators will not be able to input values above this amount in questions related to income amounts. Using previous representative surveys for this population, you can estimate this amount by using the mean income plus five (5) standard deviations, unless the country has high inflation. In the latter case, set the maximum value based on your country context (higher than the proposed approach). Provide this input in the same currency as specified above. Only digits should be inputted. | F12: 5000000
C13: THRESHOLD | E13: The threshold salary should be calculated to flag outliers (responses that look suspiciously high). Using previous representative surveys for this population, a good estimate is the average plus three (3) standard deviations, which should give the threshold for the 3 or 4% highest income values. Provide this input in the same currency as specified above. Only digits should be inputted. | F13: 1200000
C14: local vegetables | E14: Input some common local vegetables [to be used as examples in the food consumption score indicator]. | F14: eggplants, zucchini, cauliflower
C15: local fruits | E15: Input some common local fruits [to be used as examples in the food consumption score indicator]. | F15: apples, bananas, oranges
B17: FILL OUT FOR QUESTIONNAIRE DURATION ESTIMATION . | C17: Expected percentage of respondents cultivating crops | D17: 0.91 | E17: If the survey is representative and has no quotas, write the proportion of rural households cultivating crops at country level, or if the survey follows a previous round with identical sample design, just report the percentage from the previous round. If you are using quotas, calculate the ratio of the quota over the minimum sample size at the level where the quota is implemented (so if you have a minimum sample size per strata of 110 with a quota of 100 crop producers, then it's 100/110 = 91% (the maximum you should write is 100%). | F17: 0.91
C18: Expected percentage of respondents raising livestock | D18: 0.91 | E18: If the survey is representative and has no quotas, write the proportion of rural households raising livestock at country level, or if the survey follows a previous round with identical sample design, just report the percentage from the previous round. If you are using quotas, calculate the ratio of the quota over the minimum sample size at the level where the quota is implemented (so if you have a minimum sample size of 110 but a quota of 100 livestock producers, then it's 100/110 = 91% (the maximum you should write is 100%) | F18: 0.91
C19: Expected percentage of respondents involved in fishery | D19: 0.05 | E19: If the survey is representative and has no quotas, write the proportion of rural households involved in fisheries or aquaculture, otherwise if you are using quotas, calculate the ratio of the quota over the sample size at the level where the quota is implemented. (so if you haven't set a quota, and you expect to have a representative proportion of fishermen, just write the percentage of fishermen in the population you are targeting, in the example to the right, 5%) | F19: 0.05

Sheet Admin 3 info
A1: adm3_name | B1: adm3_name_local | C1: adm3_pcode | D1: adm2_name | E1: adm2_pcode | F1: adm1_name | G1: adm1_pcode | H1: adm0_name | I1: adm0_ISO3 | J1: adm0_M49
A2: Ramree | B2: ရမ်းဗြဲ | C2: MMR012013 | D2: Kyaukpyu | E2: MMR012D003 | F2: Rakhine | G2: MMR012 | H2: Myanmar | I2: MMR | J2: 104
A3: Toungup | B3: တောင်ကုတ် | C3: MMR012016 | D3: Thandwe | E3: MMR012D004 | F3: Rakhine | G3: MMR012 | H3: Myanmar | I3: MMR | J3: 104
A4: Kyaukpyu | B4: ကျောက်ဖြူ | C4: MMR012011 | D4: Kyaukpyu | E4: MMR012D003 | F4: Rakhine | G4: MMR012 | H4: Myanmar | I4: MMR | J4: 104
A5: Labutta | B5: လပွတ္တာ | C5: MMR017016 | D5: Labutta | E5: MMR017D004 | F5: Ayeyarwady | G5: MMR017 | H5: Myanmar | I5: MMR | J5: 104
A6: Ngapudaw | B6: ငပုတော | C6: MMR017004 | D6: Pathein | E6: MMR017D001 | F6: Ayeyarwady | G6: MMR017 | H6: Myanmar | I6: MMR | J6: 104
A7: Bogale | B7: ဘိုကလေး | C7: MMR017024 | D7: Pyapon | E7: MMR017D006 | F7: Ayeyarwady | G7: MMR017 | H7: Myanmar | I7: MMR | J7: 104
A8: Thandwe | B8: သံတွဲ | C8: MMR012015 | D8: Thandwe | E8: MMR012D004 | F8: Rakhine | G8: MMR012 | H8: Myanmar | I8: MMR | J8: 104
A9: Bokpyin | B9: ဘုတ်ပြင်း | C9: MMR006010 | D9: Kawthoung | E9: MMR006D003 | F9: Tanintharyi | G9: MMR006 | H9: Myanmar | I9: MMR | J9: 104
A10: Ye | B10: ရေး | C10: MMR011006 | D10: Mawlamyine | E10: MMR011D001 | F10: Mon | G10: MMR011 | H10: Myanmar | I10: MMR | J10: 104
A11: Kungyangon | B11: ကွမ်းခြံကုန်း | C11: MMR013029 | D11: Yangon (South) | E11: MMR013D003 | F11: Yangon | G11: MMR013 | H11: Myanmar | I11: MMR | J11: 104
A12: Dedaye | B12: ဒေးဒရဲ | C12: MMR017026 | D12: Pyapon | E12: MMR017D006 | F12: Ayeyarwady | G12: MMR017 | H12: Myanmar | I12: MMR | J12: 104
A13: Pyapon | B13: ဖျာပုံ | C13: MMR017023 | D13: Pyapon | E13: MMR017D006 | F13: Ayeyarwady | G13: MMR017 | H13: Myanmar | I13: MMR | J13: 104
... A331: Muse | B331: မူဆယ် | C331: MMR015009 | D331: Muse | E331: MMR015D002 | F331: Shan | G331: MMR222 | H331: Myanmar | I331: MMR | J331: 104
