Workbook

Sheet survey
A1: type | B1: name | C1: label::Arabic (ar) | D1: label::English (en) | E1: label:: | F1: hint::English (en) | G1: hint::Arabic (ar) | H1: hint:: | I1: required | J1: appearance | K1: constraint | L1: constraint_message::English (en) | M1: constraint_message::Arabic (ar) | N1: relevant | O1: choice_filter | P1: parameters | Q1: calculation | R1: trigger | S1: default | V1: Mandatory | X1: New question duration (sec) | Y1: Estimated percentage of repondents | Z1: Weighted time | AA1: Weighted time for core vars
A2: start | B2: start | Z2: =IF(X2<>"",X2*Y2,"") | AA2: =IF(AND(X2<>"",V2="yes"),X2*Y2,"")
A3: end | B3: end | Z3: =IF(X3<>"",X3*Y3,"") | AA3: =IF(AND(X3<>"",V3="yes"),X3*Y3,"")
A4: today | B4: today | Z4: =IF(X4<>"",X4*Y4,"") | AA4: =IF(AND(X4<>"",V4="yes"),X4*Y4,"")
A5: deviceid | B5: deviceid | Z5: =IF(X5<>"",X5*Y5,"") | AA5: =IF(AND(X5<>"",V5="yes"),X5*Y5,"")
A6: audit | B6: audit
A7: dateTime | B7: Interview_start_Time | C7: وقت بداية المقابلة | D7: Interview Start Time | I7: true | V7: no
A8: select_one enumteam | B8: enum_team | C8: فريق جمع البيانات (حسب المنطقة) | D8: Enumerator team number or code (according to the district) | I8: true
A9: dateTime | B9: First_update_time | Q9: if(${First_update_time}='', now(), ${First_update_time}) | R9: ${enum_team}
A10: select_one enumerator | B10: enumerator | C10: رمز جامع البيانات | D10: Code of enumerator | I10: true | O10: my_filter_admin=${enum_team} | V10: yes | Z10: =IF(X10<>"",X10*Y10,"") | AA10: =IF(AND(X10<>"",V10="yes"),X10*Y10,"")
A11: text | B11: enumerator_ | C11: اسم جامع البيانات | D11: Name of enumerator | I11: true | K11: string-length(.)>=3 | L11: عفوا، الرجاء تقديم نص و شرح اكثر وضوحا. | M11: Sorry, Please provide a much more meaningful text | V11: yes | Z11: =IF(X11<>"",X11*Y11,"") | AA11: =IF(AND(X11<>"",V11="yes"),X11*Y11,"")
A12: note | B12: introduction | C12: مرحبًا سيدي / سيدتي ، اسمي ${enumerator_}. نجري دراسة استقصائية نيابة عن منظمة الأغذية والزراعة للأمم المتحدة (الفاو) حول سبل عيش الأسر والقدرة على الوصول إلى الغذاء في منطقتك. أود أن أطرح عليك بعض الأسئلة حول أسرتك. يستغرق الاستبيان عادةً 30 دقيقة. سيتم الاحتفاظ بسرية تامة بأي معلومات تقدمها ، ولن يتم استخدامها إلا لغرض الدراسة ولن يتم عرضها لأشخاص آخرين. إن مشاركتك الطوعية في نتيجة هذه الدراسة ليست مرتبطة بأي شكل من الأشكال بفرصتك الشخصية في تلقي أي مساعدة. هذا تطوعي ويمكنك اختيار عدم الإجابة على أي من الأسئلة أو جميعها إذا كنت تريد ذلك. ومع ذلك ، نأمل أن تشارك لأن آرائك مهمة. هل لديك اسئلة؟ | D12: Hello sir/ma'am, my name is ${enumerator_}. On behalf of the Food and Agriculture Organization of the United Nations (FAO), we are conducting a survey on household livelihoods and the ability to access food in your area. I would like to ask you some questions about your household. The survey usually takes 30 minutes to complete. Any information that you provide will be kept strictly confidential, only used for the purpose of the survey and will not be shown to other people. Your voluntary participation in the outcome of this interview is NOT IN ANY WAY linked to your personal chance of receiving any assistance. This is voluntary and you can choose not to answer any or all of the questions if you want. However, we hope that you will participate since your views are important. Do you have any questions? | F12: [INSTRUCTIONS: ADDRESS QUESTIONS FROM RESPONDENT, IF ANY.] | G12: [تعليمات: أجب عن أسئلة المُجيب ، إن وجدت] | I12: false | V12: no | X12: 50.82254 | Z12: =IF(X12<>"",X12*Y12,"") | AA12: =IF(AND(X12<>"",V12="yes"),X12*Y12,"")
A13: select_one yesno | B13: resp_agree | C13: هل لديك رغبة في بالمشاركة في هذه الدراسة؟ | D13: Are you interested in participating in this survey? | I13: true | V13: yes | X13: 3.5 | Y13: =1 | Z13: =IF(X13<>"",X13*Y13,"") | AA13: =IF(AND(X13<>"",V13="yes"),X13*Y13,"")
A14: note | B14: Refusal | C14: شكراً جزيلاً على وقتك، سنقوم بحذف إسمك من دراسة اليوم. | D14: Thank you for your time, you will be removed from today's survey. | I14: false | N14: ${resp_agree} = '2' | V14: no | X14: 0 | Y14: 1 | Z14: =IF(X14<>"",X14*Y14,"") | AA14: =IF(AND(X14<>"",V14="yes"),X14*Y14,"")
A15: begin_group | B15: eligibility | C15: 1. معايير الأهلية | D15: 1. ELIGIBILITY CRITERIA | I15: false | N15: ${resp_agree} = '1' | V15: yes | Z15: =IF(X15<>"",X15*Y15,"") | AA15: =IF(AND(X15<>"",V15="yes"),X15*Y15,"")
A16: text | B16: resp_firstname | C16: 1.1 ما اسمك؟ | D16: 1.1 What is your first name? | F16: [INSTRUCTIONS: RECORD THE RESPONDENT'S FIRST NAME. ENTER 999 FOR REFUSED] | G16: [تعليمات: سجل اسم المجيب. أدخل 999 في حالة الرفض] | I16: true | K16: string-length(.)>=3 | L16: عفوا، الرجاء تقديم نص و شرح اكثر وضوحا. | M16: Sorry, Please provide a much more meaningful text | V16: yes | X16: 10 | Y16: =1 | Z16: =IF(X16<>"",X16*Y16,"") | AA16: =IF(AND(X16<>"",V16="yes"),X16*Y16,"")
A17: text | B17: resp_lastname | C17: 1.2 ما هو لقبك\كنيتك؟ | D17: 1.2 What is your last name? | F17: [INSTRUCTIONS: RECORD THE RESPONDENT'S LAST NAME. ENTER 999 FOR REFUSED] | G17: [تعليمات: سجل اسم عائلة المجيب. أدخل 999 في حالة الرفض] | I17: true | K17: string-length(.)>=3 | L17: عفوا، الرجاء تقديم نص و شرح اكثر وضوحا. | M17: Sorry, Please provide a much more meaningful text | V17: yes | X17: 10 | Y17: =1 | Z17: =IF(X17<>"",X17*Y17,"") | AA17: =IF(AND(X17<>"",V17="yes"),X17*Y17,"")
A18: integer | B18: resp_age | C18: 1.3 كم عمرك؟ | D18: 1.3 How old are you? | F18: [INSTRUCTIONS: RECORD AGE IN NUMBER OF YEARS. ROUND UP TO NEAREST WHOLE NUMBER. IF THE RESPONDENT GIVES BIRTH YEAR, REPEAT THE QUESTION. ENTER 888 FOR DON'T KNOW.] | G18: [تعليمات: سجل العمر في عدد السنوات. قم بالتقريب لأقرب رقم كامل. إذا أعطى المجيب سنة الميلاد ، فكرر السؤال. أدخل 888 إذا كان الجواب لا أعرف] | I18: true | K18: (. >= 16 and . <= 100) or . = 888 | V18: yes | X18: 13.753073 | Y18: =1 | Z18: =IF(X18<>"",X18*Y18,"") | AA18: =IF(AND(X18<>"",V18="yes"),X18*Y18,"")
A19: select_one gender | B19: resp_gender | C19: 1.4 ما هو جنس المجيب؟ | D19: 1.4 What is the gender of the respondent? | F19: [INSTRUCTIONS: DO NOT ASK THIS QUESTION OUT LOUD. SELECT THE GENDER OF THE RESPONDENT.] | G19: [تعليمات: لا تطرح هذا السؤال. حدد جنس المجيب] | I19: true | V19: no | X19: 2.1173561 | Y19: =1 | Z19: =IF(X19<>"",X19*Y19,"") | AA19: =IF(AND(X19<>"",V19="yes"),X19*Y19,"")
A20: text | B20: phone_number_personal | C20: 1.5 ما هو رقم هاتفك؟ | D20: 1.5 What is your phone number? | I20: false | J20: numbers | K20: regex(.,'^(\+?( |-|\.)?\d{1,2}( |-|\.)?)?(\(?\d{3}\)?|\d{3})( |-|\.)?(\d{2,3}( |-|\.)?\d{4,6})$') | L20: Please enter a valid phone number | M20: الرجاء ادخال رقم هاتف صحيح | V20: yes - panel | X20: 10 | Y20: =1 | Z20: =IF(X20<>"",X20*Y20,"") | AA20: =IF(AND(X20<>"",V20="yes"),X20*Y20,"")
A21: select_one contact_info | B21: contact_2 | C21: 1.6 هل يمكن أن تعطيني رقم هاتف إضافي يخصك ، أو يخص قريبًا أو صديقًا يمكن الوصول إليك من خلاله؟ | D21: 1.6 Can you give me an additional phone number belonging to you, a relative or a friend at which you can be reached? | I21: false | V21: yes - panel | X21: 10 | Y21: =1 | Z21: =IF(X21<>"",X21*Y21,"") | AA21: =IF(AND(X21<>"",V21="yes"),X21*Y21,"")
A22: text | B22: phone_number_2 | C22: 1.7 ما هو رقم الهاتف الإضافي؟ | D22: 1.7 What is the additional phone number? | I22: false | J22: numbers | K22: regex(.,'^(\+?( |-|\.)?\d{1,2}( |-|\.)?)?(\(?\d{3}\)?|\d{3})( |-|\.)?(\d{2,3}( |-|\.)?\d{4,6})$') | L22: Please enter a valid phone number | M22: الرجاء ادخال رقم هاتف صحيح | N22: ${contact_2} = '1' or ${contact_2} = '2' or ${contact_2} = '3' | V22: yes - panel | X22: 10 | Y22: =1 | Z22: =IF(X22<>"",X22*Y22,"") | AA22: =IF(AND(X22<>"",V22="yes"),X22*Y22,"")
A23: text | B23: contact_2_name | C23: 1.8 ما هو اسم صاحب رقم الهاتف الإضافي الذي قمت بمشاركته؟ | D23: 1.8 What is the name of the contact? | I23: false | K23: string-length(.)>=3 | L23: عفوا، الرجاء تقديم نص و شرح اكثر وضوحا. | M23: Sorry, Please provide a much more meaningful text | N23: ${contact_2} = '2' or ${contact_2} = '3' | V23: yes - panel | X23: 10 | Y23: =1 | Z23: =IF(X23<>"",X23*Y23,"") | AA23: =IF(AND(X23<>"",V23="yes"),X23*Y23,"")
A24: select_one admin1 | B24: adm1_pcode | C24: 1.9 حاليًا ، في أي محافظة تقيم أسرتك؟ | D24: 1.9 Currently, in which Governorate does your household reside? | F24: [HINT: HOUSEHOLD CONSISTS OF ALL MEMBERS LIVING TOGETHER, SHARING RESOURCES & EATING FROM THE SAME POT.] | G24: [ملحوظة: تتكون الأسرة من جميع الأعضاء الذين يعيشون معًا ، ويتشاركون الموارد ويأكلون من نفس القدر] | I24: true | J24: autocomplete | V24: yes | X24: 8.8 | Y24: =1 | Z24: =IF(X24<>"",X24*Y24,"") | AA24: =IF(AND(X24<>"",V24="yes"),X24*Y24,"")
A25: calculate | B25: adm1_name | Q25: jr:choice-name(${adm1_pcode},'${adm1_pcode}') | V25: yes | Y25: =1 | Z25: =IF(X25<>"",X25*Y25,"") | AA25: =IF(AND(X25<>"",V25="yes"),X25*Y25,"")
A26: select_one admin2 | B26: adm2_pcode | C26: 1.10 حاليًا ، في أي منطقة تقيم أسرتك؟ | D26: 1.10 Currently, in which District does your household reside? | F26: [HINT: HOUSEHOLD CONSISTS OF ALL MEMBERS LIVING TOGETHER, SHARING RESOURCES & EATING FROM THE SAME POT.] | G26: [ملحوظة: تتكون الأسرة من جميع الأعضاء الذين يعيشون معًا ، ويتشاركون الموارد ويأكلون من نفس القدر] | I26: true | J26: autocomplete | O26: my_filter_admin=${adm1_pcode} | V26: yes | X26: 10.4 | Y26: =1 | Z26: =IF(X26<>"",X26*Y26,"") | AA26: =IF(AND(X26<>"",V26="yes"),X26*Y26,"")
A27: calculate | B27: adm2_name | Q27: jr:choice-name(${adm2_pcode},'${adm2_pcode}') | V27: yes | Y27: =1 | Z27: =IF(X27<>"",X27*Y27,"") | AA27: =IF(AND(X27<>"",V27="yes"),X27*Y27,"")
A28: select_one admin3 | B28: adm3_pcode | C28: 1.11 حاليًا ، في أي ناحية تقيم أسرتك؟ | D28: 1.11 Currently, in which Sub-District does your household reside? | F28: [HINT: HOUSEHOLD CONSISTS OF ALL MEMBERS LIVING TOGETHER, SHARING RESOURCES & EATING FROM THE SAME POT.] | G28: [ملحوظة: تتكون الأسرة من جميع الأعضاء الذين يعيشون معًا ، ويتشاركون الموارد ويأكلون من نفس القدر] | I28: true | J28: autocomplete | O28: my_filter_admin=${adm2_pcode} | V28: yes | X28: 8.8 | Y28: =1 | Z28: =IF(X28<>"",X28*Y28,"") | AA28: =IF(AND(X28<>"",V28="yes"),X28*Y28,"")
A29: calculate | B29: adm3_name | Q29: jr:choice-name(${adm3_pcode},'${adm3_pcode}') | V29: yes | Y29: =1 | Z29: =IF(X29<>"",X29*Y29,"") | AA29: =IF(AND(X29<>"",V29="yes"),X29*Y29,"")
A30: select_one admin4 | B30: adm4_pcode | C30: 1.12 حاليًا ، في أي مجتمع تقيم أسرتك؟ | D30: 1.12 Currently, in which Community does your household reside? | F30: [HINT: HOUSEHOLD CONSISTS OF ALL MEMBERS LIVING TOGETHER, SHARING RESOURCES & EATING FROM THE SAME POT.] | G30: [ملحوظة: تتكون الأسرة من جميع الأعضاء الذين يعيشون معًا ، ويتشاركون الموارد ويأكلون من نفس القدر] | I30: true | J30: autocomplete | O30: my_filter_admin=${adm3_pcode} | V30: yes | X30: 10.4 | Y30: =1 | Z30: =IF(X30<>"",X30*Y30,"") | AA30: =IF(AND(X30<>"",V30="yes"),X30*Y30,"")
A31: calculate | B31: adm4_name | Q31: jr:choice-name(${adm4_pcode},'${adm4_pcode}') | V31: yes | Y31: =1 | Z31: =IF(X31<>"",X31*Y31,"") | AA31: =IF(AND(X31<>"",V31="yes"),X31*Y31,"")
A32: select_one agricactivity | B32: hh_agricactivity | C32: 1.13 هل قام أي شخص في أسرتك بإنتاج المحاصيل أو الثروة الحيوانية أو الأسماك وتربية الأحياء المائية للاستهلاك المنزلي أو للبيع خلال الاثني عشر شهرًا الماضية ، بما في ذلك أفراد الأسرة الغير موجودين بغرض الرعي؟ | D32: 1.13 Have you or anyone in your household been producing vegetables, crops, livestock or fish and aquaculture for household consumption or for sale in the past 12 months, including household members currently away for transhumance? | F32: [INSTRUCTIONS: THIS IS THE MAIN SCREENING QUESTION.] [HINT FOR PROBING: Do you cultivate any plants to sale or consume? Do you raise any animals with the intent of selling or consuming them or their products like meat, milk, wool or leather? Is one of your household member currently away with cattle or other animals for transhumance?] | G32: [تعليمات: هذا هو سؤال الفرز الرئيسي] [ملحوظة للتحقيق: هل قمت بزراعة أي نباتات للبيع أو الاستهلاك ؟ هل قمت بتربية أي حيوانات بنية البيع أو الاستهلاك أو انتاج منتجات مثل اللحوم و الالبان و الصوف و الجلد ؟ هل أي فرد من أفراد أسرتك حاليا بعيدًا عن الأسرة مع الماشية أو حيوانات أخري بغرض التنقل الرعوي ؟] | I32: true | V32: yes | X32: 31.372377 | Y32: =1 | Z32: =IF(X32<>"",X32*Y32,"") | AA32: =IF(AND(X32<>"",V32="yes"),X32*Y32,"")
A33: select_one yes_no | B33: hh_agricactivity_conflict | C33: 1.14 هل قام أي شخص في أسرتك بإنتاج المحاصيل أو الثروة الحيوانية أو الأسماك وتربية الأحياء المائية للاستهلاك المنزلي أو للبيع منذ بداية الصراع عام ٢٠١١؟ | D33: 1.14 Have you or anyone in your household been producing vegetables, crops, livestock or fish and aquaculture for household consumption or for sale since the start of the conflict in 2011? | F33: [HINT FOR PROBING: Did you cultivate any plants to sale or consume? Did you raise any animals with the intent of selling or consuming them or their products like meat, milk, wool or leather?] | G33: ملحوظة للتحقيق: هل قمت بزراعة أي نباتات للبيع أو الاستهلاك ؟ هل قمت بتربية أي حيوانات بنية البيع أو الاستهلاك أو انتاج منتجات مثل اللحوم و الالبان و الصوف و الجلد ؟ | I33: true | N33: ${hh_agricactivity}='4'
A34: select_one yes_no | B34: hh_agricactivity_ever | C34: 1.15 هل قام أي شخص في أسرتك بإنتاج المحاصيل أو الثروة الحيوانية أو الأسماك وتربية الأحياء المائية للاستهلاك المنزلي أو للبيع من قبل؟ | D34: 1.15 Have you or anyone in your household ever produced vegetables, crops, livestock or fish and aquaculture for household consumption or for sale? | F34: [HINT FOR PROBING: Did you cultivate any plants to sale or consume? Did you raise any animals with the intent of selling or consuming them or their products like meat, milk, wool or leather?] | G34: ملحوظة للتحقيق: هل قمت بزراعة أي نباتات للبيع أو الاستهلاك ؟ هل قمت بتربية أي حيوانات بنية البيع أو الاستهلاك أو انتاج منتجات مثل اللحوم و الالبان و الصوف و الجلد ؟ | I34: true | N34: ${hh_agricactivity_conflict}='2'
A35: select_one agric_checktime | B35: hh_agricactivity_stopduration | C35: 1.16 منذ متى توقفت أسرتك عن الأنشطة الزراعية؟ | D35: 1.16 For how long has your household stopped agricultural activities? | I35: true | N35: ${hh_agricactivity}='4' and (${hh_agricactivity_conflict}='1' or ${hh_agricactivity_ever}='1')
A36: select_one reason_stop | B36: hh_agricactivity_stopreason | C36: 1.17 لماذا أوقفت أسرتك أنشطتها الزراعية؟ | D36: 1.17 Why has your household stopped agricultural activities? | I36: true | N36: ${hh_agricactivity}='4' and (${hh_agricactivity_conflict}='1' or ${hh_agricactivity_ever}='1')
A37: text | B37: hh_agricactivity_stopreason_otherspecify | C37: 1.18 إذا كانت الإجابة "آخر"، حدد | D37: 1.18 If other, specify. | F37: [INSTRUCTIONS: RECORD THE OPEN RESPONSE GIVEN IN FEW WORDS. ENTER 888 FOR DON'T KNOW AND 999 FOR REFUSED] | G37: [تعليمات: سجل في بضع كلمات الاستجابة المفتوحة المعطاة . أدخل 888 للا أعرف و 999 في حالة الرفض] | I37: true | K37: string-length(.)>=3 | L37: عفوا، الرجاء تقديم نص و شرح اكثر وضوحا. | M37: Sorry, Please provide a much more meaningful text | N37: ${hh_agricactivity_stopreason} = 'other' | V37: yes | Y37: ='Additional information'!$C$14 | Z37: =IF(X37<>"",X37*Y37,"") | AA37: =IF(AND(X37<>"",V37="yes"),X37*Y37,"")
A38: select_one yes_no | B38: hh_agricactivity_resume_will | C38: 1.19 هل تنوي استئناف النشاط الزراعي؟ | D38: 1.19 Are you willing to resume agricultural activity ? | I38: true | N38: ${hh_agricactivity}='4' and (${hh_agricactivity_conflict}='1' or ${hh_agricactivity_ever}='1')
A39: select_one agric_checkresume | B39: hh_agricactivity_resume_date | C39: 1.20 متى تعتقد أن أسرتك ستكون قادر على استئناف الأنشطة الزراعية؟ | D39: 1.20 When do you think that your household will be able to resume agricultural activities? | I39: true | N39: ${hh_agricactivity}='4' and (${hh_agricactivity_conflict}='1' or ${hh_agricactivity_ever}='1') and ${hh_agricactivity_resume_will}='1' | Y39: =1 | Z39: =IF(X39<>"",X39*Y39,"") | AA39: =IF(AND(X39<>"",V39="yes"),X39*Y39,"")
A40: end_group | Z40: =IF(X40<>"",X40*Y40,"") | AA40: =IF(AND(X40<>"",V40="yes"),X40*Y40,"")
A41: begin_group | B41: generalInfo | C41: 2. معلومات عامة | D41: 2. GENERAL INFORMATION | I41: false | N41: ${resp_agree} = '1' and ${hh_agricactivity} != 'ref' and ${hh_agricactivity} != 'dk' | V41: yes | Z41: =IF(X41<>"",X41*Y41,"") | AA41: =IF(AND(X41<>"",V41="yes"),X41*Y41,"")
A42: select_one yes_no | B42: resp_id | C42: 2.1 هل أنت رب الأسرة ؟ | D42: 2.1 Are you the head of household? | F42: [HINT: HOUSEHOLD CONSISTS OF ALL MEMBERS LIVING TOGETHER, SHARING RESOURCES & EATING FROM THE SAME POT] | G42: [.ملحوظة: تتكون الأسرة من جميع الأعضاء الذين يعيشون معًا ، ويتشاركون الموارد ويأكلون من نفس القدر] | I42: true | V42: yes
A43: select_one gender | B43: hh_gender | C43: 2.2 هل رب أسرتك ذكر أم أنثى؟ | D43: 2.2 Is the head of your household male or female? | F43: [HINT: HOUSEHOLD CONSISTS OF ALL MEMBERS LIVING TOGETHER, SHARING RESOURCES & EATING FROM THE SAME POT] | G43: [.ملحوظة: تتكون الأسرة من جميع الأعضاء الذين يعيشون معًا ، ويتشاركون الموارد ويأكلون من نفس القدر] | I43: true | N43: ${resp_id} != '1' | V43: yes | X43: 10.085732 | Y43: =1 | Z43: =IF(X43<>"",X43*Y43,"") | AA43: =IF(AND(X43<>"",V43="yes"),X43*Y43,"")
A44: select_one edu | B44: hh_education | C44: 2.3 ما هو المستوى التعليمي الذي وصل إليه رب الأسرة؟ | D44: 2.3 What is the educational level attained by the head of household? | F44: [HINT: HOUSEHOLD CONSISTS OF ALL MEMBERS LIVING TOGETHER, SHARING RESOURCES & EATING FROM THE SAME POT] | G44: [.ملحوظة: تتكون الأسرة من جميع الأعضاء الذين يعيشون معًا ، ويتشاركون الموارد ويأكلون من نفس القدر] | I44: true | V44: yes | X44: 12.894034 | Y44: =1 | Z44: =IF(X44<>"",X44*Y44,"") | AA44: =IF(AND(X44<>"",V44="yes"),X44*Y44,"")
A45: select_one water | B45: hh_wealth_water | C45: 2.4 من أين تأتي المياه التي تشربونها في المنزل؟ | D45: 2.4 Where does the water that you drink at home come from? | I45: true | V45: yes | X45: 15.265829 | Y45: =1 | Z45: =IF(AND(X45<>"",V45="yes"),X45*Y45,"")
A46: integer | B46: HHSize_adultM | C46: 2.5 كم عدد الذكور البالغين (بين ١٨ و ٦٠ سنة) الذين يعيشون في منزلك؟ | D46: 2.5 How many adult males (between 18 and 60) are living in your household? | F46: [HINT: HOUSEHOLD CONSISTS OF ALL MEMBERS LIVING TOGETHER, SHARING RESOURCES & EATING FROM THE SAME POT. ENTER 888 FOR DON'T KNOW AND 999 FOR REFUSED] | G46: [.ملحوظة: تتكون الأسرة من جميع الأعضاء الذين يعيشون معًا ، ويتشاركون الموارد ويأكلون من نفس القدر] [أدخل 888 للا أعرف و 999 في حالة الرفض] | I46: true | K46: .>=0 and .<25
A47: integer | B47: HHSize_adultF | C47: 2.6 كم عدد الإناث البالغات (بين ١٨ و ٦٠ سنة) اللواتي يعشن في منزلك؟ | D47: 2.6 How many adult females (between 18 and 60) are living in your household? | F47: [HINT: HOUSEHOLD CONSISTS OF ALL MEMBERS LIVING TOGETHER, SHARING RESOURCES & EATING FROM THE SAME POT. ENTER 888 FOR DON'T KNOW AND 999 FOR REFUSED] | G47: [.ملحوظة: تتكون الأسرة من جميع الأعضاء الذين يعيشون معًا ، ويتشاركون الموارد ويأكلون من نفس القدر] [أدخل 888 للا أعرف و 999 في حالة الرفض] | I47: true | K47: .>=0 and .<25
A48: integer | B48: HHSize_elderly | C48: 2.7كم عدد المسنين (فوق ٦٠ سنة) الذين يعيشون في منزلك؟ | D48: 2.7How many elderly (above 60) are living in your household? | F48: [HINT: HOUSEHOLD CONSISTS OF ALL MEMBERS LIVING TOGETHER, SHARING RESOURCES & EATING FROM THE SAME POT. ENTER 888 FOR DON'T KNOW AND 999 FOR REFUSED] | G48: [.ملحوظة: تتكون الأسرة من جميع الأعضاء الذين يعيشون معًا ، ويتشاركون الموارد ويأكلون من نفس القدر] [أدخل 888 للا أعرف و 999 في حالة الرفض] | I48: true | K48: .>=0 and .<25
A49: integer | B49: HHSize_child | C49: 2.8كم عدد القاصرين (بين ٠ و ١٧ سنة) الذين يعيشون في منزلك؟ | D49: 2.8How many minors (between 0 and 17) are living in your household? | F49: [HINT: HOUSEHOLD CONSISTS OF ALL MEMBERS LIVING TOGETHER, SHARING RESOURCES & EATING FROM THE SAME POT. ENTER 888 FOR DON'T KNOW AND 999 FOR REFUSED] | G49: [.ملحوظة: تتكون الأسرة من جميع الأعضاء الذين يعيشون معًا ، ويتشاركون الموارد ويأكلون من نفس القدر] [أدخل 888 للا أعرف و 999 في حالة الرفض] | I49: true | K49: .>=0 and .<25
A50: integer | B50: Dis_num | C50: 2.9هل يوجد في الأسرة أشخاص من ذوي الاحتياجات الخاصة؟ إذا كانت الإجابة بنعم ، فكم عددها؟ | D50: 2.9Does your household include disabled persons? If yes how many disabled? | F50: [HINT: HOUSEHOLD CONSISTS OF ALL MEMBERS LIVING TOGETHER, SHARING RESOURCES & EATING FROM THE SAME POT. ENTER 888 FOR DON'T KNOW AND 999 FOR REFUSED] | G50: [.ملحوظة: تتكون الأسرة من جميع الأعضاء الذين يعيشون معًا ، ويتشاركون الموارد ويأكلون من نفس القدر] [أدخل 888 للا أعرف و 999 في حالة الرفض] | I50: true | K50: .>=0 and .<25
A51: select_one residence | B51: hh_residencetype | C51: 2.10أي من أنواع الإقامة التالية يصف إقامتك بشكل أفضل؟ | D51: 2.10Which in the following types of residence best describes your residence? | F51: [INSTRUCTIONS: READ OUT THE OPTIONS.] [HINT: IF RESPONDENT IS ONLY AWAY FROM THE HOUSEHOLD FOR SHORT SEASONAL WORK (<6 MONTHS) OR TRANSHUMANCE, MAKE SURE TO REFER TO THEIR HOUSEHOLD BACK WHERE THEY TYPICALLY ARE LOCATED.] | G51: [تعليمات: اقرأ الخيارات] [ملحوظة: إذا كان المجيب بعيدًا فقط عن الأسرة للعمل الموسمي القصير (أقل من 6 أشهر) أو بغرض الرعي ، فتأكد من الرجوع إلى أسرته في المكان الذي يوجد فيه عادةً] | I51: true | V51: no | X51: 30.646189 | Y51: =1 | Z51: =IF(X51<>"",X51*Y51,"") | AA51: =IF(AND(X51<>"",V51="yes"),X51*Y51,"")
A52: select_one yes_no | B52: Host_IDP | C52: 2.11 هل تستضيف أسرتك حاليا أي عائلات أو أشخاص نازحين؟ | D52: 2.11 Are you presently hosting any displaced families or people? | I52: true
A53: integer | B53: Host_IDP_num | C53: 2.12 يرجى تحديد عدد النازحين الذين تستضيفهم أسرتك | D53: 2.12 Please provide the number of IDPs hosted by your household. | I53: true | K53: .>=0 and .<50 | N53: ${Host_IDP}='1'
A54: select_multiple asset_prod | B54: hh_asset_prod | C54: 2.13 هل تمتلك أسرتك أي من الأصول الإنتاجية الآتية ؟ | D54: 2.13 Does your household own any of the following productive assets? | F54: [INSTRUCTIONS: MULTIPLE RESPONSES POSSIBLE. READ ANSWER OPTIONS OUT LOUD.] | G54: [تعليمات: عدة استجابات محتملة. يرجي قراءة اختيارات الإجابة بصوت مرتفع] | I54: true | K54: if(selected(.,'none') or selected(.,'dk') or selected(.,'ref'), count-selected(.) = 1, count-selected(.) >= 1) | V54: no | X54: 17 | Y54: =1 | Z54: =IF(X54<>"",X54*Y54,"") | AA54: =IF(AND(X54<>"",V54="yes"),X54*Y54,"")
A55: select_multiple asset_transp | B55: hh_asset_transp | C55: 2.14 هل تمتلك انت أو اي فرد من أفراد أسرتك أي من أصول النقل التالية ؟ | D55: 2.14 Do you or any member of household own any of the following transportation assets? | F55: [INSTRUCTIONS: MULTIPLE RESPONSES POSSIBLE. READ ANSWER OPTIONS OUT LOUD.] | G55: [تعليمات: عدة استجابات محتملة. يرجي قراءة اختيارات الإجابة بصوت مرتفع] | I55: true | K55: if(selected(.,'none') or selected(.,'dk') or selected(.,'ref'), count-selected(.) = 1, count-selected(.) >= 1) | V55: no | X55: 17 | Y55: =1 | Z55: =IF(X55<>"",X55*Y55,"") | AA55: =IF(AND(X55<>"",V55="yes"),X55*Y55,"")
A56: select_one sourceelec | B56: source_elecmain | C56: 2.15 ما هو مصدر الكهرباء الذي تستخدمه معظم الوقت في منزلك؟ | D56: 2.15 What source of electricity is used most of the time in your household? | F56: [INSTRUCTIONS: READ OUT THE OPTIONS.] | G56: [تعليمات: اقرأ الخيارات] | I56: true
A57: text | B57: source_elecmain_other | C57: 2.16 إذا كانت الإجابة "آخر"، حدد | D57: 2.16 If other, specify | F57: [INSTRUCTIONS: RECORD THE OPEN RESPONSE GIVEN IN FEW WORDS. ENTER 888 FOR DON'T KNOW AND 999 FOR REFUSED] | G57: [تعليمات: سجل في بضع كلمات الاستجابة المفتوحة المعطاة . أدخل 888 للا أعرف و 999 في حالة الرفض] | I57: true | K57: string-length(.)>=3 | L57: عفوا، الرجاء تقديم نص و شرح اكثر وضوحا. | M57: Sorry, Please provide a much more meaningful text | N57: ${source_elecmain} = 'other' | Y57: =1 | Z57: =IF(X57<>"",X57*Y57,"") | AA57: =IF(AND(X57<>"",V57="yes"),X57*Y57,"")
A58: integer | B58: source_elecmain_price | C58: 2.17 كم تنفق شهرياً على هذا المصدر للكهرباء؟ (بالدولار الأمريكي) | D58: 2.17 How much do you spend per month on this source of electricity? (in USD) | I58: true | K58: .>=0 and .<=150 | N58: ${source_elecmain} != '1' and ${source_elecmain} != 'ref' and ${source_elecmain} != 'dk'
A59: select_one sourceelec2 | B59: source_elec2 | C59: 2.18 ما هو ثاني أكثر مصدر للكهرباء استخدامًا في منزلك؟ | D59: 2.18 What is the second most used source of electricity in your household? | F59: [INSTRUCTIONS: READ OUT THE OPTIONS.] | G59: [تعليمات: اقرأ الخيارات] | I59: true | K59: ${source_elec2} != ${source_elecmain} | N59: ${source_elecmain} != '1' and ${source_elecmain} != 'ref' and ${source_elecmain} != 'dk'
A60: text | B60: source_elec2_other | C60: 2.19 إذا كانت الإجابة "آخر"، حدد | D60: 2.19 If other, specify | F60: [INSTRUCTIONS: RECORD THE OPEN RESPONSE GIVEN IN FEW WORDS. ENTER 888 FOR DON'T KNOW AND 999 FOR REFUSED] | G60: [تعليمات: سجل في بضع كلمات الاستجابة المفتوحة المعطاة . أدخل 888 للا أعرف و 999 في حالة الرفض] | I60: true | K60: string-length(.)>=3 | L60: عفوا، الرجاء تقديم نص و شرح اكثر وضوحا. | M60: Sorry, Please provide a much more meaningful text | N60: ${source_elecmain} != '1' and ${source_elecmain} != 'ref' and ${source_elecmain} != 'dk' and ${source_elec2} = 'other'
A61: integer | B61: source_elec2_price | C61: 2.20 كم تنفق شهرياً على هذا المصدر للكهرباء؟ (بالدولار الأمريكي) | D61: 2.20 How much do you spend per month on this source of electricity? (in USD) | I61: true | K61: .>=0 and .<=150 | N61: ${source_elecmain} != '1' and ${source_elecmain} != 'ref' and ${source_elecmain} != 'dk' and ${source_elec2} != '7' and ${source_elec2} != 'ref' and ${source_elec2} != 'dk'
A62: end_group | Y62: =1 | Z62: =IF(X62<>"",X62*Y62,"") | AA62: =IF(AND(X62<>"",V62="yes"),X62*Y62,"")
A63: begin_group | B63: Income_Shocks_group | C63: 3. مصادر الدخل وسبل العيش والصدمات | D63: 3. INCOME SOURCES, LIVELIHOODS AND SHOCKS | I63: false | N63: ${resp_agree} = '1' and ${hh_agricactivity} != 'dk' and ${hh_agricactivity} != 'ref' | V63: yes | Y63: =1 | Z63: =IF(X63<>"",X63*Y63,"") | AA63: =IF(AND(X63<>"",V63="yes"),X63*Y63,"")
A64: select_one incomesource1 | B64: income_main | C64: 3.1 ما هو مصدر الدخل الرئيسي لأسرتك منذ الزلزال؟ | D64: 3.1 What has your household's main source of income been since the earthquake? | F64: [INSTRUCTIONS: REFUSED OPTIONS SHOULD BE AVOIDED AS MUCH AS POSSIBLE.] | G64: [تعليمات: يجب تجنب الخيار "رفض الإجابة" قدر الإمكان] | I64: true | J64: minimal | O64: if(${hh_agricactivity}='1',agfilter1='1',if(${hh_agricactivity}='2',agfilter2='2',if(${hh_agricactivity}='3',agfilter3='3',agfilter4='4'))) | V64: yes | X64: 36.928734 | Y64: =1 | Z64: =IF(X64<>"",X64*Y64,"") | AA64: =IF(AND(X64<>"",V64="yes"),X64*Y64,"")
A65: calculate | B65: incomemain | Q65: jr:choice-name(${income_main},'${income_main}') | V65: yes | Y65: =1 | Z65: =IF(X65<>"",X65*Y65,"") | AA65: =IF(AND(X65<>"",V65="yes"),X65*Y65,"")
A66: select_one yes_no | B66: income_main_crop_check | C66: 3.2 هل المحاصيل التي تبيعها هي من إنتاجك أنت أو أي شخص في أسرتك؟ | D66: 3.2 Are the crops that you sell produced by you or anyone in your household? | I66: true | N66: ${income_main} = '1' or ${income_main} = '2' or ${income_main} = '3' | V66: yes | X66: 0 | Y66: =1 | Z66: =IF(X66<>"",X66*Y66,"") | AA66: =IF(AND(X66<>"",V66="yes"),X66*Y66,"")
A67: select_one yes_no | B67: income_main_ls_check | C67: 3.3 هل المواشي ومنتجاتها التي تبيعها هي من إنتاجك أنت أو أي شخص في أسرتك؟ | D67: 3.3 Are the livestock and livestock products that you sell produced by you or anyone in your household? | I67: true | N67: ${income_main} = '4' | V67: yes | X67: 0 | Y67: =1 | Z67: =IF(X67<>"",X67*Y67,"") | AA67: =IF(AND(X67<>"",V67="yes"),X67*Y67,"")
A68: select_one yes_no | B68: income_main_fish_check | C68: 3.4 هل الأسماك/منتجات الأسماك التي تبيعها هي من إنتاجك أنت أو أي شخص في أسرتك؟ | D68: 3.4 Are the fish and/or fish products that you sell also captured or harvested by you or anyone in your household? | I68: true | N68: ${income_main} = '6' | V68: yes | X68: 0 | Y68: =1 | Z68: =IF(X68<>"",X68*Y68,"") | AA68: =IF(AND(X68<>"",V68="yes"),X68*Y68,"")
A69: select_one gender_inc_1 | B69: income_main_gender | C69: 3.5 ما هو جنس الفرد ( الأفراد ) داخل الاسرة الذين يحصلون علي الدخل من هذا المصدر ؟ | D69: 3.5 What is the gender of the household member(s) generating income from this source? | I69: true | N69: ${income_main} != '19' and ${income_main} != 'ref'
A70: select_one gender_inc_2 | B70: income_main_control | C70: 3.6 من هو المتحكم فى الدخل الذي تكسبه الاسرة من هذا المصدر ؟ | D70: 3.6 Who controls the revenue that is earned from this source? | I70: true | N70: ${income_main} != '19' and ${income_main} != 'ref'
A71: select_one change2 | B71: income_main_comp | C71: 3.7 هل تغير دخل أسرتك من ${incomemain} منذ الزلزال مقارنة بنفس الفترة من السنة العادية؟ | D71: 3.7 Has your household's income from ${incomemain} changed since the earthquake compared to the same period of a normal year? | I71: true | N71: ${income_main} != '19' and ${income_main} != 'ref' | V71: yes | X71: 27.242167 | Y71: =1 | Z71: =IF(X71<>"",X71*Y71,"") | AA71: =IF(AND(X71<>"",V71="yes"),X71*Y71,"")
A72: select_one incomesource2 | B72: income_sec | C72: 3.8 ما هو ثاني أهم مصدر دخل لأسرتك منذ الزلزال ؟ | D72: 3.8 What has your household's second most important source of income been since the earthquake? | F72: [INSTRUCTIONS: DON'T KNOW AND REFUSED OPTIONS SHOULD BE AVOIDED AS MUCH AS POSSIBLE.] | G72: [تعليمات: يجب تجنب خيارات الإجابة "لا أعرف" و "رفض الإجابة" قدر الإمكان] | I72: true | J72: minimal | N72: ${income_main} != '19' and ${income_main} != 'ref' | O72: if(${hh_agricactivity}='1',agfilter1='1',if(${hh_agricactivity}='2',agfilter2='2',if(${hh_agricactivity}='3',agfilter3='3',agfilter4='4'))) and not(selected(${income_main}, name)) | V72: yes | X72: 25.308004 | Y72: =1 | Z72: =IF(X72<>"",X72*Y72,"") | AA72: =IF(AND(X72<>"",V72="yes"),X72*Y72,"")
A73: calculate | B73: incomesec | Q73: jr:choice-name(${income_sec},'${income_sec}') | V73: yes | Y73: =1 | Z73: =IF(X73<>"",X73*Y73,"") | AA73: =IF(AND(X73<>"",V73="yes"),X73*Y73,"")
A74: select_one yes_no | B74: income_sec_crop_check | C74: 3.9 هل المحاصيل التي تبيعها هي من إنتاجك أنت أو أي شخص في أسرتك؟ | D74: 3.9 Are the crops that you sell produced by you or anyone in your household? | I74: true | N74: ${income_sec} = '1' or ${income_sec} = '2' or ${income_sec} = '3' | V74: yes | X74: 0 | Y74: =1 | Z74: =IF(X74<>"",X74*Y74,"") | AA74: =IF(AND(X74<>"",V74="yes"),X74*Y74,"")
A75: select_one yes_no | B75: income_sec_ls_check | C75: 3.10 هل المواشي ومنتجاتها التي تبيعها هي من إنتاجك أنت أو أي شخص في أسرتك؟ | D75: 3.10 Are the livestock and livestock products that you sell produced by you or anyone in your household? | I75: true | N75: ${income_sec} = '4' | V75: yes | X75: 0 | Y75: =1 | Z75: =IF(X75<>"",X75*Y75,"") | AA75: =IF(AND(X75<>"",V75="yes"),X75*Y75,"")
A76: select_one yes_no | B76: income_sec_fish_check | C76: 3.11 هل الأسماك/منتجات الأسماك التي تبيعها هي من إنتاجك أنت أو أي شخص في أسرتك؟ | D76: 3.11 Are the fish products that you sell produced by you or anyone in your household? | I76: true | N76: ${income_sec} = '6' | V76: yes | X76: 0 | Y76: =1 | Z76: =IF(X76<>"",X76*Y76,"") | AA76: =IF(AND(X76<>"",V76="yes"),X76*Y76,"")
A77: select_one change2 | B77: income_sec_comp | C77: 3.12 هل تغير دخل أسرتك من ${incomesec} منذ الزلزال مقارنة بنفس الفترة من السنة العادية؟ | D77: 3.12 Has your household's income from ${incomesec} changed since the earthquake compared to the same period of a normal year? | I77: true | N77: ${income_main} != '19' and ${income_main} != 'ref' and ${income_sec} != '19' and ${income_sec} != 'dk' and ${income_sec} != 'ref' | V77: yes | X77: 21.193256 | Y77: =1 | Z77: =IF(X77<>"",X77*Y77,"") | AA77: =IF(AND(X77<>"",V77="yes"),X77*Y77,"")
A78: select_one incomesource3 | B78: income_third | C78: 3.13 ما هو ثالث أهم مصدر دخل لأسرتك منذ الزلزال؟ | D78: 3.13 What has your household's third most important source of income been since the earthquake? | F78: [INSTRUCTIONS: DON'T KNOW AND REFUSED OPTIONS SHOULD BE AVOIDED AS MUCH AS POSSIBLE.] | G78: [تعليمات: يجب تجنب خيارات الإجابة "لا أعرف" و "رفض الإجابة" قدر الإمكان] | I78: true | J78: minimal | N78: ${income_main} != '19' and ${income_main} != 'ref' and ${income_sec} != '19' and ${income_sec} != 'ref' and ${income_sec} != 'dk' | O78: if(${hh_agricactivity}='1',agfilter1='1',if(${hh_agricactivity}='2',agfilter2='2',if(${hh_agricactivity}='3',agfilter3='3',agfilter4='4'))) and not(selected(${income_main}, name) or selected(${income_sec}, name)) | V78: yes | X78: 20.229927 | Y78: =1 | Z78: =IF(X78<>"",X78*Y78,"") | AA78: =IF(AND(X78<>"",V78="yes"),X78*Y78,"")
A79: calculate | B79: incomethird | Q79: jr:choice-name(${income_third},'${income_third}') | V79: yes | Y79: =1 | Z79: =IF(X79<>"",X79*Y79,"") | AA79: =IF(AND(X79<>"",V79="yes"),X79*Y79,"")
A80: select_one yes_no | B80: income_third_crop_check | C80: 3.14 هل المحاصيل التي تبيعها هي من إنتاجك أنت أو أي شخص في أسرتك؟ | D80: 3.14 Are the crops that you sell produced by you or anyone in your household? | I80: true | N80: ${income_third} = '1' or ${income_third} = '2' or ${income_third} = '3' | V80: yes | X80: 0 | Y80: =1 | Z80: =IF(X80<>"",X80*Y80,"") | AA80: =IF(AND(X80<>"",V80="yes"),X80*Y80,"")
A81: select_one yes_no | B81: income_third_ls_check | C81: 3.15 هل المواشي ومنتجاتها التي تبيعها هي من إنتاجك أنت أو أي شخص في أسرتك؟ | D81: 3.15 Are the livestock and livestock products that you sell produced by you or anyone in your household? | I81: true | N81: ${income_third} = '4' | V81: yes | X81: 0 | Y81: =1 | Z81: =IF(X81<>"",X81*Y81,"") | AA81: =IF(AND(X81<>"",V81="yes"),X81*Y81,"")
A82: select_one yes_no | B82: income_third_fish_check | C82: 3.16 هل الأسماك/منتجات الأسماك التي تبيعها هي من إنتاجك أنت أو أي شخص في أسرتك؟ | D82: 3.16 Are the fish products that you sell produced by you or anyone in your household? | I82: true | N82: ${income_third} = '6' | V82: yes | X82: 0 | Y82: =1 | Z82: =IF(X82<>"",X82*Y82,"") | AA82: =IF(AND(X82<>"",V82="yes"),X82*Y82,"")
A83: select_one change2 | B83: income_third_comp | C83: 3.17 هل تغير دخل أسرتك من ${incomethird} منذ الزلزال مقارنة بنفس الفترة من السنة العادية؟ | D83: 3.17 Has your household's income from ${incomethird} changed since the earthquake compared to the same period of a normal year? | I83: true | N83: ${income_main} != '19' and ${income_main} != 'ref' and ${income_sec} != '19' and ${income_sec} != 'ref' and ${income_sec} != 'dk' and ${income_third} != '19' and ${income_third} != 'ref' and ${income_third} != 'dk' | V83: yes | X83: 16.348396
A84: select_one incomesource1 | B84: income_main_lastyear | C84: 3.18 ماذا كان مصدر الدخل الرئيسي لأسرتك خلال نفس الفترة من العام الماضي؟ | D84: 3.18 What was your household's main source of income during the same period of last year? | F84: [INSTRUCTIONS: REFUSED OPTIONS SHOULD BE AVOIDED AS MUCH AS POSSIBLE.] | G84: [تعليمات: يجب تجنب الخيار "رفض الإجابة" قدر الإمكان] | I84: true | J84: minimal | O84: if(${hh_agricactivity}='1',agfilter1='1',if(${hh_agricactivity}='2',agfilter2='2',if(${hh_agricactivity}='3',agfilter3='3',agfilter4='4'))) | V84: yes | X84: 36.928734 | Y84: =1 | Z84: =IF(X84<>"",X84*Y84,"") | AA84: =IF(AND(X84<>"",V84="yes"),X84*Y84,"")
A85: select_multiple shock | B85: shock | C85: 3.19 هل واجهت أسرتك أو هل واجه مجتمعك أي كارثة أو أزمة معينة أثرت على قدرة أسرتك على توليد الدخل و / أو إنتاج الغذاء للاستهلاك الذاتي منذ الزلزال ، وإذا كان الأمر كذلك ، فما كانت؟ | D85: 3.19 Has your household or community faced any particular disaster or crisis affecting your household's ability to raise an income and/or to produce food for self consumption since the earthquake, and if so, which ones? | F85: [INSTRUCTIONS: SELECT RELEVANT SHOCKS EXPERIENCED BY THE HOUSEHOLD. MULTIPLE RESPONSES POSSIBLE. REFER TO ECONOMIC SHOCKS, CROP AND LIVESTOCK SHOCKS, INTRA-HOUSEHOLD SHOCK, NATURAL HAZARDS AND HUMAN-INDUCED HAZARDS.] | G85: [تعليمات: حدد الصدمات ذات الصلة التي اختبرتها الأسرة. استجابات متعددة ممكنة. راجع الصدمات الاقتصادية والصدمات التي تصيب المحصول والمواشي و داخل الأسرة والمخاطر الطبيعية والأخطار التي يسببها الإنسان] | I85: true | K85: if(selected(.,'noshock') or selected(.,'dk') or selected(.,'ref'), count-selected(.) = 1, count-selected(.) >= 1) | V85: yes | X85: 46.247528 | Y85: =1 | Z85: =IF(X85<>"",X85*Y85,"") | AA85: =IF(AND(X85<>"",V85="yes"),X85*Y85,"")
A86: end_group | Z86: =IF(X86<>"",X86*Y86,"") | AA86: =IF(AND(X86<>"",V86="yes"),X86*Y86,"")
A87: begin_group | B87: CropProduction_group | C87: 4. إنتاج المحاصيل | D87: 4. CROP PRODUCTION | I87: false | N87: ${resp_agree} = '1' and (${hh_agricactivity}='1' or ${hh_agricactivity} = '3' or ${income_main_crop_check}='1' or ${income_sec_crop_check}='1' or ${income_third_crop_check}='1') | V87: yes | Z87: =IF(X87<>"",X87*Y87,"") | AA87: =IF(AND(X87<>"",V87="yes"),X87*Y87,"")
A88: note | B88: crp_intro | C88: سنطرح عليك الآن بعض الأسئلة حول إنتاج المحاصيل التي تنطبق عليك وعلى أي شخص في أسرتك يشارك في إنتاج المحاصيل أو بيعها. تشير جميع الأسئلة إلى المحاصيل المزروعة خلال موسم الأمطار. | D88: We will now ask you some questions about crop production which apply to you and anyone in your household that is involved in crop production or sales. All questions refer to the crops grown during the wet season. | I88: false | V88: yes | X88: 7.5 | Y88: ='Additional information'!$C$14 | Z88: =IF(X88<>"",X88*Y88,"") | AA88: =IF(AND(X88<>"",V88="yes"),X88*Y88,"")
A89: decimal | B89: crp_landsize_num | C89: 4.1 ما هو الحجم الإجمالي للأرض التي يمكنك الوصول إليها لإنتاج المحاصيل؟؟ | D89: 4.1 What is the total size of the land you have access to for crop production? | F89: [INSTRUCTIONS: RECORD THE TOTAL LAND SIZE PROVIDED BY THE RESPONDENT. WRITE 888 FOR DON'T KNOW AND 999 FOR REFUSED. MEASUREMENT UNIT WILL BE SPECIFIED IN THE FOLLOWING QUESTION.] | G89: [تعليمات: سجل إجمالي حجم الأرض الذي ذكره المجيب. اكتب 888 للا أعرف و 999 في حالة الرفض. سيتم تحديد وحدة القياس في السؤال التالي] | I89: true | K89: . >= 0 | V89: yes | X89: 17 | Y89: ='Additional information'!$C$14 | Z89: =IF(X89<>"",X89*Y89,"") | AA89: =IF(AND(X89<>"",V89="yes"),X89*Y89,"")
A90: select_one landsize_unit | B90: crp_landsize_unit | C90: 4.2 وحدة قياس مساحة الارض: | D90: 4.2 Unit of measurement for land size: | F90: [INSTRUCTIONS: DO NOT READ QUESTION. SELECT UNIT OF MEASUREMENT IN WHICH LAND SIZE WAS PROVIDED.] | G90: [تعليمات: لا تقرأ السؤال. حدد وحدة القياس لمساحة الأرض] | I90: true | N90: ${crp_landsize_num} != 888 and ${crp_landsize_num} != 999 | V90: yes | X90: 0 | Y90: ='Additional information'!$C$14 | Z90: =IF(X90<>"",X90*Y90,"") | AA90: =IF(AND(X90<>"",V90="yes"),X90*Y90,"")
A91: decimal | B91: AreaPlanted | C91: 4.3 ما هو الحجم الإجمالي للأرض التي زرعتها هذا العام؟ | D91: 4.3 What is the total size of land that you have planted this year? | F91: Using the same unit of measure that was chosen | G91: باستخدام نفس وحدة القياس التي تم اختيارها | I91: true | K91: . <= ${crp_landsize_num}
A92: select_one crop | B92: crp_main | C92: 4.4 ما هو المحصول الرئيسي الذي تزرعه أسرتك من أجل الغذاء وتوليد الدخل في موسم الأمطار ، إن وجد؟ | D92: 4.4 What is the main crop that your household grows for food or income generation in wet season, if any? | F92: [INSTRUCTIONS: "NO CROP PRODUCTION" APPEARS AT THE END OF THE LIST OF OPTIONS.] | G92: [تعليمات: "لا إنتاج للمحصول" في آخر الخيارات في النهاية] | I92: true | J92: autocomplete | V92: yes | X92: 27.057552 | Y92: ='Additional information'!$C$14 | Z92: =IF(X92<>"",X92*Y92,"") | AA92: =IF(AND(X92<>"",V92="yes"),X92*Y92,"")
A93: calculate | B93: crpmain | Q93: jr:choice-name(${crp_main},'${crp_main}') | V93: yes | Y93: ='Additional information'!$C$14 | Z93: =IF(X93<>"",X93*Y93,"") | AA93: =IF(AND(X93<>"",V93="yes"),X93*Y93,"")
A94: select_one cropcheck | B94: crp_main_check | C94: 4.5 لماذا لم تنتج أي محاصيل في الموسم الحالي ؟ | D94: 4.5 Why did you not produce any crops in Current season? | I94: true | N94: ${crp_main} = '777' | V94: yes | X94: 0 | Y94: ='[1]Additional information'!$D$18 | Z94: =IF(X94<>"",X94*Y94,"")
A95: begin_group | B95: cul_area | C95: المساحة المزروعة | D95: The cultivated area | J95: field-list
A96: note | B96: crp_area_change | C96: هل يمكنك من فضلك تحديد المساحة التي قمت بزراعتها في الأشهر الثلاثة الماضية لكل مجموعة من المحاصيل أدناه: | D96: Can you please indicate the area you have cultivated in the past three months for each group of crops below | I96: false | N96: ${AreaPlanted} > 0
A97: decimal | B97: AreaPlantedGrains | C97: 4.5 الحبوب والمحاصيل الزيتية (القمح والذرة و حبة البركة ، إلخ) | D97: 4.5 Grains and oil crops (wheat, corn, black caraway, etc) | I97: true | K97: .<=${AreaPlanted} and .>=0 | L97: This a positive number that shouldn't exceed the total area planted | M97: هذا رقم موجب لا ينبغي أن يتجاوز إجمالي المساحة المزروعة | N97: ${AreaPlanted} > 0
A98: select_one landsize_unit | B98: AreaPlantedGrains_unit | C98: 4.6 وحدة قياس مساحة الارض: | D98: 4.6 Unit of measurement for land size: | I98: true | J98: minimal | N98: ${AreaPlantedGrains} > 0 | O98: my_filter_admin=${crp_landsize_unit}
A99: select_one AreaPlantedcompare | B99: AreacompareGrains | C99: 4.7 مقارنة بالعام الماضي ، حدد ما إذا كانت المساحة التي قمت بزراعتها هذا العام قد زادت أو انخفضت لنفس الفترة بالنسبة للحبوب والمحاصيل الزيتية؟ | D99: 4.7 Compared to last year, indicate if the area you have cultivated this year increased or decreased for the same period for grains and oil crops? | I99: true | J99: minimal | N99: ${AreaPlantedGrains} > 0
A100: select_one change_reason | B100: AreacompareGrains_reason | C100: 4.8 ما هو سبب هذا التغيير؟ | D100: 4.8 What is the reason for this change? | I100: true | J100: minimal | N100: ${AreacompareGrains} = '5' or ${AreacompareGrains} = '6' or ${AreacompareGrains} = '7'
...

Sheet choices
A1: list_name | B1: name | C1: label::English (en) | D1: label::Arabic (ar) | E1: label:: | F1: my_filter_admin | G1: agfilter1 | H1: agfilter2 | I1: agfilter3 | J1: agfilter4
A2: enumteam | B2: 1 | C2: 1. Al Bab | D2: 1. الباب
A3: enumteam | B3: 2 | C3: 2. Afrin | D3: 2. عفرين
A4: enumteam | B4: 3 | C4: 3. A'zaz | D4: 3. اعزاز
A5: enumteam | B5: 4 | C5: 4. Jarablus | D5: 4. جرابلس
A6: enumteam | B6: 5 | C6: 5. Harim | D6: 5. حارم
A7: enumteam | B7: 6 | C7: 6. Idleb | D7: 6. إدلب
A8: enumteam | B8: 7 | C8: 7. Jebel Saman | D8: 7. جبل سمعان
A10: enumerator | B10: 1 | C10: C1202AS009 | D10: C1202AS009 | F10: 1
A11: enumerator | B11: 2 | C11: C1202BS020 | D11: C1202BS020 | F11: 1
A12: enumerator | B12: 3 | C12: C1202TT013 | D12: C1202TT013 | F12: 1
A13: enumerator | B13: 4 | C13: C1202ME002 | D13: C1202ME002 | F13: 1
A14: enumerator | B14: 5 | C14: C1202BA010 | D14: C1202BA010 | F14: 1
A15: enumerator | B15: 6 | C15: C1202FA003 | D15: C1202FA003 | F15: 1
A16: enumerator | B16: 7 | C16: SY020304MI002 | D16: SY020304MI002 | F16: 2
A17: enumerator | B17: 8 | C17: C1366MM015 | D17: C1366MM015 | F17: 2
A18: enumerator | B18: 9 | C18: C6115FA001 | D18: C6115FA001 | F18: 2
A19: enumerator | B19: 10 | C19: SY020301MI003 | D19: SY020301MI003 | F19: 2
A20: enumerator | B20: 11 | C20: SY020301LA002 | D20: SY020301LA002 | F20: 2
A21: enumerator | B21: 12 | C21: C6287MS002 | D21: C6287MS002 | F21: 2
... A61: enumerator | B61: 52 | C61: C1022BE023 | D61: C1022BE023 | F61: 7
A63: yes_no | B63: 1 | C63: Yes | D63: نعم
A64: yes_no | B64: 2 | C64: No | D64: لا
A65: yes_no | B65: dk | C65: Don't know | D65: لا أعرف
A66: yes_no | B66: ref | C66: Refused | D66: رفض الإجابة
A68: continue | B68: continue | C68: continue | D68: تابع
A70: yesno | B70: 1 | C70: Yes | D70: نعم
A71: yesno | B71: 2 | C71: No | D71: لا
A73: language | B73: en | C73: English | D73: الإنجليزية
A74: language | B74: ar | C74: Arabic | D74: العربية
A76: gender | B76: 1 | C76: Male | D76: ذكر
A77: gender | B77: 2 | C77: Female | D77: أنثى
A78: gender | B78: dk | C78: Don't know | D78: لا أعرف
A79: gender | B79: ref | C79: Refused | D79: رفض الإجابة
A81: contact_info | B81: 1 | C81: YES - mine | D81: نعم - لي
A82: contact_info | B82: 2 | C82: YES - other household member | D82: نعم - فرد اخر من أفراد الأسرة
A83: contact_info | B83: 3 | C83: YES - friend or relative (non-household member) | D83: نعم - أحد الأقارب او الاصدقاء [ ليس فردا من أفراد الأسرة]
A84: contact_info | B84: 4 | C84: NO | D84: لا
C86: Wheat | D86: القمح
C87: Maize | D87: الذرة
C88: Barley | D88: الشعير
C89: Potatoe | D89: البطاطا
C90: Beans | D90: الفاصوليا
C91: Lentils | D91: العدس
C92: Peas | D92: البازيلاء
C93: Soybeans | D93: فول الصويا
C94: Chickpeas | D94: الحمص
C95: Fava beans | D95: الفول
C96: Lettuce | D96: الخس
C97: Green salad herbs (thyme, parsley, mint, rocca, other) | D97: أعشاب السلطة الخضراء [زعتر ، بقدونس ، نعناع ، جرجير ، أنواع أخرى]
... C114: No crop production | D114: لا شيء
A116: agricactivity | B116: 1 | C116: Yes - crop production | D116: نعم - إنتاج المحاصيل
A117: agricactivity | B117: 2 | C117: Yes - livestock production | D117: نعم - إنتاج الماشية
A118: agricactivity | B118: 3 | C118: Yes - both crop and livestock production | D118: نعم - كل من إنتاج المحاصيل والماشية
A119: agricactivity | B119: 4 | C119: No | D119: لا
A120: agricactivity | B120: dk | C120: Don't know | D120: لا أعرف
A121: agricactivity | B121: ref | C121: Refused | D121: رفض الإجابة
A123: edu | B123: 1 | C123: None or did not complete primary school | D123: لا شيء أو لم يكمل المرحلة الابتدائية
A124: edu | B124: 2 | C124: Completed primary school | D124: أكمل المرحلة الابتدائية
A125: edu | B125: 3 | C125: Completed secondary school | D125: أكمل المرحلة الثانوية
A126: edu | B126: 4 | C126: Completed higher education [University / College] degree | D126: أكمل درجة تعليم عالي [جامعة / كلية]
A127: edu | B127: 5 | C127: Religious or informal education only | D127: تربية دينية أو غير رسمية فقط
A128: edu | B128: dk | C128: Don't know | D128: لا أعرف
A129: edu | B129: ref | C129: Refused | D129: رفض الإجابة
A131: residence | B131: 1 | C131: Permanent Resident - you have been living in your village / town for longer than two years and this is what you consider your habitual residence | D131: مقيم دائم - تعيش في قريتك / بلدتك لمدة تزيد عن عامين وهذا ما تعتبره مكان إقامتك المعتاد
A132: residence | B132: 2 | C132: Recent migrant not forcefully displaced - you have been living in your current place of residence for less than two years and you moved there voluntarily for work / family or other reasons that are not related to conflict or natural disaster | D132: مهاجر حديث لم ينزح قسراً - تعيش في مكان إقامتك الحالي لمدة تقل عن عامين وانتقلت إلى هناك بمحض ارادتك من أجل العمل/ الأسرة أو لأسباب أخرى لا تتعلق بالنزاعات أو الكوارث الطبيعية
A133: residence | B133: 3 | C133: Returnee (from within country) - you have only come back to this residence in the last two years after having been forced to move to another location having fled conflict or natural disaster [if return was over 2 years ago the respondent is considered a permanent resident] | D133: عائد (من داخل البلد) - لقد عدت إلى مكان إقامتك الحالي في العامين الماضيين فقط بعد أن أجبرت على الانتقال إلى مكان آخر للهرب من نزاع أو كارثة طبيعية [إذا تمت العودة منذ أكثر من عامين ، يُعتبر المجيب مقيمًا دائمًا]
A134: residence | B134: 4 | C134: Returnee (from outside country) - you have only come back to this residence in the last two years after having been forced to move to another location having fled conflict or natural disaster [if return was over 2 years ago the respondent is considered a permanent resident] | D134: عائد (من خارج البلد) - لقد عدت إلى مكان إقامتك الحالي في العامين الماضيين فقط بعد أن أجبرت على الانتقال إلى مكان آخر للهرب من نزاع أو كارثة طبيعية [إذا تمت العودة منذ أكثر من عامين ، يُعتبر المجيب مقيمًا دائمًا]
A135: residence | B135: 5 | C135: Internally displaced person [IDP] - you were forced to flee your village or town because of conflict or natural disaster and you are now an internally displaced person in your current place of residence | D135: شخص نازح داخليًا [IDP] - لقد أُجبرت على الفرار من قريتك أو بلدتك بسبب نزاع أو كارثة طبيعية وأنت الآن نازح داخليًا في مكان إقامتك الحالي
A136: residence | B136: 6 | C136: Refugee - you were forced to flee your country because of conflict or natural disaster and you are now a refugee in your current place of residence | D136: لاجئ - لقد أُجبرت على الفرار من بلدك بسبب نزاع أو كارثة طبيعية وأنت الآن لاجئ في مكان إقامتك الحالي
A137: residence | B137: dk | C137: Don't know | D137: لا أعرف
A138: residence | B138: ref | C138: Refused | D138: رفض الإجابة
A140: asset_prod | B140: land | C140: Productive agricultural land | D140: أرض زراعية منتجة
A141: asset_prod | B141: livestock | C141: Productive animals | D141: حيوانات منتجة
A142: asset_prod | B142: process | C142: Processing assets (e.g. grinding/crushing machine, mill, oil press) | D142: أصول المعالجة (على سبيل المثال ماكينات الطحن و العصر)
A143: asset_prod | B143: farmmach | C143: Farm machinery (e.g. tractor, plough, sickle, etc.) | D143: آلات زراعية ( جرار زراعي ، محراث، منجل ، غيرها)
A144: asset_prod | B144: sewing | C144: Sewing machine or weaving tool | D144: ماكينات الخياطة و حياكة الصوف
A145: asset_prod | B145: taxi | C145: Taxi | D145: تاكسي (سيارة أجرة)
A146: asset_prod | B146: truck | C146: Truck | D146: شاحنة
A147: asset_prod | B147: other | C147: Other productive machines or assets | D147: آلات و معدات انتاجية أخرى
A148: asset_prod | B148: none | C148: No productive machines or assets | D148: لا تمتلك أي آلات أو أصول انتاجية
A149: asset_prod | B149: dk | C149: Don't know | D149: لا أعرف
... A161: asset_transp | B161: ref | C161: Refused | D161: رفض الإجابة
A163: incomesource1 | B163: 1 | C163: Production and sale of staple crops | D163: إنتاج وبيع المحاصيل الأساسية | G163: 1 | I163: 3
A164: incomesource1 | B164: 2 | C164: Production and sale of vegetables or fruit | D164: إنتاج وبيع الخضار أو الفاكهة | G164: 1 | I164: 3
A165: incomesource1 | B165: 3 | C165: Production and sale of cashcrops | D165: إنتاج وبيع المحاصيل النقدية | G165: 1 | I165: 3
A166: incomesource1 | B166: 4 | C166: Production and sale of livestock and livestock products | D166: إنتاج وبيع المواشي ومنتجاتها | H166: 2 | I166: 3
A167: incomesource1 | B167: 5 | C167: Production and sale of honey and bee products | D167: انتاج و بيع العسل أو منتجات النحل | G167: 1 | H167: 2 | I167: 3 | J167: 4
A168: incomesource1 | B168: 6 | C168: Production and sale of fish | D168: إنتاج وبيع الأسماك | G168: 1 | H168: 2 | I168: 3 | J168: 4
A169: incomesource1 | B169: 7 | C169: Collection and sale of natural resources (including forestry or bush products) | D169: جمع وبيع منتجات الغابات أو الأحراش | G169: 1 | H169: 2 | I169: 3 | J169: 4
A170: incomesource1 | B170: 8 | C170: Agricultural trade EXCLUDING producers (formal or informal) | D170: التجارة الزراعية الرسمية و غير الرسمية باستثناء المنتجين | G170: 1 | H170: 2 | I170: 3 | J170: 4
A171: incomesource1 | B171: 9 | C171: Daily wage on farms and other casual employment in agricultural sector | D171: الأجر اليومي في المزارع وغيرها من العمالة العرضية في قطاع الزراعة | G171: 1 | H171: 2 | I171: 3 | J171: 4
A172: incomesource1 | B172: 10 | C172: Stable employment in agricultural sector | D172: العمالة المستقرة في القطاع الزراعي | G172: 1 | H172: 2 | I172: 3 | J172: 4
A173: incomesource1 | B173: 11 | C173: Non-agricultural self-employed or liberal profession, doctor, architect, lawyer, including restaurant | D173: العاملين لحسابهم الخاص غير الزراعيين أو المهنة الحرة / طبيب / مهندس معماري / محامٍ / بما في ذلك مطعم | G173: 1 | H173: 2 | I173: 3 | J173: 4
A174: incomesource1 | B174: 12 | C174: Off-farm daily wages and other non-agricultural casual employment | D174: الأجور اليومية خارج المزرعة وغيرها من العمالة العرضية غير الزراعية | G174: 1 | H174: 2 | I174: 3 | J174: 4
A175: incomesource1 | B175: 13 | C175: Stable employment in non-agricultural sector | D175: العمالة المستقرة في القطاع غير الزراعي | G175: 1 | H175: 2 | I175: 3 | J175: 4
A176: incomesource1 | B176: 14 | C176: Public employment | D176: الوظائف العامة | G176: 1 | H176: 2 | I176: 3 | J176: 4
A177: incomesource1 | B177: 15 | C177: Income not derived from work / Charity | D177: الدخل غير المستمد من العمل / الاعمال الخيرية | G177: 1 | H177: 2 | I177: 3 | J177: 4
A178: incomesource1 | B178: 16 | C178: Income not derived from work / Welfare transfer, pension, humanitarian aid | D178: الدخل غير المستمد من العمل / المدفوعات التحويلية ، المعاش التقاعدي ، المساعدات الإنسانية | G178: 1 | H178: 2 | I178: 3 | J178: 4
... A181: incomesource1 | B181: 19 | C181: No income source in the last 3 months and used exclusively savings / debts | D181: لم يكن هناك مصدر دخل خلال الأشهر الثلاثة الماضية واستخدمت المدخرات أو الدين حصريًا | G181: 1 | H181: 2 | I181: 3 | J181: 4
...

Sheet settings
A1: version | B1: default_language | C1: allow_choice_duplicates | D1: style
A2: vM6cWXyHNhR3djPbARkHWi | B2: Arabic (ar) | C2: yes | D2: theme-grid no-text-transform

Sheet Crop list
C3: Select top 10 crops / حدد أكبر 10 محاصيل | D3: Dataset code | E3: Label (EN) | F3: Label (AR)
D4: 1.1 | E4: Rice | F4: الرز
C5: x | D5: 1.2 | E5: Wheat | F5: القمح
D6: 1.3 | E6: Millet | F6: الدخن
D7: 1.4 | E7: Sorghum | F7: الذرة الرفيعة
C8: x | D8: 1.5 | E8: Maize | F8: الذرة
C9: x | D9: 1.6 | E9: Barley | F9: الشعير
D10: 1.99 | E10: Other Cereal | F10: الحبوب الأخرى
D11: 2.1 | E11: Cassava | F11: الكسافا
C12: x | D12: 2.2 | E12: Potatoe | F12: البطاطا
D13: 2.3 | E13: Sweet Potatoes | F13: البطاطا الحلوة
D14: 2.4 | E14: Yams | F14: اليام
D15: 2.5 | E15: Carrots | F15: الجزر
D16: 2.6 | E16: Cocoyam | F16: القلقاس
D17: 2.99 | E17: Other tubers | F17: الدرنات الأخرى
C18: x | D18: 3.1 | E18: Beans | F18: الفاصوليا
C19: x | D19: 3.2 | E19: Lentils | F19: العدس
C20: x | D20: 3.3 | E20: Peas | F20: البازيلاء
C21: x | D21: 3.4 | E21: Soybeans | F21: فول الصويا
C22: x | D22: 3.5 | E22: Chickpeas | F22: الحمص
C23: x | D23: 3.6 | E23: Fava beans | F23: الفول
D24: 3.7 | E24: Broad beans | F24: الفاصوليا العريضة
D25: 3.99 | E25: Other pulses | F25: البقول الاخرى
D26: 4.1 | E26: Cabbage | F26: الملفوف
C27: x | D27: 4.2 | E27: Lettuce | F27: الخس
D28: 4.3 | E28: Spinach-Amaranth | F28: السبانخ - القطيفة
D29: 4.4 | E29: Cassava leaves | F29: أوراق الكسافا
D30: 4.5 | E30: Potatoe leaves | F30: أوراق البطاطا
D31: 4.6 | E31: Moringa | F31: المورينجا
D32: 4.7 | E32: Sorrel Hibiscus / Rosselle | F32: الكركديه
C33: x | D33: 4.9 | E33: Green salad herbs (thyme, parsley, mint, rocca, other) | F33: أعشاب السلطة الخضراء [زعتر ، بقدونس ، نعناع ، جرجير ، أنواع أخرى]
D34: 4.101 | E34: Cauliflower | F34: القرنبيط
D35: 4.99 | E35: Other leafy vegetables | F35: الخضار الورقية الأخرى
C36: x | D36: 5.1 | E36: Tomatoes | F36: الطماطم
C37: x | D37: 5.2 | E37: Cucumber | F37: الخيار
D38: 5.3 | E38: Pumpkin | F38: اليقطين
C39: x | D39: 5.4 | E39: Eggplant/aubergine | F39: الباذنجان
C40: x | D40: 5.5 | E40: Zucchini | F40: الكوسة
C41: x | D41: 5.6 | E41: Okra | F41: البامية
C42: x | D42: 5.7 | E42: Bell pepper | F42: الفلفل حلو
C43: x | D43: 5.8 | E43: Onions | F43: بصل
D44: 5.9 | E44: Haricot | F44: اللوبياء
C45: x | D45: 5.101 | E45: Green peas | F45: البازلاء الخضراء
C46: x | D46: 5.11 | E46: Fava beans green | F46: الفول الأخضر
D47: 5.99 | E47: Other non leafy vegs | F47: الخضار غير الورقية الأخرى
D48: 6.1 | E48: Orange | F48: البرتقال
D49: 6.2 | E49: Lemon | F49: الليمون
D50: 6.3 | E50: Grapefruit | F50: الجريب فروت
D51: 6.4 | E51: Mandarins/clementines | F51: اليوسفي / الكليمنتين
D52: 6.99 | E52: Other citrus fruit | F52: الحمضيات الأخرى
D53: 7.1 | E53: Sweet Banana | F53: الموز
D54: 7.2 | E54: Plantains | F54: موز الجنة
D55: 7.3 | E55: Papaya | F55: البابايا
D56: 7.4 | E56: Mango | F56: المانجو
D57: 7.5 | E57: Guava | F57: الجوافة
D58: 7.6 | E58: Pineapple | F58: الأناناس
D59: 7.7 | E59: Avocado | F59: الأفوكادو
C60: x | D60: 7.8 | E60: Water Melon | F60: البطيخ الأحمر
D61: 7.9 | E61: Dates | F61: التمر
D62: 7.101 | E62: Figs | F62: التين
C63: x | D63: 7.11 | E63: Grapes | F63: العنب
C64: x | D64: 7.12 | E64: Olives | F64: الزيتون
D65: 7.13 | E65: Apple | F65: التفاح
D66: 7.14 | E66: Apricot | F66: المشمش
C67: x | D67: 7.15 | E67: Cherries | F67: الكرز
D68: 7.16 | E68: Peach/nectarine | F68: الدراق / النكتارين
D69: 7.17 | E69: Strawberries | F69: الفراولة
D70: 7.18 | E70: Melon (Cantaloupe) | F70: الشمام
D71: 7.99 | E71: Other fruit | F71: الفواكه الأخرى
D72: 8.1 | E72: Coconuts | F72: جوز الهند
D73: 8.2 | E73: Groundnut/peanut | F73: الفول السوداني
D74: 8.3 | E74: Cashew Nut | F74: الكاجو
D75: 8.4 | E75: Kola Nut | F75: جوز الكولا
C76: x | D76: 8.5 | E76: Sesame | F76: السمسم
D77: 8.6 | E77: Bambara nut | F77: جوز البامبارا
C78: x | D78: 8.7 | E78: Almond | F78: اللوز
D79: 8.8 | E79: Walnut | F79: الجوز
D80: 8.99 | E80: Other nuts | F80: المكسرات الأخرى
D81: 9.1 | E81: Cocoa | F81: الكاكاو
D82: 9.2 | E82: Coffee | F82: القهوة
D83: 9.3 | E83: Tea | F83: الشاي
D84: 9.4 | E84: Sugarcane | F84: قصب السكر
D85: 9.5 | E85: Sunflower | F85: دوار الشمس
D86: 9.99 | E86: Other food cash crop | F86: المحاصيل الغذائية النقدية الأخرى
D87: 10.1 | E87: Cotton | F87: القطن
D88: 10.2 | E88: Rubber | F88: المطاط
D89: 10.3 | E89: Jute | F89: الجوت
D90: 10.4 | E90: Fodder | F90: العلف
... D93: 10.99 | E93: Other non-food cash crop | F93: المحاصيل النقدية غير الغذائية الأخرى

Sheet Additional information
B2: Original | C2: Replacement (AR) | D2: Replacement (EN) | E2: Comment (AR) | F2: Comment (EN) | G2: Exemple (AR) | H2: Example(EN)
B3: age | C3: 16 | D3: =IF(C3="","",C3) | E3: الحد الأدنى لسن المجيب (يفضل أن يكون عمره 18 عامًا على الأقل). يرجى إدخال الأرقام في الأبجدية اللاتينية (...3, 2, 1). | F3: Minimum age of respondent (recommend 18 years old). Only digits in Latin numbers should be inputted. | G3: 18 | H3: 18
B4: ADMIN1 | C4: المحافظة | D4: Governorate | E4: التقسيم الأول للبلاد ، بعد المستوى الوطني ؛ منطقة؛ محافظة؛ ولاية ؛ إلخ. يجب إدخال كلمة واحدة فقط - لا تقم بتضمين مسافات. | F4: The first subdivision of the country, after national level; region; province; governorate; etc. Only one word should be inputted - Do not include spaces. | G4: منطقة | H4: region
B5: ADMIN2 | C5: المنطقة | D5: District | E5: التقسيم الثاني للبلاد ؛ قضاء؛ بلدية؛ إلخ. يجب إدخال كلمة واحدة فقط - لا تقم بتضمين مسافات. | F5: The second subdivision of the country; district; municipality; LGA; etc. Only one word should be inputted - Do not include spaces. | G5: قضاء | H5: district
B6: ADMIN 3 | C6: الناحية | D6: Sub-District
B7: ADMIN 4 | C7: القرية | D7: Community
B8: reference year | C8: العام العادي | D8: Normal year | E8: سوف تحتاج أسئلة المقارنة إلى سنة مرجعية. حدد ما إذا كنت تريد استخدام "العام الماضي" أو "العام العادي" كخط أساس. يجب أن يشير "العام العادي" إلى متوسط ​​عام من السنوات الخمس الماضية - تأكد من تدريب جامعي البيانات وفقًا لذلك. | F8: Comparison questions will need need a reference year. Select whether you want to use "last year" or "a normal year" as a baseline. A "normal year" should refers to an average year from the past 5 years - make sure to train the enumerators accordingly. | G8: العام العادي | H8: a normal year
B9: season | C9: الموسم الجاري | D9: ongoing season | E9: قم بتسمية موسم (مواسم) المحاصيل ذات الأهمية إذا كان هناك عدة مواسم محصولية في البلد (على سبيل المثال ، Meher و Belg في إثيوبيا ، موسم الأمطار / محاصيل الركود بسبب الفيضانات / موسم الجفاف المروي في منطقة الساحل). يمكنك الرجوع إلى "الموسم الماضي" أو "الموسم الجاري". | F9: Name the crop season(s) of interest if there are several cropping seasons in the country (e.g. Meher and Belg in Ethiopia, rainy season / flood-recession cropping / irrigated dry season in the Sahel). You can refer to the “last season” or “ongoing season". | G9: موسم الأمطار | H9: wet season
B10: local measurement unit | C10: دنم | D10: donum | E10: حدد وحدة القياس المحلية لمساحة الأرض ، بخلاف الفدان والهكتار والمتر المربع والقدم المربع. إذا لم تكن هناك حاجة إلى وحدة قياس أخرى ، احتفظ بهذه الخلية فارغة. | F10: Specify the local measurement unit for land size, other than acres, hectares, square meters and square feet. If no other unit of measurement is needed, keep this cell blank. | G10: جريب | H10: Jeribs
B11: local measurement unit conversion | C11: 0.1 | D11: =IF(C11<>"",C11,"") | E11: قم بتضمين تحويل وحدة القياس المحلية إلى هكتار. بمعنى آخر ، إلى كم هو عدد وحدات القياس المحلية في هكتار واحد. يرجى إدخال الأرقام في الأبجدية اللاتينية (...3, 2, 1). | F11: Include the conversion of the local measurement unit to hectares. In other words, how many local measurement units are in 1 ha. Only digits in Latin numbers should be inputted. | G11: 0.2 | H11: 0.2
B12: currency | C12: دولار أمريكي | D12: USD | E12: اسم العملة الرئيسية المستخدمة وطنيا ؛ دولار أمريكي؛ نيرة؛ الريال؛ بيزو؛ إلخ. | F12: The name of the main currency used nationally; USD; Naira; Rial; Pesos; etc. | G12: نيرة | H12: Naira
B14: Expected percentage of respondents cultivating crops | C14: 0.91 | D14: =IF(C14="","",C14) | E14: إذا كان المسح تمثيليًا وليس له حصص نسبية ، فاكتب نسبة الأسر الريفية التي تزرع محاصيل على المستوى الوطني ، أو إذا كان المسح يتبع جولة سابقة بتصميم عينة متطابق ، فما عليك سوى الإبلاغ عن النسبة المئوية من الجولة السابقة. إذا كنت تستخدم نظام الحصص النسبية ، فاحسب نسبة الحصة إلى الحد الأدنى لحجم العينة على المستوى الذي يتم فيه تنفيذ الحصة (لذلك إذا كان لديك حد أدنى لحجم العينة لكل طبقة 110 مع حصة 100 منتج محصول ، فسيكون 100 / 110 = 91٪ (الحد الأقصى الذي يجب أن تكتبه هو 100٪). | F14: If the survey is representative and has no quotas, write the proportion of rural households cultivating crops at country level, or if the survey follows a previous round with identical sample design, just report the percentage from the previous round. If you are using quotas, calculate the ratio of the quota over the minimum sample size at the level where the quota is implemented (so if you have a minimum sample size per strata of 110 with a quota of 100 crop producers, then it's 100/110 = 91% (the maximum you should write is 100%). | G14: 0.91 | H14: 0.91
B15: Expected percentage of respondents raising livestock | C15: 0.91 | D15: =IF(C15="","",C15) | E15: إذا كان المسح تمثيليًا وليس له حصص نسبية ، فاكتب نسبة الأسر الريفية التي تربي الماشية على المستوى الوطني ، أو إذا كان المسح يتبع جولة سابقة بتصميم عينة متطابق ، فما عليك سوى الإبلاغ عن النسبة المئوية من الجولة السابقة. إذا كنت تستخدم نظام الحصص النسبية ، فاحسب نسبة الحصة إلى الحد الأدنى لحجم العينة على المستوى الذي يتم فيه تنفيذ الحصة (لذلك إذا كان لديك حد أدنى لحجم العينة لكل طبقة 110 مع حصة 100 مربي الماشية ، فسيكون 100 / 110 = 91٪ (الحد الأقصى الذي يجب أن تكتبه هو 100٪). | F15: If the survey is representative and has no quotas, write the proportion of rural households raising livestock at country level, or if the survey follows a previous round with identical sample design, just report the percentage from the previous round. If you are using quotas, calculate the ratio of the quota over the minimum sample size at the level where the quota is implemented (so if you have a minimum sample size of 110 but a quota of 100 livestock producers, then it's 100/110 = 91% (the maximum you should write is 100%) | G15: 0.91 | H15: 0.91
B16: Expected percentage of respondents involved in fishery | C16: 0.05 | D16: =IF(C16="","",C16) | E16: إذا كان المسح تمثيليًا وليس له حصص نسبية ، فاكتب نسبة الأسر الريفية العاملة في مصايد الأسماك أو تربية الأحياء المائية على المستوى الوطني. وإلا إذا كنت تستخدم الحصص النسبية ، فاحسب نسبة الحصة إلى حجم العينة على المستوى الذي يتم فيه تنفيذ الحصة. (لذلك إذا لم تحدد حصة ، وكنت تتوقع أن يكون لديك نسبة تمثيلية من الصيادين ، فاكتب فقط النسبة المئوية للصيادين من السكان الذين تستهدفهم ، في المثال على اليمين ، 5٪). | F16: If the survey is representative and has no quotas, write the proportion of rural households involved in fisheries or aquaculture, otherwise if you are using quotas, calculate the ratio of the quota over the sample size at the level where the quota is implemented. (so if you haven't set a quota, and you expect to have a representative proportion of fishermen, just write the percentage of fishermen in the population you are targeting, in the example to the right, 5%) | G16: 0.05 | H16: 0.05
