Workbook

Sheet survey
A1: GeoPoll Submission Form
A2: FAO - Household Questionnaire | N2: Additional notes
A3: Q # | B3: Q Name | C3: Suggested Qname | D3: English | E3: Length | F3: Q Type | G3: Randomize | H3: Conditional | I3: Programming Instructions | J3: Skip Pattern | K3: Codes | L3: Default skip patterns & conditional | M3: Specify skip pattern variable (from blue text) | O3: Estimated percentage of repondents | R3: Mandatory | V3: Duration (sec) | W3: Weighted duration | X3: Core questions only
A4: A. PRESENTATION OF THE SURVEY AND ELIGIBILITY CRITERIA SELECTION | R4: no | W4: =IF(V4="","",V4*T4) | X4: =IF(R4="yes",W4,"")
A5: NA | B5: Optin | D5: Optin | E5: =LEN(D5) -> 5 | F5: Open Ended | G5: NA | H5: NA | I5: Form Type - TextBox | J5: Any Response = phone_number | K5: NA | L5: NA | R5: no | V5: 0 | W5: =IF(V5="","",V5*O5) -> 0 | X5: =IF(R5="yes",W5,"")
A6: NA | B6: phone_number | C6: phone_number | D6: Input the phone number that you are contacting: | E6: =LEN(D6) -> 48 | F6: Open Ended | G6: NA | H6: NA | I6: Form Type - TextBox | J6: Any Response = calldispo | K6: NA | L6: NA | R6: yes | V6: 0 | W6: =IF(V6="","",V6*O6) -> 0 | X6: =IF(R6="yes",W6,"") -> 0
A7: NA | B7: calldispo | C7: calldispo | D7: Phone number: #CATI_MOBILENUMBER# 1)Someone answers 2)Answering machine 3)No answer 4)Hang up or refusal 5)Call back 6)Under review 7)Disconnected | E7: =LEN(D7) -> 146 | F7: Single Choice | G7: NA | H7: NA | I7: Form Type - Buttons | J7: 1 = resp_language 2 = AnsweringMachine 3 = NoAnswer 4 = Refusal 5 = WhenCallBack 6 = UnderReview 7 = Disconnected | K7: NA | L7: NA | R7: no | V7: 14.695308 | W7: =IF(V7="","",V7*O7) -> 0 | X7: =IF(R7="yes",W7,"")
A8: NA | B8: AnsweringMachine | C8: calldispo_answeringmachine | D8: Reached an answering machine. | E8: =LEN(D8) -> 29 | F8: NA | G8: NA | H8: NA | I8: NA | J8: End Poll AnsweringMachine | K8: NA | L8: NA | R8: no | V8: 0 | W8: =IF(V8="","",V8*O8) -> 0 | X8: =IF(R8="yes",W8,"")
A9: NA | B9: NoAnswer | C9: calldispo_noanswer | D9: Phone rang and no one answered. | E9: =LEN(D9) -> 31 | F9: NA | G9: NA | H9: NA | I9: NA | J9: End Poll NoAnswer | K9: NA | L9: NA | R9: no | V9: 0 | W9: =IF(V9="","",V9*O9) -> 0 | X9: =IF(R9="yes",W9,"")
A10: NA | B10: UnderReview | C10: calldispo_underreview | D10: Case needs review by a supervisor. | E10: =LEN(D10) -> 34 | F10: NA | G10: NA | H10: NA | I10: NA | J10: End Poll UnderReview | K10: NA | L10: NA | R10: no | V10: 0 | W10: =IF(V10="","",V10*O10) -> 0 | X10: =IF(R10="yes",W10,"")
A11: NA | B11: Disconnected | C11: calldispo_disconnected | D11: Phone was disconnected or out of service. | E11: =LEN(D11) -> 41 | F11: NA | G11: NA | H11: NA | I11: NA | J11: End Poll Disconnected | K11: NA | L11: NA | R11: no | V11: 0 | W11: =IF(V11="","",V11*O11) -> 0 | X11: =IF(R11="yes",W11,"")
A12: NA | B12: resp_language | C12: resp_language | D12: Which language do you wish to proceed with? [OPERATOR: READ ANSWER CHOICES. SINGLE RESPONSE.] 1)English 2)other options [add as many as necessary] | E12: =LEN(D12) -> 148 | F12: Single Choice | G12: NA | H12: NA | I12: Form Type - Buttons | J12: 1 = introduction [English] 2 = introduction [languages & add more if needed] | K12: NA | L12: For any response, go to introduction | N12: Insert most common national languages here [max 4 for translation with GeoPoll]. | R12: no | V12: 3.1032724 | W12: =IF(V12="","",V12*O12) -> 0 | X12: =IF(R12="yes",W12,"")
A13: NA | B13: introduction | C13: introduction | D13: Hello sir/ma'am, my name is #OPERATOR#, and I am calling from GeoPoll Polling Agency on behalf of the Food and Agriculture Organization of the United Nations [FAO]. We are conducting a survey on household livelihoods and the ability to access food in your area. I would like to ask you some questions about your household. The survey usually takes 15/20 minutes to complete. Any information that you provide will be kept strictly confidential, only used for the purpose of the survey and will not be shown to other people. Your voluntary participation in the outcome of this interview is NOT IN ANY WAY linked to your personal chance of receiving any assistance. This is voluntary and you can choose not to answer any or all of the questions if you want. However, we hope that you will participate since your views are important. You will receive #TOPUP#! of communication credit as an incentive for the participation of the survey. Please note that this call may be recorded for quality purposes. Do you have any questions? [OPERATOR: ADDRESS QUESTIONS FROM RESPONDENT, IF ANY.] 1)CONTINUE | E13: =LEN(D13) -> 1098 | F13: Single Choice | G13: NA | H13: NA | I13: Form Type - Buttons | J13: 1 = Agree | K13: NA | L13: For any response, go to Agree | N13: Set the amount of incentive here, if any. | R13: no | V13: 37.418449 | W13: =IF(V13="","",V13*O13) -> 0 | X13: =IF(R13="yes",W13,"")
A14: NA | B14: Agree | C14: resp_agree | D14: Are you interested in participating in this survey? [OPERATOR: SINGLE RESPONSE] 1)Yes 2)Not now but another time in the week 3)No | E14: =LEN(D14) -> 134 | F14: StartRecording | G14: NA | H14: NA | I14: Form Type - Buttons | J14: 1 = [id_panel OR resp_firstname] 2 = WhenCallBack 3 = resp_refusalwhy | K14: NA | L14: if Agree = 1, go to id_panel OR resp_firstname if Agree = 2, go to WhenCallBack if Agree = 3, go to resp_refusalwhy | O14: 1 | R14: no | V14: 3.8059516 | W14: =IF(V14="","",V14*O14) -> 3.8059516 | X14: =IF(R14="yes",W14,"")
A15: NA | B15: id_panel | C15: id_panel | D15: Have you or any member of your household received a call on behalf of FAO regarding this topic in the past two years? [OPERATOR: SINGLE RESPONSE.] 1)YES 2)NO 3)DON'T KNOW | E15: =LEN(D15) -> 172 | F15: Single Choice | G15: NA | H15: NA | I15: Form Type - Buttons | J15: 1-3 = resp_firstname | K15: NA | L15: For any response, go to resp_firstname | N15: It is highly recommended to include the question id_panel if a panelist approach is used. | O15: 1 | R15: no
A16: NA | B16: resp_refusalwhy | C16: resp_refusalwhy | D16: Please let us know why you have REFUSED to take the survey. [OPERATOR: SINGLE RESPONSE] 1)Not interested 2)Do not want to be recorded 3)Other [specify] | E16: =LEN(D16) -> 153 | F16: Open Ended - Single Choice | G16: NA | H16: NA | I16: Form Type - RadioList | J16: Any Response = Refusal | K16: NA | L16: For any response, go to Refusal | O16: 1 | R16: no | V16: 0 | W16: =IF(V16="","",V16*O16) -> 0 | X16: =IF(R16="yes",W16,"")
A17: NA | B17: WhenCallBack | C17: resp_whencallback | D17: When would it be a good time to call you back? [RECORD HH/MM/DD/MM OF CALLBACK] | E17: =LEN(D17) -> 80 | F17: Open Ended | G17: NA | H17: NA | I17: Form Type - TextBox IsCallBackDemographic | J17: Any Response = CallbackMessageEN | K17: NA | L17: For any response, go to CallbackMessageEN | O17: 1 | R17: no | V17: 0 | W17: =IF(V17="","",V17*O17) -> 0 | X17: =IF(R17="yes",W17,"")
A18: NA | B18: CallbackMessageEN | C18: callbackmessage_en | D18: Thank you, we will call you back at {WhenCallBack} you requested. Thank you again and have a great day! [OPERATOR: ENTER CALL NOTES BELOW, WHO YOU SPOKE TO AND WHAT THEY SAID] | E18: =LEN(D18) -> 176 | F18: Open Ended | G18: NA | H18: NA | I18: Form Type - TextBox | J18: Any Response = End poll callback | K18: NA | L18: NA | O18: 1 | R18: no | V18: 0 | W18: =IF(V18="","",V18*O18) -> 0 | X18: =IF(R18="yes",W18,"")
A19: NA | B19: Ineligible | C19: NA | D19: You are ineligible for this survey. Thank you for your time and please look out for future surveys! | E19: =LEN(D19) -> 99 | F19: NA | G19: NA | H19: NA | I19: NA | J19: End Poll Ineligible | K19: NA | L19: NA | O19: 1 | R19: no | V19: 0 | W19: =IF(V19="","",V19*O19) -> 0 | X19: =IF(R19="yes",W19,"")
A20: NA | B20: Refusal | C20: NA | D20: Thank you for your time, you will be removed from today's survey. | E20: =LEN(D20) -> 65 | F20: NA | G20: NA | H20: NA | I20: NA | J20: End poll declined | K20: NA | L20: NA | O20: 1 | R20: no | V20: 0 | W20: =IF(V20="","",V20*O20) -> 0 | X20: =IF(R20="yes",W20,"")
A21: B. GENERAL INFORMATION & ELIGIBILITY CRITERIA | W21: =IF(V21="","",V21*O21) | X21: =IF(R21="yes",W21,"")
A22: NA | B22: resp_firstname | C22: resp_firstname | D22: What is your first name? [OPERATOR: RECORD THE RESPONDENT'S FIRST NAME. ENTER 999 FOR REFUSED.] | E22: =LEN(D22) -> 96 | F22: Open Ended | G22: NA | H22: NA | I22: Form Type - TextBox | J22: Any Response = resp_lastname | K22: NA | L22: For any response, go to resp_lastname | O22: =1 -> 1 | R22: yes | V22: 25.874027 | W22: =IF(V22="","",V22*O22) -> 25.874027 | X22: =IF(R22="yes",W22,"") -> 25.874027
A23: NA | B23: resp_lastname | C23: resp_lastname | D23: What is your last name? [OPERATOR: RECORD THE RESPONDENT'S LAST NAME. ENTER 999 FOR REFUSED.] | E23: =LEN(D23) -> 95 | F23: Open Ended | G23: NA | H23: NA | I23: Form Type - TextBox | J23: Any Response = resp_age | K23: NA | L23: For any response, go to resp_age | O23: =1 -> 1 | R23: yes | V23: 8.5994816 | W23: =IF(V23="","",V23*O23) -> 8.5994816 | X23: =IF(R23="yes",W23,"") -> 8.5994816
A24: 1 | B24: resp_age | C24: resp_age | D24: How old are you? [OPERATOR: RECORD AGE IN NUMBER OF YEARS. ROUND UP TO NEAREST WHOLE NUMBER. IF THE RESPONDENT GIVES BIRTH YEAR, REPEAT THE QUESTION. ENTER 00 FOR DON'T KNOW.] | E24: =LEN(D24) -> 177 | F24: Range | G24: NA | H24: NA | I24: Form Type - TextBox | J24: 0-17 = Ineligible 18-100 = resp_gender 00 = Ineligible | K24: NA | L24: Only respondents from 18-100 will be eligible for the survey. | O24: =1 -> 1 | R24: yes | V24: 9.8907185 | W24: =IF(V24="","",V24*O24) -> 9.8907185 | X24: =IF(R24="yes",W24,"") -> 9.8907185
A25: =A24+1 -> 2 | B25: resp_gender | C25: resp_gender | D25: What is the gender of the respondent? [OPERATOR: DO NOT ASK THIS QUESTION OUT LOUD. LISTEN TO THE VOICE AND SELECT THE GENDER.] 1)Male 2)Female 3)DON'T KNOW 4)REFUSED | E25: =LEN(D25) -> 168 | F25: Single Choice | G25: NA | H25: NA | I25: Form Type - Buttons | J25: 1-4 = phone_number_conf | K25: NA | L25: For any response, go to phone_number_conf | O25: =1 -> 1 | R25: yes | V25: 1.7156482 | W25: =IF(V25="","",V25*O25) -> 1.7156482 | X25: =IF(R25="yes",W25,"") -> 1.7156482
O26: =1 -> 1 | W26: =IF(V26="","",V26*O26) | X26: =IF(R26="yes",W26,"")
B27: phone_number_conf | C27: phone_number_conf | D27: Is the phone number I am calling you on yours or a household members? [OPERATOR: SINGLE RESPONSE.] 1)YES 2)NO 3)DON'T KNOW 4)REFUSED | E27: =LEN(D27) -> 134 | F27: Single Choice | G27: NA | H27: NA | I27: Form Type - Buttons | J27: 1 = contact_2 2 = phone_number_personal 3-4 = contact_2 | K27: NA | L27: if phone_number_conf = 1, go to contact_2 if phone_number_conf = 2, go to phone_number_personal if phone_number_conf = 3-4, go to contact_2 | O27: =1 -> 1 | R27: yes - panel | V27: 6.375237 | W27: =IF(V27="","",V27*O27) -> 6.375237 | X27: =IF(R27="yes",W27,"")
B28: phone_number_personal | C28: phone_number_pers | D28: What is your phone number? [OPERATOR: RECORD THE NUMBER GIVEN] | E28: =LEN(D28) -> 63 | F28: Open Ended | G28: NA | H28: NA | I28: Form Type - TextBox | J28: Any Response = contact_2 | K28: NA | L28: For any response, go to contact_2 | O28: =1 -> 1 | R28: yes - panel | V28: 28.700001 | W28: =IF(V28="","",V28*O28) -> 28.700001 | X28: =IF(R28="yes",W28,"")
B29: contact_2 | C29: contact_2 | D29: Can you give me an additonal phone number belonging to you, a relative or a friend at which you can be reached? [OPERATOR: SINGLE RESPONSE.] 1)YES - mine 2)YES - other household member 3)YES - friend or relative [non-household member] 4)NO 5)DON'T KNOW 6)REFUSED | E29: =LEN(D29) -> 265 | F29: Single Choice | G29: NA | H29: NA | I29: Form Type - Buttons | J29: 1-3 = phone_number_2 4-6 = hh_admin1 | K29: NA | L29: if contact_2 = 1-3, go to phone_number_2 if contact_2 = 4-6, go to contact_3 | O29: =1 -> 1 | R29: yes - panel | V29: 10.141817 | W29: =IF(V29="","",V29*O29) -> 10.141817 | X29: =IF(R29="yes",W29,"")
B30: phone_number_2 | C30: phone_number_2 | D30: What is the additional phone number? [OPERATOR: RECORD THE NUMBER GIVEN] | E30: =LEN(D30) -> 73 | F30: Open Ended | G30: NA | H30: NA | I30: Form Type - TextBox | J30: Any Response = contact_2_name | K30: NA | L30: For any response, go to contact_2_name | O30: =1 -> 1 | R30: yes - panel | V30: 21.659983 | W30: =IF(V30="","",V30*O30) -> 21.659983 | X30: =IF(R30="yes",W30,"")
B31: contact_2_name | C31: contact_2_name | D31: What is the name of the contact? [OPERATOR: RECORD THE NAME OF THE CONTACT FOR THE PHONE NUMBER.] | E31: =LEN(D31) -> 98 | F31: Open Ended | G31: NA | H31: Send if "contact_2" "Equals" "YES - other household member" OR "contact_2" "Equals" "YES - friend or relative [non-household member]", if not satisfied go to "contact_3" | I31: Form Type - TextBox | J31: Any Response = contact_3 | K31: NA | L31: Asked if response to contact_2 was "YES - other household member" or "YES - friend or relative [non-household member]". Otherwise, it skips to "contact_3". For any response, go to contact_3 | O31: =1 -> 1 | R31: yes - panel | V31: 11.821796 | W31: =IF(V31="","",V31*O31) -> 11.821796 | X31: =IF(R31="yes",W31,"")
B32: contact_3 | C32: contact_3 | D32: Can you give me an additonal phone number belonging to you, a relative or a friend at which you can be reached? [OPERATOR: SINGLE RESPONSE.] 1)YES - mine 2)YES - other household member 3)YES - friend or relative [non-household member] 4)NO 5)DON'T KNOW 6)REFUSED | E32: =LEN(D32) -> 265 | F32: Single Choice | G32: NA | H32: NA | I32: Form Type - Buttons | J32: 1-3= phone_number_3 4-6 = hh_admin1 | K32: NA | L32: if contact_3 = 1-3, go to phone_number_3 if contact_3 = 4-6, go to hh_admin1 | O32: =1 -> 1 | R32: yes - panel | V32: 3.163594 | W32: =IF(V32="","",V32*O32) -> 3.163594 | X32: =IF(R32="yes",W32,"")
B33: phone_number_3 | C33: phone_number_3 | D33: What is the additional phone number? [OPERATOR: RECORD THE NUMBER GIVEN] | E33: =LEN(D33) -> 73 | F33: Open Ended | G33: NA | H33: NA | I33: Form Type - TextBox | J33: Any Response = contact_3_name | K33: NA | L33: For any response, go to contact_3_name | O33: =1 -> 1 | R33: yes - panel | V33: 10.830144 | W33: =IF(V33="","",V33*O33) -> 10.830144 | X33: =IF(R33="yes",W33,"")
B34: contact_3_name | C34: phone_number_3_name | D34: What is the name of the contact? [OPERATOR: RECORD THE NAME OF THE CONTACT FOR THE PHONE NUMBER.] | E34: =LEN(D34) -> 98 | F34: Open Ended | G34: NA | H34: Send if "contact_3" "Equals" "YES - other household member" OR "contact_3" "Equals" "YES - friend or relative [non-household member]", if not satisfied go to "hh_admin1" | I34: Form Type - TextBox | J34: Any Response = hh_admin1 | K34: NA | L34: Asked if response to contact_3 was "YES - other household member" or "YES - friend or relative [non-household member]". Otherwise, it skips to "hh_admin1". For any response, go to hh_admin1 | O34: =1 -> 1 | R34: yes - panel | V34: 11.260417 | W34: =IF(V34="","",V34*O34) -> 11.260417 | X34: =IF(R34="yes",W34,"")
O35: =1 -> 1 | W35: =IF(V35="","",V35*O35) | X35: =IF(R35="yes",W35,"")
A36: 3 | B36: hh_admin1 | C36: hh_admin1 | D36: Currently, in which Region does your household reside? [OPERATOR: SINGLE SELECTION.] [HINT: HOUSEHOLD CONSISTS OF ALL MEMBERS LIVING TOGETHER, SHARING RESOURCES & EATING FROM THE SAME POT.] 1)ADMIN1 2)DON'T KNOW 3)REFUSED | E36: =LEN(D36) -> 224 | F36: Single Choice | G36: NA | H36: NA | I36: Form Type - Buttons IsDemographic - ADM1 | J36: 1 = hh_admin2_1 2-3 = Ineligible | K36: NA | L36: The administrative information will be updated by GeoPoll based on the sample design document and the administrative boundaries provided by the dashboard team after the questionnaire validation. | O36: =1 -> 1 | R36: yes | V36: 13.957259 | W36: =IF(V36="","",V36*O36) -> 13.957259 | X36: =IF(R36="yes",W36,"") -> 13.957259
A37: =A36+1 -> 4 | B37: hh_admin2_1 | C37: hh_admin2_1 | D37: Currently, in which District does your household reside? [OPERATOR: SINGLE RESPONSE.] 1)ADMIN2 2)DON'T KNOW 3)REFUSED | E37: =LEN(D37) -> 120 | F37: Single Choice | G37: NA | H37: NA | I37: Form Type - Buttons IsDemographic - ADM2 | J37: 1 = hh_agricactivity 2-3 = Ineligible | K37: NA | O37: =1 -> 1 | R37: yes | V37: 7.954999 | W37: =IF(V37="","",V37*O37) -> 7.954999 | X37: =IF(R37="yes",W37,"") -> 7.954999
B38: quotareached | C38: quotareached | D38: [OPERATOR: DO NOT READ. ANSWER QUESTION BELOW.] THIS RESPONDENT REPORTED THEY LIVE IN: {ADM1} {ADM2} 1)THE GOAL FOR THIS LOCATION HAS BEEN ACHIEVED - END SURVEY 2)THE GOAL FOR THIS LOCATION IS OPEN - CONTINUE SURVEY | E38: =LEN(D38) -> 218 | F38: Single Choice | G38: NA | H38: NA | I38: Form Type - Buttons | J38: 1 = End Poll Quota Reached 2 = hh_agricactivity | K38: NA
A39: =#REF!+1 -> #REF! | B39: hh_agricactivity | C39: hh_agricactivity | D39: Has anybody in your household produced crops or livestock for household consumption or for sale in the past 12 months, including household members currently away for transhumance? [OPERATOR: SINGLE RESPONSE. THIS IS THE MAIN SCREENING QUESTION.] [HINT FOR PROBING: Do you cultivate any plants to sale or consume? Do you raise any animals with the intent of selling or consuming them or their products like meat, milk, wool or leather? Is one of your household member currently away with cattle or other animals for transhumance?] 1)Yes - crop production 2)Yes - livestock production 3)Yes - both crop and livestock production 4)No 5)DON'T KNOW 6)REFUSED | E39: =LEN(D39) -> 658 | F39: Single Choice | G39: NA | H39: NA | I39: Form Type - Buttons | J39: 1-4 = resp_id 5-6 = Ineligible | K39: NA | L39: if hh_agricactivity = 1-4, go to resp_id. Otherwise, the respondent is ineligible. | O39: =1 -> 1 | R39: yes | V39: 24.410839 | W39: =IF(V39="","",V39*O39) -> 24.410839 | X39: =IF(R39="yes",W39,"") -> 24.410839
O40: =1 -> 1 | W40: =IF(V40="","",V40*O40) | X40: =IF(R40="yes",W40,"")
A41: B. GENERAL HOUSEHOLD INFORMATION | W41: =IF(V41="","",V41*O41) | X41: =IF(R41="yes",W41,"")
O42: =1 -> 1 | W42: =IF(V42="","",V42*O42) | X42: =IF(R42="yes",W42,"")
A43: =A39+1 -> #REF! | B43: resp_id | C43: resp_id | D43: Are you the head of household? [OPERATOR: SINGLE RESPONSE.] 1)Yes 2)No 3)DON'T KNOW 4)REFUSED | E43: =LEN(D43) -> 97 | F43: Single Choice | G43: NA | H43: NA | I43: Form Type - Buttons | J43: 1 = hh_education 2-4 = hh_gender | K43: NA | L43: if resp_id = 1, go to hh_education. Otherwise, go to hh_gender. | O43: 1 | R43: yes | V43: 10.5 | W43: =IF(V43="","",V43*O43) -> 10.5 | X43: =IF(R43="yes",W43,"") -> 10.5
A44: =A43+1 -> #REF! | B44: hh_gender | C44: hh_gender | D44: Is the head of your household male or female? [OPERATOR: SINGLE RESPONSE.] 1)Male 2)Female 3)DON'T KNOW 4)REFUSED | E44: =LEN(D44) -> 116 | F44: Single Choice | G44: NA | H44: NA | I44: Form Type - Buttons | J44: 1-4 = hh_education | K44: NA | L44: if hh_gender = 1-4, go to hh_education. | O44: =1 -> 1 | R44: yes | V44: 10.504534 | W44: =IF(V44="","",V44*O44) -> 10.504534 | X44: =IF(R44="yes",W44,"") -> 10.504534
O45: =1 -> 1 | W45: =IF(V45="","",V45*O45) | X45: =IF(R45="yes",W45,"")
A46: =A44+1 -> #REF! | B46: hh_education | C46: hh_education | D46: What is the educational level attained by the head of household? [OPERATOR: SINGLE RESPONSE.] 1)None or did not complete primary school 2)Completed primary school 3)Completed secondary school 4)Completed higher education [University / College] degree 5)Religious or informal education only 6)DON'T KNOW 7)REFUSED | E46: =LEN(D46) -> 314 | F46: Single Choice | G46: NA | H46: NA | I46: Form Type - Buttons | J46: 1-7 = hh_wealth | K46: NA | L46: if hh_education = 1-7, go to hh_wealth. | O46: =1 -> 1 | R46: yes | V46: 12.421899 | W46: =IF(V46="","",V46*O46) -> 12.421899 | X46: =IF(R46="yes",W46,"") -> 12.421899
O47: =1 -> 1 | W47: =IF(V47="","",V47*O47) | X47: =IF(R47="yes",W47,"")
A48: 10 | B48: hh_wealth_water | C48: hh_wealth_water | D48: Where does the water that you drink at home come from? [OPERATOR: SINGLE CHOICE.] 1)Private tap from piped water 2)Public tap 3)Protected well 4)Bottled water 5)Other safe source 6)River 7)Unprotected well 8)Spring water 9)Surface water [e.g. canals, ponds, dams] 10)Other unsafe source 11)DON'T KNOW 12)REFUSED | E48: =LEN(D48) -> 313 | F48: Single Choice | G48: NA | H48: NA | I48: Form Type - Buttons | J48: 1-12 = [income_main OR other optional question] | K48: NA | L48: For any response, go to [income_main OR other optional question] | N48: Select wealth indicators based on baseline information available; you can delete those that you do not want to use. If none of these indicators work in the context of your country, other wealth proxies are proposed in the optional questions below. Remember that baseline data will be necessary, and the variable should be defined properly in the "weight_input_table". | O48: =1 -> 1 | R48: yes | V48: 16.615656 | W48: =IF(V48="","",V48*O48) -> 16.615656 | X48: =IF(R48="yes",W48,"") -> 16.615656
A49: 10 | B49: hh_wealth_toilet | C49: hh_wealth_toilet | D49: Where do household members typically go to use a toilet? [OPERATOR: SINGLE CHOICE.] 1)Flush latrine [toilet with water] 2)Traditional pit latrine [no water] 3)Open pit [hole in the ground for excrement without water, roof or wall] 4)Communal latrine [with or without water] 5)None – bush 6)DON'T KNOW 7)REFUSED | E49: =LEN(D49) -> 312 | F49: Single Choice | G49: NA | H49: NA | I49: Form Type - Buttons | J49: 1-7 = [income_main OR other optional question] | K49: NA | L49: For any response, go to [income_main OR other optional question] | O49: =1 -> 1 | R49: yes | V49: 12.600021 | W49: =IF(V49="","",V49*O49) -> 12.600021 | X49: =IF(R49="yes",W49,"") -> 12.600021
A50: 10 | B50: hh_wealth_light | C50: hh_wealth_light | D50: What is the main source of light in your dwelling? [OPERATOR: SINGLE RESPONSE.] 1)Electricity [from generator or electrical grid] 2)Candle 3)Petrol lamp 4)Lamp with batteries 5)Solar panel 6)Other [no electric supply to the house] 7)DON'T KNOW 8)REFUSED | E50: =LEN(D50) -> 255 | F50: Single Choice | G50: NA | H50: NA | I50: Form Type - Buttons | J50: 1-8 = [income_main OR other optional question] | K50: NA | L50: For any response, go to [income_main OR other optional question] | O50: =1 -> 1 | R50: yes | V50: 11.655923 | W50: =IF(V50="","",V50*O50) -> 11.655923 | X50: =IF(R50="yes",W50,"") -> 11.655923
O51: =1 -> 1 | W51: =IF(V51="","",V51*O51) | X51: =IF(R51="yes",W51,"")
A52: =A50+1 -> 11 | B52: hh_residencetype | C52: hh_residencetype | D52: Which in the following types of residence best describes your residence? [OPERATOR: READ OUT THE OPTIONS. SINGLE RESPONSE.] [HINT: IF RESPONDENT IS ONLY AWAY FROM THE HOUSEHOLD FOR SHORT SEASONAL WORK (<6 MONTHS) OR TRANSHUMANCE, MAKE SURE TO REFER TO THEIR HOUSEHOLD BACK WHERE THEY TYPICALLY ARE LOCATED.] 1)Permanent Resident - you have been living in your village / town for longer than two years and this is what you consider your habitual residence 2)Recent migrant not forcefully displaced - you have been living in your current place of residence for less than two years and you moved there voluntarily for work / family or other reasons that are not related to conflict or natural disaster 3)Returnee - you have only come back to this residence in the last two years after having been forced to move to another location having fled conflict or natural disaster [if return was over 2 years ago the respondent is considered a permanent resident] 4)Internally displaced person [IDP] - you were forced to flee your village or town because of conflict or natural disaster and you are now an internally displaced person in your current place of residence 5)Refugee - you were forced to flee your country because of conflict or natural disaster and you are now a refugee in your current place of residence 6)DON'T KNOW 7)REFUSED | E52: =LEN(D52) -> 1333 | F52: Single Choice | G52: NA | H52: NA | I52: Form Type - Buttons | J52: 1-7 = hh_size | K52: NA | L52: For any response, go to [next question] | O52: =1 -> 1 | R52: no | V52: 13.220665 | W52: =IF(V52="","",V52*O52) -> 13.220665 | X52: =IF(R52="yes",W52,"")
A53: =A52+1 -> 12 | B53: hh_size | C53: hh_size | D53: How many people are part of the household? [OPERATOR: RECORD NUMBER OF MEMBERS IN HOUSEHOLD. ENTER 88 FOR DON'T KNOW & 99 FOR REFUSED.] [HINT: TO BE A PART OF THE SAME HOUSEHOLD, MEMBERS MUST LIVE UNDER THE SAME ROOF, SHARE THE SAME RESOURCES & EAT FROM THE SAME POT.] | E53: =LEN(D53) -> 269 | F53: Range | G53: NA | H53: NA | I53: Form Type - TextBox | J53: 1-50 = hh_asset_prod 88-88 = hh_asset_prod 99-99 = hh_asset_prod | K53: NA | L53: For any response, go to [next question] | O53: =1 -> 1 | R53: no | V53: 16.902294 | W53: =IF(V53="","",V53*O53) -> 16.902294 | X53: =IF(R53="yes",W53,"")
A54: =A53+1 -> 13 | B54: hh_asset_prod | C54: hh_asset_prod_ 1) hh_asset_prod_process 2) hh_asset_prod_farmmach 3) hh_asset_prod_sewing 4) hh_asset_prod_taxi 5) hh_asset_prod_truck 6) hh_asset_prod_other 7) hh_asset_prod_none 8) hh_asset_prod_dk 9) hh_asset_prod_ref | D54: Does your household own any of the following productive assets? [OPERATOR: MULTIPLE RESPONSES POSSIBLE. READ ANSWER OPTIONS OUT LOUD.] 1)Processing assets [e.g. grinding/crushing machine, mill, oil press] 2)Farm machinery [e.g. tractor, plough, sickle, etc.] 3)Sewing machine or weaving tool 4)Taxi 5)Truck 6)Other productive machines or assets 7)No productive machines or assets 8)DON'T KNOW 9)REFUSED | E54: =LEN(D54) -> 406 | F54: Select All That Apply | G54: NA | H54: NA | I54: Form Type - Checklist 7,8,9 = IsNone | J54: 1-9 = hh_asset_transp | K54: 1)hh_asset_prod_process 2)hh_asset_prod_farmmach 3)hh_asset_prod_sewing 4)hh_asset_prod_taxi 5)hh_asset_prod_truck 6)hh_asset_prod_other 7)hh_asset_prod_none 8)hh_asset_prod_dk 9)hh_asset_prod_ref | L54: For any response, go to [next question] | N54: This wealth indicator may be useful to Identify poor households in middle income countries. It could be interesting for F2F surveys, to be used as baseline reference for follow-up surveys. | O54: =1 -> 1 | R54: no | V54: 16.957804 | W54: =IF(V54="","",V54*O54) -> 16.957804 | X54: =IF(R54="yes",W54,"")
A55: =A54+1 -> 14 | B55: hh_asset_transp | C55: hh_asset_transp_ 1) hh_asset_transp_bici 2) hh_asset_transp_cart 3) hh_asset_transp_boat 4) hh_asset_transp_motorbike 5) hh_asset_transp_car 6) hh_asset_transp_van 7) hh_asset_transp_other 8) hh_asset_transp_none 9) hh_asset_transp_dk 10) hh_asset_transp_ref | D55: Do you or any member of your household own any of the following transportation assets? [OPERATOR: MULTIPLE RESPONSES POSSIBLE. READ ANSWER OPTIONS OUT LOUD.] 1)Bicycle 2)Cart [animal drawn] 3)Boat/canoe 4)Motorbike / scooter / auto rickshaw 5)Car 6)Van or small truck 7)Other motor vehicle 8)None of the above 9)DON'T KNOW 10)REFUSED | E55: =LEN(D55) -> 336 | F55: Select All That Apply | G55: NA | H55: NA | I55: Form Type - Checklist 8,9,10 = IsNone | J55: 1-10 = hh_maritalstat | K55: 1)hh_asset_transp_bici 2)hh_asset_transp_cart 3)hh_asset_transp_boat 4)hh_asset_transp_motorbike 5)hh_asset_transp_car 6)hh_asset_transp_van 7)hh_asset_transp_other 8)hh_asset_transp_none 9)hh_asset_transp_dk 10)hh_asset_transp_ref | L55: For any response, go to [next question] | N55: This wealth indicator may be useful to Identify poor households in middle income countries. It could be interesting for F2F surveys, to be used as baseline reference for follow-up surveys. | O55: =1 -> 1 | R55: no | V55: 11.022029 | W55: =IF(V55="","",V55*O55) -> 11.022029 | X55: =IF(R55="yes",W55,"")
A56: =A55+1 -> 15 | B56: hh_maritalstat | C56: hh_maritalstat | D56: What is the head of household’s current marital status? [OPERATOR: SINGLE RESPONSE.] 1)Single / never married 2)Married 3)Separated 4)Divorced 5)Widowed 6)DON’T KNOW 7)REFUSED | E56: =LEN(D56) -> 180 | F56: Single Choice | G56: NA | H56: NA | I56: Form Type - Buttons | J56: 1-7 = hh_age | K56: NA | L56: For any response, go to [next question] | O56: =1 -> 1 | R56: no | V56: 9.9618664 | W56: =IF(V56="","",V56*O56) -> 9.9618664 | X56: =IF(R56="yes",W56,"")
A57: =A56+1 -> 16 | B57: hh_age | C57: hh_age | D57: How old is the head of household? [OPERATOR: SINGLE RESPONSE.] 1)Under 18 2)18 to 40 3)41 to 65 4)Over 65 5)DON'T KNOW 6)REFUSED | E57: =LEN(D57) -> 133 | F57: Single Choice | G57: NA | H57: NA | I57: Form Type - Buttons | J57: 1-6 = income_main | K57: NA | L57: For any response, go to [next question] | O57: =1 -> 1 | R57: no | V57: 7.0248413 | W57: =IF(V57="","",V57*O57) -> 7.0248413 | X57: =IF(R57="yes",W57,"")
A58: C. INCOME SOURCES, LIVELIHOOD AND SHOCKS | W58: =IF(V58="","",V58*O58) | X58: =IF(R58="yes",W58,"")
O59: =1 -> 1 | W59: =IF(V59="","",V59*O59) | X59: =IF(R59="yes",W59,"")
A60: =A57+1 -> 17 | B60: income_main | C60: income_main | D60: What was your household's main source of income in the past 3 months? [OPERATOR: SINGLE RESPONSE. REFUSED OPTION SHOULD BE AVOIDED AS MUCH AS POSSIBLE.] 1)Production and sale of staple crops 2)Production and sale of vegetables or fruit 3)Production and sale of cashcrops 4)Production and sale of livestock and livestock products 5)Production and sale of honey or bee products 6)Production and sale of fish 7)Collection and sale of forestry or bush products 8)Agricultural trade EXCLUDING producers [formal or informal] 9)Daily wage on farms and other casual employment in agricultural sector 10)Stable employment in agricultural sector 11)Non-agricultural self-employed or liberal profession / doctor / architect / lawyer / including restaurant 12)Off-farm daily wages and other non-agricultural casual employment 13)Stable employment in non-agricultural sector 14)Public employment 15)Income not derived from work / Charity 16)Income not derived from work / Welfare transfer, pension, humanitarian aid 17)Income not derived from work / Remittances 18)Income not derived from work / Income from other rents 19)No income source in the last 3 months and used exclusively savings / debt 20)REFUSED | E60: =LEN(D60) -> 1204 | F60: Single Choice | G60: NA | H60: NA | I60: Form Type - Buttons IsDemographic | J60: 1-3 = income_main_crop_check 4 = income_main_ls_check 5 = income_main_comp OR optional question 6 = income_main_fish_check 7-18 = income_main_comp OR optional question 19-20 = shock | K60: NA | L60: if options #1-3 selected go to income_main_crop_check if options #4 selected go to income_main_ls_check if options #6 selected go to income_main_fish_check if options #5, 7-18 selected, go to [income_main_comp OR optional question] if options #19-20 selected, go to shock | O60: =1 -> 1 | R60: yes | V60: 31.888334 | W60: =IF(V60="","",V60*O60) -> 31.888334 | X60: =IF(R60="yes",W60,"") -> 31.888334
B61: income_main_crop_check | C61: income_main_crop_check | D61: Are the crops that you sell also produced by you or anyone in your household? [OPERATOR: SINGLE RESPONSE.] 1)YES 2)NO 3)DON'T KNOW 4)REFUSED | E61: =LEN(D61) -> 143 | F61: Single Choice | G61: NA | H61: NA | I61: Form Type - Buttons | J61: 1-4 = income_main_comp OR optional question | K61: NA | L61: if income_main_crop_check = 1-4, go to [income_main_comp OR optional question] | O61: =1 -> 1 | R61: yes | V61: 8 | W61: =IF(V61="","",V61*O61) -> 8 | X61: =IF(R61="yes",W61,"") -> 8
B62: income_main_ls_check | C62: income_main_ls_check | D62: Are the livestock and livestock products that you sell also produced by you or anyone in your household? [OPERATOR: SINGLE RESPONSE.] 1)YES 2)NO 3)DON'T KNOW 4)REFUSED | E62: =LEN(D62) -> 170 | F62: Single Choice | G62: NA | H62: NA | I62: Form Type - Buttons | J62: 1-4 = income_main_comp OR optional question | K62: NA | L62: if income_main_ls_check = 1-4, go to [income_main_comp OR optional question] | O62: =1 -> 1 | R62: yes | V62: 8 | W62: =IF(V62="","",V62*O62) -> 8 | X62: =IF(R62="yes",W62,"") -> 8
B63: income_main_fish_check | C63: income_main_fish_check | D63: Are the fish and/or fish products that you sell also captured or harvested by you or anyone in your household? [OPERATOR: SINGLE RESPONSE.] 1)YES 2)NO 3)DON'T KNOW 4)REFUSED | E63: =LEN(D63) -> 176 | F63: Single Choice | G63: NA | H63: NA | I63: Form Type - Buttons | J63: 1-4 = income_main_comp OR optional question | K63: NA | L63: if income_main_fish_check = 1-4, go to [income_main_comp OR optional question] | O63: =1 -> 1 | R63: yes | V63: 8 | W63: =IF(V63="","",V63*O63) -> 8 | X63: =IF(R63="yes",W63,"") -> 8
O64: =1 -> 1 | W64: =IF(V64="","",V64*O64) | X64: =IF(R64="yes",W64,"")
A65: 19 | B65: income_main_amount | C65: income_main_amount | D65: How much was earned [in Leones] from your main income source, {income_main}, in the past 3 months ? [OPERATOR: MAKE SURE THE INFORMATION IS RECORDED IN THE CORRECT CURRENCY. ENTER 8888888 FOR DON'T KNOW AND 9999999 FOR REFUSED.] | E65: =LEN(D65) -> 229 | F65: Range | G65: NA | H65: NA | I65: Form Type - TextBox | J65: 50 - 5000 = income_main_comp OR optional question 5000 - 20000 = income_main_amount_conf 8888888-8888888 = income_main_comp OR optional question 9999999-9999999 = income_main_comp OR optional question | K65: NA | L65: If the income amount is over the threshold set in "Additional information", the respondent will be asked to confirm with income_main_amount_conf. Otherwise, go to income_main_comp or optional question. | N65: We recommend using this pair of questions together. | O65: =1 -> 1 | R65: no | V65: 31.963766 | W65: =IF(V65="","",V65*O65) -> 31.963766 | X65: =IF(R65="yes",W65,"")
A66: 19 | B66: income_main_amount_conf | C66: income_main_amount_conf | D66: Can you confirm the amount of income you just stated is correct? [OPERATOR: IF THE AMOUNT EARNED FROM THIS INCOME SOURCE OVER THE PAST 3 MONTH IS INDEED OVER 5000, CLICK ON CONTINUE. OTHERWISE, GO BACK AND CHANGE THE AMOUNT ENTERED.] 1)CONTINUE | E66: =LEN(D66) -> 246 | F66: Single Choice | G66: NA | H66: NA | I66: Form Type - Buttons | J66: 1 = income_main_comp OR optional question | K66: NA | L66: if income_main_amount_conf = 1, go to income_main_comp or optional question | O66: =1 -> 1 | R66: no | V66: 2.2273674 | W66: =IF(V66="","",V66*O66) -> 2.2273674 | X66: =IF(R66="yes",W66,"")
A67: 18 | B67: income_main_gender | C67: income_main_gender | D67: What is the gender of the household member[s] generating income from this source? [OPERATOR: SINGLE RESPONSE.] 1)Male 2)Female 3)Joint [both male & female] 4)DON'T KNOW 5)REFUSED | E67: =LEN(D67) -> 181 | F67: Single Choice | G67: NA | H67: NA | I67: Form Type - Buttons | J67: 1-5 = [income_main_comp OR optional question] | K67: NA | L67: if income_main_gender = 1-5, go to income_main_comp or optional question | O67: =1 -> 1 | R67: no | V67: 4.7874017 | W67: =IF(V67="","",V67*O67) -> 4.7874017 | X67: =IF(R67="yes",W67,"")
B68: income_main_control | C68: income_main_control | D68: Who controls the revenue that is earned from this source? [OPERATOR: SINGLE RESPONSE.] 1)Male household member[s] 2)Female household member[s] 3)Joint household members [both female & male] 4)DON'T KNOW 5)REFUSED | E68: =LEN(D68) -> 215 | F68: Single Choice | G68: NA | H68: NA | I68: Form Type - Buttons | J68: 1-5 = income_main_comp | K68: NA | L68: if income_main_control = 1-5, go to income_main_comp | O68: =1 -> 1 | R68: no | V68: 20.918367 | W68: =IF(V68="","",V68*O68) -> 20.918367 | X68: =IF(R68="yes",W68,"")
O69: =1 -> 1 | W69: =IF(V69="","",V69*O69) | X69: =IF(R69="yes",W69,"")
A70: =A66+1 -> 20 | B70: income_main_comp | C70: income_main_comp | D70: Has your household's income from {income_main} changed in the last 3 months compared to the same period of a normal year? [OPERATOR: SINGLE RESPONSE.] 1)A lot more [increased by more than 50%] 2)Slightly more 3)Same 4)Slightly less 5)A lot less [less than half as much] 6)DON'T KNOW 7)REFUSED | E70: =LEN(D70) -> 294 | F70: Single Choice | G70: NA | H70: NA | I70: Form Type - Buttons | J70: 1-7= income_sec | K70: NA | L70: if income_main_comp = 1-7, go to income_sec | O70: =1 -> 1 | R70: yes | V70: 22.126215 | W70: =IF(V70="","",V70*O70) -> 22.126215 | X70: =IF(R70="yes",W70,"") -> 22.126215
O71: =1 -> 1 | W71: =IF(V71="","",V71*O71) | X71: =IF(R71="yes",W71,"")
A72: =A70+1 -> 21 | B72: income_sec | C72: income_sec | D72: What was your household's second most important source of income in the past 3 months? [OPERATOR: SINGLE RESPONSE. DON'T KNOW AND REFUSED OPTIONS SHOULD BE AVOIDED AS MUCH AS POSSIBLE.] 1)Production and sale of staple crops 2)Production and sale of vegetables or fruit 3)Production and sale of cashcrops 4)Production and sale of livestock and livestock products 5)Production and sale of honey or bee products 6)Production and sale of fish 7)Collection and sale of forestry or bush products 8)Agricultural trade EXCLUDING producers [formal or informal] 9)Daily wage on farms and other casual employment in agricultural sector 10)Stable employment in agricultural sector 11)Non-agricultural self-employed or liberal profession / doctor / architect / lawyer / including restaurant 12)Off-farm daily wages and other non-agricultural casual employment 13)Stable employment in non-agricultural sector 14)Public employment 15)Income not derived from work / Charity 16)Income not derived from work / Welfare transfer, pension, humanitarian aid 17)Income not derived from work / Remittances 18)Income not derived from work / Income from other rents 19)No second most important source of income 20)DON'T KNOW 21)REFUSED | E72: =LEN(D72) -> 1218 | F72: Single Choice | G72: NA | H72: NA | I72: Form Type - Buttons exclude selected "income_main" IsDemographic | J72: 1-3 = income_sec_crop_check 4 = income_sec_ls_check 5 = income_sec_comp OR optional question 6 = income_sec_fish_check 7-18 = income_sec_comp OR optional question 19-21 = shock | K72: NA | L72: if options #1-3 selected, go to income_sec_crop_check if options #4 selected, go to income_sec_ls_check if options #6 selected, go to income_sec_fish_check if options #5, 7-18 selected, go to [income_sec_comp OR optional question] if options #19-21 selected, go to shock | O72: =1 -> 1 | R72: yes | V72: 18.710653 | W72: =IF(V72="","",V72*O72) -> 18.710653 | X72: =IF(R72="yes",W72,"") -> 18.710653
B73: income_sec_crop_check | C73: income_sec_crop_check | D73: Are the crops that you sell also produced by you or anyone in your household? [OPERATOR: SINGLE RESPONSE.] 1)YES 2)NO 3)DON'T KNOW 4)REFUSED | E73: =LEN(D73) -> 143 | F73: Single Choice | G73: NA | H73: NA | I73: Form Type - Buttons | J73: 1-4 = income_sec_comp OR optional question | K73: NA | L73: if income_sec_crop_check = 1-4, go to [income_sec_comp OR optional question] | O73: =1 -> 1 | R73: yes | V73: 8 | W73: =IF(V73="","",V73*O73) -> 8 | X73: =IF(R73="yes",W73,"") -> 8
B74: income_sec_ls_check | C74: income_sec_ls_check | D74: Are the livestock and livestock products that you sell also produced by you or anyone in your household? [OPERATOR: SINGLE RESPONSE.] 1)YES 2)NO 3)DON'T KNOW 4)REFUSED | E74: =LEN(D74) -> 170 | F74: Single Choice | G74: NA | H74: NA | I74: Form Type - Buttons | J74: 1-4 = income_sec_comp OR optional question | K74: NA | L74: if income_sec_ls_check = 1-4, go to [income_sec_comp OR optional question] | O74: =1 -> 1 | R74: yes | V74: 8 | W74: =IF(V74="","",V74*O74) -> 8 | X74: =IF(R74="yes",W74,"") -> 8
B75: income_sec_fish_check | C75: income_sec_fish_check | D75: Are the fish and/or fish products that you sell also captured or harvested by you or anyone in your household? [OPERATOR: SINGLE RESPONSE.] 1)YES 2)NO 3)DON'T KNOW 4)REFUSED | E75: =LEN(D75) -> 176 | F75: Single Choice | G75: NA | H75: NA | I75: Form Type - Buttons | J75: 1-4 = income_sec_comp OR optional question | K75: NA | L75: if income_sec_fish_check = 1-4, go to [income_sec_comp OR optional question] | O75: =1 -> 1 | R75: yes | V75: 8 | W75: =IF(V75="","",V75*O75) -> 8 | X75: =IF(R75="yes",W75,"") -> 8
O76: =1 -> 1 | W76: =IF(V76="","",V76*O76) | X76: =IF(R76="yes",W76,"")
A77: 19 | B77: income_sec_amount | C77: income_sec_amount | D77: How much was earned [in Leones] from your second main income source, {income_sec}, in the past 3 months ? [OPERATOR: MAKE SURE THE INFORMATION IS RECORDED IN THE CORRECT CURRENCY. ENTER 8888888 FOR DON'T KNOW AND 9999999 FOR REFUSED.] | E77: =LEN(D77) -> 235 | F77: Range | G77: NA | H77: NA | I77: Form Type - TextBox | J77: 50 - 5000 = income_sec_comp or optional question 5000 - 20000 = income_sec_amount_conf 8888888-8888888 = income_sec_comp or optional question 9999999-9999999 = income_sec_comp or optional question | K77: NA | L77: If the income amount is over the threshold set in "Additional information", the respondent will be asked to confirm with income_sec_amount_conf. Otherwise, go to income_sec_comp. | N77: We recommend using this pair of questions together. | O77: =1 -> 1 | R77: no | V77: 23.20038 | W77: =IF(V77="","",V77*O77) -> 23.20038 | X77: =IF(R77="yes",W77,"")
A78: =#REF!+1 -> #REF! | B78: income_sec_amount_conf | C78: income_sec_amount_conf | D78: Can you confirm the amount of income you just stated is correct? [OPERATOR: IF THE AMOUNT EARNED FROM THIS INCOME SOURCE OVER THE PAST 3 MONTH IS INDEED OVER 5000, CLICK ON CONTINUE. OTHERWISE, GO BACK AND CHANGE THE AMOUNT ENTERED.] 1)CONTINUE | E78: =LEN(D78) -> 246 | F78: Single Choice | G78: NA | H78: NA | I78: Form Type - Buttons | J78: 1 = income_sec_comp or optional question | K78: NA | L78: if income_sec_amount_conf = 1, go to income_sec_comp | O78: =1 -> 1 | R78: no | V78: 1.9277389 | W78: =IF(V78="","",V78*O78) -> 1.9277389 | X78: =IF(R78="yes",W78,"")
A79: 18 | B79: income_sec_gender | C79: income_sec_gender | D79: What is the gender of the household member[s] generating income from this source? [OPERATOR: SINGLE RESPONSE.] 1)Male 2)Female 3)Joint [both male & female] 4)DON'T KNOW 5)REFUSED | E79: =LEN(D79) -> 181 | F79: Single Choice | G79: NA | H79: NA | I79: Form Type - Buttons | J79: 1-5 = [income_sec_comp OR optional question] | K79: NA | L79: if income_sec_gender = 1-5, go to income_sec_comp or optional question | O79: =1 -> 1 | R79: no | V79: 4.7874017 | W79: =IF(V79="","",V79*O79) -> 4.7874017 | X79: =IF(R79="yes",W79,"")
B80: income_sec_control | C80: income_sec_control | D80: Who controls the revenue that is earned from this source? [OPERATOR: SINGLE RESPONSE.] 1)Male household member[s] 2)Female household member[s] 3)Joint household members [both female & male] 4)DON'T KNOW 5)REFUSED | E80: =LEN(D80) -> 215 | F80: Single Choice | G80: NA | H80: NA | I80: Form Type - Buttons | J80: 1-5 = income_sec_comp | K80: NA | L80: if income_sec_control = 1-5, go to income_sec_comp | O80: =1 -> 1 | R80: no | V80: 20.918367 | W80: =IF(V80="","",V80*O80) -> 20.918367 | X80: =IF(R80="yes",W80,"")
O81: =1 -> 1 | W81: =IF(V81="","",V81*O81) | X81: =IF(R81="yes",W81,"")
A82: =#REF!+1 -> #REF! | B82: income_sec_comp | C82: income_sec_comp | D82: Has your household's income from {income_sec} changed in the last 3 months compared to the same period of a normal year? [OPERATOR: SINGLE RESPONSE.] 1)A lot more [increased by more than 50%] 2)Slightly more 3)Same 4)Slightly less 5)A lot less [less than half as much] 6)DON'T KNOW 7)REFUSED | E82: =LEN(D82) -> 294 | F82: Single Choice | G82: NA | H82: NA | I82: Form Type - Buttons | J82: 1-7= income_third | K82: NA | L82: if income_sec_comp = 1-7, go to income_third | O82: =1 -> 1 | R82: yes | V82: 17.261402 | W82: =IF(V82="","",V82*O82) -> 17.261402 | X82: =IF(R82="yes",W82,"") -> 17.261402
O83: =1 -> 1 | W83: =IF(V83="","",V83*O83) | X83: =IF(R83="yes",W83,"")
A84: =A82+1 -> #REF! | B84: income_third | C84: income_third | D84: What was your household's third most important source of income in the past 3 months? [OPERATOR: SINGLE RESPONSE. DON'T KNOW AND REFUSED OPTIONS SHOULD RARELY/NOT AVOIDED AS MUCH AS POSSIBLE.] 1)Production and sale of staple crops 2)Production and sale of vegetables or fruit 3)Production and sale of cashcrops 4)Production and sale of livestock and livestock products 5)Production and sale of honey or bee products 6)Production and sale of fish 7)Collection and sale of forestry or bush products 8)Agricultural trade EXCLUDING producers [formal and informal] 9)Daily wage on farms and other casual employment in agricultural sector 10)Stable employment in agricultural sector 11)Non-agricultural self-employed or liberal profession / doctor / architect / lawyer / including restaurant 12)Off-farm daily wages and other non-agricultural casual employment 13)Stable employment in non-agricultural sector 14)Public employment 15)Income not derived from work / Charity 16)Income not derived from work / Welfare transfer, pension, humanitarian aid 17)Income not derived from work / Remittances 18)Income not derived from work / Income from other rents 19)No third most important source of income 20)DON'T KNOW 21)REFUSED | E84: =LEN(D84) -> 1225 | F84: Single Choice | G84: NA | H84: NA | I84: Form Type - Buttons exclude selected "income_main" exclude selected "income_sec" IsDemographic | J84: 1-3 = income_third_crop_check 4 = income_third_ls_check 5 = income_third_comp OR optional question 6 = income_third_fish_check 7-18 = income_third_comp OR optional question 19-21 = shock | K84: NA | L84: if options #1-3 selected, go to income_third_crop_check if options #4 selected, go to income_third_ls_check if option #6 selected, go to income_third_fish_check if options #5, 7-18 selected, go to [income_third_comp OR optional question] if options #19-21 selected, go to shock | O84: =1 -> 1 | R84: yes | V84: 14.475392 | W84: =IF(V84="","",V84*O84) -> 14.475392 | X84: =IF(R84="yes",W84,"") -> 14.475392
B85: income_third_crop_check | C85: income_third_crop_check | D85: Are the crops that you sell also produced by you or anyone in your household? [OPERATOR: SINGLE RESPONSE.] 1)YES 2)NO 3)DON'T KNOW 4)REFUSED | E85: =LEN(D85) -> 143 | F85: Single Choice | G85: NA | H85: NA | I85: Form Type - Buttons | J85: 1-4 = income_third_comp OR optional question | K85: NA | L85: if income_third_crop_check = 1-4, go to [income_third_comp OR optional question] | O85: =1 -> 1 | R85: yes | V85: 8 | W85: =IF(V85="","",V85*O85) -> 8 | X85: =IF(R85="yes",W85,"") -> 8
B86: income_third_ls_check | C86: income_third_ls_check | D86: Are the livestock and livestock products that you sell also produced by you or anyone in your household? [OPERATOR: SINGLE RESPONSE.] 1)YES 2)NO 3)DON'T KNOW 4)REFUSED | E86: =LEN(D86) -> 170 | F86: Single Choice | G86: NA | H86: NA | I86: Form Type - Buttons | J86: 1-4 = income_third_comp OR optional question | K86: NA | L86: if income_third_ls_check = 1-4, go to [income_third_comp OR optional question] | O86: =1 -> 1 | R86: yes | V86: 8 | W86: =IF(V86="","",V86*O86) -> 8 | X86: =IF(R86="yes",W86,"") -> 8
B87: income_third_fish_check | C87: income_third_fish_check | D87: Are the fish and/or fish products that you sell also captured or harvested by you or anyone in your household? [OPERATOR: SINGLE RESPONSE.] 1)YES 2)NO 3)DON'T KNOW 4)REFUSED | E87: =LEN(D87) -> 176 | F87: Single Choice | G87: NA | H87: NA | I87: Form Type - Buttons | J87: 1-4 = income_third_comp OR optional question | K87: NA | L87: if income_third_fish_check = 1-4, go to [income_third_comp OR optional question] | O87: =1 -> 1 | R87: yes | V87: 8 | W87: =IF(V87="","",V87*O87) -> 8 | X87: =IF(R87="yes",W87,"") -> 8
O88: =1 -> 1 | W88: =IF(V88="","",V88*O88) | X88: =IF(R88="yes",W88,"")
O89: =1 -> 1 | W89: =IF(V89="","",V89*O89) | X89: =IF(R89="yes",W89,"")
A90: =#REF!+1 -> #REF! | B90: income_third_comp | C90: income_third_comp | D90: Has your household's income from {income_third} changed in the last 3 months compared to the same period of a normal year? [OPERATOR: SINGLE RESPONSE.] 1)A lot more [increased by more than 50%] 2)Slightly more 3)Same 4)Slightly less 5)A lot less [less than half as much] 6)DON'T KNOW 7)REFUSED | E90: =LEN(D90) -> 295 | F90: Single Choice | G90: NA | H90: NA | I90: Form Type - Buttons | J90: 1-7= shock | K90: NA | L90: if income_third_comp = 1-7, go to shock | O90: =1 -> 1 | R90: yes | V90: 15.876503 | W90: =IF(V90="","",V90*O90) -> 15.876503 | X90: =IF(R90="yes",W90,"") -> 15.876503
O91: =1 -> 1 | W91: =IF(V91="","",V91*O91) | X91: =IF(R91="yes",W91,"")
A92: =#REF!+1 -> #REF! | B92: shock | C92: shock_ 1) shock_noshock 2) shock_sicknessordeathofhh 3) shock_lostemplorwork 4) shock_otherintrahhshock 5) shock_higherfoodprices 6) shock_higherfuelprices 7) shock_mvtrestrict 8) shock_othereconomicshock 9) shock_pestoutbreak 10) shock_plantdisease 11) shock_animaldisease 12) shock_napasture 13) shock_othercropandlivests 14) shock_coldtemporhail 15) shock_flood 16) shock_hurricane 17) shock_drought 18) shock_earthquake 19) shock_landslides 20) shock_firenatural 21) shock_othernathazard 22) shock_violenceinsecconf 23) shock_theftofprodassets 24) shock_firemanmade 25) shock_othermanmadehazard 26) shock_dk 27) shock_ref | D92: Has your household or community faced any particular disaster or crisis affecting your household's ability to raise an income and/or to produce food for self consumption in the last 3 months, and if so, which one[s]? [OPERATOR: SELECT RELEVANT SHOCKS EXPERIENCED BY THE HOUSEHOLD. MULTIPLE RESPONSES POSSIBLE. REFER TO ECONOMIC SHOCKS, CROP AND LIVESTOCK SHOCKS, INTRA-HOUSEHOLD SHOCK, NATURAL HAZARDS AND HUMAN-INDUCED HAZARDS.] 1)No shock 2)Sickness or accident or death of household member[s] [sickness of breadwinner / unusually high medical expenditure / funeral expenses / death of breadwinner] 3)Lost employment or working opportunities [not due to illness/accident] 4)Other intra-household shock 5)Unusually high food prices 6)Unusually high fuel prices or transport prices 7)Population movement restrictions [e.g. due to epidemic or infrastructure damage] 8)Other economic shock 9)Pest outbreak 10)Plant disease 11)Animal disease [affecting many animals] or death 12)Lack of physical access to pasture 13)Other crop and livestock shock 14)Cold temperatures or hail 15)Flood / riverbank erosion 16)Hurricane / cyclone / tornado 17)Drought / heat stress 18)Earthquake 19)Landslides 20)Fire from natural disaster 21)Other natural hazard 22)Violence and insecurity / conflict 23)Theft of production assets [land / livestock / tools / etc] 24)Fire from human-induced disaster 25)Other human-induced hazard 26)DON'T KNOW 27)REFUSED | E92: =LEN(D92) -> 1440 | F92: Select All That Apply | G92: NA | H92: NA | I92: Form Type - Checklist 1,26,27 = IsNone | J92: 1-27 = [crp_intro or optional question] | K92: 1)shock_noshock 2)shock_sicknessordeathofhh 3)shock_lostemplorwork 4)shock_otherintrahhshock 5)shock_higherfoodprices 6)shock_higherfuelprices 7)shock_mvtrestrict 8)shock_othereconomicshock 9)shock_pestoutbreak 10)shock_plantdisease 11)shock_animaldisease 12)shock_napasture 13)shock_othercropandlivests 14)shock_coldtemporhail 15)shock_flood 16)shock_hurricane 17)shock_drought 18)shock_earthquake 19)shock_landslides 20)shock_firenatural 21)shock_othernathazard 22)shock_violenceinsecconf 23)shock_theftofprodassets 24)shock_firemanmade 25)shock_othermanmadehazard 26)shock_dk 27)shock_ref | L92: if shock = 1-27, go to [crp_intro or optional question] | O92: =1 -> 1 | R92: yes | V92: 37.85363 | W92: =IF(V92="","",V92*O92) -> 37.85363 | X92: =IF(R92="yes",W92,"") -> 37.85363
A93: 28 | B93: hh_explanation | C93: hh_explanation | D93: If the household was affected by a major recent shock as indicated in this assessment [for example, an earthquake], what are the [already observed or expected] consequences for your household, in your own words? [OPERATOR: RECORD IN FEW WORDS THE MAIN CONSEQUENCE OF THE RECENT SHOCKS. ENTER 88 FOR DON'T KNOW AND 99 FOR REFUSED.] | E93: =LEN(D93) -> 331 | F93: Open Ended | G93: NA | H93: NA | I93: Form Type - TextBox | J93: Any Response = covid | K93: NA | L93: For any response to hh_explanation, go to covid. | O93: =1 -> 1 | R93: no | W93: =IF(V93="","",V93*O93) | X93: =IF(R93="yes",W93,"")
O94: =1 -> 1 | W94: =IF(V94="","",V94*O94) | X94: =IF(R94="yes",W94,"")
A95: D. CROP PRODUCTION | W95: =IF(V95="","",V95*O95) | X95: =IF(R95="yes",W95,"")
A96: =A93+1 -> 29 | B96: crp_intro | C96: crp_intro | D96: We will now ask you some questions about crop production which apply to you and anyone in your household that is involved in crop production or sales. All questions refer to the crops grown during rain season. 1)CONTINUE | E96: =LEN(D96) -> 221 | F96: Single Choice | G96: NA | H96: Send if "hh_agricactivity" "Equals" "Yes - crop production" Or "hh_agricactivity" "Equals" "Yes - both crop and livestock production" Or "income_main_crop_check" "Equals" "YES" Or "income_sec_crop_check" "Equals" "YES" Or "income_third_crop_check" "Equals" "YES", if not satisfied go to "crp_salesmain" | I96: Form Type - Buttons | J96: 1 = crp_landsize_num | K96: NA | L96: If hh_agricactivity = "Yes - crop production" or "Yes - both crop and livestock production" or if they reported production and sales of crops in one of the three main income sources and confirmed that they are involved in production, then this section will be asked to respondents. Otherwise, skip to crp_salesmain. Next question is crp_landsize_num | O96: ='Additional information'!$D$17 -> 0.91 | R96: yes | V96: 7.3040729 | W96: =IF(V96="","",V96*O96) -> 6.6467063 | X96: =IF(R96="yes",W96,"") -> 6.6467063
O97: ='Additional information'!$D$17 -> 0.91 | W97: =IF(V97="","",V97*O97) | X97: =IF(R97="yes",W97,"")
B98: crp_landsize_num | C98: crp_landsize_num | D98: What is the total size of the land you can cultivate? [OPERATOR: RECORD THE TOTAL LAND SIZE PROVIDED BY THE RESPONDENT. WRITE 8888888 FOR DON'T KNOW AND 9999999 FOR REFUSED. MEASUREMENT UNIT WILL BE SPECIFIED IN THE FOLLOWING QUESTION.] | E98: =LEN(D98) -> 237 | F98: Range | G98: NA | H98: NA | I98: Form Type - TextBox | J98: 0-1000000 = crp_landsize_unit 8888888-8888888 = crp_main 9999999-9999999 = crp_main | K98: NA | L98: For any response, go to crp_landsize_unit. Range is between 0 and 1000000. For "Don't know" and "Refused", go to crp_main. | O98: ='Additional information'!$D$17 -> 0.91 | R98: yes | V98: 23.939905 | W98: =IF(V98="","",V98*O98) -> 21.785314 | X98: =IF(R98="yes",W98,"") -> 21.785314
B99: crp_landsize_unit | C99: crp_landsize_unit | D99: Unit of measurement for land size: [OPERATOR: DO NOT READ. SINGLE RESPONSE.] 1)Acres 2)Hectares 3)Square meters 4)Square feet 5)acres | E99: =LEN(D99) -> 138 | F99: Single Choice | G99: NA | H99: NA | I99: Form Type - Buttons | J99: 1-5 = crp_main | K99: NA | L99: if crp_landsize_unit = 1-5, go to crp_main | O99: ='Additional information'!$D$17 -> 0.91 | R99: yes | V99: 2.2494626 | W99: =IF(V99="","",V99*O99) -> 2.047011 | X99: =IF(R99="yes",W99,"") -> 2.047011
O100: ='Additional information'!$D$17 -> 0.91 | W100: =IF(V100="","",V100*O100) | X100: =IF(R100="yes",W100,"")
...

Sheet New Durations
A1: question | B1: duration | C1: responded % | D1: weighted time
A2: introduction | B2: 50.82254 | C2: 1 | D2: 50.82254
A3: agree | B3: 3.4964738 | C3: 0.79698741 | D3: 2.7866456
A4: resp_age | B4: 13.753073 | C4: 1 | D4: 13.753073
A5: resp_gender | B5: 2.1173561 | C5: 1 | D5: 2.1173561
A6: quotareached | B6: 2.28425 | C6: 0.79698741 | D6: 1.8205185
A7: hh_agricactivity | B7: 31.372377 | C7: 1 | D7: 31.372377
A8: hh_milieu | B8: 7.9225454 | C8: 0.15190348 | D8: 1.2034622
A9: hh_gender | B9: 10.085732 | C9: 1 | D9: 10.085732
A10: hh_education | B10: 12.894034 | C10: 1 | D10: 12.894034
A11: hh_wealth_water | B11: 15.265829 | C11: 0.63796463 | D11: 9.739059
A12: hh_wealth_toilet | B12: 15.123718 | C12: 0.59180156 | D12: 8.95024
A13: hh_wealthwall | B13: 12.821411 | C13: 0.15190348 | D13: 1.9476169
... A164: adm1_name | B164: 10.743817 | C164: 0.20301259 | D164: 2.1811302
A165: adm2_name | C165: 0 | D165: 0
A166: covid | B166: 56.471024 | C166: 0.20301259 | D166: 11.464329
A167: crp_landright | B167: 31 | C167: 0.0040467626 | D167: 0.12544964
A168: crp_seed | B168: 30.833334 | C168: 0.0040467626 | D168: 0.12477518
A169: crp_proddif | B169: 16.882986 | C169: 0.11848022 | D169: 2.0002998
A170: crp_salesdif | B170: 16.82699 | C170: 0.086630695 | D170: 1.4577339
A171: crp_saledif_2 | B171: 39.486874 | C171: 0.03139988 | D171: 1.2398831
A172: ls_proddif | B172: 15.938099 | C172: 0.10169365 | D172: 1.6208034
A173: ls_salesdif | B173: 13.330855 | C173: 0.060476619 | D173: 0.80620506
A174: ls_proc | B174: 16.437651 | C174: 0.0625 | D174: 1.0273532
A175: ls_proc_fac_state | B175: 8.666667 | C175: 0.00067446043 | D175: 0.005845324
A176: fish_proddif | B176: 12.523809 | C176: 0.001573741 | D176: 0.019709232
A177: cs_spentsavings | B177: 22.220184 | C177: 0.0081684652 | D177: 0.1815048
... A193: ls_proddif_2_covid19 | B193: 3.3438249 | C193: 1 | D193: 3.3438249

Sheet Crop list
C3: Select top 10 crops | D3: GeoPoll code | E3: Dataset code | F3: Label (EN)
C4: x | D4: {=_xlfn.SEQUENCE(90,1,1,1)} -> 1 | E4: 1.1 | F4: Rice
D5: 2 | E5: 1.2 | F5: Wheat
D6: 3 | E6: 1.3 | F6: Millet
D7: 4 | E7: 1.4 | F7: Sorghum
C8: x | D8: 5 | E8: 1.5 | F8: Maize
D9: 6 | E9: 1.6 | F9: Barley
D10: 7 | E10: 1.99 | F10: Other Cereal
C11: x | D11: 8 | E11: 2.1 | F11: Cassava
D12: 9 | E12: 2.2 | F12: Potatoe
C13: x | D13: 10 | E13: 2.3 | F13: Sweet Potatoes
D14: 11 | E14: 2.4 | F14: Yams
D15: 12 | E15: 2.5 | F15: Carrots
D16: 13 | E16: 2.6 | F16: Cocoyam
D17: 14 | E17: 2.99 | F17: Other tubers
D18: 15 | E18: 3.1 | F18: Beans
D19: 16 | E19: 3.2 | F19: Lentils
C20: x | D20: 17 | E20: 3.3 | F20: Peas
D21: 18 | E21: 3.4 | F21: Soybeans
D22: 19 | E22: 3.5 | F22: Chickpeas
D23: 20 | E23: 3.6 | F23: Fava beans
D24: 21 | E24: 3.7 | F24: Broad beans
D25: 22 | E25: 3.99 | F25: Other pulses
D26: 23 | E26: 4.1 | F26: Cabbage
D27: 24 | E27: 4.2 | F27: Lettuce
D28: 25 | E28: 4.3 | F28: Spinach-Amaranth
D29: 26 | E29: 4.4 | F29: Cassava leaves
D30: 27 | E30: 4.5 | F30: Potatoe leaves
D31: 28 | E31: 4.6 | F31: Moringa
D32: 29 | E32: 4.7 | F32: Sorrel Hibiscus / Rosselle
... D40: 37 | E40: 5.5 | F40: Zucchini
C41: x | D41: 38 | E41: 5.6 | F41: Okra
D42: 39 | E42: 5.7 | F42: Bell pepper
D43: 40 | E43: 5.8 | F43: Onions
D44: 41 | E44: 5.9 | F44: Haricot
D45: 42 | E45: 5.101 | F45: Green peas
D46: 43 | E46: 5.11 | F46: Fava beans green
D47: 44 | E47: 5.99 | F47: Other non leafy vegs
D48: 45 | E48: 6.1 | F48: Orange
D49: 46 | E49: 6.2 | F49: Lemon
D50: 47 | E50: 6.3 | F50: Grapefruit
D51: 48 | E51: 6.4 | F51: Mandarins/clementines
D52: 49 | E52: 6.99 | F52: Other citrus fruit
D53: 50 | E53: 7.1 | F53: Sweet Banana
... D72: 69 | E72: 8.1 | F72: Coconuts
C73: x | D73: 70 | E73: 8.2 | F73: Groundnut/peanut
C74: x | D74: 71 | E74: 8.3 | F74: Cashew Nut
D75: 72 | E75: 8.4 | F75: Kola Nut
D76: 73 | E76: 8.5 | F76: Sesame
D77: 74 | E77: 8.6 | F77: Bambara nut
D78: 75 | E78: 8.7 | F78: Almond
D79: 76 | E79: 8.8 | F79: Walnut
D80: 77 | E80: 8.99 | F80: Other nuts
C81: x | D81: 78 | E81: 9.1 | F81: Cocoa
C82: x | D82: 79 | E82: 9.2 | F82: Coffee
D83: 80 | E83: 9.3 | F83: Tea
D84: 81 | E84: 9.4 | F84: Sugarcane
D85: 82 | E85: 9.5 | F85: Sunflower
D86: 83 | E86: 9.99 | F86: Other food cash crop
D87: 84 | E87: 10.1 | F87: Cotton
D88: 85 | E88: 10.2 | F88: Rubber
D89: 86 | E89: 10.3 | F89: Jute
D90: 87 | E90: 10.4 | F90: Fodder
D91: 88 | E91: 10.5 | F91: Tobacco
D92: 89 | E92: 10.6 | F92: Qat
D93: 90 | E93: 10.99 | F93: Other non-food cash crop

Sheet Additional information
C2: Original | D2: Replacement | E2: Comment | F2: Examples
B3: FOR CORE QUESTIONS . (Mandatory to fill out) . | C3: ADMIN1 | D3: Region | E3: The first subdivision of the country, after national level; region; province; governorate; etc. | F3: region
C4: ADMIN2 | D4: District | E4: The second subdivision of the country; district; municipality; LGA; etc. | F4: district
C5: reference year | D5: a normal year | E5: Comparison questions will need need a reference year. Select whether you want to use "last year" or "a normal year" as a baseline. A "normal year" should refers to an average year from the past 5 years - make sure to train the enumerators accordingly. | F5: a normal year
C6: season | D6: rain season | E6: Name the crop season(s) of interest if there are several cropping seasons in the country (e.g. Meher and Belg in Ethiopia, rainy season / flood-recession cropping / irrigated dry season in the Sahel). You can refer to the “last season” or “ongoing season". | F6: wet season
C7: season phase | D7: Planting | E7: Indicate the phase of the season at the time of data collection. If the harvest from the season has not yet occurred, the question on crop harvest (crp_harv_change) will include the word “expected” (where #expected or nothing# is located). If the harvest has occured, "expected" will not be inserted in the question. | F7: Harvesting
C8: local measurement unit | D8: acres | E8: Specify the local measurement unit for land size, other than acres, hectares, square meters and square feet. If no other unit of measurement is needed, keep this cell blank. | F8: Jeribs
C9: local measurement unit conversion | D9: 2.5 | E9: Include the conversion of the local measurement unit to hectares. In other words, how many local measurement units are in 1 ha. | F9: 0.2
B10: FOR OPTIONAL QUESTIONS . (Fill out if applicable) . | C10: currency | D10: Leones | E10: The name of the main currency used nationally; USD; Naira; Rial; Pesos; etc. | F10: Naira
C11: MIN AMOUNT | D11: 50 | E11: The minimum amount for an income source should be set at 0 or any value below which it is not possible to do a transaction. For example, the smallest coin/banknote in a currency can be 1000, in which case you would set the minimum at 1000. Provide this input in the same currency as specified above. Only digits should be inputted. | F11: 5
C12: MAX AMOUNT | D12: 20000 | E12: Set the maximum amount for an income source over 3 months. Enumerators will not be able to input values above this amount in questions related to income amounts. Using previous representative surveys for this population, you can estimate this amount by using the mean income plus five (5) standard deviations, unless the country has high inflation. In the latter case, set the maximum value based on your country context (higher than the proposed approach). Provide this input in the same currency as specified above. Only digits should be inputted. | F12: 5000000
C13: THRESHOLD | D13: 5000 | E13: The threshold salary should be calculated to flag outliers (responses that look suspiciously high). Using previous representative surveys for this population, a good estimate is the average plus three (3) standard deviations, which should give the threshold for the 3 or 4% highest income values. Provide this input in the same currency as specified above. Only digits should be inputted. | F13: 1200000
C14: local vegetables | D14: Okra, cucumber, Tomatoes, egg plants, cabage, carrot, ball peper , onions, cassava leaves, potato leaves | E14: Input some common local vegetables [to be used as examples in the food consumption score indicator]. | F14: eggplants, zucchini, cauliflower
C15: local fruits | D15: Banana, plantain, Papaya, Orange, Grape fruit,Mango, Pineapple, Watermelon | E15: Input some common local fruits [to be used as examples in the food consumption score indicator]. | F15: apples, bananas, oranges
B17: FILL OUT FOR QUESTIONNAIRE DURATION ESTIMATION . | C17: Expected percentage of respondents cultivating crops | D17: 0.91 | E17: If the survey is representative and has no quotas, write the proportion of rural households cultivating crops at country level, or if the survey follows a previous round with identical sample design, just report the percentage from the previous round. If you are using quotas, calculate the ratio of the quota over the minimum sample size at the level where the quota is implemented (so if you have a minimum sample size per strata of 110 with a quota of 100 crop producers, then it's 100/110 = 91% (the maximum you should write is 100%). | F17: 0.91
C18: Expected percentage of respondents raising livestock | D18: 0.91 | E18: If the survey is representative and has no quotas, write the proportion of rural households raising livestock at country level, or if the survey follows a previous round with identical sample design, just report the percentage from the previous round. If you are using quotas, calculate the ratio of the quota over the minimum sample size at the level where the quota is implemented (so if you have a minimum sample size of 110 but a quota of 100 livestock producers, then it's 100/110 = 91% (the maximum you should write is 100%) | F18: 0.91
C19: Expected percentage of respondents involved in fishery | D19: 0.05 | E19: If the survey is representative and has no quotas, write the proportion of rural households involved in fisheries or aquaculture, otherwise if you are using quotas, calculate the ratio of the quota over the sample size at the level where the quota is implemented. (so if you haven't set a quota, and you expect to have a representative proportion of fishermen, just write the percentage of fishermen in the population you are targeting, in the example to the right, 5%) | F19: 0.05

Sheet Admin 2 info
A1: adm2_name | B1: adm2_name_local | C1: adm2_pcode | D1: adm1_name | E1: adm1_pcode | F1: adm0_name | G1: adm0_ISO3
A2: Pujehun | C2: SL0304 | D2: Southern | E2: SL03 | F2: Sierra Leone | G2: SLE
A3: Bonthe | C3: SL0302 | D3: Southern | E3: SL03 | F3: Sierra Leone | G3: SLE
A4: Bo | C4: SL0301 | D4: Southern | E4: SL03 | F4: Sierra Leone | G4: SLE
A5: Kailahun | C5: SL0101 | D5: Eastern | E5: SL01 | F5: Sierra Leone | G5: SLE
A6: Moyamba | C6: SL0303 | D6: Southern | E6: SL03 | F6: Sierra Leone | G6: SLE
A7: Kenema | C7: SL0102 | D7: Eastern | E7: SL01 | F7: Sierra Leone | G7: SLE
A8: Tonkolili | C8: SL0205 | D8: Northern | E8: SL02 | F8: Sierra Leone | G8: SLE
A9: Kono | C9: SL0103 | D9: Eastern | E9: SL01 | F9: Sierra Leone | G9: SLE
A10: Western Area Rural | C10: SL0401 | D10: Western | E10: SL04 | F10: Sierra Leone | G10: SLE
A11: Western Area Urban | C11: SL0402 | D11: Western | E11: SL04 | F11: Sierra Leone | G11: SLE
A12: Falaba | C12: SL0206 | D12: Northern | E12: SL02 | F12: Sierra Leone | G12: SLE
A13: Bombali | C13: SL0201 | D13: Northern | E13: SL02 | F13: Sierra Leone | G13: SLE
... A17: Karene | C17: SL0503 | D17: North Western | E17: SL05 | F17: Sierra Leone | G17: SLE
