Workbook

Sheet survey
A1: GeoPoll Submission Form
A2: FAO - Household Questionnaire | P2: Additional notes
A3: Q # | B3: Q Name | C3: Suggested Qname | D3: English | E3: Length | F3: Arabic | G3: Length | H3: Q Type | I3: Randomize | J3: Conditional | K3: Programming Instructions | L3: Skip Pattern | M3: Codes | N3: Default skip patterns & conditional | O3: Specify skip pattern variable (from blue text) | Q3: Estimated percentage of repondents | T3: Mandatory | X3: Duration (sec) | Y3: Weighted duration | Z3: Core questions only
A4: A. PRESENTATION OF THE SURVEY AND ELIGIBILITY CRITERIA SELECTION | T4: no | Y4: =IF(X4="","",X4*V4) | Z4: =IF(T4="yes",Y4,"")
A5: NA | B5: Optin | D5: Optin | E5: =LEN(D5) -> 5 | F5: Optin | G5: =LEN(F5) -> 5 | H5: Open Ended | I5: NA | J5: NA | K5: Form Type - TextBox | L5: Any Response = phone_number | M5: NA | N5: NA | T5: no | X5: 0 | Y5: =IF(X5="","",X5*Q5) -> 0 | Z5: =IF(T5="yes",Y5,"")
A6: NA | B6: phone_number | C6: phone_number | D6: Input the phone number that you are contacting: | E6: =LEN(D6) -> 48 | F6: أدخل رقم الهاتف الذي تتصل به: | G6: =LEN(F6) -> 29 | H6: Open Ended | I6: NA | J6: NA | K6: Form Type - TextBox | L6: Any Response = calldispo | M6: NA | N6: NA | T6: yes | X6: 0 | Y6: =IF(X6="","",X6*Q6) -> 0 | Z6: =IF(T6="yes",Y6,"") -> 0
A7: NA | B7: calldispo | C7: calldispo | D7: Phone number: #CATI_MOBILENUMBER# 1)Someone answers 2)Answering machine 3)No answer 4)Hang up or refusal 5)Call back 6)Under review 7)Disconnected | E7: =LEN(D7) -> 146 | F7: رقم الهاتف: #CATI_MOBILENUMBER# 1) يجيب شخص ما 2) جهاز الرد الالي 3) لا جواب 4) إنهاء المكالمة أو الرفض 5) معاودة الاتصال 6) قيد المراجعة 7) قطع الاتصال | G7: =LEN(F7) -> 153 | H7: Single Choice | I7: NA | J7: NA | K7: Form Type - Buttons | L7: 1 = resp_language 2 = AnsweringMachine 3 = NoAnswer 4 = Refusal 5 = WhenCallBack 6 = UnderReview 7 = Disconnected | M7: NA | N7: NA | T7: no | X7: 14.695308 | Y7: =IF(X7="","",X7*Q7) -> 0 | Z7: =IF(T7="yes",Y7,"")
A8: NA | B8: AnsweringMachine | C8: calldispo_answeringmachine | D8: Reached an answering machine. | E8: =LEN(D8) -> 29 | F8: لقد تم توجيهك إلى جهاز الرد الالي | G8: =LEN(F8) -> 33 | H8: NA | I8: NA | J8: NA | K8: NA | L8: End Poll AnsweringMachine | M8: NA | N8: NA | T8: no | X8: 0 | Y8: =IF(X8="","",X8*Q8) -> 0 | Z8: =IF(T8="yes",Y8,"")
A9: NA | B9: NoAnswer | C9: calldispo_noanswer | D9: Phone rang and no one answered. | E9: =LEN(D9) -> 31 | F9: رن الهاتف ولم يرد أحد | G9: =LEN(F9) -> 21 | H9: NA | I9: NA | J9: NA | K9: NA | L9: End Poll NoAnswer | M9: NA | N9: NA | T9: no | X9: 0 | Y9: =IF(X9="","",X9*Q9) -> 0 | Z9: =IF(T9="yes",Y9,"")
A10: NA | B10: UnderReview | C10: calldispo_underreview | D10: Case needs review by a supervisor. | E10: =LEN(D10) -> 34 | F10: الحالة تحتاج إلى مراجعة من قبل مشرف | G10: =LEN(F10) -> 35 | H10: NA | I10: NA | J10: NA | K10: NA | L10: End Poll UnderReview | M10: NA | N10: NA | T10: no | X10: 0 | Y10: =IF(X10="","",X10*Q10) -> 0 | Z10: =IF(T10="yes",Y10,"")
A11: NA | B11: Disconnected | C11: calldispo_disconnected | D11: Phone was disconnected or out of service. | E11: =LEN(D11) -> 41 | F11: تم فصل الهاتف أو الهاتف خارج الخدمة | G11: =LEN(F11) -> 35 | H11: NA | I11: NA | J11: NA | K11: NA | L11: End Poll Disconnected | M11: NA | N11: NA | T11: no | X11: 0 | Y11: =IF(X11="","",X11*Q11) -> 0 | Z11: =IF(T11="yes",Y11,"")
A12: NA | B12: resp_language | C12: resp_language | D12: Which language do you wish to proceed with? [OPERATOR: READ ANSWER CHOICES. SINGLE RESPONSE.] 1)English 2)Kurdish | E12: =LEN(D12) -> 115 | F12: ما هي اللغة التي ترغب في المتابعة بها؟ [المُشغل: اقرأ خيارات الإجابة. استجابة واحدة.] 1) عربي 2) كردي | G12: =LEN(F12) -> 103 | H12: Single Choice | I12: NA | J12: NA | K12: Form Type - Buttons | L12: Any response = introduction | M12: NA | N12: For any response, go to introduction | P12: To be added Kurdish language | T12: no | X12: 3.1032724 | Y12: =IF(X12="","",X12*Q12) -> 0 | Z12: =IF(T12="yes",Y12,"")
A13: NA | B13: introduction | C13: introduction | D13: Hello sir/ma'am, my name is #OPERATOR#, and I am calling from GeoPoll Polling Agency on behalf of the Food and Agriculture Organization of the United Nations [FAO]. We are conducting a survey on household livelihoods and the ability to access food in your area. I would like to ask you some questions about your household. The survey usually takes 15/20 minutes to complete. Any information that you provide will be kept strictly confidential, only used for the purpose of the survey and will not be shown to other people. Your voluntary participation in the outcome of this interview is NOT IN ANY WAY linked to your personal chance of receiving any assistance. This is voluntary and you can choose not to answer any or all of the questions if you want. However, we hope that you will participate since your views are important. You will receive #TOPUP#! of communication credit as an incentive for the participation of the survey. Please note that this call may be recorded for quality purposes. Do you have any questions? [OPERATOR: ADDRESS QUESTIONS FROM RESPONDENT, IF ANY.] 1)CONTINUE | E13: =LEN(D13) -> 1098 | F13: مرحبًا سيدي / سيدتي ، اسمي #OPERATOR#. أتصل من وكالة GeoPoll الاستقصائية نيابة عن منظمة الأغذية والزراعة للأمم المتحدة (الفاو). نجري دراسة استقصائية حول سبل عيش الأسر والقدرة على الوصول إلى الغذاء في منطقتك. أود أن أطرح عليك بعض الأسئلة حول أسرتك. يستغرق الاستبيان عادةً 15/20 دقيقة. سيتم الاحتفاظ بسرية تامة بأي معلومات تقدمها ، ولن يتم استخدامها إلا لغرض الدراسة ولن يتم عرضها لأشخاص آخرين. إن مشاركتك الطوعية في نتيجة هذه الدراسة ليست مرتبطة بأي شكل من الأشكال بفرصتك الشخصية في تلقي أي مساعدة. هذا تطوعي ويمكنك اختيار عدم الإجابة على أي من الأسئلة أو جميعها إذا كنت تريد ذلك. ومع ذلك ، نأمل أن تشارك لأن آرائك مهمة. سوف تتلقى #TOPUP#! ائتمان الاتصال كحافز للمشاركة في هذه الدراسة. يرجى الملاحظة أنه قد يتم تسجيل هذه المكالمة لغاية مراقبة الجودة. هل لديك اسئلة؟ [المُشغل: أجب على أسئلة المُجيب ، إن وجدت.] 1) تابع | G13: =LEN(F13) -> 823 | H13: Single Choice | I13: NA | J13: NA | K13: Form Type - Buttons | L13: 1 = Agree | M13: NA | N13: For any response, go to Agree | P13: 1$ | T13: no | X13: 37.418449 | Y13: =IF(X13="","",X13*Q13) -> 0 | Z13: =IF(T13="yes",Y13,"")
A14: NA | B14: Agree | C14: resp_agree | D14: Are you interested in participating in this survey? [OPERATOR: SINGLE RESPONSE] 1)Yes 2)Not now but another time in the week 3)No | E14: =LEN(D14) -> 134 | F14: هل لديك رغبة في بالمشاركة في هذه الدراسة؟ [المشغل: استجابة واحدة] 1) نعم 2) ليس الآن ولكن في وقت آخر في الأسبوع 3) لا | G14: =LEN(F14) -> 119 | H14: StartRecording | I14: NA | J14: NA | K14: Form Type - Buttons | L14: 1 = id_panel 2 = WhenCallBack 3 = resp_refusalwhy | M14: NA | N14: if Agree = 1, go to id_panel OR resp_firstname if Agree = 2, go to WhenCallBack if Agree = 3, go to resp_refusalwhy | Q14: 1 | T14: no | X14: 3.8059516 | Y14: =IF(X14="","",X14*Q14) -> 3.8059516 | Z14: =IF(T14="yes",Y14,"")
A15: NA | B15: id_panel | C15: id_panel | D15: Have you or any member of your household received a call on behalf of FAO regarding this topic in the past two years? [OPERATOR: SINGLE RESPONSE.] 1)YES 2)NO 3)DON'T KNOW | E15: =LEN(D15) -> 172 | F15: هل تلقيت انت أو أي أحد من أفراد أسرتك أي مكالمه بالنيابة عن منظمة الأغذيه و الزراعه [ الفاو ] بخصوص هذا الموضوع خلال العامين السابقين ؟ [ المشغل : أجابه واحده ] 1)نعم 2)لا 3)لا أعرف | G15: =LEN(F15) -> 185 | H15: Single Choice | I15: NA | J15: NA | K15: Form Type - Buttons | L15: 1-3 = resp_firstname | M15: NA | N15: For any response, go to resp_firstname | P15: It is highly recommended to include the question id_panel if a panelist approach is used. | Q15: 1 | T15: no
A16: NA | B16: resp_refusalwhy | C16: resp_refusalwhy | D16: Please let us know why you have REFUSED to take the survey. [OPERATOR: SINGLE RESPONSE] 1)Not interested 2)Do not want to be recorded 3)Other [specify] | E16: =LEN(D16) -> 153 | F16: يرجى إخبارنا سبب رفضك للمشاركة في هذه الدراسة. [المشغل: استجابة واحدة] 1) غير مهتم 2) لا أريد أن يتم تسجيلي 3) آخر [حدد] | G16: =LEN(F16) -> 122 | H16: Open Ended - Single Choice | I16: NA | J16: NA | K16: Form Type - RadioList | L16: Any Response = Refusal | M16: NA | N16: For any response, go to Refusal | Q16: 1 | T16: no | X16: 0 | Y16: =IF(X16="","",X16*Q16) -> 0 | Z16: =IF(T16="yes",Y16,"")
A17: NA | B17: WhenCallBack | C17: resp_whencallback | D17: When would it be a good time to call you back? [RECORD HH/MM/DD/MM OF CALLBACK] | E17: =LEN(D17) -> 80 | F17: ما هو التاريخ / الوقت المناسب لمعاودة الاتصال بك؟ [RECORD HH / MM / DD / MM of CALLBACK] | G17: =LEN(F17) -> 89 | H17: Open Ended | I17: NA | J17: NA | K17: Form Type - TextBox IsCallBackDemographic | L17: Any Response = CallbackMessageEN | M17: NA | N17: For any response, go to CallbackMessageEN | Q17: 1 | T17: no | X17: 0 | Y17: =IF(X17="","",X17*Q17) -> 0 | Z17: =IF(T17="yes",Y17,"")
A18: NA | B18: CallbackMessageEN | C18: callbackmessage_en | D18: Thank you, we will call you back at {WhenCallBack} you requested. Thank you again and have a great day! [OPERATOR: ENTER CALL NOTES BELOW, WHO YOU SPOKE TO AND WHAT THEY SAID] | E18: =LEN(D18) -> 176 | F18: شكرًا لك ، سوف نعاود الاتصال بك في #WhenCallBack# الذي طلبته. شكرا لك مرة أخرى و نتمنى لك يوم جميل! [المُشغل: أدخل ملاحظات الاتصال أدناه ، مع من تحدثت وماذا قالوا] | G18: =LEN(F18) -> 164 | H18: Open Ended | I18: NA | J18: NA | K18: Form Type - TextBox | L18: Any Response = End poll callback | M18: NA | N18: NA | Q18: 1 | T18: no | X18: 0 | Y18: =IF(X18="","",X18*Q18) -> 0 | Z18: =IF(T18="yes",Y18,"")
A19: NA | B19: Ineligible | C19: NA | D19: You are ineligible for this survey. Thank you for your time and please look out for future surveys! | E19: =LEN(D19) -> 99 | F19: أنت غير مؤهل للمشاركة في هذه الدراسة، شكرًا لك على وقتك. ترقب دراسات GeoPoll المستقبلية! | G19: =LEN(F19) -> 89 | H19: NA | I19: NA | J19: NA | K19: NA | L19: End Poll Ineligible | M19: NA | N19: NA | Q19: 1 | T19: no | X19: 0 | Y19: =IF(X19="","",X19*Q19) -> 0 | Z19: =IF(T19="yes",Y19,"")
A20: NA | B20: Refusal | C20: NA | D20: Thank you for your time, you will be removed from today's survey. | E20: =LEN(D20) -> 65 | F20: شكراً جزيلاً على وقتك، سنقوم بحذف إسمك من دراسة اليوم. | G20: =LEN(F20) -> 54 | H20: NA | I20: NA | J20: NA | K20: NA | L20: End poll declined | M20: NA | N20: NA | Q20: 1 | T20: no | X20: 0 | Y20: =IF(X20="","",X20*Q20) -> 0 | Z20: =IF(T20="yes",Y20,"")
A21: B. GENERAL INFORMATION & ELIGIBILITY CRITERIA | Y21: =IF(X21="","",X21*Q21) | Z21: =IF(T21="yes",Y21,"")
A22: NA | B22: resp_firstname | C22: resp_firstname | D22: What is your first name? [OPERATOR: RECORD THE RESPONDENT'S FIRST NAME. ENTER 999 FOR REFUSED.] | E22: =LEN(D22) -> 96 | F22: ما اسمك؟ [المُشغل: سجل اسم المجيب. أدخل 999 في حالة الرفض.] | G22: =LEN(F22) -> 60 | H22: Open Ended | I22: NA | J22: NA | K22: Form Type - TextBox | L22: Any Response = resp_lastname | M22: NA | N22: For any response, go to resp_lastname | Q22: =1 -> 1 | T22: yes | X22: 25.874027 | Y22: =IF(X22="","",X22*Q22) -> 25.874027 | Z22: =IF(T22="yes",Y22,"") -> 25.874027
A23: NA | B23: resp_lastname | C23: resp_lastname | D23: What is your last name? [OPERATOR: RECORD THE RESPONDENT'S LAST NAME. ENTER 999 FOR REFUSED.] | E23: =LEN(D23) -> 95 | F23: ما هو اسم عائلتك؟ [المُشغل: سجل اسم عائلة المجيب. أدخل 999 في حالة الرفض.] | G23: =LEN(F23) -> 75 | H23: Open Ended | I23: NA | J23: NA | K23: Form Type - TextBox | L23: Any Response = resp_age | M23: NA | N23: For any response, go to resp_age | Q23: =1 -> 1 | T23: yes | X23: 8.5994816 | Y23: =IF(X23="","",X23*Q23) -> 8.5994816 | Z23: =IF(T23="yes",Y23,"") -> 8.5994816
A24: 1 | B24: resp_age | C24: resp_age | D24: How old are you? [OPERATOR: RECORD AGE IN NUMBER OF YEARS. ROUND UP TO NEAREST WHOLE NUMBER. IF THE RESPONDENT GIVES BIRTH YEAR, REPEAT THE QUESTION. ENTER 00 FOR DON'T KNOW.] | E24: =LEN(D24) -> 177 | F24: كم عمرك؟ [المُشغل: سجل العمر في عدد السنوات. قم بالتقريب لأقرب رقم كامل. إذا أعطى المجيب سنة الميلاد ، فكرر السؤال. أدخل 00 للا أعرف.] | G24: =LEN(F24) -> 135 | H24: Range | I24: NA | J24: NA | K24: Form Type - TextBox | L24: 0-17 = Ineligible 18-100 = resp_gender 00 = Ineligible | M24: NA | N24: Only respondents from 18-100 will be eligible for the survey. | Q24: =1 -> 1 | T24: yes | X24: 9.8907185 | Y24: =IF(X24="","",X24*Q24) -> 9.8907185 | Z24: =IF(T24="yes",Y24,"") -> 9.8907185
A25: =A24+1 -> 2 | B25: resp_gender | C25: resp_gender | D25: What is the gender of the respondent? [OPERATOR: DO NOT ASK THIS QUESTION OUT LOUD. LISTEN TO THE VOICE AND SELECT THE GENDER.] 1)Male 2)Female 3)DON'T KNOW 4)REFUSED | E25: =LEN(D25) -> 168 | F25: ما هو جنس المجيب؟ [المُشغل: لا تطرح هذا السؤال. استمع إلى الصوت وحدد المربع الصحيح.] 1) ذكر 2) أنثى 3) لا أعرف 4) رفض الإجابة | G25: =LEN(F25) -> 127 | H25: Single Choice | I25: NA | J25: NA | K25: Form Type - Buttons | L25: 1-4 = phone_number_conf | M25: NA | N25: For any response, go to phone_number_conf | Q25: =1 -> 1 | T25: yes | X25: 1.7156482 | Y25: =IF(X25="","",X25*Q25) -> 1.7156482 | Z25: =IF(T25="yes",Y25,"") -> 1.7156482
Q26: =1 -> 1 | Y26: =IF(X26="","",X26*Q26) | Z26: =IF(T26="yes",Y26,"")
B27: phone_number_conf | C27: phone_number_conf | D27: Is the phone number I am calling you on yours or a household members? [OPERATOR: SINGLE RESPONSE.] 1)YES 2)NO 3)DON'T KNOW 4)REFUSED | E27: =LEN(D27) -> 134 | F27: هل رقم الهاتف الذي أتصل به هو رقمك أو رقم أحد أفراد أسرتك؟ [المشغل: استجابة واحدة.] 1) نعم 2) لا 3) لا أعرف 4) رفض الإجابة | G27: =LEN(F27) -> 124 | H27: Single Choice | I27: NA | J27: NA | K27: Form Type - Buttons | L27: 1 = contact_2 2 = phone_number_personal 3-4 = contact_2 | M27: NA | N27: if phone_number_conf = 1, go to contact_2 if phone_number_conf = 2, go to phone_number_personal if phone_number_conf = 3-4, go to contact_2 | Q27: =1 -> 1 | T27: yes - panel | X27: 6.375237 | Y27: =IF(X27="","",X27*Q27) -> 6.375237 | Z27: =IF(T27="yes",Y27,"")
B28: phone_number_personal | C28: phone_number_pers | D28: What is your phone number? [OPERATOR: RECORD THE NUMBER GIVEN] | E28: =LEN(D28) -> 63 | F28: ما هو رقم هاتفك؟ ( المشغل: قم بتسجيل الرقم المعطى لك ) | G28: =LEN(F28) -> 54 | H28: Open Ended | I28: NA | J28: NA | K28: Form Type - TextBox | L28: Any Response = contact_2 | M28: NA | N28: For any response, go to contact_2 | Q28: =1 -> 1 | T28: yes - panel | X28: 28.700001 | Y28: =IF(X28="","",X28*Q28) -> 28.700001 | Z28: =IF(T28="yes",Y28,"")
B29: contact_2 | C29: contact_2 | D29: Can you give me an additonal phone number belonging to you, a relative or a friend at which you can be reached? [OPERATOR: SINGLE RESPONSE.] 1)YES - mine 2)YES - other household member 3)YES - friend or relative [non-household member] 4)NO 5)DON'T KNOW 6)REFUSED | E29: =LEN(D29) -> 265 | F29: هل يمكن أن تعطيني رقم هاتف إضافي يخصك ، أو يخص قريبًا أو صديقًا يمكن الوصول إليك من خلاله؟ [المشغل: استجابة واحدة.] 1) نعم - لي 2) نعم - فرد اخر من أفراد الأسرة 3) نعم - صديق أو أحد الأقارب [ ليس فردا من أفراد الأسرة ] 4) لا 5) لا أعرف 6) رفض الإجابة | G29: =LEN(F29) -> 252 | H29: Single Choice | I29: NA | J29: NA | K29: Form Type - Buttons | L29: 1-3 = phone_number_2 4-6 = hh_admin1 | M29: NA | N29: if contact_2 = 1-3, go to phone_number_2 if contact_2 = 4-6, go to contact_3 | Q29: =1 -> 1 | T29: yes - panel | X29: 10.141817 | Y29: =IF(X29="","",X29*Q29) -> 10.141817 | Z29: =IF(T29="yes",Y29,"")
B30: phone_number_2 | C30: phone_number_2 | D30: What is the additional phone number? [OPERATOR: RECORD THE NUMBER GIVEN] | E30: =LEN(D30) -> 73 | F30: ما هو رقم الهاتف الإضافي؟ ( المشغل: قم بتسجيل الرقم المعطى لك ) | G30: =LEN(F30) -> 63 | H30: Open Ended | I30: NA | J30: NA | K30: Form Type - TextBox | L30: Any Response = contact_2_name | M30: NA | N30: For any response, go to contact_2_name | Q30: =1 -> 1 | T30: yes - panel | X30: 21.659983 | Y30: =IF(X30="","",X30*Q30) -> 21.659983 | Z30: =IF(T30="yes",Y30,"")
B31: contact_2_name | C31: contact_2_name | D31: What is the name of the contact? [OPERATOR: RECORD THE NAME OF THE CONTACT FOR THE PHONE NUMBER.] | E31: =LEN(D31) -> 98 | F31: ما هو اسم صاحب رقم الهاتف الإضافي الذي قمت بمشاركته؟ ( المشغل: قم بتسجيل اسم صاحب رقم الهاتف ) | G31: =LEN(F31) -> 94 | H31: Open Ended | I31: NA | J31: Send if "contact_2" "Equals" "YES - other household member" OR "contact_2" "Equals" "YES - friend or relative [non-household member]", if not satisfied go to "contact_3" | K31: Form Type - TextBox | L31: Any Response = contact_3 | M31: NA | N31: Asked if response to contact_2 was "YES - other household member" or "YES - friend or relative [non-household member]". Otherwise, it skips to "contact_3". For any response, go to contact_3 | Q31: =1 -> 1 | T31: yes - panel | X31: 11.821796 | Y31: =IF(X31="","",X31*Q31) -> 11.821796 | Z31: =IF(T31="yes",Y31,"")
B32: contact_3 | C32: contact_3 | D32: Can you give me an additonal phone number belonging to you, a relative or a friend at which you can be reached? [OPERATOR: SINGLE RESPONSE.] 1)YES - mine 2)YES - other household member 3)YES - friend or relative [non-household member] 4)NO 5)DON'T KNOW 6)REFUSED | E32: =LEN(D32) -> 265 | F32: هل يمكن أن تعطيني رقم هاتف إضافي يخصك ، أو يخص قريبًا أو صديقًا يمكن الوصول إليك من خلاله؟ [المشغل: استجابة واحدة.] 1) نعم - لي 2) نعم - فرد اخر من أفراد الأسرة 3) نعم - صديق أو أحد الأقارب [ ليس فردا من أفراد الأسرة ] 4) لا 5) لا أعرف 6) رفض الإجابة | G32: =LEN(F32) -> 252 | H32: Single Choice | I32: NA | J32: NA | K32: Form Type - Buttons | L32: 1-3= phone_number_3 4-6 = hh_admin1 | M32: NA | N32: if contact_3 = 1-3, go to phone_number_3 if contact_3 = 4-6, go to hh_admin1 | Q32: =1 -> 1 | T32: yes - panel | X32: 3.163594 | Y32: =IF(X32="","",X32*Q32) -> 3.163594 | Z32: =IF(T32="yes",Y32,"")
B33: phone_number_3 | C33: phone_number_3 | D33: What is the additional phone number? [OPERATOR: RECORD THE NUMBER GIVEN] | E33: =LEN(D33) -> 73 | F33: ما هو رقم الهاتف الإضافي؟ ( المشغل: قم بتسجيل الرقم المعطى لك ) | G33: =LEN(F33) -> 63 | H33: Open Ended | I33: NA | J33: NA | K33: Form Type - TextBox | L33: Any Response = contact_3_name | M33: NA | N33: For any response, go to contact_3_name | Q33: =1 -> 1 | T33: yes - panel | X33: 10.830144 | Y33: =IF(X33="","",X33*Q33) -> 10.830144 | Z33: =IF(T33="yes",Y33,"")
B34: contact_3_name | C34: phone_number_3_name | D34: What is the name of the contact? [OPERATOR: RECORD THE NAME OF THE CONTACT FOR THE PHONE NUMBER.] | E34: =LEN(D34) -> 98 | F34: ما هو اسم صاحب رقم الهاتف الإضافي الذي قمت بمشاركته؟ (المشغل: قم بتسجيل اسم صاحب رقم الهاتف) | G34: =LEN(F34) -> 92 | H34: Open Ended | I34: NA | J34: Send if "contact_3" "Equals" "YES - other household member" OR "contact_3" "Equals" "YES - friend or relative [non-household member]", if not satisfied go to "hh_admin1" | K34: Form Type - TextBox | L34: Any Response = hh_admin1 | M34: NA | N34: Asked if response to contact_3 was "YES - other household member" or "YES - friend or relative [non-household member]". Otherwise, it skips to "hh_admin1". For any response, go to hh_admin1 | Q34: =1 -> 1 | T34: yes - panel | X34: 11.260417 | Y34: =IF(X34="","",X34*Q34) -> 11.260417 | Z34: =IF(T34="yes",Y34,"")
Q35: =1 -> 1 | Y35: =IF(X35="","",X35*Q35) | Z35: =IF(T35="yes",Y35,"")
A36: 3 | B36: hh_admin1 | C36: hh_admin1 | D36: Currently, in which Governorate does your household reside? [OPERATOR: SINGLE SELECTION.] [HINT: HOUSEHOLD CONSISTS OF ALL MEMBERS LIVING TOGETHER, SHARING RESOURCES & EATING FROM THE SAME POT.] 1)ADMIN1 2)DON'T KNOW 3)REFUSED | E36: =LEN(D36) -> 229 | F36: حاليًا ، في أي المحافظة تقيم أسرتك؟ [المشغل: استجابة واحدة.] [ملحوظة: تتكون الأسرة من جميع الأعضاء الذين يعيشون معًا ، ويتشاركون الموارد ويأكلون من نفس القدر.] 1) ADMIN 1 2) لا أعرف 3) رفض الإجابة | G36: =LEN(F36) -> 198 | H36: Single Choice | I36: NA | J36: NA | K36: Form Type - Buttons IsDemographic - ADM1 | L36: 1 = hh_admin2_1 2-3 = Ineligible | M36: NA | N36: The administrative information will be updated by GeoPoll based on the sample design document and the administrative boundaries provided by the dashboard team after the questionnaire validation. | Q36: =1 -> 1 | T36: yes | X36: 13.957259 | Y36: =IF(X36="","",X36*Q36) -> 13.957259 | Z36: =IF(T36="yes",Y36,"") -> 13.957259
A37: =A36+1 -> 4 | B37: hh_admin2_1 | C37: hh_admin2_1 | D37: Currently, in which District does your household reside? [OPERATOR: SINGLE RESPONSE.] 1)ADMIN2 2)DON'T KNOW 3)REFUSED | E37: =LEN(D37) -> 120 | F37: حاليًا ، في أي القضاء تقيم أسرتك؟ [المشغل: استجابة واحدة.] 1) ADMIN 2 2) لا أعرف 3) رفض الإجابة | G37: =LEN(F37) -> 98 | H37: Single Choice | I37: NA | J37: NA | K37: Form Type - Buttons IsDemographic - ADM2 | L37: 1 = hh_agricactivity 2-3 = Ineligible | M37: NA | Q37: =1 -> 1 | T37: yes | X37: 7.954999 | Y37: =IF(X37="","",X37*Q37) -> 7.954999 | Z37: =IF(T37="yes",Y37,"") -> 7.954999
B38: quotareached | C38: quotareached | D38: [OPERATOR: DO NOT READ. ANSWER QUESTION BELOW.] THIS RESPONDENT REPORTED THEY LIVE IN: {ADM1} {ADM2} 1)THE GOAL FOR THIS LOCATION HAS BEEN ACHIEVED - END SURVEY 2)THE GOAL FOR THIS LOCATION IS OPEN - CONTINUE SURVEY | E38: =LEN(D38) -> 218 | F38: [المُشغل: لا تقرأ. أجب على السؤال أدناه.] أبلغ هذا المجيب أنه يعيش في: {ADM1} {ADM2} 1) تم تحقيق الهدف لهذا الموقع - إنه الاستبيان 2) لا يزال يتعين تحقيق الهدف لهذا الموقع - تابع الاستبيان | G38: =LEN(F38) -> 190 | H38: Single Choice | I38: NA | J38: NA | K38: Form Type - Buttons | L38: 1 = End Poll Quota Reached 2 = hh_agricactivity | M38: NA
A39: =#REF!+1 -> #REF! | B39: hh_agricactivity | C39: hh_agricactivity | D39: Has anybody in your household produced crops or livestock for household consumption or for sale in the past 12 months, including household members currently away for transhumance? [OPERATOR: SINGLE RESPONSE. THIS IS THE MAIN SCREENING QUESTION.] [HINT FOR PROBING: Do you cultivate any plants to sale or consume? Do you raise any animals with the intent of selling or consuming them or their products like meat, milk, wool or leather? Is one of your household member currently away with cattle or other animals for transhumance?] 1)Yes - crop production 2)Yes - livestock production 3)Yes - both crop and livestock production 4)No 5)DON'T KNOW 6)REFUSED | E39: =LEN(D39) -> 658 | F39: هل قام أي شخص في أسرتك بإنتاج المحاصيل أو الماشية للاستهلاك المنزلي أو للبيع خلال الاثني عشر شهرًا الماضية ، بما في ذلك أفراد الأسرة الغير موجودين بغرض التنقل الرعوي؟ [المشغل: استجابة واحدة. هذا هو سؤال الفرز الرئيسي.] [ملحوظة للتحقيق: هل قمت بزراعة أي نباتات للبيع أو الاستهلاك ؟ هل قمت بتربية أي حيوانات بنية البيع أو الاستهلاك أو انتاج منتجات مثل اللحوم و الالبان و الصوف و الجلد ؟ هل أي فرد من أفراد أسرتك حاليا بعيدًا عن الأسرة مع الماشية أو حيوانات أخري بغرض التنقل الرعوي ؟] 1) نعم - إنتاج المحاصيل 2) نعم - إنتاج الماشية 3) نعم - كل من إنتاج المحاصيل والماشية 4) لا 5) لا أعرف 6) رفض الإجابة | G39: =LEN(F39) -> 600 | H39: Single Choice | I39: NA | J39: NA | K39: Form Type - Buttons | L39: 1-4 = resp_id 5-6 = Ineligible | M39: NA | N39: if hh_agricactivity = 1-4, go to resp_id. Otherwise, the respondent is ineligible. | Q39: =1 -> 1 | T39: yes | X39: 24.410839 | Y39: =IF(X39="","",X39*Q39) -> 24.410839 | Z39: =IF(T39="yes",Y39,"") -> 24.410839
Q40: =1 -> 1 | Y40: =IF(X40="","",X40*Q40) | Z40: =IF(T40="yes",Y40,"")
A41: B. GENERAL HOUSEHOLD INFORMATION | Y41: =IF(X41="","",X41*Q41) | Z41: =IF(T41="yes",Y41,"")
Q42: =1 -> 1 | Y42: =IF(X42="","",X42*Q42) | Z42: =IF(T42="yes",Y42,"")
A43: =A39+1 -> #REF! | B43: resp_id | C43: resp_id | D43: Are you the head of household? [OPERATOR: SINGLE RESPONSE.] 1)Yes 2)No 3)DON'T KNOW 4)REFUSED | E43: =LEN(D43) -> 97 | F43: هل أنت رب الأسرة ؟ [المشغل: استجابة واحدة.] 1) نعم 2) لا 3) لا أعرف 4) رفض الإجابة | G43: =LEN(F43) -> 84 | H43: Single Choice | I43: NA | J43: NA | K43: Form Type - Buttons | L43: 1 = hh_education 2-4 = hh_gender | M43: NA | N43: if resp_id = 1, go to hh_education. Otherwise, go to hh_gender. | Q43: 1 | T43: yes | X43: 10.5 | Y43: =IF(X43="","",X43*Q43) -> 10.5 | Z43: =IF(T43="yes",Y43,"") -> 10.5
A44: =A43+1 -> #REF! | B44: hh_gender | C44: hh_gender | D44: Is the head of your household male or female? [OPERATOR: SINGLE RESPONSE.] 1)Male 2)Female 3)DON'T KNOW 4)REFUSED | E44: =LEN(D44) -> 116 | F44: هل رب أسرتك ذكر أم أنثى؟ [المشغل: استجابة واحدة.] 1) ذكر 2) أنثى 3) لا أعرف 4) رفض الإجابة | G44: =LEN(F44) -> 92 | H44: Single Choice | I44: NA | J44: NA | K44: Form Type - Buttons | L44: 1-4 = hh_education | M44: NA | N44: if hh_gender = 1-4, go to hh_education. | Q44: =1 -> 1 | T44: yes | X44: 10.504534 | Y44: =IF(X44="","",X44*Q44) -> 10.504534 | Z44: =IF(T44="yes",Y44,"") -> 10.504534
Q45: =1 -> 1 | Y45: =IF(X45="","",X45*Q45) | Z45: =IF(T45="yes",Y45,"")
A46: =A44+1 -> #REF! | B46: hh_education | C46: hh_education | D46: What is the educational level attained by the head of household? [OPERATOR: SINGLE RESPONSE.] 1)None or did not complete primary school 2)Completed primary school 3)Completed secondary school 4)Completed higher education [University / College] degree 5)Religious or informal education only 6)DON'T KNOW 7)REFUSED | E46: =LEN(D46) -> 314 | F46: ما هو المستوى التعليمي الذي وصل إليه رب الأسرة؟ [المشغل: استجابة واحدة.] 1) لا شيء أو لم يكمل المرحلة الابتدائية 2) أكمل المرحلة الابتدائية 3) أكمل المرحلة الثانوية 4) أكمل درجة تعليم عالي [جامعة / كلية] 5) تربية دينية أو غير رسمية فقط 6) لا أعرف 7) رفض الإجابة | G46: =LEN(F46) -> 263 | H46: Single Choice | I46: NA | J46: NA | K46: Form Type - Buttons | L46: 1-7 = hh_wealth | M46: NA | N46: if hh_education = 1-7, go to hh_wealth. | Q46: =1 -> 1 | T46: yes | X46: 12.421899 | Y46: =IF(X46="","",X46*Q46) -> 12.421899 | Z46: =IF(T46="yes",Y46,"") -> 12.421899
Q47: =1 -> 1 | Y47: =IF(X47="","",X47*Q47) | Z47: =IF(T47="yes",Y47,"")
A48: 10 | B48: hh_wealth_toilet | C48: hh_wealth_toilet | D48: Where do household members typically go to use a toilet? [OPERATOR: SINGLE CHOICE.] 1)Flush latrine [toilet with water] 2)Traditional pit latrine [no water] 3)Open pit [hole in the ground for excrement without water, roof or wall] 4)Communal latrine [with or without water] 5)None – bush 6)DON'T KNOW 7)REFUSED | E48: =LEN(D48) -> 312 | F48: أين يذهب أفراد الأسرة عادة لاستخدام المرحاض؟ [المُشغل: استجابة واحدة.] 1) مرحاض دافق/مزود بنظام شطف [مرحاض به ماء] 2) مرحاض الحفرة التقليدي [بدون ماء] 3) حفرة مفتوحة [حفرة في الأرض للفضلات بدون ماء أو سقف أو جدار] 4) مرحاض مشترك/جماعي [بالماء أو بدون الماء] 5) لا شيء - في العراء 6) لا أعرف 7) رفض الإجابة | G48: =LEN(F48) -> 307 | H48: Single Choice | I48: NA | J48: NA | K48: Form Type - Buttons | L48: 1-7, go to hh_size | M48: NA | N48: For any response, go to hh_size | Q48: =1 -> 1 | T48: yes | X48: 12.600021 | Y48: =IF(X48="","",X48*Q48) -> 12.600021 | Z48: =IF(T48="yes",Y48,"") -> 12.600021
Q49: =1 -> 1 | Y49: =IF(X49="","",X49*Q49) | Z49: =IF(T49="yes",Y49,"")
A50: =#REF!+1 -> #REF! | B50: hh_size | C50: hh_size | D50: How many people are part of the household? [OPERATOR: RECORD NUMBER OF MEMBERS IN HOUSEHOLD. ENTER 88 FOR DON'T KNOW & 99 FOR REFUSED.] [HINT: TO BE A PART OF THE SAME HOUSEHOLD, MEMBERS MUST LIVE UNDER THE SAME ROOF, SHARE THE SAME RESOURCES & EAT FROM THE SAME POT.] | E50: =LEN(D50) -> 269 | F50: كم عدد الأشخاص الذين هم جزء من الأسرة؟ [المُشغل: سجل عدد أعضاء الأسرة. أدخل 88 للا أعرف و 99 في حالة الرفض.] [ملحوظة: لكي يكونوا جزءًا من نفس الأسرة، يجب أن يكون جميع الاعضاء يعيشون تحت سقف منزل واحد، و يتشاركون نفس الموارد و يأكلون من نفس القدر] | G50: =LEN(F50) -> 247 | H50: Range | I50: NA | J50: NA | K50: Form Type - TextBox | L50: Any response = hh_age | M50: NA | N50: For any response, go to hh_age | Q50: =1 -> 1 | T50: no | X50: 16.902294 | Y50: =IF(X50="","",X50*Q50) -> 16.902294 | Z50: =IF(T50="yes",Y50,"")
A51: =#REF!+1 -> #REF! | B51: hh_age | C51: hh_age | D51: How old is the head of household? [OPERATOR: SINGLE RESPONSE.] 1)Under 18 2)18 to 40 3)41 to 65 4)Over 65 5)DON'T KNOW 6)REFUSED | E51: =LEN(D51) -> 133 | F51: كم عمر رب الاسرة؟ [المشغل: استجابة واحدة.] 1) أقل من 18 عامًا 2) بين 18 و 40 عامًا 3) بين 41 و 65 عامًا 4) فوق 65 عامًا 5) لا أعرف 6) رفض الإجابة | G51: =LEN(F51) -> 147 | H51: Single Choice | I51: NA | J51: NA | K51: Form Type - Buttons | L51: 1-6 = income_main | M51: NA | N51: For any response, go to income_main | Q51: =1 -> 1 | T51: no | X51: 7.0248413 | Y51: =IF(X51="","",X51*Q51) -> 7.0248413 | Z51: =IF(T51="yes",Y51,"")
A52: C. INCOME SOURCES, LIVELIHOOD AND SHOCKS | Y52: =IF(X52="","",X52*Q52) | Z52: =IF(T52="yes",Y52,"")
Q53: =1 -> 1 | Y53: =IF(X53="","",X53*Q53) | Z53: =IF(T53="yes",Y53,"")
A54: =A51+1 -> #REF! | B54: income_main | C54: income_main | D54: What was your household's main source of income in the past 3 months? [OPERATOR: SINGLE RESPONSE. REFUSED OPTION SHOULD BE AVOIDED AS MUCH AS POSSIBLE.] 1)Production and sale of staple crops 2)Production and sale of vegetables or fruit 3)Production and sale of cashcrops 4)Production and sale of livestock and livestock products 5)Production and sale of honey or bee products 6)Production and sale of fish 7)Collection and sale of forestry or bush products 8)Agricultural trade EXCLUDING producers [formal or informal] 9)Daily wage on farms and other casual employment in agricultural sector 10)Stable employment in agricultural sector 11)Non-agricultural self-employed or liberal profession / doctor / architect / lawyer / including restaurant 12)Off-farm daily wages and other non-agricultural casual employment 13)Stable employment in non-agricultural sector 14)Public employment 15)Income not derived from work / Charity 16)Income not derived from work / Welfare transfer, pension, humanitarian aid 17)Income not derived from work / Remittances 18)Income not derived from work / Income from other rents 19)No income source in the last 3 months and used exclusively savings / debt 20)REFUSED | E54: =LEN(D54) -> 1204 | F54: ما كان مصدر الدخل الرئيسي لأسرتك في الأشهر الثلاثة الماضية؟ [المشغل: استجابة واحدة. يجب تجنب الخيار "رفض الإجابة" قدر الإمكان.] 1) إنتاج وبيع المحاصيل الأساسية 2) إنتاج وبيع الخضار أو الفاكهة 3) إنتاج وبيع المحاصيل النقدية 4) إنتاج وبيع المواشي ومنتجاتها 5) انتاج و بيع العسل أو منتجات النحل 6) إنتاج وبيع الأسماك 7) جمع وبيع منتجات الغابات أو الأحراش 8) التجارة الزراعية الرسمية و غير الرسمية باستثناء المنتجين 9) الأجر اليومي في المزارع وغيرها من العمالة العرضية في قطاع الزراعة 10) العمالة المستقرة في القطاع الزراعي 11) العاملين لحسابهم الخاص غير الزراعيين أو المهنة الحرة / طبيب / مهندس معماري / محامٍ / بما في ذلك مطعم 12) الأجور اليومية خارج المزرعة وغيرها من العمالة العرضية غير الزراعية 13) العمالة المستقرة في القطاع غير الزراعي 14) الوظائف العامة 15) الدخل غير المستمد من العمل / الاعمال الخيرية 16) الدخل غير المستمد من العمل / المدفوعات التحويلية ، المعاش التقاعدي ، المساعدات الإنسانية 17) الدخل غير المستمد من العمل / التحويلات 18) الدخل غير المستمد من العمل / الدخل من الإيجارات الأخرى 19) لم يكن هناك مصدر دخل خلال الأشهر الثلاثة الماضية واستخدمت المدخرات أو الدين حصريًا 20) رفض الإجابة | G54: =LEN(F54) -> 1108 | H54: Single Choice | I54: NA | J54: NA | K54: Form Type - Buttons IsDemographic | L54: 1-3 = income_main_crop_check 4 = income_main_ls_check 5 = income_main_comp 6 = income_main_fish_check 7-18 = income_main_comp 19-20 = shock | M54: NA | N54: if options #1-3 selected go to income_main_crop_check if options #4 selected go to income_main_ls_check if options #6 selected go to income_main_fish_check if options #5, 7-18 selected, go to [income_main_comp OR optional question] if options #19-20 selected, go to shock | Q54: =1 -> 1 | T54: yes | X54: 31.888334 | Y54: =IF(X54="","",X54*Q54) -> 31.888334 | Z54: =IF(T54="yes",Y54,"") -> 31.888334
B55: income_main_crop_check | C55: income_main_crop_check | D55: Are the crops that you sell also produced by you or anyone in your household? [OPERATOR: SINGLE RESPONSE.] 1)YES 2)NO 3)DON'T KNOW 4)REFUSED | E55: =LEN(D55) -> 143 | F55: هل المحاصيل التي تبيعها من إنتاجك أنت أو أي شخص في أسرتك؟ [المشغل: استجابة واحدة.] 1) نعم 2) لا 3) لا أعرف 4) رفض الإجابة | G55: =LEN(F55) -> 123 | H55: Single Choice | I55: NA | J55: NA | K55: Form Type - Buttons | L55: 1-4 = income_main_comp | M55: NA | N55: if income_main_crop_check = 1-4, go to [income_main_comp OR optional question] | Q55: =1 -> 1 | T55: yes | X55: 8 | Y55: =IF(X55="","",X55*Q55) -> 8 | Z55: =IF(T55="yes",Y55,"") -> 8
B56: income_main_ls_check | C56: income_main_ls_check | D56: Are the livestock and livestock products that you sell also produced by you or anyone in your household? [OPERATOR: SINGLE RESPONSE.] 1)YES 2)NO 3)DON'T KNOW 4)REFUSED | E56: =LEN(D56) -> 170 | F56: هل المواشي ومنتجاتها التي تبيعها من إنتاجك أنت أو أي شخص في أسرتك؟ [المشغل: استجابة واحدة.] 1) نعم 2) لا 3) لا أعرف 4) رفض الإجابة | G56: =LEN(F56) -> 132 | H56: Single Choice | I56: NA | J56: NA | K56: Form Type - Buttons | L56: 1-4 = income_main_comp | M56: NA | N56: if income_main_ls_check = 1-4, go to [income_main_comp OR optional question] | Q56: =1 -> 1 | T56: yes | X56: 8 | Y56: =IF(X56="","",X56*Q56) -> 8 | Z56: =IF(T56="yes",Y56,"") -> 8
B57: income_main_fish_check | C57: income_main_fish_check | D57: Are the fish and/or fish products that you sell also captured or harvested by you or anyone in your household? [OPERATOR: SINGLE RESPONSE.] 1)YES 2)NO 3)DON'T KNOW 4)REFUSED | E57: =LEN(D57) -> 176 | F57: هل منتجات الأسماك التي تبيعها من إنتاجك أنت أو أي شخص في أسرتك؟ [المشغل: استجابة واحدة.] 1) نعم 2) لا 3) لا أعرف 4) رفض الإجابة | G57: =LEN(#REF!) -> #REF! | H57: Single Choice | I57: NA | J57: NA | K57: Form Type - Buttons | L57: 1-4 = income_main_comp | M57: NA | N57: if income_main_fish_check = 1-4, go to [income_main_comp OR optional question] | Q57: =1 -> 1 | T57: yes | X57: 8 | Y57: =IF(X57="","",X57*Q57) -> 8 | Z57: =IF(T57="yes",Y57,"") -> 8
A58: 21 | B58: income_main_comp | C58: income_main_comp | D58: Has your household's income from {income_main} changed in the last 3 months compared to the same period of last year? [OPERATOR: SINGLE RESPONSE.] 1)A lot more [increased by more than 50%] 2)Slightly more 3)Same 4)Slightly less 5)A lot less [less than half as much] 6)DON'T KNOW 7)REFUSED | E58: =LEN(D58) -> 290 | F58: هل تغير دخل أسرتك من {income_main} في الأشهر الثلاثة الماضية مقارنة بنفس الفترة من العام الماضي؟ [المشغل: استجابة واحدة.] 1) أكثر بكثير [زاد بنسبة تزيد عن 50٪] 2) أكثر قليلا 3) نفس الشيء 4) أقل قليلاً 5) أقل بكثير [أقل من نصف الكمية] 6) لا أعرف 7) رفض الإجابة | G58: =LEN(F61) -> 1080 | H58: Single Choice | I58: NA | J58: NA | K58: Form Type - Buttons | L58: 1-3 or 6-7= income_sec 4-5= o_income_main_comp_reason | M58: NA | N58: if income_main_comp = 1-7, go to income_sec | Q58: =1 -> 1 | T58: yes | X58: 22.126215 | Y58: =IF(X58="","",X58*Q58) -> 22.126215 | Z58: =IF(T58="yes",Y58,"") -> 22.126215
B60: o_income_main_comp_reason | D60: If the main income source was "Slightly less" or "A lot less", specify the reason. [OPERATOR: RECORD THE RESPONSE GIVEN] | E60: =LEN(D60) -> 121 | F60: إذا كان مصدر الدخل الرئيسي "أقل قليلاً" أو "أقل بكثير" ، حدد السبب [المُشغل: تسجيل الجواب المُعطى] | H60: Open Ended | I60: NA | J60: NA | K60: Form Type - Buttons | L60: Any Response = income_sec | M60: NA | N60: Any Response = income_sec | Q60: =1 -> 1 | Y60: =IF(X60="","",X60*Q60) | Z60: =IF(T60="yes",Y60,"")
A61: =A58+1 -> 22 | B61: income_sec | C61: income_sec | D61: What was your household's second most important source of income in the past 3 months? [OPERATOR: SINGLE RESPONSE. DON'T KNOW AND REFUSED OPTIONS SHOULD BE AVOIDED AS MUCH AS POSSIBLE.] 1)Production and sale of staple crops 2)Production and sale of vegetables or fruit 3)Production and sale of cashcrops 4)Production and sale of livestock and livestock products 5)Production and sale of honey or bee products 6)Production and sale of fish 7)Collection and sale of forestry or bush products 8)Agricultural trade EXCLUDING producers [formal or informal] 9)Daily wage on farms and other casual employment in agricultural sector 10)Stable employment in agricultural sector 11)Non-agricultural self-employed or liberal profession / doctor / architect / lawyer / including restaurant 12)Off-farm daily wages and other non-agricultural casual employment 13)Stable employment in non-agricultural sector 14)Public employment 15)Income not derived from work / Charity 16)Income not derived from work / Welfare transfer, pension, humanitarian aid 17)Income not derived from work / Remittances 18)Income not derived from work / Income from other rents 19)No second most important source of income 20)DON'T KNOW 21)REFUSED | E61: =LEN(D61) -> 1218 | F61: ما هو ثاني أهم مصدر دخل لأسرتك فى الثلاثة أشهر الماضية ؟ [المشغل: استجابة واحدة. يجب تجنب خيارات الإجابة "لا أعرف" و "رفض الإجابة" قدر الإمكان.] 1) إنتاج وبيع المحاصيل الأساسية 2) إنتاج وبيع الخضار أو الفاكهة 3) إنتاج وبيع المحاصيل النقدية 4) إنتاج وبيع المواشي ومنتجاتها 5) انتاج و بيع العسل أو منتجات النحل 6) إنتاج وبيع الأسماك 7) جمع وبيع منتجات الغابات أو الأحراش 8) التجارة الزراعية الرسمية و غير الرسمية باستثناء المنتجين 9) الأجر اليومي في المزارع وغيرها من العمالة العرضية في قطاع الزراعة 10) العمالة المستقرة في القطاع الزراعي 11) العاملين لحسابهم الخاص غير الزراعيين أو المهنة الحرة / طبيب / مهندس معماري / محامٍ / بما في ذلك مطعم 12) الأجور اليومية خارج المزرعة وغيرها من العمالة العرضية غير الزراعية 13) العمالة المستقرة في القطاع غير الزراعي 14) الوظائف العامة 15) الدخل غير المستمد من العمل / الاعمال الخيرية 16) الدخل غير المستمد من العمل / المدفوعات التحويلية ، المعاش التقاعدي ، المساعدات الإنسانية 17) الدخل غير المستمد من العمل / التحويلات 18) الدخل غير المستمد من العمل / الدخل من الإيجارات الأخرى 19) لم يكن هناك مصدر دخل ثانٍ 20) لا أعرف 21) رفض الإجابة | G61: =LEN(#REF!) -> #REF! | H61: Single Choice | I61: NA | J61: NA | K61: Form Type - Buttons exclude selected "income_main" IsDemographic | L61: 1-3 = income_sec_crop_check 4 = income_sec_ls_check 5 = income_sec_comp 6 = income_sec_fish_check 7-18 = income_sec_comp 19-21 = shock | M61: NA | N61: if options #1-3 selected, go to income_sec_crop_check if options #4 selected, go to income_sec_ls_check if options #6 selected, go to income_sec_fish_check if options #5, 7-18 selected, go to [income_sec_comp OR optional question] if options #19-21 selected, go to shock | Q61: =1 -> 1 | T61: yes | X61: 18.710653 | Y61: =IF(X61="","",X61*Q61) -> 18.710653 | Z61: =IF(T61="yes",Y61,"") -> 18.710653
B62: income_sec_crop_check | C62: income_sec_crop_check | D62: Are the crops that you sell also produced by you or anyone in your household? [OPERATOR: SINGLE RESPONSE.] 1)YES 2)NO 3)DON'T KNOW 4)REFUSED | E62: =LEN(D62) -> 143 | F62: هل المحاصيل التي تبيعها من إنتاجك أنت أو أي شخص في أسرتك؟ [المشغل: استجابة واحدة.] 1) نعم 2) لا 3) لا أعرف 4) رفض الإجابة | G62: =LEN(#REF!) -> #REF! | H62: Single Choice | I62: NA | J62: NA | K62: Form Type - Buttons | L62: 1-4 = income_sec_comp | M62: NA | N62: if income_sec_crop_check = 1-4, go to [income_sec_comp OR optional question] | Q62: =1 -> 1 | T62: yes | X62: 8 | Y62: =IF(X62="","",X62*Q62) -> 8 | Z62: =IF(T62="yes",Y62,"") -> 8
B63: income_sec_ls_check | C63: income_sec_ls_check | D63: Are the livestock and livestock products that you sell also produced by you or anyone in your household? [OPERATOR: SINGLE RESPONSE.] 1)YES 2)NO 3)DON'T KNOW 4)REFUSED | E63: =LEN(D63) -> 170 | F63: هل المواشي ومنتجاتها التي تبيعها من إنتاجك أنت أو أي شخص في أسرتك؟ [المشغل: استجابة واحدة.] 1) نعم 2) لا 3) لا أعرف 4) رفض الإجابة | G63: =LEN(#REF!) -> #REF! | H63: Single Choice | I63: NA | J63: NA | K63: Form Type - Buttons | L63: 1-4 = income_sec_comp | M63: NA | N63: if income_sec_ls_check = 1-4, go to [income_sec_comp OR optional question] | Q63: =1 -> 1 | T63: yes | X63: 8 | Y63: =IF(X63="","",X63*Q63) -> 8 | Z63: =IF(T63="yes",Y63,"") -> 8
B64: income_sec_fish_check | C64: income_sec_fish_check | D64: Are the fish and/or fish products that you sell also captured or harvested by you or anyone in your household? [OPERATOR: SINGLE RESPONSE.] 1)YES 2)NO 3)DON'T KNOW 4)REFUSED | E64: =LEN(D64) -> 176 | F64: هل منتجات الأسماك التي تبيعها من إنتاجك أنت أو أي شخص في أسرتك؟ [المشغل: استجابة واحدة.] 1) نعم 2) لا 3) لا أعرف 4) رفض الإجابة | G64: =LEN(#REF!) -> #REF! | H64: Single Choice | I64: NA | J64: NA | K64: Form Type - Buttons | L64: 1-4 = income_sec_comp | M64: NA | N64: if income_sec_fish_check = 1-4, go to [income_sec_comp OR optional question] | Q64: =1 -> 1 | T64: yes | X64: 8 | Y64: =IF(X64="","",X64*Q64) -> 8 | Z64: =IF(T64="yes",Y64,"") -> 8
A65: =#REF!+1 -> #REF! | B65: income_sec_comp | C65: income_sec_comp | D65: Has your household's income from {income_sec} changed in the last 3 months compared to the same period of last year? [OPERATOR: SINGLE RESPONSE.] 1)A lot more [increased by more than 50%] 2)Slightly more 3)Same 4)Slightly less 5)A lot less [less than half as much] 6)DON'T KNOW 7)REFUSED | E65: =LEN(D65) -> 290 | F65: هل تغير دخل أسرتك من {income_sec} في الأشهر الثلاثة الماضية مقارنة بنفس الفترة من العام الماضي؟ [المشغل: استجابة واحدة.] 1) أكثر بكثير [زاد بنسبة تزيد عن 50٪] 2) أكثر قليلا 3) نفس الشيء 4) أقل قليلاً 5) أقل بكثير [أقل من نصف الكمية] 6) لا أعرف 7) رفض الإجابة | G65: =LEN(F69) -> 132 | H65: Single Choice | I65: NA | J65: NA | K65: Form Type - Buttons | L65: 1-7= income_third | M65: NA | N65: if income_sec_comp = 1-7, go to income_third | Q65: =1 -> 1 | T65: yes | X65: 17.261402 | Y65: =IF(X65="","",X65*Q65) -> 17.261402 | Z65: =IF(T65="yes",Y65,"") -> 17.261402
Q66: =1 -> 1 | Y66: =IF(X66="","",X66*Q66) | Z66: =IF(T66="yes",Y66,"")
A67: =A65+1 -> #REF! | B67: income_third | C67: income_third | D67: What was your household's third most important source of income in the past 3 months? [OPERATOR: SINGLE RESPONSE. DON'T KNOW AND REFUSED OPTIONS SHOULD BE AVOIDED AS MUCH AS POSSIBLE.] 1)Production and sale of staple crops 2)Production and sale of vegetables or fruit 3)Production and sale of cashcrops 4)Production and sale of livestock and livestock products 5)Production and sale of honey or bee products 6)Production and sale of fish 7)Collection and sale of forestry or bush products 8)Agricultural trade EXCLUDING producers [formal and informal] 9)Daily wage on farms and other casual employment in agricultural sector 10)Stable employment in agricultural sector 11)Non-agricultural self-employed or liberal profession / doctor / architect / lawyer / including restaurant 12)Off-farm daily wages and other non-agricultural casual employment 13)Stable employment in non-agricultural sector 14)Public employment 15)Income not derived from work / Charity 16)Income not derived from work / Welfare transfer, pension, humanitarian aid 17)Income not derived from work / Remittances 18)Income not derived from work / Income from other rents 19)No third most important source of income 20)DON'T KNOW 21)REFUSED | E67: =LEN(D67) -> 1217 | F67: ما هو ثالث أهم مصدر دخل لأسرتك فى الثلاثة أشهر الماضية ؟ [المشغل: استجابة واحدة. يجب تجنب خيارات الإجابة "لا أعرف" و "رفض الإجابة" قدر الإمكان.] 1) إنتاج وبيع المحاصيل الأساسية 2) إنتاج وبيع الخضار أو الفاكهة 3) إنتاج وبيع المحاصيل النقدية 4) إنتاج وبيع المواشي ومنتجاتها 5) انتاج و بيع العسل أو منتجات النحل 6) إنتاج وبيع الأسماك 7) جمع وبيع منتجات الغابات أو الأحراش 8) التجارة الزراعية الرسمية و غير الرسمية باستثناء المنتجين 9) الأجر اليومي في المزارع وغيرها من العمالة العرضية في قطاع الزراعة 10) العمالة المستقرة في القطاع الزراعي 11) العاملين لحسابهم الخاص غير الزراعيين أو المهنة الحرة / طبيب / مهندس معماري / محامٍ / بما في ذلك مطعم 12) الأجور اليومية خارج المزرعة وغيرها من العمالة العرضية غير الزراعية 13) العمالة المستقرة في القطاع غير الزراعي 14) الوظائف العامة 15) الدخل غير المستمد من العمل / الاعمال الخيرية 16) الدخل غير المستمد من العمل / المدفوعات التحويلية ، المعاش التقاعدي ، المساعدات الإنسانية 17) الدخل غير المستمد من العمل / التحويلات 18) الدخل غير المستمد من العمل / الدخل من الإيجارات الأخرى 19) لم يكن هناك مصدر دخل ثالث 20) لا أعرف 21) رفض الإجابة | G67: =LEN(#REF!) -> #REF! | H67: Single Choice | I67: NA | J67: NA | K67: Form Type - Buttons exclude selected "income_main" exclude selected "income_sec" IsDemographic | L67: 1-3 = income_third_crop_check 4 = income_third_ls_check 5 = income_third_comp 6 = income_third_fish_check 7-18 = income_third_comp 19-21 = shock | M67: NA | N67: if options #1-3 selected, go to income_third_crop_check if options #4 selected, go to income_third_ls_check if option #6 selected, go to income_third_fish_check if options #5, 7-18 selected, go to [income_third_comp OR optional question] if options #19-21 selected, go to shock | Q67: =1 -> 1 | T67: yes | X67: 14.475392 | Y67: =IF(X67="","",X67*Q67) -> 14.475392 | Z67: =IF(T67="yes",Y67,"") -> 14.475392
B68: income_third_crop_check | C68: income_third_crop_check | D68: Are the crops that you sell also produced by you or anyone in your household? [OPERATOR: SINGLE RESPONSE.] 1)YES 2)NO 3)DON'T KNOW 4)REFUSED | E68: =LEN(D68) -> 143 | F68: هل المحاصيل التي تبيعها من إنتاجك أنت أو أي شخص في أسرتك؟ [المشغل: استجابة واحدة.] 1) نعم 2) لا 3) لا أعرف 4) رفض الإجابة | G68: =LEN(#REF!) -> #REF! | H68: Single Choice | I68: NA | J68: NA | K68: Form Type - Buttons | L68: 1-4 = income_third_comp | M68: NA | N68: if income_third_crop_check = 1-4, go to [income_third_comp OR optional question] | Q68: =1 -> 1 | T68: yes | X68: 8 | Y68: =IF(X68="","",X68*Q68) -> 8 | Z68: =IF(T68="yes",Y68,"") -> 8
B69: income_third_ls_check | C69: income_third_ls_check | D69: Are the livestock and livestock products that you sell also produced by you or anyone in your household? [OPERATOR: SINGLE RESPONSE.] 1)YES 2)NO 3)DON'T KNOW 4)REFUSED | E69: =LEN(D69) -> 170 | F69: هل المواشي ومنتجاتها التي تبيعها من إنتاجك أنت أو أي شخص في أسرتك؟ [المشغل: استجابة واحدة.] 1) نعم 2) لا 3) لا أعرف 4) رفض الإجابة | G69: =LEN(#REF!) -> #REF! | H69: Single Choice | I69: NA | J69: NA | K69: Form Type - Buttons | L69: 1-4 = income_third_comp | M69: NA | N69: if income_third_ls_check = 1-4, go to [income_third_comp OR optional question] | Q69: =1 -> 1 | T69: yes | X69: 8 | Y69: =IF(X69="","",X69*Q69) -> 8 | Z69: =IF(T69="yes",Y69,"") -> 8
B70: income_third_fish_check | C70: income_third_fish_check | D70: Are the fish and/or fish products that you sell also captured or harvested by you or anyone in your household? [OPERATOR: SINGLE RESPONSE.] 1)YES 2)NO 3)DON'T KNOW 4)REFUSED | E70: =LEN(D70) -> 176 | F70: هل منتجات الأسماك التي تبيعها من إنتاجك أنت أو أي شخص في أسرتك؟ [المشغل: استجابة واحدة.] 1) نعم 2) لا 3) لا أعرف 4) رفض الإجابة | G70: =LEN(#REF!) -> #REF! | H70: Single Choice | I70: NA | J70: NA | K70: Form Type - Buttons | L70: 1-4 = income_third_comp | M70: NA | N70: if income_third_fish_check = 1-4, go to [income_third_comp OR optional question] | Q70: =1 -> 1 | T70: yes | X70: 8 | Y70: =IF(X70="","",X70*Q70) -> 8 | Z70: =IF(T70="yes",Y70,"") -> 8
A71: =#REF!+1 -> #REF! | B71: income_third_comp | C71: income_third_comp | D71: Has your household's income from {income_third} changed in the last 3 months compared to the same period of last year? [OPERATOR: SINGLE RESPONSE.] 1)A lot more [increased by more than 50%] 2)Slightly more 3)Same 4)Slightly less 5)A lot less [less than half as much] 6)DON'T KNOW 7)REFUSED | E71: =LEN(D71) -> 291 | F71: هل تغير دخل أسرتك من {income_third} في الأشهر الثلاثة الماضية مقارنة بنفس الفترة من العام الماضي؟ [المشغل: استجابة واحدة.] 1) أكثر بكثير [زاد بنسبة تزيد عن 50٪] 2) أكثر قليلا 3) نفس الشيء 4) أقل قليلاً 5) أقل بكثير [أقل من نصف الكمية] 6) لا أعرف 7) رفض الإجابة | G71: =LEN(#REF!) -> #REF! | H71: Single Choice | I71: NA | J71: NA | K71: Form Type - Buttons | L71: 1-7= shock | M71: NA | N71: if income_third_comp = 1-7, go to shock | Q71: =1 -> 1 | T71: yes | X71: 15.876503 | Y71: =IF(X71="","",X71*Q71) -> 15.876503 | Z71: =IF(T71="yes",Y71,"") -> 15.876503
A72: =#REF!+1 -> #REF! | B72: shock | C72: shock_ 1) shock_noshock 2) shock_sicknessordeathofhh 3) shock_lostemplorwork 4) shock_otherintrahhshock 5) shock_higherfoodprices 6) shock_higherfuelprices 7) shock_mvtrestrict 8) shock_othereconomicshock 9) shock_pestoutbreak 10) shock_plantdisease 11) shock_animaldisease 12) shock_napasture 13) shock_othercropandlivests 14) shock_coldtemporhail 15) shock_flood 16) shock_hurricane 17) shock_drought 18) shock_earthquake 19) shock_landslides 20) shock_firenatural 21) shock_othernathazard 22) shock_violenceinsecconf 23) shock_theftofprodassets 24) shock_firemanmade 25) shock_othermanmadehazard 26) shock_dk 27) shock_ref | D72: Has your household or community faced any particular disaster or crisis affecting your household's ability to raise an income and/or to produce food for self consumption in the last 3 months, and if so, which one[s]? [OPERATOR: SELECT RELEVANT SHOCKS EXPERIENCED BY THE HOUSEHOLD. MULTIPLE RESPONSES POSSIBLE. REFER TO ECONOMIC SHOCKS, CROP AND LIVESTOCK SHOCKS, INTRA-HOUSEHOLD SHOCK, NATURAL HAZARDS AND HUMAN-INDUCED HAZARDS.] 1)No shock 2)Sickness or accident or death of household member[s] [sickness of breadwinner / unusually high medical expenditure / funeral expenses / death of breadwinner] 3)Lost employment or working opportunities [not due to illness/accident] 4)Other intra-household shock 5)Unusually high food prices 6)Unusually high fuel prices or transport prices 7)Population movement restrictions [e.g. due to epidemic or infrastructure damage] 8)Other economic shock 9)Pest outbreak 10)Plant disease 11)Animal disease [affecting many animals] or death 12)Lack of physical access to pasture 13)Other crop and livestock shock 14)Cold temperatures or hail 15)Flood / riverbank erosion 16)Hurricane / cyclone / tornado 17)Drought / heat stress 18)Earthquake 19)Landslides 20)Fire from natural disaster 21)Other natural hazard 22)Violence and insecurity / conflict 23)Theft of production assets [land / livestock / tools / etc] 24)Fire from human-induced disaster 25)Other human-induced hazard 26)DON'T KNOW 27)REFUSED | E72: =LEN(D72) -> 1440 | F72: هل واجهت أسرتك أو هل واجه مجتمعك أي كارثة أو أزمة معينة أثرت على قدرة أسرتك على إدرار الدخل و / أو إنتاج الغذاء للاستهلاك الذاتي في الأشهر الثلاثة الماضية ، وإذا كان الأمر كذلك ، فما كانت؟ [المُشغل: حدد الصدمات ذات الصلة التي اختبرتها الأسرة. استجابات متعددة ممكنة. راجع الصدمات الاقتصادية والصدمات التي تصيب المحصول والمواشي و داخل الأسرة والمخاطر الطبيعية والأخطار التي يسببها الإنسان.] 1) لا صدمة 2) مرض أو حادث أو وفاة أحد أفراد الأسرة [مرض العائل / النفقات الطبية المرتفعة بشكل غير عادي / نفقات الجنازة / وفاة العائل] 3) فرص العمل أو العمل المفقودة [ليس بسبب مرض / حادث] 4) صدمة أخرى داخل الأسرة 5) أسعار المواد الغذائية أعلى بكثير من المعتاد 6) أسعار الوقود أو أسعار النقل أعلى بكثير من المعتاد 7) القيود المفروضة على حركة السكان [على سبيل المثال بسبب الوباء أو تلف البنية التحتية] 8) صدمة اقتصادية أخرى 9) تفشي الآفات 10) أمراض نباتية 11) أمراض حيوانية تصيب العديد من الحيوانات أو تتسبب بنفقها 12) عدم إمكانية الوصول للمراعي 13) صدمة أخرى للمحاصيل والماشية 14) درجات الحرارة الباردة أو البرد 15) الفيضانات / تآكل ضفاف الأنهار 16) إعصار 17) الجفاف / الإجهاد الحراري 18) زلزال 19) الانهيارات الارضية 20) حريق مسبب من كارثة طبيعية 21) مخاطر طبيعية أخرى 22) العنف وانعدام الأمن / النزاع 23) سرقة أصول الإنتاج [الأرض / الماشية / الأدوات / إلخ] 24) حريق مسبب من كارثة من صنع الإنسان 25) مخاطر أخرى من صنع الإنسان 26) لا أعرف 27) رفض الإجابة | G72: =LEN(#REF!) -> #REF! | H72: Select All That Apply | I72: NA | J72: NA | K72: Form Type - Checklist 1,26,27 = IsNone | L72: 1-27 = crp_intro | M72: 1)shock_noshock 2)shock_sicknessordeathofhh 3)shock_lostemplorwork 4)shock_otherintrahhshock 5)shock_higherfoodprices 6)shock_higherfuelprices 7)shock_mvtrestrict 8)shock_othereconomicshock 9)shock_pestoutbreak 10)shock_plantdisease 11)shock_animaldisease 12)shock_napasture 13)shock_othercropandlivests 14)shock_coldtemporhail 15)shock_flood 16)shock_hurricane 17)shock_drought 18)shock_earthquake 19)shock_landslides 20)shock_firenatural 21)shock_othernathazard 22)shock_violenceinsecconf 23)shock_theftofprodassets 24)shock_firemanmade 25)shock_othermanmadehazard 26)shock_dk 27)shock_ref | N72: if shock = 1-27, go to [crp_intro or optional question] | Q72: =1 -> 1 | T72: yes | X72: 37.85363 | Y72: =IF(X72="","",X72*Q72) -> 37.85363 | Z72: =IF(T72="yes",Y72,"") -> 37.85363
A73: D. CROP PRODUCTION | Y73: =IF(X73="","",X73*Q73) | Z73: =IF(T73="yes",Y73,"")
A74: =#REF!+1 -> #REF! | B74: crp_intro | C74: crp_intro | D74: We will now ask you some questions about crop production which apply to you and anyone in your household that is involved in crop production or sales. All questions refer to the crops grown during Harvest season. 1)CONTINUE | E74: =LEN(D74) -> 224 | F74: سنطرح عليك الآن بعض الأسئلة حول إنتاج المحاصيل التي تنطبق عليك وعلى أي شخص في أسرتك يشارك في إنتاج المحاصيل أو بيعها. تشير جميع الأسئلة إلى المحاصيل المزروعة خلال موسم الحصاد. 1) تابع | G74: =LEN(F74) -> 185 | H74: Single Choice | I74: NA | J74: Send if "hh_agricactivity" "Equals" "Yes - crop production" Or "hh_agricactivity" "Equals" "Yes - both crop and livestock production" Or "income_main_crop_check" "Equals" "YES" Or "income_sec_crop_check" "Equals" "YES" Or "income_third_crop_check" "Equals" "YES", if not satisfied go to "crp_salesmain" | K74: Form Type - Buttons | L74: 1 = crp_landsize_num | M74: NA | N74: If hh_agricactivity = "Yes - crop production" or "Yes - both crop and livestock production" or if they reported production and sales of crops in one of the three main income sources and confirmed that they are involved in production, then this section will be asked to respondents. Otherwise, skip to crp_salesmain. Next question is crp_landsize_num | Q74: ='Additional information'!$D$17 -> 0.81 | T74: yes | X74: 7.3040729 | Y74: =IF(X74="","",X74*Q74) -> 5.916299 | Z74: =IF(T74="yes",Y74,"") -> 5.916299
Q75: ='Additional information'!$D$17 -> 0.81 | Y75: =IF(X75="","",X75*Q75) | Z75: =IF(T75="yes",Y75,"")
B76: crp_landsize_num | C76: crp_landsize_num | D76: What is the total size of the land you can cultivate? [OPERATOR: RECORD THE TOTAL LAND SIZE PROVIDED BY THE RESPONDENT. WRITE 8888888 FOR DON'T KNOW AND 9999999 FOR REFUSED. MEASUREMENT UNIT WILL BE SPECIFIED IN THE FOLLOWING QUESTION.] | E76: =LEN(D76) -> 237 | F76: ما هو الحجم الإجمالي للأرض التي يمكنك زراعتها؟ [المُشغل: سجل إجمالي حجم الأرض الذي ذكره المجيب. اكتب 8888888 للا أعرف و 9999999 في حالة الرفض. سيتم تحديد وحدة القياس في السؤال التالي.] | G76: =LEN(F76) -> 185 | H76: Range | I76: NA | J76: NA | K76: Form Type - TextBox | L76: 0-1000000 = crp_landsize_unit 8888888-8888888 = crp_main 9999999-9999999 = crp_main | M76: NA | N76: For any response, go to crp_landsize_unit. Range is between 0 and 1000000. For "Don't know" and "Refused", go to crp_main. | Q76: ='Additional information'!$D$17 -> 0.81 | T76: yes | X76: 23.939905 | Y76: =IF(X76="","",X76*Q76) -> 19.391323 | Z76: =IF(T76="yes",Y76,"") -> 19.391323
B77: crp_landsize_unit | C77: crp_landsize_unit | D77: Unit of measurement for land size: [OPERATOR: DO NOT READ. SINGLE RESPONSE.] 1)Acres 2)Hectares 3)Square meters 4)Square feet 5)Donum | E77: =LEN(D77) -> 138 | F77: وحدة قياس مساحة الارض: [المُشغل: لا تقرأ. استجابة واحدة.] 1) فدان 2) هكتار 3) متر مربع 4) قدم مربع 5) دونم | G77: =LEN(F77) -> 108 | H77: Single Choice | I77: NA | J77: NA | K77: Form Type - Buttons | L77: 1-5 = crp_main | M77: NA | N77: if crp_landsize_unit = 1-5, go to crp_main | P77: 5= Donum | Q77: ='Additional information'!$D$17 -> 0.81 | T77: yes | X77: 2.2494626 | Y77: =IF(X77="","",X77*Q77) -> 1.8220647 | Z77: =IF(T77="yes",Y77,"") -> 1.8220647
A78: =A74+1 -> #REF! | B78: crp_main | C78: crp_main | D78: What has been the main crop that your household has grown for food and income generation in Harvest season, if any? [OPERATOR: SINGLE RESPONSE. "NO CROP PRODUCTION" IS IN LAST OPTIONS AT THE END.] 1)Wheat 2)Maize 3)Barley 4)Potatoe 5)Chickpeas 6)Tomatoes 7)Cucumber 8)Eggplant/aubergine 9)Onions 10)Water Melon 11)Dates 12)Grapes 13)Olives 14)Melon [Cantaloupe] 15)Rice 16)Millet 17)Sorghum 18)Other Cereal 19)Cassava 20)Sweet Potatoes 21)Yams 22)Carrots 23)Cocoyam 24)Other tubers 25)Beans 26)Lentils 27)Peas 28)Soybeans 29)Fava beans 30)Broad beans 31)Other pulses 32)Cabbage 33)Lettuce 34)Spinach-Amaranth 35)Cassava leaves 36)Potatoe leaves 37)Moringa 38)Sorrel Hibiscus / Rosselle 39)Green salad herbs [thyme, parsley, mint, rocca, other] 40)Cauliflower 41)Other leafy vegetables 42)Pumpkin 43)Zucchini 44)Okra 45)Bell pepper 46)Haricot 47)Green peas 48)Fava beans green 49)Other non leafy vegs 50)Orange 51)Lemon 52)Grapefruit 53)Mandarins/clementines 54)Other citrus fruit 55)Sweet Banana 56)Plantains 57)Papaya 58)Mango 59)Guava 60)Pineapple 61)Avocado 62)Figs 63)Apple 64)Apricot 65)Cherries 66)Peach/nectarine 67)Strawberries 68)Other fruit 69)Coconuts 70)Groundnut/peanut 71)Cashew Nut 72)Kola Nut 73)Sesame 74)Bambara nut 75)Almond 76)Walnut 77)Other nuts 78)Cocoa 79)Coffee 80)Tea 81)Sugarcane 82)Sunflower 83)Other food cash crop 84)Cotton 85)Rubber 86)Jute 87)Fodder 88)Tobacco 89)Qat 90)Other non-food cash crop | E78: =LEN(D78) -> 1432 | F78: ما هو المحصول الرئيسي الذي تزرعه أسرتك من أجل الغذاء وتوليد الدخل في موسم الحصاد ، إن وجد؟ [المشغل: استجابة واحدة. 'لا إنتاج للمحصول' في آخر الخيارات في النهاية.] 1)القمح 2)الذرة 3)الشعير 4)البطاطا 5)الحمص 6)الطماطم 7)الخيار 8)الباذنجان 9)بصل 10)البطيخ الأحمر 11)التمر 12)العنب 13)الزيتون 14)الشمام 15)الرز 16)الدخن 17)الذرة الرفيعة 18)الحبوب الأخرى 19)الكسافا 20)البطاطا الحلوة 21)اليام 22)الجزر 23)القلقاس 24)الدرنات الأخرى 25)الفاصوليا 26)العدس 27)البازيلاء 28)فول الصويا 29)الفول 30)الفاصوليا العريضة 31)البقول الاخرى 32)الملفوف 33)الخس 34)السبانخ - القطيفة 35)أوراق الكسافا 36)أوراق البطاطا 37)المورينجا 38)الكركديه 39)أعشاب السلطة الخضراء [زعتر ، بقدونس ، نعناع ، جرجير ، أنواع أخرى] 40)القرنبيط 41)الخضار الورقية الأخرى 42)اليقطين 43)الكوسة 44)البامية 45)الفلفل حلو 46)اللوبياء 47)البازلاء الخضراء 48)الفول الأخضر 49)الخضار غير الورقية الأخرى 50)البرتقال 51)الليمون 52)الجريب فروت 53)اليوسفي / الكليمنتين 54)الحمضيات الأخرى 55)الموز 56)موز الجنة 57)البابايا 58)المانجو 59)الجوافة 60)الأناناس 61)الأفوكادو 62)التين 63)التفاح 64)المشمش 65)الكرز 66)الدراق / النكتارين 67)الفراولة 68)الفواكه الأخرى 69)جوز الهند 70)الفول السوداني 71)الكاجو 72)جوز الكولا 73)السمسم 74)جوز البامبارا 75)اللوز 76)الجوز 77)المكسرات الأخرى 78)الكاكاو 79)القهوة 80)الشاي 81)قصب السكر 82)دوار الشمس 83)المحاصيل الغذائية النقدية الأخرى 84)القطن 85)المطاط 86)الجوت 87)العلف 88)التبغ 89)القات 90) المحاصيل النقدية غير الغذائية الأخرى | G78: =LEN(F78) -> 1417 | H78: Single Choice | I78: NA | J78: NA | K78: Form Type - Dropdown IsDemographic | L78: 1-90 = crp_irrig_source 91 = crp_main_check 92-93 = crp_salesmain | M78: $CROP CODES$ | N78: if crp_main = any type of crop, go to crp_irrig_source; if crp_main = "No crop production", go to crp_main_check if crp_main = "Don't know" or "Refused", go to crp_salesmain | Q78: ='Additional information'!$D$17 -> 0.81 | T78: yes | X78: 23.440117 | Y78: =IF(X78="","",X78*Q78) -> 18.986495 | Z78: =IF(T78="yes",Y78,"") -> 18.986495
B79: crp_main_check | C79: crp_main_check | D79: Why did you not produce any crops in Harvest season? [OPERATOR: SINGLE RESPONSE.] 1)Don’t usually produce during this season 2)Wasn't able to produce [e.g. due to difficulties] | E79: =LEN(D79) -> 179 | F79: لماذا لم تنتج أي محاصيل في موسم الحصاد؟ [المشغل: استجابة واحدة.] 1) لا أنتج عادة محاصيل خلال هذا الموسم 2) لم أتمكن من إنتاج المحاصيل (على سبيل المثال بسبب الصعوبات) | G79: =LEN(F79) -> 167 | H79: Single Choice | I79: NA | J79: NA | K79: Form Type - Buttons | L79: 1 = crp_salesmain 2 = crp_proddif | M79: NA | N79: if crp_main_check = 1, go to crp_salesmain if crp_main_check = 2, go to crp_proddif | Q79: ='Additional information'!$D$17 -> 0.81 | T79: yes | X79: 7.7659574 | Y79: =IF(X79="","",X79*Q79) -> 6.2904255 | Z79: =IF(T79="yes",Y79,"") -> 6.2904255
Q80: ='Additional information'!$D$17 -> 0.81 | Y80: =IF(X80="","",X80*Q80) | Z80: =IF(T80="yes",Y80,"")
A81: =A78+1 -> #REF! | B81: crp_irrig_source | C81: crp_irrig_source | D81: Where do you normally and mainly obtain water for the production of {crp_main}? [OPERATOR: SINGLE RESPONSE.] 1)Rainfed 2)Groundwater 3)Natural surface water [river / lake / stream / pond / etc.] 4)Constructed water point [canal / dam / etc.] 5)Public water supply system [e.g. tap water] 6)Other [specify] 7)DON'T KNOW 8)REFUSED | E81: =LEN(D81) -> 331 | F81: كيف تحصل عادة على الماء لري {crp_main} بشكل رئيسي؟ [المشغل: استجابة واحدة.] 1) بعلي (لا يوجد نظام ري) 2) مياه جوفية 3) مياه سطحية طبيعية ( نهر / بحيرة / بركة مياه / إلخ ) 4) نقطة مياه منشأة ( قناة / سد / إلخ) 5) نظام تزويد مياه عام ( ماء الصنبور علي سبيل المثال ) 6) آخر [حدد] 7) لا أعرف 8) رفض الإجابة | G81: =LEN(F81) -> 306 | H81: Open Ended - Single Choice | I81: NA | J81: NA | K81: Form Type - RadioList | L81: 1-8 = crp_seed_supply | M81: NA | N81: if crp_irrig_source = 1-8, go to [crp_area_change or optional question] | Q81: ='Additional information'!$D$17 -> 0.81 | T81: yes | X81: 16.481756 | Y81: =IF(X81="","",X81*Q81) -> 13.350223 | Z81: =IF(T81="yes",Y81,"") -> 13.350223
Q82: ='Additional information'!$D$17 -> 0.81 | Y82: =IF(X82="","",X82*Q82) | Z82: =IF(T82="yes",Y82,"")
A83: =A81+1 -> #REF! | B83: crp_seed_supply | C83: crp_seed_supply 1) crp_seed_ownprod 2) crp_seed_market 3) crp_seed_company 4) crp_seed_ngo 5) crp_seed_organized_community 6) crp_seed_gov 7) crp_seed_relatives_friends 8) crp_seed_other 9) crp_seed_dk 10) crp_seed_ref | D83: Who do you normally procure your seeds from? [OPERATOR: MULTIPLE RESPONSES POSSIBLE.] 1)Own production 2)Local market or agro-input shop/dealer 3)Private seed company 4)NGOs 5)Community seed banks / farmer networks / farmers' association / etc. 6)Government [e.g. MoA] 7)Relatives or friends 8)Other 9)DON'T KNOW 10)REFUSED | E83: =LEN(D83) -> 326 | F83: من أين تحصل عادة على البذور؟ [المُشغل: احتمال وجود عدة استجابات.] 1) الإنتاج الخاص 2) اشتريها من السوق أو متجر المدخلات الزراعية 3) اشتريها من شركة بذور خاصة 4) المنظمات الغير حكومية 5) بنوك البذور المجتمعية / شبكات المزارعين / إلخ 6) الحكومة ( وزارة الزراعة علي سبيل المثال ) 7) الاقارب أو الاصدقاء 8) آخر 9) لا أعرف 10) رفض الإجابة | G83: =LEN(F83) -> 336 | H83: Select All That Apply | I83: NA | J83: NA | K83: Form Type - Checklist 9,10 = IsNone | L83: 1-10 = crp_area_change | M83: 1)crp_seed_ownprod 2)crp_seed_market 3)crp_seed_company 4)crp_seed_ngo 5)crp_seed_organized_community 6)crp_seed_gov 7)crp_seed_relatives_friends 8)crp_seed_other 9)crp_seed_dk 10)crp_seed_ref | N83: if crp_seed_supply = 1-10, go to crp_area_change | Q83: ='Additional information'!$D$17 -> 0.81 | T83: no | X83: 18.51111 | Y83: =IF(X83="","",X83*Q83) -> 14.993999 | Z83: =IF(T83="yes",Y83,"")
Q84: ='Additional information'!$D$17 -> 0.81 | Y84: =IF(X84="","",X84*Q84) | Z84: =IF(T84="yes",Y84,"")
A85: =A83+1 -> #REF! | B85: crp_area_change | C85: crp_area_change | D85: How did the area planted for {crp_main} from Harvest season compare to last year? [OPERATOR: SINGLE RESPONSE.] 1)A lot more [increased by more than 50%] 2)Slightly more 3)Same 4)Slightly less 5)A lot less [less than half as much] 6)DON'T KNOW 7)REFUSED | E85: =LEN(D85) -> 254 | F85: كيف يمكن مقارنة المساحة المزروعة ل {crp_main} في موسم الحصاد نسبةً ل العام الماضي؟ [المشغل: استجابة واحدة.] 1) أكثر بكثير [زادت بنسبة تزيد عن 50٪] 2) أكثر قليلا 3) نفس الشيء 4) أقل قليلاً 5) أقل بكثير [أقل من نصف الكمية] 6) لا أعرف 7) رفض الإجابة | G85: =LEN(F85) -> 248 | H85: Single Choice | I85: NA | J85: NA | K85: Form Type - Buttons | L85: 1-3 or 6-7 = crp_harv_change 4-5 = o_crp_area_change_reason | M85: NA | N85: if crp_area_change = 1-7, go to crp_harv_change | Q85: ='Additional information'!$D$17 -> 0.81 | T85: yes | X85: 20.308681 | Y85: =IF(X85="","",X85*Q85) -> 16.450032 | Z85: =IF(T85="yes",Y85,"") -> 16.450032
B86: o_crp_area_change_reason | D86: If the area planted was "slightly less" or "A lot less", please specify the reason. [OPERATOR: RECORD THE RESPONSE GIVEN] | E86: =LEN(D86) -> 122 | F86: إذا كانت المساحة المزروعة "أقل قليلاً" أو "أقل بكثير" ، يرجى تحديد السبب [المُشغل: تسجيل الجواب المُعطى] | H86: Open Ended | I86: NA | J86: NA | K86: Form Type - Buttons | L86: Any response = crp_harv_change | Q86: ='Additional information'!$D$17 -> 0.81 | Y86: =IF(X86="","",X86*Q86) | Z86: =IF(T86="yes",Y86,"")
A87: =A85+1 -> #REF! | B87: crp_harv_change | C87: crp_harv_change | D87: How does the harvest of {crp_main} in the Harvest season compare to last year? [OPERATOR: SINGLE RESPONSE.] 1)A lot more [increased by more than 50%] 2)Slightly more 3)Same 4)Slightly less 5)A lot less [less than half as much] 6)DON'T KNOW 7)REFUSED | E87: =LEN(D87) -> 253 | F87: كيف يمكن مقارنة الحصاد لـ {crp_main} في موسم الحصاد نسبةً ل العام الماضي؟ [المشغل: استجابة واحدة.] 1) أكثر بكثير [زادت بنسبة تزيد عن 50٪] 2) أكثر قليلا 3) نفس الشيء 4) أقل قليلاً 5) أقل بكثير [أقل من نصف الكمية] 6) لا أعرف 7) رفض الإجابة | G87: =LEN(F87) -> 241 | H87: Single Choice | I87: NA | J87: NA | K87: Form Type - Buttons | L87: 1-7 = crp_proddif | M87: NA | N87: if crp_harv_change = 1-7, go to [crp_proddif or crp_harv_vol] | Q87: ='Additional information'!$D$17 -> 0.81 | T87: yes | X87: 15.448612 | Y87: =IF(X87="","",X87*Q87) -> 12.513376 | Z87: =IF(T87="yes",Y87,"") -> 12.513376
Q88: ='Additional information'!$D$17 -> 0.81 | Y88: =IF(X88="","",X88*Q88) | Z88: =IF(T88="yes",Y88,"")
A89: =#REF!+1 -> #REF! | B89: crp_proddif | C89: crp_proddif | D89: Has your household faced any significant difficulty in terms of crop production in Harvest season? [OPERATOR: SINGLE RESPONSE.] 1)YES 2)NO 3)DON'T KNOW 4)REFUSED | E89: =LEN(D89) -> 163 | F89: هل واجهت أسرتك أي صعوبة في إنتاج المحاصيل في موسم الحصاد؟ [المشغل: استجابة واحدة.] 1) نعم 2) لا 3) لا أعرف 4) رفض الإجابة | G89: =LEN(F89) -> 123 | H89: Single Choice | I89: NA | J89: NA | K89: Form Type - Buttons | L89: 1 = crp_proddif_2 2-4 = o_climate_change_crop | M89: NA | N89: if crp_proddif = 1, go to crp_proddif_2 ; if crp_proddif = 2-4, go to [crp_salesmain or optional question] | Q89: ='Additional information'!$D$17 -> 0.81 | T89: yes | X89: 11.37533 | Y89: =IF(X89="","",X89*Q89) -> 9.2140173 | Z89: =IF(T89="yes",Y89,"") -> 9.2140173
A90: =A89+1 -> #REF! | B90: crp_proddif_2 | C90: crp_proddif_ 1) crp_proddif_plant_disease 2) crp_proddif_pest_outbreak 3) crp_proddif_animal_grazing 4) crp_proddif_access_plot 5) crp_proddif_access_fertilize 6) crp_proddif_seed_quality 7) crp_proddif_seed_quantity 8) crp_proddif_access_pesticide 9) crp_proddif_access_labour 10) crp_proddif_access_machinery 11) crp_proddif_access_fuel 12) crp_proddif_soil_erosion 13) crp_proddif_lack_irrigation 14) crp_proddif_excess_water 15) crp_proddif_access_credit 16) crp_proddif_other 17) crp_proddif_dk 18) crp_proddif_ref | D90: Which difficulty has your household faced with crop production in Harvest season? [OPERATOR: MULTIPLE RESPONSES POSSIBLE. SELECT OPTION(S) THAT BEST FIT THE INFORMATION PROVIDED BY THE RESPONDENTS.] 1)Plant disease 2)Pest outbreak [including birds] 3)Uncontrolled animal grazing 4)Access to plot 5)Access to fertilizer [not available on markets or prices too high] 6)Access to quality seeds 7)Access to enough seeds [not available on markets or prices too high] 8)Access to pesticides 9)Access to manpower labour 10)Access to machinery, tools or animals for ploughing 11)Access to fuel or electricity to power agricultural equipment 12)Soil erosion 13)Not enough irrigation / rainfall water 14)Too much irrigation / water 15)Access to credit 16)Other 17)DON'T KNOW 18)REFUSED | E90: =LEN(D90) -> 779 | F90: ما الصعوبات التي واجهتها أسرتك في إنتاج المحاصيل في موسم الحصاد؟ [المُشغل: عدة استجابات محتملة. حدد الخيار (الخيارات) الأنسب للمعلومات المقدمة من المجيب.] 1) مرض نباتي 2) تفشي الافات ( بما في ذلك الطيور ) 3) رعي الحيوانات الغير منضبط 4) الوصول إلى قطعة الأرض 5) الوصول إلى الأسمدة [غير متوفرة في الأسواق أو أن اسعارها مرتفعة جداً] 6) الوصول الي البذور الجيدة 7) الوصول إلى ما يكفي من البذور [غير متوفرة في الأسواق أو أن اسعارها مرتفعة جداً] 8) الوصول إلى المبيدات الحشرية 9) الوصول إلى العمالة أو القوى العاملة 10) الوصول إلى آلات أو أدوات أو حيوانات للحراثة 11) الحصول على الوقود أو الكهرباء لتشغيل المعدات الزراعية 12) تعرية التربة 13) عدم كفاية مياه الري أو مياه الأمطار 14) زيادة مياه الري 15) الحصول على تمويل 16) آخر 17) لا أعرف 18) رفض الإجابة | G90: =LEN(F90) -> 754 | H90: Select All That Apply | I90: NA | J90: NA | K90: Form Type - Checklist 17,18 = IsNone | L90: 1-3, 6 or 8-18 =o_climate_change_crop 4=o_crp_prodiff_reason1 5=o_crp_prodiff_reason2 7=o_crp_prodiff_reason3 | M90: 1)crp_proddif_plant_disease 2)crp_proddif_pest_outbreak 3)crp_proddif_animal_grazing 4)crp_proddif_access_plot 5)crp_proddif_access_fertilize 6)crp_proddif_seed_quality 7)crp_proddif_seed_quantity 8)crp_proddif_access_pesticide 9)crp_proddif_access_labour 10)crp_proddif_access_machinery 11)crp_proddif_access_fuel 12)crp_proddif_soil_erosion 13)crp_proddif_lack_irrigation 14)crp_proddif_excess_water 15)crp_proddif_access_credit 16)crp_proddif_other 17)crp_proddif_dk 18)crp_proddif_ref | N90: if crp_proddif_2 = 1-18, go to [crp_salesmain OR optional question] | Q90: ='Additional information'!$D$17 -> 0.81 | T90: yes | X90: 25.844999 | Y90: =IF(X90="","",X90*Q90) -> 20.934449 | Z90: =IF(T90="yes",Y90,"") -> 20.934449
B91: o_crp_proddif_reason1 | D91: What is the main reason why you could not access your plot? [OPERATOR: MULTIPLE RESPONSES POSSIBLE.] 1)Far roads or offroads [including bad roads] 2)Do not have transportation means [car…] 3)Conflicts 4)Other 5)DON'T KNOW 6)REFUSED | E91: =LEN(D91) -> 233 | F91: ما هو السبب الرئيسي لعدم تمكنك من الوصول إلى قطعة الأرض الخاصة بك؟ [المُشغل: احتمال وجود عدة استجابات.] 1) الطرق البعيدة أو الطرق الوعرة [بما في ذلك الطرق السيئة] 2) ليس لديك وسيلة نقل [سيارة …] 3) الصراعات 4) آخر 5) لا أعرف 6) رفض الإجابة | H91: Select All That Apply | I91: NA | J91: Send if "crp_proddif_2" "Contains" "Access to plot" if not satisfied go to "o_crp_proddif_reason2" | K91: Form Type - Checklist 5,6 = IsNone | L91: 1-6 = o_climate_change_crop | Q91: ='Additional information'!$D$17 -> 0.81 | Y91: =IF(X91="","",X91*Q91) | Z91: =IF(T91="yes",Y91,"")
B92: o_crp_proddif_reason2 | D92: What is the main reason why you could not access fertilizers? [OPERATOR: MULTIPLE RESPONSES POSSIBLE.] 1)High price 2)Bad quality of fertilizers 3)No support from government 4)Other 5)DON'T KNOW 6)REFUSED | E92: =LEN(D92) -> 206 | F92: ما هو السبب الرئيسي لعدم تمكنك من الوصول إلى الأسمدة؟ [المُشغل: احتمال وجود عدة استجابات.] 1) سعر مرتفع 2) سوء جودة الأسمدة 3) لا يوجد دعم من الحكومة 4) آخر 5) لا أعرف 6) رفض الإجابة | H92: Select All That Apply | I92: NA | J92: Send if "crp_proddif_2" "Contains" "Access to fertilizer [not available on markets or prices too high]" if not satisfied go to "o_crp_proddif_reason3" | K92: Form Type - Checklist 5,6 = IsNone | L92: 1-6 = o_climate_change_crop
B93: o_crp_proddif_reason3 | D93: What is the main reason why you could not access enough seeds? [OPERATOR: MULTIPLE RESPONSES POSSIBLE.] 1)High price 2)Bad quality of seeds 3)No support from government 4)Other 5)DON'T KNOW 6)REFUSED | E93: =LEN(D93) -> 201 | F93: ما هو السبب الرئيسي لعدم تمكنك من الحصول على ما يكفي من البذور؟ [المُشغل: احتمال وجود عدة استجابات.] 1) سعر مرتفع 2) سوء جودة الأسمدة 3) لا يوجد دعم من الحكومة 4) آخر 5) لا أعرف 6) رفض الإجابة | H93: Select All That Apply | I93: NA | J93: Send if "crp_proddif_2" "Contains" "Access to enough seeds [not available on markets or prices too high]" if not satisfied go to "crp_salesmain" | K93: Form Type - Checklist 5,6 = IsNone | L93: 1-6 = o_climate_change_crop | Q93: ='Additional information'!$D$17 -> 0.81 | Y93: =IF(X93="","",X93*Q93) | Z93: =IF(T93="yes",Y93,"")
B94: o_climate_change_crop | D94: Have you changed your cropping pattern as a result of recent climatic events? [OPERATOR: SINGLE RESPONSE] 1)YES 2)NO 3)DON'T KNOW 4)REFUSED' | F94: هل قمت بتغيير نمط المحاصيل الخاص بك نتيجة للأحداث المناخية الأخيرة؟ [المشغل: استجابة واحدة] 1) نعم 2) لا 3) لا أعرف 4) رفض الإجابة | H94: Single Choice | I94: NA | L94: 1 = o_climate_change_croptype 2-4 = crp_salesmain
B95: o_climate_change_croptype | D95: If so, what was the crop that you typically grew, instead of {crp_main} ? [OPERATOR: SINGLE RESPONSE] | F95: إذا كان الأمر كذلك ، فما هو المحصول الذي تزرعه عادةً بدلاً من {crp_main}؟ [المشغل: استجابة واحدة] | H95: Single Choice | L95: Any response = o_climate_change_crop_reason
B96: o_climate_change_crop_reason | D96: What were the reasons for changing the crop type you are cultivating? [OPERATOR: MULTIPLE RESPONSES POSSIBLE.] 1)Lack of available inputs for usual crops 2)Lack of money to buy usual crop inputs 3)Fuel needs for usual crop too high [due to higher prices at current] 4)New crop inputs cheaper 5)New crops use less work on field 6)New crops use less fuel to cultivate 7)New crops need less water on field 8)New crops have higher value for sale 9)New crops are growing faster 10)New crops need less maintenance and work 11)The climate in my area has changed and the new crop is more adapted 12)DON'T KNOW 13)REFUSED | F96: ما هي أسباب تغيير نوع المحصول الذي تزرعه؟ [المُشغل: إمكانية الحصول على إجابات متعددة.] 1) نقص المدخلات المتاحة للمحاصيل المعتادة 2) قلة المال لشراء مدخلات المحاصيل المعتادة 3) احتياجات الوقود للمحاصيل المعتادة مرتفعة للغاية [بسبب ارتفاع الأسعار في الوقت الحالي] 4) مدخلات المحاصيل الجديدة أرخص 5) المحاصيل الجديدة تستخدم القليل من العمل في الحقل 6) المحاصيل الجديدة تستخدم وقودًا أقل للزراعة 7) تحتاج المحاصيل الجديدة إلى كميات أقل من المياه في الحقل 8) المحاصيل الجديدة لها قيمة أعلى للبيع 9) تنمو المحاصيل الجديدة بشكل أسرع 10) المحاصيل الجديدة تحتاج إلى صيانة وعمل أقل 11) تغير المناخ في منطقتي وأصبح المحصول الجديد أكثر تكيفًا 12) لا أعرف 13) رفض | H96: Multiple Choice | I96: NA | L96: 1-13 = crp_salesmain
A97: D. CROP MARKETING | Y97: =IF(X97="","",X97*Q97) | Z97: =IF(T97="yes",Y97,"")
B98: crp_salesmain | C98: crp_salesmain | D98: What has been the main crop that you have sold over the last 3 months? [OPERATOR: SELECT ALL CROPS LISTED BY THE RESPONDENT.] 1)Wheat 2)Maize 3)Barley 4)Potatoe 5)Chickpeas 6)Tomatoes 7)Cucumber 8)Eggplant/aubergine 9)Onions 10)Water Melon 11)Dates 12)Grapes 13)Olives 14)Melon [Cantaloupe] 15)Rice 16)Millet 17)Sorghum 18)Other Cereal 19)Cassava 20)Sweet Potatoes 21)Yams 22)Carrots 23)Cocoyam 24)Other tubers 25)Beans 26)Lentils 27)Peas 28)Soybeans 29)Fava beans 30)Broad beans 31)Other pulses 32)Cabbage 33)Lettuce 34)Spinach-Amaranth 35)Cassava leaves 36)Potatoe leaves 37)Moringa 38)Sorrel Hibiscus / Rosselle 39)Green salad herbs [thyme, parsley, mint, rocca, other] 40)Cauliflower 41)Other leafy vegetables 42)Pumpkin 43)Zucchini 44)Okra 45)Bell pepper 46)Haricot 47)Green peas 48)Fava beans green 49)Other non leafy vegs 50)Orange 51)Lemon 52)Grapefruit 53)Mandarins/clementines 54)Other citrus fruit 55)Sweet Banana 56)Plantains 57)Papaya 58)Mango 59)Guava 60)Pineapple 61)Avocado 62)Figs 63)Apple 64)Apricot 65)Cherries 66)Peach/nectarine 67)Strawberries 68)Other fruit 69)Coconuts 70)Groundnut/peanut 71)Cashew Nut 72)Kola Nut 73)Sesame 74)Bambara nut 75)Almond 76)Walnut 77)Other nuts 78)Cocoa 79)Coffee 80)Tea 81)Sugarcane 82)Sunflower 83)Other food cash crop 84)Cotton 85)Rubber 86)Jute 87)Fodder 88)Tobacco 89)Qat 90)Other non-food cash crop 92)DON'T KNOW 93)REFUSED | E98: =LEN(D98) -> 1382 | F98: ما هو المحصول الرئيسي الذي بعته خلال الأشهر الثلاثة الماضية؟ [حدد جميع المحاصيل التي سجلها المجيب.] 1)القمح 2)الذرة 3)الشعير 4)البطاطا 5)الحمص 6)الطماطم 7)الخيار 8)الباذنجان 9)بصل 10)البطيخ الأحمر 11)التمر 12)العنب 13)الزيتون 14)الشمام 15)الرز 16)الدخن 17)الذرة الرفيعة 18)الحبوب الأخرى 19)الكسافا 20)البطاطا الحلوة 21)اليام 22)الجزر 23)القلقاس 24)الدرنات الأخرى 25)الفاصوليا 26)العدس 27)البازيلاء 28)فول الصويا 29)الفول 30)الفاصوليا العريضة 31)البقول الاخرى 32)الملفوف 33)الخس 34)السبانخ - القطيفة 35)أوراق الكسافا 36)أوراق البطاطا 37)المورينجا 38)الكركديه 39)أعشاب السلطة الخضراء [زعتر ، بقدونس ، نعناع ، جرجير ، أنواع أخرى] 40)القرنبيط 41)الخضار الورقية الأخرى 42)اليقطين 43)الكوسة 44)البامية 45)الفلفل حلو 46)اللوبياء 47)البازلاء الخضراء 48)الفول الأخضر 49)الخضار غير الورقية الأخرى 50)البرتقال 51)الليمون 52)الجريب فروت 53)اليوسفي / الكليمنتين 54)الحمضيات الأخرى 55)الموز 56)موز الجنة 57)البابايا 58)المانجو 59)الجوافة 60)الأناناس 61)الأفوكادو 62)التين 63)التفاح 64)المشمش 65)الكرز 66)الدراق / النكتارين 67)الفراولة 68)الفواكه الأخرى 69)جوز الهند 70)الفول السوداني 71)الكاجو 72)جوز الكولا 73)السمسم 74)جوز البامبارا 75)اللوز 76)الجوز 77)المكسرات الأخرى 78)الكاكاو 79)القهوة 80)الشاي 81)قصب السكر 82)دوار الشمس 83)المحاصيل الغذائية النقدية الأخرى 84)القطن 85)المطاط 86)الجوت 87)العلف 88)التبغ 89)القات 90) المحاصيل النقدية غير الغذائية الأخرى 92) لا اعرف 93)رفض الإجابة | G98: =LEN(F98) -> 1380 | H98: Single Choice | I98: NA | J98: Send if "income_main" "Equals" "Production and sale of staple crops" Or "income_main" "Equals" "Production and sale of vegetable or fruit" Or "income_main" "Equals" "Production and sale of cashcrops" Or "income_sec" "Equals" "Production and sale of staple crops" Or "income_sec" "Equals" "Production and sale of vegetable or fruit" Or "income_sec" "Equals" "Production and sale of cashcrops" Or "income_third" "Equals" "Production and sale of staple crops" Or "income_third" "Equals" "Production and sale of vegetable or fruit" Or "income_third" "Equals" "Production and sale of cashcrops", if not satisfied go to "ls_intro" | K98: Form Type - Buttons | L98: 1-90 = crp_salesdif 91-92 = ls_intro | M98: $CROP SOLD CODES$ | N98: If either income_main or income_sec or income_third = "Production and sale of staple crops" or "Production and sale of vegetable/ fruit" or "Production and sale of cashcrops (cocoa, tobacco, etc)", then this section will be asked to respondents. Otherwise, skip to ls_intro. For any crop selected, go to crp_salesdif If "Don't know" or "Refused", go to ls_intro | Q98: ='Additional information'!$D$17 -> 0.81 | T98: yes | X98: 17.612015 | Y98: =IF(X98="","",X98*Q98) -> 14.265732 | Z98: =IF(T98="yes",Y98,"") -> 14.265732
Q99: ='Additional information'!$D$17 -> 0.81 | Y99: =IF(X99="","",X99*Q99) | Z99: =IF(T99="yes",Y99,"")
A100: =A90+1 -> #REF! | B100: crp_salesdif | C100: crp_salesdif | D100: Has your household faced any significant difficulty in the last 3 months selling your {crp_salesmain}? [OPERATOR: SINGLE RESPONSE.] 1)YES 2)NO 3)DON'T KNOW 4)REFUSED | E100: =LEN(D100) -> 167 | F100: هل واجهت أسرتك أي صعوبة خلال الأشهر الثلاثة الماضية في بيع {crp_salesmain}؟ [المشغل: استجابة واحدة.] 1) نعم 2) لا 3) لا أعرف 4) رفض الإجابة | G100: =LEN(F100) -> 141 | H100: Single Choice | I100: NA | J100: NA | K100: Form Type - Buttons | L100: 1 = crp_salesdif_2 2-4 = crp_salesprice | M100: NA | N100: if crp_salesdif = 1, go to crp_salesdif_2 ; if crp_salesdif = 2-4, go to crp_salesprice | Q100: ='Additional information'!$D$17 -> 0.81 | T100: yes | X100: 10.457156 | Y100: =IF(X100="","",X100*Q100) -> 8.4702965 | Z100: =IF(T100="yes",Y100,"") -> 8.4702965
A101: =A100+1 -> #REF! | B101: crp_salesdif_2 | C101: crp_saledif_ 1) crp_saledif_marketing_cost 2) crp_saledif_damage_losses 3) crp_saledif_low_demand 4) crp_saledif_pay_delay 5) crp_saledif_low_price 6) crp_saledif_processing 7) crp_saledif_competition 8) crp_saledif_other 9) crp_saledif_dk 10) crp_saledif_ref | D101: Which difficulties has your household faced in the last 3 months selling your {crp_salesmain}? [OPERATOR: MULTIPLE RESPONSES POSSIBLE. SELECT OPTION(S) THAT BEST FIT THE INFORMATION PROVIDED BY THE RESPONDENTS.] 1)High transportation or other marketing costs 2)Damages and losses due to storage difficulties and/or difficulty accessing the market [e.g. insecurity, poor infrastructure, etc.] 3)Lack of demand from usual traders or buyers 4)Payment delays from traders / buyers 5)Low selling prices [e.g. compared to input prices / inflation] 6)Difficulty processing product [lack of processing inputs / equipment / etc] 7)Market flooded with products 8)Other 9)DON'T KNOW 10)REFUSED | E101: =LEN(D101) -> 684 | F101: ما الصعوبات التي واجهتها أسرتك في الأشهر الثلاثة الماضية عند بيع {crp_salesmain}؟ [المشغل: عدة استجابات محتملة. حدد الخيار (الخيارات) الأنسب للمعلومات المقدمة من المجيب.] 1) ارتفاع تكاليف النقل أو تكاليف التسويق الأخرى 2) الاضرار و الخسائر نتيجة صعوبات التخزين و صعوبة الوصول الي السوق ( انعدام الامن / البنية التحتية الفقيرة و غيرها ) 3) قلة الطلب من المشترين و التجار المعتادين 4) تأخر المدفوعات من التجار و المشترين 5) انخفاض أسعار البيع ( مقارنة باسعار المدخلات / التضخم علي سبيل المثال ) 6) صعوبة معالجة المنتج (قلة مدخلات المعالجة ، المعدات و غيرها ) 7) تشبع السوق بالمنتجات 8) آخر 9) لا اعرف 10 ) رفض الإجابة | G101: =LEN(F101) -> 622 | H101: Select All That Apply | I101: NA | J101: NA | K101: Form Type - Checklist 9,10 = IsNone | L101: 1-10 = o_crp_salesdif_2_lowprice | M101: 1)crp_saledif_marketing_cost 2)crp_saledif_damage_losses 3)crp_saledif_low_demand 4)crp_saledif_pay_delay 5)crp_saledif_low_price 6)crp_saledif_processing 7)crp_saledif_competition 8)crp_saledif_other 9)crp_saledif_dk 10)crp_saledif_ref | N101: if crp_salesdif_2 = 1-10, go to crp_salesprice | Q101: ='Additional information'!$D$17 -> 0.81 | T101: yes | X101: 20.769962 | Y101: =IF(X101="","",X101*Q101) -> 16.823669 | Z101: =IF(T101="yes",Y101,"") -> 16.823669
...

Sheet Crop list
C3: Select top 10 crops | D3: GeoPoll code | E3: Dataset code | F3: Label (EN) | G3: Label (AR)
C4: x | D4: {=_xlfn.SEQUENCE(90,1,1,1)} -> 1 | E4: 1.1 | F4: Rice | G4: الرز
C5: x | D5: 2 | E5: 1.2 | F5: Wheat | G5: القمح
D6: 3 | E6: 1.3 | F6: Millet | G6: الدخن
D7: 4 | E7: 1.4 | F7: Sorghum | G7: الذرة الرفيعة
C8: x | D8: 5 | E8: 1.5 | F8: Maize | G8: الذرة
C9: x | D9: 6 | E9: 1.6 | F9: Barley | G9: الشعير
D10: 7 | E10: 1.99 | F10: Other Cereal | G10: الحبوب الأخرى
D11: 8 | E11: 2.1 | F11: Cassava | G11: الكسافا
C12: x | D12: 9 | E12: 2.2 | F12: Potatoe | G12: البطاطا
D13: 10 | E13: 2.3 | F13: Sweet Potatoes | G13: البطاطا الحلوة
D14: 11 | E14: 2.4 | F14: Yams | G14: اليام
D15: 12 | E15: 2.5 | F15: Carrots | G15: الجزر
D16: 13 | E16: 2.6 | F16: Cocoyam | G16: القلقاس
D17: 14 | E17: 2.99 | F17: Other tubers | G17: الدرنات الأخرى
D18: 15 | E18: 3.1 | F18: Beans | G18: الفاصوليا
D19: 16 | E19: 3.2 | F19: Lentils | G19: العدس
D20: 17 | E20: 3.3 | F20: Peas | G20: البازيلاء
D21: 18 | E21: 3.4 | F21: Soybeans | G21: فول الصويا
C22: x | D22: 19 | E22: 3.5 | F22: Chickpeas | G22: الحمص
D23: 20 | E23: 3.6 | F23: Fava beans | G23: الفول
D24: 21 | E24: 3.7 | F24: Broad beans | G24: الفاصوليا العريضة
D25: 22 | E25: 3.99 | F25: Other pulses | G25: البقول الاخرى
D26: 23 | E26: 4.1 | F26: Cabbage | G26: الملفوف
D27: 24 | E27: 4.2 | F27: Lettuce | G27: الخس
D28: 25 | E28: 4.3 | F28: Spinach-Amaranth | G28: السبانخ - القطيفة
D29: 26 | E29: 4.4 | F29: Cassava leaves | G29: أوراق الكسافا
D30: 27 | E30: 4.5 | F30: Potatoe leaves | G30: أوراق البطاطا
D31: 28 | E31: 4.6 | F31: Moringa | G31: المورينجا
D32: 29 | E32: 4.7 | F32: Sorrel Hibiscus / Rosselle | G32: الكركديه
D33: 30 | E33: 4.9 | F33: Green salad herbs [thyme, parsley, mint, rocca, other] | G33: أعشاب السلطة الخضراء [زعتر ، بقدونس ، نعناع ، جرجير ، أنواع أخرى]
D34: 31 | E34: 4.101 | F34: Cauliflower | G34: القرنبيط
D35: 32 | E35: 4.99 | F35: Other leafy vegetables | G35: الخضار الورقية الأخرى
C36: x | D36: 33 | E36: 5.1 | F36: Tomatoes | G36: الطماطم
C37: x | D37: 34 | E37: 5.2 | F37: Cucumber | G37: الخيار
D38: 35 | E38: 5.3 | F38: Pumpkin | G38: اليقطين
C39: x | D39: 36 | E39: 5.4 | F39: Eggplant/aubergine | G39: الباذنجان
D40: 37 | E40: 5.5 | F40: Zucchini | G40: الكوسة
D41: 38 | E41: 5.6 | F41: Okra | G41: البامية
D42: 39 | E42: 5.7 | F42: Bell pepper | G42: الفلفل حلو
C43: x | D43: 40 | E43: 5.8 | F43: Onions | G43: بصل
D44: 41 | E44: 5.9 | F44: Haricot | G44: اللوبياء
D45: 42 | E45: 5.101 | F45: Green peas | G45: البازلاء الخضراء
D46: 43 | E46: 5.11 | F46: Fava beans green | G46: الفول الأخضر
D47: 44 | E47: 5.99 | F47: Other non leafy vegs | G47: الخضار غير الورقية الأخرى
D48: 45 | E48: 6.1 | F48: Orange | G48: البرتقال
D49: 46 | E49: 6.2 | F49: Lemon | G49: الليمون
D50: 47 | E50: 6.3 | F50: Grapefruit | G50: الجريب فروت
D51: 48 | E51: 6.4 | F51: Mandarins/clementines | G51: اليوسفي / الكليمنتين
D52: 49 | E52: 6.99 | F52: Other citrus fruit | G52: الحمضيات الأخرى
D53: 50 | E53: 7.1 | F53: Sweet Banana | G53: الموز
D54: 51 | E54: 7.2 | F54: Plantains | G54: موز الجنة
D55: 52 | E55: 7.3 | F55: Papaya | G55: البابايا
... D59: 56 | E59: 7.7 | F59: Avocado | G59: الأفوكادو
C60: x | D60: 57 | E60: 7.8 | F60: Water Melon | G60: البطيخ الأحمر
C61: x | D61: 58 | E61: 7.9 | F61: Dates | G61: التمر
D62: 59 | E62: 7.101 | F62: Figs | G62: التين
C63: x | D63: 60 | E63: 7.11 | F63: Grapes | G63: العنب
C64: x | D64: 61 | E64: 7.12 | F64: Olives | G64: الزيتون
D65: 62 | E65: 7.13 | F65: Apple | G65: التفاح
D66: 63 | E66: 7.14 | F66: Apricot | G66: المشمش
D67: 64 | E67: 7.15 | F67: Cherries | G67: الكرز
D68: 65 | E68: 7.16 | F68: Peach/nectarine | G68: الدراق / النكتارين
D69: 66 | E69: 7.17 | F69: Strawberries | G69: الفراولة
C70: x | D70: 67 | E70: 7.18 | F70: Melon [Cantaloupe] | G70: الشمام
D71: 68 | E71: 7.99 | F71: Other fruit | G71: الفواكه الأخرى
D72: 69 | E72: 8.1 | F72: Coconuts | G72: جوز الهند
D73: 70 | E73: 8.2 | F73: Groundnut/peanut | G73: الفول السوداني
D74: 71 | E74: 8.3 | F74: Cashew Nut | G74: الكاجو
D75: 72 | E75: 8.4 | F75: Kola Nut | G75: جوز الكولا
D76: 73 | E76: 8.5 | F76: Sesame | G76: السمسم
D77: 74 | E77: 8.6 | F77: Bambara nut | G77: جوز البامبارا
D78: 75 | E78: 8.7 | F78: Almond | G78: اللوز
D79: 76 | E79: 8.8 | F79: Walnut | G79: الجوز
D80: 77 | E80: 8.99 | F80: Other nuts | G80: المكسرات الأخرى
D81: 78 | E81: 9.1 | F81: Cocoa | G81: الكاكاو
D82: 79 | E82: 9.2 | F82: Coffee | G82: القهوة
... D93: 90 | E93: 10.99 | F93: Other non-food cash crop | G93: المحاصيل النقدية غير الغذائية الأخرى

Sheet Additional information
C2: Original | D2: Replacement (EN) | E2: Replacement (AR) | F2: Comment (EN) | G2: Comment (AR) | H2: Example (EN) | I2: Example (AR)
B3: FOR CORE QUESTIONS . (Mandatory to fill out) . | C3: ADMIN1 | D3: Governorate | E3: المحافظة | F3: The first subdivision of the country, after national level; region; province; governorate; etc. | G3: التقسيم الأول للبلاد ، بعد المستوى الوطني ؛ منطقة؛ محافظة؛ ولاية ؛ إلخ. | H3: region | I3: منطقة
C4: ADMIN2 | D4: District | E4: القضاء | F4: The second subdivision of the country; district; municipality; LGA; etc. | G4: التقسيم الثاني للبلاد ؛ قضاء؛ بلدية؛ إلخ. | H4: district | I4: قضاء
C5: reference year | D5: last year | E5: العام الماضي | F5: Comparison questions will need need a reference year. Select whether you want to use "last year" or "a normal year" as a baseline. A "normal year" should refers to an average year from the past 5 years - make sure to train the enumerators accordingly. | G5: سوف تحتاج أسئلة المقارنة إلى سنة مرجعية. حدد ما إذا كنت تريد استخدام "العام الماضي" أو "العام العادي" كخط أساس. يجب أن يشير "العام العادي" إلى متوسط ​​عام من السنوات الخمس الماضية - تأكد من تدريب جامعي البيانات وفقًا لذلك. | H5: a normal year | I5: العام العادي
C6: season | D6: Harvest season | E6: موسم الحصاد | F6: Name the crop season(s) of interest if there are several cropping seasons in the country (e.g. Meher and Belg in Ethiopia, rainy season / flood-recession cropping / irrigated dry season in the Sahel). You can refer to the “last season” or “ongoing season". | G6: قم بتسمية موسم (مواسم) المحاصيل ذات الأهمية إذا كان هناك عدة مواسم محصولية في البلد (على سبيل المثال ، Meher و Belg في إثيوبيا ، موسم الأمطار / محاصيل الركود بسبب الفيضانات / موسم الجفاف المروي في منطقة الساحل). يمكنك الرجوع إلى "الموسم الماضي" أو "الموسم الجاري". | H6: wet season | I6: موسم الأمطار
C7: season phase | D7: Harvesting | E7: الحصاد | F7: Indicate the phase of the season at the time of data collection. If the harvest from the season has not yet occurred, the question on crop harvest (crp_harv_change) will include the word “expected” (where #expected or nothing# is located). If the harvest has occured, "expected" will not be inserted in the question. | G7: حدد مرحلة الموسم في وقت جمع البيانات. إذا لم يتم الحصاد من الموسم بعد ، فإن السؤال عن حصاد المحاصيل (crp_harv_change) سيتضمن كلمة "متوقع" (حيث يوجد # متوقع أو لا شيء #). إذا تم الحصاد ، لن يتم إدخال "متوقع" في السؤال . | H7: Harvesting | I7: الحصاد
C8: local measurement unit | D8: Donum | E8: دونم | F8: Specify the local measurement unit for land size, other than acres, hectares, square meters and square feet. If no other unit of measurement is needed, keep this cell blank. | G8: حدد وحدة القياس المحلية لمساحة الأرض ، بخلاف الفدان والهكتار والمتر المربع والقدم المربع. إذا لم تكن هناك حاجة إلى وحدة قياس أخرى ، احتفظ بهذه الخلية فارغة. | H8: Jeribs | I8: جريب
C9: local measurement unit conversion | D9: 0.25 | E9: 0.25 | F9: Include the conversion of the local measurement unit to hectares. In other words, how many local measurement units are in 1 ha. Only digits in Latin numbers should be inputted. | G9: قم بتضمين تحويل وحدة القياس المحلية إلى هكتار. بمعنى آخر ، إلى كم هو عدد وحدات القياس المحلية في هكتار واحد. يرجى إدخال الأرقام في الأبجدية اللاتينية (...3, 2, 1). | H9: 0.2 | I9: 0.2
B10: FOR OPTIONAL QUESTIONS . (Fill out if applicable) . | C10: currency | D10: Dinar | E10: دينار | F10: The name of the main currency used nationally; USD; Naira; Rial; Pesos; etc. | G10: اسم العملة الرئيسية المستخدمة وطنيا ؛ دولار أمريكي؛ نيرة؛ الريال؛ بيزو؛ إلخ. | H10: Naira | I10: نيرة
C11: MIN AMOUNT | D11: NA | E11: NA | F11: The minimum amount for an income source should be set at 0 or any value below which it is not possible to do a transaction. For example, the smallest coin/banknote in a currency can be 1000, in which case you would set the minimum at 1000. Provide this input in the same currency as specified above. Only digits in Latin numbers should be inputted. | G11: يجب تعيين الحد الأدنى لمبلغ مصدر الدخل على 0 أو أي قيمة أقل منها لا يمكن إجراء معاملة. على سبيل المثال ، يمكن أن تكون أصغر عملة / ورقة نقدية في عملة ما هي 1000 ، وفي هذه الحالة يمكنك تعيين الحد الأدنى عند 1000. يجب أن يكون هذا المبلغ بنفس العملة المحددة في الصف أعلاه. يرجى إدخال الأرقام في الأبجدية اللاتينية (...3, 2, 1). | H11: 5 | I11: 5
C12: MAX AMOUNT | D12: NA | E12: NA | F12: Set the maximum amount for an income source over 3 months. Enumerators will not be able to input values above this amount in questions related to income amounts. Using previous representative surveys for this population, you can estimate this amount by using the mean income plus five (5) standard deviations, unless the country has high inflation. In the latter case, set the maximum value based on your country context (higher than the proposed approach). Provide this input in the same currency as specified above. Only digits in Latin numbers should be inputted. | G12: حدد الحد الأقصى لمبلغ مصدر الدخل على مدى 3 أشهر. لن يتمكن جامعي البيانات من إدخال قيم أعلى من هذا المبلغ في الأسئلة المتعلقة بمبالغ الدخل. باستخدام المسوح التمثيلية السابقة لهذه الفئة من السكان ، يمكنك تقدير هذا المبلغ باستخدام متوسط ​​الدخل بالإضافة إلى خمسة انحرافات معيارية ما لم يكن هناك تضخم مرتفع في الدولة. في الحالة الأخيرة ، قم بتعيين الحد الأقصى للقيمة بناءً على سياق بلدك (أعلى من النهج المقترح). يجب أن يكون هذا المبلغ بنفس العملة المحددة أعلاه. يرجى إدخال الأرقام في الأبجدية اللاتينية (...3, 2, 1). | H12: 5000000 | I12: 5000000
C13: THRESHOLD | D13: NA | E13: NA | F13: The threshold salary should be calculated to flag outliers (responses that look suspiciously high). Using previous representative surveys for this population, a good estimate is the average plus three (3) standard deviations, which should give the threshold for the 3 or 4% highest income values. Provide this input in the same currency as specified above. Only digits in Latin numbers should be inputted. | G13: يجب حساب قيمة العتبة للراتب لتحديد القيم المتطرفة (الاستجابات التي تبدو مرتفعة بشكل مثير للريبة). باستخدام المسوح التمثيلية السابقة لهذه الفئة من السكان ، فإن التقدير الجيد هو المتوسط ​​زائد ثلاثة انحرافات معيارية ، والذي يجب أن يعطي قيمة العتبة لقيم الدخل الأعلى بنسبة 3 أو 4٪. يجب أن يكون هذا المبلغ بنفس العملة المحددة أعلاه. يرجى إدخال الأرقام في الأبجدية اللاتينية (...3, 2, 1). | H13: 1200000 | I13: 1200000
C14: local vegetables | D14: Tomato, cucumber, eggplant, onion, potato,… | E14: طماطم, خيار, باذنجان, بصل, بطاطا | F14: Input some common local vegetables [to be used as examples in the food consumption score indicator]. | G14: أدخل بعض الخضروات المحلية الشائعة [لاستخدامها كأمثلة في مؤشر درجة استهلاك الغذاء]. | H14: eggplants, zucchini, cauliflower | I14: باذنجان ، كوسة ، قرنبيط
C15: local fruits | D15: apple, orange, grape, pomegranate, date, watermelon | E15: تفاح, برتقال, عنب, رمان, تمر, بطيخ | F15: Input some common local fruits [to be used as examples in the food consumption score indicator]. | G15: أدخل بعض الفاكهة المحلية الشائعة [لاستخدامها كأمثلة في مؤشر درجة استهلاك الغذاء]. | H15: apples, bananas, oranges | I15: التفاح والموز والبرتقال
B17: FILL OUT FOR QUESTIONNAIRE DURATION ESTIMATION . | C17: Expected percentage of respondents cultivating crops | D17: =IF(E17="","",E17) -> 0.81 | E17: 0.81 | F17: If the survey is representative and has no quotas, write the proportion of rural households cultivating crops at country level, or if the survey follows a previous round with identical sample design, just report the percentage from the previous round. If you are using quotas, calculate the ratio of the quota over the minimum sample size at the level where the quota is implemented (so if you have a minimum sample size per strata of 110 with a quota of 100 crop producers, then it's 100/110 = 91% (the maximum you should write is 100%). | G17: إذا كان المسح تمثيليًا وليس له حصص نسبية ، فاكتب نسبة الأسر الريفية التي تزرع محاصيل على المستوى الوطني ، أو إذا كان المسح يتبع جولة سابقة بتصميم عينة متطابق ، فما عليك سوى الإبلاغ عن النسبة المئوية من الجولة السابقة. إذا كنت تستخدم نظام الحصص النسبية ، فاحسب نسبة الحصة إلى الحد الأدنى لحجم العينة على المستوى الذي يتم فيه تنفيذ الحصة (لذلك إذا كان لديك حد أدنى لحجم العينة لكل طبقة 110 مع حصة 100 منتج محصول ، فسيكون 100 / 110 = 91٪ (الحد الأقصى الذي يجب أن تكتبه هو 100٪). | H17: 0.91 | I17: 0.91
C18: Expected percentage of respondents raising livestock | D18: =IF(E18="","",E18) -> 0.56 | E18: 0.56 | F18: If the survey is representative and has no quotas, write the proportion of rural households raising livestock at country level, or if the survey follows a previous round with identical sample design, just report the percentage from the previous round. If you are using quotas, calculate the ratio of the quota over the minimum sample size at the level where the quota is implemented (so if you have a minimum sample size of 110 but a quota of 100 livestock producers, then it's 100/110 = 91% (the maximum you should write is 100%) | G18: إذا كان المسح تمثيليًا وليس له حصص نسبية ، فاكتب نسبة الأسر الريفية التي تربي الماشية على المستوى الوطني ، أو إذا كان المسح يتبع جولة سابقة بتصميم عينة متطابق ، فما عليك سوى الإبلاغ عن النسبة المئوية من الجولة السابقة. إذا كنت تستخدم نظام الحصص النسبية ، فاحسب نسبة الحصة إلى الحد الأدنى لحجم العينة على المستوى الذي يتم فيه تنفيذ الحصة (لذلك إذا كان لديك حد أدنى لحجم العينة لكل طبقة 110 مع حصة 100 مربي الماشية ، فسيكون 100 / 110 = 91٪ (الحد الأقصى الذي يجب أن تكتبه هو 100٪). | H18: 0.91 | I18: 0.91
C19: Expected percentage of respondents involved in fishery | D19: =IF(E19="","",E19) -> 0 | E19: 0 | F19: If the survey is representative and has no quotas, write the proportion of rural households involved in fisheries or aquaculture, otherwise if you are using quotas, calculate the ratio of the quota over the sample size at the level where the quota is implemented. (so if you haven't set a quota, and you expect to have a representative proportion of fishermen, just write the percentage of fishermen in the population you are targeting, in the example to the right, 5%) | G19: إذا كان المسح تمثيليًا وليس له حصص نسبية ، فاكتب نسبة الأسر الريفية العاملة في مصايد الأسماك أو تربية الأحياء المائية على المستوى الوطني. وإلا إذا كنت تستخدم الحصص النسبية ، فاحسب نسبة الحصة إلى حجم العينة على المستوى الذي يتم فيه تنفيذ الحصة. (لذلك إذا لم تحدد حصة ، وكنت تتوقع أن يكون لديك نسبة تمثيلية من الصيادين ، فاكتب فقط النسبة المئوية للصيادين من السكان الذين تستهدفهم ، في المثال على اليمين ، 5٪). | H19: 0.05 | I19: 0.05

Sheet Admin 1 info
A1: adm1_name | B1: adm1_pcode | C1: adm0_name | D1: adm0_ISO3
A2: Anbar | B2: IQG01 | C2: Iraq | D2: IRQ
A3: Basrah | B3: IQG02 | C3: Iraq | D3: IRQ
A4: Muthanna | B4: IQG03 | C4: Iraq | D4: IRQ
A5: Najaf | B5: IQG04 | C5: Iraq | D5: IRQ
A6: Qadisiya | B6: IQG05 | C6: Iraq | D6: IRQ
A7: Sulaimaniyah | B7: IQG06 | C7: Iraq | D7: IRQ
A8: Babylon | B8: IQG07 | C8: Iraq | D8: IRQ
A9: Baghdad | B9: IQG08 | C9: Iraq | D9: IRQ
A10: Dohuk | B10: IQG09 | C10: Iraq | D10: IRQ
A11: Diyala | B11: IQG10 | C11: Iraq | D11: IRQ
A12: Erbil | B12: IQG11 | C12: Iraq | D12: IRQ
... A19: Wasit | B19: IQG18 | C19: Iraq | D19: IRQ

Sheet Admin 2 info
A1: adm2_name | B1: adm2_name_local | C1: adm2_pcode | D1: adm1_name | E1: adm1_pcode | F1: adm0_name | G1: adm0_ISO3
A2: Al-Azezia | B2: العزيزية | C2: IQG18Q06 | D2: Wasit | E2: IQG18 | F2: Iraq | G2: IRQ
A3: Kirkuk | B3: كركوك | C3: IQG13Q04 | D3: Kirkuk | E3: IQG13 | F3: Iraq | G3: IRQ
A4: Ru'ua | B4: راوة | C4: IQG01Q09 | D4: Anbar | E4: IQG01 | F4: Iraq | G4: IRQ
A5: Ana | B5: عنه | C5: IQG01Q06 | D5: Anbar | E5: IQG01 | F5: Iraq | G5: IRQ
A6: Djel | B6: دجيل | C6: IQG16Q08 | D6: Salah al-deen | E6: IQG16 | F6: Iraq | G6: IRQ
A7: Al-Sadir1 | B7: الثورة 1 | C7: IQG08Q07 | D7: Baghdad | E7: IQG08 | F7: Iraq | G7: IRQ
A8: Al-Sadir2 | B8: الثورة 2 | C8: IQG08Q08 | D8: Baghdad | E8: IQG08 | F8: Iraq | G8: IRQ
A9: Abu Ghraib | B9: أبو غريب | C9: IQG08Q09 | D9: Baghdad | E9: IQG08 | F9: Iraq | G9: IRQ
A10: Darbandihkan | B10: دربندخان | C10: IQG06Q03 | D10: Sulaimaniyah | E10: IQG06 | F10: Iraq | G10: IRQ
A11: Penjwin | B11: بنجوين | C11: IQG06Q07 | D11: Sulaimaniyah | E11: IQG06 | F11: Iraq | G11: IRQ
A12: Halabja | B12: حلبجة | C12: IQG06Q05 | D12: Sulaimaniyah | E12: IQG06 | F12: Iraq | G12: IRQ
... A126: Al-Suwaira | B126: الصويرة | C126: IQG18Q03 | D126: Wasit | E126: IQG18 | F126: Iraq | G126: IRQ
