Workbook

Sheet survey
A1: GeoPoll Submission Form
A2: FAO - Household Questionnaire | R2: Additional notes
A3: Q # | B3: Q Name | C3: Suggested Qname | D3: English | E3: Length | F3: Arabic | G3: Length | H3: Q Type | I3: Randomize | J3: Conditional | K3: Programming Instructions | L3: Skip Pattern | M3: Codes | N3: GeoPoll Comments | O3: FAO Response | P3: Default skip patterns & conditional | Q3: Specify skip pattern variable (from blue text) | S3: Estimated percentage of repondents | V3: Mandatory | Z3: Duration (sec) | AA3: Weighted duration | AB3: Core questions only
A4: A. PRESENTATION OF THE SURVEY AND ELIGIBILITY CRITERIA SELECTION | V4: no | AA4: =IF(Z4="","",Z4*X4) | AB4: =IF(V4="yes",AA4,"")
A5: NA | B5: Optin | D5: Optin | E5: =LEN(D5) -> 5 | F5: Optin | G5: =LEN(F5) -> 5 | H5: Open Ended | I5: NA | J5: NA | K5: Form Type - TextBox | L5: Any Response = calldispo | M5: NA | P5: NA | V5: no | Z5: 0 | AA5: =IF(Z5="","",Z5*S5) -> 0 | AB5: =IF(V5="yes",AA5,"")
A6: NA | B6: calldispo | C6: calldispo | D6: Phone number: #CATI_MOBILENUMBER# 1)Someone answers 2)Answering machine 3)No answer 4)Hang up or refusal 5)Call back 6)Under review 7)Disconnected | E6: =LEN(D6) -> 146 | F6: رقم الهاتف: #CATI_MOBILENUMBER# 1) يجيب شخص ما 2) جهاز الرد الالي 3) لا جواب 4) إنهاء المكالمة أو الرفض 5) معاودة الاتصال 6) قيد المراجعة 7) قطع الاتصال | G6: =LEN(F6) -> 153 | H6: Single Choice | I6: NA | J6: NA | K6: Form Type - Buttons | L6: 1 = resp_language 2 = AnsweringMachine 3 = NoAnswer 4 = Refusal 5 = WhenCallBack 6 = UnderReview 7 = Disconnected | M6: NA | P6: NA | V6: no | Z6: 14.695308 | AA6: =IF(Z6="","",Z6*S6) -> 0 | AB6: =IF(V6="yes",AA6,"")
A7: NA | B7: AnsweringMachine | C7: calldispo_answeringmachine | D7: Reached an answering machine. | E7: =LEN(D7) -> 29 | F7: لقد تم توجيهك إلى جهاز الرد الالي | G7: =LEN(F7) -> 33 | H7: NA | I7: NA | J7: NA | K7: NA | L7: End Poll AnsweringMachine | M7: NA | P7: NA | V7: no | Z7: 0 | AA7: =IF(Z7="","",Z7*S7) -> 0 | AB7: =IF(V7="yes",AA7,"")
A8: NA | B8: NoAnswer | C8: calldispo_noanswer | D8: Phone rang and no one answered. | E8: =LEN(D8) -> 31 | F8: رن الهاتف ولم يرد أحد | G8: =LEN(F8) -> 21 | H8: NA | I8: NA | J8: NA | K8: NA | L8: End Poll NoAnswer | M8: NA | P8: NA | V8: no | Z8: 0 | AA8: =IF(Z8="","",Z8*S8) -> 0 | AB8: =IF(V8="yes",AA8,"")
A9: NA | B9: UnderReview | C9: calldispo_underreview | D9: Case needs review by a supervisor. | E9: =LEN(D9) -> 34 | F9: الحالة تحتاج إلى مراجعة من قبل مشرف | G9: =LEN(F9) -> 35 | H9: NA | I9: NA | J9: NA | K9: NA | L9: End Poll UnderReview | M9: NA | P9: NA | V9: no | Z9: 0 | AA9: =IF(Z9="","",Z9*S9) -> 0 | AB9: =IF(V9="yes",AA9,"")
A10: NA | B10: Disconnected | C10: calldispo_disconnected | D10: Phone was disconnected or out of service. | E10: =LEN(D10) -> 41 | F10: تم فصل الهاتف أو الهاتف خارج الخدمة | G10: =LEN(F10) -> 35 | H10: NA | I10: NA | J10: NA | K10: NA | L10: End Poll Disconnected | M10: NA | P10: NA | V10: no | Z10: 0 | AA10: =IF(Z10="","",Z10*S10) -> 0 | AB10: =IF(V10="yes",AA10,"")
A11: NA | B11: resp_language | C11: resp_language | D11: Which language do you wish to proceed with? [OPERATOR: READ ANSWER CHOICES. SINGLE RESPONSE.] 1)Arabic 2)English - TESTING | E11: =LEN(D11) -> 124 | F11: ما هي اللغة التي ترغب في المتابعة بها؟ [المُشغل: اقرأ خيارات الإجابة. استجابة واحدة.] 1) العربية 2)English - TESTING | G11: =LEN(F11) -> 118 | H11: Single Choice | I11: NA | J11: NA | K11: Form Type - Buttons | L11: 1 = introduction [Arabic] 2 = introduction [English] | M11: NA | N11: GeoPoll: Added English for testing purpose considering the survey will be running in Arabic only. | O11: OK | P11: For any response, go to introduction | R11: Arabic | V11: no | Z11: 3.1032724 | AA11: =IF(Z11="","",Z11*S11) -> 0 | AB11: =IF(V11="yes",AA11,"")
A12: 1 | B12: introduction | C12: introduction | D12: Hello sir/ma'am, my name is #OPERATOR#, and I am calling on behalf of the Food and Agriculture Organization of the United Nations [FAO] because your name appeared on the organization's beneficiary list in recent years. I would like to ask you some questions about the impact of the current situation on your source of livelihood and your household's ability to obtain food. The survey usually takes 20/25 minutes to complete. Any information that you provide will be kept strictly confidential, only used for the purpose of the survey and will not be shown to other people. Your voluntary participation in the outcome of this interview is NOT IN ANY WAY linked to your personal chance of receiving any assistance. This is voluntary and you can choose not to answer any or all of the questions if you want. However, we hope that you will participate since your views are important. Please note that this call may be recorded for quality purposes. Do you have any questions? [OPERATOR: ADDRESS QUESTIONS FROM RESPONDENT, IF ANY.] 1)CONTINUE | E12: =LEN(D12) -> 1046 | F12: مرحبا، أنا إسمي #OPERATOR# وبحكي معك نيابة عن منظمة الأمم الممتحده للأغذية والزراعة (فاو) لأنه إسمك ورد على قوائم المستفيدين من المنظمة خلال الاعوام الأخيره. بدي أسالك شويه أسئله حول أثر الوضع الحالي على مصدر رزقك وقدرة أسرتك على الحصول على الغذاء. رح آخد من وقتك 25 ل 20 دقيقه. بدي احكيلك انه هاي المعلومات رح تضل سريه وإنه نتبيجه هاي الدراسه ما الها اي علاقه بأي مساعدات بتقدمها المنظمة. من حقك ترفض المشاركه بس يا ريت تشارك لأنه رأيك بهمنا وبحب احكيلك أنه هاي المكالمة رح تكون مسجله لهدف رصد الجودة. يرجى الملاحظة أنه قد يتم تسجيل هذه المكالمة لغاية مراقبة الجودة. عندك أي سؤال الي؟ [المُشغل: أجب على أسئلة المُجيب ، إن وجدت.] 1) تابع | G12: =LEN(F12) -> 643 | H12: Single Choice | I12: NA | J12: NA | K12: Form Type - Buttons | L12: 1 = Agree | M12: NA | N12: GeoPoll [3/18/2024]. Removed the reference to incentives given this will be a non-incentive survey. Kindly also advise if we should include a series of introductory messages to verify that we are speaking with the correct person/beneficiary listed in the database, or if this is not required. Example: "Our records indicate that this is the mobile number of [input name] from [input locality]. Are you this same person? (yes, proceed with interview. No, next screener question) May I speak with this person now? (yes, proceed with interview. No, next screener question) Are you part of the same household as [input name]? (yes, proceed with interview. No, next screener question). GeoPoll [4/11/2024]: Added in QNames Beneficiary - Beneficiary_Confirm2 below. Also updated length of interview to reference 20/25 instead of 15/20.. | O12: Removal of incentives: ok, thanks. Introductory message: Yes, we should verify the respondent (or someone in their household) is indeed a former FAO beneficiary, however we must find an alternative approach. The proposed text is not appropriate as it would provide senstive information (name and location) up front. | P12: For any response, go to Agree | R12: Set the amount of incentive here, if any. | V12: no | Z12: 37.418449 | AA12: =IF(Z12="","",Z12*S12) -> 0 | AB12: =IF(V12="yes",AA12,"")
A13: NA | B13: Agree | C13: resp_agree | D13: Are you interested in participating in this survey? [OPERATOR: SINGLE RESPONSE] 1)Yes 2)Not now but another time in the week 3)No | E13: =LEN(D13) -> 131 | F13: هل لديك رغبة في بالمشاركة في هذه الدراسة؟ [المشغل: استجابة واحدة] 1) نعم 2) ليس الآن ولكن في وقت آخر في الأسبوع 3) لا | G13: =LEN(F13) -> 119 | H13: StartRecording | I13: NA | J13: NA | K13: Form Type - Buttons | L13: 1 = Beneficiary 2 = WhenCallBack 3 = resp_refusalwhy | M13: NA | P13: if Agree = 1, go to id_panel OR resp_firstname if Agree = 2, go to WhenCallBack if Agree = 3, go to resp_refusalwhy | Q13: if Agree = 1, go to resp_age if Agree = 2, go to WhenCallBack if Agree = 3, go to resp_refusalwhy | S13: 1 | V13: no | Z13: 3.8059516 | AA13: =IF(Z13="","",Z13*S13) -> 3.8059516 | AB13: =IF(V13="yes",AA13,"")
A14: NA | B14: resp_refusalwhy | C14: resp_refusalwhy | D14: Please let us know why you have REFUSED to take the survey. [OPERATOR: SINGLE RESPONSE] 1)Not interested 2)Do not want to be recorded 3)Other [specify] | E14: =LEN(D14) -> 153 | F14: يرجى إخبارنا سبب رفضك للمشاركة في هذه الدراسة. [المشغل: استجابة واحدة] 1) غير مهتم 2) لا أريد أن يتم تسجيلي 3) آخر [حدد] | G14: =LEN(F14) -> 122 | H14: Open Ended-Single Choice | I14: NA | J14: NA | K14: Form Type - RadioList | L14: Any Response = Refusal | M14: NA | P14: For any response, go to Refusal | S14: 1 | V14: no | Z14: 0 | AA14: =IF(Z14="","",Z14*S14) -> 0 | AB14: =IF(V14="yes",AA14,"")
A15: NA | B15: WhenCallBack | C15: resp_whencallback | D15: When would it be a good time to call you back? [RECORD HH/MM/DD/MM OF CALLBACK] | E15: =LEN(D15) -> 80 | F15: ما هو التاريخ / الوقت المناسب لمعاودة الاتصال بك؟ [RECORD HH / MM / DD / MM of CALLBACK] | G15: =LEN(F15) -> 89 | H15: Open Ended | I15: NA | J15: NA | K15: Form Type - TextBox IsCallBackDemographic | L15: Any Response = CallbackMessageEN | M15: NA | P15: For any response, go to CallbackMessageEN | S15: 1 | V15: no | Z15: 0 | AA15: =IF(Z15="","",Z15*S15) -> 0 | AB15: =IF(V15="yes",AA15,"")
A16: NA | B16: CallbackMessageEN | C16: callbackmessage_en | D16: Thank you, we will call you back at {WhenCallBack} you requested. Thank you again and have a great day! [OPERATOR: ENTER CALL NOTES BELOW, WHO YOU SPOKE TO AND WHAT THEY SAID] | E16: =LEN(D16) -> 176 | F16: شكرًا لك ، سوف نعاود الاتصال بك في {WhenCallBack} الذي طلبته. شكرا لك مرة أخرى و نتمنى لك يوم جميل! [المُشغل: أدخل ملاحظات الاتصال أدناه ، مع من تحدثت وماذا قالوا] | G16: =LEN(F16) -> 164 | H16: Open Ended | I16: NA | J16: NA | K16: Form Type - TextBox | L16: Any Response = End poll callback | M16: NA | P16: NA | S16: 1 | V16: no | Z16: 0 | AA16: =IF(Z16="","",Z16*S16) -> 0 | AB16: =IF(V16="yes",AA16,"")
A17: NA | B17: Ineligible | C17: NA | D17: You are ineligible for this survey. Thank you for your time and please look out for future surveys! | E17: =LEN(D17) -> 99 | F17: أنت غير مؤهل للمشاركة في هذه الدراسة، شكرًا لك على وقتك. ترقب دراسات GeoPoll المستقبلية! | G17: =LEN(F17) -> 89 | H17: NA | I17: NA | J17: NA | K17: NA | L17: End Poll Ineligible | M17: NA | P17: NA | S17: 1 | V17: no | Z17: 0 | AA17: =IF(Z17="","",Z17*S17) -> 0 | AB17: =IF(V17="yes",AA17,"")
A18: NA | B18: Refusal | C18: NA | D18: Thank you for your time, you will be removed from today's survey. | E18: =LEN(D18) -> 65 | F18: شكراً جزيلاً على وقتك، سنقوم بحذف إسمك من دراسة اليوم. | G18: =LEN(F18) -> 54 | H18: NA | I18: NA | J18: NA | K18: NA | L18: End poll declined | M18: NA | P18: NA | S18: 1 | V18: no | Z18: 0 | AA18: =IF(Z18="","",Z18*S18) -> 0 | AB18: =IF(V18="yes",AA18,"")
A19: B. GENERAL INFORMATION & ELIGIBILITY CRITERIA | AA19: =IF(Z19="","",Z19*S19) | AB19: =IF(V19="yes",AA19,"")
A20: 2 | B20: Beneficiary | C20: Beneficiary | D20: Were you or anyone in your household a beneficiary of a FAO project or Ministry of Agriculture project during the past five years? [OPERATOR: SINGLE RESPONSE] 1)YES 2)NO 3)DON'T KNOW | E20: =LEN(D20) -> 184 | F20: خلال ال 5 سنوات الماضية، هل استفدت انت او أي فرد من افراد اسرتك من أي مشروع نفذته منظمة الأغذية والزراعة – الفاو اأو مشروع تفذته وزارة الزراعة؟ [المشغل: استجابة واحدة] 1) نعم 2) لا 3)لا أعرف | G20: =LEN(F20) -> 192 | H20: Single Choice | I20: NA | J20: NA | K20: Form Type - Buttons | L20: 1=Beneficiary_Confirm1 2=Ineligible 3=Beneficiary_Confirm2 | M20: NA | N20: GeoPoll [4/11/2024]: Added in QNames Beneficiary - Beneficiary_Confirm2. Our team is in the process of inputting the translations. Kindly advise if any further feedback.
A21: 3 | B21: Beneficiary_Confirm1 | C21: Beneficiary_Confirm1 | D21: Thank you. Kindly provide me with their name and location during the period that they were a FAO or Ministry of Agriculture beneficiary. [OPERATOR: LISTEN TO THE NAME AND LOCATION OF THE BENEFICIARY PROVIDED BY THE RESPONDENT. SELECT CONTINUE IF IT IS THE SAME AS THE DATABASE. OTHERWISE, SELECT INELIGIBLE. 1)Continue 2)Ineligible | E21: =LEN(D21) -> 334 | F21: شكرًا لك. يرجى تزويدي باسم المستفيد ومكان سكنه خلال الفترة التي كان بها مستفيد من مشروع الممول من المنذمة الاغذية و الزراعة - الفاو او مشروع وزارة الزراعة [المشغل: استمع إلى اسم مكان سكن المستفيد. حدد متابعة إذا كان هو نفسه الموجود في قاعدة البيانات. بخلاف ذلك، حدد غير مؤهل] 1) تابع 2) غير مؤهل | G21: =LEN(F21) -> 298 | H21: Single Choice | I21: NA | J21: NA | K21: Form Type - Buttons | L21: 1=resp_age 2=Ineligible | M21: NA
A22: 4 | B22: Beneficiary_Confirm2 | C22: Beneficiary_Confirm2 | D22: Our records indicate the beneficiary is [IDENTIFY FIRST NAME BASED ON RESPONDENT ID]. Is this you or a member of your household? [OPERATOR: SINGLE RESPONSE. PROMPT FIRST WITH THE FIRST NAME ONLY, THEN PROCEED TO FAMILY NAME AND LASTLY LOCATION IF PROBING IS REQUIRED. DO NOT REVEAL NAME AND LOCATION AT THE SAME TIME / TAKE CARE TO AVOID REVEALING PERSONAL IDENTIFYING INFORMATION]. 1)YES 2)NO | E22: =LEN(D22) -> 396 | F22: تشير القوائم لدينا إلى أن المستفيد هو [اذكر الاسم الأول فقط من القائمة]. هل هو أنت أو أحد أفراد أسرتك؟ [المشغل: استجابة واحدة. اذكر الاسم الاول للمستميد, و من ثم اسم العائلة و الموقع الجغرافي لاحقا. لا تذكر الاسم و الموقع الجغرافي في ان واحد للحفاظ على عدم كشف معلومات تعريفية شخصية] 1) نعم 2) لا | G22: =LEN(F22) -> 298 | H22: Single Choice | I22: NA | J22: NA | K22: Form Type - Buttons | L22: 1=resp_age 2=Ineligible | M22: NA
A23: 5 | B23: resp_age | C23: resp_age | D23: How old are you? [OPERATOR: RECORD AGE IN NUMBER OF YEARS. ROUND UP TO NEAREST WHOLE NUMBER. IF THE RESPONDENT GIVES BIRTH YEAR, REPEAT THE QUESTION. ENTER 00 FOR DON'T KNOW.] | E23: =LEN(D23) -> 177 | F23: كم عمرك؟ [المُشغل: سجل العمر في عدد السنوات. قم بالتقريب لأقرب رقم كامل. إذا أعطى المجيب سنة الميلاد ، فكرر السؤال. أدخل 00 للا أعرف.] | G23: =LEN(F23) -> 135 | H23: Range | I23: NA | J23: NA | K23: Form Type - TextBox | L23: 0-17 = Ineligible 18-100 = resp_gender 00 = Ineligible | M23: NA | P23: Only respondents from 18-100 will be eligible for the survey. | S23: =1 -> 1 | V23: yes | Z23: 9.8907185 | AA23: =IF(Z23="","",Z23*S23) -> 9.8907185 | AB23: =IF(V23="yes",AA23,"") -> 9.8907185
A24: =A23+1 -> 6 | B24: resp_gender | C24: resp_gender | D24: What is the gender of the respondent? [OPERATOR: DO NOT ASK THIS QUESTION OUT LOUD. LISTEN TO THE VOICE AND SELECT THE GENDER.] 1)Male 2)Female 3)DON'T KNOW 4)REFUSED | E24: =LEN(D24) -> 168 | F24: ما هو جنس المجيب؟ [المُشغل: لا تطرح هذا السؤال. استمع إلى الصوت وحدد المربع الصحيح.] 1) ذكر 2) أنثى 3) لا أعرف 4) رفض الإجابة | G24: =LEN(F24) -> 127 | H24: Single Choice | I24: NA | J24: NA | K24: Form Type - Buttons | L24: 1-4 = hh_admin1 | M24: NA | P24: For any response, go to phone_number_conf | Q24: For any response, go to hh_admin1 | S24: =1 -> 1 | V24: yes | Z24: 1.7156482 | AA24: =IF(Z24="","",Z24*S24) -> 1.7156482 | AB24: =IF(V24="yes",AA24,"") -> 1.7156482
A25: 7 | B25: hh_admin1 | C25: hh_admin1 | D25: Currently, in which Governorate does your household reside in? [OPERATOR: SINGLE SELECTION.] [HINT: HOUSEHOLD CONSISTS OF ALL MEMBERS LIVING TOGETHER, SHARING RESOURCES & EATING FROM THE SAME POT.] 1)HEBRON 2)NABLUS 3)RAMALLAH 4)SALFIT 5)BETHLEHEM 6)JENIN 7)JERICHO 8)JERUSALEM 9)QALQILIA 10)TUBAS 11)TULKARM 12)DON'T KNOW 13)REFUSED | E25: =LEN(D25) -> 338 | F25: حاليًا ، في أي محافظة تقيم أسرتك؟ [المشغل: استجابة واحدة.] [ملحوظة: تتكون الأسرة من جميع الأعضاء الذين يعيشون معًا ، ويتشاركون الموارد ويأكلون من نفس القدر.] 1)الخليل 2)نابلس 3)رام الله 4)سلفيت 5)بيت لحم 6)جنين 7)أريحا 8)القدس [J2] 9)قلقيلية 10)طوباس 11)طولكرم 12) لا أعرف 13) رفض الإجابة | G25: =LEN(F25) -> 291 | H25: Single Choice | I25: NA | J25: NA | K25: Form Type - Dropdown IsDemographic - ADM1 | L25: 1 = hh_admin2_1 2 = hh_admin2_2 3 = hh_admin2_3 4 = hh_admin2_4 5 = hh_admin2_5 6 = hh_admin2_6 7 = hh_admin2_7 8 = hh_admin2_8 9 = hh_admin2_9 10 = hh_admin2_10 11 = hh_admin2_11 12-13 = Ineligible | M25: NA | N25: GeoPoll [4/11/2024]: Added in translation for governorate in Arabic. | P25: The administrative information will be updated by GeoPoll based on the sample design document and the administrative boundaries provided by the dashboard team after the questionnaire validation. | S25: =1 -> 1 | V25: yes | Z25: 13.957259 | AA25: =IF(Z25="","",Z25*S25) -> 13.957259 | AB25: =IF(V25="yes",AA25,"") -> 13.957259
A26: =A25+1 -> 8 | B26: hh_admin2_1 | C26: hh_admin2_1 | D26: Currently, in which locality [village/town/city] does your household reside? [OPERATOR: SINGLE RESPONSE.] 1) 'ANAB AL KABIR 2)AD DEIRAT 3)ADH DHAHIRIYA 4)AL 'ARRUB CAMP 5)AL BAQA 6)AL BOWEREH [AQABAT INJELEH] 7)AL BURJ 8)AL BUWEIB 9)AL FAWWAR CAMP 10)AL HEILA 11)AL KARMIL 12)AL MAJD 13)AN NAJADA 14)AR RAMADIN 15)AR RIHIYA 16)ARAB AL FUREIJAT 17)AS SAMU' 18)AS SURA 19)ASH SHUYUKH 20)AT TUWANI 21)BANI NA'IM 22)BEIT 'AMRA 23)BEIT AR RUSH AL FAUQA 24)BEIT AR RUSH AT TAHTA 25)BEIT 'AWWA 26)BEIT 'EINUN 27)BEIT KAHIL 28)BEIT MAQDUM 29)BEIT MIRSIM 30)BEIT ULA 31)BEIT UMMAR 32)DEIR AL 'ASAL AL FAUQA 33)DEIR AL 'ASAL AT TAHTA 34)DEIR RAZIH 35)DEIR SAMIT 36)DURA 37)FUQEIQIS 38)HADAB AL 'ALAQA 39)HADAB AL FAWWAR 40)HALHUL 41)HAMRUSH 42)HEBRON [AL KHALIL] 43)HITTA 44)IDHNA 45)IMNEIZIL 46)IMREISH 47)JALA 48)KARMA 49)KHALLET AL 'AQED 50)KHALLET AL MAIYYA 51)KHALLET AL MASAFER 52)KHALLET EDAR 53)KHALLET SALIH 54)KHARAS 55)KHASHEM ADARAJ [AL-HATHALEEN] 56)KHEROSHEWESH WAL HADEDEYAH 57)KHIRBET AD DEIR 58)KHIRBET AL FAKHEIT 59)KHIRBET ASAFI 60)KHIRBET BIR AL 'IDD 61)KHIRBET SALAMA 62)KHIRBET TAWIL ASH SHIH 63)KHIRBET ZANUTA 64)KHURSA 65)KURZA 66)MAGHAYIR AL 'ABEED 67)MA'IN 68)MANTIQAT SHI'B AL BATIN 69)MARAH AL BAQQAR 70)NUBA 71)OM ADARAJ [ARAB AL KA’ABNEH] 72)OM AL AMAD [SAHEL WADI ELMA] 73)OM ASHOQHAN 74)QALQAS 75)QLA’A ZETA 76)RABUD 77)SA'IR 78)SHUYUKH AL 'ARRUB 79)SIKKA 80)SURIF 81)TAFFUH 82)TARQUMIYA 83)TARRAMA 84)UM AL-KHAIR 85)UMM AL BUTM 86)UMM LASAFA 87)WADI AL AMAYER 88)WADI AL KILAB 89)WADI ASH SHAJINA 90)WADI 'UBEID 91)YATTA 92)ZIF 93)DON'T KNOW 94)REFUSED | E26: =LEN(D26) -> 1578 | F26: حالياً، في أي تجمع سكاني [قرية/بلدة/مدينة] تقيم أسرتك؟ [المشغل: استجابة واحدة.] 1)عناب الكبير 2)الديرات 3)الظاهرية 4)مخيم العروب 5)البقعة 6)البويرة [عقبة انجيله] 7)البرج 8)البويب 9)مخيم الفوار 10)الحيلة 11)الكرمل 12)المجد 13)النَجادَة 14)الرماضين 15)الريحية 16)عرب الفريجات 17)السموع 18)الصرة 19)الشيوخ 20)التواني 21)بني نعيم 22)بيت عمرة 23)بيت الرش الفوقا 24)بيت الرش التحتا 25)بيت عوا 26)بيت عينون 27)بيت كاحل 28)بيت مقدوم 29)بيت مرسم 30)بيت أولا 31)بيت أومر 32)دير العسل الفوقا 33)دير العسل التحتا 34)دير رازح 35)دير سامت 36)دورا 37)فقيقيس 38)هدب العلقة 39)هدب الفوار 40)حلحول 41)حمروش 42)الخليل 43)حتا 44)إذنا 45)إِمنيزِل 46)إمريش 47)جالا 48)كرمة 49)خلة العقد 50)خلة المية 51)خلة المسافر 52)خلة الدار 53)خلة صالح 54)خاراس 55)خشم درج [الهذالين] 56)خيروشيوش والحديدية 57)خربة الدير 58)خربة الفخيت 59)خربة اصفي 60)خربة بير العد 61)خربة سلامة 62)خربة طويل الشيح 63)خربة زنوتة 64)خرسا 65)كرزه 66)مغاير العبيد 67)معين 68)منطقة شعب الباطن 69)مراح البقار 70)النوبة 71)أم الدرج [عرب الكعابنة] 72)أم العمد [ساحل وادي الماء] 73)أم الشقحان 74)قلقس 75)قلعة زيتا 76)رابود 77)سعير 78)شيوخ العروب 79)سكة 80)صوريف 81)تفوح 82)ترقوميا 83)طرّامة 84)ام الخير 85)أم البطم 86)أم لصفا 87)وادي العماير 88)وادي الكلاب 89)وادي الشاجنة 90)وادي عبيد 91)يطا 92)زيف 93) لا أعرف 94) رفض الإجابة | G26: =LEN(F26) -> 1269 | H26: Single Choice | I26: NA | J26: NA | K26: Form Type - Dropdown IsDemographic - ADM2 | L26: 1-92 = quotareached 93-94 = Ineligible | M26: NA | N26: GeoPoll [4/11/2024]: Added in translation for locality in Arabic. | O26: FAOPAL- kindly provide translation | S26: =1 -> 1 | V26: yes | Z26: 7.954999 | AA26: =IF(Z26="","",Z26*S26) -> 7.954999 | AB26: =IF(V26="yes",AA26,"") -> 7.954999
A27: =A26+1 -> 9 | B27: hh_admin2_2 | C27: hh_admin2_2 | D27: Currently, in which locality [village/town/city] does your household reside? [OPERATOR: SINGLE RESPONSE.] 1) 'AMMURIYA 2) 'ASIRA AL QIBLIYA 3) 'ASIRA ASH SHAMALIYA 4) 'ASKAR CAMP 5) 'AWARTA 6) 'AZMUT 7) 'EIN BEIT EL MA CAMP 8) 'EIN SHIBLI 9) 'EINABUS 10) 'URIF 11)AL 'AQRABANIYA 12)AL BADHAN 13)AL LUBBAN ASH SHARQIYA 14)AN NAQURA 15)AN NASSARIYA 16)AQRABA 17)AR RAJMAN 18)AS SAWIYA 19)BALATA CAMP 20)BEIT DAJAN 21)BEIT FURIK 22)BEIT HASAN 23)BEIT IBA 24)BEIT IMRIN 25)BEIT WAZAN 26)BEITA 27)BIZZARIYA 28)BURIN 29)BURQA 30)DEIR AL HATAB 31)DEIR SHARAF 32)DUMA 33)FURUSH BEIT DAJAN 34)HUWWARA 35)IJNISINYA 36)'IRAQ BURIN 37)JALUD 38)JAMMA'IN 39)JURISH 40)KAFR QALLIL 41)MADAMA 42)MAJDAL BANI FADIL 43)NABLUS 44)NISF JUBEIL 45)ODALA 46)OSARIN 47)QABALAN 48)QARYUT 49)QUSIN 50)QUSRA 51)RUJEIB 52)SABASTIYA 53)SALIM 54)SARRA 55)TALFIT 56)TALL AL KHASHABA 57)TALLUZA 58)TELL 59)YANUN 60)YASID 61)YATMA 62)ZA'TARA 63)ZAWATA 64)ZEITA JAMMA'IN 65)DON'T KNOW 66)REFUSED | E27: =LEN(D27) -> 963 | F27: حالياً، في أي تجمع سكاني [قرية/بلدة/مدينة] تقيم أسرتك؟ [المشغل: استجابة واحدة.] 1)عمورية 2)عصيرة القبلية 3)عصيرة الشمالية 4)مخيم عسكر 5)عورتا 6)عزموط 7)مخيم عين بيت الماء 8)عين شبلي 9)عينبوس 10)عوريف 11)العقربانية 12)الباذان 13)اللبن الشرقية 14)الناقورة 15)النصارية 16)عقربة 17)الرجمان 18)الساوية 19)مخيم بلاطة 20)بيت دجن 21)بيت فوريك 22)بيت حسن 23)بيت إيبا 24)بيت امرين 25)بيت وزان 26)بيتا 27)بزارية 28)بورين 29)برقة 30)دير الحطب 31)دير شرف 32)دوما 33)فروش بيت دجن 34)حوارة 35)إجنيسينيا 36)عراق بورين 37)جالود 38)جماعين 39)جوريش 40)كفر قليل 41)مادما 42)مجدل بني فاضل 43)نابلس 44)نصف جبيل 45)أودلة 46)أوصرين 47)قبلان 48)قريوت 49)قوصين 50)قصرة 51)روجيب 52)سبسطية 53)سالم 54)صرة 55)تلفيت 56)تل الخشبة 57)طلوزة 58)تل 59)يانون 60)ياصيد 61)يتما 62)زعترة 63)زواتا 64)زيتا جماعين 65) لا أعرف 66) رفض الإجابة | G27: =LEN(F27) -> 803 | H27: Single Choice | I27: NA | J27: NA | K27: Form Type - Dropdown IsDemographic - ADM2 | L27: 1-64 = quotareached 65-66 = Ineligible | M27: NA | O27: FAOPAL- kindly provide translation | S27: =1 -> 1 | V27: yes | Z27: 7.954999 | AA27: =IF(Z27="","",Z27*S27) -> 7.954999 | AB27: =IF(V27="yes",AA27,"") -> 7.954999
A28: =A27+1 -> 10 | B28: hh_admin2_3 | C28: hh_admin2_3 | D28: Currently, in which locality [village/town/city] does your household reside? [OPERATOR: SINGLE RESPONSE.] 1) 'ABUD 2) 'ABWEIN 3) 'AJJUL 4) 'ATARA 5) 'EIN QINIYA 6) 'EIN YABRUD 7)ABU QASH 8)AL AM'ARI CAMP 9)AL BIREH 10)AL JALAZUN CAMP 11)AL JANIYA 12)AL LUBBAN AL GHARBI 13)AL MAZRA'A ASH SHARQIYA 14)AL MIDYA 15)AL MUGHAYYIR 16)AL-DOHA 17)AL-ITIHAD 18)AL-ZAYTOUNEH 19)AN NABI SALIH 20)AT TAYBA 21)AT TIRA 22)BADIW AL MU'ARRAJAT 23)BANI ZEID 24)BANI ZEID ASH SHARQIYA 25)BEIT LIQYA 26)BEIT NUBA 27)BEIT SIRA 28)BEIT 'UR AL FAUQA 29)BEIT 'UR AT TAHTA 30)BEITIN 31)BEITUNIYA 32)BIL'IN 33)BIR ZEIT 34)BUDRUS 35)BURHAM 36)BURQA 37)DEIR ABU MASH'AL 38)DEIR 'AMMAR CAMP 39)DEIR AS SUDAN 40)DEIR DIBWAN 41)DEIR IBZI' 42)DEIR JARIR 43)DEIR NIDHAM 44)DEIR QADDIS 45)DURA AL QAR' 46)'EIN 'ARIK 47)'EIN SINIYA 48)JIBIYA 49)JIFNA 50)JILIJLIYA 51)KAFR 'EIN 52)KAFR MALIK 53)KAFR NI'MA 54)KHARBATHA AL MISBAH 55)KHARBATHA BANI HARITH 56)KHIRBET ABU FALAH 57)KOBAR 58)NI'LIN 59)QADDURA CAMP 60)QARAWAT BANI ZEID 61)QIBYA 62)RAMALLAH 63)RAMMUN 64)RANTIS 65)RAS KARKAR 66)SAFFA 67)SHABTIN 68)SHUQBA 69)SILWAD 70)SILWAD CAMP 71)SINJIL 72)SURDA 73)TURMUS'AYYA 74)UMM SAFA 75)YABRUD 76)DON'T KNOW 77)REFUSED | E28: =LEN(D28) -> 1189 | F28: حالياً، في أي تجمع سكاني [قرية/بلدة/مدينة] تقيم أسرتك؟ [المشغل: استجابة واحدة.] 1)عابود 2)عبوين 3)عجول 4)عطارة 5)عين قينيا 6)عين يبرود 7)ابو قش 8)مخيم الأمعري 9)البيرة 10)مخيم الجلزون 11)الجانية 12)اللبن الغربي 13)المزرعة الشرقية 14)المدية 15)المغير 16)الدوحة 17)الاتحاد 18)الزيتونة 19)النبي صالح 20)الطيبة 21)الطيرة 22)بدو المعرّجات 23)بني زيد 24)بني زيد الشرقية 25)بيت لقيا 26)بيت نوبا 27)بيت سيرا 28)بيت عور الفوقا 29)بيت عور التحتا 30)بيتين 31)بيتونيا 32)بلعين 33)بير زيت 34)بدرس 35)برهام 36)برقة 37)دير أبو مشعل 38)مخيم دير عمار 39)دير السودان 40)دير دبوان 41)دير ابزيع 42)دير جرير 43)دير نظام 44)دير قديس 45)دورا القرع 46)عين عريك 47)عين سينيا 48)جيبيا 49)جفنا 50)جليليا 51)كفر عين 52)كفر مالك 53)كفر نعمة 54)خربثا المصباح 55)خربثا بني حارث 56)خربة ابو فلاح 57)كوبر 58)نعلين 59)مخيم قدورة 60)قراوة بني زيد 61)قبية 62)رام الله 63)رمون 64)رنتيس 65)رأس كركر 66)صفا 67)شبتين 68)شقبة 69)سلواد 70)مخيم سلواد 71)سنجل 72)سردا 73)ترمسعيا 74)أم صفا 75)يبرود 76) لا أعرف 77) رفض الإجابة | G28: =LEN(F28) -> 984 | H28: Single Choice | I28: NA | J28: NA | K28: Form Type - Dropdown IsDemographic - ADM2 | L28: 1-75 = quotareached 76-77 = Ineligible | M28: NA | O28: FAOPAL- kindly provide translation | S28: =1 -> 1 | V28: yes | Z28: 7.954999 | AA28: =IF(Z28="","",Z28*S28) -> 7.954999 | AB28: =IF(V28="yes",AA28,"") -> 7.954999
A29: =A28+1 -> 11 | B29: hh_admin2_4 | C29: hh_admin2_4 | D29: Currently, in which locality [village/town/city] does your household reside? [OPERATOR: SINGLE RESPONSE.] 1)AZ ZAWIYA 2)BIDDYA 3)BRUQIN 4)DEIR BALLUT 5)DEIR ISTIYA 6)FARKHA 7)HARIS 8)ISKAKA 9)'IZBAT ABU ADAM 10)KAFR AD DIK 11)KHIRBET QEIS 12)KIFL HARIS 13)MARDA 14)MAS-HA 15)QARAWAT BANI HASSAN 16)QIRA 17)RAFAT 18)SALFIT 19)SARTA 20)YASUF 21)DON'T KNOW 22)REFUSED | E29: =LEN(D29) -> 367 | F29: حالياً، في أي تجمع سكاني [قرية/بلدة/مدينة] تقيم أسرتك؟ [المشغل: استجابة واحدة.] 1)الزاوية 2)بديا 3)بروقين 4)دير بلوط 5)دير استيا 6)فرخة 7)حارس 8)إسكاكا 9)عِزْبِة أبو آدَم 10)كفر الديك 11)خربة قيس 12)كفل حارث 13)مردة 14)مسحة 15)قراوة بني حسان 16)قيرة 17)رافات 18)سلفيت 19)سرطة 20)ياسوف 21) لا أعرف 22) رفض الإجابة | G29: =LEN(F29) -> 315 | H29: Single Choice | I29: NA | J29: NA | K29: Form Type - Dropdown IsDemographic - ADM2 | L29: 1-20 = quotareached 21-22 = Ineligible | M29: NA | O29: FAOPAL- kindly provide translation | S29: =1 -> 1 | V29: yes | Z29: 7.954999 | AA29: =IF(Z29="","",Z29*S29) -> 7.954999 | AB29: =IF(V29="yes",AA29,"") -> 7.954999
A30: =A29+1 -> 12 | B30: hh_admin2_5 | C30: hh_admin2_5 | D30: Currently, in which locality [village/town/city] does your household reside? [OPERATOR: SINGLE RESPONSE.] 1)AD DOHA 2)AD DUHEISHA CAMP 3)AL 'AZA CAMP 4)AL HADDADIYA 5)AL JAB'A 6)AL KHADR 7)AL KHAS 8)AL MANIYA 9)AL MANSHIYA 10)AL MA'SARA 11)AL 'UBEIDIYA 12)AL WALAJA 13)'ARAB AR RASHAYIDA 14)ARTAS 15)ASH SHAWAWRA 16)'AYDA CAMP 17)BATTIR 18)BEIT FAJJAR 19)BEIT JALA 20)BEIT SAHUR 21)BEIT TA'MIR 22)BETHLEHEM [BEIT LAHM] 23)BIR ONAH 24)DAR SALAH 25)HINDAZA 26)HUSAN 27)JANNATAH 28)JUBBET ADH DHIB 29)JURAT ASH SHAM'A 30)KHALLET 'AFANA 31)KHALLET AL HADDAD 32)KHALLET AL LOUZA 33)KHALLET AN NU'MAN 34)KHALLET HAMAMEH 35)KHALLET SAKARIYA 36)KISAN 37)MARAH MA'ALLA 38)MARAH RABAH 39)NAHHALIN 40)TUQU' 41)UMM SALAMUNA 42)WADI AN NIS 43)WADI FUKIN 44)WADI RAHHAL 45)ZA'TARA 46)DON'T KNOW 47)REFUSED | E30: =LEN(D30) -> 795 | F30: حالياً، في أي تجمع سكاني [قرية/بلدة/مدينة] تقيم أسرتك؟ [المشغل: استجابة واحدة.] 1)الدوحة 2)مخيم الدهيشة 3)مخيم العزة 4)الحدادية 5)الجبعة 6)الخضر 7)الخاص 8)المنية 9)المنشية 10)المعصرة 11)العبيدية 12)الولجة 13)عرب الرشايدة 14)ارطاس 15)الشواورة 16)مخيم عايدة 17)بتير 18)بيت فجار 19)بيت جالا 20)بيت ساحور 21)بيت تعمر 22)بيت لحم 23)بئر عونة 24)دار صلاح 25)هندازة 26)حوسان 27)جناتة 28)جبة الديب 29)جورة الشمة 30)خلة عفانة 31)خلة الحداد 32)خلة اللوزة 33)خلة النعمان 34)خلة حمامة 35)خلة سكاريا 36)كيسان 37)مرح معلا 38)مراح رباح 39)نحالين 40)تقوع 41)أم سلمونة 42)وادي النيص 43)وادي فوكين 44)وادي رحال 45)زعترة 46) لا أعرف 47) رفض الإجابة | G30: =LEN(F30) -> 632 | H30: Single Choice | I30: NA | J30: NA | K30: Form Type - Dropdown IsDemographic - ADM2 | L30: 1-45 = quotareached 46-47 = Ineligible | M30: NA | O30: FAOPAL- kindly provide translation | S30: =1 -> 1 | V30: yes | Z30: 7.954999 | AA30: =IF(Z30="","",Z30*S30) -> 7.954999 | AB30: =IF(V30="yes",AA30,"") -> 7.954999
A31: =A30+1 -> 13 | B31: hh_admin2_6 | C31: hh_admin2_6 | D31: Currently, in which locality [village/town/city] does your household reside? [OPERATOR: SINGLE RESPONSE.] 1) 'ARABBUNA 2)'ABA 3)'AJJA 4)AL 'ARAQA 5)AL 'ASA'ASA 6)AL 'ATTARA 7)AL FANDAQUMIYA 8)AL HAFIRA 9)AL HASHIMIYA 10)AL JALAMA 11)AL JAMEELAT 12)AL JARBA 13)AL JUDEIDA 14)AL KHULJAN 15)AL KUFEIR 16)AL MANSURA 17)AL MUGHAYYIR 18)AL MUTILLA 19)AL YAMUN 20)'ANIN 21)'ANZA 22)AR RAMA 23)ARRABA 24)'ARRANA 25)AS SA'AIDA 26)ASH SHUHADA 27)AT TAREM 28)AT TAYBA 29)AZ ZABABIDA 30)AZ ZAWIYA 31)BARTA'A ASH SHARQIYA 32)BEIT QAD 33)BIR AL BASHA 34)BIRQIN 35)DEIR ABU DA'IF 36)DEIR GHAZALA 37)DHAHER AL 'ABED 38)DHAHER AL MALIH 39)FAHMA 40)FAHMA AL JADIDA 41)FAQQU'A 42)IMREIHA 43)JABA' 44)JALBUN 45)JALQAMUS 46)JENIN 47)JENIN CAMP 48)KAFR DAN 49)KAFR QUD 50)KAFR RA'I 51)KHIRBET 'ABDALLAH AL YUNIS 52)KHIRBET AL MUNTAR AL GHARBIYA 53)KHIRBET AL MUNTAR ASH SHARQIYA 54)KHIRBET MAS'UD 55)KHIRBET SURUJ 56)KUFEIRIT 57)MEITHALUN 58)MIRKA 59)MISLIYA 60)NAZLAT ASH SHEIKH ZEID 61)QABATIYA 62)RABA 63)RUMMANA 64)SANUR 65)SILAT ADH DHAHR 66)SILAT AL HARITHIYA 67)SIR 68)SIRIS 69)TELFIT 70)TI'INNIK 71)TURA AL GHARBIYA 72)TURA ASH SHARQIYA 73)UMM AR RIHAN 74)UMM AT TUT 75)UMM DAR 76)WAD AD DABI' 77)WADI DU'OQ 78)YA'BAD 79)ZABDA 80)ZUBUBA 81)DON'T KNOW 82)REFUSED | E31: =LEN(D31) -> 1256 | F31: حالياً، في أي تجمع سكاني [قرية/بلدة/مدينة] تقيم أسرتك؟ [المشغل: استجابة واحدة.] 1)عربّونة 2)عابا 3)عجّه 4)العرقة 5)العصاعصة 6)العطارة 7)الفندقومية 8)الحفيرة 9)الهاشمية 10)الجلمة 11)الجميلات 12)الجربا 13)الجديدة 14)الخلجان 15)الكفير 16)المنصورة 17)المغير 18)المطلة 19)اليامون 20)عنين 21)عنزة 22)الرامة 23)عرّابة 24)عرّانه 25)السعايدة 26)الشهداء 27)الطرم 28)الطيبه 29) الزبابدة 30)الزاوية 31)برطعة الشرقية 32)بيت قاد 33)بئر الباشا 34)برقين 35)دير أبو ضعيف 36)دير غزالة 37)ظهر العبد 38)ظهر المالح 39)فحمة 40)فهمة الجديدة 41)فقوعة 42)إمريحة 43)جبع 44)جلبون 45)جلقموس 46)جنين 47)مخيم جنين 48)كفر دان 49)كفر قود 50)كفر راعي 51)خربة عبد الله اليونس 52)خربة المنطار الغربية 53)خربة المنطار الشرقية 54)خربة مسعود 55)خربة سروج 56)كفيرت 57)ميثالون 58)ميركا 59)مسلية 60)نزلة الشيخ زيد 61)قباطية 62)رابا 63)رمّانة 64)سانور 65)سيلة الظهر 66)سيلة الحارثية 67)سير 68)سيريس 69)تلفيت 70)تعنّك 71)طورة الغربية 72)طورة الشرقية 73)ام الريحان 74)أم التوت 75)أم دار 76)واد الضبع 77)وادي دْعُوق 78)يعبد 79)زبدة 80)زبوبا 81) لا أعرف 82) رفض الإجابة | G31: =LEN(F31) -> 1030 | H31: Single Choice | I31: NA | J31: NA | K31: Form Type - Dropdown IsDemographic - ADM2 | L31: 1-80 = quotareached 81-82 = Ineligible | M31: NA | O31: FAOPAL- kindly provide translation | S31: =1 -> 1 | V31: yes | Z31: 7.954999 | AA31: =IF(Z31="","",Z31*S31) -> 7.954999 | AB31: =IF(V31="yes",AA31,"") -> 7.954999
A32: =A31+1 -> 14 | B32: hh_admin2_7 | C32: hh_admin2_7 | D32: Currently, in which locality [village/town/city] does your household reside? [OPERATOR: SINGLE RESPONSE.] 1)AL 'AUJA 2)AL JIFTLIK 3)AN NABI MUSA 4)AN NUWEI'MA 5)AQBAT JABER CAMP 6)AZ ZUBEIDAT 7)DEIR AL QILT 8)DEIR HAJLA 9)'EIN AD DUYUK AL FAUQA 10)'EIN AS SULTAN CAMP 11)FASAYIL 12)JERICHO [ARIHA] 13)MARJ AL GHAZAL 14)MARJ NA'JA 15)DON'T KNOW 16)REFUSED | E32: =LEN(D32) -> 358 | F32: حالياً، في أي تجمع سكاني [قرية/بلدة/مدينة] تقيم أسرتك؟ [المشغل: استجابة واحدة.] 1)العوجا 2)الجفتلك 3)النبي موسى 4)النويعمة 5)مخيم عقبة جبر 6)الزبيدات 7)دير القلط 8)دير حجلة 9)عين الديوك الفوقا 10) مخيم عين السلطان 11)فصايل 12)أريحا 13)مرج الغزال 14)مرج نعجة 15) لا أعرف 16) رفض الإجابة | G32: =LEN(F32) -> 288 | H32: Single Choice | I32: NA | J32: NA | K32: Form Type - Dropdown IsDemographic - ADM2 | L32: 1-14 = quotareached 15-16 = Ineligible | M32: NA | O32: FAOPAL- kindly provide translation | S32: =1 -> 1 | V32: yes | Z32: 7.954999 | AA32: =IF(Z32="","",Z32*S32) -> 7.954999 | AB32: =IF(V32="yes",AA32,"") -> 7.954999
A33: =A32+1 -> 15 | B33: hh_admin2_8 | C33: hh_admin2_8 | D33: Currently, in which locality [village/town/city] does your household reside? [OPERATOR: SINGLE RESPONSE.] 1) 'ARAB AL JAHALIN 2)ABU DIS 3)AL 'EIZARIYA 4)AL 'ISAWIYA 5)AL JIB 6)AL JUDEIRA 7)AL KA'ABINA [TAJAMMU' BADAWI] 8)AL QUBEIBA 9)AN NABI SAMWIL 10)'ANATA 11)AR RAM & DAHIYAT AL BAREED 12)AS SAWAHIRA AL GHARBIYA 13)AS SAWAHIRA ASH SHARQIYA 14)ASH SHEIKH SA'D 15)ATH THURI 16)AZ ZA'AYYEM 17)BEIT 'ANAN 18)BEIT DUQQU 19)BEIT HANINA 20)BEIT HANINA AL BALAD 21)BEIT IJZA 22)BEIT IKSA 23)BEIT SAFAFA 24)BEIT SURIK 25)BIDDU 26)BIR NABALA 27)HIZMA 28)JABA' 29)JABA' [TAJAMMU' BADAWI] 30)JABAL AL MUKABBIR 31)JERUSALEM [AL QUDS] 32)KAFR 'AQAB 33)KHARAYIB UMM AL LAHIM 34)MIKHMAS 35)QALANDIYA 36)QALANDIYA CAMP 37)QATANNA 38)RAFAT 39)SHARAFAT 40)SHU'FAT 41)SHU'FAT CAMP 42)SILWAN 43)SUR BAHIR 44)UMM TUBA 45)DON'T KNOW 46)REFUSED | E33: =LEN(D33) -> 827 | F33: حالياً، في أي تجمع سكاني [قرية/بلدة/مدينة] تقيم أسرتك؟ [المشغل: استجابة واحدة.] 1)عرب الجهالين 2)ابو ديس 3)العيزرية 4)العيسوية 5)الجيب 6)الجديرة 7)الكعابنة [تجمع البدوي] 8)القبيبة 9)النبي صموئيل 10)عناتا 11)الرام وضاحية البريد 12)السواحرة الغربية 13)السواحرة الشرقية 14)الشيخ سعد 15)الثوري 16)الزعيّم 17)بيت عنان 18)بيت دقو 19)بيت حنينا 20)بيت حنينا البلد 21)بيت اجزا 22)بيت اكسا 23)بيت صفافا 24)بيت سوريك 25)بدو 26)بير نبالا 27)حزما 28)جبع 29)جبع [التجمع البدوي] 30)جبل المكبر 31)القدس 32)كفر عقب 33)خَرائِب أمُّ اللَحْمْ 34)مخماس 35)قلنديا 36)مخيم قلنديا 37)قطنة 38)رافات 39)شرفات 40)شعفاط 41)مخيم شعفاط 42)سلوان 43)صور باهر 44)أم توبا 45) لا أعرف 46) رفض الإجابة | G33: =LEN(F33) -> 668 | H33: Single Choice | I33: NA | J33: NA | K33: Form Type - Dropdown IsDemographic - ADM2 | L33: 1-44 = quotareached 45-46 = Ineligible | M33: NA | O33: FAOPAL- kindly provide translation | S33: =1 -> 1 | V33: yes | Z33: 7.954999 | AA33: =IF(Z33="","",Z33*S33) -> 7.954999 | AB33: =IF(V33="yes",AA33,"") -> 7.954999
A34: =A33+1 -> 16 | B34: hh_admin2_9 | C34: hh_admin2_9 | D34: Currently, in which locality [village/town/city] does your household reside? [OPERATOR: SINGLE RESPONSE.] 1) 'ARAB ABU FARDA 2) 'ARAB AR RAMADIN AL JANUBI 3) 'ARAB AR RAMADIN ASH SHAMALI 4) 'ISLA 5) 'IZBAT AL ASHQAR 6) 'IZBAT AT TABIB 7) 'IZBAT JAL'UD 8)AD DAB'A 9)AL FUNDUQ 10)AL MUDAWWAR 11)AN NABI ELYAS 12)ARAB AL-KHOULEH 13)'AZZUN 14)'AZZUN 'ATMA 15)BAQAT AL HATAB 16)BEIT AMIN 17)FALAMYA 18)FAR'ATA 19)HABLA 20)HAJJA 21)IMMATIN 22)'IZBAT SALMAN 23)JAYYUS 24)JINSAFUT 25)JIT 26)KAFR LAQIF 27)KAFR QADDUM 28)KAFR THULTH 29)KHIRBET SIR 30)QALQILIYA 31)RAS AT TIRA 32)RAS 'ATIYA 33)SANNIRIYA 34)WADI AR RASHA 35)DON'T KNOW 36)REFUSED | E34: =LEN(D34) -> 638 | F34: حالياً، في أي تجمع سكاني [قرية/بلدة/مدينة] تقيم أسرتك؟ [المشغل: استجابة واحدة.] 1)عرب أبو فردة 2)عَرَب الرَماضِين الجَنُوبي 3)عرب الرماضين الشّمالي 4)عسلة 5)عزبة الأشقر 6)عزبة الطبيب 7)عِزْبَة جَالود 8)الضبعة 9)الفندق 10)المدوّر 11)النبي الياس 12)عرب الخولي 13)عزون 14)عزون عتمة 15)باقة الحطب 16)بيت أمين 17)فلامية 18)فرعتا 19)حبلة 20)حجة 21)إيماتين 22)عزبة سلمان 23)جيوس 24)جينسافوط 25)جيت 26)كفر لاقف 27)كفر قدوم 28)كفر ثلث 29)خربة صير 30)قلقيلية 31)راس الطيرة 32)رأس عطية 33)سنيريا 34)وادي الرشا 35) لا أعرف 36) رفض الإجابة | G34: =LEN(F34) -> 529 | H34: Single Choice | I34: NA | J34: NA | K34: Form Type - Dropdown IsDemographic - ADM2 | L34: 1-34 = quotareached 35-36 = Ineligible | M34: NA | O34: FAOPAL- kindly provide translation | S34: =1 -> 1 | V34: yes | Z34: 7.954999 | AA34: =IF(Z34="","",Z34*S34) -> 7.954999 | AB34: =IF(V34="yes",AA34,"") -> 7.954999
A35: =A34+1 -> 17 | B35: hh_admin2_10 | C35: hh_admin2_10 | D35: Currently, in which locality [village/town/city] does your household reside? [OPERATOR: SINGLE RESPONSE.] 1)A’QQABA 2)AL A’QABA 3)AL FARISIYA 4)AL HADIDIYA 5)AL MALIH 6)BARDALA 7)'EIN EL BEIDA 8)EL FARA’A CAMP 9)IBZIQ 10)KARDALA 11)KHIRBET A’TUF 12)RAS AL FAR'A 13)SALHAB 14)TAMMUN 15)TAYASIR 16)TUBAS 17)WADI AL FARA’A 18)DON'T KNOW 19)REFUSED | E35: =LEN(D35) -> 347 | F35: حالياً، في أي تجمع سكاني [قرية/بلدة/مدينة] تقيم أسرتك؟ [المشغل: استجابة واحدة.] 1) العقبة 2) العقبة 3) الفارسية 4) الحديدية 5) المالح 6)بردلة 7) عين البيضاء 8) مخيم الفارعة 9) إبزيق 10) كردلة 11) خربة عاطوف 12) رأس الفارعة 13) سلحب 14) طمّون 15) تياسير 16) طوباس 17) وادي الافرعة 18) لا أعرف 19) رفض الإجابة | G35: =LEN(F35) -> 310 | H35: Single Choice | I35: NA | J35: NA | K35: Form Type - Dropdown IsDemographic - ADM2 | L35: 1-17 = quotareached 18-19 = Ineligible | M35: NA | S35: =1 -> 1 | V35: yes | Z35: 7.954999 | AA35: =IF(Z35="","",Z35*S35) -> 7.954999 | AB35: =IF(V35="yes",AA35,"") -> 7.954999
A36: =A34+1 -> 17 | B36: hh_admin2_11 | C36: hh_admin2_11 | D36: Currently, in which locality [village/town/city] does your household reside? [OPERATOR: SINGLE RESPONSE.] 1) 'AKKABA 2)AL HAFFASI 3)AL JARUSHIYA 4)AL MASQUFA 5)AN NAZLA AL GHARBIYA 6)AN NAZLA AL WUSTA 7)AN NAZLA ASH SHARQIYA 8)ANABTA 9)AR RAS 10)'ATTIL 11)BAL'A 12)BAQA ASH SHARQIYA 13)BEIT LID 14)DEIR AL GHUSUN 15)FAR'UN 16)IKTABA 17)'ILLAR 18)KAFA 19)KAFR 'ABBUSH 20)KAFR AL LABAD 21)KAFR JAMMAL 22)KAFR SUR 23)KAFR ZIBAD 24)KHIRBET JUBARA 25)KUR 26)NAZLAT 'ISA 27)NUR SHAMS CAMP 28)QAFFIN 29)RAMIN 30)SAFFARIN 31)SEIDA 32)SHUFA 33)TULKARM CAMP 34)TULKARM 35)ZEITA 36)DON'T KNOW 37)REFUSED | E36: =LEN(D36) -> 599 | F36: حالياً، في أي تجمع سكاني [قرية/بلدة/مدينة] تقيم أسرتك؟ [المشغل: استجابة واحدة.] 1)العقبة 2)الحفاصي 3)الجاروشية 4)المسقوفة 5)النزلة الغربية 6)النزلة الوسطى 7)النزلة الشرقية 8)عنبتا 9)الراس 10)عتيل 11)بلعة 12)باقة الشرقية 13)بيت ليد 14)دير الغصون 15)فرعون 16)إكتابا 17)عيلار 18)كفا 19)كفر عبوش 20)كفر اللبد 21)كفر جمال 22)كفر صور 23)كفر زيباد 24)خربة جبارة 25)كور 26)نزلة عيسى 27)مخيم نور شمس 28)قفين 29)رامين 30)سفارين 31)صيدا 32)شوفة 33)مخيم طولكرم 34)طولكرم 35)زيتا 36) لا أعرف 37) رفض الإجابة | G36: =LEN(F36) -> 497 | H36: Single Choice | I36: NA | J36: NA | K36: Form Type - Dropdown IsDemographic - ADM2 | L36: 1-35 = quotareached 36-37 = Ineligible | M36: NA | O36: FAOPAL- kindly provide translation | S36: =1 -> 1 | V36: yes | Z36: 7.954999 | AA36: =IF(Z36="","",Z36*S36) -> 7.954999 | AB36: =IF(V36="yes",AA36,"") -> 7.954999
A37: =A36+1 -> 18 | B37: quotareached | C37: quotareached | D37: [OPERATOR: DO NOT READ. ANSWER QUESTION BELOW.] THIS RESPONDENT REPORTED THEY LIVE IN: {ADM1} {ADM2} 1)THE GOAL FOR THIS LOCATION HAS BEEN ACHIEVED - END SURVEY 2)THE GOAL FOR THIS LOCATION IS OPEN - CONTINUE SURVEY | E37: =LEN(D37) -> 218 | F37: [المُشغل: لا تقرأ. أجب على السؤال أدناه.] أبلغ هذا المجيب أنه يعيش في: {ADM1} {ADM2} 1) تم تحقيق الهدف لهذا الموقع - إنه الاستبيان 2) لا يزال يتعين تحقيق الهدف لهذا الموقع - تابع الاستبيان | G37: =LEN(F37) -> 191 | H37: Single Choice | I37: NA | J37: NA | K37: Form Type - Buttons | L37: 1 = End Poll Quota Reached 2 = o_hh_area | M37: NA
A38: =A37+1 -> 19 | B38: o_hh_area | C38: o_hh_area | D38: In which area are you located? [OPERATOR: READ OUT THE OPTIONS. SINGLE RESPONSE.] 1)Area A / B 2)Area C 3)DON'T KNOW 4)REFUSED | E38: =LEN(D38) -> 128 | F38: ما هو تصنيف المنطقعه التي تسكن فيها؟ [المُشغل: اقرأ خيارات الإجابة. استجابة واحدة.] 1) مناطق ألف أو مناطق باء 2)مناطق ج 3)لا أعلم 4)رفض الإجاب’ | G38: =LEN(F38) -> 148 | H38: Single Choice | I38: NA | J38: NA | K38: Form Type - Buttons | L38: 1-4 = hh_agricactivity | M38: NA | Q38: 1-4 = hh_agricactivity | S38: =1 -> 1 | V38: no | Z38: 13.220665 | AA38: =IF(Z38="","",Z38*S38) -> 13.220665 | AB38: =IF(V38="yes",AA38,"")
A39: =A38+1 -> 20 | B39: hh_agricactivity | C39: hh_agricactivity | D39: Has anybody in your household produced crops or livestock for household consumption or for sale in the past 12 months, including household members currently away for transhumance? [OPERATOR: SINGLE RESPONSE. THIS IS THE MAIN SCREENING QUESTION.] [HINT FOR PROBING: Do you cultivate any plants to sale or consume? Do you raise any animals with the intent of selling or consuming them or their products like meat, milk, wool or leather? Is one of your household member currently away with cattle or other animals for transhumance?] 1)Yes - crop production 2)Yes - livestock production 3)Yes - both crop and livestock production 4)No 5)DON'T KNOW 6)REFUSED | E39: =LEN(D39) -> 655 | F39: هل قام أي شخص في أسرتك بإنتاج المحاصيل أو تربية الماشية للاستهلاك المنزلي أو للبيع خلال الاثني عشر شهرًا الماضية ، بما في ذلك أفراد الأسرة الغير موجودين بغرض التنقل الرعوي؟ [المشغل: استجابة واحدة. هذا هو سؤال الفرز الرئيسي.] [ملحوظة للتحقيق: هل قمت بزراعة أي نباتات للبيع أو الاستهلاك ؟ هل قمت بتربية أي حيوانات بنية البيع أو الاستهلاك أو انتاج منتجات مثل اللحوم و الالبان و الصوف و الجلد ؟ هل أي فرد من أفراد أسرتك حاليا بعيدًا عن الأسرة مع الماشية أو حيوانات أخري بغرض التنقل الرعوي ؟] 1) نعم - إنتاج المحاصيل 2) نعم - إنتاج الماشية 3) نعم - كل من إنتاج المحاصيل والماشية 4) لا 5) لا أعرف 6) رفض الإجابة | G39: =LEN(F39) -> 607 | H39: Single Choice | I39: NA | J39: NA | K39: Form Type - Buttons | L39: 1-4 = resp_id 5-6 = Ineligible | M39: NA | N39: GeoPoll [4/11/2024]. Updated skip patterns to make any "no" responses eligible as advised. | O39: "No" responses are still eligible. These respondents should be asked all sections aside from Crop/Livestock modules. | P39: if hh_agricactivity = 1-4, go to resp_id or hh_fish. Otherwise, the respondent is ineligible. | Q39: if hh_agricactivity = 1-4, go to resp_id. Otherwise, the respondent is ineligible. | S39: =1 -> 1 | V39: yes | Z39: 24.410839 | AA39: =IF(Z39="","",Z39*S39) -> 24.410839 | AB39: =IF(V39="yes",AA39,"") -> 24.410839
A40: B. GENERAL HOUSEHOLD INFORMATION | AA40: =IF(Z40="","",Z40*S40) | AB40: =IF(V40="yes",AA40,"")
A41: =A39+1 -> 21 | B41: resp_id | C41: resp_id | D41: Are you the head of household? [OPERATOR: SINGLE RESPONSE.] 1)YES 2)NO 3)DON'T KNOW 4)REFUSED | E41: =LEN(D41) -> 96 | F41: هل أنت رب الأسرة ؟ [المشغل: استجابة واحدة.] 1) نعم 2) لا 3) لا أعرف 4) رفض الإجابة | G41: =LEN(F41) -> 84 | H41: Single Choice | I41: NA | J41: NA | K41: Form Type - Buttons | L41: 1 = hh_education 2-4 = hh_gender | M41: NA | P41: if resp_id = 1, go to hh_education. Otherwise, go to hh_gender. | S41: 1 | V41: yes | Z41: 10.5 | AA41: =IF(Z41="","",Z41*S41) -> 10.5 | AB41: =IF(V41="yes",AA41,"") -> 10.5
A42: =A41+1 -> 22 | B42: hh_gender | C42: hh_gender | D42: Is the head of your household male or female? [OPERATOR: SINGLE RESPONSE.] 1)Male 2)Female 3)DON'T KNOW 4)REFUSED | E42: =LEN(D42) -> 116 | F42: هل رب أسرتك ذكر أم أنثى؟ [المشغل: استجابة واحدة.] 1) ذكر 2) أنثى 3) لا أعرف 4) رفض الإجابة | G42: =LEN(F42) -> 92 | H42: Single Choice | I42: NA | J42: NA | K42: Form Type - Buttons | L42: 1-4 = hh_education | M42: NA | P42: if hh_gender = 1-4, go to hh_education. | S42: =1 -> 1 | V42: yes | Z42: 10.504534 | AA42: =IF(Z42="","",Z42*S42) -> 10.504534 | AB42: =IF(V42="yes",AA42,"") -> 10.504534
A43: =A42+1 -> 23 | B43: hh_education | C43: hh_education | D43: What is the educational level attained by the head of household? [OPERATOR: SINGLE RESPONSE.] 1)None or did not complete primary school 2)Completed primary school 3)Completed secondary school 4)Completed higher education [University / College] degree 5)Religious or informal education only 6)DON'T KNOW 7)REFUSED | E43: =LEN(D43) -> 314 | F43: ما هو المستوى التعليمي الذي وصل إليه رب الأسرة؟ [المشغل: استجابة واحدة.] 1)لا شيء لم يكمل المرحلة الأساسية 2) أكمل المرحلة الأساسية 3) أكمل المرحلة الثانوية 4) أكمل درجة تعليم عالي [جامعة / كلية] 5) تربية دينية أو غير رسمية فقط 6) لا أعرف 7) رفض الإجابة | G43: =LEN(F43) -> 257 | H43: Single Choice | I43: NA | J43: NA | K43: Form Type - Buttons | L43: 1-7 = o_hh_wealth_water | M43: NA | P43: if hh_education = 1-7, go to hh_wealth. | Q43: if hh_education = 1-7, go to o_hh_wealth_water | S43: =1 -> 1 | V43: yes | Z43: 12.421899 | AA43: =IF(Z43="","",Z43*S43) -> 12.421899 | AB43: =IF(V43="yes",AA43,"") -> 12.421899
A44: =A43+1 -> 24 | B44: o_hh_wealth_water | C44: hh_wealth_other | D44: What is the main source of water in the dwelling? [OPERATOR: SINGLE RESPONSE.] 1)Local public network 2)Isreali network 3)Collected rain-water wells 4)Spring 5)Tanks 6)Ground well 7)Other [specify] | E44: =LEN(D44) -> 207 | F44: ما هو المصدر الرئيسي للمياه في المنزل؟ [المشغل: استجابة واحدة.] 1)شبكة مياه العامة المحلية 2)شبكة مياه عامة إسرائيليه [ميكوروت] 3)تجميع مياه الأمطار 4)الينابيع 5)تنكات المياه المشتراه 6)آبار جوفية 7)آخر [حدد] | G44: =LEN(F44) -> 213 | H44: Open Ended-Single Choice | I44: NA | J44: NA | K44: Form Type - RadioList | L44: 1-7 = o_hh_wealth_water_drinking | M44: NA | Q44: 1-7 = o_hh_wealth_water_drinking | S44: =1 -> 1 | AA44: =IF(Z44="","",Z44*S44) | AB44: =IF(V44="yes",AA44,"")
A45: =A44+1 -> 25 | B45: o_hh_wealth_water_drinking | C45: o_hh_wealth_water_drinking | D45: What is the main source of drinking water in the dwelling? [OPERATOR: SINGLE RESPONSE.] 1)Public water network connection 2)Protected ground well/spring 3)Unprotected ground well/spring 4)Rainwater harvesting 5)Water tanker 6)Bottled water 7)Public tab water 8)Other [specify] | E45: =LEN(D45) -> 280 | F45: ما هو المصدر الرئيسي لمياه الشرب في المنزل؟ [المشغل: استجابة واحدة.] 1)شبكة المياه العامة 2)آبار المياه الجوفية أو الينابيع المحمية 3)آبار المياه الجوفية أو الينابيع غير محمية 4)تجميع مياه الأمطار 5)تنكات المياه المشتراه 6)مياه معبئة 7)صنابير المياه العامة 8)آخر [حدد] | G45: =LEN(F45) -> 277 | H45: Open Ended-Single Choice | I45: NA | J45: NA | K45: Form Type - RadioList | L45: 1-8 = o_hh_wealth_electricity | M45: NA | Q45: 1-8 = o_hh_wealth_electricity
A46: =A45+1 -> 26 | B46: o_hh_wealth_electricity | C46: o_hh_wealth_electricity | D46: What is the main source of electricity in the dwelling? [OPERATOR: SINGLE RESPONSE.] 1)Public network 2)Private generator 3)Private network 4)Solar units 5)Other [specify] 6)None | E46: =LEN(D46) -> 187 | F46: ما هو المصدر الرئيسي للكهرباء في المنزل؟ [المشغل: استجابة واحدة.] 1)الشبكة العامة 2)مولد خاص 3)شبكة خاصة 4)وحدات الطاقة الشمسية 5)آخر [حدد] 6)لا شيء | G46: =LEN(F46) -> 151 | H46: Open Ended-Single Choice | I46: NA | J46: NA | K46: Form Type - RadioList | L46: 1-6 = o_hh_wealth_toilet | M46: NA | Q46: 1-6 = o_hh_wealth_toilet
A47: =A46+1 -> 27 | B47: o_hh_wealth_toilet | C47: o_hh_wealth_toilet | D47: Does the household unit include a toilet? [OPERATOR: SINGLE RESPONSE.] 1)Yes - toilet with piped water 2)Yes - toilet without piped water 3)No toilet 4)Other [specify] | E47: =LEN(D47) -> 169 | F47: هل يوجد حمام [مرحاض] في الوحدة السكنية؟ [المشغل: استجابة واحدة.] 1)نعم، مرحاض موصول بالمياه 2)نعم، مرحاض غير موصول بالمياه 3)لا يوجد مرحاض 4)آخر [حدد] | G47: =LEN(F47) -> 153 | H47: Open Ended-Single Choice | I47: NA | J47: NA | K47: Form Type - RadioList | L47: 1-4 = hh_size | M47: NA | Q47: 1-4 = hh_size
A48: =A47+1 -> 28 | B48: hh_size | C48: hh_size | D48: How many people are part of the household? [OPERATOR: RECORD NUMBER OF MEMBERS IN HOUSEHOLD. ENTER 88 FOR DON'T KNOW & 99 FOR REFUSED.] [HINT: TO BE A PART OF THE SAME HOUSEHOLD, MEMBERS MUST LIVE UNDER THE SAME ROOF, SHARE THE SAME RESOURCES & EAT FROM THE SAME POT.] | E48: =LEN(D48) -> 269 | F48: كم عدد الأشخاص الذين هم جزء من الأسرة؟ [المُشغل: سجل عدد أعضاء الأسرة. أدخل 88 للا أعرف و 99 في حالة الرفض.] [ملحوظة: لكي يكونوا جزءًا من نفس الأسرة، يجب أن يكون جميع الاعضاء يعيشون تحت سقف منزل واحد، و يتشاركون نفس الموارد و يأكلون من نفس القدر] | G48: =LEN(F48) -> 247 | H48: Range | I48: NA | J48: NA | K48: Form Type - TextBox | L48: 1-50 = hh_maritalstat 88-88 = hh_maritalstat 99-99 = hh_maritalstat | M48: NA | P48: For any response, go to [next question] | S48: =1 -> 1 | V48: no | Z48: 16.902294 | AA48: =IF(Z48="","",Z48*S48) -> 16.902294 | AB48: =IF(V48="yes",AA48,"")
A49: =A48+1 -> 29 | B49: hh_maritalstat | C49: hh_maritalstat | D49: What is the head of household’s current marital status? [OPERATOR: SINGLE RESPONSE.] 1)Single / never married 2)Married 3)Separated 4)Divorced 5)Widowed 6)DON’T KNOW 7)REFUSED | E49: =LEN(D49) -> 180 | F49: ما هي الحالة الاجتماعية الحالية لرب الأسرة؟ [المشغل: استجابة واحدة.] 1) أعزب / لم يتزوج قط 2) متزوج 3) منفصل 4) مطلق 5) أرمل 6) لا أعرف 7) رفض الإجابة | G49: =LEN(F49) -> 152 | H49: Single Choice | I49: NA | J49: NA | K49: Form Type - Buttons | L49: 1-7 = hh_age | M49: NA | P49: For any response, go to [next question] | S49: =1 -> 1 | V49: no | Z49: 9.9618664 | AA49: =IF(Z49="","",Z49*S49) -> 9.9618664 | AB49: =IF(V49="yes",AA49,"")
A50: =A49+1 -> 30 | B50: hh_age | C50: hh_age | D50: How old is the head of household? [OPERATOR: SINGLE RESPONSE.] 1)Under 18 2)18 to 40 3)41 to 65 4)Over 65 5)DON'T KNOW 6)REFUSED | E50: =LEN(D50) -> 133 | F50: كم عمر رب الاسرة؟ [المشغل: استجابة واحدة.] 1) أقل من 18 عامًا 2) بين 18 و 40 عامًا 3) بين 41 و 65 عامًا 4) فوق 65 عامًا 5) لا أعرف 6) رفض الإجابة | G50: =LEN(F50) -> 147 | H50: Single Choice | I50: NA | J50: Send if "resp_id" "NotEqual" "YES" if not satisfied go to "income_main" | K50: Form Type - Buttons | L50: 1-6 = income_main | M50: NA | N50: GeoPoll [3/18/2024]. : Added a conditional logic here so that this question is not asked if the respondent is the head of household (resp_id), the hh age is already captured in resp_age. | O50: OK, thank you | P50: For any response, go to [next question] | S50: =1 -> 1 | V50: no | Z50: 7.0248413 | AA50: =IF(Z50="","",Z50*S50) -> 7.0248413 | AB50: =IF(V50="yes",AA50,"")
A51: C. INCOME SOURCES, LIVELIHOOD AND SHOCKS | AA51: =IF(Z51="","",Z51*S51) | AB51: =IF(V51="yes",AA51,"")
A52: =A50+1 -> 31 | B52: income_main | C52: income_main | D52: What was your household's main source of income in the past 3 months? [OPERATOR: SINGLE RESPONSE. REFUSED OPTION SHOULD BE AVOIDED AS MUCH AS POSSIBLE.] 1)Production and sale of staple crops 2)Production and sale of vegetables or fruit 3)Production and sale of cashcrops 4)Production and sale of livestock or livestock products 5)Production and sale of honey or bee products 6)Production and sale of fish or aquatic products 7)Collection and sale of forestry or bush products 8)Agricultural trade EXCLUDING producers [formal or informal] 9)Daily wage on farms and other casual employment in agricultural sector 10)Stable employment in agricultural sector 11)Non-agricultural self-employed or liberal profession / doctor / architect / lawyer / including restaurant 12)Off-farm daily wages and other non-agricultural casual employment 13)Stable employment in non-agricultural sector 14)Public employment 15)Income not derived from work / Charity 16)Income not derived from work / Welfare transfer/ pension/ humanitarian aid 17)Income not derived from work / Remittances 18)Income not derived from work / Income from other rents 19)No income source in the last 3 months and used exclusively savings / debt 20)REFUSED | E52: =LEN(D52) -> 1215 | F52: ما كان مصدر الدخل الرئيسي لأسرتك في الأشهر الثلاثة الماضية؟ [المشغل: استجابة واحدة. يجب تجنب الخيار "رفض الإجابة" قدر الإمكان.] 1) إنتاج وبيع المحاصيل الأساسية 2) إنتاج وبيع الخضار أو الفاكهة 3) إنتاج وبيع المحاصيل النقدية 4) تربية الثروة الحيوانية وانتاج وبيع منتجاتها 5) انتاج و بيع العسل أو منتجات النحل 6) إنتاج وبيع الأسماك أو منتجات المنتجات المائية 7) جمع وبيع منتجات الغابات أو الأحراش 8) التجارة الزراعية الرسمية و غير الرسمية باستثناء المنتجين 9) الأجر اليومي في المزارع وغيرها من العمالة العرضية في قطاع الزراعة 10) العمالة المستقرة في القطاع الزراعي 11) العاملين لحسابهم الخاص غير الزراعيين أو المهنة الحرة / طبيب / مهندس معماري / محامٍ / بما في ذلك مطعم 12) الأجور اليومية خارج المزرعة وغيرها من العمالة العرضية غير الزراعية 13) العمالة المستقرة في القطاع غير الزراعي 14) الوظائف العامة 15) الدخل غير المستمد من العمل / الاعمال الخيرية 16) الدخل غير المستمد من العمل / المدفوعات التحويلية ، المعاش التقاعدي ، المساعدات الإنسانية 17) الدخل غير المستمد من العمل / التحويلات 18) الدخل غير المستمد من العمل / الدخل من الإيجارات الأخرى 19) لم يكن هناك مصدر دخل خلال الأشهر الثلاثة الماضية واستخدمت المدخرات أو الدين حصريًا 20) رفض الإجابة | G52: =LEN(F52) -> 1150 | H52: Single Choice | I52: NA | J52: NA | K52: Form Type - Buttons IsDemographic - income_main | L52: 1-18 = income_main_amount 19-20 = shock | M52: NA | P52: if options #1-3 selected go to income_main_crop_check if options #4 selected go to income_main_ls_check if options #6 selected go to income_main_fish_check if options #5, 7-18 selected, go to [income_main_comp OR optional question] if options #19-20 selected, go to shock | Q52: if options #1-14, 16-19 selected, go to income_main_amount if options #15 selected, go to o_income_main_previous if options #20-21 selected, go to shock | S52: =1 -> 1 | V52: yes | Z52: 31.888334 | AA52: =IF(Z52="","",Z52*S52) -> 31.888334 | AB52: =IF(V52="yes",AA52,"") -> 31.888334
A53: =A52+1 -> 32 | B53: income_main_amount | C53: income_main_amount | D53: How much was earned [in NIS] from your main income source, {income_main}, in the past 3 months ? [OPERATOR: MAKE SURE THE INFORMATION IS RECORDED IN THE CORRECT CURRENCY. ENTER 8888888 FOR DON'T KNOW AND 9999999 FOR REFUSED.] | E53: =LEN(D53) -> 226 | F53: ما المبلغ الذي كسبته أسرتك [بالعملة شيكل] من مصدر دخلها الرئيسي ، {income_main} ، في الأشهر الثلاثة الماضية؟ [المُشغل: تأكد من تسجيل المعلومات بالعملة الصحيحة. أدخل 8888888 للا أعرف و 9999999 في حالة الرفض.] | G53: =LEN(F53) -> 208 | H53: Range | I53: NA | J53: NA | K53: Form Type - TextBox IsDemographic - income_main_amount | L53: 300 - 4000 = income_main_gender 4001 - 1500000 = income_main_amount_conf 8888888-8888888 = income_main_gender 9999999-9999999 = income_main_gender | M53: NA | N53: GeoPoll [3/18/2024]. Kindly help confirm the appropriate value constraints in column L. | O53: Confirmed, thanks | P53: If the income amount is over the threshold set in "Additional information", the respondent will be asked to confirm with income_main_amount_conf. Otherwise, go to income_main_comp or optional question. | Q53: If the income amount is over the threshold set in "Additional information", the respondent will be asked to confirm with income_main_amount_conf. Otherwise, go to income_main_gender | S53: =1 -> 1 | V53: no | Z53: 31.963766 | AA53: =IF(Z53="","",Z53*S53) -> 31.963766 | AB53: =IF(V53="yes",AA53,"")
A54: =A53+1 -> 33 | B54: income_main_amount_conf | C54: income_main_amount_conf | D54: Can you confirm the amount of income you just stated of {income_main_amount} NIS is correct? [OPERATOR: IF THE AMOUNT EARNED FROM THIS INCOME SOURCE OVER THE PAST 3 MONTH IS INDEED OVER 4000 NIS, CLICK ON CONTINUE. OTHERWISE, GO BACK AND CHANGE THE AMOUNT ENTERED.] 1)CONTINUE | E54: =LEN(D54) -> 278 | F54: هل يمكنك تأكيد مبلغ الدخل {income_main_amount} [بالعملة شيكل] الذي ذكرته للتو؟ [المُشغل: إذا كان المبلغ المكتسب من مصدر الدخل هذا خلال الأشهر الثلاثة الماضية أكثر من 4000 شيكل ، انقر على "تابع". بخلاف ذلك ، الرجاء الرجوع وتغيير المبلغ الذي تم إدخاله.] 1) تابع | G54: =LEN(F54) -> 262 | H54: Single Choice | I54: NA | J54: NA | K54: Form Type - Buttons | L54: 1 = income_main_gender | M54: NA | N54: GeoPoll [3/18/2024]. Added additional text in English so the question will directly reference the value provided at income_main_amount. If in agreement, kindly support with the translations. | O54: Ok for the English text. FAOPAL - kindly provide translation | P54: if income_main_amount_conf = 1, go to income_main_comp or optional question | Q54: if income_main_amount_conf = 1, go to income_main_gender | S54: =1 -> 1 | V54: no | Z54: 2.2273674 | AA54: =IF(Z54="","",Z54*S54) -> 2.2273674 | AB54: =IF(V54="yes",AA54,"")
A55: =A54+1 -> 34 | B55: income_main_gender | C55: income_main_gender | D55: What is the gender of the household member[s] generating income from this source? [OPERATOR: SINGLE RESPONSE.] 1)Male 2)Female 3)Joint [both male & female] 4)DON'T KNOW 5)REFUSED | E55: =LEN(D55) -> 181 | F55: ما هو جنس الفرد ( الأفراد ) داخل الاسرة الذين يحصلون علي الدخل من هذا المصدر ؟ [المشغل: استجابة واحدة.] 1)ذكر 2)أنثى 3)مختلط [ ذكر و أنثى ] 4)لا أعرف 5)رفض الإجابة | G55: =LEN(F55) -> 167 | H55: Single Choice | I55: NA | J55: NA | K55: Form Type - Buttons | L55: 1-5 = income_main_control | M55: NA | P55: if income_main_gender = 1-5, go to income_main_comp or optional question | Q55: if income_main_gender = 1-5, go to income_main_control | S55: =1 -> 1 | V55: no | Z55: 4.7874017 | AA55: =IF(Z55="","",Z55*S55) -> 4.7874017 | AB55: =IF(V55="yes",AA55,"")
A56: =A55+1 -> 35 | B56: income_main_control | C56: income_main_control | D56: Who controls the revenue that is earned from this source? [OPERATOR: SINGLE RESPONSE.] 1)Male household member[s] 2)Female household member[s] 3)Joint household members [both female & male] 4)DON'T KNOW 5)REFUSED | E56: =LEN(D56) -> 215 | F56: من المتحكم فى الدخل الذي تكسبه الاسرة من هذا المصدر ؟ [المشغل: استجابة واحدة.] 1)الافراد الذكور 2)الافراد الاناث 3)كلا من الذكور و الاناث 4)لا أعرف 5)رفض الإجابة | G56: =LEN(F56) -> 164 | H56: Single Choice | I56: NA | J56: NA | K56: Form Type - Buttons | L56: 1-5 = income_main_comp | M56: NA | P56: if income_main_control = 1-5, go to income_main_comp | S56: =1 -> 1 | V56: no | Z56: 20.918367 | AA56: =IF(Z56="","",Z56*S56) -> 20.918367 | AB56: =IF(V56="yes",AA56,"")
A57: =A56+1 -> 36 | B57: income_main_comp | C57: income_main_comp | D57: Has your household's income from {income_main} changed in the last 3 months compared to the same period of a normal year? [OPERATOR: SINGLE RESPONSE.] 1)A lot more [increased by more than 50%] 2)Slightly more 3)Same 4)Slightly less 5)A lot less [less than half as much] 6)DON'T KNOW 7)REFUSED | E57: =LEN(D57) -> 294 | F57: هل تغير دخل أسرتك من {income_main} في الأشهر الثلاثة الماضية مقارنة بنفس الفترة من العام العادي؟ [المشغل: استجابة واحدة.] 1)أكثر بكثير [زاد بنسبة تزيد عن 50٪] 2)أكثر قليلا 3)نفس الشيء 4)أقل قليلاً 5)أقل بكثير [أقل من نصف الكمية] 6)لا أعرف 7)رفض الإجابة | G57: =LEN(F57) -> 254 | H57: Single Choice | I57: NA | J57: NA | K57: Form Type - Buttons | L57: 1-7= o_income_other | M57: NA | P57: if income_main_comp = 1-7, go to income_sec | Q57: if income_main_comp = 1-7, go to o_income_other | S57: =1 -> 1 | V57: yes | Z57: 22.126215 | AA57: =IF(Z57="","",Z57*S57) -> 22.126215 | AB57: =IF(V57="yes",AA57,"") -> 22.126215
A58: =A57+1 -> 37 | B58: o_income_other | C58: o_income_other 1) o_income_ag_prod_staple_crp 2) o_income_ag_prod_veg_fruit 3) o_income_ag_prod_cash_crp 4) o_income_ag_prod_livestock 5) o_income_ag_prod_bee 6) o_income_ag_prod_aquatic 7) o_income_ag_prod_forestry 8) o_income_ag_trade_nonprod 9) o_income_ag_dailywage 10) o_income_ag_stable_employ 11) o_income_nonag_selfemploy 12) o_income_nonag_dailywage 13) o_income_nonag_stable_employ 14) o_income_nonag_public_employ 15) o_income_israel_settlemt 15) o_income_charity 16) o_income_welfare 17) o_income_remittances 18) o_income_rents 19) o_income_no_other 20) o_income_dk 21) o_income_ref | D58: Does your household have any other sources of income in the past 3 months? [OPERATOR: MULTIPLE RESPONSES POSSIBLE. DON'T KNOW AND REFUSED OPTIONS SHOULD BE AVOIDED AS MUCH AS POSSIBLE.] 1)Production and sale of staple crops 2)Production and sale of vegetables or fruit 3)Production and sale of cashcrops 4)Production and sale of livestock or livestock products 5)Production and sale of honey or bee products 6)Production and sale of fish or aquatic products 7)Collection and sale of forestry or bush products 8)Agricultural trade EXCLUDING producers [formal or informal] 9)Daily wage on farms and other casual employment in agricultural sector 10)Stable employment in agricultural sector 11)Non-agricultural self-employed or liberal profession / doctor / architect / lawyer / including restaurant 12)Off-farm daily wages and other non-agricultural casual employment 13)Stable employment in non-agricultural sector 14)Public employment 15)Income not derived from work / Charity 16)Income not derived from work / Welfare transfer/ pension/ humanitarian aid 17)Income not derived from work / Remittances from family members or relatives 18)Income not derived from work / Income from other rents 19)No other source of income 20)DON'T KNOW 21)REFUSED | E58: =LEN(D58) -> 1247 | F58: ما هي مصار الدخل الأخرى المتوفرة للأسرة، أختار كل مصادر الدخل ألأخرى [المشغل: استجابة واحدة. يجب تجنب خيارات الإجابة "لا أعرف" و "رفض الإجابة" قدر الإمكان.] 1)إنتاج وبيع المحاصيل الأساسية 2)إنتاج وبيع الخضار أو الفاكهة 3)إنتاج وبيع المحاصيل النقدية 4)تربية وبيع الثروة الحيوانية ومنتجاتها 5)انتاج و بيع العسل أو منتجات النحل 6)إنتاج وبيع الأسماك أو منتجات المنتجات المائية 7)جمع وبيع منتجات الغابات أو الأحراش 8)التجارة الزراعية الرسمية و غير الرسمية باستثناء المنتجين 9)الأجر اليومي في المزارع وغيرها من العمالة العرضية في قطاع الزراعة 10)العمالة المستقرة في القطاع الزراعي 11)العاملين لحسابهم الخاص غير الزراعيين أو المهنة الحرة / طبيب / مهندس معماري / محامٍ / بما في ذلك مطعم 12)الأجور اليومية خارج المزرعة وغيرها من العمالة العرضية غير الزراعية 13)العمالة المستقرة في القطاع غير الزراعي 14)الوظائف العامة 15)الدخل غير المستمد من العمل / الاعمال الخيرية 16)الدخل غير المستمد من العمل / المدفوعات التحويلية ، المعاش التقاعدي ، المساعدات الإنسانية 17)الدخل غير المستمد من العمل/التحويات من أفراد الأسرة والأقارب 18)الدخل غير المستمد من العمل / الدخل من الإيجارات الأخرى 19)لم يكن هناك مصدر دخل ثانٍ 20)لا أعرف 21)رفض الإجابة | G58: =LEN(F58) -> 1131 | H58: Select All That Apply | I58: NA | J58: NA | K58: Form Type - Checklist exclude selected "income_main" 19,20,21 = IsNone | L58: 1-18 = o_income_tot_amount 19-21 = o_income_before | M58: 1)o_income_ag_prod_staple_crp 2)o_income_ag_prod_veg_fruit 3)o_income_ag_prod_cash_crp 4)o_income_ag_prod_livestock 5)o_income_ag_prod_bee 6)o_income_ag_prod_aquatic 7)o_income_ag_prod_forestry 8)o_income_ag_trade_nonprod 9)o_income_ag_dailywage 10)o_income_ag_stable_employ 11)o_income_nonag_selfemploy 12)o_income_nonag_dailywage 13)o_income_nonag_stable_employ 14)o_income_nonag_public_employ 15)o_income_israel_settlemt 15)o_income_charity 16)o_income_welfare 17)o_income_remittances 18)o_income_rents 19)o_income_no_other 20)o_income_dk 21)o_income_ref | N58: GeoPoll [3/18/2024]. Added a filter here to filter out the answer selected at income_main. | O58: OK thanks | P58: if options #1-3 selected, go to income_sec_crop_check if options #4 selected, go to income_sec_ls_check if options #6 selected, go to income_sec_fish_check if options #5, 7-18 selected, go to [income_sec_comp OR optional question] if options #19-21 selected, go to shock | Q58: if options #1-14, 16-19 selected, go to o_income_tot_amount if options #15 selected, go to o_income_other_previous if options #20-22 selected, go to shock | S58: =1 -> 1 | V58: yes | Z58: 18.710653 | AA58: =IF(Z58="","",Z58*S58) -> 18.710653 | AB58: =IF(V58="yes",AA58,"") -> 18.710653
A59: =A58+1 -> 38 | B59: o_income_tot_amount | C59: o_income_tot_amount | D59: How much was earned [in NIS] in total by your household in the past 3 months ? Include total income from all sources including the main income {income_main}. [OPERATOR: MAKE SURE THE INFORMATION IS RECORDED IN THE CORRECT CURRENCY AND THAT IT INCLUDES THE INCOME FROM THE MAIN INCOME SOURCE. INCOME SHOULD NOT BE LESS THAN {income_main_amount} NIS (THE VALUE REPORTED AS EARNED IN THE PAST 3 MONTHS FOR THE MAIN INCOME SOURCE). ENTER 8888888 FOR DON'T KNOW AND 9999999 FOR REFUSED.] | E59: =LEN(D59) -> 484 | F59: ما مجموع المبلغ الذي كسبته أسرتك (بالعملة شيكل) من كل مصادر الدخل المتاحة للأسره والتي تم ذكرها سابقا بما في ذلك مصدر الدخل الرئيس {income_main} ، في الأشهر الثلاثة الماضية؟ [المُشغل: تأكد من تسجيل المعلومات بالعملة الصحيحة.الدخل لا ينبغي أن يقل عن {income_main_amount} شيكل (القيمة المُبلغ عنها كدخل في الشهور الثلاثة الماضية للمصدر الرئيسي للدخل). أدخل 8888888 للا أعرف و 9999999 في حالة الرفض.] | G59: =LEN(F59) -> 399 | H59: Range | I59: NA | J59: NA | K59: Form Type - TextBox IsDemographic - o_income_tot_amount Validation Rule: Answer to this question is VALID IF "income_main_amount" "LesserThanOrEqual" "CurrentAnswer" Unmatched Response [You have given an answer less than the amount earned from your main income source. Please provide the correct total amount earned by your household in the past 3 months] ar_Arabic [لقد قدمت إجابة أقل من المبلغ الذي كسبته من مصدر دخلك الرئيسي. يرجى تقديم المبلغ الإجمالي الصحيح الذي كسبته أسرتك خلال الأشهر الثلاثة الماضية] | L59: 300 - 4000 = o_income_before 4001 - 1500000 = o_income_tot_amount_conf 8888888-8888888 = shock 9999999-9999999 = shock | M59: NA | N59: GeoPoll [3/18/2024]. Kindly help Review the Arabic translations to match English section and advise on the constraints established in column L. GeoPoll [4/11/2024]: Updated Arabic to align with English text Arabic referenced second source of income value. . GeoPoll [17/4/2024]: Added the validation rule to ensure the amount entered here is not less that in Q-"income_main_amount". | O59: Contraints are ok, thanks. FAOPAL - kindly provide translations | P59: If the income amount is over the threshold set in "Additional information", the respondent will be asked to confirm with income_sec_amount_conf. Otherwise, go to income_sec_comp. | Q59: If the income amount is over the threshold set in "Additional information", the respondent will be asked to confirm with income_sec_amount_conf. Otherwise, go to shock. | S59: =1 -> 1 | V59: no | Z59: 23.20038 | AA59: =IF(Z59="","",Z59*S59) -> 23.20038 | AB59: =IF(V59="yes",AA59,"")
A60: =A59+1 -> 39 | B60: o_income_tot_amount_conf | C60: o_income_tot_amount_conf | D60: Can you confirm the amount of income you just stated of {o_income_tot_amount} NIS is correct? [OPERATOR: IF THE AMOUNT EARNED FROM THIS INCOME SOURCE OVER THE PAST 3 MONTH IS INDEED OVER 4000 NIS, CLICK ON CONTINUE. OTHERWISE, GO BACK AND CHANGE THE AMOUNT ENTERED.] 1)CONTINUE | E60: =LEN(D60) -> 279 | F60: هل يمكنك تأكيد مبلغ الدخل {o_income_tot_amount} [بالعملة شيكل] الذي ذكرته للتو؟ [المُشغل: إذا كان المبلغ المكتسب من مصدر الدخل هذا خلال الأشهر الثلاثة الماضية أكثر من 4000 شيكل ، انقر على "تابع". بخلاف ذلك ، الرجاء الرجوع وتغيير المبلغ الذي تم إدخاله.] 1) تابع | G60: =LEN(F60) -> 263 | H60: Single Choice | I60: NA | J60: NA | K60: Form Type - Buttons | L60: 1 = o_income_before | M60: NA | N60: GeoPoll [3/18/2024]. Added additional text in English so the question will directly reference the value provided at o_income_tot_amount. If in agreement, kindly support with the translations. GeoPoll [4/11/2024]: Updated arabic translation. | O60: Ok for the English text. FAOPAL - kindly provide translation | P60: if income_sec_amount_conf = 1, go to income_sec_comp | Q60: if income_sec_amount_conf = 1, go to shock | S60: =1 -> 1 | V60: no | Z60: 1.9277389 | AA60: =IF(Z60="","",Z60*S60) -> 1.9277389 | AB60: =IF(V60="yes",AA60,"")
A61: =A60+1 -> 40 | B61: o_income_before | C61: o_income_before | D61: In the 3 months before October 2023, were any household members earning an income from work in Israel or the settlements? [OPERATOR: SINGLE RESPONSE.] 1)YES 2)NO 3)DON'T KNOW 4)REFUSED | E61: =LEN(D61) -> 186 | F61: في الثلاثة أشهر التي سبقت أكتوبر 2023، هل كان أي من أفراد الأسرة يكسب دخلاً من العمل في إسرائيل أو المستوطنات؟ [المشغل: استجابة واحدة.] 1) نعم 2) لا 3) لا أعلم 4) رفض الإجابة | G61: =LEN(F61) -> 176 | H61: Single Choice | I61: NA | J61: NA | K61: Form Type - Buttons | L61: 1 = o_income_before_ag 2-4 = shock | M61: NA | Q61: if o_income_before = 2 or 3 or 4, go to shock if o_income_before = 1, go to o_income_before_ag
A62: =A61+1 -> 41 | B62: o_income_before_ag | C62: o_income_before_ag | D62: Was this income earned from work related to agriculture (agricultural production, farm labour, etc), non-agricultural work, or both? [OPERATOR: SINGLE RESPONSE.] 1)Agricutlure-related work 2)Non Agricutlure-related work 3)Both agricultural and non-agricultural work 4)DON'T KNOW 5)REFUSED | E62: =LEN(D62) -> 292 | F62: هل تم كسب هذا الدخل من العمل المتعلق بالزراعة (الإنتاج الزراعي، العمل في المزارع، إلخ)، أو العمل غير الزراعي، أو كلاهما؟ [المشغل: استجابة واحدة.] 1) العمل المتعلق بالزراعة 2) العمل غير المتعلق بالزراعة 3) كل من العمل الزراعي وغير الزراعي 4) لا أعلم 5) رفض الإجابة | G62: =LEN(F62) -> 265 | H62: Single Choice | I62: NA | J62: NA | K62: Form Type - Buttons | L62: 1-5 = o_income_before_lost | M62: NA | Q62: for any response, go to o_income_before_lost
A63: =A62+1 -> 42 | B63: o_income_before_lost | C63: o_income_before_lost | D63: Is this income source still available to the household now? [OPERATOR: SINGLE RESPONSE.] 1)YES 2)NO 3)DON'T KNOW 4)REFUSED | E63: =LEN(D63) -> 124 | F63: هل لا يزال مصدر الدخل هذا متاحًا للأسرة الآن؟ [المشغل: استجابة واحدة.] 1) نعم 2) لا 3) لا أعلم 4) رفض الإجابة | G63: =LEN(F63) -> 111 | H63: Single Choice | I63: NA | J63: NA | K63: Form Type - Buttons | L63: 1 = shock 2 = o_income_before_mitigate 3-4 = shock | M63: NA | Q63: if o_income_before_lost = 1 or 3 or 4, go to shock if o_income_before_lost = 2, go to o_income_before_mitigate
A64: =A63+1 -> 43 | B64: o_income_before_mitigate | C64: o_income_before_mitigate | D64: For household members who were earning an income in Israel or the settlements before October 2023, have they since found other income-generating work? [OPERATOR: SINGLE RESPONSE.] 1)Yes - found other income-generating work in agriculture 2)Yes - found other income-generating work NOT in agriculture 3)Yes - found other income-generating work in BOTH agriculture and non-agriculture 4)No 5)DON'T KNOW 6)REFUSED | E64: =LEN(D64) -> 412 | F64: بالنسبة لأفراد الأسرة الذين كانوا يكسبون دخلاً في إسرائيل أو المستوطنات قبل أكتوبر 2023، هل وجدوا منذ ذلك الحين أعمالًا أخرى مدرة للدخل؟ [المشغل: استجابة واحدة.] 1) نعم، وجدوا أعمالًا أخرى تدر دخلاً في الزراعة 2) نعم، وجدوا أعمالًا أخرى تدر دخلاً ليس في الزراعة 3) نعم، وجدوا أعمالًا أخرى تدر دخلاً في كل من الزراعة وغير الزراعة 4) لا 5) لا أعلم 6) رفض الإجابة | G64: =LEN(F64) -> 363 | H64: Single Choice | I64: NA | J64: NA | K64: Form Type - Buttons | L64: 1-3 = o_income_before_change 4-6 = shock | M64: NA | Q64: if o_income_before_mitigate = 1 or 2 or 3, go to o_income_before_change Otherwise, go to shock
A65: =A64+1 -> 44 | B65: o_income_before_change | C65: o_income_before_change | D65: For those who found other income-generating work, how does the income earned compare to previous work in Israel and the settlements? [OPERATOR: SINGLE RESPONSE.] 1)A lot more [increased by more than 50%] 2)Slightly more 3)Same 4)Slightly less 5)A lot less [less than half as much] 6)DON'T KNOW 7)REFUSED | E65: =LEN(D65) -> 307 | F65: بالنسبة لأولئك الذين وجدوا أعمالًا أخرى تدر دخلاً، كيف يقارن الدخل المكتسب مع العمل السابق في إسرائيل والمستوطنات؟ [المشغل: استجابة واحدة.] 1) أكثر بكثير [زاد بأكثر من 50%] 2) أكثر قليلاً 3) نفسه 4) أقل قليلاً 5) أقل بكثير [أقل من النصف] 6) لا أعلم 7) رفض الإجابة | G65: =LEN(F65) -> 266 | H65: Single Choice | I65: NA | J65: NA | K65: Form Type - Buttons | L65: 1-7 = shock | M65: NA | Q65: for any response, go to shock
A66: =A65+1 -> 45 | B66: shock | C66: shock_ 1) shock_noshock 2) shock_sicknessordeathofhh 3) shock_lostemplorwork 4) shock_otherintrahhshock 5) shock_higherfoodprices 6) shock_higherfuelprices 7) shock_mvtrestrict 8) shock_othereconomicshock 9) shock_pestoutbreak 10) shock_plantdisease 11) shock_animaldisease 12) shock_napasture 13) shock_othercropandlivests 14) shock_coldtemporhail 15) shock_flood 16) shock_hurricane 17) shock_drought 18) shock_earthquake 19) shock_landslides 20) shock_firenatural 21) shock_othernathazard 22) shock_violenceinsecconf 23) shock_theftofprodassets 24) shock_firemanmade 25) shock_othermanmadehazard 26) shock_dk 27) shock_ref | D66: Has your household or community faced any particular disaster or crisis affecting your household's ability to raise an income and/or to produce food for self consumption in the last 3 months, and if so, which one[s]? [OPERATOR: SELECT RELEVANT SHOCKS EXPERIENCED BY THE HOUSEHOLD. MULTIPLE RESPONSES POSSIBLE. REFER TO ECONOMIC SHOCKS, CROP AND LIVESTOCK SHOCKS, INTRA-HOUSEHOLD SHOCK, NATURAL HAZARDS AND HUMAN-INDUCED HAZARDS.] 1)No shock 2)Sickness or accident or death of household member[s] [sickness of breadwinner / unusually high medical expenditure / funeral expenses / death of breadwinner] 3)Lost employment or working opportunities [not due to illness/accident] 4)Other intra-household shock 5)Unusually high food prices 6)Unusually high fuel prices or transport prices 7)Population movement restrictions [e.g. due to epidemic or infrastructure damage] 8)Other economic shock 9)Pest outbreak 10)Plant disease 11)Animal disease [affecting many animals] or death 12)Lack of physical access to pasture 13)Other crop and livestock shock 14)Cold temperatures or hail 15)Flood / riverbank erosion 16)Hurricane / cyclone / tornado 17)Drought / heat stress 18)Earthquake 19)Landslides 20)Fire from natural disaster 21)Other natural hazard 22)Violence and insecurity / conflict 23)Theft of production assets [land / livestock / tools / etc] 24)Fire from human-induced disaster 25)Other human-induced hazard 26)DON'T KNOW 27)REFUSED | E66: =LEN(D66) -> 1440 | F66: هل واجهت أسرتك أو هل واجه مجتمعك أي كارثة أو أزمة أو صدمة معينة أثرت على قدرة أسرتك على إدرار الدخل و / أو إنتاج الغذاء للاستهلاك الذاتي في الأشهر الثلاثة الماضية ، وإذا كان الأمر كذلك ، فما كانت؟ [المُشغل: حدد الأزمات/الكوارث/الصدمات ذات الصلة التي اختبرتها الأسرة. استجابات متعددة ممكنة. راجع الصدمات الاقتصادية والصدمات التي تصيب المحصول والمواشي و داخل الأسرة والمخاطر الطبيعية والأخطار التي يسببها الإنسان.] 1)لا أزمات/كوارث/صدمات أو أنها لم تؤثر على الأسرة 2) مرض أو حادث أو وفاة أحد أفراد الأسرة [مرض العائل / النفقات الطبية المرتفعة بشكل غير عادي / نفقات الجنازة / وفاة العائل] 3) فرص العمل أو العمل المفقودة [ليس بسبب مرض / حادث] 4) صدمة أخرى داخل الأسرة 5) أسعار المواد الغذائية أعلى بكثير من المعتاد 6) أسعار الوقود أو أسعار النقل أعلى بكثير من المعتاد 7) القيود المفروضة على حركة السكان [على سبيل المثال بسبب الوباء أو تلف البنية التحتية] 8) صدمة اقتصادية أخرى 9) تفشي الآفات 10) أمراض نباتية 11)أمراض حيوانية تصيب العديد من الحيوانات أو تتسبب بموتها 12) عدم إمكانية الوصول للمراعي 13) صدمة أخرى للمحاصيل والماشية 14)درجات الحرارة الباردة أو السقيع 15) الفيضانات / تآكل ضفاف الأنهار 16) إعصار 17) الجفاف / الإجهاد الحراري 18) زلزال 19) الانهيارات الارضية 20)حريق مسبب من كارثة طبيعية أو حدث عرضي آخر 21) مخاطر طبيعية أخرى 22) العنف وانعدام الأمن / النزاع 23) سرقة أصول الإنتاج [الأرض / الماشية / الأدوات / إلخ] 24) حريق مسبب من كارثة من صنع الإنسان 25) مخاطر أخرى من صنع الإنسان 26) لا أعرف 27) رفض الإجابة | G66: =LEN(F66) -> 1426 | H66: Select All That Apply | I66: NA | J66: NA | K66: Form Type - Checklist 1,26,27 = IsNone | L66: 1-27 = o_conflict_any | M66: 1)shock_noshock 2)shock_sicknessordeathofhh 3)shock_lostemplorwork 4)shock_otherintrahhshock 5)shock_higherfoodprices 6)shock_higherfuelprices 7)shock_mvtrestrict 8)shock_othereconomicshock 9)shock_pestoutbreak 10)shock_plantdisease 11)shock_animaldisease 12)shock_napasture 13)shock_othercropandlivests 14)shock_coldtemporhail 15)shock_flood 16)shock_hurricane 17)shock_drought 18)shock_earthquake 19)shock_landslides 20)shock_firenatural 21)shock_othernathazard 22)shock_violenceinsecconf 23)shock_theftofprodassets 24)shock_firemanmade 25)shock_othermanmadehazard 26)shock_dk 27)shock_ref | P66: if shock = 1-27, go to [crp_intro or optional question] | Q66: if shock = 1-27, go to o_conflict_any | S66: =1 -> 1 | V66: yes | Z66: 37.85363 | AA66: =IF(Z66="","",Z66*S66) -> 37.85363 | AB66: =IF(V66="yes",AA66,"") -> 37.85363
A67: CONFLICT MODULE | AA67: =IF(Z67="","",Z67*S67) | AB67: =IF(V67="yes",AA67,"")
A68: =A66+1 -> 46 | B68: o_conflict_any | C68: o_conflict_any | D68: Have you or anyone within your household been exposed to any form of insecurity or conflict since October 2023? [OPERATOR: SINGLE RESPONSE.] 1)YES 2)NO 3)DON'T KNOW 4)REFUSED | E68: =LEN(D68) -> 176 | F68: هل تعرضت أنت أو أي شخص ضمن أسرتك لأي نوع من أنواع عدم الأمان أو النزاع منذ أكتوبر 2023؟ [المشغل: استجابة واحدة.] 1) نعم 2) لا 3) لا أعلم 4) رفض الإجابة | G68: =LEN(F68) -> 153 | H68: Single Choice | I68: NA | J68: NA | K68: Form Type - Buttons | L68: 1 = o_conflict_type 2-4 = o_movement_any | M68: NA | P68: If o_conflict_any = 1, go to o_conflict_type If o_conflict_any = 2 OR 3 OR 4, go to o_movement_any
A69: =A68+1 -> 47 | B69: o_conflict_type | C69: o_conflict_type 1)o_confl_type_land_agri 2)o_confl_type_criminality 3)o_confl_type_community_gp 4)o_confl_type_armed_conflict 5)o_confl_type_assistance 6)o_confl_type_other 7)o_confl_type_dk 8)o_confl_type_ref | D69: What types of insecurity has your household been affected by? [OPERATOR: MULTIPLE RESPONSES POSSIBLE.] 1)Disputes or conflicts or attacks related to land/ water or pasture or agricultural assets/land 2)Criminality 3)Conflict between community groups 4)Armed conflict 5)Disputes or conflicts over assistance being provided 6)Other [specify] 7)DON'T KNOW 8)REFUSED | E69: =LEN(D69) -> 364 | F69: ما أشكال عدم الأمان التي تأثرت بها أسرتك؟ [المشغل: ممكن عدة استجابات.] 1)النزاعات أو الصراعات أو الهجمات المتعلقة بالأرض أو الماء أو المراعي أو الأصول/الأراضي الزراعية [مصادرة أراضي، مصادرة ممتلكات، منع الوصول وقت الحصاد و الخلافات المتعلقة بالميراث وغيرها بغض النظر عن هوية الفاعل] 2)الإجرام [السرقة، القتل، الاعتداء على الأشخاص، تدمير الممتلكات بغض النظر عن هوية الفاعل] 3) الصراع بين مجموعات داخل المجتمع [مثلا النزاع بين الأسر وغيرها] 4) النزاع المسلح 5) النزاعات أو الصراعات حول المساعدات المقدمة 6) أخرى [يرجى التحديد] 7) لا أعلم 8) رفض الإجابة | G69: =LEN(F69) -> 553 | H69: Open Ended-Select All That Apply | I69: NA | J69: NA | K69: Form Type - Checklist 7,8 = IsNone | L69: 1-8 = o_conflict_agri | M69: 1)o_confl_type_land_agri 2)o_confl_type_criminality 3)o_confl_type_community_gp 4)o_confl_type_armed_conflict 5)o_confl_type_assistance 6)o_confl_type_other 7)o_confl_type_dk 8)o_confl_type_ref | P69: if o_conflict_type = 1, go to o_conflict_agri if o_conflict_type = 2-8, go to o_movement_any
A70: =A69+1 -> 48 | B70: o_conflict_agri | C70: o_conflict_agri 1)o_confl_agri_land_occupied 2)o_confl_agri_land_damage 3)o_confl_agri_land_boundaries 4)o_confl_agri_nonfarm_occupied 5)o_confl_agri_water_hh_use 6)o_confl_agri_water_agri 7)o_confl_agri_livestock_confisc 8)o_confl_agri_other 9)o_confl_agri_dk 10)o_confl_agri_ref | D70: Which types of conflicts over land, water or pasture or agricultural assets has your household been affected by? [OPERATOR: MULTIPLE RESPONSES POSSIBLE.] 1)Farming land/pasture/assets occupied/used by others 2)Farming land/pasture/assets damaged or destroyed by others 3)Contested boundaries of farming land/pasture 4)Non-farming land/assets occupied/used by others 5)Conflict around water for household use 6)Conflict around water for agricultural use 7)Confiscation of livestock 8)Other [specify] 9)DON'T KNOW 10)REFUSED | E70: =LEN(D70) -> 526 | F70: ما أنواع النزاعات على الأرض أو الماء أو المراعي أو الأصول الزراعية التي تأثرت بها أسرتك؟ [المشغل: ممكن عدة استجابات.] 1) إنتزاع أراضي زراعية /مراعي/أصول زراعية أو إستخدامها من قبل آخرين 2) تدمير أو إتلاف أرض زراعية /مراعي/أصول زراعية من قبل الآخرين 3) نزاع حول حدود أراضي زراعية/مراعي 4) إنتزاع أراضي غير زراعية /أصول غير زراعية أو إستخددامها من قبل الآخرين 5) نزاع حول مصادر المياه للاستخدام المنزلي 6) نزاع حول مصادر المياه للاستخدام الزراعي 7) مصادرة الماشية 8) أخرى [يرجى التحديد] 9) لا أعلم 10) رفض الإجابة | G70: =LEN(F70) -> 515 | H70: Open Ended-Select All That Apply | I70: NA | J70: Send if "o_conflict_type" "Contains" "Disputes or conflicts or attacks related to land/ water or pasture or agricultural assets/land" if not satisfied go to "o_movement_any" | K70: Form Type - Checklist 9,10 = IsNone | L70: 1-10 = o_movement_any | M70: 1)o_confl_agri_land_occupied 2)o_confl_agri_land_damage 3)o_confl_agri_land_boundaries 4)o_confl_agri_nonfarm_occupied 5)o_confl_agri_water_hh_use 6)o_confl_agri_water_agri 7)o_confl_agri_livestock_confisc 8)o_confl_agri_other 9)o_confl_agri_dk 10)o_confl_agri_ref | P70: for nay response, go to o_movement_any
A71: =A70+1 -> 49 | B71: o_movement_any | C71: o_movement_any | D71: Have you or anyone within your household been exposed to any form of movement restrictions since October 2023? [OPERATOR: SINGLE RESPONSE.] 1)YES 2)NO 3)DON'T KNOW 4)REFUSED | E71: =LEN(D71) -> 175 | F71: هل تعرضت أنت أو أي شخص ضمن أسرتك لأي نوع من أنواع قيود الحركة منذ أكتوبر 2023؟ [المشغل: استجابة واحدة.] 1) نعم 2) لا 3) لا أعلم 4) رفض الإجابة | G71: =LEN(F71) -> 144 | H71: Single Choice | I71: NA | J71: NA | K71: Form Type - Buttons | L71: 1 = o_movement_type 2-4 = o_displace_any | M71: NA | P71: if o_movement_any = 1, go to o_movement_type if o_movement_any = 2 or 3 or 4, go to o_displace_any
A72: =A71+1 -> 50 | B72: o_movement_type | C72: o_movement_type 1)o_mvt_checkpt 2)o_mvt_flyingcheckpt 3)o_mvt_permits 4)o_mvt_insecurity 5)o_mvt_other 6)o_mvt_dk 7)o_mvt_ref | D72: What types of movement restrictions has your household been exposed to? [OPERATOR: MULTIPLE RESPONSES ] 1)Checkpoints 2)Flying checkpoints 3)Permits required 4)Insecurity [e.g. settler violence] 5)Other [specify] 6)DON'T KNOW 7)REFUSED | E72: =LEN(D72) -> 238 | F72: ما أنواع قيود الحركة التي تعرضت لها أسرتك؟ [المشغل: استجابات متعددة ممكنة.] 1) نقاط التفتيش 2) نقاط تفتيش متنقلة/مؤقتة 3) الحصول على تصاريح 4) عدم الأمان [على سبيل المثال، عنف المستوطنين] 5) أخرى [يرجى التحديد] 6) لا أعلم 7) رفض الإجابة | G72: =LEN(F72) -> 239 | H72: Open Ended-Select All That Apply | I72: NA | J72: NA | K72: Form Type - Checklist 6,7 = IsNone | L72: 1-7 = o_displace_any | M72: 1)o_mvt_checkpt 2)o_mvt_flyingcheckpt 3)o_mvt_permits 4)o_mvt_insecurity 5)o_mvt_other 6)o_mvt_dk 7)o_mvt_ref | P72: for any response, go to o_displace_any
A73: =A72+1 -> 51 | B73: o_displace_any | C73: o_displace_any | D73: Have you been displaced from your own residence since October 2023 due to the security situation? [OPERATOR: SINGLE RESPONSE.] 1)YES 2)NO 3)DON'T KNOW 4)REFUSED | E73: =LEN(D73) -> 162 | F73: هل أجبرت على ترك مكان سكنك منذ أكتوبر 2023 بسبب الوضع الأمني؟ [المشغل: استجابة واحدة.] 1) نعم 2) لا 3) لا أعلم 4) رفض | G73: =LEN(F73) -> 119 | H73: Single Choice | I73: NA | J73: NA | K73: Form Type - Buttons | L73: 1 = o_displace_where 2-4 = o_conflict_food | M73: NA | P73: if o_displace_any = 1, go to o_displace_where If o_displace_any = 2 or 3 or 4, go to o_conflict_food
A74: =A73+1 -> 52 | B74: o_displace_where | C74: o_displace_where | D74: Have you remained within your own community or governorate or have you moved elsewhere? [OPERATOR: SINGLE RESPONSE.] [HINT: 'COMMUNITY' MAY BE DEFINED AS BEDOUIN COMMUNITY, VILLAGE, CITY, OR SIMILAR WHERE YOU MAINTAIN SOCIAL OR CULTURAL TIES WITH OTHERS] 1)I have been displaced within my same community in the same governorate 2)I have been displaced to a different community in the same governorate 3)I have been displaced to another governorate 4)DON'T KNOW 5)REFUSED | E74: =LEN(D74) -> 473 | F74: هل أجبرت [بشكل مباشر أو غير مباشر] على الإنتقال ضمن نفس التجمع السكاني أو ضمن نفس المحافظة أم انتقلت إلى مكان آخر؟ [المشغل: استجابة واحدة.] [تلميح: 'المجتمع' قد يُعرف على أنه تجمع بدوي، قرية، مدينة، أو ما شابه حيث تحافظ على علاقات اجتماعية أو ثقافية مع الآخرين] 1)ضمن نفس التجمع السكني في نفس المحافظة 2)إلى تجمع سكني مختلف في نفس المحافظة 3)إلى محافظة أخرى 4) لا أعلم 5) رفض الإجابة | G74: =LEN(F74) -> 387 | H74: Single Choice | I74: NA | J74: NA | K74: Form Type - Buttons | L74: 1-5 = o_conflict_food | M74: NA | P74: for any response, go to o_conflict_food
A75: =A74+1 -> 53 | B75: o_conflict_food | C75: o_conflict_food 1)o_confl_food_prices 2)o_confl_food_lack_income 3)o_confl_food_lack_assist 4)o_confl_food_market_access 5)o_confl_food_demand_illicit 6)o_confl_food_lack_mktprod 7)o_confl_food_lack_selfprod 8)o_confl_food_lack_hh_stock 9)o_confl_food_none 10)o_confl_food_other 11)o_confl_food_dk 12)o_confl_food_ref | D75: How has insecurity and/or conflict affected household AVAILABILITY or ACCESS to food? [OPERATOR: MULTIPLE RESPONSES POSSIBLE.] 1)High food prices 2)Reduced income to buy food 3)Reduced or lack of ability to access assistance [food/ cash or vouchers] 4)Reduced or lack of ability to access markets 5)Reduced availability of different food products at the market 6)Reduced availability of self-produced food 7)Depletion of household food stocks 8)There has been no significant impact on household availability or access to food 9)Other [specify] 10)DON'T KNOW 11)REFUSED | E75: =LEN(D75) -> 570 | F75: كيف أثرت حالة عدم الأمان و/أو النزاع على توفر الغذاء للأسرة أو القدرة على الوصول إليه؟ [المشغل: ممكن عدة استجابات.] 1) ارتفاع أسعار الغذاء 2) انخفاض الدخل المخصص لشراء الغذاء 3) أصبحت القدرة على الوصول إلى المساعدات قليلة أو معدومة [غذاء، نقود أو قسائم] 4) أصبحت القدرة على الوصول إلى الأسواق قليلة أو معدومة 5) انخفاض توفر منتجات غذائية مختلفة في السوق 6) انخفاض توفر الغذاء المنتج ذاتيًا 7) استنزاف مخزون الأسرة من الغذاء 8) لم يكن هناك تأثير كبير على توفر الغذاء أو قدرة الأسرة على الوصول إليه 9) أخرى [يرجى التحديد] 10) لا أعلم 11) رفض الإجابة | G75: =LEN(F75) -> 552 | H75: Open Ended-Select All That Apply | I75: NA | J75: NA | K75: Form Type - Checklist 8,10,11 = IsNone | L75: 1-11 = crp_intro | M75: 1)o_confl_food_prices 2)o_confl_food_lack_income 3)o_confl_food_lack_assist 4)o_confl_food_market_access 5)o_confl_food_demand_illicit 6)o_confl_food_lack_mktprod 7)o_confl_food_lack_selfprod 8)o_confl_food_lack_hh_stock 9)o_confl_food_none 10)o_confl_food_other 11)o_confl_food_dk 12)o_confl_food_ref | N75: GeoPoll [4/11/2024]: Correct the codes, we have more codes than the actual answer options. | P75: for any response, go to crp_intro
A76: D. CROP PRODUCTION | AA76: =IF(Z76="","",Z76*S76) | AB76: =IF(V76="yes",AA76,"")
A77: =A75+1 -> 54 | B77: crp_intro | C77: crp_intro | D77: We will now ask you some questions about crop production which apply to you and anyone in your household that is involved in crop production or sales. All questions refer to the crops grown during Winter season. 1)CONTINUE | E77: =LEN(D77) -> 223 | F77: سنطرح عليك الآن بعض الأسئلة حول إنتاج المحاصيل التي تنطبق عليك وعلى أي شخص في أسرتك يشارك في إنتاج المحاصيل أو بيعها. تشير جميع الأسئلة إلى المحاصيل المزروعة خلال الموسم الشتوي. 1) تابع | G77: =LEN(F77) -> 187 | H77: Single Choice | I77: NA | J77: Send if "hh_agricactivity" "Equals" "Yes - crop production" Or "hh_agricactivity" "Equals" "Yes - both crop and livestock production" if not satisfied go to "crp_salesmain" | K77: Form Type - Buttons | L77: 1 = crp_landsize_num | M77: NA | P77: If hh_agricactivity = "Yes - crop production" or "Yes - both crop and livestock production" or if they reported production and sales of crops in one of the three main income sources and confirmed that they are involved in production, then this section will be asked to respondents. Otherwise, skip to crp_salesmain. Next question is crp_landsize_num | Q77: If hh_agricactivity = "Yes - crop production" or "Yes - both crop and livestock production", then this section will be asked to respondents. Otherwise, skip to crp_salesmain. Next question is crp_landsize_num | S77: ='Additional information'!$D$17 -> 0.91 | V77: yes | Z77: 7.3040729 | AA77: =IF(Z77="","",Z77*S77) -> 6.6467063 | AB77: =IF(V77="yes",AA77,"") -> 6.6467063
A78: =A77+1 -> 55 | B78: crp_landsize_num | C78: crp_landsize_num | D78: What is the total size of the land you can cultivate? [OPERATOR: RECORD THE TOTAL LAND SIZE PROVIDED BY THE RESPONDENT. WRITE 8888888 FOR DON'T KNOW AND 9999999 FOR REFUSED. MEASUREMENT UNIT WILL BE SPECIFIED IN THE FOLLOWING QUESTION.] | E78: =LEN(D78) -> 237 | F78: ما هو الحجم الإجمالي للأرض التي يمكنك زراعتها؟ [المُشغل: سجل إجمالي حجم الأرض الذي ذكره المجيب. اكتب 8888888 للا أعرف و 9999999 في حالة الرفض. سيتم تحديد وحدة القياس في السؤال التالي.] | G78: =LEN(F78) -> 185 | H78: Range | I78: NA | J78: NA | K78: Form Type - TextBox | L78: 0-1000000 = crp_landsize_unit 8888888-8888888 = crp_main 9999999-9999999 = crp_main | M78: NA | P78: For any response, go to crp_landsize_unit. Range is between 0 and 1000000. For "Don't know" and "Refused", go to crp_main. | S78: ='Additional information'!$D$17 -> 0.91 | V78: yes | Z78: 23.939905 | AA78: =IF(Z78="","",Z78*S78) -> 21.785314 | AB78: =IF(V78="yes",AA78,"") -> 21.785314
A79: =A78+1 -> 56 | B79: crp_landsize_unit | C79: crp_landsize_unit | D79: Unit of measurement for land size: [OPERATOR: DO NOT READ. SINGLE RESPONSE.] 1)Acres 2)Hectares 3)Square meters 4)Square feet 5)Dunum | E79: =LEN(D79) -> 136 | F79: وحدة قياس مساحة الارض: [المُشغل: لا تقرأ. استجابة واحدة.] 1) فدان 2) هكتار 3) متر مربع 4) قدم مربع 5) دونم | G79: =LEN(F79) -> 108 | H79: Single Choice | I79: NA | J79: NA | K79: Form Type - Buttons | L79: 1-5 = crp_main | M79: NA | P79: if crp_landsize_unit = 1-5, go to crp_main | S79: ='Additional information'!$D$17 -> 0.91 | V79: yes | Z79: 2.2494626 | AA79: =IF(Z79="","",Z79*S79) -> 2.047011 | AB79: =IF(V79="yes",AA79,"") -> 2.047011
A80: =A79+1 -> 57 | B80: crp_main | C80: crp_main | D80: What has been the main crop that your household has grown for food and income generation in Winter season, if any? [OPERATOR: SINGLE RESPONSE. "NO CROP PRODUCTION" IS IN LAST OPTIONS AT THE END.] 1)Wheat 2)Barley 3)Potatoe 4)Peas 5)Chickpeas 6)Fava beans 7)Cabbage 8)Lettuce 9)Cauliflower 10)Tomatoes 11)Cucumber 12)Eggplant/aubergine 13)Onions 14)Lemon 15)Mango 16)Guava 17)Avocado 18)Grapes 19)Olives 20)Almond 21)Fodder 22)Rice 23)Millet 24)Sorghum 25)Maize 26)Other Cereal 27)Cassava 28)Sweet Potatoes 29)Yams 30)Carrots 31)Cocoyam 32)Other tubers 33)Beans 34)Lentils 35)Soybeans 36)Broad beans 37)Other pulses 38)Spinach-Amaranth 39)Cassava leaves 40)Potatoe leaves 41)Moringa 42)Sorrel Hibiscus / Rosselle 43)Green salad herbs [thyme/ parsley/ mint/ rocca/ other] 44)Other leafy vegetables 45)Pumpkin 46)Zucchini 47)Okra 48)Bell pepper 49)Haricot 50)Green peas 51)Fava beans green 52)Other non leafy vegs 53)Orange 54)Grapefruit 55)Mandarins/clementines 56)Other citrus fruit 57)Sweet Banana 58)Plantains 59)Papaya 60)Pineapple 61)Water Melon 62)Dates 63)Figs 64)Apple 65)Apricot 66)Cherries 67)Peach/nectarine 68)Strawberries 69)Melon [Cantaloupe] 70)Other fruit 71)Coconuts 72)Groundnut/peanut 73)Cashew Nut 74)Kola Nut 75)Sesame 76)Bambara nut 77)Walnut 78)Other nuts 79)Cocoa 80)Coffee 81)Tea 82)Sugarcane 83)Sunflower 84)Other food cash crop 85)Cotton 86)Rubber 87)Jute 88)Tobacco 89)Qat 90)Other non-food cash crop 91)No crop production 92)DON'T KNOW 93)REFUSED | E80: =LEN(D80) -> 1476 | F80: ما هو المحصول الرئيسي الذي تزرعه أسرتك من أجل الغذاء وتوليد الدخل في موسم الموسم الشتوي ، إن وجد؟ [المشغل: استجابة واحدة. 'لا إنتاج للمحصول' في آخر الخيارات في النهاية.] 1)القمح 2)الشعير 3)البطاطا 4)البازيلاء 5)الحمص 6)الفول 7)الملفوف 8)الخس 9)القرنبيط 10)بندورة 11)الخيار 12)الباذنجان 13)بصل 14)الليمون 15)المانجو 16)الجوافة 17)الأفوكادو 18)العنب 19)الزيتون 20)اللوز 21)العلف 22)الرز 23)الدخن 24)الذرة الرفيعة 25)الذرة 26)الحبوب الأخرى 27)الكسافا 28)البطاطا الحلوة 29)اليام 30)الجزر 31)القلقاس 32)الدرنات الأخرى 33)الفاصوليا 34)العدس 35)فول الصويا 36)الفاصوليا العريضة 37)البقول الاخرى 38)السبانخ - القطيفة 39)أوراق الكسافا 40)أوراق البطاطا 41)المورينجا 42)الكركديه 43)أعشاب السلطة الخضراء [زعتر ، بقدونس ، نعناع ، جرجير ، أنواع أخرى] 44)الخضار الورقية الأخرى 45)اليقطين 46)الكوسة 47)البامية 48)الفلفل حلو 49)اللوبياء 50)البازلاء الخضراء 51)الفول الأخضر 52)الخضار غير الورقية الأخرى 53)البرتقال 54)الجريب فروت 55)اليوسفي / الكليمنتين 56)الحمضيات الأخرى 57)الموز 58)موز الجنة 59)البابايا 60)الأناناس 61)البطيخ الأحمر 62)التمر 63)التين 64)التفاح 65)المشمش 66)الكرز 67)الدراق / النكتارين 68)الفراولة 69)الشمام 70)الفواكه الأخرى 71)جوز الهند 72)الفول السوداني 73)الكاجو 74)جوز الكولا 75)السمسم 76)جوز البامبارا 77)الجوز 78)المكسرات الأخرى 79)الكاكاو 80)القهوة 81)الشاي 82)قصب السكر 83)دوار الشمس 84)المحاصيل الغذائية النقدية الأخرى 85)القطن 86)المطاط 87)الجوت 88)التبغ 89)القات 90)المحاصيل النقدية غير الغذائية الأخرى 91)لا إنتاج للمحصول 92) لا أعلم 93) رفض الإ‘جابه | G80: =LEN(F80) -> 1473 | H80: Single Choice | I80: NA | J80: NA | K80: Form Type - Dropdown IsDemographic - crp_main | L80: 1-90 = crp_irrig_source 91 = crp_main_check 92-93 = crp_salesmain | M80: 1.2)Wheat 1.6)Barley 2.2)Potatoe 3.3)Peas 3.5)Chickpeas 3.6)Fava beans 4.1)Cabbage 4.2)Lettuce 4.101)Cauliflower 5.1)Tomatoes 5.2)Cucumber 5.4)Eggplant/aubergine 5.8)Onions 6.2)Lemon 7.4)Mango 7.5)Guava 7.7)Avocado 7.11)Grapes 7.12)Olives 8.7)Almond 10.4)Fodder 1.1)Rice 1.3)Millet 1.4)Sorghum 1.5)Maize 1.99)Other Cereal 2.1)Cassava 2.3)Sweet Potatoes 2.4)Yams 2.5)Carrots 2.6)Cocoyam 2.99)Other tubers 3.1)Beans 3.2)Lentils 3.4)Soybeans 3.7)Broad beans 3.99)Other pulses 4.3)Spinach-Amaranth 4.4)Cassava leaves 4.5)Potatoe leaves 4.6)Moringa 4.7)Sorrel Hibiscus / Rosselle 4.9)Green salad herbs [thyme/ parsley/ mint/ rocca/ other] 4.99)Other leafy vegetables 5.3)Pumpkin 5.5)Zucchini 5.6)Okra 5.7)Bell pepper 5.9)Haricot 5.101)Green peas 5.11)Fava beans green 5.99)Other non leafy vegs 6.1)Orange 6.3)Grapefruit 6.4)Mandarins/clementines 6.99)Other citrus fruit 7.1)Sweet Banana 7.2)Plantains 7.3)Papaya 7.6)Pineapple 7.8)Water Melon 7.9)Dates 7.101)Figs 7.13)Apple 7.14)Apricot 7.15)Cherries 7.16)Peach/nectarine 7.17)Strawberries 7.18)Melon [Cantaloupe] 7.99)Other fruit 8.1)Coconuts 8.2)Groundnut/peanut 8.3)Cashew Nut 8.4)Kola Nut 8.5)Sesame 8.6)Bambara nut 8.8)Walnut 8.99)Other nuts 9.1)Cocoa 9.2)Coffee 9.3)Tea 9.4)Sugarcane 9.5)Sunflower 9.99)Other food cash crop 10.1)Cotton 10.2)Rubber 10.3)Jute 10.5)Tobacco 10.6)Qat 10.99)Other non-food cash crop 777)No crop production 88)DON'T KNOW 99)REFUSED | P80: if crp_main = any type of crop, go to crp_irrig_source; if crp_main = "No crop production", go to crp_main_check if crp_main = "Don't know" or "Refused", go to crp_salesmain | S80: ='Additional information'!$D$17 -> 0.91 | V80: yes | Z80: 23.440117 | AA80: =IF(Z80="","",Z80*S80) -> 21.330506 | AB80: =IF(V80="yes",AA80,"") -> 21.330506
A81: =A80+1 -> 58 | B81: crp_main_check | C81: crp_main_check | D81: Why did you not produce any crops in Winter season? [OPERATOR: SINGLE RESPONSE.] 1)Don’t usually produce during this season 2)Wasn't able to produce [e.g. due to difficulties] | E81: =LEN(D81) -> 178 | F81: لماذا لم تنتج أي محاصيل في الموسم الشتوي؟ [المشغل: استجابة واحدة.] 1) لا أنتج عادة محاصيل خلال هذا الموسم 2) لم أتمكن من إنتاج المحاصيل [على سبيل المثال بسبب الصعوبات] | G81: =LEN(F81) -> 169 | H81: Single Choice | I81: NA | J81: NA | K81: Form Type - Buttons | L81: 1 = crp_salesmain 2 = crp_proddif | M81: NA | P81: if crp_main_check = 1, go to crp_salesmain if crp_main_check = 2, go to crp_proddif | S81: ='Additional information'!$D$17 -> 0.91 | V81: yes | Z81: 7.7659574 | AA81: =IF(Z81="","",Z81*S81) -> 7.0670212 | AB81: =IF(V81="yes",AA81,"") -> 7.0670212
A82: =A81+1 -> 59 | B82: crp_irrig_source | C82: crp_irrig_source | D82: Where do you normally and mainly obtain water for the production of {crp_main}? [OPERATOR: SINGLE RESPONSE.] 1)Rainfed 2)Groundwater 3)Natural surface water [river / lake / stream / pond / etc.] 4)Constructed water point [canal / dam / etc.] 5)Public water supply system [e.g. tap water] 6)Other [specify] 7)DON'T KNOW 8)REFUSED | E82: =LEN(D82) -> 331 | F82: كيف تحصل عادة على الماء لري {crp_main} بشكل رئيسي؟ [المشغل: استجابة واحدة.] 1) بعلي [لا يوجد نظام ري] 2) مياه جوفية 3) مياه سطحية طبيعية [ نهر / بحيرة / بركة مياه / إلخ ] 4) نقطة مياه منشأة [ قناة / سد / إلخ] 5) نظام تزويد مياه عام [ ماء الصنبور علي سبيل المثال ] 6) آخر [حدد] 7) لا أعرف 8) رفض الإجابة | G82: =LEN(F82) -> 306 | H82: Open Ended-Single Choice | I82: NA | J82: NA | K82: Form Type - RadioList | L82: 1 = crp_seed_supply 2-6 = crp_irrig_system 7,8 = crp_seed_supply | M82: NA | P82: if crp_irrig_source = 1-8, go to [crp_area_change or optional question] | Q82: if crp_irrig_source = 1-8, go to crp_irrig_system | S82: ='Additional information'!$D$17 -> 0.91 | V82: yes | Z82: 16.481756 | AA82: =IF(Z82="","",Z82*S82) -> 14.998398 | AB82: =IF(V82="yes",AA82,"") -> 14.998398
A83: =A82+1 -> 60 | B83: crp_irrig_system | C83: crp_irrig_system | D83: Do you [your community] use a pump for your own [the communal] irrigation system? [OPERATOR: SINGLE RESPONSE.] 1)No - everything works on gravity 2)Yes - there is a communal diesel/gas/electric pump 3)Yes - there is a communal manual pump 4)Yes - there is a manual pump in my field 5)Yes - there is a diesel/gas/electric pump in my field 6)DON'T KNOW 7)REFUSED | E83: =LEN(D83) -> 362 | F83: هل تستخدم [أو هل يستخدم المجتمع الذي تنتمي اليه] مضخة لنظام الري ؟ [المشغل: استجابة واحدة.] 1) لا ، كل شيء يعمل علي الجاذبية 2)نعم ، توجد مضخة مشتركة تعمل علي الديزل أو الغاز أو الكهرباء 3) نعم، توجد مضخة يدوية مشتركة 4) نعم ، توجد مضخة يدوية فى حقلي 5)نعم، توجد مضخة تعمل الديزل أو الغاز أو الكهرباء فى حقلي 6) لا أعرف 7) رفض الإجابة | G83: =LEN(F83) -> 340 | H83: Single Choice | I83: NA | J83: NA | K83: Form Type - Buttons | L83: 1-7 = crp_irrig_pay | M83: NA | P83: if crp_irrig_system = 1-7, go to [crp_area_change or optional question] | Q83: 1-7 = crp_irrig_pay | V83: no
A84: =A83+1 -> 61 | B84: crp_irrig_pay | C84: crp_irrig_pay | D84: Do you have to pay for water rights [e.g. water rights, communal infrastructure maintenance, gas for communal pump, etc.]? [OPERATOR: SINGLE RESPONSE.] 1)YES 2)NO 3)DON'T KNOW 4)REFUSED | E84: =LEN(D84) -> 188 | F84: هل يتعين عليك الدفع مقابل الحصول علي حقوق المياه [ علي سبيل المثال حقوق المياه ، صيانة البنية التحتية المشتركة، الغاز للمضخات المشتركة ، إلخ ] ؟ [المشغل: استجابة واحدة.] 1) نعم 2) لا 3) لا أعرف 4) رفض الإجابة | G84: =LEN(F84) -> 213 | H84: Single Choice | I84: NA | J84: NA | K84: Form Type - Buttons | L84: 1-4 = crp_seed_supply | M84: NA | P84: if crp_irrig_pay = 1-4, go to [crp_area_change or optional question] | Q84: 1-4 = crp_seed_supply | V84: no
A85: =A84+1 -> 62 | B85: crp_seed_supply | C85: crp_seed_supply 1) crp_seed_ownprod 2) crp_seed_market 3) crp_seed_company 4) crp_seed_ngo 5) crp_seed_organized_community 6) crp_seed_gov 7) crp_seed_relatives_friends 8) crp_seed_other 9) crp_seed_dk 10) crp_seed_ref | D85: Who do you normally procure your seeds from? [OPERATOR: MULTIPLE RESPONSES POSSIBLE.] 1)Own production 2)Local market or agro-input shop/dealer 3)Private seed company 4)NGOs 5)Community seed banks / farmer networks / farmers' association / etc. 6)Government [e.g. MoA] 7)Relatives or friends 8)Other 9)DON'T KNOW 10)REFUSED | E85: =LEN(D85) -> 326 | F85: من أين تحصل عادة على البذور؟ [المُشغل: احتمال وجود عدة استجابات.] 1) الإنتاج الخاص 2) اشتريها من السوق أو متجر المدخلات الزراعية 3) اشتريها من شركة بذور خاصة 4) المنظمات الغير حكومية 5) بنوك البذور المجتمعية / شبكات المزارعين / إلخ 6) الحكومة [وزارة الزراعة علي سبيل المثال ] 7) الاقارب أو الاصدقاء 8) آخر 9) لا أعرف 10) رفض الإجابة | G85: =LEN(F85) -> 335 | H85: Select All That Apply | I85: NA | J85: NA | K85: Form Type - Checklist 9,10 = IsNone | L85: 1-10 = crp_area_change | M85: 1)crp_seed_ownprod 2)crp_seed_market 3)crp_seed_company 4)crp_seed_ngo 5)crp_seed_organized_community 6)crp_seed_gov 7)crp_seed_relatives_friends 8)crp_seed_other 9)crp_seed_dk 10)crp_seed_ref | P85: if crp_seed_supply = 1-10, go to crp_area_change | S85: ='Additional information'!$D$17 -> 0.91 | V85: no | Z85: 18.51111 | AA85: =IF(Z85="","",Z85*S85) -> 16.84511 | AB85: =IF(V85="yes",AA85,"")
A86: =A85+1 -> 63 | B86: crp_area_change | C86: crp_area_change | D86: How did the area planted for {crp_main} from Winter season compare to a normal year? [OPERATOR: SINGLE RESPONSE.] 1)A lot more [increased by more than 50%] 2)Slightly more 3)Same 4)Slightly less 5)A lot less [less than half as much] 6)DON'T KNOW 7)REFUSED | E86: =LEN(D86) -> 257 | F86: كيف يمكن مقارنة المساحة المزروعة ل {crp_main} في الموسم الشتوي نسبةً ل العام العادي؟ [المشغل: استجابة واحدة.] 1) أكثر بكثير [زادت بنسبة تزيد عن 50٪] 2) أكثر قليلا 3) نفس الشيء 4) أقل قليلاً 5) أقل بكثير [أقل من نصف الكمية] 6) لا أعرف 7) رفض الإجابة | G86: =LEN(F86) -> 250 | H86: Single Choice | I86: NA | J86: NA | K86: Form Type - Buttons | L86: 1-7 = crp_harv_change | M86: NA | P86: if crp_area_change = 1-7, go to crp_harv_change | S86: ='Additional information'!$D$17 -> 0.91 | V86: yes | Z86: 20.308681 | AA86: =IF(Z86="","",Z86*S86) -> 18.4809 | AB86: =IF(V86="yes",AA86,"") -> 18.4809
A87: =A86+1 -> 64 | B87: crp_harv_change | C87: crp_harv_change | D87: How does the harvest of {crp_main} in the Winter season compare to a normal year? [OPERATOR: SINGLE RESPONSE.] 1)A lot more [increased by more than 50%] 2)Slightly more 3)Same 4)Slightly less 5)A lot less [less than half as much] 6)DON'T KNOW 7)REFUSED | E87: =LEN(D87) -> 254 | F87: كيف يمكن مقارنة الحصاد لـ {crp_main} في الموسم الشتوي نسبةً ل العام العادي؟ [المشغل: استجابة واحدة.] 1) أكثر بكثير [زادت بنسبة تزيد عن 50٪] 2) أكثر قليلا 3) نفس الشيء 4) أقل قليلاً 5) أقل بكثير [أقل من نصف الكمية] 6) لا أعرف 7) رفض الإجابة | G87: =LEN(F87) -> 242 | H87: Single Choice | I87: NA | J87: NA | K87: Form Type - Buttons | L87: 1-7 = crp_harv_vol | M87: NA | P87: if crp_harv_change = 1-7, go to [crp_proddif or crp_harv_vol] | Q87: 1-7 = crp_harv_vol | S87: ='Additional information'!$D$17 -> 0.91 | V87: yes | Z87: 15.448612 | AA87: =IF(Z87="","",Z87*S87) -> 14.058237 | AB87: =IF(V87="yes",AA87,"") -> 14.058237
A88: =A87+1 -> 65 | B88: crp_harv_vol | C88: crp_harv_vol | D88: How much [threshed] {crp_main} did you harvest this Winter season? [OPERATOR: RECORD THE RESPONSE GIVEN. UNIT OF MEASUREMENT TO BE SPECIFIED IN NEXT QUESTION. ENTER 8888888 FOR DON'T KNOW & 9999999 FOR REFUSED, TO BE USED RARELY - PROBE!] | E88: =LEN(D88) -> 239 | F88: ما هي كمية ال {crp_main} [المدروس/ة] التي قمت بحصادها هذا الموسم الموسم الشتوي؟ [المُشغل: سجل الاستجابة المُعطاة. يتم تحديد وحدة القياس في السؤال التالي. أدخل 8888888 للا أعرف و 9999999 في حالة الرفض ، والتي يجب استخدامها نادرًا - تحقق!] | G88: =LEN(F88) -> 240 | H88: Range | I88: NA | J88: NA | K88: Form Type - TextBox | L88: 1-1000000 = crp_harv_unit 8888888-8888888 = crp_proddif 9999999-9999999 = crp_proddif | M88: NA | P88: For any response, go to crp_harv_unit. For "Don't know" or "Refused", go to crp_proddif | S88: ='Additional information'!$D$17 -> 0.91 | V88: no | Z88: 30.343916 | AA88: =IF(Z88="","",Z88*S88) -> 27.612964 | AB88: =IF(V88="yes",AA88,"")
A89: =A88+1 -> 66 | B89: crp_harv_unit | C89: crp_harv_unit | D89: Unit of measurement for harvested {crp_main} : [OPERATOR: SINGLE SELECTION] 1)Kilograms [kgs] 2)Tonnes 3)Ounces 4)Pounds 5)Bags 6)Boxes 7)Bundles 8)Packets 9)Other [specify] | E89: =LEN(D89) -> 175 | F89: وحدة قياس حصاد {crp_main}: [المشغل: اختيار واحد] 1) كيلوغرامات [كلغ] 2) أطنان 3) أوقية 4) أرطال 5) أكياس 6) صناديق 7) حزم 8) رزمات 9) آخر [حدد] | G89: =LEN(F89) -> 145 | H89: Open Ended-Single Choice | I89: NA | J89: NA | K89: Form Type - RadioList IsDemographic - crp_harv_unit | L89: 1-4 = crp_harv_lastyr 5-9 = crp_harv_unit_kg | M89: NA | P89: If crp_harv_unit = 1-4, go to crp_harv_lastyr If crp_harv_unit = 5-9, go to crp_harv_unit_kg | S89: ='Additional information'!$D$17 -> 0.91 | V89: no | Z89: 5.4708996 | AA89: =IF(Z89="","",Z89*S89) -> 4.9785186 | AB89: =IF(V89="yes",AA89,"")
A90: =A89+1 -> 67 | B90: crp_harv_unit_kg | C90: crp_harv_unit_kg | D90: How many kilograms [kgs] in each unit? [OPERATOR: RECORD THE AMOUNT GIVEN. ENTER 88888 FOR DON'T KNOW & 99999 FOR REFUSED] | E90: =LEN(D90) -> 123 | F90: كم كيلوغرام [كلغ] في كل وحدة؟ [المُشغل: سجل المبلغ المعطى. أدخل 88888 لـلا أعرف و 99999 في حالة الرفض] | G90: =LEN(F90) -> 103 | H90: Range | I90: NA | J90: NA | K90: Form Type - TextBox | L90: 1-10000 = crp_harv_lastyr 88888-88888 = crp_harv_lastyr 99999-99999 = crp_harv_lastyr | M90: NA | P90: For any response, go to crp_harv_lastyr | S90: ='Additional information'!$D$17 -> 0.91 | V90: no | Z90: 7.9054728 | AA90: =IF(Z90="","",Z90*S90) -> 7.1939802 | AB90: =IF(V90="yes",AA90,"")
A91: =A90+1 -> 68 | B91: crp_harv_lastyr | C91: crp_harv_lastyr | D91: How many {crp_harv_unit} of [threshed] {crp_main} did you harvest last year during the same season? [OPERATOR: RECORD THE RESPONSE GIVEN. ENTER 8888888 FOR DON'T KNOW & 9999999 FOR REFUSED, TO BE USED RARELY - PROBE!] | E91: =LEN(D91) -> 218 | F91: كم {crp_harv_unit} من {crp_main} [(المدروس/ة] قمت بحصادها العام الماضي خلال نفس الموسم؟ [المُشغل: سجل الاستجابة المُعطاة. أدخل 8888888 لـلا أعرف و 9999999 في حالة الرفض ، والتي يجب استخدامها نادرًا - تحقق!] | G91: =LEN(F91) -> 208 | H91: Range | I91: NA | J91: NA | K91: Form Type - TextBox | L91: 1-1000000 = crp_proddif 8888888-8888888 = crp_proddif 9999999-9999999 = crp_proddif | M91: NA | P91: For any response, go to crp_proddif | S91: ='Additional information'!$D$17 -> 0.91 | V91: no | Z91: 16.435978 | AA91: =IF(Z91="","",Z91*S91) -> 14.95674 | AB91: =IF(V91="yes",AA91,"")
A92: =A91+1 -> 69 | B92: crp_proddif | C92: crp_proddif | D92: Has your household faced any significant difficulty in terms of crop production in Winter season? [OPERATOR: SINGLE RESPONSE.] 1)YES 2)NO 3)DON'T KNOW 4)REFUSED | E92: =LEN(D92) -> 162 | F92: هل واجهت أسرتك أي صعوبة في إنتاج المحاصيل في الموسم الشتوي؟ [المشغل: استجابة واحدة.] 1) نعم 2) لا 3) لا أعرف 4) رفض الإجابة | G92: =LEN(F92) -> 125 | H92: Single Choice | I92: NA | J92: NA | K92: Form Type - Buttons | L92: 1 = crp_proddif_2 2-4 = crp_storage | M92: NA | P92: if crp_proddif = 1, go to crp_proddif_2 ; if crp_proddif = 2-4, go to [crp_salesmain or optional question] | Q92: if crp_proddif = 1, go to crp_proddif_2 ; if crp_proddif = 2-4, go to crp_storage | S92: ='Additional information'!$D$17 -> 0.91 | V92: yes | Z92: 11.37533 | AA92: =IF(Z92="","",Z92*S92) -> 10.35155 | AB92: =IF(V92="yes",AA92,"") -> 10.35155
A93: =A92+1 -> 70 | B93: crp_proddif_2 | C93: crp_proddif_ 1) crp_proddif_plant_disease 2) crp_proddif_pest_outbreak 3) crp_proddif_animal_grazing 4) crp_proddif_access_plot 5) crp_proddif_access_fertilize 6) crp_proddif_seed_quality 7) crp_proddif_seed_quantity 8) crp_proddif_access_pesticide 9) crp_proddif_access_labour 10) crp_proddif_access_machinery 11) crp_proddif_access_fuel 12) crp_proddif_soil_erosion 13) crp_proddif_lack_irrigation 14) crp_proddif_excess_water 15) crp_proddif_access_credit 16) crp_proddif_other 17) crp_proddif_dk 18) crp_proddif_ref | D93: Which difficulty has your household faced with crop production in Winter season? [OPERATOR: MULTIPLE RESPONSES POSSIBLE. SELECT OPTION(S) THAT BEST FIT THE INFORMATION PROVIDED BY THE RESPONDENTS.] 1)Plant disease 2)Pest outbreak [including birds] 3)Uncontrolled animal grazing 4)Access to plot 5)Access to fertilizer [not available on markets or prices too high] 6)Access to quality seeds 7)Access to enough seeds [not available on markets or prices too high] 8)Access to pesticides 9)Access to manpower labour 10)Access to machinery/ tools or animals for ploughing 11)Access to fuel or electricity to power agricultural equipment 12)Soil erosion 13)Not enough irrigation / rainfall water 14)Too much irrigation / water 15)Access to credit 16)Other 17)DON'T KNOW 18)REFUSED | E93: =LEN(D93) -> 778 | F93: ما الصعوبات التي واجهتها أسرتك في إنتاج المحاصيل في الموسم الشتوي؟ [المُشغل: عدة استجابات محتملة. حدد الخيار (الخيارات) الأنسب للمعلومات المقدمة من المجيب.] 1) مرض نباتي 2) تفشي الافات [ بما في ذلك الطيور ] 3) رعي الحيوانات الغير منضبط 4) الوصول إلى قطعة الأرض 5) الوصول إلى الأسمدة [غير متوفرة في الأسواق أو أن اسعارها مرتفعة جداً] 6) الوصول الي البذور الجيدة 7) الوصول إلى ما يكفي من البذور [غير متوفرة في الأسواق أو أن اسعارها مرتفعة جداً] 8) الوصول إلى المبيدات الحشرية 9) الوصول إلى العمالة أو القوى العاملة 10) الوصول إلى آلات أو أدوات أو حيوانات للحراثة 11) الحصول على الوقود أو الكهرباء لتشغيل المعدات الزراعية 12) تعرية التربة 13) عدم كفاية مياه الري أو مياه الأمطار 14) زيادة مياه الري 15) الحصول على تمويل 16) آخر 17) لا أعرف 18) رفض الإجابة | G93: =LEN(F93) -> 756 | H93: Select All That Apply | I93: NA | J93: NA | K93: Form Type - Checklist 17,18 = IsNone | L93: 1-18 = o_crp_proddif_conflict | M93: 1)crp_proddif_plant_disease 2)crp_proddif_pest_outbreak 3)crp_proddif_animal_grazing 4)crp_proddif_access_plot 5)crp_proddif_access_fertilize 6)crp_proddif_seed_quality 7)crp_proddif_seed_quantity 8)crp_proddif_access_pesticide 9)crp_proddif_access_labour 10)crp_proddif_access_machinery 11)crp_proddif_access_fuel 12)crp_proddif_soil_erosion 13)crp_proddif_lack_irrigation 14)crp_proddif_excess_water 15)crp_proddif_access_credit 16)crp_proddif_other 17)crp_proddif_dk 18)crp_proddif_ref | P93: if crp_proddif_2 = 1-18, go to [crp_salesmain OR optional question] | Q93: if crp_proddif_2 = 1-18, go to o_crp_proddif_conflict | S93: ='Additional information'!$D$17 -> 0.91 | V93: yes | Z93: 25.844999 | AA93: =IF(Z93="","",Z93*S93) -> 23.518949 | AB93: =IF(V93="yes",AA93,"") -> 23.518949
A94: =A93+1 -> 71 | B94: o_crp_proddif_conflict | C94: o_crp_proddif_conflict 1) o_crp_pd_conf_field_access 2) o_crp_pd_conf_field_abandon 3) o_crp_pd_conf_crp_damage 4) o_crp_pd_conf_asset_damage 5) o_crp_pd_conf_loss_harv 6) o_crp_pd_conf_stop_prod 7) o_crp_pd_conf_labour 8) o_crp_pd_conf_agri_input 9) o_crp_pd_conf_none 10) o_crp_pd_conf_other 11) o_crp_pd_conf_dk 12) o_crp_pd_conf_ref | D94: How has insecurity and/or conflict affected household's production of {crp_main}? [OPERATOR: MULTIPLE RESPONSES POSSIBLE.] 1)Unable to safely access field 2)Abandonment of field after being displaced 3)Damage or destruction of crops 4)Damage or loss of household or productive assets 5)Loss of harvest 6)Stopped crop or livestock production 7)Lack of access to farm labour / labour too expensive 8)Lack of access to agricultural inputs / inputs too expensive 9)No impact on productivity so far 10)Other [specify] 11)DON'T KNOW 12)REFUSED | E94: =LEN(D94) -> 540 | F94: كيف أثرت حالة عدم الأمان و/أو النزاع على إنتاج الأسرة لـ {crp_main}؟ [المشغل: ممكن عدة استجابات.] 1) عدم القدرة على الوصول إلى الحقل بأمان 2) ترك الحقل بعد التهجير 3) تلف أو دمار المحاصيل 4) تضرر أو فقدان أصول الأسرة أو الأصول الإنتاجية 5) فقدان المحصول 6) توقف إنتاج المحاصيل أو الثروة الحيوانية 7) عدم القدرة على الوصول إلى الأيدي العاملة الزراعية / تكلفة العمالة مرتفعة جدًا 8) عدم القدرة على الوصول إلى المدخلات الزراعية / المدخلات باهظة الثمن 9) لم يكن هناك تأثير على الإنتاجية حتى الآن 10) أخرى [يرجى التحديد] 11) لا أعلم 12) رفض الإجابة | G94: =LEN(F94) -> 548 | H94: Open Ended-Select All That Apply | I94: NA | J94: NA | K94: Form Type - Checklist 9,11,12 = IsNone | L94: 1-12 = o_crp_proddif_conflict_damage | M94: 1) o_crp_pd_conf_field_access 2) o_crp_pd_conf_field_abandon 3) o_crp_pd_conf_crp_damage 4) o_crp_pd_conf_asset_damage 5) o_crp_pd_conf_loss_harv 6) o_crp_pd_conf_stop_prod 7) o_crp_pd_conf_labour 8) o_crp_pd_conf_agri_input 9) o_crp_pd_conf_none 10) o_crp_pd_conf_other 11) o_crp_pd_conf_dk 12) o_crp_pd_conf_ref | Q94: if o_crp_proddif_conflict = 4, go to o_crp_proddif_conflict_damage Otherwise, go to crp_storage
A95: =A94+1 -> 72 | B95: o_crp_proddif_conflict_damage | C95: o_crp_proddif_conflict_damage 1) o_crp_pd_confl_dam_confiscation 2) o_crp_pd_confl_dam_water_infra 3) o_crp_pd_confl_dam_agri_prod 4) o_crp_pd_confl_dam_farm_infra 5) o_crp_pd_confl_dam_dk 6) o_crp_pd_confl_dam_ref | D95: What types of damage or losses to assets and equipments have you experienced, if any? [OPERATOR: MULTIPLE RESPONSES POSSIBLE.] 1)Confiscation of productive assets/ stored products/ inputs/ etc 2)Damages to water infrastructure 3)Damages to harvested/stored crops and agricultural products 4)Damage or destruction of other farm infrastructure / buildings [e.g. animal barn/ storage/ etc] 5)DON'T KNOW 6)REFUSED | E95: =LEN(D95) -> 412 | F95: ما أنواع الأضرار أو الخسائر في الأصول والمعدات التي تعرضت لها، إن وجدت؟ [المشغل: ممكن عدة استجابات.] 1) مصادرة الأصول الإنتاجية، المنتجات المخزنة، المدخلات، إلخ 2) أضرار في البنية التحتية للمياه 3) أضرار في المحاصيل المحصودة/المخزنة والمنتجات الزراعية 4) تضرر أو تدمير بنية تحتية زراعية أخرى / مباني (مثل حظائر الحيوانات، المخازن، إلخ) 5) لا أعلم 6) رفض الإجابة | G95: =LEN(F95) -> 363 | H95: Select All That Apply | I95: NA | J95: Send if "o_crp_proddif_conflict" "Contains" "Damage or loss of household or productive assets" if not satisfied go to "crp_storage" | K95: Form Type - Checklist 5,6 = IsNone | L95: 1-6 = crp_storage | M95: 1) o_crp_pd_confl_dam_confiscation 2) o_crp_pd_confl_dam_water_infra 3) o_crp_pd_confl_dam_agri_prod 4) o_crp_pd_confl_dam_farm_infra 5) o_crp_pd_confl_dam_dk 6) o_crp_pd_confl_dam_ref | Q95: for any response, go to crp_storage
A96: =A95+1 -> 73 | B96: crp_storage | C96: crp_storage | D96: Last year, what proportion of your {crp_main} stock did you lose [to pests, rotting, mould, security situation etc.] after the harvest? [OPERATOR: SINGLE RESPONSE.] 1)None 2)A little 3)An important part of it/ but less than half 4)Most of it [half or more] 5)Almost everything 6)Everything 7)DON'T KNOW 8)REFUSED | E96: =LEN(D96) -> 315 | F96: في العام الماضي ، ما هي نسبة مخزونك التي خسرتها [بسبب الآفات ، والتعفن ، والعفن ، الظروف الأمنية وما إلى ذلك] من إجمالي {crp_main} المخزن؟ [المشغل: استجابة واحدة.] 1) لا شيء 2) قليلا 3) جزء مهم منه ولكن أقل من النصف 4) معظمها [نصف أو أكثر] 5) كل شيء تقريبا 6) كل شيء 7) لا أعرف 8) رفض الإجابة | G96: =LEN(F96) -> 295 | H96: Single Choice | I96: NA | J96: Send if "crp_main" "Equals" "Wheat" Or "crp_main" "Equals" "Barley" Or "crp_main" "Equals" "Potatoe" Or "crp_main" "Equals" "Peas" Or "crp_main" "Equals" "Chickpeas" Or "crp_main" "Equals" "Fava beans" Or "crp_main" "Equals" "Cabbage" Or "crp_main" "Equals" "Lettuce" Or "crp_main" "Equals" "Cauliflower" Or "crp_main" "Equals" "Tomatoes" Or "crp_main" "Equals" "Cucumber" Or "crp_main" "Equals" "Eggplant/aubergine" Or "crp_main" "Equals" "Onions" Or "crp_main" "Equals" "Lemon" Or "crp_main" "Equals" "Mango" Or "crp_main" "Equals" "Guava" Or "crp_main" "Equals" "Avocado" Or "crp_main" "Equals" "Grapes" Or "crp_main" "Equals" "Olives" Or "crp_main" "Equals" "Almond" Or "crp_main" "Equals" "Fodder" Or "crp_main" "Equals" "Rice" Or "crp_main" "Equals" "Millet" Or "crp_main" "Equals" "Sorghum" Or "crp_main" "Equals" "Maize" Or "crp_main" "Equals" "Other Cereal" Or "crp_main" "Equals" "Cassava" Or "crp_main" "Equals" "Sweet Potatoes" Or "crp_main" "Equals" "Yams" Or "crp_main" "Equals" "Carrots" Or "crp_main" "Equals" "Cocoyam" Or "crp_main" "Equals" "Other tubers" Or "crp_main" "Equals" "Beans" Or "crp_main" "Equals" "Lentils" Or "crp_main" "Equals" "Soybeans" Or "crp_main" "Equals" "Broad beans" Or "crp_main" "Equals" "Other pulses" Or "crp_main" "Equals" "Spinach-Amaranth" Or "crp_main" "Equals" "Cassava leaves" Or "crp_main" "Equals" "Potatoe leaves" Or "crp_main" "Equals" "Moringa" Or "crp_main" "Equals" "Sorrel Hibiscus / Rosselle" Or "crp_main" "Equals" "Green salad herbs [thyme/ parsley/ mint/ rocca/ other]" Or "crp_main" "Equals" "Other leafy vegetables" Or "crp_main" "Equals" "Pumpkin" Or "crp_main" "Equals" "Zucchini" Or "crp_main" "Equals" "Okra" Or "crp_main" "Equals" "Bell pepper" Or "crp_main" "Equals" "Haricot" Or "crp_main" "Equals" "Green peas" Or "crp_main" "Equals" "Fava beans green" Or "crp_main" "Equals" "Other non leafy vegs" Or "crp_main" "Equals" "Orange" Or "crp_main" "Equals" "Grapefruit" Or "crp_main" "Equals" "Mandarins/clementines" Or "crp_main" "Equals" "Other citrus fruit" Or "crp_main" "Equals" "Sweet Banana" Or "crp_main" "Equals" "Plantains" Or "crp_main" "Equals" "Papaya" Or "crp_main" "Equals" "Pineapple" Or "crp_main" "Equals" "Water Melon" Or "crp_main" "Equals" "Dates" Or "crp_main" "Equals" "Figs" Or "crp_main" "Equals" "Apple" Or "crp_main" "Equals" "Apricot" Or "crp_main" "Equals" "Cherries" Or "crp_main" "Equals" "Peach/nectarine" Or "crp_main" "Equals" "Strawberries" Or "crp_main" "Equals" "Melon [Cantaloupe]" Or "crp_main" "Equals" "Other fruit" Or "crp_main" "Equals" "Coconuts" Or "crp_main" "Equals" "Groundnut/peanut" Or "crp_main" "Equals" "Cashew Nut" Or "crp_main" "Equals" "Kola Nut" Or "crp_main" "Equals" "Sesame" Or "crp_main" "Equals" "Bambara nut" Or "crp_main" "Equals" "Walnut" Or "crp_main" "Equals" "Other nuts" Or "crp_main" "Equals" "Cocoa" Or "crp_main" "Equals" "Coffee" Or "crp_main" "Equals" "Tea" Or "crp_main" "Equals" "Sugarcane" Or "crp_main" "Equals" "Sunflower" Or "crp_main" "Equals" "Other food cash crop" Or "crp_main" "Equals" "Cotton" Or "crp_main" "Equals" "Rubber" Or "crp_main" "Equals" "Jute" Or "crp_main" "Equals" "Tobacco" Or "crp_main" "Equals" "Qat" Or "crp_main" "Equals" "Other non-food cash crop" if not satisfied go to "crp_salesmain" | K96: Form Type - Buttons | L96: 1-8 = crp_salesmain | M96: NA | P96: if the respondent has listed any crop as a main crop, they will be administered this question. If not, they will be sent to the crop marketing module, since the rest of the questions reference the main crop specifically in the question text. if crp_storage = 1-8, go to crp_salesmain or optional question | Q96: if the respondent has listed any crop as a main crop, they will be administered this question. If not, they will be sent to the crop marketing module, since the rest of the questions reference the main crop specifically in the question text. if crp_storage = 1-8, go to crp_salesmain | S96: ='Additional information'!$D$17 -> 0.91 | V96: no | Z96: 12.186037 | AA96: =IF(Z96="","",Z96*S96) -> 11.089294 | AB96: =IF(V96="yes",AA96,"")
A97: D. CROP MARKETING | AA97: =IF(Z97="","",Z97*S97) | AB97: =IF(V97="yes",AA97,"")
A98: =A96+1 -> 74 | B98: crp_salesmain | C98: crp_salesmain | D98: What has been the main crop that you have sold over the last 3 months? [OPERATOR: SELECT ALL CROPS LISTED BY THE RESPONDENT.] 1)Wheat 2)Barley 3)Potatoe 4)Peas 5)Chickpeas 6)Fava beans 7)Cabbage 8)Lettuce 9)Cauliflower 10)Tomatoes 11)Cucumber 12)Eggplant/aubergine 13)Onions 14)Lemon 15)Mango 16)Guava 17)Avocado 18)Grapes 19)Olives 20)Almond 21)Fodder 22)Rice 23)Millet 24)Sorghum 25)Maize 26)Other Cereal 27)Cassava 28)Sweet Potatoes 29)Yams 30)Carrots 31)Cocoyam 32)Other tubers 33)Beans 34)Lentils 35)Soybeans 36)Broad beans 37)Other pulses 38)Spinach-Amaranth 39)Cassava leaves 40)Potatoe leaves 41)Moringa 42)Sorrel Hibiscus / Rosselle 43)Green salad herbs [thyme/ parsley/ mint/ rocca/ other] 44)Other leafy vegetables 45)Pumpkin 46)Zucchini 47)Okra 48)Bell pepper 49)Haricot 50)Green peas 51)Fava beans green 52)Other non leafy vegs 53)Orange 54)Grapefruit 55)Mandarins/clementines 56)Other citrus fruit 57)Sweet Banana 58)Plantains 59)Papaya 60)Pineapple 61)Water Melon 62)Dates 63)Figs 64)Apple 65)Apricot 66)Cherries 67)Peach/nectarine 68)Strawberries 69)Melon [Cantaloupe] 70)Other fruit 71)Coconuts 72)Groundnut/peanut 73)Cashew Nut 74)Kola Nut 75)Sesame 76)Bambara nut 77)Walnut 78)Other nuts 79)Cocoa 80)Coffee 81)Tea 82)Sugarcane 83)Sunflower 84)Other food cash crop 85)Cotton 86)Rubber 87)Jute 88)Tobacco 89)Qat 90)Other non-food cash crop 91)DON'T KNOW 92)REFUSED | E98: =LEN(D98) -> 1383 | F98: ما هو المحصول الرئيسي الذي بعته خلال الأشهر الثلاثة الماضية؟ [حدد جميع المحاصيل التي سجلها المجيب.] 1)القمح 2)الشعير 3)البطاطا 4)البازيلاء 5)الحمص 6)الفول 7)الملفوف 8)الخس 9)القرنبيط 10)الطماطم 11)الخيار 12)الباذنجان 13)بصل 14)الليمون 15)المانجو 16)الجوافة 17)الأفوكادو 18)العنب 19)الزيتون 20)اللوز 21)العلف 22)الرز 23)الدخن 24)الذرة الرفيعة 25)الذرة 26)الحبوب الأخرى 27)الكسافا 28)البطاطا الحلوة 29)اليام 30)الجزر 31)القلقاس 32)الدرنات الأخرى 33)الفاصوليا 34)العدس 35)فول الصويا 36)الفاصوليا العريضة 37)البقول الاخرى 38)السبانخ - القطيفة 39)أوراق الكسافا 40)أوراق البطاطا 41)المورينجا 42)الكركديه 43)أعشاب السلطة الخضراء [زعتر ، بقدونس ، نعناع ، جرجير ، أنواع أخرى] 44)الخضار الورقية الأخرى 45)اليقطين 46)الكوسة 47)البامية 48)الفلفل حلو 49)اللوبياء 50)البازلاء الخضراء 51)الفول الأخضر 52)الخضار غير الورقية الأخرى 53)البرتقال 54)الجريب فروت 55)اليوسفي / الكليمنتين 56)الحمضيات الأخرى 57)الموز 58)موز الجنة 59)البابايا 60)الأناناس 61)البطيخ الأحمر 62)التمر 63)التين 64)التفاح 65)المشمش 66)الكرز 67)الدراق / النكتارين 68)الفراولة 69)الشمام 70)الفواكه الأخرى 71)جوز الهند 72)الفول السوداني 73)الكاجو 74)جوز الكولا 75)السمسم 76)جوز البامبارا 77)الجوز 78)المكسرات الأخرى 79)الكاكاو 80)القهوة 81)الشاي 82)قصب السكر 83)دوار الشمس 84)المحاصيل الغذائية النقدية الأخرى 85)القطن 86)المطاط 87)الجوت 88)التبغ 89)القات 90)المحاصيل النقدية غير الغذائية الأخرى 91) لا أعلم 92) رفض الإ‘جابه | G98: =LEN(F98) -> 1383 | H98: Single Choice | I98: NA | J98: Send if "income_main" "Equals" "Production and sale of staple crops" Or "income_main" "Equals" "Production and sale of vegetables or fruit" Or "income_main" "Equals" "Production and sale of cashcrops" Or "o_income_other" "Contains" "Production and sale of staple crops" Or "o_income_other" "Contains" "Production and sale of vegetables or fruit" Or "o_income_other" "Contains" "Production and sale of cashcrops" if not satisfied go to "ls_intro" | K98: Form Type - Dropdown IsDemographic - crp_salesmain | L98: 1-90 = crp_salesdif 91-92 = ls_intro | M98: 1.2)Wheat 1.6)Barley 2.2)Potatoe 3.3)Peas 3.5)Chickpeas 3.6)Fava beans 4.1)Cabbage 4.2)Lettuce 4.101)Cauliflower 5.1)Tomatoes 5.2)Cucumber 5.4)Eggplant/aubergine 5.8)Onions 6.2)Lemon 7.4)Mango 7.5)Guava 7.7)Avocado 7.11)Grapes 7.12)Olives 8.7)Almond 10.4)Fodder 1.1)Rice 1.3)Millet 1.4)Sorghum 1.5)Maize 1.99)Other Cereal 2.1)Cassava 2.3)Sweet Potatoes 2.4)Yams 2.5)Carrots 2.6)Cocoyam 2.99)Other tubers 3.1)Beans 3.2)Lentils 3.4)Soybeans 3.7)Broad beans 3.99)Other pulses 4.3)Spinach-Amaranth 4.4)Cassava leaves 4.5)Potatoe leaves 4.6)Moringa 4.7)Sorrel Hibiscus / Rosselle 4.9)Green salad herbs [thyme/ parsley/ mint/ rocca/ other] 4.99)Other leafy vegetables 5.3)Pumpkin 5.5)Zucchini 5.6)Okra 5.7)Bell pepper 5.9)Haricot 5.101)Green peas 5.11)Fava beans green 5.99)Other non leafy vegs 6.1)Orange 6.3)Grapefruit 6.4)Mandarins/clementines 6.99)Other citrus fruit 7.1)Sweet Banana 7.2)Plantains 7.3)Papaya 7.6)Pineapple 7.8)Water Melon 7.9)Dates 7.101)Figs 7.13)Apple 7.14)Apricot 7.15)Cherries 7.16)Peach/nectarine 7.17)Strawberries 7.18)Melon [Cantaloupe] 7.99)Other fruit 8.1)Coconuts 8.2)Groundnut/peanut 8.3)Cashew Nut 8.4)Kola Nut 8.5)Sesame 8.6)Bambara nut 8.8)Walnut 8.99)Other nuts 9.1)Cocoa 9.2)Coffee 9.3)Tea 9.4)Sugarcane 9.5)Sunflower 9.99)Other food cash crop 10.1)Cotton 10.2)Rubber 10.3)Jute 10.5)Tobacco 10.6)Qat 10.99)Other non-food cash crop 888)DON'T KNOW 999)REFUSED | N98: GeoPoll [3/18/2024]: We do not have "income_sec" & "income_third", that’s why we have used "o_income_other" in the conditional logic instead. Kindly confirm. | O98: Yes this is correct, however it is not currently reflected in the logic | P98: If either income_main or income_sec or income_third = "Production and sale of staple crops" or "Production and sale of vegetable/ fruit" or "Production and sale of cashcrops (cocoa, tobacco, etc)", then this section will be asked to respondents. Otherwise, skip to ls_intro. For any crop selected, go to crp_salesdif If "Don't know" or "Refused", go to ls_intro | S98: ='Additional information'!$D$17 -> 0.91 | V98: yes | Z98: 17.612015 | AA98: =IF(Z98="","",Z98*S98) -> 16.026933 | AB98: =IF(V98="yes",AA98,"") -> 16.026933
A99: =A98+1 -> 75 | B99: crp_salesdif | C99: crp_salesdif | D99: Has your household faced any significant difficulty in the last 3 months selling your {crp_salesmain}? [OPERATOR: SINGLE RESPONSE.] 1)YES 2)NO 3)DON'T KNOW 4)REFUSED | E99: =LEN(D99) -> 167 | F99: هل واجهت أسرتك أي صعوبة خلال الأشهر الثلاثة الماضية في بيع {crp_salesmain}؟ [المشغل: استجابة واحدة.] 1) نعم 2) لا 3) لا أعرف 4) رفض الإجابة | G99: =LEN(F99) -> 141 | H99: Single Choice | I99: NA | J99: NA | K99: Form Type - Buttons | L99: 1 = crp_salesdif_2 2-4 = o_crp_sales_markets | M99: NA | P99: if crp_salesdif = 1, go to crp_salesdif_2 ; if crp_salesdif = 2-4, go to crp_salesprice | Q99: if crp_salesdif = 1, go to crp_salesdif_2 ; if crp_salesdif = 2-4, go to o_crp_sales_markets | S99: ='Additional information'!$D$17 -> 0.91 | V99: yes | Z99: 10.457156 | AA99: =IF(Z99="","",Z99*S99) -> 9.5160121 | AB99: =IF(V99="yes",AA99,"") -> 9.5160121
A100: =A99+1 -> 76 | B100: crp_salesdif_2 | C100: crp_saledif_ 1) crp_saledif_marketing_cost 2) crp_saledif_damage_losses 3) crp_saledif_low_demand 4) crp_saledif_pay_delay 5) crp_saledif_low_price 6) crp_saledif_processing 7) crp_saledif_competition 8) crp_saledif_other 9) crp_saledif_dk 10) crp_saledif_ref | D100: Which difficulties has your household faced in the last 3 months selling your {crp_salesmain}? [OPERATOR: MULTIPLE RESPONSES POSSIBLE. SELECT OPTION(S) THAT BEST FIT THE INFORMATION PROVIDED BY THE RESPONDENTS.] 1)High transportation or other marketing costs 2)Damages and losses due to storage difficulties and/or difficulty accessing the market [e.g. insecurity/ poor infrastructure/ etc.] 3)Lack of demand from usual traders or buyers 4)Payment delays from traders / buyers 5)Low selling prices [e.g. compared to input prices / inflation] 6)Difficulty processing product [lack of processing inputs / equipment / etc] 7)Market flooded with products 8)Other 9)DON'T KNOW 10)REFUSED | E100: =LEN(D100) -> 684 | F100: ما الصعوبات التي واجهتها أسرتك في الأشهر الثلاثة الماضية عند بيع {crp_salesmain}؟ [المشغل: عدة استجابات محتملة. حدد الخيار (الخيارات) الأنسب للمعلومات المقدمة من المجيب.] 1) ارتفاع تكاليف النقل أو تكاليف التسويق الأخرى 2) الاضرار و الخسائر نتيجة صعوبات التخزين و صعوبة الوصول الي السوق [ انعدام الامن / البنية التحتية الفقيرة و غيرها ] 3) قلة الطلب من المشترين و التجار المعتادين 4) تأخر المدفوعات من التجار و المشترين 5) انخفاض أسعار البيع [ مقارنة باسعار المدخلات / التضخم علي سبيل المثال ] 6) صعوبة معالجة المنتج [قلة مدخلات المعالجة ، المعدات و غيرها ] 7) تشبع السوق بالمنتجات 8) آخر 9) لا اعرف 10) رفض الإجابة | G100: =LEN(F100) -> 621 | H100: Select All That Apply | I100: NA | J100: NA | K100: Form Type - Checklist 9,10 = IsNone | L100: 1-10 = o_crp_salesdif_conflict | M100: 1)crp_saledif_marketing_cost 2)crp_saledif_damage_losses 3)crp_saledif_low_demand 4)crp_saledif_pay_delay 5)crp_saledif_low_price 6)crp_saledif_processing 7)crp_saledif_competition 8)crp_saledif_other 9)crp_saledif_dk 10)crp_saledif_ref | P100: if crp_salesdif_2 = 1-10, go to crp_salesprice | Q100: if crp_salesdif_2 = 1-10, go to o_crp_salesdif_conflict | S100: ='Additional information'!$D$17 -> 0.91 | V100: yes | Z100: 20.769962 | AA100: =IF(Z100="","",Z100*S100) -> 18.900666 | AB100: =IF(V100="yes",AA100,"") -> 18.900666
...

Sheet Crop list
C3: Select top 10 crops | D3: GeoPoll code | E3: Dataset code | F3: Label (EN) | G3: Label (AR)
D4: {=_xlfn.SEQUENCE(90,1,1,1)} -> 1 | E4: 1.1 | F4: Rice | G4: الرز
C5: x | D5: 2 | E5: 1.2 | F5: Wheat | G5: القمح
D6: 3 | E6: 1.3 | F6: Millet | G6: الدخن
D7: 4 | E7: 1.4 | F7: Sorghum | G7: الذرة الرفيعة
D8: 5 | E8: 1.5 | F8: Maize | G8: الذرة
C9: x | D9: 6 | E9: 1.6 | F9: Barley | G9: الشعير
D10: 7 | E10: 1.99 | F10: Other Cereal | G10: الحبوب الأخرى
D11: 8 | E11: 2.1 | F11: Cassava | G11: الكسافا
C12: x | D12: 9 | E12: 2.2 | F12: Potatoe | G12: البطاطا
D13: 10 | E13: 2.3 | F13: Sweet Potatoes | G13: البطاطا الحلوة
D14: 11 | E14: 2.4 | F14: Yams | G14: اليام
D15: 12 | E15: 2.5 | F15: Carrots | G15: الجزر
D16: 13 | E16: 2.6 | F16: Cocoyam | G16: القلقاس
D17: 14 | E17: 2.99 | F17: Other tubers | G17: الدرنات الأخرى
D18: 15 | E18: 3.1 | F18: Beans | G18: الفاصوليا
D19: 16 | E19: 3.2 | F19: Lentils | G19: العدس
C20: x | D20: 17 | E20: 3.3 | F20: Peas | G20: البازيلاء
D21: 18 | E21: 3.4 | F21: Soybeans | G21: فول الصويا
C22: x | D22: 19 | E22: 3.5 | F22: Chickpeas | G22: الحمص
C23: x | D23: 20 | E23: 3.6 | F23: Fava beans | G23: الفول
D24: 21 | E24: 3.7 | F24: Broad beans | G24: الفاصوليا العريضة
D25: 22 | E25: 3.99 | F25: Other pulses | G25: البقول الاخرى
C26: x | D26: 23 | E26: 4.1 | F26: Cabbage | G26: الملفوف
C27: x | D27: 24 | E27: 4.2 | F27: Lettuce | G27: الخس
D28: 25 | E28: 4.3 | F28: Spinach-Amaranth | G28: السبانخ - القطيفة
D29: 26 | E29: 4.4 | F29: Cassava leaves | G29: أوراق الكسافا
D30: 27 | E30: 4.5 | F30: Potatoe leaves | G30: أوراق البطاطا
D31: 28 | E31: 4.6 | F31: Moringa | G31: المورينجا
D32: 29 | E32: 4.7 | F32: Sorrel Hibiscus / Rosselle | G32: الكركديه
D33: 30 | E33: 4.9 | F33: Green salad herbs [thyme, parsley, mint, rocca, other] | G33: أعشاب السلطة الخضراء [زعتر ، بقدونس ، نعناع ، جرجير ، أنواع أخرى]
C34: x | D34: 31 | E34: 4.101 | F34: Cauliflower | G34: القرنبيط
D35: 32 | E35: 4.99 | F35: Other leafy vegetables | G35: الخضار الورقية الأخرى
C36: x | D36: 33 | E36: 5.1 | F36: Tomatoes | G36: الطماطم
C37: x | D37: 34 | E37: 5.2 | F37: Cucumber | G37: الخيار
D38: 35 | E38: 5.3 | F38: Pumpkin | G38: اليقطين
C39: x | D39: 36 | E39: 5.4 | F39: Eggplant/aubergine | G39: الباذنجان
D40: 37 | E40: 5.5 | F40: Zucchini | G40: الكوسة
D41: 38 | E41: 5.6 | F41: Okra | G41: البامية
D42: 39 | E42: 5.7 | F42: Bell pepper | G42: الفلفل حلو
C43: x | D43: 40 | E43: 5.8 | F43: Onions | G43: بصل
D44: 41 | E44: 5.9 | F44: Haricot | G44: اللوبياء
D45: 42 | E45: 5.101 | F45: Green peas | G45: البازلاء الخضراء
D46: 43 | E46: 5.11 | F46: Fava beans green | G46: الفول الأخضر
D47: 44 | E47: 5.99 | F47: Other non leafy vegs | G47: الخضار غير الورقية الأخرى
D48: 45 | E48: 6.1 | F48: Orange | G48: البرتقال
C49: x | D49: 46 | E49: 6.2 | F49: Lemon | G49: الليمون
D50: 47 | E50: 6.3 | F50: Grapefruit | G50: الجريب فروت
D51: 48 | E51: 6.4 | F51: Mandarins/clementines | G51: اليوسفي / الكليمنتين
D52: 49 | E52: 6.99 | F52: Other citrus fruit | G52: الحمضيات الأخرى
D53: 50 | E53: 7.1 | F53: Sweet Banana | G53: الموز
D54: 51 | E54: 7.2 | F54: Plantains | G54: موز الجنة
D55: 52 | E55: 7.3 | F55: Papaya | G55: البابايا
C56: x | D56: 53 | E56: 7.4 | F56: Mango | G56: المانجو
C57: x | D57: 54 | E57: 7.5 | F57: Guava | G57: الجوافة
D58: 55 | E58: 7.6 | F58: Pineapple | G58: الأناناس
C59: x | D59: 56 | E59: 7.7 | F59: Avocado | G59: الأفوكادو
D60: 57 | E60: 7.8 | F60: Water Melon | G60: البطيخ الأحمر
D61: 58 | E61: 7.9 | F61: Dates | G61: التمر
D62: 59 | E62: 7.101 | F62: Figs | G62: التين
C63: x | D63: 60 | E63: 7.11 | F63: Grapes | G63: العنب
C64: x | D64: 61 | E64: 7.12 | F64: Olives | G64: الزيتون
D65: 62 | E65: 7.13 | F65: Apple | G65: التفاح
D66: 63 | E66: 7.14 | F66: Apricot | G66: المشمش
D67: 64 | E67: 7.15 | F67: Cherries | G67: الكرز
D68: 65 | E68: 7.16 | F68: Peach/nectarine | G68: الدراق / النكتارين
D69: 66 | E69: 7.17 | F69: Strawberries | G69: الفراولة
D70: 67 | E70: 7.18 | F70: Melon [Cantaloupe] | G70: الشمام
D71: 68 | E71: 7.99 | F71: Other fruit | G71: الفواكه الأخرى
D72: 69 | E72: 8.1 | F72: Coconuts | G72: جوز الهند
D73: 70 | E73: 8.2 | F73: Groundnut/peanut | G73: الفول السوداني
D74: 71 | E74: 8.3 | F74: Cashew Nut | G74: الكاجو
D75: 72 | E75: 8.4 | F75: Kola Nut | G75: جوز الكولا
D76: 73 | E76: 8.5 | F76: Sesame | G76: السمسم
D77: 74 | E77: 8.6 | F77: Bambara nut | G77: جوز البامبارا
C78: x | D78: 75 | E78: 8.7 | F78: Almond | G78: اللوز
D79: 76 | E79: 8.8 | F79: Walnut | G79: الجوز
D80: 77 | E80: 8.99 | F80: Other nuts | G80: المكسرات الأخرى
D81: 78 | E81: 9.1 | F81: Cocoa | G81: الكاكاو
D82: 79 | E82: 9.2 | F82: Coffee | G82: القهوة
D83: 80 | E83: 9.3 | F83: Tea | G83: الشاي
D84: 81 | E84: 9.4 | F84: Sugarcane | G84: قصب السكر
D85: 82 | E85: 9.5 | F85: Sunflower | G85: دوار الشمس
D86: 83 | E86: 9.99 | F86: Other food cash crop | G86: المحاصيل الغذائية النقدية الأخرى
D87: 84 | E87: 10.1 | F87: Cotton | G87: القطن
D88: 85 | E88: 10.2 | F88: Rubber | G88: المطاط
D89: 86 | E89: 10.3 | F89: Jute | G89: الجوت
C90: x | D90: 87 | E90: 10.4 | F90: Fodder | G90: العلف
D91: 88 | E91: 10.5 | F91: Tobacco | G91: التبغ
D92: 89 | E92: 10.6 | F92: Qat | G92: القات
D93: 90 | E93: 10.99 | F93: Other non-food cash crop | G93: المحاصيل النقدية غير الغذائية الأخرى

Sheet Admin 2 info
A1: adm2_name | B1: adm2_name_local | C1: adm2_pcode | D1: adm1_name | E1: adm1_pcode | F1: adm0_name | G1: adm0_ISO3
A2: North Gaza | C2: PS0255 | D2: Gaza Strip | E2: PS02 | F2: State of Palestine (the) | G2: PSE
A3: Gaza | C3: PS0260 | D3: Gaza Strip | E3: PS02 | F3: State of Palestine (the) | G3: PSE
A4: Deir Al-Balah | C4: PS0265 | D4: Gaza Strip | E4: PS02 | F4: State of Palestine (the) | G4: PSE
A5: Khan Younis | C5: PS0270 | D5: Gaza Strip | E5: PS02 | F5: State of Palestine (the) | G5: PSE
A6: Rafah | C6: PS0275 | D6: Gaza Strip | E6: PS02 | F6: State of Palestine (the) | G6: PSE
A7: Jenin | C7: PS0101 | D7: West Bank | E7: PS01 | F7: State of Palestine (the) | G7: PSE
A8: Tubas | C8: PS0105 | D8: West Bank | E8: PS01 | F8: State of Palestine (the) | G8: PSE
A9: Tulkarm | C9: PS0110 | D9: West Bank | E9: PS01 | F9: State of Palestine (the) | G9: PSE
A10: Nablus | C10: PS0115 | D10: West Bank | E10: PS01 | F10: State of Palestine (the) | G10: PSE
A11: Qalqilya | C11: PS0120 | D11: West Bank | E11: PS01 | F11: State of Palestine (the) | G11: PSE
A12: Salfit | C12: PS0125 | D12: West Bank | E12: PS01 | F12: State of Palestine (the) | G12: PSE
A13: Ramallah | C13: PS0130 | D13: West Bank | E13: PS01 | F13: State of Palestine (the) | G13: PSE
... A17: Hebron | C17: PS0150 | D17: West Bank | E17: PS01 | F17: State of Palestine (the) | G17: PSE

Sheet Admin 1
A1: 1 | B1: Jenin
A2: 5 | B2: Tubas
A3: 10 | B3: Tulkarm
A4: 20 | B4: Qalqilia
A5: 25 | B5: Salfit
A6: 15 | B6: Nablus
A7: 30 | B7: Ramallah
A8: 35 | B8: Jericho
A9: 40 | B9: Jerusalem (J2)
A10: 45 | B10: Bethlehem
A11: 50 | B11: Hebron

Sheet Admin 2
A1: Admin 1 code | B1: Admin 2 Code | C1: Admin 2 name
A2: 1 | B2: 10005 | C2: Zububa
A3: 1 | B3: 10010 | C3: Rummana
A4: 1 | B4: 10015 | C4: Ti'innik
A5: 1 | B5: 10020 | C5: At Tayba
A6: 1 | B6: 10025 | C6: 'Arabbuna
A7: 1 | B7: 10030 | C7: Al Jalama
A8: 1 | B8: 10035 | C8: Silat al Harithiya
A9: 1 | B9: 10040 | C9: As Sa'aida
A10: 1 | B10: 10045 | C10: 'Anin
A11: 1 | B11: 10050 | C11: 'Arrana
A12: 1 | B12: 10055 | C12: Deir Ghazala
A13: 1 | B13: 10060 | C13: Faqqu'a
... A504: 50 | B504: 503405 | C504: 'Arab al Fureijat

Sheet Additional information
C2: Original | D2: Replacement (EN) | E2: Replacement (AR) | F2: Comment (EN) | G2: Comment (AR) | H2: Example (EN) | I2: Example (AR)
B3: FOR CORE QUESTIONS . (Mandatory to fill out) . | C3: ADMIN1 | D3: Region | E3: محافظة | F3: The first subdivision of the country, after national level; region; province; governorate; etc. | G3: التقسيم الأول للبلاد ، بعد المستوى الوطني ؛ منطقة؛ محافظة؛ ولاية ؛ إلخ. | H3: region | I3: منطقة
C4: ADMIN2 | D4: Governorate | E4: تجمع سكاني | F4: The second subdivision of the country; district; municipality; LGA; etc. | G4: التقسيم الثاني للبلاد ؛ قضاء؛ بلدية؛ إلخ. | H4: district | I4: قضاء
C5: reference year | D5: a normal year | E5: العام العادي | F5: Comparison questions will need need a reference year. Select whether you want to use "last year" or "a normal year" as a baseline. A "normal year" should refers to an average year from the past 5 years - make sure to train the enumerators accordingly. | G5: سوف تحتاج أسئلة المقارنة إلى سنة مرجعية. حدد ما إذا كنت تريد استخدام "العام الماضي" أو "العام العادي" كخط أساس. يجب أن يشير "العام العادي" إلى متوسط ​​عام من السنوات الخمس الماضية - تأكد من تدريب جامعي البيانات وفقًا لذلك. | H5: a normal year | I5: العام العادي
C6: season | D6: Winter season | E6: الموسم الشتوي | F6: Name the crop season(s) of interest if there are several cropping seasons in the country (e.g. Meher and Belg in Ethiopia, rainy season / flood-recession cropping / irrigated dry season in the Sahel). You can refer to the “last season” or “ongoing season". | G6: قم بتسمية موسم (مواسم) المحاصيل ذات الأهمية إذا كان هناك عدة مواسم محصولية في البلد (على سبيل المثال ، Meher و Belg في إثيوبيا ، موسم الأمطار / محاصيل الركود بسبب الفيضانات / موسم الجفاف المروي في منطقة الساحل). يمكنك الرجوع إلى "الموسم الماضي" أو "الموسم الجاري". | H6: wet season | I6: موسم الأمطار
C7: season phase | D7: Harvesting | E7: الحصاد | F7: Indicate the phase of the season at the time of data collection. If the harvest from the season has not yet occurred, the question on crop harvest (crp_harv_change) will include the word “expected” (where #expected or nothing# is located). If the harvest has occured, "expected" will not be inserted in the question. | G7: حدد مرحلة الموسم في وقت جمع البيانات. إذا لم يتم الحصاد من الموسم بعد ، فإن السؤال عن حصاد المحاصيل (crp_harv_change) سيتضمن كلمة "متوقع" (حيث يوجد # متوقع أو لا شيء #). إذا تم الحصاد ، لن يتم إدخال "متوقع" في السؤال . | H7: Harvesting | I7: الحصاد
C8: local measurement unit | D8: Dunum | E8: دونم | F8: Specify the local measurement unit for land size, other than acres, hectares, square meters and square feet. If no other unit of measurement is needed, keep this cell blank. | G8: حدد وحدة القياس المحلية لمساحة الأرض ، بخلاف الفدان والهكتار والمتر المربع والقدم المربع. إذا لم تكن هناك حاجة إلى وحدة قياس أخرى ، احتفظ بهذه الخلية فارغة. | H8: Jeribs | I8: جريب
C9: local measurement unit conversion | D9: 0.1 | E9: 0.1 | F9: Include the conversion of the local measurement unit to hectares. In other words, how many local measurement units are in 1 ha. Only digits in Latin numbers should be inputted. | G9: قم بتضمين تحويل وحدة القياس المحلية إلى هكتار. بمعنى آخر ، إلى كم هو عدد وحدات القياس المحلية في هكتار واحد. يرجى إدخال الأرقام في الأبجدية اللاتينية (...3, 2, 1). | H9: 0.2 | I9: 0.2
B10: FOR OPTIONAL QUESTIONS . (Fill out if applicable) . | C10: currency | D10: NIS | E10: شيكل | F10: The name of the main currency used nationally; USD; Naira; Rial; Pesos; etc. | G10: اسم العملة الرئيسية المستخدمة وطنيا ؛ دولار أمريكي؛ نيرة؛ الريال؛ بيزو؛ إلخ. | H10: Naira | I10: نيرة
C11: MIN AMOUNT | D11: 300 | E11: 300 | F11: The minimum amount for an income source should be set at 0 or any value below which it is not possible to do a transaction. For example, the smallest coin/banknote in a currency can be 1000, in which case you would set the minimum at 1000. Provide this input in the same currency as specified above. Only digits in Latin numbers should be inputted. | G11: يجب تعيين الحد الأدنى لمبلغ مصدر الدخل على 0 أو أي قيمة أقل منها لا يمكن إجراء معاملة. على سبيل المثال ، يمكن أن تكون أصغر عملة / ورقة نقدية في عملة ما هي 1000 ، وفي هذه الحالة يمكنك تعيين الحد الأدنى عند 1000. يجب أن يكون هذا المبلغ بنفس العملة المحددة في الصف أعلاه. يرجى إدخال الأرقام في الأبجدية اللاتينية (...3, 2, 1). | H11: 5 | I11: 5
C12: MAX AMOUNT | D12: 1500000 | E12: 1500000 | F12: Set the maximum amount for an income source over 3 months. Enumerators will not be able to input values above this amount in questions related to income amounts. Using previous representative surveys for this population, you can estimate this amount by using the mean income plus five (5) standard deviations, unless the country has high inflation. In the latter case, set the maximum value based on your country context (higher than the proposed approach). Provide this input in the same currency as specified above. Only digits in Latin numbers should be inputted. | G12: حدد الحد الأقصى لمبلغ مصدر الدخل على مدى 3 أشهر. لن يتمكن جامعي البيانات من إدخال قيم أعلى من هذا المبلغ في الأسئلة المتعلقة بمبالغ الدخل. باستخدام المسوح التمثيلية السابقة لهذه الفئة من السكان ، يمكنك تقدير هذا المبلغ باستخدام متوسط ​​الدخل بالإضافة إلى خمسة انحرافات معيارية ما لم يكن هناك تضخم مرتفع في الدولة. في الحالة الأخيرة ، قم بتعيين الحد الأقصى للقيمة بناءً على سياق بلدك (أعلى من النهج المقترح). يجب أن يكون هذا المبلغ بنفس العملة المحددة أعلاه. يرجى إدخال الأرقام في الأبجدية اللاتينية (...3, 2, 1). | H12: 5000000 | I12: 5000000
C13: THRESHOLD | D13: 4000 | E13: 4000 | F13: The threshold salary should be calculated to flag outliers (responses that look suspiciously high). Using previous representative surveys for this population, a good estimate is the average plus three (3) standard deviations, which should give the threshold for the 3 or 4% highest income values. Provide this input in the same currency as specified above. Only digits in Latin numbers should be inputted. | G13: يجب حساب قيمة العتبة للراتب لتحديد القيم المتطرفة (الاستجابات التي تبدو مرتفعة بشكل مثير للريبة). باستخدام المسوح التمثيلية السابقة لهذه الفئة من السكان ، فإن التقدير الجيد هو المتوسط ​​زائد ثلاثة انحرافات معيارية ، والذي يجب أن يعطي قيمة العتبة لقيم الدخل الأعلى بنسبة 3 أو 4٪. يجب أن يكون هذا المبلغ بنفس العملة المحددة أعلاه. يرجى إدخال الأرقام في الأبجدية اللاتينية (...3, 2, 1). | H13: 1200000 | I13: 1200000
C14: local vegetables | D14: Tomatoes, eggplant, zucchini, cauliflower | E14: بندورة، باذنجان، كوسا، قرنبيط | F14: Input some common local vegetables [to be used as examples in the food consumption score indicator]. | G14: أدخل بعض الخضروات المحلية الشائعة [لاستخدامها كأمثلة في مؤشر درجة استهلاك الغذاء]. | H14: eggplants, zucchini, cauliflower | I14: باذنجان ، كوسة ، قرنبيط
C15: local fruits | D15: Apple, banana, orange | E15: تفاح، موز، برتقال | F15: Input some common local fruits [to be used as examples in the food consumption score indicator]. | G15: أدخل بعض الفاكهة المحلية الشائعة [لاستخدامها كأمثلة في مؤشر درجة استهلاك الغذاء]. | H15: apples, bananas, oranges | I15: التفاح والموز والبرتقال
B17: FILL OUT FOR QUESTIONNAIRE DURATION ESTIMATION . | C17: Expected percentage of respondents cultivating crops | D17: 0.91 | E17: 0.91 | F17: If the survey is representative and has no quotas, write the proportion of rural households cultivating crops at country level, or if the survey follows a previous round with identical sample design, just report the percentage from the previous round. If you are using quotas, calculate the ratio of the quota over the minimum sample size at the level where the quota is implemented (so if you have a minimum sample size per strata of 110 with a quota of 100 crop producers, then it's 100/110 = 91% (the maximum you should write is 100%). | G17: إذا كان المسح تمثيليًا وليس له حصص نسبية ، فاكتب نسبة الأسر الريفية التي تزرع محاصيل على المستوى الوطني ، أو إذا كان المسح يتبع جولة سابقة بتصميم عينة متطابق ، فما عليك سوى الإبلاغ عن النسبة المئوية من الجولة السابقة. إذا كنت تستخدم نظام الحصص النسبية ، فاحسب نسبة الحصة إلى الحد الأدنى لحجم العينة على المستوى الذي يتم فيه تنفيذ الحصة (لذلك إذا كان لديك حد أدنى لحجم العينة لكل طبقة 110 مع حصة 100 منتج محصول ، فسيكون 100 / 110 = 91٪ (الحد الأقصى الذي يجب أن تكتبه هو 100٪). | H17: 0.91 | I17: 0.91
C18: Expected percentage of respondents raising livestock | D18: 0.91 | E18: 0.91 | F18: If the survey is representative and has no quotas, write the proportion of rural households raising livestock at country level, or if the survey follows a previous round with identical sample design, just report the percentage from the previous round. If you are using quotas, calculate the ratio of the quota over the minimum sample size at the level where the quota is implemented (so if you have a minimum sample size of 110 but a quota of 100 livestock producers, then it's 100/110 = 91% (the maximum you should write is 100%) | G18: إذا كان المسح تمثيليًا وليس له حصص نسبية ، فاكتب نسبة الأسر الريفية التي تربي الماشية على المستوى الوطني ، أو إذا كان المسح يتبع جولة سابقة بتصميم عينة متطابق ، فما عليك سوى الإبلاغ عن النسبة المئوية من الجولة السابقة. إذا كنت تستخدم نظام الحصص النسبية ، فاحسب نسبة الحصة إلى الحد الأدنى لحجم العينة على المستوى الذي يتم فيه تنفيذ الحصة (لذلك إذا كان لديك حد أدنى لحجم العينة لكل طبقة 110 مع حصة 100 مربي الماشية ، فسيكون 100 / 110 = 91٪ (الحد الأقصى الذي يجب أن تكتبه هو 100٪). | H18: 0.91 | I18: 0.91
C19: Expected percentage of respondents involved in fishery | D19: 0.05 | E19: 0.05 | F19: If the survey is representative and has no quotas, write the proportion of rural households involved in fisheries or aquaculture, otherwise if you are using quotas, calculate the ratio of the quota over the sample size at the level where the quota is implemented. (so if you haven't set a quota, and you expect to have a representative proportion of fishermen, just write the percentage of fishermen in the population you are targeting, in the example to the right, 5%) | G19: إذا كان المسح تمثيليًا وليس له حصص نسبية ، فاكتب نسبة الأسر الريفية العاملة في مصايد الأسماك أو تربية الأحياء المائية على المستوى الوطني. وإلا إذا كنت تستخدم الحصص النسبية ، فاحسب نسبة الحصة إلى حجم العينة على المستوى الذي يتم فيه تنفيذ الحصة. (لذلك إذا لم تحدد حصة ، وكنت تتوقع أن يكون لديك نسبة تمثيلية من الصيادين ، فاكتب فقط النسبة المئوية للصيادين من السكان الذين تستهدفهم ، في المثال على اليمين ، 5٪). | H19: 0.05 | I19: 0.05

Sheet Quotas
A1: Governorate | B1: Livelihoodtype | C1: Sample Size
A2: Jenin | B2: Plant | C2: 140
B3: Livestock | C3: 30
B4: Mixed | C4: 35
A5: Tubas & Northern Valleys | B5: Plant | C5: 35
B6: Livestock | C6: 30
B7: Mixed | C7: 30
A8: Tulkarm/Qalqiliya/Salfit | B8: Plant | C8: 201
B9: Livestock
B10: Mixed | C10: 33
A11: Nablus | B11: Plant | C11: 110
B12: Livestock | C12: 30
B13: Mixed | C13: 30
A14: Ramallah & Al-Bireh | B14: Plant | C14: 115
B15: Livestock | C15: 45
B16: Mixed | C16: 38
A17: Jericho & Al- Aghwar | B17: Plant | C17: 30
B18: Livestock | C18: 30
B19: Mixed | C19: 30
A20: Jerusalem | B20: Plant | C20: 30
B21: Livestock | C21: 30
B22: Mixed | C22: 30
A23: Bethlehem | B23: Plant | C23: 61
B24: Livestock | C24: 30
B25: Mixed | C25: 30
A26: Hebron | B26: Plant | C26: 145
B27: Livestock | C27: 40
B28: Mixed | C28: 45
A29: TOTAL | C29: =SUM(C2:C28) -> 1433
